Workbook

Sheet Summary
A1: Governance Practices: Final Equal-Weight Results | B1: Value
A2: Entries | B2: 112
A3: Final metrics | B3: G1-G7
A4: Weight per metric | B4: 1/7 = 14.29%
A5: Coverage gate | B5: None
A6: Unavailable data | B6: Zero in final score
A7: Mean score | B7: =AVERAGE(Scoring!S2:S113) -> 64.177296
A8: Median score | B8: =MEDIAN(Scoring!S2:S113) -> 70.214286
A9: Standard deviation | B9: 26.000086
A10: Minimum score | B10: =MIN(Scoring!S2:S113) -> 0
A11: Maximum score | B11: =MAX(Scoring!S2:S113) -> 100
A12: Mean observed coverage | B12: =AVERAGE(Coverage!J2:J113) -> 0.90178571
A13: Entries with all seven metrics observed | B13: =COUNTIF(Coverage!I2:I113,7) -> 68
A14: Interpretation | B14: Final scores reflect reported values and missingness because unavailable values score zero. Coverage is diagnostic only.
A15: Metric review | B15: See Metric Rules, Verification, Review Queue, Diagnostics, and Sensitivity.

Sheet Scoring
A1: Service | B1: Provider | C1: Solution category | D1: 024 structure status | E1: 108 bylaws status | F1: 050 board structure | G1: 950 other detail | H1: 048 community governance | I1: 029 accessibility status | J1: 035 equity status | K1: 044 privacy status | L1: G1 | M1: G2 | N1: G3 | O1: G4 | P1: G5 | Q1: G6 | R1: G7 | S1: Final score / 100 | T1: Rank | U1: Available metrics (of 7) | V1: Observed coverage | W1: Observed-only mean | X1: Data-quality notes
A2: 2i2c | B2: Code for Science and Society | C2: Authoring tool | D2: In progress | E2: Unknown | F2: Advisory board or steering committee | H2: None | I2: Considering | J2: Considering | K2: Implemented/available | L2: =Calc!B2 -> 67 | M2: =Calc!C2 -> 0 | N2: =Verification!F2 -> 100 | O2: =Calc!E2 -> 33 | P2: =Calc!F2 -> 33 | Q2: =Calc!G2 -> 100 | R2: =Calc!H2 -> 0 | S2: =AVERAGE(L2:R2) -> 47.571429 | T2: =RANK(S2,$S$2:$S$113,0)+(COUNTIF($S$2:$S$113,S2)-1)/2 -> 82.5 | U2: =Coverage!I2 -> 6 | V2: =Coverage!J2 -> 0.85714286 | W2: =IFERROR(SUMPRODUCT(L2:R2,Coverage!B2:H2)/U2,0) -> 55.5 | X2: 108_bylaws_status unavailable/unknown scored 0; No independent verification recorded
A3: Academic Preservation Trust (APTrust) | B3: Academic Preservation Trust (APTrust) | C3: Digital preservation service | D3: Implemented/available | E3: Implemented/available | F3: Multi-board governance | H3: Formal | I3: Considering | J3: Implemented/available | K3: Not planning | L3: =Calc!B3 -> 100 | M3: =Calc!C3 -> 100 | N3: =Verification!F3 -> 100 | O3: =Calc!E3 -> 33 | P3: =Calc!F3 -> 100 | Q3: =Calc!G3 -> 0 | R3: =Calc!H3 -> 100 | S3: =AVERAGE(L3:R3) -> 76.142857 | T3: =RANK(S3,$S$2:$S$113,0)+(COUNTIF($S$2:$S$113,S3)-1)/2 -> 44 | U3: =Coverage!I3 -> 7 | V3: =Coverage!J3 -> 1 | W3: =IFERROR(SUMPRODUCT(L3:R3,Coverage!B3:H3)/U3,0) -> 76.142857 | X3: No independent verification recorded
A4: AfricArXiv | B4: UbuntuNet Alliance | C4: Repository service | D4: Implemented/available | E4: Not planning | F4: Advisory board or steering committee | H4: Ad hoc | I4: In progress | J4: In progress | K4: Implemented/available | L4: =Calc!B4 -> 100 | M4: =Calc!C4 -> 0 | N4: =Verification!F4 -> 100 | O4: =Calc!E4 -> 67 | P4: =Calc!F4 -> 67 | Q4: =Calc!G4 -> 100 | R4: =Calc!H4 -> 50 | S4: =AVERAGE(L4:R4) -> 69.142857 | T4: =RANK(S4,$S$2:$S$113,0)+(COUNTIF($S$2:$S$113,S4)-1)/2 -> 58 | U4: =Coverage!I4 -> 7 | V4: =Coverage!J4 -> 1 | W4: =IFERROR(SUMPRODUCT(L4:R4,Coverage!B4:H4)/U4,0) -> 69.142857 | X4: No independent verification recorded
A5: Arches Heritage Data Management Platform | B5: Getty Conservation Institute (GCI) | C5: Data management planning tool or service | D5: Implemented/available | E5: Implemented/available | F5: Advisory board or steering committee | H5: Formal | I5: Implemented/available | J5: Not planning | K5: Not planning | L5: =Calc!B5 -> 100 | M5: =Calc!C5 -> 100 | N5: =Verification!F5 -> 100 | O5: =Calc!E5 -> 100 | P5: =Calc!F5 -> 0 | Q5: =Calc!G5 -> 0 | R5: =Calc!H5 -> 100 | S5: =AVERAGE(L5:R5) -> 71.428571 | T5: =RANK(S5,$S$2:$S$113,0)+(COUNTIF($S$2:$S$113,S5)-1)/2 -> 52 | U5: =Coverage!I5 -> 7 | V5: =Coverage!J5 -> 1 | W5: =IFERROR(SUMPRODUCT(L5:R5,Coverage!B5:H5)/U5,0) -> 71.428571 | X5: No independent verification recorded
A6: Archipelago Commons | B6: Metropolitan New York Library Council | C6: Digital library, collection or exhibit platform | Repository software | D6: Implemented/available | E6: Implemented/available | F6: Advisory board or steering committee | H6: Formal | I6: Implemented/available | J6: Implemented/available | K6: Considering | L6: =Calc!B6 -> 100 | M6: =Calc!C6 -> 100 | N6: =Verification!F6 -> 100 | O6: =Calc!E6 -> 100 | P6: =Calc!F6 -> 100 | Q6: =Calc!G6 -> 33 | R6: =Calc!H6 -> 100 | S6: =AVERAGE(L6:R6) -> 90.428571 | T6: =RANK(S6,$S$2:$S$113,0)+(COUNTIF($S$2:$S$113,S6)-1)/2 -> 23 | U6: =Coverage!I6 -> 7 | V6: =Coverage!J6 -> 1 | W6: =IFERROR(SUMPRODUCT(L6:R6,Coverage!B6:H6)/U6,0) -> 90.428571 | X6: No independent verification recorded
A7: Archival Resource Key | B7: ARK Alliance | C7: Standard, specification or protocol | D7: In progress | E7: Unknown | F7: Advisory board or steering committee | H7: Ad hoc | I7: In progress | J7: Considering | K7: Not applicable | L7: =Calc!B7 -> 67 | M7: =Calc!C7 -> 0 | N7: =Verification!F7 -> 100 | O7: =Calc!E7 -> 67 | P7: =Calc!F7 -> 33 | Q7: =Calc!G7 -> 0 | R7: =Calc!H7 -> 50 | S7: =AVERAGE(L7:R7) -> 45.285714 | T7: =RANK(S7,$S$2:$S$113,0)+(COUNTIF($S$2:$S$113,S7)-1)/2 -> 84.5 | U7: =Coverage!I7 -> 5 | V7: =Coverage!J7 -> 0.71428571 | W7: =IFERROR(SUMPRODUCT(L7:R7,Coverage!B7:H7)/U7,0) -> 63.4 | X7: 108_bylaws_status unavailable/unknown scored 0; 044_commitment_to_privacy_status unavailable/unknown scored 0; No independent verification recorded
A8: Archivematica | B8: Artefactual | C8: Digital preservation system | D8: Considering | E8: Considering | F8: None | H8: None | I8: Considering | J8: Considering | K8: Implemented/available | L8: =Calc!B8 -> 33 | M8: =Calc!C8 -> 33 | N8: =Verification!F8 -> 0 | O8: =Calc!E8 -> 33 | P8: =Calc!F8 -> 33 | Q8: =Calc!G8 -> 100 | R8: =Calc!H8 -> 0 | S8: =AVERAGE(L8:R8) -> 33.142857 | T8: =RANK(S8,$S$2:$S$113,0)+(COUNTIF($S$2:$S$113,S8)-1)/2 -> 99 | U8: =Coverage!I8 -> 7 | V8: =Coverage!J8 -> 1 | W8: =IFERROR(SUMPRODUCT(L8:R8,Coverage!B8:H8)/U8,0) -> 33.142857 | X8: No independent verification recorded
A9: ArchivesSpace | B9: ArchivesSpace | C9: Archive information management system | Discovery system | D9: Implemented/available | E9: Implemented/available | F9: Advisory board or steering committee | H9: Formal | I9: Implemented/available | J9: Implemented/available | K9: Implemented/available | L9: =Calc!B9 -> 100 | M9: =Calc!C9 -> 100 | N9: =Verification!F9 -> 100 | O9: =Calc!E9 -> 100 | P9: =Calc!F9 -> 100 | Q9: =Calc!G9 -> 100 | R9: =Calc!H9 -> 100 | S9: =AVERAGE(L9:R9) -> 100 | T9: =RANK(S9,$S$2:$S$113,0)+(COUNTIF($S$2:$S$113,S9)-1)/2 -> 4 | U9: =Coverage!I9 -> 7 | V9: =Coverage!J9 -> 1 | W9: =IFERROR(SUMPRODUCT(L9:R9,Coverage!B9:H9)/U9,0) -> 100 | X9: No independent verification recorded
A10: ARGOS | B10: OpenAIRE | C10: Data management planning tool or service | D10: Implemented/available | E10: Implemented/available | F10: Advisory board or steering committee | H10: Formal | I10: In progress | J10: Implemented/available | K10: Implemented/available | L10: =Calc!B10 -> 100 | M10: =Calc!C10 -> 100 | N10: =Verification!F10 -> 100 | O10: =Calc!E10 -> 67 | P10: =Calc!F10 -> 100 | Q10: =Calc!G10 -> 100 | R10: =Calc!H10 -> 100 | S10: =AVERAGE(L10:R10) -> 95.285714 | T10: =RANK(S10,$S$2:$S$113,0)+(COUNTIF($S$2:$S$113,S10)-1)/2 -> 12.5 | U10: =Coverage!I10 -> 7 | V10: =Coverage!J10 -> 1 | W10: =IFERROR(SUMPRODUCT(L10:R10,Coverage!B10:H10)/U10,0) -> 95.285714 | X10: No independent verification recorded
A11: arXiv | B11: Cornell University | C11: Repository service | D11: Implemented/available | E11: Implemented/available | F11: Multi-board governance | H11: Formal | I11: Implemented/available | J11: Unknown | K11: Implemented/available | L11: =Calc!B11 -> 100 | M11: =Calc!C11 -> 100 | N11: =Verification!F11 -> 100 | O11: =Calc!E11 -> 100 | P11: =Calc!F11 -> 0 | Q11: =Calc!G11 -> 100 | R11: =Calc!H11 -> 100 | S11: =AVERAGE(L11:R11) -> 85.714286 | T11: =RANK(S11,$S$2:$S$113,0)+(COUNTIF($S$2:$S$113,S11)-1)/2 -> 30 | U11: =Coverage!I11 -> 6 | V11: =Coverage!J11 -> 0.85714286 | W11: =IFERROR(SUMPRODUCT(L11:R11,Coverage!B11:H11)/U11,0) -> 100 | X11: 035_commitment_to_equity_status unavailable/unknown scored 0; No independent verification recorded
A12: AtoM | B12: Artefactual | C12: Archive information management system | D12: Considering | E12: Considering | I12: In progress | J12: Considering | K12: Implemented/available | L12: =Calc!B12 -> 33 | M12: =Calc!C12 -> 33 | N12: =Verification!F12 -> 0 | O12: =Calc!E12 -> 67 | P12: =Calc!F12 -> 33 | Q12: =Calc!G12 -> 100 | R12: =Calc!H12 -> 0 | S12: =AVERAGE(L12:R12) -> 38 | T12: =RANK(S12,$S$2:$S$113,0)+(COUNTIF($S$2:$S$113,S12)-1)/2 -> 93 | U12: =Coverage!I12 -> 5 | V12: =Coverage!J12 -> 0.71428571 | W12: =IFERROR(SUMPRODUCT(L12:R12,Coverage!B12:H12)/U12,0) -> 53.2 | X12: 048 community governance missing/unrecognized scored 0; No independent verification recorded
A13: Avalon Media System | B13: Indiana University Libraries | C13: Digital library, collection or exhibit platform | Repository software | D13: Implemented/available | E13: Implemented/available | F13: Advisory board or steering committee | H13: Formal | I13: In progress | J13: Considering | K13: Not planning | L13: =Calc!B13 -> 100 | M13: =Calc!C13 -> 100 | N13: =Verification!F13 -> 100 | O13: =Calc!E13 -> 67 | P13: =Calc!F13 -> 33 | Q13: =Calc!G13 -> 0 | R13: =Calc!H13 -> 100 | S13: =AVERAGE(L13:R13) -> 71.428571 | T13: =RANK(S13,$S$2:$S$113,0)+(COUNTIF($S$2:$S$113,S13)-1)/2 -> 52 | U13: =Coverage!I13 -> 7 | V13: =Coverage!J13 -> 1 | W13: =IFERROR(SUMPRODUCT(L13:R13,Coverage!B13:H13)/U13,0) -> 71.428571 | X13: No independent verification recorded
A14: Biodiversity Heritage Library | B14: BHL Consortium | C14: Digital library, collection or exhibit platform | Open scholarly dataset | Repository service | D14: Implemented/available | E14: Implemented/available | F14: Advisory board or steering committee | H14: Formal | I14: Considering | J14: Considering | K14: Implemented/available | L14: =Calc!B14 -> 100 | M14: =Calc!C14 -> 100 | N14: =Verification!F14 -> 100 | O14: =Calc!E14 -> 33 | P14: =Calc!F14 -> 33 | Q14: =Calc!G14 -> 100 | R14: =Calc!H14 -> 100 | S14: =AVERAGE(L14:R14) -> 80.857143 | T14: =RANK(S14,$S$2:$S$113,0)+(COUNTIF($S$2:$S$113,S14)-1)/2 -> 37 | U14: =Coverage!I14 -> 7 | V14: =Coverage!J14 -> 1 | W14: =IFERROR(SUMPRODUCT(L14:R14,Coverage!B14:H14)/U14,0) -> 80.857143 | X14: No independent verification recorded
A15: bioRxiv | B15: Cold Spring Harbor Laboratory | C15: Repository service | D15: In progress | E15: Unknown | F15: Advisory board or steering committee | H15: Ad hoc | I15: Considering | J15: In progress | K15: Implemented/available | L15: =Calc!B15 -> 67 | M15: =Calc!C15 -> 0 | N15: =Verification!F15 -> 100 | O15: =Calc!E15 -> 33 | P15: =Calc!F15 -> 67 | Q15: =Calc!G15 -> 100 | R15: =Calc!H15 -> 50 | S15: =AVERAGE(L15:R15) -> 59.571429 | T15: =RANK(S15,$S$2:$S$113,0)+(COUNTIF($S$2:$S$113,S15)-1)/2 -> 67 | U15: =Coverage!I15 -> 6 | V15: =Coverage!J15 -> 0.85714286 | W15: =IFERROR(SUMPRODUCT(L15:R15,Coverage!B15:H15)/U15,0) -> 69.5 | X15: 108_bylaws_status unavailable/unknown scored 0; No independent verification recorded
A16: BitCurator Environment | B16: BitCurator Consortium | C16: Digital preservation tool | D16: Implemented/available | E16: Implemented/available | F16: Advisory board or steering committee | H16: Formal | I16: Considering | J16: Implemented/available | K16: Implemented/available | L16: =Calc!B16 -> 100 | M16: =Calc!C16 -> 100 | N16: =Verification!F16 -> 100 | O16: =Calc!E16 -> 33 | P16: =Calc!F16 -> 100 | Q16: =Calc!G16 -> 100 | R16: =Calc!H16 -> 100 | S16: =AVERAGE(L16:R16) -> 90.428571 | T16: =RANK(S16,$S$2:$S$113,0)+(COUNTIF($S$2:$S$113,S16)-1)/2 -> 23 | U16: =Coverage!I16 -> 7 | V16: =Coverage!J16 -> 1 | W16: =IFERROR(SUMPRODUCT(L16:R16,Coverage!B16:H16)/U16,0) -> 90.428571 | X16: No independent verification recorded
A17: Blacklight | B17: Blacklight | C17: Discovery system | Integrated Library System (ILS) or Library Services Platform (LSP) | D17: In progress | E17: In progress | F17: None | H17: Ad hoc | I17: In progress | J17: In progress | K17: In progress | L17: =Calc!B17 -> 67 | M17: =Calc!C17 -> 67 | N17: =Verification!F17 -> 0 | O17: =Calc!E17 -> 67 | P17: =Calc!F17 -> 67 | Q17: =Calc!G17 -> 67 | R17: =Calc!H17 -> 50 | S17: =AVERAGE(L17:R17) -> 55 | T17: =RANK(S17,$S$2:$S$113,0)+(COUNTIF($S$2:$S$113,S17)-1)/2 -> 73 | U17: =Coverage!I17 -> 7 | V17: =Coverage!J17 -> 1 | W17: =IFERROR(SUMPRODUCT(L17:R17,Coverage!B17:H17)/U17,0) -> 55 | X17: No independent verification recorded
A18: BrCRIS | B18: IBICT | C18: Discovery system | Research profiling system | D18: Unknown | E18: Unknown | F18: Advisory board or steering committee | H18: Ad hoc | I18: In progress | J18: Considering | K18: Implemented/available | L18: =Calc!B18 -> 0 | M18: =Calc!C18 -> 0 | N18: =Verification!F18 -> 100 | O18: =Calc!E18 -> 67 | P18: =Calc!F18 -> 33 | Q18: =Calc!G18 -> 100 | R18: =Calc!H18 -> 50 | S18: =AVERAGE(L18:R18) -> 50 | T18: =RANK(S18,$S$2:$S$113,0)+(COUNTIF($S$2:$S$113,S18)-1)/2 -> 79 | U18: =Coverage!I18 -> 5 | V18: =Coverage!J18 -> 0.71428571 | W18: =IFERROR(SUMPRODUCT(L18:R18,Coverage!B18:H18)/U18,0) -> 70 | X18: 024_governance_structure_status unavailable/unknown scored 0; 108_bylaws_status unavailable/unknown scored 0; No independent verification recorded
A19: Browsertrix | B19: Webrecorder | C19: Digital library, collection or exhibit platform | Web archiving system | D19: Not planning | E19: Not planning | F19: None | H19: None | I19: Unknown | J19: Unknown | K19: Implemented/available | L19: =Calc!B19 -> 0 | M19: =Calc!C19 -> 0 | N19: =Verification!F19 -> 0 | O19: =Calc!E19 -> 0 | P19: =Calc!F19 -> 0 | Q19: =Calc!G19 -> 100 | R19: =Calc!H19 -> 0 | S19: =AVERAGE(L19:R19) -> 14.285714 | T19: =RANK(S19,$S$2:$S$113,0)+(COUNTIF($S$2:$S$113,S19)-1)/2 -> 108 | U19: =Coverage!I19 -> 5 | V19: =Coverage!J19 -> 0.71428571 | W19: =IFERROR(SUMPRODUCT(L19:R19,Coverage!B19:H19)/U19,0) -> 20 | X19: 029_web_accessibility_status unavailable/unknown scored 0; 035_commitment_to_equity_status unavailable/unknown scored 0; No independent verification recorded
A20: CLOCKSS | B20: CLOCKSS | C20: Digital preservation service | D20: Implemented/available | E20: Implemented/available | F20: Advisory board or steering committee | H20: Formal | I20: In progress | J20: Implemented/available | K20: Implemented/available | L20: =Calc!B20 -> 100 | M20: =Calc!C20 -> 100 | N20: =Verification!F20 -> 100 | O20: =Calc!E20 -> 67 | P20: =Calc!F20 -> 100 | Q20: =Calc!G20 -> 100 | R20: =Calc!H20 -> 100 | S20: =AVERAGE(L20:R20) -> 95.285714 | T20: =RANK(S20,$S$2:$S$113,0)+(COUNTIF($S$2:$S$113,S20)-1)/2 -> 12.5 | U20: =Coverage!I20 -> 7 | V20: =Coverage!J20 -> 1 | W20: =IFERROR(SUMPRODUCT(L20:R20,Coverage!B20:H20)/U20,0) -> 95.285714 | X20: No independent verification recorded
A21: COAR International Repository Directory (IRD) | B21: COAR | C21: Index or directory | D21: Implemented/available | E21: In progress | F21: Advisory board or steering committee | H21: Ad hoc | I21: Considering | J21: Implemented/available | K21: Not planning | L21: =Calc!B21 -> 100 | M21: =Calc!C21 -> 67 | N21: =Verification!F21 -> 100 | O21: =Calc!E21 -> 33 | P21: =Calc!F21 -> 100 | Q21: =Calc!G21 -> 0 | R21: =Calc!H21 -> 50 | S21: =AVERAGE(L21:R21) -> 64.285714 | T21: =RANK(S21,$S$2:$S$113,0)+(COUNTIF($S$2:$S$113,S21)-1)/2 -> 61 | U21: =Coverage!I21 -> 7 | V21: =Coverage!J21 -> 1 | W21: =IFERROR(SUMPRODUCT(L21:R21,Coverage!B21:H21)/U21,0) -> 64.285714 | X21: No independent verification recorded
A22: COAR Notify | B22: COAR | C22: Standard, specification or protocol | D22: Implemented/available | E22: Not planning | F22: Other | G22: Editorial Board | H22: Ad hoc | I22: Considering | J22: Implemented/available | K22: Not planning | L22: =Calc!B22 -> 100 | M22: =Calc!C22 -> 0 | N22: =Verification!F22 -> 0 | O22: =Calc!E22 -> 33 | P22: =Calc!F22 -> 100 | Q22: =Calc!G22 -> 0 | R22: =Calc!H22 -> 50 | S22: =AVERAGE(L22:R22) -> 40.428571 | T22: =RANK(S22,$S$2:$S$113,0)+(COUNTIF($S$2:$S$113,S22)-1)/2 -> 89 | U22: =Coverage!I22 -> 7 | V22: =Coverage!J22 -> 1 | W22: =IFERROR(SUMPRODUCT(L22:R22,Coverage!B22:H22)/U22,0) -> 40.428571 | X22: Review 050 Other response; override available; No independent verification recorded
A23: CollectiveAccess | B23: Whirl-i-Gig | C23: Archive information management system | Digital asset management system | Digital library, collection or exhibit platform | D23: Not planning | E23: Not planning | F23: None | H23: Ad hoc | I23: In progress | J23: Not planning | K23: Not planning | L23: =Calc!B23 -> 0 | M23: =Calc!C23 -> 0 | N23: =Verification!F23 -> 0 | O23: =Calc!E23 -> 67 | P23: =Calc!F23 -> 0 | Q23: =Calc!G23 -> 0 | R23: =Calc!H23 -> 50 | S23: =AVERAGE(L23:R23) -> 16.714286 | T23: =RANK(S23,$S$2:$S$113,0)+(COUNTIF($S$2:$S$113,S23)-1)/2 -> 106 | U23: =Coverage!I23 -> 7 | V23: =Coverage!J23 -> 1 | W23: =IFERROR(SUMPRODUCT(L23:R23,Coverage!B23:H23)/U23,0) -> 16.714286 | X23: No independent verification recorded
A24: CORE | B24: The Open University | C24: Discovery system | D24: Implemented/available | E24: Implemented/available | F24: Multi-board governance | H24: Formal | I24: Implemented/available | J24: Considering | K24: Implemented/available | L24: =Calc!B24 -> 100 | M24: =Calc!C24 -> 100 | N24: =Verification!F24 -> 100 | O24: =Calc!E24 -> 100 | P24: =Calc!F24 -> 33 | Q24: =Calc!G24 -> 100 | R24: =Calc!H24 -> 100 | S24: =AVERAGE(L24:R24) -> 90.428571 | T24: =RANK(S24,$S$2:$S$113,0)+(COUNTIF($S$2:$S$113,S24)-1)/2 -> 23 | U24: =Coverage!I24 -> 7 | V24: =Coverage!J24 -> 1 | W24: =IFERROR(SUMPRODUCT(L24:R24,Coverage!B24:H24)/U24,0) -> 90.428571 | X24: No independent verification recorded
A25: COUNTER Code of Practice | B25: COUNTER Metrics | C25: Standard, specification or protocol | D25: Implemented/available | E25: Implemented/available | F25: Multi-board governance | H25: Formal | I25: Implemented/available | J25: In progress | K25: Implemented/available | L25: =Calc!B25 -> 100 | M25: =Calc!C25 -> 100 | N25: =Verification!F25 -> 100 | O25: =Calc!E25 -> 100 | P25: =Calc!F25 -> 67 | Q25: =Calc!G25 -> 100 | R25: =Calc!H25 -> 100 | S25: =AVERAGE(L25:R25) -> 95.285714 | T25: =RANK(S25,$S$2:$S$113,0)+(COUNTIF($S$2:$S$113,S25)-1)/2 -> 12.5 | U25: =Coverage!I25 -> 7 | V25: =Coverage!J25 -> 1 | W25: =IFERROR(SUMPRODUCT(L25:R25,Coverage!B25:H25)/U25,0) -> 95.285714 | X25: No independent verification recorded
A26: Creative Commons Licenses | B26: Creative Commons | C26: Standard, specification or protocol | D26: Implemented/available | E26: Unknown | F26: Advisory board or steering committee | H26: None | I26: Considering | J26: In progress | K26: Implemented/available | L26: =Calc!B26 -> 100 | M26: =Calc!C26 -> 0 | N26: =Verification!F26 -> 100 | O26: =Calc!E26 -> 33 | P26: =Calc!F26 -> 67 | Q26: =Calc!G26 -> 100 | R26: =Calc!H26 -> 0 | S26: =AVERAGE(L26:R26) -> 57.142857 | T26: =RANK(S26,$S$2:$S$113,0)+(COUNTIF($S$2:$S$113,S26)-1)/2 -> 71 | U26: =Coverage!I26 -> 6 | V26: =Coverage!J26 -> 0.85714286 | W26: =IFERROR(SUMPRODUCT(L26:R26,Coverage!B26:H26)/U26,0) -> 66.666667 | X26: 108_bylaws_status unavailable/unknown scored 0; No independent verification recorded
A27: Crossref Metadata Retrieval | B27: Crossref | C27: Open scholarly dataset | D27: Implemented/available | E27: Implemented/available | F27: Multi-board governance | H27: Formal | I27: In progress | J27: Implemented/available | K27: Implemented/available | L27: =Calc!B27 -> 100 | M27: =Calc!C27 -> 100 | N27: =Verification!F27 -> 100 | O27: =Calc!E27 -> 67 | P27: =Calc!F27 -> 100 | Q27: =Calc!G27 -> 100 | R27: =Calc!H27 -> 100 | S27: =AVERAGE(L27:R27) -> 95.285714 | T27: =RANK(S27,$S$2:$S$113,0)+(COUNTIF($S$2:$S$113,S27)-1)/2 -> 12.5 | U27: =Coverage!I27 -> 7 | V27: =Coverage!J27 -> 1 | W27: =IFERROR(SUMPRODUCT(L27:R27,Coverage!B27:H27)/U27,0) -> 95.285714 | X27: No independent verification recorded
A28: D4Science Infrastructure | B28: National Research Council of Italy | C28: Computing framework | Informal scholarly communications | Repository service | D28: In progress | E28: Not planning | I28: Considering | J28: Considering | K28: Implemented/available | L28: =Calc!B28 -> 67 | M28: =Calc!C28 -> 0 | N28: =Verification!F28 -> 0 | O28: =Calc!E28 -> 33 | P28: =Calc!F28 -> 33 | Q28: =Calc!G28 -> 100 | R28: =Calc!H28 -> 0 | S28: =AVERAGE(L28:R28) -> 33.285714 | T28: =RANK(S28,$S$2:$S$113,0)+(COUNTIF($S$2:$S$113,S28)-1)/2 -> 97.5 | U28: =Coverage!I28 -> 5 | V28: =Coverage!J28 -> 0.71428571 | W28: =IFERROR(SUMPRODUCT(L28:R28,Coverage!B28:H28)/U28,0) -> 46.6 | X28: 048 community governance missing/unrecognized scored 0; No independent verification recorded
A29: DART (Digital Archivist's Resource Tool) | B29: Academic Preservation Trust (APTrust) | C29: Digital preservation tool | D29: Implemented/available | E29: Implemented/available | F29: Advisory board or steering committee | H29: Formal | I29: In progress | J29: Implemented/available | K29: Not planning | L29: =Calc!B29 -> 100 | M29: =Calc!C29 -> 100 | N29: =Verification!F29 -> 100 | O29: =Calc!E29 -> 67 | P29: =Calc!F29 -> 100 | Q29: =Calc!G29 -> 0 | R29: =Calc!H29 -> 100 | S29: =AVERAGE(L29:R29) -> 81 | T29: =RANK(S29,$S$2:$S$113,0)+(COUNTIF($S$2:$S$113,S29)-1)/2 -> 33 | U29: =Coverage!I29 -> 7 | V29: =Coverage!J29 -> 1 | W29: =IFERROR(SUMPRODUCT(L29:R29,Coverage!B29:H29)/U29,0) -> 81 | X29: No independent verification recorded
A30: Database Information System | B30: University Library of Regensburg | C30: Discovery system | Index or directory | D30: Implemented/available | E30: Unknown | F30: Advisory board or steering committee | H30: Ad hoc | I30: Unknown | J30: Unknown | K30: Implemented/available | L30: =Calc!B30 -> 100 | M30: =Calc!C30 -> 0 | N30: =Verification!F30 -> 100 | O30: =Calc!E30 -> 0 | P30: =Calc!F30 -> 0 | Q30: =Calc!G30 -> 100 | R30: =Calc!H30 -> 50 | S30: =AVERAGE(L30:R30) -> 50 | T30: =RANK(S30,$S$2:$S$113,0)+(COUNTIF($S$2:$S$113,S30)-1)/2 -> 79 | U30: =Coverage!I30 -> 4 | V30: =Coverage!J30 -> 0.57142857 | W30: =IFERROR(SUMPRODUCT(L30:R30,Coverage!B30:H30)/U30,0) -> 87.5 | X30: 108_bylaws_status unavailable/unknown scored 0; 029_web_accessibility_status unavailable/unknown scored 0; 035_commitment_to_equity_status unavailable/unknown scored 0; No independent verification recorded
A31: Data Citation Corpus | B31: Make Data Count | C31: Discovery system | Open scholarly dataset | D31: Implemented/available | E31: Not planning | F31: None | H31: Ad hoc | I31: Considering | J31: Not planning | K31: Implemented/available | L31: =Calc!B31 -> 100 | M31: =Calc!C31 -> 0 | N31: =Verification!F31 -> 0 | O31: =Calc!E31 -> 33 | P31: =Calc!F31 -> 0 | Q31: =Calc!G31 -> 100 | R31: =Calc!H31 -> 50 | S31: =AVERAGE(L31:R31) -> 40.428571 | T31: =RANK(S31,$S$2:$S$113,0)+(COUNTIF($S$2:$S$113,S31)-1)/2 -> 89 | U31: =Coverage!I31 -> 7 | V31: =Coverage!J31 -> 1 | W31: =IFERROR(SUMPRODUCT(L31:R31,Coverage!B31:H31)/U31,0) -> 40.428571 | X31: No independent verification recorded
A32: DataCite | B32: DataCite | C32: Discovery system | Persistent identifier service | D32: Implemented/available | E32: Implemented/available | F32: Advisory board or steering committee | H32: Formal | I32: In progress | J32: Implemented/available | K32: Implemented/available | L32: =Calc!B32 -> 100 | M32: =Calc!C32 -> 100 | N32: =Verification!F32 -> 100 | O32: =Calc!E32 -> 67 | P32: =Calc!F32 -> 100 | Q32: =Calc!G32 -> 100 | R32: =Calc!H32 -> 100 | S32: =AVERAGE(L32:R32) -> 95.285714 | T32: =RANK(S32,$S$2:$S$113,0)+(COUNTIF($S$2:$S$113,S32)-1)/2 -> 12.5 | U32: =Coverage!I32 -> 7 | V32: =Coverage!J32 -> 1 | W32: =IFERROR(SUMPRODUCT(L32:R32,Coverage!B32:H32)/U32,0) -> 95.285714 | X32: No independent verification recorded
A33: Data Stewardship Wizard | B33: DSW Team | C33: Data management planning tool or service | D33: Implemented/available | E33: Not planning | F33: Advisory board or steering committee | H33: Ad hoc | I33: In progress | J33: Implemented/available | K33: Not planning | L33: =Calc!B33 -> 100 | M33: =Calc!C33 -> 0 | N33: =Verification!F33 -> 100 | O33: =Calc!E33 -> 67 | P33: =Calc!F33 -> 100 | Q33: =Calc!G33 -> 0 | R33: =Calc!H33 -> 50 | S33: =AVERAGE(L33:R33) -> 59.571429 | T33: =RANK(S33,$S$2:$S$113,0)+(COUNTIF($S$2:$S$113,S33)-1)/2 -> 67 | U33: =Coverage!I33 -> 7 | V33: =Coverage!J33 -> 1 | W33: =IFERROR(SUMPRODUCT(L33:R33,Coverage!B33:H33)/U33,0) -> 59.571429 | X33: No independent verification recorded
A34: Dataverse | B34: Harvard University Institute for Quantitative Social Science (IQSS) | C34: Repository software | D34: Implemented/available | E34: Unknown | F34: None | H34: Ad hoc | I34: In progress | J34: Implemented/available | K34: Implemented/available | L34: =Calc!B34 -> 100 | M34: =Calc!C34 -> 0 | N34: =Verification!F34 -> 0 | O34: =Calc!E34 -> 67 | P34: =Calc!F34 -> 100 | Q34: =Calc!G34 -> 100 | R34: =Calc!H34 -> 50 | S34: =AVERAGE(L34:R34) -> 59.571429 | T34: =RANK(S34,$S$2:$S$113,0)+(COUNTIF($S$2:$S$113,S34)-1)/2 -> 67 | U34: =Coverage!I34 -> 6 | V34: =Coverage!J34 -> 0.85714286 | W34: =IFERROR(SUMPRODUCT(L34:R34,Coverage!B34:H34)/U34,0) -> 69.5 | X34: 108_bylaws_status unavailable/unknown scored 0; No independent verification recorded
A35: DLCM Backend | B35: DLCM Technology | C35: Archive information management system | Digital preservation system | D35: Implemented/available | E35: Not planning | F35: Advisory board or steering committee | H35: None | I35: Considering | J35: Not planning | K35: Considering | L35: =Calc!B35 -> 100 | M35: =Calc!C35 -> 0 | N35: =Verification!F35 -> 100 | O35: =Calc!E35 -> 33 | P35: =Calc!F35 -> 0 | Q35: =Calc!G35 -> 33 | R35: =Calc!H35 -> 0 | S35: =AVERAGE(L35:R35) -> 38 | T35: =RANK(S35,$S$2:$S$113,0)+(COUNTIF($S$2:$S$113,S35)-1)/2 -> 93 | U35: =Coverage!I35 -> 7 | V35: =Coverage!J35 -> 1 | W35: =IFERROR(SUMPRODUCT(L35:R35,Coverage!B35:H35)/U35,0) -> 38 | X35: No independent verification recorded
A36: DLCM Portal | B36: DLCM Technology | C36: Archive information management system | Digital preservation system | Software preservation service | D36: Implemented/available | E36: Not planning | F36: Advisory board or steering committee | H36: None | I36: Considering | J36: Not planning | K36: Considering | L36: =Calc!B36 -> 100 | M36: =Calc!C36 -> 0 | N36: =Verification!F36 -> 100 | O36: =Calc!E36 -> 33 | P36: =Calc!F36 -> 0 | Q36: =Calc!G36 -> 33 | R36: =Calc!H36 -> 0 | S36: =AVERAGE(L36:R36) -> 38 | T36: =RANK(S36,$S$2:$S$113,0)+(COUNTIF($S$2:$S$113,S36)-1)/2 -> 93 | U36: =Coverage!I36 -> 7 | V36: =Coverage!J36 -> 1 | W36: =IFERROR(SUMPRODUCT(L36:R36,Coverage!B36:H36)/U36,0) -> 38 | X36: No independent verification recorded
A37: DMP Tool | B37: California Digital Library | C37: Data management planning tool or service | D37: Not planning | E37: Not planning | F37: None | H37: None | I37: Implemented/available | J37: Not planning | K37: Implemented/available | L37: =Calc!B37 -> 0 | M37: =Calc!C37 -> 0 | N37: =Verification!F37 -> 0 | O37: =Calc!E37 -> 100 | P37: =Calc!F37 -> 0 | Q37: =Calc!G37 -> 100 | R37: =Calc!H37 -> 0 | S37: =AVERAGE(L37:R37) -> 28.571429 | T37: =RANK(S37,$S$2:$S$113,0)+(COUNTIF($S$2:$S$113,S37)-1)/2 -> 100 | U37: =Coverage!I37 -> 7 | V37: =Coverage!J37 -> 1 | W37: =IFERROR(SUMPRODUCT(L37:R37,Coverage!B37:H37)/U37,0) -> 28.571429 | X37: No independent verification recorded
A38: DOAJ (Directory of Open Access Journals) | B38: DOAJ Foundation | C38: Discovery system | Index or directory | Open scholarly dataset | D38: Implemented/available | E38: Implemented/available | F38: Advisory board or steering committee | Other | G38: Foundation Board & Advisory Board | H38: Formal | I38: Implemented/available | J38: Implemented/available | K38: Implemented/available | L38: =Calc!B38 -> 100 | M38: =Calc!C38 -> 100 | N38: =Verification!F38 -> 100 | O38: =Calc!E38 -> 100 | P38: =Calc!F38 -> 100 | Q38: =Calc!G38 -> 100 | R38: =Calc!H38 -> 100 | S38: =AVERAGE(L38:R38) -> 100 | T38: =RANK(S38,$S$2:$S$113,0)+(COUNTIF($S$2:$S$113,S38)-1)/2 -> 4 | U38: =Coverage!I38 -> 7 | V38: =Coverage!J38 -> 1 | W38: =IFERROR(SUMPRODUCT(L38:R38,Coverage!B38:H38)/U38,0) -> 100 | X38: No independent verification recorded
A39: dokieli | B39: dokieli | C39: Annotations system | Authoring tool | Informal scholarly communications | D39: Unknown | E39: Unknown | H39: None | I39: Implemented/available | J39: Unknown | K39: Not applicable | L39: =Calc!B39 -> 0 | M39: =Calc!C39 -> 0 | N39: =Verification!F39 -> 0 | O39: =Calc!E39 -> 100 | P39: =Calc!F39 -> 0 | Q39: =Calc!G39 -> 0 | R39: =Calc!H39 -> 0 | S39: =AVERAGE(L39:R39) -> 14.285714 | T39: =RANK(S39,$S$2:$S$113,0)+(COUNTIF($S$2:$S$113,S39)-1)/2 -> 108 | U39: =Coverage!I39 -> 2 | V39: =Coverage!J39 -> 0.28571429 | W39: =IFERROR(SUMPRODUCT(L39:R39,Coverage!B39:H39)/U39,0) -> 50 | X39: 024_governance_structure_status unavailable/unknown scored 0; 108_bylaws_status unavailable/unknown scored 0; 035_commitment_to_equity_status unavailable/unknown scored 0; 044_commitment_to_privacy_status unavailable/unknown scored 0; No independent verification recorded
A40: Dryad | B40: Dryad | C40: Repository service | D40: Implemented/available | E40: Implemented/available | F40: Other | H40: Formal | I40: Implemented/available | J40: In progress | K40: Implemented/available | L40: =Calc!B40 -> 100 | M40: =Calc!C40 -> 100 | N40: =Verification!F40 -> 0 | O40: =Calc!E40 -> 100 | P40: =Calc!F40 -> 67 | Q40: =Calc!G40 -> 100 | R40: =Calc!H40 -> 100 | S40: =AVERAGE(L40:R40) -> 81 | T40: =RANK(S40,$S$2:$S$113,0)+(COUNTIF($S$2:$S$113,S40)-1)/2 -> 33 | U40: =Coverage!I40 -> 7 | V40: =Coverage!J40 -> 1 | W40: =IFERROR(SUMPRODUCT(L40:R40,Coverage!B40:H40)/U40,0) -> 81 | X40: Review 050 Other response; override available; No independent verification recorded
A41: DSpace | B41: Lyrasis | C41: Repository software | D41: Implemented/available | E41: Implemented/available | F41: Advisory board or steering committee | H41: Formal | I41: Implemented/available | J41: Implemented/available | K41: Implemented/available | L41: =Calc!B41 -> 100 | M41: =Calc!C41 -> 100 | N41: =Verification!F41 -> 100 | O41: =Calc!E41 -> 100 | P41: =Calc!F41 -> 100 | Q41: =Calc!G41 -> 100 | R41: =Calc!H41 -> 100 | S41: =AVERAGE(L41:R41) -> 100 | T41: =RANK(S41,$S$2:$S$113,0)+(COUNTIF($S$2:$S$113,S41)-1)/2 -> 4 | U41: =Coverage!I41 -> 7 | V41: =Coverage!J41 -> 1 | W41: =IFERROR(SUMPRODUCT(L41:R41,Coverage!B41:H41)/U41,0) -> 100 | X41: No independent verification recorded
A42: DuraCloud | B42: Lyrasis | C42: Digital preservation service | Digital preservation system | Digital preservation tool | D42: Unknown | E42: Not planning | F42: None | I42: Unknown | J42: Unknown | K42: Unknown | L42: =Calc!B42 -> 0 | M42: =Calc!C42 -> 0 | N42: =Verification!F42 -> 0 | O42: =Calc!E42 -> 0 | P42: =Calc!F42 -> 0 | Q42: =Calc!G42 -> 0 | R42: =Calc!H42 -> 0 | S42: =AVERAGE(L42:R42) -> 0 | T42: =RANK(S42,$S$2:$S$113,0)+(COUNTIF($S$2:$S$113,S42)-1)/2 -> 111 | U42: =Coverage!I42 -> 2 | V42: =Coverage!J42 -> 0.28571429 | W42: =IFERROR(SUMPRODUCT(L42:R42,Coverage!B42:H42)/U42,0) -> 0 | X42: 024_governance_structure_status unavailable/unknown scored 0; 029_web_accessibility_status unavailable/unknown scored 0; 035_commitment_to_equity_status unavailable/unknown scored 0; 044_commitment_to_privacy_status unavailable/unknown scored 0; 048 community governance missing/unrecognized scored 0; No independent verification recorded
A43: Episciences | B43: Center for Direct Scientific Communication (CCSD) | C43: Peer review system | Publishing system | Submissions system | D43: Implemented/available | E43: Implemented/available | F43: Multi-board governance | H43: Ad hoc | I43: In progress | J43: Considering | K43: Implemented/available | L43: =Calc!B43 -> 100 | M43: =Calc!C43 -> 100 | N43: =Verification!F43 -> 100 | O43: =Calc!E43 -> 67 | P43: =Calc!F43 -> 33 | Q43: =Calc!G43 -> 100 | R43: =Calc!H43 -> 50 | S43: =AVERAGE(L43:R43) -> 78.571429 | T43: =RANK(S43,$S$2:$S$113,0)+(COUNTIF($S$2:$S$113,S43)-1)/2 -> 40.5 | U43: =Coverage!I43 -> 7 | V43: =Coverage!J43 -> 1 | W43: =IFERROR(SUMPRODUCT(L43:R43,Coverage!B43:H43)/U43,0) -> 78.571429 | X43: No independent verification recorded
A44: EPrints | B44: EPrints Services | C44: Repository software | D44: In progress | E44: Unknown | I44: In progress | J44: Unknown | K44: Unknown | L44: =Calc!B44 -> 67 | M44: =Calc!C44 -> 0 | N44: =Verification!F44 -> 0 | O44: =Calc!E44 -> 67 | P44: =Calc!F44 -> 0 | Q44: =Calc!G44 -> 0 | R44: =Calc!H44 -> 0 | S44: =AVERAGE(L44:R44) -> 19.142857 | T44: =RANK(S44,$S$2:$S$113,0)+(COUNTIF($S$2:$S$113,S44)-1)/2 -> 105 | U44: =Coverage!I44 -> 2 | V44: =Coverage!J44 -> 0.28571429 | W44: =IFERROR(SUMPRODUCT(L44:R44,Coverage!B44:H44)/U44,0) -> 67 | X44: 108_bylaws_status unavailable/unknown scored 0; 035_commitment_to_equity_status unavailable/unknown scored 0; 044_commitment_to_privacy_status unavailable/unknown scored 0; 048 community governance missing/unrecognized scored 0; No independent verification recorded
A45: Érudit | B45: Érudit | C45: Discovery system | Publishing system | Repository software | D45: Implemented/available | E45: Implemented/available | F45: Multi-board governance | H45: Formal | I45: Implemented/available | J45: Implemented/available | K45: Implemented/available | L45: =Calc!B45 -> 100 | M45: =Calc!C45 -> 100 | N45: =Verification!F45 -> 100 | O45: =Calc!E45 -> 100 | P45: =Calc!F45 -> 100 | Q45: =Calc!G45 -> 100 | R45: =Calc!H45 -> 100 | S45: =AVERAGE(L45:R45) -> 100 | T45: =RANK(S45,$S$2:$S$113,0)+(COUNTIF($S$2:$S$113,S45)-1)/2 -> 4 | U45: =Coverage!I45 -> 7 | V45: =Coverage!J45 -> 1 | W45: =IFERROR(SUMPRODUCT(L45:R45,Coverage!B45:H45)/U45,0) -> 100 | X45: No independent verification recorded
A46: Europe PMC | B46: EMBL European Bioinformatics Institute (EMBL-EBI) | C46: Digital preservation system | Discovery system | Repository service | D46: Implemented/available | E46: Implemented/available | F46: Advisory board or steering committee | H46: Formal | I46: Implemented/available | J46: Implemented/available | K46: Implemented/available | L46: =Calc!B46 -> 100 | M46: =Calc!C46 -> 100 | N46: =Verification!F46 -> 100 | O46: =Calc!E46 -> 100 | P46: =Calc!F46 -> 100 | Q46: =Calc!G46 -> 100 | R46: =Calc!H46 -> 100 | S46: =AVERAGE(L46:R46) -> 100 | T46: =RANK(S46,$S$2:$S$113,0)+(COUNTIF($S$2:$S$113,S46)-1)/2 -> 4 | U46: =Coverage!I46 -> 7 | V46: =Coverage!J46 -> 1 | W46: =IFERROR(SUMPRODUCT(L46:R46,Coverage!B46:H46)/U46,0) -> 100 | X46: No independent verification recorded
A47: FAIR Wizard | B47: Codevence Solution s.r.o. | C47: Data management planning tool or service | D47: In progress | E47: Not planning | F47: None | H47: Ad hoc | I47: In progress | J47: Considering | K47: Implemented/available | L47: =Calc!B47 -> 67 | M47: =Calc!C47 -> 0 | N47: =Verification!F47 -> 0 | O47: =Calc!E47 -> 67 | P47: =Calc!F47 -> 33 | Q47: =Calc!G47 -> 100 | R47: =Calc!H47 -> 50 | S47: =AVERAGE(L47:R47) -> 45.285714 | T47: =RANK(S47,$S$2:$S$113,0)+(COUNTIF($S$2:$S$113,S47)-1)/2 -> 84.5 | U47: =Coverage!I47 -> 7 | V47: =Coverage!J47 -> 1 | W47: =IFERROR(SUMPRODUCT(L47:R47,Coverage!B47:H47)/U47,0) -> 45.285714 | X47: No independent verification recorded
A48: Fedora | B48: Lyrasis | C48: Repository software | D48: Implemented/available | E48: Implemented/available | F48: Advisory board or steering committee | H48: Formal | I48: Considering | J48: Implemented/available | K48: Implemented/available | L48: =Calc!B48 -> 100 | M48: =Calc!C48 -> 100 | N48: =Verification!F48 -> 100 | O48: =Calc!E48 -> 33 | P48: =Calc!F48 -> 100 | Q48: =Calc!G48 -> 100 | R48: =Calc!H48 -> 100 | S48: =AVERAGE(L48:R48) -> 90.428571 | T48: =RANK(S48,$S$2:$S$113,0)+(COUNTIF($S$2:$S$113,S48)-1)/2 -> 23 | U48: =Coverage!I48 -> 7 | V48: =Coverage!J48 -> 1 | W48: =IFERROR(SUMPRODUCT(L48:R48,Coverage!B48:H48)/U48,0) -> 90.428571 | X48: No independent verification recorded
A49: fido | B49: Open Preservation Foundation | C49: Digital preservation tool | D49: Implemented/available | E49: Unknown | F49: Advisory board or steering committee | H49: Formal | I49: Considering | J49: In progress | K49: Implemented/available | L49: =Calc!B49 -> 100 | M49: =Calc!C49 -> 0 | N49: =Verification!F49 -> 100 | O49: =Calc!E49 -> 33 | P49: =Calc!F49 -> 67 | Q49: =Calc!G49 -> 100 | R49: =Calc!H49 -> 100 | S49: =AVERAGE(L49:R49) -> 71.428571 | T49: =RANK(S49,$S$2:$S$113,0)+(COUNTIF($S$2:$S$113,S49)-1)/2 -> 52 | U49: =Coverage!I49 -> 6 | V49: =Coverage!J49 -> 0.85714286 | W49: =IFERROR(SUMPRODUCT(L49:R49,Coverage!B49:H49)/U49,0) -> 83.333333 | X49: 108_bylaws_status unavailable/unknown scored 0; No independent verification recorded
A50: Fulcrum | B50: Michigan Publishing | C50: Publishing system | D50: Implemented/available | E50: Unknown | F50: Other | H50: Ad hoc | I50: Implemented/available | J50: Implemented/available | K50: Implemented/available | L50: =Calc!B50 -> 100 | M50: =Calc!C50 -> 0 | N50: =Verification!F50 -> 0 | O50: =Calc!E50 -> 100 | P50: =Calc!F50 -> 100 | Q50: =Calc!G50 -> 100 | R50: =Calc!H50 -> 50 | S50: =AVERAGE(L50:R50) -> 64.285714 | T50: =RANK(S50,$S$2:$S$113,0)+(COUNTIF($S$2:$S$113,S50)-1)/2 -> 61 | U50: =Coverage!I50 -> 6 | V50: =Coverage!J50 -> 0.85714286 | W50: =IFERROR(SUMPRODUCT(L50:R50,Coverage!B50:H50)/U50,0) -> 75 | X50: Review 050 Other response; override available; 108_bylaws_status unavailable/unknown scored 0; No independent verification recorded
A51: Galaxy | B51: The Galaxy community | C51: Computing framework | Discovery system | D51: Implemented/available | E51: Implemented/available | F51: Multi-board governance | H51: Formal | I51: In progress | J51: Implemented/available | K51: Implemented/available | L51: =Calc!B51 -> 100 | M51: =Calc!C51 -> 100 | N51: =Verification!F51 -> 100 | O51: =Calc!E51 -> 67 | P51: =Calc!F51 -> 100 | Q51: =Calc!G51 -> 100 | R51: =Calc!H51 -> 100 | S51: =AVERAGE(L51:R51) -> 95.285714 | T51: =RANK(S51,$S$2:$S$113,0)+(COUNTIF($S$2:$S$113,S51)-1)/2 -> 12.5 | U51: =Coverage!I51 -> 7 | V51: =Coverage!J51 -> 1 | W51: =IFERROR(SUMPRODUCT(L51:R51,Coverage!B51:H51)/U51,0) -> 95.285714 | X51: No independent verification recorded
A52: GeoServer | B52: Open Source Geospatial Foundation | C52: Geospatial data tool or platform | D52: Implemented/available | E52: Implemented/available | F52: Advisory board or steering committee | H52: Formal | I52: Not planning | J52: Not planning | K52: Not planning | L52: =Calc!B52 -> 100 | M52: =Calc!C52 -> 100 | N52: =Verification!F52 -> 100 | O52: =Calc!E52 -> 0 | P52: =Calc!F52 -> 0 | Q52: =Calc!G52 -> 0 | R52: =Calc!H52 -> 100 | S52: =AVERAGE(L52:R52) -> 57.142857 | T52: =RANK(S52,$S$2:$S$113,0)+(COUNTIF($S$2:$S$113,S52)-1)/2 -> 71 | U52: =Coverage!I52 -> 7 | V52: =Coverage!J52 -> 1 | W52: =IFERROR(SUMPRODUCT(L52:R52,Coverage!B52:H52)/U52,0) -> 57.142857 | X52: No independent verification recorded
A53: Hyku | B53: Samvera | C53: Repository software | D53: Implemented/available | E53: Implemented/available | F53: Advisory board or steering committee | H53: Formal | I53: Implemented/available | J53: Considering | K53: Implemented/available | L53: =Calc!B53 -> 100 | M53: =Calc!C53 -> 100 | N53: =Verification!F53 -> 100 | O53: =Calc!E53 -> 100 | P53: =Calc!F53 -> 33 | Q53: =Calc!G53 -> 100 | R53: =Calc!H53 -> 100 | S53: =AVERAGE(L53:R53) -> 90.428571 | T53: =RANK(S53,$S$2:$S$113,0)+(COUNTIF($S$2:$S$113,S53)-1)/2 -> 23 | U53: =Coverage!I53 -> 7 | V53: =Coverage!J53 -> 1 | W53: =IFERROR(SUMPRODUCT(L53:R53,Coverage!B53:H53)/U53,0) -> 90.428571 | X53: No independent verification recorded
A54: Hyrax | B54: Samvera | C54: Repository software | D54: Implemented/available | E54: Implemented/available | F54: Advisory board or steering committee | H54: Formal | I54: In progress | J54: In progress | K54: In progress | L54: =Calc!B54 -> 100 | M54: =Calc!C54 -> 100 | N54: =Verification!F54 -> 100 | O54: =Calc!E54 -> 67 | P54: =Calc!F54 -> 67 | Q54: =Calc!G54 -> 67 | R54: =Calc!H54 -> 100 | S54: =AVERAGE(L54:R54) -> 85.857143 | T54: =RANK(S54,$S$2:$S$113,0)+(COUNTIF($S$2:$S$113,S54)-1)/2 -> 28 | U54: =Coverage!I54 -> 7 | V54: =Coverage!J54 -> 1 | W54: =IFERROR(SUMPRODUCT(L54:R54,Coverage!B54:H54)/U54,0) -> 85.857143 | X54: No independent verification recorded
A55: IIIF | B55: IIIF Consortium | C55: Standard, specification or protocol | D55: Implemented/available | E55: Implemented/available | F55: Advisory board or steering committee | H55: Formal | I55: Not applicable | J55: Implemented/available | K55: Implemented/available | L55: =Calc!B55 -> 100 | M55: =Calc!C55 -> 100 | N55: =Verification!F55 -> 100 | O55: =Calc!E55 -> 0 | P55: =Calc!F55 -> 100 | Q55: =Calc!G55 -> 100 | R55: =Calc!H55 -> 100 | S55: =AVERAGE(L55:R55) -> 85.714286 | T55: =RANK(S55,$S$2:$S$113,0)+(COUNTIF($S$2:$S$113,S55)-1)/2 -> 30 | U55: =Coverage!I55 -> 6 | V55: =Coverage!J55 -> 0.85714286 | W55: =IFERROR(SUMPRODUCT(L55:R55,Coverage!B55:H55)/U55,0) -> 100 | X55: 029_web_accessibility_status unavailable/unknown scored 0; No independent verification recorded
A56: ImpactU | B56: Universidad de Antioquia and other Colombian universities | C56: Open scholarly dataset | Research profiling system | D56: Unknown | E56: Unknown | F56: None | H56: None | I56: Unknown | J56: Unknown | K56: Unknown | L56: =Calc!B56 -> 0 | M56: =Calc!C56 -> 0 | N56: =Verification!F56 -> 0 | O56: =Calc!E56 -> 0 | P56: =Calc!F56 -> 0 | Q56: =Calc!G56 -> 0 | R56: =Calc!H56 -> 0 | S56: =AVERAGE(L56:R56) -> 0 | T56: =RANK(S56,$S$2:$S$113,0)+(COUNTIF($S$2:$S$113,S56)-1)/2 -> 111 | U56: =Coverage!I56 -> 2 | V56: =Coverage!J56 -> 0.28571429 | W56: =IFERROR(SUMPRODUCT(L56:R56,Coverage!B56:H56)/U56,0) -> 0 | X56: 024_governance_structure_status unavailable/unknown scored 0; 108_bylaws_status unavailable/unknown scored 0; 029_web_accessibility_status unavailable/unknown scored 0; 035_commitment_to_equity_status unavailable/unknown scored 0; 044_commitment_to_privacy_status unavailable/unknown scored 0; No independent verification recorded
A57: International Generic Sample Number (IGSN) | B57: International Generic Sample Number Organization e.V. | C57: Persistent identifier service | D57: Implemented/available | E57: Implemented/available | F57: Advisory board or steering committee | I57: In progress | J57: Considering | K57: Considering | L57: =Calc!B57 -> 100 | M57: =Calc!C57 -> 100 | N57: =Verification!F57 -> 100 | O57: =Calc!E57 -> 67 | P57: =Calc!F57 -> 33 | Q57: =Calc!G57 -> 33 | R57: =Calc!H57 -> 0 | S57: =AVERAGE(L57:R57) -> 61.857143 | T57: =RANK(S57,$S$2:$S$113,0)+(COUNTIF($S$2:$S$113,S57)-1)/2 -> 63.5 | U57: =Coverage!I57 -> 6 | V57: =Coverage!J57 -> 0.85714286 | W57: =IFERROR(SUMPRODUCT(L57:R57,Coverage!B57:H57)/U57,0) -> 72.166667 | X57: 048 community governance missing/unrecognized scored 0; No independent verification recorded
A58: InvenioRDM | B58: CERN | C58: Repository software | D58: Implemented/available | E58: Implemented/available | F58: Advisory board or steering committee | H58: Formal | I58: In progress | J58: Implemented/available | K58: Not applicable | L58: =Calc!B58 -> 100 | M58: =Calc!C58 -> 100 | N58: =Verification!F58 -> 100 | O58: =Calc!E58 -> 67 | P58: =Calc!F58 -> 100 | Q58: =Calc!G58 -> 0 | R58: =Calc!H58 -> 100 | S58: =AVERAGE(L58:R58) -> 81 | T58: =RANK(S58,$S$2:$S$113,0)+(COUNTIF($S$2:$S$113,S58)-1)/2 -> 33 | U58: =Coverage!I58 -> 6 | V58: =Coverage!J58 -> 0.85714286 | W58: =IFERROR(SUMPRODUCT(L58:R58,Coverage!B58:H58)/U58,0) -> 94.5 | X58: 044_commitment_to_privacy_status unavailable/unknown scored 0; No independent verification recorded
A59: iRODS | B59: Renaissance Computing Institute (RENCI) | C59: Data management planning tool or service | Digital preservation system | Discovery system | D59: Implemented/available | E59: Implemented/available | F59: Advisory board or steering committee | G59: In addition to the Executive Committee (which makes decisions on budgets and by laws), there is an Advisory Board that is advisory/strategic: https://irods.org/advisory-board/ | H59: Ad hoc | I59: Not planning | J59: Not planning | K59: Not planning | L59: =Calc!B59 -> 100 | M59: =Calc!C59 -> 100 | N59: =Verification!F59 -> 100 | O59: =Calc!E59 -> 0 | P59: =Calc!F59 -> 0 | Q59: =Calc!G59 -> 0 | R59: =Calc!H59 -> 50 | S59: =AVERAGE(L59:R59) -> 50 | T59: =RANK(S59,$S$2:$S$113,0)+(COUNTIF($S$2:$S$113,S59)-1)/2 -> 79 | U59: =Coverage!I59 -> 7 | V59: =Coverage!J59 -> 1 | W59: =IFERROR(SUMPRODUCT(L59:R59,Coverage!B59:H59)/U59,0) -> 50 | X59: No independent verification recorded
A60: Islandora | B60: Islandora Foundation | C60: Authoring tool | Digital asset management system | D60: Implemented/available | E60: Implemented/available | F60: Advisory board or steering committee | H60: None | I60: Implemented/available | J60: Implemented/available | K60: Unknown | L60: =Calc!B60 -> 100 | M60: =Calc!C60 -> 100 | N60: =Verification!F60 -> 100 | O60: =Calc!E60 -> 100 | P60: =Calc!F60 -> 100 | Q60: =Calc!G60 -> 0 | R60: =Calc!H60 -> 0 | S60: =AVERAGE(L60:R60) -> 71.428571 | T60: =RANK(S60,$S$2:$S$113,0)+(COUNTIF($S$2:$S$113,S60)-1)/2 -> 52 | U60: =Coverage!I60 -> 6 | V60: =Coverage!J60 -> 0.85714286 | W60: =IFERROR(SUMPRODUCT(L60:R60,Coverage!B60:H60)/U60,0) -> 83.333333 | X60: 044_commitment_to_privacy_status unavailable/unknown scored 0; No independent verification recorded
A61: Janeway | B61: Open Library of Humanities | C61: Publishing system | D61: In progress | E61: Unknown | F61: Advisory board or steering committee | H61: Ad hoc | I61: Implemented/available | J61: Implemented/available | K61: Implemented/available | L61: =Calc!B61 -> 67 | M61: =Calc!C61 -> 0 | N61: =Verification!F61 -> 100 | O61: =Calc!E61 -> 100 | P61: =Calc!F61 -> 100 | Q61: =Calc!G61 -> 100 | R61: =Calc!H61 -> 50 | S61: =AVERAGE(L61:R61) -> 73.857143 | T61: =RANK(S61,$S$2:$S$113,0)+(COUNTIF($S$2:$S$113,S61)-1)/2 -> 46.5 | U61: =Coverage!I61 -> 6 | V61: =Coverage!J61 -> 0.85714286 | W61: =IFERROR(SUMPRODUCT(L61:R61,Coverage!B61:H61)/U61,0) -> 86.166667 | X61: 108_bylaws_status unavailable/unknown scored 0; No independent verification recorded
A62: JHOVE | B62: Open Preservation Foundation | C62: Computing library | Digital preservation tool | D62: Implemented/available | E62: Not planning | F62: Advisory board or steering committee | H62: Ad hoc | I62: In progress | J62: In progress | K62: Implemented/available | L62: =Calc!B62 -> 100 | M62: =Calc!C62 -> 0 | N62: =Verification!F62 -> 100 | O62: =Calc!E62 -> 67 | P62: =Calc!F62 -> 67 | Q62: =Calc!G62 -> 100 | R62: =Calc!H62 -> 50 | S62: =AVERAGE(L62:R62) -> 69.142857 | T62: =RANK(S62,$S$2:$S$113,0)+(COUNTIF($S$2:$S$113,S62)-1)/2 -> 58 | U62: =Coverage!I62 -> 7 | V62: =Coverage!J62 -> 1 | W62: =IFERROR(SUMPRODUCT(L62:R62,Coverage!B62:H62)/U62,0) -> 69.142857 | X62: No independent verification recorded
A63: LA Referencia | B63: LA Referencia | C63: Discovery system | D63: Implemented/available | E63: Unknown | F63: Multi-board governance | H63: Formal | I63: Considering | J63: Considering | K63: In progress | L63: =Calc!B63 -> 100 | M63: =Calc!C63 -> 0 | N63: =Verification!F63 -> 100 | O63: =Calc!E63 -> 33 | P63: =Calc!F63 -> 33 | Q63: =Calc!G63 -> 67 | R63: =Calc!H63 -> 100 | S63: =AVERAGE(L63:R63) -> 61.857143 | T63: =RANK(S63,$S$2:$S$113,0)+(COUNTIF($S$2:$S$113,S63)-1)/2 -> 63.5 | U63: =Coverage!I63 -> 6 | V63: =Coverage!J63 -> 0.85714286 | W63: =IFERROR(SUMPRODUCT(L63:R63,Coverage!B63:H63)/U63,0) -> 72.166667 | X63: 108_bylaws_status unavailable/unknown scored 0; No independent verification recorded
A64: Manifold | B64: Manifold Digital Services | C64: Publishing system | D64: Unknown | E64: Unknown | F64: Advisory board or steering committee | H64: None | I64: Implemented/available | J64: In progress | K64: Unknown | L64: =Calc!B64 -> 0 | M64: =Calc!C64 -> 0 | N64: =Verification!F64 -> 100 | O64: =Calc!E64 -> 100 | P64: =Calc!F64 -> 67 | Q64: =Calc!G64 -> 0 | R64: =Calc!H64 -> 0 | S64: =AVERAGE(L64:R64) -> 38.142857 | T64: =RANK(S64,$S$2:$S$113,0)+(COUNTIF($S$2:$S$113,S64)-1)/2 -> 91 | U64: =Coverage!I64 -> 4 | V64: =Coverage!J64 -> 0.57142857 | W64: =IFERROR(SUMPRODUCT(L64:R64,Coverage!B64:H64)/U64,0) -> 66.75 | X64: 024_governance_structure_status unavailable/unknown scored 0; 108_bylaws_status unavailable/unknown scored 0; 044_commitment_to_privacy_status unavailable/unknown scored 0; No independent verification recorded
A65: medRxiv | B65: Cold Spring Harbor Laboratory | C65: Repository service | D65: In progress | E65: Unknown | F65: Advisory board or steering committee | H65: Ad hoc | I65: Considering | J65: In progress | K65: Implemented/available | L65: =Calc!B65 -> 67 | M65: =Calc!C65 -> 0 | N65: =Verification!F65 -> 100 | O65: =Calc!E65 -> 33 | P65: =Calc!F65 -> 67 | Q65: =Calc!G65 -> 100 | R65: =Calc!H65 -> 50 | S65: =AVERAGE(L65:R65) -> 59.571429 | T65: =RANK(S65,$S$2:$S$113,0)+(COUNTIF($S$2:$S$113,S65)-1)/2 -> 67 | U65: =Coverage!I65 -> 6 | V65: =Coverage!J65 -> 0.85714286 | W65: =IFERROR(SUMPRODUCT(L65:R65,Coverage!B65:H65)/U65,0) -> 69.5 | X65: 108_bylaws_status unavailable/unknown scored 0; No independent verification recorded
A66: Metadata Encoding and Transmission Standard (METS) | B66: METS Editorial Board | C66: Standard, specification or protocol | D66: Implemented/available | E66: Implemented/available | F66: Advisory board or steering committee | H66: Ad hoc | I66: Not planning | J66: Not planning | K66: Not planning | L66: =Calc!B66 -> 100 | M66: =Calc!C66 -> 100 | N66: =Verification!F66 -> 100 | O66: =Calc!E66 -> 0 | P66: =Calc!F66 -> 0 | Q66: =Calc!G66 -> 0 | R66: =Calc!H66 -> 50 | S66: =AVERAGE(L66:R66) -> 50 | T66: =RANK(S66,$S$2:$S$113,0)+(COUNTIF($S$2:$S$113,S66)-1)/2 -> 79 | U66: =Coverage!I66 -> 7 | V66: =Coverage!J66 -> 1 | W66: =IFERROR(SUMPRODUCT(L66:R66,Coverage!B66:H66)/U66,0) -> 50 | X66: No independent verification recorded
A67: Mirador | B67: Project Mirador | C67: Annotations system | Media viewer/player | D67: Considering | E67: Unknown | F67: None | H67: Ad hoc | I67: Implemented/available | J67: Implemented/available | K67: Unknown | L67: =Calc!B67 -> 33 | M67: =Calc!C67 -> 0 | N67: =Verification!F67 -> 0 | O67: =Calc!E67 -> 100 | P67: =Calc!F67 -> 100 | Q67: =Calc!G67 -> 0 | R67: =Calc!H67 -> 50 | S67: =AVERAGE(L67:R67) -> 40.428571 | T67: =RANK(S67,$S$2:$S$113,0)+(COUNTIF($S$2:$S$113,S67)-1)/2 -> 89 | U67: =Coverage!I67 -> 5 | V67: =Coverage!J67 -> 0.71428571 | W67: =IFERROR(SUMPRODUCT(L67:R67,Coverage!B67:H67)/U67,0) -> 56.6 | X67: 108_bylaws_status unavailable/unknown scored 0; 044_commitment_to_privacy_status unavailable/unknown scored 0; No independent verification recorded
A68: Mukurtu CMS | B68: Center for Digital Scholarship and Curation | C68: Archive information management system | Digital asset management system | D68: In progress | E68: Unknown | F68: Advisory board or steering committee | H68: Ad hoc | I68: In progress | J68: Implemented/available | K68: Implemented/available | L68: =Calc!B68 -> 67 | M68: =Calc!C68 -> 0 | N68: =Verification!F68 -> 100 | O68: =Calc!E68 -> 67 | P68: =Calc!F68 -> 100 | Q68: =Calc!G68 -> 100 | R68: =Calc!H68 -> 50 | S68: =AVERAGE(L68:R68) -> 69.142857 | T68: =RANK(S68,$S$2:$S$113,0)+(COUNTIF($S$2:$S$113,S68)-1)/2 -> 58 | U68: =Coverage!I68 -> 6 | V68: =Coverage!J68 -> 0.85714286 | W68: =IFERROR(SUMPRODUCT(L68:R68,Coverage!B68:H68)/U68,0) -> 80.666667 | X68: 108_bylaws_status unavailable/unknown scored 0; No independent verification recorded
A69: MyCoRe | B69: MyCoRe Community | C69: Digital asset management system | Digital library, collection or exhibit platform | Repository software | D69: Not planning | E69: Not planning | F69: None | H69: Ad hoc | I69: Implemented/available | J69: Unknown | K69: Implemented/available | L69: =Calc!B69 -> 0 | M69: =Calc!C69 -> 0 | N69: =Verification!F69 -> 0 | O69: =Calc!E69 -> 100 | P69: =Calc!F69 -> 0 | Q69: =Calc!G69 -> 100 | R69: =Calc!H69 -> 50 | S69: =AVERAGE(L69:R69) -> 35.714286 | T69: =RANK(S69,$S$2:$S$113,0)+(COUNTIF($S$2:$S$113,S69)-1)/2 -> 95.5 | U69: =Coverage!I69 -> 6 | V69: =Coverage!J69 -> 0.85714286 | W69: =IFERROR(SUMPRODUCT(L69:R69,Coverage!B69:H69)/U69,0) -> 41.666667 | X69: 035_commitment_to_equity_status unavailable/unknown scored 0; No independent verification recorded
A70: NumPy | B70: NumPy Community | C70: Computing library | Standard, specification or protocol | D70: Implemented/available | E70: Implemented/available | F70: Advisory board or steering committee | H70: Formal | I70: In progress | J70: In progress | K70: Not planning | L70: =Calc!B70 -> 100 | M70: =Calc!C70 -> 100 | N70: =Verification!F70 -> 100 | O70: =Calc!E70 -> 67 | P70: =Calc!F70 -> 67 | Q70: =Calc!G70 -> 0 | R70: =Calc!H70 -> 100 | S70: =AVERAGE(L70:R70) -> 76.285714 | T70: =RANK(S70,$S$2:$S$113,0)+(COUNTIF($S$2:$S$113,S70)-1)/2 -> 42 | U70: =Coverage!I70 -> 7 | V70: =Coverage!J70 -> 1 | W70: =IFERROR(SUMPRODUCT(L70:R70,Coverage!B70:H70)/U70,0) -> 76.285714 | X70: No independent verification recorded
A71: OA.Report | B71: OA.Works | C71: Open access or subscription management tool | Research profiling system | D71: Implemented/available | E71: Implemented/available | F71: Advisory board or steering committee | H71: Formal | I71: Implemented/available | J71: Considering | K71: Implemented/available | L71: =Calc!B71 -> 100 | M71: =Calc!C71 -> 100 | N71: =Verification!F71 -> 100 | O71: =Calc!E71 -> 100 | P71: =Calc!F71 -> 33 | Q71: =Calc!G71 -> 100 | R71: =Calc!H71 -> 100 | S71: =AVERAGE(L71:R71) -> 90.428571 | T71: =RANK(S71,$S$2:$S$113,0)+(COUNTIF($S$2:$S$113,S71)-1)/2 -> 23 | U71: =Coverage!I71 -> 7 | V71: =Coverage!J71 -> 1 | W71: =IFERROR(SUMPRODUCT(L71:R71,Coverage!B71:H71)/U71,0) -> 90.428571 | X71: No independent verification recorded
A72: OA Switchboard | B72: Stichting OA Switchboard | C72: Open access or subscription management tool | D72: Implemented/available | E72: Implemented/available | H72: Formal | I72: Unknown | J72: Implemented/available | K72: Implemented/available | L72: =Calc!B72 -> 100 | M72: =Calc!C72 -> 100 | N72: =Verification!F72 -> 0 | O72: =Calc!E72 -> 0 | P72: =Calc!F72 -> 100 | Q72: =Calc!G72 -> 100 | R72: =Calc!H72 -> 100 | S72: =AVERAGE(L72:R72) -> 71.428571 | T72: =RANK(S72,$S$2:$S$113,0)+(COUNTIF($S$2:$S$113,S72)-1)/2 -> 52 | U72: =Coverage!I72 -> 5 | V72: =Coverage!J72 -> 0.71428571 | W72: =IFERROR(SUMPRODUCT(L72:R72,Coverage!B72:H72)/U72,0) -> 100 | X72: 029_web_accessibility_status unavailable/unknown scored 0; No independent verification recorded
A73: Omeka | B73: Digital Scholar | C73: Digital library, collection or exhibit platform | D73: Implemented/available | E73: Implemented/available | F73: Advisory board or steering committee | H73: Ad hoc | I73: Implemented/available | J73: In progress | K73: Implemented/available | L73: =Calc!B73 -> 100 | M73: =Calc!C73 -> 100 | N73: =Verification!F73 -> 100 | O73: =Calc!E73 -> 100 | P73: =Calc!F73 -> 67 | Q73: =Calc!G73 -> 100 | R73: =Calc!H73 -> 50 | S73: =AVERAGE(L73:R73) -> 88.142857 | T73: =RANK(S73,$S$2:$S$113,0)+(COUNTIF($S$2:$S$113,S73)-1)/2 -> 27 | U73: =Coverage!I73 -> 7 | V73: =Coverage!J73 -> 1 | W73: =IFERROR(SUMPRODUCT(L73:R73,Coverage!B73:H73)/U73,0) -> 88.142857 | X73: No independent verification recorded
A74: OpenAIRE Graph | B74: OpenAIRE | C74: Discovery system | Open scholarly dataset | D74: Implemented/available | E74: Implemented/available | F74: Advisory board or steering committee | H74: Formal | I74: Considering | J74: Implemented/available | K74: Implemented/available | L74: =Calc!B74 -> 100 | M74: =Calc!C74 -> 100 | N74: =Verification!F74 -> 100 | O74: =Calc!E74 -> 33 | P74: =Calc!F74 -> 100 | Q74: =Calc!G74 -> 100 | R74: =Calc!H74 -> 100 | S74: =AVERAGE(L74:R74) -> 90.428571 | T74: =RANK(S74,$S$2:$S$113,0)+(COUNTIF($S$2:$S$113,S74)-1)/2 -> 23 | U74: =Coverage!I74 -> 7 | V74: =Coverage!J74 -> 1 | W74: =IFERROR(SUMPRODUCT(L74:R74,Coverage!B74:H74)/U74,0) -> 90.428571 | X74: No independent verification recorded
A75: OpenAlex | B75: OurResearch | C75: Open scholarly dataset | D75: Implemented/available | E75: Unknown | F75: Advisory board or steering committee | H75: Formal | I75: Implemented/available | J75: Considering | K75: Implemented/available | L75: =Calc!B75 -> 100 | M75: =Calc!C75 -> 0 | N75: =Verification!F75 -> 100 | O75: =Calc!E75 -> 100 | P75: =Calc!F75 -> 33 | Q75: =Calc!G75 -> 100 | R75: =Calc!H75 -> 100 | S75: =AVERAGE(L75:R75) -> 76.142857 | T75: =RANK(S75,$S$2:$S$113,0)+(COUNTIF($S$2:$S$113,S75)-1)/2 -> 44 | U75: =Coverage!I75 -> 6 | V75: =Coverage!J75 -> 0.85714286 | W75: =IFERROR(SUMPRODUCT(L75:R75,Coverage!B75:H75)/U75,0) -> 88.833333 | X75: 108_bylaws_status unavailable/unknown scored 0; No independent verification recorded
A76: OpenAPC | B76: Bielefeld University | C76: Open scholarly dataset | D76: Not planning | E76: Not planning | F76: None | H76: None | I76: Not planning | J76: Implemented/available | K76: Not planning | L76: =Calc!B76 -> 0 | M76: =Calc!C76 -> 0 | N76: =Verification!F76 -> 0 | O76: =Calc!E76 -> 0 | P76: =Calc!F76 -> 100 | Q76: =Calc!G76 -> 0 | R76: =Calc!H76 -> 0 | S76: =AVERAGE(L76:R76) -> 14.285714 | T76: =RANK(S76,$S$2:$S$113,0)+(COUNTIF($S$2:$S$113,S76)-1)/2 -> 108 | U76: =Coverage!I76 -> 7 | V76: =Coverage!J76 -> 1 | W76: =IFERROR(SUMPRODUCT(L76:R76,Coverage!B76:H76)/U76,0) -> 14.285714 | X76: No independent verification recorded
A77: OpenCitations | B77: Research Centre for Open Scholarly Metadata, University of Bologna | C77: Open scholarly dataset | D77: Implemented/available | E77: Implemented/available | F77: Advisory board or steering committee | H77: Formal | I77: Considering | J77: Considering | K77: Implemented/available | L77: =Calc!B77 -> 100 | M77: =Calc!C77 -> 100 | N77: =Verification!F77 -> 100 | O77: =Calc!E77 -> 33 | P77: =Calc!F77 -> 33 | Q77: =Calc!G77 -> 100 | R77: =Calc!H77 -> 100 | S77: =AVERAGE(L77:R77) -> 80.857143 | T77: =RANK(S77,$S$2:$S$113,0)+(COUNTIF($S$2:$S$113,S77)-1)/2 -> 37 | U77: =Coverage!I77 -> 7 | V77: =Coverage!J77 -> 1 | W77: =IFERROR(SUMPRODUCT(L77:R77,Coverage!B77:H77)/U77,0) -> 80.857143 | X77: No independent verification recorded
A78: openCost | B78: openCost | C78: Open scholarly dataset | Standard, specification or protocol | D78: Not planning | E78: Not planning | F78: None | I78: Not planning | J78: Not planning | K78: Not planning | L78: =Calc!B78 -> 0 | M78: =Calc!C78 -> 0 | N78: =Verification!F78 -> 0 | O78: =Calc!E78 -> 0 | P78: =Calc!F78 -> 0 | Q78: =Calc!G78 -> 0 | R78: =Calc!H78 -> 0 | S78: =AVERAGE(L78:R78) -> 0 | T78: =RANK(S78,$S$2:$S$113,0)+(COUNTIF($S$2:$S$113,S78)-1)/2 -> 111 | U78: =Coverage!I78 -> 6 | V78: =Coverage!J78 -> 0.85714286 | W78: =IFERROR(SUMPRODUCT(L78:R78,Coverage!B78:H78)/U78,0) -> 0 | X78: 048 community governance missing/unrecognized scored 0; No independent verification recorded
A79: Open Data Editor | B79: Open Knowledge Foundation | C79: Data collection or management tool | D79: Implemented/available | E79: Implemented/available | F79: Advisory board or steering committee | H79: Formal | I79: Considering | J79: Considering | K79: Implemented/available | L79: =Calc!B79 -> 100 | M79: =Calc!C79 -> 100 | N79: =Verification!F79 -> 100 | O79: =Calc!E79 -> 33 | P79: =Calc!F79 -> 33 | Q79: =Calc!G79 -> 100 | R79: =Calc!H79 -> 100 | S79: =AVERAGE(L79:R79) -> 80.857143 | T79: =RANK(S79,$S$2:$S$113,0)+(COUNTIF($S$2:$S$113,S79)-1)/2 -> 37 | U79: =Coverage!I79 -> 7 | V79: =Coverage!J79 -> 1 | W79: =IFERROR(SUMPRODUCT(L79:R79,Coverage!B79:H79)/U79,0) -> 80.857143 | X79: No independent verification recorded
A80: OpenEdition | B80: OpenEdition Center, Aix-Marseille University, the EHESS and Avignon University | C80: Discovery system | D80: Implemented/available | E80: Implemented/available | F80: Multi-board governance | H80: Formal | I80: Considering | J80: Considering | K80: Implemented/available | L80: =Calc!B80 -> 100 | M80: =Calc!C80 -> 100 | N80: =Verification!F80 -> 100 | O80: =Calc!E80 -> 33 | P80: =Calc!F80 -> 33 | Q80: =Calc!G80 -> 100 | R80: =Calc!H80 -> 100 | S80: =AVERAGE(L80:R80) -> 80.857143 | T80: =RANK(S80,$S$2:$S$113,0)+(COUNTIF($S$2:$S$113,S80)-1)/2 -> 37 | U80: =Coverage!I80 -> 7 | V80: =Coverage!J80 -> 1 | W80: =IFERROR(SUMPRODUCT(L80:R80,Coverage!B80:H80)/U80,0) -> 80.857143 | X80: No independent verification recorded
A81: Open Journal Systems (OJS) | B81: Public Knowledge Project (PKP) | C81: Publishing system | D81: Implemented/available | E81: Implemented/available | F81: Multi-board governance | H81: Formal | I81: Implemented/available | J81: In progress | K81: Implemented/available | L81: =Calc!B81 -> 100 | M81: =Calc!C81 -> 100 | N81: =Verification!F81 -> 100 | O81: =Calc!E81 -> 100 | P81: =Calc!F81 -> 67 | Q81: =Calc!G81 -> 100 | R81: =Calc!H81 -> 100 | S81: =AVERAGE(L81:R81) -> 95.285714 | T81: =RANK(S81,$S$2:$S$113,0)+(COUNTIF($S$2:$S$113,S81)-1)/2 -> 12.5 | U81: =Coverage!I81 -> 7 | V81: =Coverage!J81 -> 1 | W81: =IFERROR(SUMPRODUCT(L81:R81,Coverage!B81:H81)/U81,0) -> 95.285714 | X81: No independent verification recorded
A82: Open Monograph Press (OMP) | B82: Public Knowledge Project (PKP) | C82: Publishing system | D82: Implemented/available | E82: Implemented/available | F82: Multi-board governance | H82: Formal | I82: Implemented/available | J82: In progress | K82: Implemented/available | L82: =Calc!B82 -> 100 | M82: =Calc!C82 -> 100 | N82: =Verification!F82 -> 100 | O82: =Calc!E82 -> 100 | P82: =Calc!F82 -> 67 | Q82: =Calc!G82 -> 100 | R82: =Calc!H82 -> 100 | S82: =AVERAGE(L82:R82) -> 95.285714 | T82: =RANK(S82,$S$2:$S$113,0)+(COUNTIF($S$2:$S$113,S82)-1)/2 -> 12.5 | U82: =Coverage!I82 -> 7 | V82: =Coverage!J82 -> 1 | W82: =IFERROR(SUMPRODUCT(L82:R82,Coverage!B82:H82)/U82,0) -> 95.285714 | X82: No independent verification recorded
A83: Open Preprint Systems (OPS) | B83: Public Knowledge Project (PKP) | C83: Publishing system | D83: Implemented/available | E83: Implemented/available | F83: Multi-board governance | H83: Formal | I83: Implemented/available | J83: In progress | K83: Implemented/available | L83: =Calc!B83 -> 100 | M83: =Calc!C83 -> 100 | N83: =Verification!F83 -> 100 | O83: =Calc!E83 -> 100 | P83: =Calc!F83 -> 67 | Q83: =Calc!G83 -> 100 | R83: =Calc!H83 -> 100 | S83: =AVERAGE(L83:R83) -> 95.285714 | T83: =RANK(S83,$S$2:$S$113,0)+(COUNTIF($S$2:$S$113,S83)-1)/2 -> 12.5 | U83: =Coverage!I83 -> 7 | V83: =Coverage!J83 -> 1 | W83: =IFERROR(SUMPRODUCT(L83:R83,Coverage!B83:H83)/U83,0) -> 95.285714 | X83: No independent verification recorded
A84: Openverse | B84: WordPress Foundation | C84: Discovery system | D84: In progress | E84: Considering | F84: None | H84: Ad hoc | I84: Implemented/available | J84: Implemented/available | K84: Implemented/available | L84: =Calc!B84 -> 67 | M84: =Calc!C84 -> 33 | N84: =Verification!F84 -> 0 | O84: =Calc!E84 -> 100 | P84: =Calc!F84 -> 100 | Q84: =Calc!G84 -> 100 | R84: =Calc!H84 -> 50 | S84: =AVERAGE(L84:R84) -> 64.285714 | T84: =RANK(S84,$S$2:$S$113,0)+(COUNTIF($S$2:$S$113,S84)-1)/2 -> 61 | U84: =Coverage!I84 -> 7 | V84: =Coverage!J84 -> 1 | W84: =IFERROR(SUMPRODUCT(L84:R84,Coverage!B84:H84)/U84,0) -> 64.285714 | X84: No independent verification recorded
A85: O Portal Brasileiro de Publicações e Dados Científicos em Acesso Aberto (The Brazilian Open Access Publications and Scientific Data Portal) (Oasisbr) | B85: Instituto Brasileiro de Informação em Ciência e Tecnologia (Brazilian Institute of Information in Science and Technology) (Ibict) | C85: Repository service | D85: Implemented/available | E85: Unknown | F85: Other | H85: None | I85: Considering | J85: Considering | K85: Considering | L85: =Calc!B85 -> 100 | M85: =Calc!C85 -> 0 | N85: =Verification!F85 -> 0 | O85: =Calc!E85 -> 33 | P85: =Calc!F85 -> 33 | Q85: =Calc!G85 -> 33 | R85: =Calc!H85 -> 0 | S85: =AVERAGE(L85:R85) -> 28.428571 | T85: =RANK(S85,$S$2:$S$113,0)+(COUNTIF($S$2:$S$113,S85)-1)/2 -> 101 | U85: =Coverage!I85 -> 6 | V85: =Coverage!J85 -> 0.85714286 | W85: =IFERROR(SUMPRODUCT(L85:R85,Coverage!B85:H85)/U85,0) -> 33.166667 | X85: Review 050 Other response; override available; 108_bylaws_status unavailable/unknown scored 0; No independent verification recorded
A86: OSF (Open Science Framework) | B86: Center for Open Science, Inc. | C86: Repository service | Repository software | D86: Implemented/available | E86: Implemented/available | F86: Advisory board or steering committee | H86: Formal | I86: Implemented/available | J86: Implemented/available | K86: Implemented/available | L86: =Calc!B86 -> 100 | M86: =Calc!C86 -> 100 | N86: =Verification!F86 -> 100 | O86: =Calc!E86 -> 100 | P86: =Calc!F86 -> 100 | Q86: =Calc!G86 -> 100 | R86: =Calc!H86 -> 100 | S86: =AVERAGE(L86:R86) -> 100 | T86: =RANK(S86,$S$2:$S$113,0)+(COUNTIF($S$2:$S$113,S86)-1)/2 -> 4 | U86: =Coverage!I86 -> 7 | V86: =Coverage!J86 -> 1 | W86: =IFERROR(SUMPRODUCT(L86:R86,Coverage!B86:H86)/U86,0) -> 100 | X86: No independent verification recorded
A87: Oxford Common File Layout | B87: Oxford Common File Layout (OCFL) | C87: Standard, specification or protocol | D87: Considering | E87: Unknown | F87: Advisory board or steering committee | H87: None | I87: Unknown | J87: Considering | K87: Not applicable | L87: =Calc!B87 -> 33 | M87: =Calc!C87 -> 0 | N87: =Verification!F87 -> 100 | O87: =Calc!E87 -> 0 | P87: =Calc!F87 -> 33 | Q87: =Calc!G87 -> 0 | R87: =Calc!H87 -> 0 | S87: =AVERAGE(L87:R87) -> 23.714286 | T87: =RANK(S87,$S$2:$S$113,0)+(COUNTIF($S$2:$S$113,S87)-1)/2 -> 103 | U87: =Coverage!I87 -> 4 | V87: =Coverage!J87 -> 0.57142857 | W87: =IFERROR(SUMPRODUCT(L87:R87,Coverage!B87:H87)/U87,0) -> 41.5 | X87: 108_bylaws_status unavailable/unknown scored 0; 029_web_accessibility_status unavailable/unknown scored 0; 044_commitment_to_privacy_status unavailable/unknown scored 0; No independent verification recorded
A88: Peer Community In | B88: PCI, Peer Community In | C88: Peer review system | D88: Implemented/available | E88: Unknown | F88: Advisory board or steering committee | H88: Formal | I88: Not planning | J88: Implemented/available | K88: Not applicable | L88: =Calc!B88 -> 100 | M88: =Calc!C88 -> 0 | N88: =Verification!F88 -> 100 | O88: =Calc!E88 -> 0 | P88: =Calc!F88 -> 100 | Q88: =Calc!G88 -> 0 | R88: =Calc!H88 -> 100 | S88: =AVERAGE(L88:R88) -> 57.142857 | T88: =RANK(S88,$S$2:$S$113,0)+(COUNTIF($S$2:$S$113,S88)-1)/2 -> 71 | U88: =Coverage!I88 -> 5 | V88: =Coverage!J88 -> 0.71428571 | W88: =IFERROR(SUMPRODUCT(L88:R88,Coverage!B88:H88)/U88,0) -> 80 | X88: 108_bylaws_status unavailable/unknown scored 0; 044_commitment_to_privacy_status unavailable/unknown scored 0; No independent verification recorded
A89: PKP Preservation Network | B89: Public Knowledge Project (PKP) | C89: Digital preservation service | D89: Implemented/available | E89: Implemented/available | F89: Multi-board governance | H89: Formal | I89: Implemented/available | J89: In progress | K89: Implemented/available | L89: =Calc!B89 -> 100 | M89: =Calc!C89 -> 100 | N89: =Verification!F89 -> 100 | O89: =Calc!E89 -> 100 | P89: =Calc!F89 -> 67 | Q89: =Calc!G89 -> 100 | R89: =Calc!H89 -> 100 | S89: =AVERAGE(L89:R89) -> 95.285714 | T89: =RANK(S89,$S$2:$S$113,0)+(COUNTIF($S$2:$S$113,S89)-1)/2 -> 12.5 | U89: =Coverage!I89 -> 7 | V89: =Coverage!J89 -> 1 | W89: =IFERROR(SUMPRODUCT(L89:R89,Coverage!B89:H89)/U89,0) -> 95.285714 | X89: No independent verification recorded
A90: PREreview | B90: Code for Science and Society | C90: Discovery system | Peer review system | D90: Implemented/available | E90: Unknown | F90: Advisory board or steering committee | H90: Ad hoc | I90: In progress | J90: Implemented/available | K90: Implemented/available | L90: =Calc!B90 -> 100 | M90: =Calc!C90 -> 0 | N90: =Verification!F90 -> 100 | O90: =Calc!E90 -> 67 | P90: =Calc!F90 -> 100 | Q90: =Calc!G90 -> 100 | R90: =Calc!H90 -> 50 | S90: =AVERAGE(L90:R90) -> 73.857143 | T90: =RANK(S90,$S$2:$S$113,0)+(COUNTIF($S$2:$S$113,S90)-1)/2 -> 46.5 | U90: =Coverage!I90 -> 6 | V90: =Coverage!J90 -> 0.85714286 | W90: =IFERROR(SUMPRODUCT(L90:R90,Coverage!B90:H90)/U90,0) -> 86.166667 | X90: 108_bylaws_status unavailable/unknown scored 0; No independent verification recorded
... A92: Public Access Submission System | B92: Eclipse Foundation | C92: Submissions system | D92: Implemented/available | E92: Implemented/available | F92: Other | H92: Formal | I92: Considering | J92: Implemented/available | K92: Implemented/available | L92: =Calc!B92 -> 100 | M92: =Calc!C92 -> 100 | N92: =Verification!F92 -> 0 | O92: =Calc!E92 -> 33 | P92: =Calc!F92 -> 100 | Q92: =Calc!G92 -> 100 | R92: =Calc!H92 -> 100 | S92: =AVERAGE(L92:R92) -> 76.142857 | T92: =RANK(S92,$S$2:$S$113,0)+(COUNTIF($S$2:$S$113,S92)-1)/2 -> 44 | U92: =Coverage!I92 -> 7 | V92: =Coverage!J92 -> 1 | W92: =IFERROR(SUMPRODUCT(L92:R92,Coverage!B92:H92)/U92,0) -> 76.142857 | X92: Review 050 Other response; override available; No independent verification recorded
A93: Public Utility Data Liberation (PUDL) | B93: Catalyst Cooperative | C93: Open scholarly dataset | Web archiving system | D93: In progress | E93: Implemented/available | F93: Other | G93: Board of directors | H93: Ad hoc | I93: Not planning | J93: Not planning | K93: In progress | L93: =Calc!B93 -> 67 | M93: =Calc!C93 -> 100 | N93: =Verification!F93 -> 100 | O93: =Calc!E93 -> 0 | P93: =Calc!F93 -> 0 | Q93: =Calc!G93 -> 67 | R93: =Calc!H93 -> 50 | S93: =AVERAGE(L93:R93) -> 54.857143 | T93: =RANK(S93,$S$2:$S$113,0)+(COUNTIF($S$2:$S$113,S93)-1)/2 -> 74.5 | U93: =Coverage!I93 -> 7 | V93: =Coverage!J93 -> 1 | W93: =IFERROR(SUMPRODUCT(L93:R93,Coverage!B93:H93)/U93,0) -> 54.857143 | X93: Review 050 Other response; override available; No independent verification recorded
A94: PubPub | B94: Knowledge Futures | C94: Publishing system | D94: Implemented/available | E94: Unknown | F94: Advisory board or steering committee | H94: Ad hoc | I94: Implemented/available | J94: Implemented/available | K94: Implemented/available | L94: =Calc!B94 -> 100 | M94: =Calc!C94 -> 0 | N94: =Verification!F94 -> 100 | O94: =Calc!E94 -> 100 | P94: =Calc!F94 -> 100 | Q94: =Calc!G94 -> 100 | R94: =Calc!H94 -> 50 | S94: =AVERAGE(L94:R94) -> 78.571429 | T94: =RANK(S94,$S$2:$S$113,0)+(COUNTIF($S$2:$S$113,S94)-1)/2 -> 40.5 | U94: =Coverage!I94 -> 6 | V94: =Coverage!J94 -> 0.85714286 | W94: =IFERROR(SUMPRODUCT(L94:R94,Coverage!B94:H94)/U94,0) -> 91.666667 | X94: 108_bylaws_status unavailable/unknown scored 0; No independent verification recorded
A95: Pundit | B95: Net7 Srl | C95: Annotations system | D95: Considering | E95: Not planning | F95: None | H95: None | I95: Not planning | J95: Considering | K95: Implemented/available | L95: =Calc!B95 -> 33 | M95: =Calc!C95 -> 0 | N95: =Verification!F95 -> 0 | O95: =Calc!E95 -> 0 | P95: =Calc!F95 -> 33 | Q95: =Calc!G95 -> 100 | R95: =Calc!H95 -> 0 | S95: =AVERAGE(L95:R95) -> 23.714286 | T95: =RANK(S95,$S$2:$S$113,0)+(COUNTIF($S$2:$S$113,S95)-1)/2 -> 103 | U95: =Coverage!I95 -> 7 | V95: =Coverage!J95 -> 1 | W95: =IFERROR(SUMPRODUCT(L95:R95,Coverage!B95:H95)/U95,0) -> 23.714286 | X95: No independent verification recorded
A96: pyOpenSci | B96: Community Initiatives | C96: Research software community | D96: Implemented/available | E96: Unknown | F96: Advisory board or steering committee | H96: Ad hoc | I96: In progress | J96: In progress | K96: Unknown | L96: =Calc!B96 -> 100 | M96: =Calc!C96 -> 0 | N96: =Verification!F96 -> 100 | O96: =Calc!E96 -> 67 | P96: =Calc!F96 -> 67 | Q96: =Calc!G96 -> 0 | R96: =Calc!H96 -> 50 | S96: =AVERAGE(L96:R96) -> 54.857143 | T96: =RANK(S96,$S$2:$S$113,0)+(COUNTIF($S$2:$S$113,S96)-1)/2 -> 74.5 | U96: =Coverage!I96 -> 5 | V96: =Coverage!J96 -> 0.71428571 | W96: =IFERROR(SUMPRODUCT(L96:R96,Coverage!B96:H96)/U96,0) -> 76.8 | X96: 108_bylaws_status unavailable/unknown scored 0; 044_commitment_to_privacy_status unavailable/unknown scored 0; No independent verification recorded
A97: Renku | B97: Swiss Data Science Center | C97: Data management planning tool or service | Discovery system | Research software community | D97: Considering | E97: Not planning | F97: None | H97: None | I97: Unknown | J97: Considering | K97: Implemented/available | L97: =Calc!B97 -> 33 | M97: =Calc!C97 -> 0 | N97: =Verification!F97 -> 0 | O97: =Calc!E97 -> 0 | P97: =Calc!F97 -> 33 | Q97: =Calc!G97 -> 100 | R97: =Calc!H97 -> 0 | S97: =AVERAGE(L97:R97) -> 23.714286 | T97: =RANK(S97,$S$2:$S$113,0)+(COUNTIF($S$2:$S$113,S97)-1)/2 -> 103 | U97: =Coverage!I97 -> 6 | V97: =Coverage!J97 -> 0.85714286 | W97: =IFERROR(SUMPRODUCT(L97:R97,Coverage!B97:H97)/U97,0) -> 27.666667 | X97: 029_web_accessibility_status unavailable/unknown scored 0; No independent verification recorded
A98: RePEc | B98: RePEc | C98: Discovery system | Index or directory | D98: In progress | E98: Implemented/available | F98: Advisory board or steering committee | H98: Ad hoc | I98: Unknown | J98: Unknown | K98: Implemented/available | L98: =Calc!B98 -> 67 | M98: =Calc!C98 -> 100 | N98: =Verification!F98 -> 100 | O98: =Calc!E98 -> 0 | P98: =Calc!F98 -> 0 | Q98: =Calc!G98 -> 100 | R98: =Calc!H98 -> 50 | S98: =AVERAGE(L98:R98) -> 59.571429 | T98: =RANK(S98,$S$2:$S$113,0)+(COUNTIF($S$2:$S$113,S98)-1)/2 -> 67 | U98: =Coverage!I98 -> 5 | V98: =Coverage!J98 -> 0.71428571 | W98: =IFERROR(SUMPRODUCT(L98:R98,Coverage!B98:H98)/U98,0) -> 83.4 | X98: 029_web_accessibility_status unavailable/unknown scored 0; 035_commitment_to_equity_status unavailable/unknown scored 0; No independent verification recorded
A99: Research Organization Registry (ROR) | B99: California Digital Library, Crossref, DataCite | C99: Persistent identifier service | D99: Implemented/available | E99: Implemented/available | F99: Advisory board or steering committee | H99: Formal | I99: Considering | J99: Considering | K99: Implemented/available | L99: =Calc!B99 -> 100 | M99: =Calc!C99 -> 100 | N99: =Verification!F99 -> 100 | O99: =Calc!E99 -> 33 | P99: =Calc!F99 -> 33 | Q99: =Calc!G99 -> 100 | R99: =Calc!H99 -> 100 | S99: =AVERAGE(L99:R99) -> 80.857143 | T99: =RANK(S99,$S$2:$S$113,0)+(COUNTIF($S$2:$S$113,S99)-1)/2 -> 37 | U99: =Coverage!I99 -> 7 | V99: =Coverage!J99 -> 1 | W99: =IFERROR(SUMPRODUCT(L99:R99,Coverage!B99:H99)/U99,0) -> 80.857143 | X99: No independent verification recorded
A100: Rogue Scholar | B100: The Rogue Scholar | C100: Digital preservation system | Discovery system | D100: In progress | E100: Unknown | F100: None | H100: Ad hoc | I100: Considering | J100: Considering | K100: In progress | L100: =Calc!B100 -> 67 | M100: =Calc!C100 -> 0 | N100: =Verification!F100 -> 0 | O100: =Calc!E100 -> 33 | P100: =Calc!F100 -> 33 | Q100: =Calc!G100 -> 67 | R100: =Calc!H100 -> 50 | S100: =AVERAGE(L100:R100) -> 35.714286 | T100: =RANK(S100,$S$2:$S$113,0)+(COUNTIF($S$2:$S$113,S100)-1)/2 -> 95.5 | U100: =Coverage!I100 -> 6 | V100: =Coverage!J100 -> 0.85714286 | W100: =IFERROR(SUMPRODUCT(L100:R100,Coverage!B100:H100)/U100,0) -> 41.666667 | X100: 108_bylaws_status unavailable/unknown scored 0; No independent verification recorded
A101: RSpace | B101: Research Innovations Ltd (trading as Research Space) | C101: Authoring tool | Digital asset management system | D101: Considering | E101: Not planning | F101: Other | G101: Board of directors of UK limited company | H101: None | I101: In progress | J101: Considering | K101: Implemented/available | L101: =Calc!B101 -> 33 | M101: =Calc!C101 -> 0 | N101: =Verification!F101 -> 100 | O101: =Calc!E101 -> 67 | P101: =Calc!F101 -> 33 | Q101: =Calc!G101 -> 100 | R101: =Calc!H101 -> 0 | S101: =AVERAGE(L101:R101) -> 47.571429 | T101: =RANK(S101,$S$2:$S$113,0)+(COUNTIF($S$2:$S$113,S101)-1)/2 -> 82.5 | U101: =Coverage!I101 -> 7 | V101: =Coverage!J101 -> 1 | W101: =IFERROR(SUMPRODUCT(L101:R101,Coverage!B101:H101)/U101,0) -> 47.571429 | X101: Review 050 Other response; override available; No independent verification recorded
...

Sheet Metric Rules
A1: Code | B1: Metric | C1: Source field(s) | D1: Exact weight | E1: Displayed weight | F1: Scoring criteria | G1: Unavailable-data treatment | H1: Why this metric is retained
A2: G1 | B2: Governance structure status | C2: 024_governance_structure_status | D2: 0.14285714 | E2: 14.29% | F2: Implemented/available=100; In progress=67; Considering=33; Not planning=0. | G2: Unknown, not applicable, blank, or unrecognized=0 in final score; omitted from observed-only diagnostics. Explicit negative response counts as observed zero. | H2: Reports whether a governance structure is implemented or at an earlier stated stage; the data show responses across the status ladder.
A3: G2 | B3: Bylaws or equivalent formal rules | C3: 108_bylaws_status | D3: 0.14285714 | E3: 14.29% | F3: Implemented/available=100; In progress=67; Considering=33; Not planning=0. | G3: Unknown, not applicable, blank, or unrecognized=0 in final score; omitted from observed-only diagnostics. Explicit negative response counts as observed zero. | H3: Captures written bylaws or equivalent rules as a distinct formal-governance element; report its comparatively high missingness.
A4: G3 | B4: Board or steering-body presence | C4: 050_board_structure + 950_board_structure_other | D4: 0.14285714 | E4: 14.29% | F4: Recognized advisory/steering or multi-board category=100; None=0; Other=100 only when field 950 substantiates a relevant board/committee; otherwise 0 pending review. | G4: Blank=0 and unavailable. Other is scored 0 provisionally and flagged unless field 950 supports a relevant body; reviewer override 0/100 available. None is an observed zero. | H4: Captures whether a board/steering body exists. Corrects the former error that credited the explicit response None.
A5: G4 | B5: Web accessibility status | C5: 029_web_accessibility_status | D5: 0.14285714 | E5: 14.29% | F5: Implemented/available=100; In progress=67; Considering=33; Not planning=0. | G5: Blank or unrecognized=0 and unavailable. Explicit None counts as observed zero. | H5: Captures the reported maturity of web accessibility status.
A6: G5 | B6: Equity commitment status | C6: 035_commitment_to_equity_status | D6: 0.14285714 | E6: 14.29% | F6: Implemented/available=100; In progress=67; Considering=33; Not planning=0. | G6: Unknown, not applicable, blank, or unrecognized=0 in final score; omitted from observed-only diagnostics. Explicit negative response counts as observed zero. | H6: Captures the reported maturity of explicit equity commitments.
A7: G6 | B7: Privacy commitment status | C7: 044_commitment_to_privacy_status | D7: 0.14285714 | E7: 14.29% | F7: Implemented/available=100; In progress=67; Considering=33; Not planning=0. | G7: Unknown, not applicable, blank, or unrecognized=0 in final score; omitted from observed-only diagnostics. Explicit negative response counts as observed zero. | H7: Captures the reported maturity of privacy commitments relevant to users and their data.
A8: G7 | B8: Community governance formality | C8: 048_community_governance_status | D8: 0.14285714 | E8: 14.29% | F8: Formal=100; Ad hoc=50; None=0. | G8: Unknown, not applicable, blank, or unrecognized=0 in final score; omitted from observed-only diagnostics. Explicit negative response counts as observed zero. | H8: Measures formal versus ad hoc community participation in governance; all source service names match the governance dataset.
A9: Total | D9: 1 | E9: 100.00% | H9: Exact weight per metric is 1/7; 14.29% is display rounding.

Sheet Methodology
A1: Methodology and interpretation | B1: Details
A2: Scope | B2: Seven indicators represent governance-structure status, formal rules, governing-body presence, community participation in governance, accessibility, equity, and privacy.
A3: Equal weighting | B3: Each top-level metric receives exactly 1/7 of the score (14.2857%; displayed as 14.29%). Equal weighting is a transparent design choice, not an empirically estimated claim of equal causal importance.
A4: Final formula | B4: Governance Practices Score = (G1 + G2 + G3 + G4 + G5 + G6 + G7) / 7. Each metric is scored from 0 to 100.
A5: No coverage gate | B5: Every infrastructure receives a score. There is no minimum coverage or eligibility rule; the denominator stays seven.
A6: Zero-fill assumption | B6: Unknown, Not applicable, blank, and unrecognized responses score zero in the final composite. This makes the score reflect reported performance and data completeness; zero does not prove absence of the underlying practice.
A7: Coverage diagnostics | B7: Observed metric count and observed coverage (count/7) are reported but do not gate scoring. Explicit negative responses such as Not planning or None count as observed zero. Unknown, N/A, blank, and unresolved status values are excluded from observed coverage.
A8: Observed-only mean | B8: Average the metric scores with observed data only. This is descriptive and uses a variable denominator; it is not the final score or primary zero-filled ranking.
A9: 048 source merge | B9: Community governance fields 048 and 049 are imported from the Community Engagement verification workbook and matched by exact service name. All 112 names match; the current Community Engagement index does not score 048 as a separate metric.
A10: 050 correction | B10: The prior binary rule awarded points to any nonblank value and therefore treated None as positive. The revised rule scores None=0 and requires field 950 evidence to count Other as a governing body. Other cases are flagged for review and may be overridden in Verification.
A11: Fields excluded from score | B11: 026 Governance records and 033 Transparent pricing are excluded as requested. Field 046 Values frameworks and 100 Board level remain descriptive; 046 contains heterogeneous frameworks and is blank for 76 entries, while 100 has only 15 responses. URLs and summaries are evidence/context, not additional metrics.
A12: Why 033 is excluded | B12: The prior source has 59 No direct costs and 47 Implemented/available responses. Treating both as fully transparent pricing places 94.6% at the score ceiling and conflates absence of charge with price transparency.
... A16: No bands | B16: No 70-point cutoff or high/medium/low performance bands are applied.

Sheet Parameters
A1: Parameter | B1: Value | C1: Explanation
A2: Number of metrics | B2: 7 | C2: G1 through G7
A3: Exact metric weight | B3: 0.14285714 | C3: Each metric contributes equally; exact weight sums to 100%.
A4: Displayed metric weight | B4: 14.29% | C4: Rounded display only.
A5: Final score denominator | B5: 7 | C5: Fixed for every infrastructure.
A6: Coverage eligibility threshold | B6: None | C6: Coverage is diagnostic only; all entries are scored.
A7: Unavailable-data treatment | B7: 0 | C7: Unknown, N/A, blank, or unrecognized values contribute zero to the final score.
A8: Status ladder | B8: 100 / 67 / 33 / 0 | C8: Implemented / In progress / Considering / Not planning.
A9: Community governance ladder | B9: 100 / 50 / 0 | C9: Formal / Ad hoc / None.
A10: 050 Other handling | B10: Review + override | C10: Use 950 description; score 100 only when a relevant board or committee is substantiated.

Sheet Diagnostics
A1: Metric | B1: Source field(s) | C1: Observed n | D1: Observed coverage | E1: Mean among observed | F1: Mean under zero-fill | G1: SD among observed | H1: % at 100 among observed | I1: % at 0 among observed | J1: Reading
A2: G1 Governance structure status | B2: 024_governance_structure_status | C2: 107 | D2: 0.95535714 | E2: 82.570093 | F2: 78.883929 | G2: 30.374335 | H2: 0.70093458 | I2: 0.065420561 | J2: Broad status variation; unknown values are zero-filled.
A3: G2 Bylaws or equivalent formal rules | B3: 108_bylaws_status | C3: 83 | D3: 0.74107143 | E3: 69.46988 | F3: 51.482143 | G3: 44.284224 | H3: 0.6626506 | I3: 0.26506024 | J3: 29 unknown values; zero-fill materially affects its mean.
A4: G3 Board or steering-body presence | B4: 050_board_structure + 950_board_structure_other | C4: 107 | D4: 0.95535714 | E4: 75.700935 | F4: 72.321429 | G4: 42.888949 | H4: 0.75700935 | I4: 0.24299065 | J4: Other values need review; explicit None correctly scores zero.
A5: G4 Web accessibility status | B5: 029_web_accessibility_status | C5: 102 | D5: 0.91071429 | E5: 62.754902 | F5: 57.151786 | G5: 32.533071 | H5: 0.33333333 | I5: 0.088235294 | J5: Accessibility applicability field is sparse; use status as recorded.
A6: G5 Equity commitment status | B6: 035_commitment_to_equity_status | C6: 103 | D6: 0.91964286 | E6: 62.106796 | F6: 57.116071 | G6: 35.477577 | H6: 0.38834951 | I6: 0.11650485 | J6: Equity commitment has good spread across status levels.
A7: G6 Privacy commitment status | B7: 044_commitment_to_privacy_status | C7: 99 | D7: 0.88392857 | E7: 79.454545 | F7: 70.232143 | G7: 36.938188 | H7: 0.73737374 | I7: 0.14141414 | J7: High implemented share; still retains non-ceiling variation.
A8: G7 Community governance formality | B8: 048_community_governance_status | C8: 106 | D8: 0.94642857 | E8: 65.566038 | F8: 62.053571 | G8: 37.844772 | H8: 0.49056604 | I8: 0.17924528 | J8: Community governance is sourced from the matched CE sheet; six blanks.
A10: Component summary | B10: Value
A11: Entries scored | B11: 112
A12: Metrics | B12: 7
A13: Weight per metric | B13: 1/7 = 14.2857% (display 14.29%)
A14: Mean zero-filled score | B14: 64.177296
A15: Median zero-filled score | B15: 70.214286
A16: Score standard deviation | B16: 26.000086
A17: Minimum score | B17: 0
A18: Maximum score | B18: 100
A19: Mean observed coverage | B19: 0.90178571
A20: All seven metrics observed | B20: 68
A21: Verification data | B21: verification_status and verification_notes are blank across the source entries.

Sheet Sensitivity
A1: Sensitivity variant | B1: Entries | C1: Spearman rho vs baseline | D1: Mean absolute score change | E1: Max absolute score change | F1: Entries moving >=10 ranks | G1: Interpretation
A2: Baseline: seven-metric zero-filled | B2: 112 | C2: 1 | D2: 0 | E2: 0 | F2: 0 | G2: Primary result; all entries scored.
A3: Observed-only mean | B3: 112 | C3: 0.9342237 | D3: 5.6517219 | E3: 47.857143 | F3: 40 | G3: Diagnostic only; variable denominator and partial coverage.
A4: Complete-data subset, same seven metrics | B4: 68 | C4: 1 | D4: 0 | E4: 0 | F4: 0 | G4: Sensitivity only; does not exclude other entries from the main score.
A5: Six-metric variant excluding G3 | B5: 112 | C5: 0.9798554 | D5: 4.7293793 | E5: 13.5 | F5: 12 | G5: Sensitivity check for the influence of board-presence metric; not the official metric set.
A7: Note | B7: G3 sensitivity uses provisional 050/950 coding. Refresh this workbook after reviewer overrides to update all result and sensitivity tables.

Sheet Coverage
A1: Service | B1: G1 observed | C1: G2 observed | D1: G3 observed | E1: G4 observed | F1: G5 observed | G1: G6 observed | H1: G7 observed | I1: Available metrics (of 7) | J1: Observed coverage | K1: Observed-only mean | L1: Zero-filled final score
A2: 2i2c | B2: 1 | C2: 0 | D2: 1 | E2: 1 | F2: 1 | G2: 1 | H2: 1 | I2: 6 | J2: 0.85714286 | K2: =Scoring!W2 -> 55.5 | L2: =Scoring!S2 -> 47.571429
A3: Academic Preservation Trust (APTrust) | B3: 1 | C3: 1 | D3: 1 | E3: 1 | F3: 1 | G3: 1 | H3: 1 | I3: 7 | J3: 1 | K3: =Scoring!W3 -> 76.142857 | L3: =Scoring!S3 -> 76.142857
A4: AfricArXiv | B4: 1 | C4: 1 | D4: 1 | E4: 1 | F4: 1 | G4: 1 | H4: 1 | I4: 7 | J4: 1 | K4: =Scoring!W4 -> 69.142857 | L4: =Scoring!S4 -> 69.142857
A5: Arches Heritage Data Management Platform | B5: 1 | C5: 1 | D5: 1 | E5: 1 | F5: 1 | G5: 1 | H5: 1 | I5: 7 | J5: 1 | K5: =Scoring!W5 -> 71.428571 | L5: =Scoring!S5 -> 71.428571
A6: Archipelago Commons | B6: 1 | C6: 1 | D6: 1 | E6: 1 | F6: 1 | G6: 1 | H6: 1 | I6: 7 | J6: 1 | K6: =Scoring!W6 -> 90.428571 | L6: =Scoring!S6 -> 90.428571
A7: Archival Resource Key | B7: 1 | C7: 0 | D7: 1 | E7: 1 | F7: 1 | G7: 0 | H7: 1 | I7: 5 | J7: 0.71428571 | K7: =Scoring!W7 -> 63.4 | L7: =Scoring!S7 -> 45.285714
A8: Archivematica | B8: 1 | C8: 1 | D8: 1 | E8: 1 | F8: 1 | G8: 1 | H8: 1 | I8: 7 | J8: 1 | K8: =Scoring!W8 -> 33.142857 | L8: =Scoring!S8 -> 33.142857
A9: ArchivesSpace | B9: 1 | C9: 1 | D9: 1 | E9: 1 | F9: 1 | G9: 1 | H9: 1 | I9: 7 | J9: 1 | K9: =Scoring!W9 -> 100 | L9: =Scoring!S9 -> 100
A10: ARGOS | B10: 1 | C10: 1 | D10: 1 | E10: 1 | F10: 1 | G10: 1 | H10: 1 | I10: 7 | J10: 1 | K10: =Scoring!W10 -> 95.285714 | L10: =Scoring!S10 -> 95.285714
A11: arXiv | B11: 1 | C11: 1 | D11: 1 | E11: 1 | F11: 0 | G11: 1 | H11: 1 | I11: 6 | J11: 0.85714286 | K11: =Scoring!W11 -> 100 | L11: =Scoring!S11 -> 85.714286
A12: AtoM | B12: 1 | C12: 1 | D12: 0 | E12: 1 | F12: 1 | G12: 1 | H12: 0 | I12: 5 | J12: 0.71428571 | K12: =Scoring!W12 -> 53.2 | L12: =Scoring!S12 -> 38
A13: Avalon Media System | B13: 1 | C13: 1 | D13: 1 | E13: 1 | F13: 1 | G13: 1 | H13: 1 | I13: 7 | J13: 1 | K13: =Scoring!W13 -> 71.428571 | L13: =Scoring!S13 -> 71.428571
... A113: Zotero | B113: 1 | C113: 1 | D113: 1 | E113: 1 | F113: 1 | G113: 1 | H113: 1 | I113: 7 | J113: 1 | K113: =Scoring!W113 -> 92.857143 | L113: =Scoring!S113 -> 92.857143

Sheet Verification
A1: Service | B1: 050 board structure | C1: 950 other detail | D1: Provisional G3 | E1: Reviewer override (0 or 100) | F1: Final G3 | G1: Review status | H1: Reviewer notes
A2: 2i2c | B2: Advisory board or steering committee | D2: 100 | F2: =IF(ISNUMBER(E2),E2,D2) -> 100 | G2: No G3 review flagged | H2: Allowed override values are 0 or 100; use only after checking the described body's role.
A3: Academic Preservation Trust (APTrust) | B3: Multi-board governance | D3: 100 | F3: =IF(ISNUMBER(E3),E3,D3) -> 100 | G3: No G3 review flagged | H3: Allowed override values are 0 or 100; use only after checking the described body's role.
A4: AfricArXiv | B4: Advisory board or steering committee | D4: 100 | F4: =IF(ISNUMBER(E4),E4,D4) -> 100 | G4: No G3 review flagged | H4: Allowed override values are 0 or 100; use only after checking the described body's role.
A5: Arches Heritage Data Management Platform | B5: Advisory board or steering committee | D5: 100 | F5: =IF(ISNUMBER(E5),E5,D5) -> 100 | G5: No G3 review flagged | H5: Allowed override values are 0 or 100; use only after checking the described body's role.
A6: Archipelago Commons | B6: Advisory board or steering committee | D6: 100 | F6: =IF(ISNUMBER(E6),E6,D6) -> 100 | G6: No G3 review flagged | H6: Allowed override values are 0 or 100; use only after checking the described body's role.
A7: Archival Resource Key | B7: Advisory board or steering committee | D7: 100 | F7: =IF(ISNUMBER(E7),E7,D7) -> 100 | G7: No G3 review flagged | H7: Allowed override values are 0 or 100; use only after checking the described body's role.
A8: Archivematica | B8: None | D8: 0 | F8: =IF(ISNUMBER(E8),E8,D8) -> 0 | G8: No G3 review flagged | H8: Allowed override values are 0 or 100; use only after checking the described body's role.
A9: ArchivesSpace | B9: Advisory board or steering committee | D9: 100 | F9: =IF(ISNUMBER(E9),E9,D9) -> 100 | G9: No G3 review flagged | H9: Allowed override values are 0 or 100; use only after checking the described body's role.
A10: ARGOS | B10: Advisory board or steering committee | D10: 100 | F10: =IF(ISNUMBER(E10),E10,D10) -> 100 | G10: No G3 review flagged | H10: Allowed override values are 0 or 100; use only after checking the described body's role.
A11: arXiv | B11: Multi-board governance | D11: 100 | F11: =IF(ISNUMBER(E11),E11,D11) -> 100 | G11: No G3 review flagged | H11: Allowed override values are 0 or 100; use only after checking the described body's role.
A12: AtoM | D12: 0 | F12: =IF(ISNUMBER(E12),E12,D12) -> 0 | G12: No G3 review flagged | H12: Allowed override values are 0 or 100; use only after checking the described body's role.
A13: Avalon Media System | B13: Advisory board or steering committee | D13: 100 | F13: =IF(ISNUMBER(E13),E13,D13) -> 100 | G13: No G3 review flagged | H13: Allowed override values are 0 or 100; use only after checking the described body's role.
A14: Biodiversity Heritage Library | B14: Advisory board or steering committee | D14: 100 | F14: =IF(ISNUMBER(E14),E14,D14) -> 100 | G14: No G3 review flagged | H14: Allowed override values are 0 or 100; use only after checking the described body's role.
A15: bioRxiv | B15: Advisory board or steering committee | D15: 100 | F15: =IF(ISNUMBER(E15),E15,D15) -> 100 | G15: No G3 review flagged | H15: Allowed override values are 0 or 100; use only after checking the described body's role.
A16: BitCurator Environment | B16: Advisory board or steering committee | D16: 100 | F16: =IF(ISNUMBER(E16),E16,D16) -> 100 | G16: No G3 review flagged | H16: Allowed override values are 0 or 100; use only after checking the described body's role.
A17: Blacklight | B17: None | D17: 0 | F17: =IF(ISNUMBER(E17),E17,D17) -> 0 | G17: No G3 review flagged | H17: Allowed override values are 0 or 100; use only after checking the described body's role.
A18: BrCRIS | B18: Advisory board or steering committee | D18: 100 | F18: =IF(ISNUMBER(E18),E18,D18) -> 100 | G18: No G3 review flagged | H18: Allowed override values are 0 or 100; use only after checking the described body's role.
A19: Browsertrix | B19: None | D19: 0 | F19: =IF(ISNUMBER(E19),E19,D19) -> 0 | G19: No G3 review flagged | H19: Allowed override values are 0 or 100; use only after checking the described body's role.
A20: CLOCKSS | B20: Advisory board or steering committee | D20: 100 | F20: =IF(ISNUMBER(E20),E20,D20) -> 100 | G20: No G3 review flagged | H20: Allowed override values are 0 or 100; use only after checking the described body's role.
A21: COAR International Repository Directory (IRD) | B21: Advisory board or steering committee | D21: 100 | F21: =IF(ISNUMBER(E21),E21,D21) -> 100 | G21: No G3 review flagged | H21: Allowed override values are 0 or 100; use only after checking the described body's role.
A22: COAR Notify | B22: Other | C22: Editorial Board | D22: 0 | F22: =IF(ISNUMBER(E22),E22,D22) -> 0 | G22: Review Other response | H22: Allowed override values are 0 or 100; use only after checking the described body's role.
A23: CollectiveAccess | B23: None | D23: 0 | F23: =IF(ISNUMBER(E23),E23,D23) -> 0 | G23: No G3 review flagged | H23: Allowed override values are 0 or 100; use only after checking the described body's role.
A24: CORE | B24: Multi-board governance | D24: 100 | F24: =IF(ISNUMBER(E24),E24,D24) -> 100 | G24: No G3 review flagged | H24: Allowed override values are 0 or 100; use only after checking the described body's role.
A25: COUNTER Code of Practice | B25: Multi-board governance | D25: 100 | F25: =IF(ISNUMBER(E25),E25,D25) -> 100 | G25: No G3 review flagged | H25: Allowed override values are 0 or 100; use only after checking the described body's role.
A26: Creative Commons Licenses | B26: Advisory board or steering committee | D26: 100 | F26: =IF(ISNUMBER(E26),E26,D26) -> 100 | G26: No G3 review flagged | H26: Allowed override values are 0 or 100; use only after checking the described body's role.
A27: Crossref Metadata Retrieval | B27: Multi-board governance | D27: 100 | F27: =IF(ISNUMBER(E27),E27,D27) -> 100 | G27: No G3 review flagged | H27: Allowed override values are 0 or 100; use only after checking the described body's role.
A28: D4Science Infrastructure | D28: 0 | F28: =IF(ISNUMBER(E28),E28,D28) -> 0 | G28: No G3 review flagged | H28: Allowed override values are 0 or 100; use only after checking the described body's role.
A29: DART (Digital Archivist's Resource Tool) | B29: Advisory board or steering committee | D29: 100 | F29: =IF(ISNUMBER(E29),E29,D29) -> 100 | G29: No G3 review flagged | H29: Allowed override values are 0 or 100; use only after checking the described body's role.
A30: Database Information System | B30: Advisory board or steering committee | D30: 100 | F30: =IF(ISNUMBER(E30),E30,D30) -> 100 | G30: No G3 review flagged | H30: Allowed override values are 0 or 100; use only after checking the described body's role.
A31: Data Citation Corpus | B31: None | D31: 0 | F31: =IF(ISNUMBER(E31),E31,D31) -> 0 | G31: No G3 review flagged | H31: Allowed override values are 0 or 100; use only after checking the described body's role.
A32: DataCite | B32: Advisory board or steering committee | D32: 100 | F32: =IF(ISNUMBER(E32),E32,D32) -> 100 | G32: No G3 review flagged | H32: Allowed override values are 0 or 100; use only after checking the described body's role.
A33: Data Stewardship Wizard | B33: Advisory board or steering committee | D33: 100 | F33: =IF(ISNUMBER(E33),E33,D33) -> 100 | G33: No G3 review flagged | H33: Allowed override values are 0 or 100; use only after checking the described body's role.
A34: Dataverse | B34: None | D34: 0 | F34: =IF(ISNUMBER(E34),E34,D34) -> 0 | G34: No G3 review flagged | H34: Allowed override values are 0 or 100; use only after checking the described body's role.
A35: DLCM Backend | B35: Advisory board or steering committee | D35: 100 | F35: =IF(ISNUMBER(E35),E35,D35) -> 100 | G35: No G3 review flagged | H35: Allowed override values are 0 or 100; use only after checking the described body's role.
A36: DLCM Portal | B36: Advisory board or steering committee | D36: 100 | F36: =IF(ISNUMBER(E36),E36,D36) -> 100 | G36: No G3 review flagged | H36: Allowed override values are 0 or 100; use only after checking the described body's role.
A37: DMP Tool | B37: None | D37: 0 | F37: =IF(ISNUMBER(E37),E37,D37) -> 0 | G37: No G3 review flagged | H37: Allowed override values are 0 or 100; use only after checking the described body's role.
A38: DOAJ (Directory of Open Access Journals) | B38: Advisory board or steering committee | Other | C38: Foundation Board & Advisory Board | D38: 100 | F38: =IF(ISNUMBER(E38),E38,D38) -> 100 | G38: No G3 review flagged | H38: Allowed override values are 0 or 100; use only after checking the described body's role.
A39: dokieli | D39: 0 | F39: =IF(ISNUMBER(E39),E39,D39) -> 0 | G39: No G3 review flagged | H39: Allowed override values are 0 or 100; use only after checking the described body's role.
A40: Dryad | B40: Other | D40: 0 | F40: =IF(ISNUMBER(E40),E40,D40) -> 0 | G40: Review Other response | H40: Allowed override values are 0 or 100; use only after checking the described body's role.
A41: DSpace | B41: Advisory board or steering committee | D41: 100 | F41: =IF(ISNUMBER(E41),E41,D41) -> 100 | G41: No G3 review flagged | H41: Allowed override values are 0 or 100; use only after checking the described body's role.
A42: DuraCloud | B42: None | D42: 0 | F42: =IF(ISNUMBER(E42),E42,D42) -> 0 | G42: No G3 review flagged | H42: Allowed override values are 0 or 100; use only after checking the described body's role.
A43: Episciences | B43: Multi-board governance | D43: 100 | F43: =IF(ISNUMBER(E43),E43,D43) -> 100 | G43: No G3 review flagged | H43: Allowed override values are 0 or 100; use only after checking the described body's role.
A44: EPrints | D44: 0 | F44: =IF(ISNUMBER(E44),E44,D44) -> 0 | G44: No G3 review flagged | H44: Allowed override values are 0 or 100; use only after checking the described body's role.
A45: Érudit | B45: Multi-board governance | D45: 100 | F45: =IF(ISNUMBER(E45),E45,D45) -> 100 | G45: No G3 review flagged | H45: Allowed override values are 0 or 100; use only after checking the described body's role.
A46: Europe PMC | B46: Advisory board or steering committee | D46: 100 | F46: =IF(ISNUMBER(E46),E46,D46) -> 100 | G46: No G3 review flagged | H46: Allowed override values are 0 or 100; use only after checking the described body's role.
A47: FAIR Wizard | B47: None | D47: 0 | F47: =IF(ISNUMBER(E47),E47,D47) -> 0 | G47: No G3 review flagged | H47: Allowed override values are 0 or 100; use only after checking the described body's role.
A48: Fedora | B48: Advisory board or steering committee | D48: 100 | F48: =IF(ISNUMBER(E48),E48,D48) -> 100 | G48: No G3 review flagged | H48: Allowed override values are 0 or 100; use only after checking the described body's role.
A49: fido | B49: Advisory board or steering committee | D49: 100 | F49: =IF(ISNUMBER(E49),E49,D49) -> 100 | G49: No G3 review flagged | H49: Allowed override values are 0 or 100; use only after checking the described body's role.
A50: Fulcrum | B50: Other | D50: 0 | F50: =IF(ISNUMBER(E50),E50,D50) -> 0 | G50: Review Other response | H50: Allowed override values are 0 or 100; use only after checking the described body's role.
A51: Galaxy | B51: Multi-board governance | D51: 100 | F51: =IF(ISNUMBER(E51),E51,D51) -> 100 | G51: No G3 review flagged | H51: Allowed override values are 0 or 100; use only after checking the described body's role.
A52: GeoServer | B52: Advisory board or steering committee | D52: 100 | F52: =IF(ISNUMBER(E52),E52,D52) -> 100 | G52: No G3 review flagged | H52: Allowed override values are 0 or 100; use only after checking the described body's role.
A53: Hyku | B53: Advisory board or steering committee | D53: 100 | F53: =IF(ISNUMBER(E53),E53,D53) -> 100 | G53: No G3 review flagged | H53: Allowed override values are 0 or 100; use only after checking the described body's role.
A54: Hyrax | B54: Advisory board or steering committee | D54: 100 | F54: =IF(ISNUMBER(E54),E54,D54) -> 100 | G54: No G3 review flagged | H54: Allowed override values are 0 or 100; use only after checking the described body's role.
A55: IIIF | B55: Advisory board or steering committee | D55: 100 | F55: =IF(ISNUMBER(E55),E55,D55) -> 100 | G55: No G3 review flagged | H55: Allowed override values are 0 or 100; use only after checking the described body's role.
A56: ImpactU | B56: None | D56: 0 | F56: =IF(ISNUMBER(E56),E56,D56) -> 0 | G56: No G3 review flagged | H56: Allowed override values are 0 or 100; use only after checking the described body's role.
... A58: InvenioRDM | B58: Advisory board or steering committee | D58: 100 | F58: =IF(ISNUMBER(E58),E58,D58) -> 100 | G58: No G3 review flagged | H58: Allowed override values are 0 or 100; use only after checking the described body's role.
A59: iRODS | B59: Advisory board or steering committee | C59: In addition to the Executive Committee (which makes decisions on budgets and by laws), there is an Advisory Board that is advisory/strategic: https://irods.org/advisory-board/ | D59: 100 | F59: =IF(ISNUMBER(E59),E59,D59) -> 100 | G59: No G3 review flagged | H59: Allowed override values are 0 or 100; use only after checking the described body's role.
A60: Islandora | B60: Advisory board or steering committee | D60: 100 | F60: =IF(ISNUMBER(E60),E60,D60) -> 100 | G60: No G3 review flagged | H60: Allowed override values are 0 or 100; use only after checking the described body's role.
A61: Janeway | B61: Advisory board or steering committee | D61: 100 | F61: =IF(ISNUMBER(E61),E61,D61) -> 100 | G61: No G3 review flagged | H61: Allowed override values are 0 or 100; use only after checking the described body's role.
A62: JHOVE | B62: Advisory board or steering committee | D62: 100 | F62: =IF(ISNUMBER(E62),E62,D62) -> 100 | G62: No G3 review flagged | H62: Allowed override values are 0 or 100; use only after checking the described body's role.
A63: LA Referencia | B63: Multi-board governance | D63: 100 | F63: =IF(ISNUMBER(E63),E63,D63) -> 100 | G63: No G3 review flagged | H63: Allowed override values are 0 or 100; use only after checking the described body's role.
A64: Manifold | B64: Advisory board or steering committee | D64: 100 | F64: =IF(ISNUMBER(E64),E64,D64) -> 100 | G64: No G3 review flagged | H64: Allowed override values are 0 or 100; use only after checking the described body's role.
A65: medRxiv | B65: Advisory board or steering committee | D65: 100 | F65: =IF(ISNUMBER(E65),E65,D65) -> 100 | G65: No G3 review flagged | H65: Allowed override values are 0 or 100; use only after checking the described body's role.
A66: Metadata Encoding and Transmission Standard (METS) | B66: Advisory board or steering committee | D66: 100 | F66: =IF(ISNUMBER(E66),E66,D66) -> 100 | G66: No G3 review flagged | H66: Allowed override values are 0 or 100; use only after checking the described body's role.
A67: Mirador | B67: None | D67: 0 | F67: =IF(ISNUMBER(E67),E67,D67) -> 0 | G67: No G3 review flagged | H67: Allowed override values are 0 or 100; use only after checking the described body's role.
A68: Mukurtu CMS | B68: Advisory board or steering committee | D68: 100 | F68: =IF(ISNUMBER(E68),E68,D68) -> 100 | G68: No G3 review flagged | H68: Allowed override values are 0 or 100; use only after checking the described body's role.
A69: MyCoRe | B69: None | D69: 0 | F69: =IF(ISNUMBER(E69),E69,D69) -> 0 | G69: No G3 review flagged | H69: Allowed override values are 0 or 100; use only after checking the described body's role.
A70: NumPy | B70: Advisory board or steering committee | D70: 100 | F70: =IF(ISNUMBER(E70),E70,D70) -> 100 | G70: No G3 review flagged | H70: Allowed override values are 0 or 100; use only after checking the described body's role.
A71: OA.Report | B71: Advisory board or steering committee | D71: 100 | F71: =IF(ISNUMBER(E71),E71,D71) -> 100 | G71: No G3 review flagged | H71: Allowed override values are 0 or 100; use only after checking the described body's role.
A72: OA Switchboard | D72: 0 | F72: =IF(ISNUMBER(E72),E72,D72) -> 0 | G72: No G3 review flagged | H72: Allowed override values are 0 or 100; use only after checking the described body's role.
A73: Omeka | B73: Advisory board or steering committee | D73: 100 | F73: =IF(ISNUMBER(E73),E73,D73) -> 100 | G73: No G3 review flagged | H73: Allowed override values are 0 or 100; use only after checking the described body's role.
A74: OpenAIRE Graph | B74: Advisory board or steering committee | D74: 100 | F74: =IF(ISNUMBER(E74),E74,D74) -> 100 | G74: No G3 review flagged | H74: Allowed override values are 0 or 100; use only after checking the described body's role.
A75: OpenAlex | B75: Advisory board or steering committee | D75: 100 | F75: =IF(ISNUMBER(E75),E75,D75) -> 100 | G75: No G3 review flagged | H75: Allowed override values are 0 or 100; use only after checking the described body's role.
A76: OpenAPC | B76: None | D76: 0 | F76: =IF(ISNUMBER(E76),E76,D76) -> 0 | G76: No G3 review flagged | H76: Allowed override values are 0 or 100; use only after checking the described body's role.
A77: OpenCitations | B77: Advisory board or steering committee | D77: 100 | F77: =IF(ISNUMBER(E77),E77,D77) -> 100 | G77: No G3 review flagged | H77: Allowed override values are 0 or 100; use only after checking the described body's role.
A78: openCost | B78: None | D78: 0 | F78: =IF(ISNUMBER(E78),E78,D78) -> 0 | G78: No G3 review flagged | H78: Allowed override values are 0 or 100; use only after checking the described body's role.
A79: Open Data Editor | B79: Advisory board or steering committee | D79: 100 | F79: =IF(ISNUMBER(E79),E79,D79) -> 100 | G79: No G3 review flagged | H79: Allowed override values are 0 or 100; use only after checking the described body's role.
A80: OpenEdition | B80: Multi-board governance | D80: 100 | F80: =IF(ISNUMBER(E80),E80,D80) -> 100 | G80: No G3 review flagged | H80: Allowed override values are 0 or 100; use only after checking the described body's role.
A81: Open Journal Systems (OJS) | B81: Multi-board governance | D81: 100 | F81: =IF(ISNUMBER(E81),E81,D81) -> 100 | G81: No G3 review flagged | H81: Allowed override values are 0 or 100; use only after checking the described body's role.
A82: Open Monograph Press (OMP) | B82: Multi-board governance | D82: 100 | F82: =IF(ISNUMBER(E82),E82,D82) -> 100 | G82: No G3 review flagged | H82: Allowed override values are 0 or 100; use only after checking the described body's role.
A83: Open Preprint Systems (OPS) | B83: Multi-board governance | D83: 100 | F83: =IF(ISNUMBER(E83),E83,D83) -> 100 | G83: No G3 review flagged | H83: Allowed override values are 0 or 100; use only after checking the described body's role.
A84: Openverse | B84: None | D84: 0 | F84: =IF(ISNUMBER(E84),E84,D84) -> 0 | G84: No G3 review flagged | H84: Allowed override values are 0 or 100; use only after checking the described body's role.
... A92: Public Access Submission System | B92: Other | D92: 0 | F92: =IF(ISNUMBER(E92),E92,D92) -> 0 | G92: Review Other response | H92: Allowed override values are 0 or 100; use only after checking the described body's role.
A93: Public Utility Data Liberation (PUDL) | B93: Other | C93: Board of directors | D93: 100 | F93: =IF(ISNUMBER(E93),E93,D93) -> 100 | G93: Review Other response | H93: Allowed override values are 0 or 100; use only after checking the described body's role.
A94: PubPub | B94: Advisory board or steering committee | D94: 100 | F94: =IF(ISNUMBER(E94),E94,D94) -> 100 | G94: No G3 review flagged | H94: Allowed override values are 0 or 100; use only after checking the described body's role.
A95: Pundit | B95: None | D95: 0 | F95: =IF(ISNUMBER(E95),E95,D95) -> 0 | G95: No G3 review flagged | H95: Allowed override values are 0 or 100; use only after checking the described body's role.
A96: pyOpenSci | B96: Advisory board or steering committee | D96: 100 | F96: =IF(ISNUMBER(E96),E96,D96) -> 100 | G96: No G3 review flagged | H96: Allowed override values are 0 or 100; use only after checking the described body's role.
A97: Renku | B97: None | D97: 0 | F97: =IF(ISNUMBER(E97),E97,D97) -> 0 | G97: No G3 review flagged | H97: Allowed override values are 0 or 100; use only after checking the described body's role.
A98: RePEc | B98: Advisory board or steering committee | D98: 100 | F98: =IF(ISNUMBER(E98),E98,D98) -> 100 | G98: No G3 review flagged | H98: Allowed override values are 0 or 100; use only after checking the described body's role.
A99: Research Organization Registry (ROR) | B99: Advisory board or steering committee | D99: 100 | F99: =IF(ISNUMBER(E99),E99,D99) -> 100 | G99: No G3 review flagged | H99: Allowed override values are 0 or 100; use only after checking the described body's role.
A100: Rogue Scholar | B100: None | D100: 0 | F100: =IF(ISNUMBER(E100),E100,D100) -> 0 | G100: No G3 review flagged | H100: Allowed override values are 0 or 100; use only after checking the described body's role.
A101: RSpace | B101: Other | C101: Board of directors of UK limited company | D101: 100 | F101: =IF(ISNUMBER(E101),E101,D101) -> 100 | G101: Review Other response | H101: Allowed override values are 0 or 100; use only after checking the described body's role.
A102: Sciety | B102: Multi-board governance | D102: 100 | F102: =IF(ISNUMBER(E102),E102,D102) -> 100 | G102: No G3 review flagged | H102: Allowed override values are 0 or 100; use only after checking the described body's role.
A103: Synapse | B103: Advisory board or steering committee | D103: 100 | F103: =IF(ISNUMBER(E103),E103,D103) -> 100 | G103: No G3 review flagged | H103: Allowed override values are 0 or 100; use only after checking the described body's role.
A104: TagTeam | B104: None | D104: 0 | F104: =IF(ISNUMBER(E104),E104,D104) -> 0 | G104: No G3 review flagged | H104: Allowed override values are 0 or 100; use only after checking the described body's role.
A105: Thoth Open Metadata | B105: Other | C105: Board of Directors | D105: 100 | F105: =IF(ISNUMBER(E105),E105,D105) -> 100 | G105: Review Other response | H105: Allowed override values are 0 or 100; use only after checking the described body's role.
A106: Tropy | B106: Advisory board or steering committee | D106: 100 | F106: =IF(ISNUMBER(E106),E106,D106) -> 100 | G106: No G3 review flagged | H106: Allowed override values are 0 or 100; use only after checking the described body's role.
A107: veraPDF | B107: None | D107: 0 | F107: =IF(ISNUMBER(E107),E107,D107) -> 0 | G107: No G3 review flagged | H107: Allowed override values are 0 or 100; use only after checking the described body's role.
A108: ViPER | B108: Advisory board or steering committee | D108: 100 | F108: =IF(ISNUMBER(E108),E108,D108) -> 100 | G108: No G3 review flagged | H108: Allowed override values are 0 or 100; use only after checking the described body's role.
...

Sheet Review Queue
A1: Service | B1: Metric / field | C1: Raw value | D1: Provisional treatment | E1: Review reason / action | F1: Reviewer notes
A2: Archipelago Commons | B2: G1: 024_governance_structure_status | C2: Implemented/available | D2: Status scored 100; no paired URL supplied | E2: Review official evidence where available; this is a documentation check, not an eligibility rule.
A3: COAR Notify | B3: G3: 050/950 | C3: Other | Editorial Board | D3: 0 | E3: Confirm the described body governs, oversees, or advises this infrastructure; then enter 0 or 100 on Verification.
A4: DMP Tool | B4: G4: 029_web_accessibility_status | C4: Implemented/available | D4: Status scored 100; no paired URL supplied | E4: Review official evidence where available; this is a documentation check, not an eligibility rule.
A5: DOAJ (Directory of Open Access Journals) | B5: G4: 029_web_accessibility_status | C5: Implemented/available | D5: Status scored 100; no paired URL supplied | E5: Review official evidence where available; this is a documentation check, not an eligibility rule.
A6: Dryad | B6: G3: 050/950 | C6: Other | | D6: 0 | E6: Confirm the described body governs, oversees, or advises this infrastructure; then enter 0 or 100 on Verification.
A7: Dryad | B7: G4: 029_web_accessibility_status | C7: Implemented/available | D7: Status scored 100; no paired URL supplied | E7: Review official evidence where available; this is a documentation check, not an eligibility rule.
A8: fido | B8: G7: 048/049 | C8: Formal | D8: Formal scored 100; no paired URL supplied | E8: Review official evidence where available; this is a documentation check, not an eligibility rule.
A9: Fulcrum | B9: G3: 050/950 | C9: Other | | D9: 0 | E9: Confirm the described body governs, oversees, or advises this infrastructure; then enter 0 or 100 on Verification.
A10: Janeway | B10: G4: 029_web_accessibility_status | C10: Implemented/available | D10: Status scored 100; no paired URL supplied | E10: Review official evidence where available; this is a documentation check, not an eligibility rule.
A11: LA Referencia | B11: G7: 048/049 | C11: Formal | D11: Formal scored 100; no paired URL supplied | E11: Review official evidence where available; this is a documentation check, not an eligibility rule.
A12: Manifold | B12: G4: 029_web_accessibility_status | C12: Implemented/available | D12: Status scored 100; no paired URL supplied | E12: Review official evidence where available; this is a documentation check, not an eligibility rule.
A13: Omeka | B13: G4: 029_web_accessibility_status | C13: Implemented/available | D13: Status scored 100; no paired URL supplied | E13: Review official evidence where available; this is a documentation check, not an eligibility rule.
A14: OpenAlex | B14: G7: 048/049 | C14: Formal | D14: Formal scored 100; no paired URL supplied | E14: Review official evidence where available; this is a documentation check, not an eligibility rule.
A15: O Portal Brasileiro de Publicações e Dados Científicos em Acesso Aberto (The Brazilian Open Access Publications and Scientific Data Portal) (Oasisbr) | B15: G3: 050/950 | C15: Other | | D15: 0 | E15: Confirm the described body governs, oversees, or advises this infrastructure; then enter 0 or 100 on Verification.
A16: Peer Community In | B16: G7: 048/049 | C16: Formal | D16: Formal scored 100; no paired URL supplied | E16: Review official evidence where available; this is a documentation check, not an eligibility rule.
A17: Public Access Submission System | B17: G3: 050/950 | C17: Other | | D17: 0 | E17: Confirm the described body governs, oversees, or advises this infrastructure; then enter 0 or 100 on Verification.
A18: Public Utility Data Liberation (PUDL) | B18: G3: 050/950 | C18: Other | Board of directors | D18: 100 | E18: Confirm the described body governs, oversees, or advises this infrastructure; then enter 0 or 100 on Verification.
A19: RSpace | B19: G3: 050/950 | C19: Other | Board of directors of UK limited company | D19: 100 | E19: Confirm the described body governs, oversees, or advises this infrastructure; then enter 0 or 100 on Verification.
A20: Sciety | B20: G7: 048/049 | C20: Formal | D20: Formal scored 100; no paired URL supplied | E20: Review official evidence where available; this is a documentation check, not an eligibility rule.
A21: Thoth Open Metadata | B21: G3: 050/950 | C21: Other | Board of Directors | D21: 100 | E21: Confirm the described body governs, oversees, or advises this infrastructure; then enter 0 or 100 on Verification.
A22: veraPDF | B22: G7: 048/049 | C22: Formal | D22: Formal scored 100; no paired URL supplied | E22: Review official evidence where available; this is a documentation check, not an eligibility rule.
A23: ViPER | B23: G7: 048/049 | C23: Formal | D23: Formal scored 100; no paired URL supplied | E23: Review official evidence where available; this is a documentation check, not an eligibility rule.

Sheet Calc
A1: Service | B1: G1 | C1: G2 | D1: G3 provisional | E1: G4 | F1: G5 | G1: G6 | H1: G7 | I1: G3 coding rationale | J1: G3 review flag | K1: Python-checked zero-filled score | L1: Available metrics | M1: Observed coverage | N1: Observed-only mean | O1: Data-quality flags
A2: 2i2c | B2: 67 | C2: 0 | D2: 100 | E2: 33 | F2: 33 | G2: 100 | H2: 0 | I2: Recognized board or steering-body category | J2: No | K2: 47.571429 | L2: 6 | M2: 0.85714286 | N2: 55.5 | O2: 108_bylaws_status unavailable/unknown scored 0; No independent verification recorded
A3: Academic Preservation Trust (APTrust) | B3: 100 | C3: 100 | D3: 100 | E3: 33 | F3: 100 | G3: 0 | H3: 100 | I3: Recognized board or steering-body category | J3: No | K3: 76.142857 | L3: 7 | M3: 1 | N3: 76.142857 | O3: No independent verification recorded
A4: AfricArXiv | B4: 100 | C4: 0 | D4: 100 | E4: 67 | F4: 67 | G4: 100 | H4: 50 | I4: Recognized board or steering-body category | J4: No | K4: 69.142857 | L4: 7 | M4: 1 | N4: 69.142857 | O4: No independent verification recorded
A5: Arches Heritage Data Management Platform | B5: 100 | C5: 100 | D5: 100 | E5: 100 | F5: 0 | G5: 0 | H5: 100 | I5: Recognized board or steering-body category | J5: No | K5: 71.428571 | L5: 7 | M5: 1 | N5: 71.428571 | O5: No independent verification recorded
A6: Archipelago Commons | B6: 100 | C6: 100 | D6: 100 | E6: 100 | F6: 100 | G6: 33 | H6: 100 | I6: Recognized board or steering-body category | J6: No | K6: 90.428571 | L6: 7 | M6: 1 | N6: 90.428571 | O6: No independent verification recorded
A7: Archival Resource Key | B7: 67 | C7: 0 | D7: 100 | E7: 67 | F7: 33 | G7: 0 | H7: 50 | I7: Recognized board or steering-body category | J7: No | K7: 45.285714 | L7: 5 | M7: 0.71428571 | N7: 63.4 | O7: 108_bylaws_status unavailable/unknown scored 0; 044_commitment_to_privacy_status unavailable/unknown scored 0; No independent verification recorded
A8: Archivematica | B8: 33 | C8: 33 | D8: 0 | E8: 33 | F8: 33 | G8: 100 | H8: 0 | I8: Explicitly reports no board/steering body | J8: No | K8: 33.142857 | L8: 7 | M8: 1 | N8: 33.142857 | O8: No independent verification recorded
A9: ArchivesSpace | B9: 100 | C9: 100 | D9: 100 | E9: 100 | F9: 100 | G9: 100 | H9: 100 | I9: Recognized board or steering-body category | J9: No | K9: 100 | L9: 7 | M9: 1 | N9: 100 | O9: No independent verification recorded
A10: ARGOS | B10: 100 | C10: 100 | D10: 100 | E10: 67 | F10: 100 | G10: 100 | H10: 100 | I10: Recognized board or steering-body category | J10: No | K10: 95.285714 | L10: 7 | M10: 1 | N10: 95.285714 | O10: No independent verification recorded
A11: arXiv | B11: 100 | C11: 100 | D11: 100 | E11: 100 | F11: 0 | G11: 100 | H11: 100 | I11: Recognized board or steering-body category | J11: No | K11: 85.714286 | L11: 6 | M11: 0.85714286 | N11: 100 | O11: 035_commitment_to_equity_status unavailable/unknown scored 0; No independent verification recorded
A12: AtoM | B12: 33 | C12: 33 | D12: 0 | E12: 67 | F12: 33 | G12: 100 | H12: 0 | I12: Blank or unrecognized board-structure response | J12: No | K12: 38 | L12: 5 | M12: 0.71428571 | N12: 53.2 | O12: 048 community governance missing/unrecognized scored 0; No independent verification recorded
A13: Avalon Media System | B13: 100 | C13: 100 | D13: 100 | E13: 67 | F13: 33 | G13: 0 | H13: 100 | I13: Recognized board or steering-body category | J13: No | K13: 71.428571 | L13: 7 | M13: 1 | N13: 71.428571 | O13: No independent verification recorded
... A113: Zotero | B113: 100 | C113: 100 | D113: 100 | E113: 100 | F113: 100 | G113: 100 | H113: 50 | I113: Recognized board or steering-body category | J113: No | K113: 92.857143 | L113: 7 | M113: 1 | N113: 92.857143 | O113: No independent verification recorded

Sheet Data
A1: 001_service_name | B1: 008_provider_name | C1: 010_website | D1: 013_location | E1: 014_solution_category | F1: 019_open_code_repository_url | G1: 024_governance_structure_status | H1: 025_governance_structure_url | I1: 026_governance_records_status | J1: 027_governance_summary | K1: 028_governance_records_url | L1: 050_board_structure | M1: 950_board_structure_other | N1: 100_board_level | O1: 900_board_level_other | P1: 108_bylaws_status | Q1: 029_web_accessibility_status | R1: 030_web_accessibility_url | S1: 031_web_accessibility_applicability | T1: 033_transparent_pricing_status | U1: 034_transparent_pricing_url | V1: 035_commitment_to_equity_status | W1: 036_commitment_to_equity_url | X1: 044_commitment_to_privacy_status | Y1: 045_commitment_to_privacy_url | Z1: 046_values_frameworks | AA1: verification_status | AB1: verification_notes | AC1: 048_community_governance_status | AD1: 049_community_governance_url
A2: 2i2c | B2: Code for Science and Society | C2: https://2i2c.org/ | D2: US | E2: Authoring tool | F2: https://github.com/2i2c-org/infrastructure | G2: In progress | H2: https://compass.2i2c.org/organization/structure/ | I2: In progress | J2: <p>2i2c is governed by a <a href="https://compass.2i2c.org/organization/structure/" target="_blank">Steering Council</a>, and is a fiscally sponsored project of <a href="https://www.codeforsociety.org/" target="_blank">Code for Science &amp; Society</a>, a US-based 501(c)3. Additional governance development is in progress. </p> | L2: Advisory board or steering committee | P2: Unknown | Q2: Considering | T2: Implemented/available | U2: https://docs.google.com/document/d/1FNiDyKNDoe_TgU2WxuNZ5CayYD56tlNJpImQsAIGOmg/edit | V2: Considering | X2: Implemented/available | Y2: https://docs.2i2c.org/user/topics/policy/privacy/ | AC2: None
A3: Academic Preservation Trust (APTrust) | B3: Academic Preservation Trust (APTrust) | C3: https://aptrust.org | D3: US | E3: Digital preservation service | F3: https://github.com/APTrust/registry | G3: Implemented/available | H3: https://aptrust.org/governance/ | I3: Implemented/available | J3: The Governing Board is the primary governing body for APTrust; however, member institutions contribute actively to governance through input gathered by the Board. The Board defines and recommends strategic direction to meet operational and strategic goals, and it provides advice and oversight for the budget and finances. The Board meets in person or by phone as needed and holds an annual meeting with all institutional members. The APTrust Advisory Committee comprises two representatives from each of the APTrust Sustaining Member institutions. They are appointed annually by their respective deans, and two members of the committee are selected to serve as co-chairs and liaisons to the APTrust Governing Board, where they are voting members. Advisory Committee members bring expertise in their respective fields, as well as in policy matters and priorities, to APTrust. The group keeps the broader community informed about and connected to the developing digital preservation infrastructure. | K3: https://aptrust.org/resources/member-meetings/ | L3: Multi-board governance | O3: The Governing Board is the primary governing body for APTrust; however, member institutions contribute actively to governance through input gathered by the Board. The Board defines and recommends strategic direction to help meet operational and strategic goals and provides advice and oversight for the budget and finances. The Board meets quarterly in person or by phone as needed and holds an annual meeting of the Board with all institutional members. APTrust is legally constituted as part of the University of Virginia. Activities and operating guidelines of APTrust are subject to the rules and policies of the University of Virginia, as are any contracts between individual member institutions and the University of Virginia. | P3: Implemented/available | Q3: Considering | T3: Implemented/available | U3: https://aptrust.org/about/services-and-fees/ | V3: Implemented/available | W3: https://aptrust.org/resources/policies/#vision-mission-and-shared-values | X3: Not planning | Z3: It Takes a Village Open Source Software Sustainability toolkit | AC3: Formal | AD3: https://aptrust.org/resources/policies/#governance-manual
A4: AfricArXiv | B4: UbuntuNet Alliance | C4: https://africarxiv.org/ | D4: MW | E4: Repository service | G4: Implemented/available | H4: https://africarxiv.org/governance | I4: Not planning | L4: Advisory board or steering committee | O4: n/a | P4: Not planning | Q4: In progress | T4: In progress | V4: In progress | X4: Implemented/available | Y4: https://africarxiv.ubuntunet.net/info/privacy | Z4: Helsinki Initiative on Multilingualism | AC4: Ad hoc
A5: Arches Heritage Data Management Platform | B5: Getty Conservation Institute (GCI) | C5: https://archesproject.org | D5: US | E5: Data management planning tool or service | F5: https://github.com/archesproject | G5: Implemented/available | H5: https://www.archesproject.org/archesgovernance/ | I5: In progress | L5: Advisory board or steering committee | O5: Works to decide on the strategic and operational requirements and priorities of the Arches Project. | P5: Implemented/available | Q5: Implemented/available | R5: https://www.archesproject.org/accessibility/ | S5: Our tool or project | T5: No direct costs | V5: Not planning | X5: Not planning | Z5: FAIR Guiding Principles for Scientific Data Management and Stewardship | AC5: Formal | AD5: https://www.archesproject.org/archesgovernance/
A6: Archipelago Commons | B6: Metropolitan New York Library Council | C6: https://docs.archipelago.nyc/ | D6: US | E6: Digital library, collection or exhibit platform | Repository software | F6: https://github.com/esmero/ | G6: Implemented/available | I6: In progress | J6: Archipelago is governed by an Advisory Board, and is a project of the <a href="https://metro.org">Metropolitan New York Library Council</a>, which is governed by a <a href="https://metro.org/team/">Board of Trustees</a>. | L6: Advisory board or steering committee | P6: Implemented/available | Q6: Implemented/available | R6: https://docs.google.com/document/d/1IXLYykwTbYS34VqzU-4AOD47EKQC95WyKrmZOKZkz6s/edit?usp=sharing | S6: Our tool or project | T6: In progress | V6: Implemented/available | W6: https://docs.archipelago.nyc/1.5.0/CODE_OF_CONDUCT/ | X6: Considering | Z6: Contributor Covenant Code of Conduct for Open Source and Other Digital Commons Communities | FAIR Guiding Principles for Scientific Data Management and Stewardship | AC6: Formal | AD6: https://metro.org/wp-content/uploads/2025/05/METROBylaws20242.pdf
A7: Archival Resource Key | B7: ARK Alliance | C7: https://arks.org/ | D7: US | E7: Standard, specification or protocol | F7: https://github.com/arks-org | G7: In progress | I7: In progress | J7: <p><a href="https://arks.org/community/" target="_blank">ARK Alliance</a> is a global community group that works to promote and support the ARK community. Participation is open to all ARK users. Oversight and activities are conducted by committees, including the Advisory Group, Outreach Group, Technical Group, and the Name Assigning Authority Number (NAAN) Group.</p> | L7: Advisory board or steering committee | P7: Unknown | Q7: In progress | T7: No direct costs | V7: Considering | X7: Not applicable | AC7: Ad hoc
A8: Archivematica | B8: Artefactual | C8: https://www.archivematica.org/ | D8: CA | E8: Digital preservation system | F8: https://github.com/artefactual/archivematica | G8: Considering | I8: Considering | L8: None | O8: We have a board of directors for the company Artefactual not the Archiveamtica software. | P8: Considering | Q8: Considering | T8: Implemented/available | U8: https://www.artefactual.com/pricing | V8: Considering | X8: Implemented/available | Y8: https://www.artefactual.com/data-collection-and-privacy-notice | AC8: None
A9: ArchivesSpace | B9: ArchivesSpace | C9: https://archivesspace.org/ | D9: US | E9: Archive information management system | Discovery system | F9: https://github.com/archivesspace/archivesspace | G9: Implemented/available | H9: https://archivesspace.org/governance-board-and-councils | I9: Implemented/available | K9: https://archivesspace.atlassian.net/wiki/spaces/AC/overview | L9: Advisory board or steering committee | O9: high level decision-making and strategic discussions, ensuring the financial health of the organization and approval of the annual budget, overseeing and representing the ArchivesSpace community at large in the relationship with Lyrasis, the organizational home | P9: Implemented/available | Q9: Implemented/available | R9: https://archivesspace.org/application/accessibility-vpat | S9: Our tool or project | T9: Implemented/available | U9: https://archivesspace.org/membership/member-benefits | V9: Implemented/available | W9: https://archivesspace.org/about/anti-racism-inclusion-initiatives | X9: Implemented/available | Y9: https://archivesspace.org/about/lyrasis-privacy-policy | Z9: It Takes a Village Open Source Software Sustainability toolkit | AC9: Formal | AD9: https://archivesspace.org/governance-board-and-councils
A10: ARGOS | B10: OpenAIRE | C10: https://argos.openaire.eu/ | E10: Data management planning tool or service | F10: https://github.com/OpenCDMP/OpenCDMP | G10: Implemented/available | H10: https://www.openaire.eu/governance | I10: Not planning | L10: Advisory board or steering committee | O10: The Board is essential in shaping OpenAIRE and thereby the ARGOS roadmap and development. They are regularly consulted and their input and decisions are highly valued and respected. | P10: Implemented/available | Q10: In progress | T10: Implemented/available | U10: https://catalogue.openaire.eu/service/openaire.argos/subscriptions | V10: Implemented/available | W10: https://www.openaire.eu/openaire-gep | X10: Implemented/available | Y10: https://www.openaire.eu/privacy-policy | Z10: FAIR Guiding Principles for Scientific Data Management and Stewardship | AC10: Formal | AD10: https://www.openaire.eu/organisation-2
A11: arXiv | B11: Cornell University | C11: https://arxiv.org/ | D11: US | E11: Repository service | F11: https://github.com/arXiv | G11: Implemented/available | H11: https://info.arxiv.org/about/governance.html | I11: Implemented/available | J11: <p>arXiv is <a href="https://info.arxiv.org/about/governance.html" target="_blank">governed</a> by the Leadership team with guidance from the arXiv <a href="https://info.arxiv.org/about/people/science_advisory_council.html" target="_blank">Science Advisory Council</a>, <a href="https://info.arxiv.org/about/people/institutions_advisory_council.html" target="_blank">Institutions Advisory Council</a>, and <a href="https://info.arxiv.org/about/people/editorial_advisory_council.html" target="_blank">Editorial Advisory Council</a>. arXiv is housed at <a href="https://www.cornell.edu/" target="_blank">Cornell University</a>.</p> | K11: https://info.arxiv.org/about/reports/index.html | L11: Multi-board governance | P11: Implemented/available | Q11: Implemented/available | R11: https://info.arxiv.org/help/web_accessibility.html | S11: Our website | T11: Implemented/available | U11: https://info.arxiv.org/about/funding.html | V11: Unknown | X11: Implemented/available | Y11: https://info.arxiv.org/help/policies/privacy_policy.html | AC11: Formal | AD11: https://info.arxiv.org/about/arXiv_bylaws.html
A12: AtoM | B12: Artefactual | C12: https://www.accesstomemory.org/en/ | D12: CA | E12: Archive information management system | F12: https://github.com/artefactual/atom | G12: Considering | I12: Considering | O12: Artefactual the company has a board of directors. AtoM does not have a board but there is the AtoM Foundation, a federally incorporated, community driven, soliciting non-profit body. The Foundation was established in 2018 to oversee and support the development, sustainability and adoption of Access to Memory (AtoM). https://accesstomemoryfoundation.org/ | P12: Considering | Q12: In progress | T12: Implemented/available | U12: https://www.artefactual.com/pricing | V12: Considering | X12: Implemented/available | Y12: https://www.artefactual.com/data-collection-and-privacy-notice
A13: Avalon Media System | B13: Indiana University Libraries | C13: https://avalon.samvera.org/ | D13: US | E13: Digital library, collection or exhibit platform | Repository software | F13: https://github.com/avalonmediasystem/avalon | G13: Implemented/available | H13: https://samvera.atlassian.net/wiki/spaces/samvera/pages/1387986974/Samvera+Bylaws | I13: Implemented/available | J13: Avalon is a project of Samvera, a distinct series entity hosted by OASIS Open. Samvera is governed by a Board of Directors. | K13: https://samvera.atlassian.net/wiki/spaces/samvera/pages/426512038/Notes+from+Samvera+Board+meetings+and+calls | L13: Advisory board or steering committee | N13: Other | O13: Avalon is a project of Samvera, a distinct series entity hosted by OASIS Open. Samvera is governed by a Board of Directors. | P13: Implemented/available | Q13: In progress | T13: No direct costs | V13: Considering | X13: Not planning | AC13: Formal | AD13: https://samvera.atlassian.net/wiki/spaces/samvera/pages/1387986974/Samvera+Bylaws
A14: Biodiversity Heritage Library | B14: BHL Consortium | C14: https://www.biodiversitylibrary.org/ | D14: US | E14: Digital library, collection or exhibit platform | Open scholarly dataset | Repository service | F14: https://github.com/gbhl/bhl-us | G14: Implemented/available | H14: https://about.biodiversitylibrary.org/about/bhl-consortium/ | I14: Implemented/available | J14: BHL is led by a global consortium of libraries and hosted by the Smithsonian Libraries and Archives. | K14: https://about.biodiversitylibrary.org/about/strategic-plan/ | L14: Advisory board or steering committee | N14: Both | P14: Implemented/available | Q14: Considering | T14: No direct costs | V14: Considering | X14: Implemented/available | Y14: https://www.si.edu/privacy | AC14: Formal | AD14: https://about.biodiversitylibrary.org/about/bylaws/
A15: bioRxiv | B15: Cold Spring Harbor Laboratory | C15: https://www.biorxiv.org/ | D15: US | E15: Repository service | G15: In progress | H15: https://www.biorxiv.org/content/about-biorxiv | I15: Not planning | J15: <p>bioRxiv is governed by an <a href="https://www.biorxiv.org/content/about-biorxiv" target="_blank">Advisory Board and Affiliates</a>, and is housed at <a href="https://www.cshl.edu/" target="_blank">Cold Spring Harbor Laboratory</a>, which is governed by a <a href="https://www.cshl.edu/about-us/board-of-trustees/" target="_blank">Board of Trustees</a>. Additional governance development is in progress. </p> | L15: Advisory board or steering committee | P15: Unknown | Q15: Considering | T15: No direct costs | V15: In progress | X15: Implemented/available | Y15: http://cshlp.org/misc/preprints_privacy_policy/ | AC15: Ad hoc
A16: BitCurator Environment | B16: BitCurator Consortium | C16: https://bitcuratorconsortium.org/ | E16: Digital preservation tool | F16: https://github.com/bitcurator/bitcurator-salt | G16: Implemented/available | H16: https://bitcuratorconsortium.org/about/executive-council/ | I16: In progress | J16: BitCurator is a project of the BitCurator Consortium (BCC) is an independent, community-led membership association hosted by the Open Library Foundation, a 501(c)(3) Public Charity organization in the United States. | L16: Advisory board or steering committee | N16: Both | P16: Implemented/available | Q16: Considering | T16: No direct costs | V16: Implemented/available | W16: https://bitcuratorconsortium.org/inclusivity-statement/ | X16: Implemented/available | Y16: https://bitcuratorconsortium.org/privacy-policy/ | AC16: Formal | AD16: https://bitcuratorconsortium.org/bitcurator-consortium-charter/
A17: Blacklight | B17: Blacklight | C17: https://projectblacklight.org/ | D17: US | E17: Discovery system | Integrated Library System (ILS) or Library Services Platform (LSP) | F17: https://github.com/projectblacklight | G17: In progress | I17: In progress | J17: Blacklight is a collaborative, open source project produced by developers from many diverse organizations. The project does not have a formal governance structure. Development is largely motivated by the needs of each developer’s organization. | L17: None | P17: In progress | Q17: In progress | T17: No direct costs | V17: In progress | X17: In progress | AC17: Ad hoc
A18: BrCRIS | B18: IBICT | C18: https://brcris.ibict.br/ | D18: BR | E18: Discovery system | Research profiling system | F18: https://github.com/projetos-codic-ibict | G18: Unknown | I18: In progress | J18: <p>BrCRIS is a project led by the <a href="https://www.gov.br/ibict/pt-br" target="_blank">Instituto Brasileiro de Informação em Ciência e Tecnologia</a> (IBICT), a national information body and research unit of the <a href="https://www.gov.br/mcti/pt-br" target="_blank">Ministério da Ciência, Tecnologia e Inovação (MCTI)</a>. </p> | K18: https://brcris.ibict.br/about | L18: Advisory board or steering committee | P18: Unknown | Q18: In progress | T18: Implemented/available | U18: https://brcris.ibict.br/about | V18: Considering | X18: Implemented/available | Y18: https://brcris.ibict.br/about | AC18: Ad hoc
A19: Browsertrix | B19: Webrecorder | C19: https://webrecorder.net/browsertrix/ | D19: US | E19: Digital library, collection or exhibit platform | Web archiving system | F19: https://github.com/webrecorder/browsertrix | G19: Not planning | I19: Not planning | J19: Browsertrix's development is overseen by Webrecorder Software LLC. | L19: None | O19: To oversee Webrecorder | P19: Not planning | Q19: Unknown | T19: Implemented/available | U19: https://webrecorder.net/browsertrix/pricing/ | V19: Unknown | X19: Implemented/available | Y19: https://webrecorder.net/legal/webrecorder-privacy-policy/ | AC19: None
A20: CLOCKSS | B20: CLOCKSS | C20: https://clockss.org | D20: US | E20: Digital preservation service | F20: https://github.com/lockss | G20: Implemented/available | H20: https://clockss.org/digital-archive-community/board-of-directors/ | I20: Considering | L20: Advisory board or steering committee | O20: *Select and remove Officers and Agents and set their Terms of Reference *Agree CLOCKSS strategy *Ensure that there are funds to deliver the strategy; set and track the budget *Agree how to invest CLOCKSS money, or to incur debt *Check that the strategy is being delivered, and request corrective action where necessary *Decide the level of risk that is right for CLOCKSS, require staff to identify risk and propose mitigating activities, agree and monitor this activity *Prepare the annual accounts and report, with support from staff *Act in the interests of CLOCKSS, not another individual or organization | P20: Implemented/available | Q20: In progress | T20: Implemented/available | U20: https://clockss.org/join-clockss/ | V20: Implemented/available | W20: https://clockss.org/biblio-equity-in-action-advancing-collection-development-for-diversity-equity-and-inclusion/ | X20: Implemented/available | Y20: https://clockss.org/clockss-privacy-policy/ | AC20: Formal | AD20: https://clockss.org/wp-content/uploads/2024/03/DIGITAL-DISTRIBUTED-COMMUNITY-ARCHIVE-ByLaws.pdf
A21: COAR International Repository Directory (IRD) | B21: COAR | C21: https://ird.coar-repositories.org/ | E21: Index or directory | F21: https://github.com/antleaf/IRD | G21: Implemented/available | H21: https://coar-repositories.org/about-coar/ | I21: Considering | J21: The Stichting COAR is a not-for-profit foundation that was created on April 3, 2023 in accordance with the Netherlands Civil Code (Art. 2:285 et seq.). It is governed by a board of directors. | L21: Advisory board or steering committee | N21: Provider | P21: In progress | Q21: Considering | T21: No direct costs | V21: Implemented/available | W21: http://www.coar-repositories.org/ | X21: Not planning | AC21: Ad hoc
A22: COAR Notify | B22: COAR | C22: https://coar-notify.net/ | E22: Standard, specification or protocol | F22: https://github.com/coar-notify/coar-notify.net | G22: Implemented/available | H22: https://coar-notify.net/about/editorial/ | I22: Considering | J22: The Stichting COAR is a not-for-profit foundation that was created on April 3, 2023 in accordance with the Netherlands Civil Code (Art. 2:285 et seq.). It is governed by a board of directors. | L22: Other | M22: Editorial Board | P22: Not planning | Q22: Considering | T22: No direct costs | V22: Implemented/available | W22: http://www.coar-repositories.org/ | X22: Not planning | AC22: Ad hoc
A23: CollectiveAccess | B23: Whirl-i-Gig | C23: https://www.collectiveaccess.org/ | D23: US | E23: Archive information management system | Digital asset management system | Digital library, collection or exhibit platform | F23: https://github.com/collectiveaccess | G23: Not planning | I23: Not planning | L23: None | O23: No board. | P23: Not planning | Q23: In progress | T23: No direct costs | V23: Not planning | X23: Not planning | Z23: It Takes a Village Open Source Software Sustainability toolkit | AC23: Ad hoc
A24: CORE | B24: The Open University | C24: https://core.ac.uk/ | D24: GB | E24: Discovery system | F24: https://github.com/oacore | G24: Implemented/available | H24: https://core.ac.uk/governance | I24: In progress | J24: <p>CORE is a <a href="https://core.ac.uk/governance" target="_blank">community governed service</a>, governed by an Advisory Board, Board of Supporters, The Open University Stakeholder Group, Research networks representatives, and CORE Leadership and management team. </p> | L24: Multi-board governance | P24: Implemented/available | Q24: Implemented/available | R24: https://core.ac.uk/accessibility | S24: Our website | T24: Implemented/available | U24: https://core.ac.uk/membership | V24: Considering | X24: Implemented/available | Y24: https://core.ac.uk/privacy | AC24: Formal | AD24: https://core.ac.uk/governance
A25: COUNTER Code of Practice | B25: COUNTER Metrics | C25: https://www.countermetrics.org/ | D25: GB | E25: Standard, specification or protocol | F25: https://cop5.countermetrics.org/en/5.1/index.html | G25: Implemented/available | H25: https://www.countermetrics.org/about/people/ | I25: Implemented/available | J25: COUNTER is a non-profit organization supported by a global community of library, publisher and vendor members, who contribute to the development of the Code of Practice through working groups and outreach. We are governed by a Board of Directors responsible for ensuring we deliver on our mission, while our Executive Committee oversees operational activities including technical development of the Code of Practice. You can find out more at https://www.countermetrics.org/about/ | K25: https://www.countermetrics.org/category/agm-minutes/ | L25: Multi-board governance | P25: Implemented/available | Q25: Implemented/available | R25: https://www.countermetrics.org/accessibility/ | S25: Our tool or project | Our website | T25: Implemented/available | U25: https://www.countermetrics.org/members/ | V25: In progress | X25: Implemented/available | Y25: https://www.countermetrics.org/privacy-data-protection/ | Z25: Principles for Open Scholarly Infrastructure (POSI) | AC25: Formal | AD25: https://find-and-update.company-information.service.gov.uk/company/04865179/filing-history
A26: Creative Commons Licenses | B26: Creative Commons | C26: https://creativecommons.org/ | D26: US | E26: Standard, specification or protocol | F26: https://github.com/creativecommons | G26: Implemented/available | H26: https://creativecommons.org/mission/team/ | I26: Implemented/available | J26: <p>Creative Commons is <a href="https://creativecommons.org/mission/team/" target="_blank">governed by</a> a Board and Advisory Council. </p> | K26: https://drive.google.com/file/d/10rQDv5Hzuss38oi1ovGuoxHagmFzqn_f/view | L26: Advisory board or steering committee | P26: Unknown | Q26: Considering | T26: No direct costs | V26: In progress | X26: Implemented/available | Y26: https://creativecommons.org/privacy/ | AC26: None
A27: Crossref Metadata Retrieval | B27: Crossref | C27: http://www.crossref.org/services/metadata-retrieval | D27: US | E27: Open scholarly dataset | F27: https://gitlab.com/crossref | G27: Implemented/available | H27: https://www.crossref.org/board-and-governance/ | I27: Implemented/available | J27: <p>Crossref is governed by a <a href="https://www.crossref.org/board-and-governance/" target="_blank">Board of Directors</a>, elected by its members. Their board consists of a representative balance of 16 institutions, publishers, or funders, and they are responsible for the fiduciary and strategic oversight of the organisation. </p> | K27: https://www.crossref.org/board-and-governance/ | L27: Multi-board governance | P27: Implemented/available | Q27: In progress | T27: Implemented/available | U27: https://www.crossref.org/fees/ | V27: Implemented/available | W27: https://www.crossref.org/gem/ | X27: Implemented/available | Y27: https://www.crossref.org/operations-and-sustainability/privacy/ | Z27: Principles for Open Scholarly Infrastructure (POSI) | AC27: Formal | AD27: https://www.crossref.org/board-and-governance/bylaws/
A28: D4Science Infrastructure | B28: National Research Council of Italy | C28: https://www.d4science.org/ | D28: IT | E28: Computing framework | Informal scholarly communications | Repository service | F28: https://code-repo.d4science.org/ | G28: In progress | I28: Considering | P28: Not planning | Q28: Considering | T28: Implemented/available | U28: https://www.d4science.org/faq | V28: Considering | X28: Implemented/available | Y28: https://www.iubenda.com/privacy-policy/441050
A29: DART (Digital Archivist's Resource Tool) | B29: Academic Preservation Trust (APTrust) | C29: https://aptrust.github.io/dart-docs/ | D29: US | E29: Digital preservation tool | F29: https://github.com/aptrust/dart/ | G29: Implemented/available | H29: https://aptrust.org/governance/ | I29: Considering | J29: The Governing Board is the primary governing body for APTrust. The Board defines and recommends strategic direction to meet operational and strategic goals, and it provides advice and oversight for the budget and finances. The Board meets in person or by phone as needed and holds an annual meeting with all institutional members. The APTrust Advisory Committee comprises two representatives from each of the APTrust Sustaining Member institutions. They are appointed annually by their respective deans, and two members of the committee are selected to serve as co-chairs and liaisons to the APTrust Governing Board, where they are voting members. Advisory Committee members bring expertise in their respective fields, as well as in policy matters and priorities, to APTrust. The group keeps the broader community informed about and connected to the developing digital preservation infrastructure. | L29: Advisory board or steering committee | O29: The Governing Board is the primary governing body for APTrust; however, member institutions contribute actively to governance through input gathered by the Board. The Board defines and recommends strategic direction to help meet operational and strategic goals and provides advice and oversight for the budget and finances. | P29: Implemented/available | Q29: In progress | T29: No direct costs | V29: Implemented/available | W29: https://aptrust.org/resources/policies/#vision-mission-and-shared-values | X29: Not planning | AC29: Formal | AD29: https://aptrust.org/resources/policies/#governance-manual
A30: Database Information System | B30: University Library of Regensburg | C30: https://dbis.ur.de/?lang=en | D30: DE | E30: Discovery system | Index or directory | F30: https://github.com/ub-regensburg/dbis | G30: Implemented/available | H30: https://www.ur-library.de/en/ezb-dbis-advisory-board/ | I30: Implemented/available | J30: The EZB-DBIS Advisory Board represents the wishes and requirements of the participating institutions. The advisory board members advise the Regensburg University Library on strategic issues, provide suggestions for optimization, and offer broad input for the further development of both the EZB and DBIS services. | K30: https://www.ur-library.de/en/ezb-dbis-advisory-board/ | L30: Advisory board or steering committee | P30: Unknown | Q30: Unknown | T30: No direct costs | V30: Unknown | X30: Implemented/available | Y30: https://www.uni-regensburg.de/en/data-protection | AC30: Ad hoc
A31: Data Citation Corpus | B31: Make Data Count | C31: https://makedatacount.org/find-a-tool/#section-1 | E31: Discovery system | Open scholarly dataset | F31: https://github.com/Make-Data-Count-Community/corpus-data-file | G31: Implemented/available | H31: https://makedatacount.org/learn-about-us/#section-4 | I31: Not planning | J31: Make Data Count is managed by the Make Data Count Director, a Sustainability Committee, and an Advisory Group. DataCite serves as a the fiscal home of Make Data Count. | L31: None | P31: Not planning | Q31: Considering | T31: No direct costs | V31: Not planning | X31: Implemented/available | Y31: https://makedatacount.org/privacy-policy/ | Z31: Principles for Open Scholarly Infrastructure (POSI) | AC31: Ad hoc
A32: DataCite | B32: DataCite | C32: https://datacite.org/ | D32: DE | E32: Discovery system | Persistent identifier service | F32: https://github.com/datacite | G32: Implemented/available | H32: https://datacite.org/governance/ | I32: Implemented/available | J32: <p>DataCite is <a href="https://datacite.org/governance/" target="_blank">governed by</a> its members and Executive Board.</p> | K32: https://datacite.org/governance/ | L32: Advisory board or steering committee | P32: Implemented/available | Q32: In progress | T32: Implemented/available | U32: https://datacite.org/fee-model/ | V32: Implemented/available | W32: https://datacite.org/commitment-to-equity-and-inclusion/ | X32: Implemented/available | Y32: https://datacite.org/privacy-policy/ | AC32: Formal | AD32: https://datacite.org/wp-content/uploads/2023/06/Statutes_26April2022.pdf
A33: Data Stewardship Wizard | B33: DSW Team | C33: https://ds-wizard.org/ | D33: CZ | E33: Data management planning tool or service | F33: https://github.com/ds-wizard | G33: Implemented/available | H33: https://ds-wizard.org/about | I33: Not planning | J33: Data Stewardship Wizard is hosted by the Czech Technical University in Prague / ELIXIR-CZ. | L33: Advisory board or steering committee | P33: Not planning | Q33: In progress | T33: No direct costs | V33: Implemented/available | W33: https://discord.com/channels/693010138302513174/1102900416783597620 | X33: Not planning | Z33: FAIR Guiding Principles for Scientific Data Management and Stewardship | AC33: Ad hoc
A34: Dataverse | B34: Harvard University Institute for Quantitative Social Science (IQSS) | C34: https://dataverse.org/ | D34: US | E34: Repository software | F34: https://github.com/IQSS/dataverse | G34: Implemented/available | H34: https://github.com/gdcc | I34: Unknown | J34: <p>Dataverse is developed at <a href="https://www.iq.harvard.edu/about" target="_blank">Harvard's Institute for Quantitative Social Science (IQSS)</a>, along with many collaborators and contributors worldwide. Harvard has <a href="https://www.harvard.edu/about/leadership-and-governance/" target="_blank">two governing boards</a>, the Board of Overseers and the Harvard Corporation. There is also a <a href="https://github.com/gdcc" target="_blank">Global Dataverse Community Consortium</a>.</p> | L34: None | P34: Unknown | Q34: In progress | T34: No direct costs | V34: Implemented/available | W34: https://edib.harvard.edu/ | X34: Implemented/available | Y34: https://support.dataverse.harvard.edu/harvard-dataverse-privacy-policy | AC34: Ad hoc
A35: DLCM Backend | B35: DLCM Technology | C35: https://gitlab.unige.ch/dlcm/community/dlcm-backend | D35: CH | E35: Archive information management system | Digital preservation system | F35: https://gitlab.unige.ch/dlcm/community/dlcm-backend | G35: Implemented/available | H35: https://olos.swiss/about-us | I35: Not planning | L35: Advisory board or steering committee | O35: Advisory board of OLOS association | P35: Not planning | Q35: Considering | T35: Implemented/available | U35: https://olos.swiss/pricing | V35: Not planning | X35: Considering | Z35: FAIR Guiding Principles for Scientific Data Management and Stewardship | AC35: None
A36: DLCM Portal | B36: DLCM Technology | C36: https://gitlab.unige.ch/dlcm/ui/dlcm-portal | D36: CH | E36: Archive information management system | Digital preservation system | Software preservation service | F36: https://gitlab.unige.ch/dlcm/ui/dlcm-portal | G36: Implemented/available | H36: https://olos.swiss/about-us | I36: Not planning | L36: Advisory board or steering committee | O36: Advisory board of OLOS association | P36: Not planning | Q36: Considering | T36: Implemented/available | U36: https://olos.swiss/pricing | V36: Not planning | X36: Considering | Z36: FAIR Guiding Principles for Scientific Data Management and Stewardship | AC36: None
A37: DMP Tool | B37: California Digital Library | C37: https://dmptool.org/ | D37: US | E37: Data management planning tool or service | F37: https://github.com/cdluc3/dmptool/wiki | G37: Not planning | I37: Not planning | J37: [Please fill in] | L37: None | P37: Not planning | Q37: Implemented/available | S37: Our tool or project | T37: No direct costs | V37: Not planning | X37: Implemented/available | Y37: https://dmptool.org/terms | AC37: None
A38: DOAJ (Directory of Open Access Journals) | B38: DOAJ Foundation | C38: https://doaj.org/ | D38: DK | E38: Discovery system | Index or directory | Open scholarly dataset | F38: https://github.com/DOAJ | G38: Implemented/available | H38: https://doaj.org/about/advisory-board-council/ | I38: Implemented/available | J38: <p>DOAJ is an independent organisation run and managed by the DOAJ Foundation, a non-profit community-governed foundation based in Denmark . DOAJ has a <a href="https://doaj.org/about/advisory-board-council/" target="_blank">Board of Directors and an Advisory Board</a>, the members of which carry out their duties voluntarily. </p> | K38: https://doaj.org/about/advisory-board-council/ | L38: Advisory board or steering committee | Other | M38: Foundation Board & Advisory Board | P38: Implemented/available | Q38: Implemented/available | S38: Our website | T38: Implemented/available | U38: https://doaj.org/support/ | V38: Implemented/available | W38: https://doaj.org/about/#diversity-equity-and-inclusion | X38: Implemented/available | Y38: https://doaj.org/privacy/ | Z38: FOREST Framework for Values-Driven Scholarly Communication | Helsinki Initiative on Multilingualism | Joint Statement of Principles of the Coalition for Diversity and Inclusion in Scholarly Communication (C4DISC) | Principles for Open Scholarly Infrastructure (POSI) | San Francisco Declaration on Research Assessment (DORA) | AC38: Formal | AD38: https://doaj.org/about/advisory-board-council/
A39: dokieli | B39: dokieli | C39: https://dokie.li/ | E39: Annotations system | Authoring tool | Informal scholarly communications | F39: https://github.com/linkeddata/dokieli | G39: Unknown | I39: Unknown | J39: <p>dokieli is a decentralised article authoring, annotation, and social notifcation tool. No governance is known of at this time. </p> | P39: Unknown | Q39: Implemented/available | R39: https://dokie.li/docs#accessibility-statement | T39: No direct costs | V39: Unknown | X39: Not applicable | AC39: None
A40: Dryad | B40: Dryad | C40: https://datadryad.org/ | D40: US | E40: Repository service | F40: https://github.com/CDL-Dryad/dryad-app | G40: Implemented/available | H40: https://datadryad.org/stash/about#our-board | I40: Implemented/available | J40: <p>Dryad is a not-for-profit membership organization, recognized as a 501(c)3 by the U.S. Internal Revenue Service. Dryad members nominate and elect the <a href="https://datadryad.org/stash/about#our-board" target="_blank">Board of Directors</a>, twelve individuals from the stakeholder community who provide strategic planning, fiscal oversight, and oversee the position of the Executive Director.</p> | K40: https://blog.datadryad.org/category/governance/ | L40: Other | P40: Implemented/available | Q40: Implemented/available | S40: Our website | T40: Implemented/available | U40: https://datadryad.org/stash/join_us#fees | V40: In progress | X40: Implemented/available | Y40: https://datadryad.org/stash/terms#privacy | AC40: Formal | AD40: https://datadryad.org/docs/DryadBylaws.pdf
A41: DSpace | B41: Lyrasis | C41: https://dspace.org/ | D41: US | E41: Repository software | F41: https://github.com/DSpace/DSpace | G41: Implemented/available | H41: https://dspace.org/governance/ | I41: Implemented/available | J41: <p><a href="https://wiki.lyrasis.org/display/DSPACE/Project+Governance" target="_blank">DSpace governance</a> is based on a representative, community-based membership model incrementally rewarding members who have made the greatest commitments to the project. It consists of a Leadership Group, Steering Group, and Working Groups.</p> | K41: https://wiki.lyrasis.org/display/DSPACE/Leadership+Group | L41: Advisory board or steering committee | P41: Implemented/available | Q41: Implemented/available | R41: https://dspace.org/accessibility/ | S41: Our tool or project | T41: Implemented/available | U41: https://dspace.org/membership/ | V41: Implemented/available | W41: https://lyrasis.org/job-bank/ | X41: Implemented/available | Y41: https://demo.dspace.org/info/privacy | Z41: It Takes a Village Open Source Software Sustainability toolkit | AC41: Formal | AD41: https://dspace.org/governance
A42: DuraCloud | B42: Lyrasis | C42: https://lyrasis.org/duracloud/ | D42: US | E42: Digital preservation service | Digital preservation system | Digital preservation tool | F42: https://github.com/duracloud/duracloud | G42: Unknown | I42: Not planning | L42: None | O42: N/A | P42: Not planning | Q42: Unknown | T42: Not planning | V42: Unknown | X42: Unknown
A43: Episciences | B43: Center for Direct Scientific Communication (CCSD) | C43: https://www.episciences.org/ | D43: FR | E43: Peer review system | Publishing system | Submissions system | F43: https://github.com/CCSDForge/episciences | G43: Implemented/available | H43: https://www.ccsd.cnrs.fr/en/governance/ | I43: Considering | L43: Multi-board governance | O43: <strong>The Steering Committee</strong> - Defines the global strategy of the CCSD and arbitrates the priority axes according to the proposals of the orientation committee; - Approves the budget and overall resources of the CCSD; ensures the coherence of the pricing policy related to the HAL portals; - Validates the annual activity report and the financial statement of the CCSD; - Proposes and deliberate on the admission of a new supervising body; - Appoints the director of the CCSD; - Appoints the members of the international scientific council. <strong>Orientation Committee</strong> - Proposes scientific and technical orientations to the Steering committee; - Centralizes and prioritizes the needs of all users. | P43: Implemented/available | Q43: In progress | T43: No direct costs | V43: Considering | X43: Implemented/available | Y43: https://www.episciences.org/privacy-and-personal-data/ | Z43: FAIR Guiding Principles for Scientific Data Management and Stewardship | AC43: Ad hoc | AD43: https://www.episciences.org/governance/
A44: EPrints | B44: EPrints Services | C44: https://www.eprints.org/ | D44: GB | E44: Repository software | F44: https://github.com/eprints/eprints3.4 | G44: In progress | I44: In progress | O44: Unknown | P44: Unknown | Q44: In progress | T44: No direct costs | V44: Unknown | X44: Unknown
A45: Érudit | B45: Érudit | C45: https://www.erudit.org/ | D45: CA | E45: Discovery system | Publishing system | Repository software | F45: https://github.com/erudit/eruditorg | G45: Implemented/available | H45: https://apropos.erudit.org/direction-et-conseils/?lang=en | I45: Implemented/available | J45: <p>Érudit is a consortium comprised of three Canadian universities: <a href="https://www.umontreal.ca/en/" target="_blank">Université de Montréal</a>, <a href="https://www.ulaval.ca/en" target="_blank">Université Laval</a>, and <a href="https://uqam.ca/" target="_blank">Université du Québec à Montréal</a>. It is governed by representatives from the research, university library, and scholarly publishing sectors. Its <a href="https://apropos.erudit.org/direction-et-conseils/?lang=en" target="_blank">governed by </a>a governing board and scientific director. </p> | K45: https://apropos.erudit.org/rapports-annuels/?lang=en | L45: Multi-board governance | P45: Implemented/available | Q45: Implemented/available | R45: https://apropos.erudit.org/accessibility-statement/?lang=en | S45: Our website | T45: No direct costs | V45: Implemented/available | W45: https://apropos.erudit.org/equity-diversity-inclusion/?lang=en | X45: Implemented/available | Y45: https://www.iubenda.com/privacy-policy/79766356 | AC45: Formal | AD45: https://apropos.erudit.org/direction-et-conseils/?lang=en
A46: Europe PMC | B46: EMBL European Bioinformatics Institute (EMBL-EBI) | C46: https://europepmc.org/ | D46: GB | E46: Digital preservation system | Discovery system | Repository service | F46: https://github.com/EuropePMC | G46: Implemented/available | H46: https://europepmc.org/Governance | I46: Implemented/available | J46: <p>Europe PMC is developed by the <a href="https://www.ebi.ac.uk/" target="_blank">EMBL-EBI</a> (European Bioinformatics Institute), an outstation of the EMBL. Europe PMC is <a href="https://europepmc.org/Governance" target="_blank">governed by</a> an international, independent Scientific Advisory Board that advises the PI of the Europe PMC grant and the Directors of the EMBL-EBI. The Europe PMC Funders are represented by the Funder Committee.</p> | K46: https://europepmc.org/Governance | L46: Advisory board or steering committee | P46: Implemented/available | Q46: Implemented/available | R46: https://europepmc.org/Accessibility | S46: Our website | T46: No direct costs | V46: Implemented/available | W46: https://www.ebi.ac.uk/about/equality-in-science | X46: Implemented/available | Y46: https://europepmc.org/PrivacyNotice | AC46: Formal | AD46: https://europepmc.org/Governance
A47: FAIR Wizard | B47: Codevence Solution s.r.o. | C47: https://fair-wizard.com/ | D47: CZ | E47: Data management planning tool or service | G47: In progress | I47: Not planning | J47: FAIR Wizard is a product of Codevence Solutions s.r.o., a company based in the Czech Republic. | L47: None | N47: Provider | P47: Not planning | Q47: In progress | T47: Implemented/available | U47: https://fair-wizard.com/plans | V47: Considering | X47: Implemented/available | Y47: https://fair-wizard.com/static/documents/privacy-policy.pdf | Z47: FAIR Guiding Principles for Scientific Data Management and Stewardship | AC47: Ad hoc
A48: Fedora | B48: Lyrasis | C48: https://fedorarepository.org/ | D48: US | E48: Repository software | F48: https://github.com/fcrepo/fcrepo | G48: Implemented/available | H48: https://wiki.lyrasis.org/display/FF/Project+Governance | I48: Implemented/available | J48: Fedora is community-owned, community-supported and community-governed. The Fedora Governance Group is responsible for the strategic leadership of the Fedora Program, its community, and associated technology. This group is responsible for leading the overall Vision & Strategy. Governance details can be found here: <a href="https://fedorarepository.org/governance/" target="_blank">https://fedorarepository.org/governance/</a> | K48: https://wiki.lyrasis.org/display/FF/Meetings | L48: Advisory board or steering committee | N48: Other | O48: Board is that of the Fedora Community | P48: Implemented/available | Q48: Considering | S48: Our tool or project | Our website | T48: Implemented/available | U48: https://fedorarepository.org/membership | V48: Implemented/available | W48: https://lyrasis.org/job-bank/ | X48: Implemented/available | Y48: https://fedorarepository.org/privacy-policy/ | Z48: It Takes a Village Open Source Software Sustainability toolkit | AC48: Formal | AD48: https://wiki.lyrasis.org/display/FF/Project+Governance
A49: fido | B49: Open Preservation Foundation | C49: https://openpreservation.org/tools/fido | D49: GB | E49: Digital preservation tool | F49: https://github.com/openpreserve/fido | G49: Implemented/available | H49: https://openpreservation.org/about-old/board-of-directors/ | I49: Considering | J49: Fido is a project of the Open Preservation Foundation a company, limited by guarantee, registered in England and Wales and Stichting Open Preservation, registered as a foundation with the Kamer van Koophandel. | L49: Advisory board or steering committee | N49: Provider | P49: Unknown | Q49: Considering | T49: No direct costs | V49: In progress | X49: Implemented/available | Y49: https://openpreservation.org/privacy-policy/ | AC49: Formal
A50: Fulcrum | B50: Michigan Publishing | C50: https://www.fulcrum.org/ | D50: US | E50: Publishing system | F50: https://github.com/mlibrary/heliotrope | G50: Implemented/available | H50: https://www.fulcrum.org/about/ | I50: In progress | J50: <p><a href="https://www.fulcrum.org/about/" target="_blank">Fulcrum</a> has been developed by a group of campus-based publishers working closely with disciplinary faculty and information science specialists, with <a href="https://www.fulcrum.org/partner-with-us/" target="_blank">publishing services</a> provided in collaboration with <a href="https://services.publishing.umich.edu/" target="_blank">Michigan Publishing</a>, an arm of the <a href="https://www.lib.umich.edu/" target="_blank">University of Michigan Library</a>, governed by the <a href="https://regents.umich.edu/" target="_blank">Regents of the University of Michigan</a>. </p> | L50: Other | P50: Unknown | Q50: Implemented/available | R50: https://www.fulcrum.org/accessibility/ | T50: Implemented/available | U50: https://www.fulcrum.org/partner-with-us/ | V50: Implemented/available | W50: https://www.lib.umich.edu/about-us/about-library/diversity-equity-inclusion-and-accessibility | X50: Implemented/available | Y50: https://www.fulcrum.org/privacy/ | AC50: Ad hoc
A51: Galaxy | B51: The Galaxy community | C51: https://galaxyproject.org/ | E51: Computing framework | Discovery system | F51: https://github.com/galaxyproject/ | G51: Implemented/available | H51: https://galaxyproject.org/community/governance/ | I51: Implemented/available | K51: https://galaxyproject.org/community/wg/ | L51: Multi-board governance | O51: Collecting feedback from the community and steering the roadmap process. | P51: Implemented/available | Q51: In progress | T51: No direct costs | V51: Implemented/available | W51: https://galaxyproject.org/community/coc/ | X51: Implemented/available | Y51: https://usegalaxy-eu.github.io/gdpr/ | AC51: Formal | AD51: https://galaxyproject.org/community/governance/
A52: GeoServer | B52: Open Source Geospatial Foundation | C52: https://geoserver.org | E52: Geospatial data tool or platform | F52: https://github.com/geoserver/geoserver | G52: Implemented/available | H52: https://docs.geoserver.org/latest/en/developer/policies/psc.html | I52: Implemented/available | J52: GeoServer is a volunteer community hosted by the Open Source Geospatial Foundation (OSGeo). | K52: https://github.com/geoserver/geoserver/wiki/Proposals | L52: Advisory board or steering committee | N52: Provider | P52: Implemented/available | Q52: Not planning | T52: No direct costs | V52: Not planning | X52: Not planning | Z52: Contributor Covenant Code of Conduct for Open Source and Other Digital Commons Communities | AC52: Formal | AD52: https://docs.geoserver.org/latest/en/developer/policies/index.html
A53: Hyku | B53: Samvera | C53: https://hyku.samvera.org/ | D53: US | E53: Repository software | F53: https://github.com/samvera/hyku | G53: Implemented/available | H53: https://samvera.atlassian.net/wiki/spaces/samvera/pages/1387986974/Samvera+Bylaws | I53: Implemented/available | J53: <p>Hyku is a project of Samvera, a distinct series entity hosted by <a href="https://www.oasis-open.org/" target="_blank">OASIS Open</a>. Samvera is <a href="https://samvera.atlassian.net/wiki/spaces/samvera/pages/1387986974/Samvera+Bylaws" target="_blank">governed by</a> a Board of Directors. </p> | K53: https://samvera.atlassian.net/wiki/spaces/samvera/pages/426512038/Notes+from+Samvera+Board+meetings+and+calls | L53: Advisory board or steering committee | P53: Implemented/available | Q53: Implemented/available | R53: https://repo.samvera.org/concern/generic_works/19cc96b4-6e98-4dba-b908-91e3439cad44 | S53: Our tool or project | T53: No direct costs | V53: Considering | X53: Implemented/available | Y53: https://repo.samvera.org/concern/generic_works/66c8c363-ac35-4e65-bb3d-2631b7c80ff6?locale=en | Z53: COAR Next Generation Repositories Principles | It Takes a Village Open Source Software Sustainability toolkit | AC53: Formal | AD53: https://samvera.atlassian.net/wiki/spaces/samvera/pages/1387986974/Samvera+Bylaws
A54: Hyrax | B54: Samvera | C54: https://hyrax.samvera.org/ | D54: US | E54: Repository software | F54: https://github.com/samvera/hyrax | G54: Implemented/available | H54: https://samvera.atlassian.net/wiki/spaces/samvera/pages/1387986974/Samvera+Bylaws | I54: Implemented/available | J54: Hyrax is a project of the Samvera Community. Samvera operates as a distinct series entity hosted by the OASIS Open Development Foundation, LLC, under the Charter and Series Agreement. | K54: https://samvera.atlassian.net/wiki/spaces/samvera/pages/426512038/Notes+from+Samvera+Board+meetings+and+calls | L54: Advisory board or steering committee | N54: Provider | P54: Implemented/available | Q54: In progress | T54: No direct costs | V54: In progress | X54: In progress | Z54: It Takes a Village Open Source Software Sustainability toolkit | AC54: Formal | AD54: https://samvera.atlassian.net/wiki/spaces/samvera/pages/1387986974/Samvera+Bylaws
A55: IIIF | B55: IIIF Consortium | C55: https://iiif.io/ | D55: US | E55: Standard, specification or protocol | F55: https://github.com/IIIF | G55: Implemented/available | H55: https://iiif.io/community/consortium/consortium_committees/ | I55: Implemented/available | J55: <p>IIIF is <a href="https://iiif.io/community/consortium/consortium_committees" target="_blank">governed by</a> an Executive Committee and an Operating Committee. </p> | K55: https://iiif.io/community/consortium/mou/ | L55: Advisory board or steering committee | P55: Implemented/available | Q55: Not applicable | T55: Implemented/available | U55: https://iiif.io/community/consortium/join/ | V55: Implemented/available | W55: https://iiif.io/community/consortium/next_steps/ | X55: Implemented/available | Y55: https://iiif.io/privacy/ | AC55: Formal | AD55: https://iiif.io/community/coordinating-committee/
A56: ImpactU | B56: Universidad de Antioquia and other Colombian universities | C56: https://impactu.colav.co/ | D56: CO | E56: Open scholarly dataset | Research profiling system | F56: https://github.com/colav/impactu | G56: Unknown | I56: Unknown | J56: The initiative is coordinated by the Collaborative Laboratory of Computational Social Sciences and Digital Humanities (CoLaV) at the University of Antioquia in collaboration with the University of Valle, the Externado University of Colombia, and the Autonomous Latin American University. | L56: None | P56: Unknown | Q56: Unknown | T56: No direct costs | V56: Unknown | X56: Unknown | AC56: None
A57: International Generic Sample Number (IGSN) | B57: International Generic Sample Number Organization e.V. | C57: https://ev.igsn.org | D57: DE | E57: Persistent identifier service | F57: https://github.com/IGSN | G57: Implemented/available | H57: https://ev.igsn.org/membership/igsn-statutes-en | I57: In progress | L57: Advisory board or steering committee | O57: The Executive Board is responsible for all affairs of the Association to the extent not entrusted to any other constituent body of the Association by its statutes. Its responsibilities include preparing and convening the General Assembly, appointing working groups, implementing resolutions of the General Assembly, accounting, etc. | P57: Implemented/available | Q57: In progress | T57: Implemented/available | U57: https://datacite.org/fee-model/ | V57: Considering | X57: Considering | AD57: https://ev.igsn.org/membership/igsn-statutes-en
A58: InvenioRDM | B58: CERN | C58: https://inveniosoftware.org/products/rdm/ | E58: Repository software | F58: https://github.com/inveniosoftware | G58: Implemented/available | H58: https://inveniosoftware.org/governance/ | I58: In progress | J58: <p>Invenio is a community-driven effort, <a href="https://inveniosoftware.org/governance/" target="_blank">governed by</a> <a href="https://home.cern/" target="_blank">CERN</a> for the benefit of the community.</p> | L58: Advisory board or steering committee | P58: Implemented/available | Q58: In progress | T58: No direct costs | V58: Implemented/available | W58: https://inveniosoftware.org/governance/ | X58: Not applicable | AC58: Formal | AD58: https://inveniosoftware.org/governance/
A59: iRODS | B59: Renaissance Computing Institute (RENCI) | C59: https://irods.org/ | D59: US | E59: Data management planning tool or service | Digital preservation system | Discovery system | F59: https://github.com/irods | G59: Implemented/available | H59: https://irods.org/uploads/2014/09/bylaws_v113015.pdf | I59: Not planning | J59: Governance is determined by Consortium Membership. | L59: Advisory board or steering committee | M59: In addition to the Executive Committee (which makes decisions on budgets and by laws), there is an Advisory Board that is advisory/strategic: https://irods.org/advisory-board/ | N59: Other | O59: Executive Board members are expected to aid the Consortium through the following actions: - Aiding in fundraising, public relations, and acquisition of new Consortium Members; - Making amendments and alterations to the Consortium Bylaws; - Providing oversight and approval of Consortium activities, staffing, budgets, and deliverables as detailed in the Bylaws. | P59: Implemented/available | Q59: Not planning | T59: Implemented/available | U59: https://irods.org/uploads/members_benefit_sheet.pdf | V59: Not planning | X59: Not planning | Z59: FAIR Guiding Principles for Scientific Data Management and Stewardship | AC59: Ad hoc | AD59: https://irods.org/uploads/2014/09/bylaws_v113015.pdf
A60: Islandora | B60: Islandora Foundation | C60: https://www.islandora.ca/ | D60: CA | E60: Authoring tool | Digital asset management system | F60: https://github.com/islandora | G60: Implemented/available | H60: https://www.islandora.ca/governance | I60: Implemented/available | J60: <p>The Islandora Foundation maintains a <a href="https://github.com/Islandora/islandora-community/wiki/Board-of-Directors-%28BOD%29" target="_blank">Board</a> and <a href="https://islandora.webflow.io/by-laws" target="_blank">By-laws</a> from which the Islandora Community grows. The Board is elected biannually from the <a href="https://github.com/Islandora/islandora-community/wiki/Leadership-Group-%28LG%29" target="_blank">Islandora Leadership Group</a>. </p> | K60: https://github.com/Islandora/islandora-community/wiki/Board-of-Directors-%28BOD%29 | L60: Advisory board or steering committee | P60: Implemented/available | Q60: Implemented/available | R60: https://islandora.github.io/documentation/user-documentation/accessibility/ | S60: Our tool or project | T60: No direct costs | V60: Implemented/available | W60: https://www.islandora.ca/about | X60: Unknown | AC60: None
A61: Janeway | B61: Open Library of Humanities | C61: https://janeway.systems/ | D61: GB | E61: Publishing system | F61: https://github.com/birkbeckctp/ | G61: In progress | I61: In progress | J61: <p>Janeway is a not for profit making organization, <a href="https://janeway.systems/" target="_blank">developed</a> at the Centre for Technology and Publishing, Birkbeck, University of London, and the Open Library of Humanities, UK. For more on Birkbeck's governance, <a href="https://www.bbk.ac.uk/about-us/governance" target="_blank">click here</a>. Additional governance development is in progress.</p> | L61: Advisory board or steering committee | P61: Unknown | Q61: Implemented/available | S61: Our website | T61: Implemented/available | U61: https://janeway.systems/hosting | V61: Implemented/available | W61: https://www.bbk.ac.uk/about-us/equality/statement | X61: Implemented/available | Y61: https://www.openlibhums.org/site/privacy/ | AC61: Ad hoc
A62: JHOVE | B62: Open Preservation Foundation | C62: https://jhove.openpreservation.org/ | D62: GB | E62: Computing library | Digital preservation tool | F62: https://github.com/openpreserve/jhove | G62: Implemented/available | H62: https://openpreservation.org/about/board-of-directors/ | I62: Not planning | J62: The OPF operates as an independent, not-for-profit membership organization. | L62: Advisory board or steering committee | O62: To oversee the overall strategic direction and sustainability of the Foundation. The Board are drawn from our membership and are expected to approve significant business decisions, ensure compliance with laws and regulations, monitoring financial performance, and appointing and evaluating senior management. While they primarily focusing on long-term vision and not day-to-day operations, their purview is important to our strategic direction. | P62: Not planning | Q62: In progress | T62: No direct costs | V62: In progress | X62: Implemented/available | Y62: https://openpreservation.org/privacy-policy/ | AC62: Ad hoc
A63: LA Referencia | B63: LA Referencia | C63: https://www.lareferencia.info | D63: UY | E63: Discovery system | F63: https://github.com/lareferencia | G63: Implemented/available | H63: https://www.lareferencia.info/en/institutional/partners-and-representatives | I63: Implemented/available | J63: <p>La Referencia is <a href="https://www.lareferencia.info/en/institutional/partners-and-representatives" target="_blank">governed by</a> a Board of Directors, network of Political Authorities from node countries, and a Technical Committee. </p> | K63: https://www.lareferencia.info/es/recursos/documentos/actas-consejo-directivo | L63: Multi-board governance | P63: Unknown | Q63: Considering | T63: No direct costs | V63: Considering | X63: In progress | AC63: Formal
A64: Manifold | B64: Manifold Digital Services | C64: https://manifoldapp.org/ | D64: US | E64: Publishing system | F64: https://github.com/ManifoldScholar/manifold | G64: Unknown | I64: Unknown | J64: <p>Manifold is a collaboration between the <a href="https://www.gc.cuny.edu/" target="_blank">CUNY Graduate Center</a>, the <a href="https://www.upress.umn.edu/" target="_blank">University of Minnesota Press</a>, and <a href="https://castironcoding.com/" target="_blank">Cast Iron Coding</a>. Additional governance information was not provided, and will be updated as made available. </p> | L64: Advisory board or steering committee | P64: Unknown | Q64: Implemented/available | S64: Our tool or project | T64: Implemented/available | U64: https://manifoldapp.org/services | V64: In progress | X64: Unknown | AC64: None
A65: medRxiv | B65: Cold Spring Harbor Laboratory | C65: https://www.medrxiv.org/ | D65: US | E65: Repository service | G65: In progress | I65: Not planning | J65: <p>medRxiv is housed at <a href="https://www.cshl.edu/" target="_blank">Cold Spring Harbor Laboratory</a>, which is governed by a <a href="https://www.cshl.edu/about-us/board-of-trustees/" target="_blank">Board of Trustees</a>. Additional governance development is in progress.</p> | L65: Advisory board or steering committee | P65: Unknown | Q65: Considering | T65: No direct costs | V65: In progress | X65: Implemented/available | Y65: http://www.cshlp.org/misc/preprints_privacy_policy/ | Z65: COAR Next Generation Repositories Principles | San Francisco Declaration on Research Assessment (DORA) | AC65: Ad hoc
A66: Metadata Encoding and Transmission Standard (METS) | B66: METS Editorial Board | C66: https://www.loc.gov/standards/mets/ | D66: US | E66: Standard, specification or protocol | F66: https://github.com/mets | G66: Implemented/available | H66: https://www.loc.gov/standards/mets/mets-board.html | I66: Implemented/available | J66: The METS schema is maintained by the METS Editorial Board, an international group of volunteers who represent important communities of interest for METS. | K66: https://github.com/mets/METS-board/wiki/01-Meeting-Agendas-and-Notes | L66: Advisory board or steering committee | O66: The METS Editorial Board is responsible for maintenance of the METS schema and its documentation and for engaging with the METS user community. | P66: Implemented/available | Q66: Not planning | T66: No direct costs | V66: Not planning | X66: Not planning | AC66: Ad hoc | AD66: https://www.loc.gov/standards/mets/mets-boardprocedures.html
A67: Mirador | B67: Project Mirador | C67: https://projectmirador.org/ | E67: Annotations system | Media viewer/player | F67: https://github.com/projectmirador/mirador | G67: Considering | I67: Implemented/available | J67: <p>The provider is considering additional governance development. </p> | K67: https://docs.google.com/document/d/1wWozmLxUsN7QRWzekiIMjjuShhDIsJw0P0lIaiARSa8/edit | L67: None | P67: Unknown | Q67: Implemented/available | R67: https://github.com/ProjectMirador/mirador/wiki/M3-Accessibility-Guidelines-for-Contributors | S67: Our tool or project | T67: Implemented/available | V67: Implemented/available | W67: https://github.com/cul/mirador/blob/master/CODE_OF_CONDUCT.md#inclusivity | X67: Unknown | AC67: Ad hoc
A68: Mukurtu CMS | B68: Center for Digital Scholarship and Curation | C68: https://mukurtu.org/ | D68: US | E68: Archive information management system | Digital asset management system | F68: https://github.com/MukurtuCMS/mukurtucms | G68: In progress | I68: In progress | J68: <p>Mukurtu CMS is managed by the <a href="https://cdsc.libraries.wsu.edu/" target="_blank">Center for Digital Scholarship and Curation</a> at Washington State University, which is governed by a <a href="https://policies.wsu.edu/prf/index/manuals/board-of-regents-policy-manual/" target="_blank">Board of Regents</a>. Additional governance development is in progress.</p> | L68: Advisory board or steering committee | P68: Unknown | Q68: In progress | T68: Implemented/available | U68: https://mukurtu.org/get-mukurtu/ | V68: Implemented/available | W68: https://mukurtu.org/about/ | X68: Implemented/available | Y68: https://mukurtu.org/privacy/ | AC68: Ad hoc
A69: MyCoRe | B69: MyCoRe Community | C69: https://www.mycore.de | D69: DE | E69: Digital asset management system | Digital library, collection or exhibit platform | Repository software | F69: https://github.com/MyCoRe-Org/mycore | G69: Not planning | I69: Not planning | L69: None | O69: n.a. | P69: Not planning | Q69: Implemented/available | R69: https://www.mycore.de/en/site/accessibility/ | S69: Our website | T69: No direct costs | V69: Unknown | X69: Implemented/available | Y69: https://www.mycore.de/en/site/privacy/ | AC69: Ad hoc
A70: NumPy | B70: NumPy Community | C70: https://numpy.org/ | E70: Computing library | Standard, specification or protocol | F70: https://github.com/numpy/numpy | G70: Implemented/available | H70: https://numpy.org/devdocs/dev/governance/governance.html#steering-council | I70: Implemented/available | K70: https://github.com/numpy/archive | L70: Advisory board or steering committee | O70: The governing board makes decisions mainly on administrative issues, such as how funds should be spent, who serves on the steering council, and whom to grant commit rights. | P70: Implemented/available | Q70: In progress | T70: No direct costs | V70: In progress | X70: Not planning | AC70: Formal | AD70: https://numpy.org/devdocs/dev/governance/index.html
A71: OA.Report | B71: OA.Works | C71: https://oa.report/ | D71: US | E71: Open access or subscription management tool | Research profiling system | F71: https://github.com/oaworks/oa-report | G71: Implemented/available | H71: https://oa.works/about/governance/ | I71: Implemented/available | K71: https://drive.google.com/drive/folders/1BRmxtsdw5_IIcyRCFoLPSNLs070vbl3T?usp=sharing | L71: Advisory board or steering committee | O71: Our Articles of Governance states "The Advisory Committee has the power to dictate all activities and affairs of OA.Works through a vote." This provides the committee the broadest possible powers to note only advise, but to bind OA.Work's to act in the communities interests. | P71: Implemented/available | Q71: Implemented/available | R71: https://about.oa.report/help/accessibility-statement | T71: In progress | V71: Considering | X71: Implemented/available | Y71: https://oa.works/policies/privacy/ | Z71: Principles for Open Scholarly Infrastructure (POSI) | AC71: Formal | AD71: https://oa.works/about/governance/articles-of-governance/
A72: OA Switchboard | B72: Stichting OA Switchboard | C72: https://www.oaswitchboard.org/ | D72: NL | E72: Open access or subscription management tool | F72: https://bitbucket.org/oaswitchboard/api/src/master/ | G72: Implemented/available | H72: https://www.oaswitchboard.org/governance | I72: Implemented/available | J72: <p>OA Switchboard is governed by a <a href="https://www.oaswitchboard.org/governance" target="_blank">Board of Directors</a>, and supported additionally by a <a href="https://www.oaswitchboard.org/governance" target="_blank">Client Advisory Board</a>, <a href="https://www.oaswitchboard.org/governance" target="_blank">Advisory Group</a>, and <a href="https://www.oaswitchboard.org/governance" target="_blank">Working Groups</a>. </p> | K72: https://www.oaswitchboard.org/governance | P72: Implemented/available | Q72: Unknown | T72: Implemented/available | U72: https://www.oaswitchboard.org/faq | V72: Implemented/available | W72: https://www.oaswitchboard.org/governance | X72: Implemented/available | Y72: https://www.oaswitchboard.org/privacy-statement | AC72: Formal | AD72: https://www.oaswitchboard.org/governance
A73: Omeka | B73: Digital Scholar | C73: https://omeka.org/ | D73: US | E73: Digital library, collection or exhibit platform | F73: https://github.com/omeka | G73: Implemented/available | H73: https://digitalscholar.org/assets/downloads/Corporation%20for%20Digital%20Scholarship%20%E2%80%93%20Articles%20of%20Incorporation.pdf | I73: In progress | J73: Omeka is a project of <a href="https://digitalscholar.org/" target="_blank">Digital Scholar</a>, a US-based non-stock corporation that operates following the guidelines laid out by the IRS for 501c3 organizations. See the articles of incorporation, bylaws, and governance documents on the Digital Scholar website. | L73: Advisory board or steering committee | P73: Implemented/available | Q73: Implemented/available | S73: Our tool or project | T73: Implemented/available | U73: https://www.omeka.net/signup | V73: In progress | W73: https://digitalscholar.org/assets/downloads/Corporation%20for%20Digital%20Scholarship%20%E2%80%93%20Governance%20Policies.pdf | X73: Implemented/available | Y73: https://forum.omeka.org/privacy | AC73: Ad hoc | AD73: https://digitalscholar.org/assets/downloads/Corporation%20for%20Digital%20Scholarship%20%E2%80%93%20Articles%20of%20Incorporation.pdf
A74: OpenAIRE Graph | B74: OpenAIRE | C74: https://graph.openaire.eu/ | E74: Discovery system | Open scholarly dataset | F74: https://code-repo.d4science.org/D-Net/dnet-hadoop | G74: Implemented/available | H74: https://www.openaire.eu/organisation-2 | I74: Unknown | L74: Advisory board or steering committee | O74: The Board is essential in shaping OpenAIRE and thereby the OpenAIRE Graph's roadmap and development. They are regularly consulted and their input and decisions are highly valued and respected. | P74: Implemented/available | Q74: Considering | T74: No direct costs | V74: Implemented/available | W74: https://www.openaire.eu/openaire-gep | X74: Implemented/available | Y74: https://www.openaire.eu/privacy-policy | Z74: Principles for Open Scholarly Infrastructure (POSI) | AC74: Formal | AD74: https://www.openaire.eu/organisation-2
A75: OpenAlex | B75: OurResearch | C75: https://openalex.org/ | D75: US | E75: Open scholarly dataset | F75: https://github.com/ourresearch | G75: Implemented/available | H75: https://ourresearch.org/transparency | I75: Not planning | J75: <p>OpenAlex is an initiative of OurResearch, which is <a href="https://ourresearch.org/team" target="_blank">governed by</a> a Board of Directors.</p> | L75: Advisory board or steering committee | P75: Unknown | Q75: Implemented/available | R75: https://ourresearch.org/accessibility | S75: Our website | T75: Implemented/available | U75: https://openalex.org/pricing | V75: Considering | X75: Implemented/available | Y75: https://openalex.org/OpenAlex_privacy_policy.pdf | AC75: Formal
A76: OpenAPC | B76: Bielefeld University | C76: https://openapc.net/ | D76: DE | E76: Open scholarly dataset | F76: https://github.com/OpenAPC/openapc-de | G76: Not planning | I76: Not planning | L76: None | O76: No governing board - not applicable | P76: Not planning | Q76: Not planning | T76: No direct costs | V76: Implemented/available | W76: https://github.com/OpenAPC/openapc-de/blob/master/CONDUCT.md | X76: Not planning | AC76: None
A77: OpenCitations | B77: Research Centre for Open Scholarly Metadata, University of Bologna | C77: https://opencitations.net/ | D77: IT | E77: Open scholarly dataset | F77: https://github.com/opencitations | G77: Implemented/available | H77: https://opencitations.net/governance/ | I77: In progress | J77: For administrative convenience, OpenCitations is managed by the <a href="https://openscholarlymetadata.org/" target="_blank">Research Centre for Open Scholarly Metadata</a> at the <a href="https://www.unibo.it/" target="_blank">University of Bologna</a>. OpenCitations' governance comprises the following bodies: the Directors; the Council, comprising one delegate appointed by each OpenCitations Member; the <a href="https://opencitations.net/about" target="_blank">International Advisory Board</a> elected by the Council, to guide the future developments of OpenCitations strategically; the Management Team. | L77: Advisory board or steering committee | P77: Implemented/available | Q77: Considering | T77: No direct costs | V77: Considering | X77: Implemented/available | Y77: https://opencitations.net/privacy-policy/ | Z77: FAIR Guiding Principles for Scientific Data Management and Stewardship | Principles for Open Scholarly Infrastructure (POSI) | AC77: Formal | AD77: https://opencitations.net/wp-content/uploads/pdf/oc_bodies.pdf
A78: openCost | B78: openCost | C78: https://www.opencost.de | D78: DE | E78: Open scholarly dataset | Standard, specification or protocol | F78: https://github.com/opencost-de/opencost/tree/main/doc | G78: Not planning | I78: Not planning | L78: None | O78: No board structure | P78: Not planning | Q78: Not planning | T78: No direct costs | V78: Not planning | X78: Not planning | Z78: FAIR Guiding Principles for Scientific Data Management and Stewardship
A79: Open Data Editor | B79: Open Knowledge Foundation | C79: https://okfn.org/en/projects/open-data-editor/ | D79: GB | E79: Data collection or management tool | F79: https://github.com/okfn/opendataeditor | G79: Implemented/available | H79: https://okfn.org/en/who-we-are/governance/ | I79: Implemented/available | J79: Open Data Editor is a project of the Open Knowledge Foundation (OKFN), a not-for-profit organization incorporated in England & Wales. | K79: https://okfn.org/en/who-we-are/board/#minutes | L79: Advisory board or steering committee | N79: Provider | P79: Implemented/available | Q79: Considering | T79: No direct costs | V79: Considering | X79: Implemented/available | Y79: https://okfn.org/en/privacy-policy/ | AC79: Formal | AD79: https://okfn.org/en/who-we-are/governance/
A80: OpenEdition | B80: OpenEdition Center, Aix-Marseille University, the EHESS and Avignon University | C80: https://www.openedition.org/ | D80: FR | E80: Discovery system | F80: https://github.com/OpenEdition | G80: Implemented/available | H80: https://www.openedition.org/19221 | I80: In progress | L80: Multi-board governance | P80: Implemented/available | Q80: Considering | R80: https://www.openedition.org/21402 | T80: No direct costs | V80: Considering | X80: Implemented/available | Y80: https://www.openedition.org/19362 | AC80: Formal | AD80: https://www.openedition.org/19221
A81: Open Journal Systems (OJS) | B81: Public Knowledge Project (PKP) | C81: https://pkp.sfu.ca | D81: CA | E81: Publishing system | F81: https://github.com/pkp | G81: Implemented/available | H81: https://pkp.sfu.ca/about/governance/ | I81: Implemented/available | J81: <p>Open Preprint Systems is an initiative of the <a href="https://pkp.sfu.ca/about/governance/" target="_blank">Public Knowledge Project</a> (PKP), a member of the Core Facility Program at <a href="https://www.sfu.ca/" target="_blank">Simon Fraser University</a> since 2022 which operates under the auspices of the Office of the Vice President, Research and International (VPRI) of Simon Fraser University. PKP is additionally guided by an <a href="https://pkp.sfu.ca/about/governance/advisory/" target="_blank">Advisory Committee</a>, <a href="https://pkp.sfu.ca/about/governance/sfu-advisory/" target="_blank">SFU Community Advisory Committee</a>, <a href="https://pkp.sfu.ca/about/governance/technical/" target="_blank">Technical Committee</a>, Members Committee, and a <a href="https://pkp.sfu.ca/about/governance/conduct/" target="_blank">Code of Conduct Committee</a>.</p> | K81: https://pkp.sfu.ca/interest-groups/ | L81: Multi-board governance | P81: Implemented/available | Q81: Implemented/available | R81: https://pkp.sfu.ca/general-accessibility-statement/ | S81: Our tool or project | T81: Implemented/available | U81: https://pkp.sfu.ca/hosting-services/hosting/journals/ | V81: In progress | W81: https://pkp.sfu.ca/code/ | X81: Implemented/available | Y81: https://pkp.sfu.ca/privacy-policy/ | AC81: Formal | AD81: http://www.sfu.ca/policies/gazette/board.html
A82: Open Monograph Press (OMP) | B82: Public Knowledge Project (PKP) | C82: https://pkp.sfu.ca/ | D82: CA | E82: Publishing system | F82: https://github.com/pkp/ | G82: Implemented/available | H82: https://pkp.sfu.ca/about/governance/ | I82: Implemented/available | J82: <p>Open Preprint Systems is an initiative of the <a href="https://pkp.sfu.ca/about/governance/" target="_blank">Public Knowledge Project</a> (PKP), a member of the Core Facility Program at <a href="https://www.sfu.ca/" target="_blank">Simon Fraser University</a> since 2022 which operates under the auspices of the Office of the Vice President, Research and International (VPRI) of Simon Fraser University. PKP is additionally guided by an <a href="https://pkp.sfu.ca/about/governance/advisory/" target="_blank">Advisory Committee</a>, <a href="https://pkp.sfu.ca/about/governance/sfu-advisory/" target="_blank">SFU Community Advisory Committee</a>, <a href="https://pkp.sfu.ca/about/governance/technical/" target="_blank">Technical Committee</a>, Members Committee, and a <a href="https://pkp.sfu.ca/about/governance/conduct/" target="_blank">Code of Conduct Committee</a>.</p> | K82: https://pkp.sfu.ca/interest-groups/ | L82: Multi-board governance | P82: Implemented/available | Q82: Implemented/available | R82: https://pkp.sfu.ca/general-accessibility-statement/ | S82: Our tool or project | T82: Implemented/available | U82: https://pkp.sfu.ca/hosting-services/hosting/monographs/ | V82: In progress | W82: https://pkp.sfu.ca/code/ | X82: Implemented/available | Y82: https://pkp.sfu.ca/privacy-policy/ | AC82: Formal | AD82: http://www.sfu.ca/policies/gazette/board.html
A83: Open Preprint Systems (OPS) | B83: Public Knowledge Project (PKP) | C83: https://pkp.sfu.ca/software/ops/ | D83: CA | E83: Publishing system | F83: https://github.com/pkp/https://github.com/pkp/ops | G83: Implemented/available | H83: https://pkp.sfu.ca/about/governance/ | I83: Implemented/available | J83: <p>Open Preprint Systems is an initiative of the <a href="https://pkp.sfu.ca/about/governance/" target="_blank">Public Knowledge Project</a> (PKP), a member of the Core Facility Program at <a href="https://www.sfu.ca/" target="_blank">Simon Fraser University</a> since 2022 which operates under the auspices of the Office of the Vice President, Research and International (VPRI) of Simon Fraser University. PKP is additionally guided by an <a href="https://pkp.sfu.ca/about/governance/advisory/" target="_blank">Advisory Committee</a>, <a href="https://pkp.sfu.ca/about/governance/sfu-advisory/" target="_blank">SFU Community Advisory Committee</a>, <a href="https://pkp.sfu.ca/about/governance/technical/" target="_blank">Technical Committee</a>, Members Committee, and a <a href="https://pkp.sfu.ca/about/governance/conduct/" target="_blank">Code of Conduct Committee</a>.</p> | K83: https://pkp.sfu.ca/about/governance/advisory/ | L83: Multi-board governance | P83: Implemented/available | Q83: Implemented/available | R83: https://pkp.sfu.ca/general-accessibility-statement/ | S83: Our tool or project | T83: Implemented/available | U83: https://pkp.sfu.ca/hosting-services/hosting/preprints/ | V83: In progress | W83: https://pkp.sfu.ca/code/ | X83: Implemented/available | Y83: https://pkp.sfu.ca/privacy-policy/ | AC83: Formal | AD83: https://pkp.sfu.ca/about/governance/advisory/
A84: Openverse | B84: WordPress Foundation | C84: https://openverse.org | D84: US | E84: Discovery system | F84: https://github.com/WordPress/openverse | G84: In progress | H84: https://docs.openverse.org/meta/index.html | I84: Implemented/available | K84: https://make.wordpress.org/openverse/ | L84: None | O84: Openverse has no board. | P84: Considering | Q84: Implemented/available | R84: https://wordpress.org/about/accessibility/ | T84: No direct costs | V84: Implemented/available | W84: https://make.wordpress.org/handbook/diversity-equity-and-inclusion-in-wordpress/ | X84: Implemented/available | Y84: https://openverse.org/privacy | AC84: Ad hoc | AD84: https://docs.openverse.org/meta/decision_making/index.html
