Workbook

Sheet Summary
A1: Organizational Capacity: Final Equal-Weight Results
A2: Infrastructure entries | B2: 112
A3: Final metrics | B3: M1, M2, H1, I2, O1
A4: Weight per metric | B4: 20.00% (1/5)
A5: Coverage / eligibility gate | B5: None
A6: Missing, unknown, N/A | B6: Scored 0; denominator remains five
A7: Mean score | B7: =AVERAGE(Scoring!O2:O113)
A8: Median score | B8: =MEDIAN(Scoring!O2:O113)
A9: Highest score | B9: =MAX(Scoring!O2:O113)
A10: Lowest score | B10: =MIN(Scoring!O2:O113)
A11: Important interpretation | B11: Zero-filled score reflects both reported capacity and missing information. Review metric-level scores and notes before interpreting rank differences.
A12: Affiliation review | B12: Field 058 is free text. Use Verification to enter a corrected I2 score of 0, 50, or 100; scoring formulas update when opened/recalculated in Excel.

Sheet Scoring
A1: Service | B1: Provider | C1: Solution category | D1: 079 Readiness | E1: 080 Maintenance | F1: 054 Full-time staff | G1: 055 Volunteers | H1: 058 Affiliations | I1: 076 Service options | J1: M1 | K1: M2 | L1: H1 | M1: I2 | N1: O1 | O1: Final score / 100 | P1: Rank | Q1: Data-quality notes
A2: 2i2c | B2: Code for Science and Society | C2: Authoring tool | D2: Actual system proven in operational environment | E2: Actively Maintained | I2: Not applicable | J2: =Calc!B2 | K2: =Calc!C2 | L2: =Calc!F2 | M2: =Verification!E2 | N2: =Calc!I2 | O2: =AVERAGE(J2:N2) | P2: =RANK.EQ(O2,$O$2:$O$113,0) | Q2: Full-time staffing missing/unknown scored 0; Volunteer staffing missing/unknown scored 0; Service-delivery field not applicable/unknown scored 0
A3: Academic Preservation Trust (APTrust) | B3: Academic Preservation Trust (APTrust) | C3: Digital preservation service | D3: Actual system proven in operational environment | E3: Actively Maintained | F3: 1-5 | H3: University of Virginia | I3: Through solution provider only | J3: =Calc!B3 | K3: =Calc!C3 | L3: =Calc!F3 | M3: =Verification!E3 | N3: =Calc!I3 | O3: =AVERAGE(J3:N3) | P3: =RANK.EQ(O3,$O$2:$O$113,0) | Q3: Volunteer staffing missing/unknown scored 0; Review affiliation coding; override available
A4: AfricArXiv | B4: UbuntuNet Alliance | C4: Repository service | D4: Actual system proven in operational environment | E4: Actively Maintained | F4: 1-5 | G4: 1-5 | H4: Access 2 Perspectives coordinates AfricArXiv’s operations. This includes managing day-to-day activities, overseeing submission processes, ensuring quality control, and facilitating the integration of AfricArXiv with other scholarly services | I4: Not applicable | J4: =Calc!B4 | K4: =Calc!C4 | L4: =Calc!F4 | M4: =Verification!E4 | N4: =Calc!I4 | O4: =AVERAGE(J4:N4) | P4: =RANK.EQ(O4,$O$2:$O$113,0) | Q4: Review affiliation coding; override available; Service-delivery field not applicable/unknown scored 0
A5: Arches Heritage Data Management Platform | B5: Getty Conservation Institute (GCI) | C5: Data management planning tool or service | D5: Actual system proven in operational environment | E5: Actively Maintained | H5: Getty Conservation Institute Farallon Geographics | I5: Through third party vendor only | J5: =Calc!B5 | K5: =Calc!C5 | L5: =Calc!F5 | M5: =Verification!E5 | N5: =Calc!I5 | O5: =AVERAGE(J5:N5) | P5: =RANK.EQ(O5,$O$2:$O$113,0) | Q5: Full-time staffing missing/unknown scored 0; Volunteer staffing missing/unknown scored 0; Review affiliation coding; override available
A6: Archipelago Commons | B6: Metropolitan New York Library Council | C6: Digital library, collection or exhibit platform | Repository software | D6: Actual system proven in operational environment | E6: Actively Maintained | I6: Through solution provider or third party vendor | J6: =Calc!B6 | K6: =Calc!C6 | L6: =Calc!F6 | M6: =Verification!E6 | N6: =Calc!I6 | O6: =AVERAGE(J6:N6) | P6: =RANK.EQ(O6,$O$2:$O$113,0) | Q6: Full-time staffing missing/unknown scored 0; Volunteer staffing missing/unknown scored 0
A7: Archival Resource Key | B7: ARK Alliance | C7: Standard, specification or protocol | D7: Technology validated in relevant environment | E7: Actively Maintained | I7: Not applicable | J7: =Calc!B7 | K7: =Calc!C7 | L7: =Calc!F7 | M7: =Verification!E7 | N7: =Calc!I7 | O7: =AVERAGE(J7:N7) | P7: =RANK.EQ(O7,$O$2:$O$113,0) | Q7: Full-time staffing missing/unknown scored 0; Volunteer staffing missing/unknown scored 0; Service-delivery field not applicable/unknown scored 0
A8: Archivematica | B8: Artefactual | C8: Digital preservation system | D8: Actual system proven in operational environment | E8: Actively Maintained | F8: More than 20 | H8: No Affiliations | I8: Through solution provider or third party vendor | J8: =Calc!B8 | K8: =Calc!C8 | L8: =Calc!F8 | M8: =Verification!E8 | N8: =Calc!I8 | O8: =AVERAGE(J8:N8) | P8: =RANK.EQ(O8,$O$2:$O$113,0) | Q8: Volunteer staffing missing/unknown scored 0; Review affiliation coding; override available
A9: ArchivesSpace | B9: ArchivesSpace | C9: Archive information management system | Discovery system | D9: Actual system proven in operational environment | E9: Actively Maintained | F9: 6-10 | H9: New York University and the University of California San Diego are the founding partners and have permanent seats on the Board; Lyrasis is the organizational home | I9: Through third party vendor only | J9: =Calc!B9 | K9: =Calc!C9 | L9: =Calc!F9 | M9: =Verification!E9 | N9: =Calc!I9 | O9: =AVERAGE(J9:N9) | P9: =RANK.EQ(O9,$O$2:$O$113,0) | Q9: Volunteer staffing missing/unknown scored 0; Review affiliation coding; override available
A10: ARGOS | B10: OpenAIRE | C10: Data management planning tool or service | D10: Actual system proven in operational environment | E10: Actively Maintained | H10: Athena Research Center (ARC) Communication & Information Technologies Experts (CITE) | I10: Through solution provider only | J10: =Calc!B10 | K10: =Calc!C10 | L10: =Calc!F10 | M10: =Verification!E10 | N10: =Calc!I10 | O10: =AVERAGE(J10:N10) | P10: =RANK.EQ(O10,$O$2:$O$113,0) | Q10: Full-time staffing missing/unknown scored 0; Volunteer staffing missing/unknown scored 0; Review affiliation coding; override available
A11: arXiv | B11: Cornell University | C11: Repository service | D11: Actual system proven in operational environment | E11: Actively Maintained | I11: Not applicable | J11: =Calc!B11 | K11: =Calc!C11 | L11: =Calc!F11 | M11: =Verification!E11 | N11: =Calc!I11 | O11: =AVERAGE(J11:N11) | P11: =RANK.EQ(O11,$O$2:$O$113,0) | Q11: Full-time staffing missing/unknown scored 0; Volunteer staffing missing/unknown scored 0; Service-delivery field not applicable/unknown scored 0
A12: AtoM | B12: Artefactual | C12: Archive information management system | D12: Actual system proven in operational environment | E12: Actively Maintained | F12: More than 20 | G12: Unknown | H12: No affiliations | I12: Through solution provider or third party vendor | J12: =Calc!B12 | K12: =Calc!C12 | L12: =Calc!F12 | M12: =Verification!E12 | N12: =Calc!I12 | O12: =AVERAGE(J12:N12) | P12: =RANK.EQ(O12,$O$2:$O$113,0) | Q12: Review affiliation coding; override available
A13: Avalon Media System | B13: Indiana University Libraries | C13: Digital library, collection or exhibit platform | Repository software | D13: Actual system proven in operational environment | E13: Actively Maintained | F13: 1-5 | H13: Indiana University Libraries | I13: No services available | J13: =Calc!B13 | K13: =Calc!C13 | L13: =Calc!F13 | M13: =Verification!E13 | N13: =Calc!I13 | O13: =AVERAGE(J13:N13) | P13: =RANK.EQ(O13,$O$2:$O$113,0) | Q13: Volunteer staffing missing/unknown scored 0; Review affiliation coding; override available
A14: Biodiversity Heritage Library | B14: BHL Consortium | C14: Digital library, collection or exhibit platform | Open scholarly dataset | Repository service | D14: Actual system proven in operational environment | E14: Actively Maintained | F14: 1-5 | H14: BHL’s fiscal sponsor is the Council on Library and Information Resources (CLIR). | I14: Not applicable | J14: =Calc!B14 | K14: =Calc!C14 | L14: =Calc!F14 | M14: =Verification!E14 | N14: =Calc!I14 | O14: =AVERAGE(J14:N14) | P14: =RANK.EQ(O14,$O$2:$O$113,0) | Q14: Volunteer staffing missing/unknown scored 0; Review affiliation coding; override available; Service-delivery field not applicable/unknown scored 0
A15: bioRxiv | B15: Cold Spring Harbor Laboratory | C15: Repository service | D15: Actual system proven in operational environment | E15: Actively Maintained | I15: Not applicable | J15: =Calc!B15 | K15: =Calc!C15 | L15: =Calc!F15 | M15: =Verification!E15 | N15: =Calc!I15 | O15: =AVERAGE(J15:N15) | P15: =RANK.EQ(O15,$O$2:$O$113,0) | Q15: Full-time staffing missing/unknown scored 0; Volunteer staffing missing/unknown scored 0; Service-delivery field not applicable/unknown scored 0
A16: BitCurator Environment | B16: BitCurator Consortium | C16: Digital preservation tool | D16: Actual system proven in operational environment | E16: Actively Maintained | F16: 0 | G16: 6-10 | H16: BitCurator Consortium is administratively hosted by the Open Library Foundation. | I16: No services available | J16: =Calc!B16 | K16: =Calc!C16 | L16: =Calc!F16 | M16: =Verification!E16 | N16: =Calc!I16 | O16: =AVERAGE(J16:N16) | P16: =RANK.EQ(O16,$O$2:$O$113,0) | Q16: Review affiliation coding; override available
A17: Blacklight | B17: Blacklight | C17: Discovery system | Integrated Library System (ILS) or Library Services Platform (LSP) | D17: Actual system proven in operational environment | E17: Actively Maintained | F17: 6-10 | H17: See website | I17: Through solution provider only | J17: =Calc!B17 | K17: =Calc!C17 | L17: =Calc!F17 | M17: =Verification!E17 | N17: =Calc!I17 | O17: =AVERAGE(J17:N17) | P17: =RANK.EQ(O17,$O$2:$O$113,0) | Q17: Volunteer staffing missing/unknown scored 0; Review affiliation coding; override available
A18: BrCRIS | B18: IBICT | C18: Discovery system | Research profiling system | D18: Actual system proven in operational environment | E18: Actively Maintained | I18: Not applicable | J18: =Calc!B18 | K18: =Calc!C18 | L18: =Calc!F18 | M18: =Verification!E18 | N18: =Calc!I18 | O18: =AVERAGE(J18:N18) | P18: =RANK.EQ(O18,$O$2:$O$113,0) | Q18: Full-time staffing missing/unknown scored 0; Volunteer staffing missing/unknown scored 0; Service-delivery field not applicable/unknown scored 0
A19: Browsertrix | B19: Webrecorder | C19: Digital library, collection or exhibit platform | Web archiving system | D19: Actual system proven in operational environment | E19: Actively Maintained | F19: 1-5 | G19: 0 | H19: No affiliations have direct involvement in governing or running our products except us. We are members of the International Internet Preservation Consortium (IIPC). | I19: Through solution provider or third party vendor | J19: =Calc!B19 | K19: =Calc!C19 | L19: =Calc!F19 | M19: =Verification!E19 | N19: =Calc!I19 | O19: =AVERAGE(J19:N19) | P19: =RANK.EQ(O19,$O$2:$O$113,0) | Q19: Review affiliation coding; override available
A20: CLOCKSS | B20: CLOCKSS | C20: Digital preservation service | D20: Actual system proven in operational environment | E20: Actively Maintained | F20: 1-5 | G20: 0 | H20: n/a | I20: Through solution provider or third party vendor | J20: =Calc!B20 | K20: =Calc!C20 | L20: =Calc!F20 | M20: =Verification!E20 | N20: =Calc!I20 | O20: =AVERAGE(J20:N20) | P20: =RANK.EQ(O20,$O$2:$O$113,0) | Q20: Review affiliation coding; override available
A21: COAR International Repository Directory (IRD) | B21: COAR | C21: Index or directory | D21: Actual system proven in operational environment | E21: Actively Maintained | F21: 1-5 | H21: Responsible Organisations: https://ird.coar-repositories.org/about?lang=en | I21: Not applicable | J21: =Calc!B21 | K21: =Calc!C21 | L21: =Calc!F21 | M21: =Verification!E21 | N21: =Calc!I21 | O21: =AVERAGE(J21:N21) | P21: =RANK.EQ(O21,$O$2:$O$113,0) | Q21: Volunteer staffing missing/unknown scored 0; Review affiliation coding; override available; Service-delivery field not applicable/unknown scored 0
A22: COAR Notify | B22: COAR | C22: Standard, specification or protocol | D22: Actual system proven in operational environment | E22: Actively Maintained | H22: No affiliations. | I22: Through solution provider or third party vendor | J22: =Calc!B22 | K22: =Calc!C22 | L22: =Calc!F22 | M22: =Verification!E22 | N22: =Calc!I22 | O22: =AVERAGE(J22:N22) | P22: =RANK.EQ(O22,$O$2:$O$113,0) | Q22: Full-time staffing missing/unknown scored 0; Volunteer staffing missing/unknown scored 0; Review affiliation coding; override available
A23: CollectiveAccess | B23: Whirl-i-Gig | C23: Archive information management system | Digital asset management system | Digital library, collection or exhibit platform | D23: Actual system proven in operational environment | E23: Actively Maintained | F23: 6-10 | G23: 0 | H23: No affiliations | I23: Through solution provider or third party vendor | J23: =Calc!B23 | K23: =Calc!C23 | L23: =Calc!F23 | M23: =Verification!E23 | N23: =Calc!I23 | O23: =AVERAGE(J23:N23) | P23: =RANK.EQ(O23,$O$2:$O$113,0) | Q23: Review affiliation coding; override available
A24: CORE | B24: The Open University | C24: Discovery system | D24: Actual system proven in operational environment | E24: Actively Maintained | I24: Not applicable | J24: =Calc!B24 | K24: =Calc!C24 | L24: =Calc!F24 | M24: =Verification!E24 | N24: =Calc!I24 | O24: =AVERAGE(J24:N24) | P24: =RANK.EQ(O24,$O$2:$O$113,0) | Q24: Full-time staffing missing/unknown scored 0; Volunteer staffing missing/unknown scored 0; Service-delivery field not applicable/unknown scored 0
A25: COUNTER Code of Practice | B25: COUNTER Metrics | C25: Standard, specification or protocol | D25: Actual system proven in operational environment | E25: Actively Maintained | I25: Not applicable | J25: =Calc!B25 | K25: =Calc!C25 | L25: =Calc!F25 | M25: =Verification!E25 | N25: =Calc!I25 | O25: =AVERAGE(J25:N25) | P25: =RANK.EQ(O25,$O$2:$O$113,0) | Q25: Full-time staffing missing/unknown scored 0; Volunteer staffing missing/unknown scored 0; Service-delivery field not applicable/unknown scored 0
A26: Creative Commons Licenses | B26: Creative Commons | C26: Standard, specification or protocol | D26: System complete and qualified | E26: Actively Maintained | I26: Not applicable | J26: =Calc!B26 | K26: =Calc!C26 | L26: =Calc!F26 | M26: =Verification!E26 | N26: =Calc!I26 | O26: =AVERAGE(J26:N26) | P26: =RANK.EQ(O26,$O$2:$O$113,0) | Q26: Full-time staffing missing/unknown scored 0; Volunteer staffing missing/unknown scored 0; Service-delivery field not applicable/unknown scored 0
A27: Crossref Metadata Retrieval | B27: Crossref | C27: Open scholarly dataset | D27: Actual system proven in operational environment | E27: Actively Maintained | I27: Not applicable | J27: =Calc!B27 | K27: =Calc!C27 | L27: =Calc!F27 | M27: =Verification!E27 | N27: =Calc!I27 | O27: =AVERAGE(J27:N27) | P27: =RANK.EQ(O27,$O$2:$O$113,0) | Q27: Full-time staffing missing/unknown scored 0; Volunteer staffing missing/unknown scored 0; Service-delivery field not applicable/unknown scored 0
A28: D4Science Infrastructure | B28: National Research Council of Italy | C28: Computing framework | Informal scholarly communications | Repository service | D28: Actual system proven in operational environment | E28: Actively Maintained | F28: 6-10 | G28: More than 20 | H28: D4Science is managed by the Italian National Research Council (CNR). Its headquarters are hosted by CNR's Institute of Information Science and Technologies "A. Faedo" (CNR-ISTI) in Pisa, Tuscany, Italy. | I28: Through solution provider only | J28: =Calc!B28 | K28: =Calc!C28 | L28: =Calc!F28 | M28: =Verification!E28 | N28: =Calc!I28 | O28: =AVERAGE(J28:N28) | P28: =RANK.EQ(O28,$O$2:$O$113,0) | Q28: Review affiliation coding; override available
A29: DART (Digital Archivist's Resource Tool) | B29: Academic Preservation Trust (APTrust) | C29: Digital preservation tool | D29: Actual system proven in operational environment | E29: Actively Maintained | F29: 1-5 | H29: University of Virginia | I29: No services available | J29: =Calc!B29 | K29: =Calc!C29 | L29: =Calc!F29 | M29: =Verification!E29 | N29: =Calc!I29 | O29: =AVERAGE(J29:N29) | P29: =RANK.EQ(O29,$O$2:$O$113,0) | Q29: Volunteer staffing missing/unknown scored 0; Review affiliation coding; override available
A30: Database Information System | B30: University Library of Regensburg | C30: Discovery system | Index or directory | D30: Actual system proven in operational environment | E30: Actively Maintained | H30: DBIS is operated by the University Library of Regensburg. | I30: Through solution provider or third party vendor | J30: =Calc!B30 | K30: =Calc!C30 | L30: =Calc!F30 | M30: =Verification!E30 | N30: =Calc!I30 | O30: =AVERAGE(J30:N30) | P30: =RANK.EQ(O30,$O$2:$O$113,0) | Q30: Full-time staffing missing/unknown scored 0; Volunteer staffing missing/unknown scored 0; Review affiliation coding; override available
A31: Data Citation Corpus | B31: Make Data Count | C31: Discovery system | Open scholarly dataset | D31: Technology validated in relevant environment | E31: Actively Maintained | G31: 11-20 | H31: DataCite leads the development of the Data Citation Corpus as part of Make Data Count activities. | I31: Not applicable | J31: =Calc!B31 | K31: =Calc!C31 | L31: =Calc!F31 | M31: =Verification!E31 | N31: =Calc!I31 | O31: =AVERAGE(J31:N31) | P31: =RANK.EQ(O31,$O$2:$O$113,0) | Q31: Full-time staffing missing/unknown scored 0; Review affiliation coding; override available; Service-delivery field not applicable/unknown scored 0
A32: DataCite | B32: DataCite | C32: Discovery system | Persistent identifier service | D32: Actual system proven in operational environment | E32: Actively Maintained | I32: Not applicable | J32: =Calc!B32 | K32: =Calc!C32 | L32: =Calc!F32 | M32: =Verification!E32 | N32: =Calc!I32 | O32: =AVERAGE(J32:N32) | P32: =RANK.EQ(O32,$O$2:$O$113,0) | Q32: Full-time staffing missing/unknown scored 0; Volunteer staffing missing/unknown scored 0; Service-delivery field not applicable/unknown scored 0
A33: Data Stewardship Wizard | B33: DSW Team | C33: Data management planning tool or service | D33: Actual system proven in operational environment | E33: Actively Maintained | H33: Czech Technical University in Prague / ELIXIR-CZ Codevence Solutions | I33: Through third party vendor only | J33: =Calc!B33 | K33: =Calc!C33 | L33: =Calc!F33 | M33: =Verification!E33 | N33: =Calc!I33 | O33: =AVERAGE(J33:N33) | P33: =RANK.EQ(O33,$O$2:$O$113,0) | Q33: Full-time staffing missing/unknown scored 0; Volunteer staffing missing/unknown scored 0; Review affiliation coding; override available
A34: Dataverse | B34: Harvard University Institute for Quantitative Social Science (IQSS) | C34: Repository software | D34: Actual system proven in operational environment | E34: Actively Maintained | I34: Through third party vendor only | J34: =Calc!B34 | K34: =Calc!C34 | L34: =Calc!F34 | M34: =Verification!E34 | N34: =Calc!I34 | O34: =AVERAGE(J34:N34) | P34: =RANK.EQ(O34,$O$2:$O$113,0) | Q34: Full-time staffing missing/unknown scored 0; Volunteer staffing missing/unknown scored 0
A35: DLCM Backend | B35: DLCM Technology | C35: Archive information management system | Digital preservation system | D35: Actual system proven in operational environment | E35: Actively Maintained | F35: 1-5 | G35: 1-5 | H35: University of Geneva (https://www.unige.ch/) HEG, HES-SO (https://www.hesge.ch/heg/en) UNIFR (https://www.unifr.ch/home/en/) BFH (https://www.bfh.ch/en/) OLOS (https://olos.swiss/) | I35: Through third party vendor only | J35: =Calc!B35 | K35: =Calc!C35 | L35: =Calc!F35 | M35: =Verification!E35 | N35: =Calc!I35 | O35: =AVERAGE(J35:N35) | P35: =RANK.EQ(O35,$O$2:$O$113,0) | Q35: Review affiliation coding; override available
A36: DLCM Portal | B36: DLCM Technology | C36: Archive information management system | Digital preservation system | Software preservation service | D36: Actual system proven in operational environment | E36: Actively Maintained | F36: 1-5 | G36: 1-5 | H36: University of Geneva (https://www.unige.ch/)HEG, HES-SO (https://www.hesge.ch/heg/en)UNIFR (https://www.unifr.ch/home/en/)BFH (https://www.bfh.ch/en/)OLOS (https://olos.swiss/) | I36: Through third party vendor only | J36: =Calc!B36 | K36: =Calc!C36 | L36: =Calc!F36 | M36: =Verification!E36 | N36: =Calc!I36 | O36: =AVERAGE(J36:N36) | P36: =RANK.EQ(O36,$O$2:$O$113,0) | Q36: Review affiliation coding; override available
A37: DMP Tool | B37: California Digital Library | C37: Data management planning tool or service | D37: Actual system proven in operational environment | E37: Actively Maintained | F37: 1-5 | G37: 0 | I37: Through solution provider only | J37: =Calc!B37 | K37: =Calc!C37 | L37: =Calc!F37 | M37: =Verification!E37 | N37: =Calc!I37 | O37: =AVERAGE(J37:N37) | P37: =RANK.EQ(O37,$O$2:$O$113,0)
A38: DOAJ (Directory of Open Access Journals) | B38: DOAJ Foundation | C38: Discovery system | Index or directory | Open scholarly dataset | D38: Actual system proven in operational environment | E38: Actively Maintained | I38: Not applicable | J38: =Calc!B38 | K38: =Calc!C38 | L38: =Calc!F38 | M38: =Verification!E38 | N38: =Calc!I38 | O38: =AVERAGE(J38:N38) | P38: =RANK.EQ(O38,$O$2:$O$113,0) | Q38: Full-time staffing missing/unknown scored 0; Volunteer staffing missing/unknown scored 0; Service-delivery field not applicable/unknown scored 0
A39: dokieli | B39: dokieli | C39: Annotations system | Authoring tool | Informal scholarly communications | D39: Technology validated in relevant environment | E39: Actively Maintained | I39: Unknown | J39: =Calc!B39 | K39: =Calc!C39 | L39: =Calc!F39 | M39: =Verification!E39 | N39: =Calc!I39 | O39: =AVERAGE(J39:N39) | P39: =RANK.EQ(O39,$O$2:$O$113,0) | Q39: Full-time staffing missing/unknown scored 0; Volunteer staffing missing/unknown scored 0; Service-delivery field not applicable/unknown scored 0
A40: Dryad | B40: Dryad | C40: Repository service | D40: Actual system proven in operational environment | E40: Actively Maintained | I40: Not applicable | J40: =Calc!B40 | K40: =Calc!C40 | L40: =Calc!F40 | M40: =Verification!E40 | N40: =Calc!I40 | O40: =AVERAGE(J40:N40) | P40: =RANK.EQ(O40,$O$2:$O$113,0) | Q40: Full-time staffing missing/unknown scored 0; Volunteer staffing missing/unknown scored 0; Service-delivery field not applicable/unknown scored 0
A41: DSpace | B41: Lyrasis | C41: Repository software | D41: Actual system proven in operational environment | E41: Actively Maintained | F41: 1-5 | G41: Unknown | I41: Through solution provider or third party vendor | J41: =Calc!B41 | K41: =Calc!C41 | L41: =Calc!F41 | M41: =Verification!E41 | N41: =Calc!I41 | O41: =AVERAGE(J41:N41) | P41: =RANK.EQ(O41,$O$2:$O$113,0)
A42: DuraCloud | B42: Lyrasis | C42: Digital preservation service | Digital preservation system | Digital preservation tool | D42: Actual system proven in operational environment | E42: Actively Maintained | H42: N/A | I42: Through solution provider only | J42: =Calc!B42 | K42: =Calc!C42 | L42: =Calc!F42 | M42: =Verification!E42 | N42: =Calc!I42 | O42: =AVERAGE(J42:N42) | P42: =RANK.EQ(O42,$O$2:$O$113,0) | Q42: Full-time staffing missing/unknown scored 0; Volunteer staffing missing/unknown scored 0; Review affiliation coding; override available
A43: Episciences | B43: Center for Direct Scientific Communication (CCSD) | C43: Peer review system | Publishing system | Submissions system | D43: Actual system proven in operational environment | E43: Actively Maintained | F43: 1-5 | G43: More than 20 | H43: The financing of the CCSD is jointly ensured by its supervising bodies (CNRS, Inria, INRAE) ; the French Ministry of higher education and research (MESR) Inria and Institut Fourier bring a specific support to Episciences by their contribution to the editorial support of the journals. The IT infrastructure of Episciences is shared with HAL and Sciencesconf. Long-term preservation of content published on Episciences is ensured by C.I.N.E.S. (Centre Informatique National de l’Enseignement Supérieur). | I43: Not applicable | J43: =Calc!B43 | K43: =Calc!C43 | L43: =Calc!F43 | M43: =Verification!E43 | N43: =Calc!I43 | O43: =AVERAGE(J43:N43) | P43: =RANK.EQ(O43,$O$2:$O$113,0) | Q43: Review affiliation coding; override available; Service-delivery field not applicable/unknown scored 0
A44: EPrints | B44: EPrints Services | C44: Repository software | D44: Actual system proven in operational environment | E44: Actively Maintained | H44: ECS Partners Ltd | I44: Through solution provider only | J44: =Calc!B44 | K44: =Calc!C44 | L44: =Calc!F44 | M44: =Verification!E44 | N44: =Calc!I44 | O44: =AVERAGE(J44:N44) | P44: =RANK.EQ(O44,$O$2:$O$113,0) | Q44: Full-time staffing missing/unknown scored 0; Volunteer staffing missing/unknown scored 0; Review affiliation coding; override available
A45: Érudit | B45: Érudit | C45: Discovery system | Publishing system | Repository software | D45: Actual system proven in operational environment | E45: Actively Maintained | I45: Not applicable | J45: =Calc!B45 | K45: =Calc!C45 | L45: =Calc!F45 | M45: =Verification!E45 | N45: =Calc!I45 | O45: =AVERAGE(J45:N45) | P45: =RANK.EQ(O45,$O$2:$O$113,0) | Q45: Full-time staffing missing/unknown scored 0; Volunteer staffing missing/unknown scored 0; Service-delivery field not applicable/unknown scored 0
A46: Europe PMC | B46: EMBL European Bioinformatics Institute (EMBL-EBI) | C46: Digital preservation system | Discovery system | Repository service | D46: Actual system proven in operational environment | E46: Actively Maintained | F46: 11-20 | I46: Not applicable | J46: =Calc!B46 | K46: =Calc!C46 | L46: =Calc!F46 | M46: =Verification!E46 | N46: =Calc!I46 | O46: =AVERAGE(J46:N46) | P46: =RANK.EQ(O46,$O$2:$O$113,0) | Q46: Volunteer staffing missing/unknown scored 0; Service-delivery field not applicable/unknown scored 0
A47: FAIR Wizard | B47: Codevence Solution s.r.o. | C47: Data management planning tool or service | D47: Actual system proven in operational environment | E47: Actively Maintained | F47: 1-5 | H47: Codevence Solutions s.r.o. | I47: Through solution provider only | J47: =Calc!B47 | K47: =Calc!C47 | L47: =Calc!F47 | M47: =Verification!E47 | N47: =Calc!I47 | O47: =AVERAGE(J47:N47) | P47: =RANK.EQ(O47,$O$2:$O$113,0) | Q47: Volunteer staffing missing/unknown scored 0; Review affiliation coding; override available
A48: Fedora | B48: Lyrasis | C48: Repository software | D48: Actual system proven in operational environment | E48: Actively Maintained | F48: 1-5 | G48: Unknown | I48: Through third party vendor only | J48: =Calc!B48 | K48: =Calc!C48 | L48: =Calc!F48 | M48: =Verification!E48 | N48: =Calc!I48 | O48: =AVERAGE(J48:N48) | P48: =RANK.EQ(O48,$O$2:$O$113,0)
A49: fido | B49: Open Preservation Foundation | C49: Digital preservation tool | D49: Actual system proven in operational environment | E49: Actively Maintained | F49: 6-10 | H49: Artefactual | I49: Not applicable | J49: =Calc!B49 | K49: =Calc!C49 | L49: =Calc!F49 | M49: =Verification!E49 | N49: =Calc!I49 | O49: =AVERAGE(J49:N49) | P49: =RANK.EQ(O49,$O$2:$O$113,0) | Q49: Volunteer staffing missing/unknown scored 0; Review affiliation coding; override available; Service-delivery field not applicable/unknown scored 0
A50: Fulcrum | B50: Michigan Publishing | C50: Publishing system | D50: Actual system proven in operational environment | E50: Actively Maintained | I50: Through solution provider only | J50: =Calc!B50 | K50: =Calc!C50 | L50: =Calc!F50 | M50: =Verification!E50 | N50: =Calc!I50 | O50: =AVERAGE(J50:N50) | P50: =RANK.EQ(O50,$O$2:$O$113,0) | Q50: Full-time staffing missing/unknown scored 0; Volunteer staffing missing/unknown scored 0
A51: Galaxy | B51: The Galaxy community | C51: Computing framework | Discovery system | D51: Actual system proven in operational environment | E51: Actively Maintained | F51: More than 20 | G51: More than 20 | H51: It's an open source project with many affiliations. | I51: Through solution provider or third party vendor | J51: =Calc!B51 | K51: =Calc!C51 | L51: =Calc!F51 | M51: =Verification!E51 | N51: =Calc!I51 | O51: =AVERAGE(J51:N51) | P51: =RANK.EQ(O51,$O$2:$O$113,0) | Q51: Review affiliation coding; override available
A52: GeoServer | B52: Open Source Geospatial Foundation | C52: Geospatial data tool or platform | D52: Actual system proven in operational environment | E52: Actively Maintained | F52: 0 | G52: More than 20 | H52: https://www.osgeo.org https://www.geosolutionsgroup.com/ https://www.afrigis.co.za/ https://www.geocat.net/ https://camptocamp.com/ | I52: Through third party vendor only | J52: =Calc!B52 | K52: =Calc!C52 | L52: =Calc!F52 | M52: =Verification!E52 | N52: =Calc!I52 | O52: =AVERAGE(J52:N52) | P52: =RANK.EQ(O52,$O$2:$O$113,0) | Q52: Review affiliation coding; override available
A53: Hyku | B53: Samvera | C53: Repository software | D53: Actual system proven in operational environment | E53: Actively Maintained | F53: 1-5 | G53: 1-5 | I53: Through third party vendor only | J53: =Calc!B53 | K53: =Calc!C53 | L53: =Calc!F53 | M53: =Verification!E53 | N53: =Calc!I53 | O53: =AVERAGE(J53:N53) | P53: =RANK.EQ(O53,$O$2:$O$113,0)
A54: Hyrax | B54: Samvera | C54: Repository software | D54: Actual system proven in operational environment | E54: Actively Maintained | F54: 1-5 | G54: 1-5 | H54: No affiliations | I54: Through third party vendor only | J54: =Calc!B54 | K54: =Calc!C54 | L54: =Calc!F54 | M54: =Verification!E54 | N54: =Calc!I54 | O54: =AVERAGE(J54:N54) | P54: =RANK.EQ(O54,$O$2:$O$113,0) | Q54: Review affiliation coding; override available
A55: IIIF | B55: IIIF Consortium | C55: Standard, specification or protocol | D55: Actual system proven in operational environment | E55: Actively Maintained | I55: Not applicable | J55: =Calc!B55 | K55: =Calc!C55 | L55: =Calc!F55 | M55: =Verification!E55 | N55: =Calc!I55 | O55: =AVERAGE(J55:N55) | P55: =RANK.EQ(O55,$O$2:$O$113,0) | Q55: Full-time staffing missing/unknown scored 0; Volunteer staffing missing/unknown scored 0; Service-delivery field not applicable/unknown scored 0
A56: ImpactU | B56: Universidad de Antioquia and other Colombian universities | C56: Open scholarly dataset | Research profiling system | D56: Actual system proven in operational environment | E56: Actively Maintained | H56: ImpactU is created and coordinated by CoLaV at the Universidad de Antioquia, the Universidad del Valle, the Universidad Externado de Colombia and the Universidad Autonoma Latinoamericana. It is in the process of constituting a national consortium authorized by ASCUN which will democratize ownership between all the Colombian institutions interested in membership. | I56: Through solution provider or third party vendor | J56: =Calc!B56 | K56: =Calc!C56 | L56: =Calc!F56 | M56: =Verification!E56 | N56: =Calc!I56 | O56: =AVERAGE(J56:N56) | P56: =RANK.EQ(O56,$O$2:$O$113,0) | Q56: Full-time staffing missing/unknown scored 0; Volunteer staffing missing/unknown scored 0; Review affiliation coding; override available
A57: International Generic Sample Number (IGSN) | B57: International Generic Sample Number Organization e.V. | C57: Persistent identifier service | D57: Actual system proven in operational environment | E57: Actively Maintained | F57: 1-5 | G57: 11-20 | H57: DataCite e.V. SESAR GFZ Data Services Kiel University IGSN Service Lithodat Pty Ltd Commonwealth Scientific and Industrial Research Organisation Institut Français de Recherche pour l'Exploitation de la Mer | I57: Through solution provider only | J57: =Calc!B57 | K57: =Calc!C57 | L57: =Calc!F57 | M57: =Verification!E57 | N57: =Calc!I57 | O57: =AVERAGE(J57:N57) | P57: =RANK.EQ(O57,$O$2:$O$113,0) | Q57: Review affiliation coding; override available
A58: InvenioRDM | B58: CERN | C58: Repository software | D58: System complete and qualified | E58: Actively Maintained | I58: No services available | J58: =Calc!B58 | K58: =Calc!C58 | L58: =Calc!F58 | M58: =Verification!E58 | N58: =Calc!I58 | O58: =AVERAGE(J58:N58) | P58: =RANK.EQ(O58,$O$2:$O$113,0) | Q58: Full-time staffing missing/unknown scored 0; Volunteer staffing missing/unknown scored 0
A59: iRODS | B59: Renaissance Computing Institute (RENCI) | C59: Data management planning tool or service | Digital preservation system | Discovery system | D59: Actual system proven in operational environment | E59: Actively Maintained | F59: 6-10 | G59: 0 | H59: Executive Board Members (Premier Level) | I59: Through solution provider or third party vendor | J59: =Calc!B59 | K59: =Calc!C59 | L59: =Calc!F59 | M59: =Verification!E59 | N59: =Calc!I59 | O59: =AVERAGE(J59:N59) | P59: =RANK.EQ(O59,$O$2:$O$113,0) | Q59: Review affiliation coding; override available
A60: Islandora | B60: Islandora Foundation | C60: Authoring tool | Digital asset management system | D60: Actual system proven in operational environment | E60: Actively Maintained | I60: Through third party vendor only | J60: =Calc!B60 | K60: =Calc!C60 | L60: =Calc!F60 | M60: =Verification!E60 | N60: =Calc!I60 | O60: =AVERAGE(J60:N60) | P60: =RANK.EQ(O60,$O$2:$O$113,0) | Q60: Full-time staffing missing/unknown scored 0; Volunteer staffing missing/unknown scored 0
A61: Janeway | B61: Open Library of Humanities | C61: Publishing system | D61: Actual system proven in operational environment | E61: Actively Maintained | I61: Through solution provider only | J61: =Calc!B61 | K61: =Calc!C61 | L61: =Calc!F61 | M61: =Verification!E61 | N61: =Calc!I61 | O61: =AVERAGE(J61:N61) | P61: =RANK.EQ(O61,$O$2:$O$113,0) | Q61: Full-time staffing missing/unknown scored 0; Volunteer staffing missing/unknown scored 0
A62: JHOVE | B62: Open Preservation Foundation | C62: Computing library | Digital preservation tool | D62: Actual system proven in operational environment | E62: Actively Maintained | F62: 1-5 | G62: 0 | H62: OPF Membership | I62: No services available | J62: =Calc!B62 | K62: =Calc!C62 | L62: =Calc!F62 | M62: =Verification!E62 | N62: =Calc!I62 | O62: =AVERAGE(J62:N62) | P62: =RANK.EQ(O62,$O$2:$O$113,0) | Q62: Review affiliation coding; override available
A63: LA Referencia | B63: LA Referencia | C63: Discovery system | D63: Actual system proven in operational environment | E63: Actively Maintained | I63: Not applicable | J63: =Calc!B63 | K63: =Calc!C63 | L63: =Calc!F63 | M63: =Verification!E63 | N63: =Calc!I63 | O63: =AVERAGE(J63:N63) | P63: =RANK.EQ(O63,$O$2:$O$113,0) | Q63: Full-time staffing missing/unknown scored 0; Volunteer staffing missing/unknown scored 0; Service-delivery field not applicable/unknown scored 0
A64: Manifold | B64: Manifold Digital Services | C64: Publishing system | D64: Actual system proven in operational environment | E64: Actively Maintained | I64: Through third party vendor only | J64: =Calc!B64 | K64: =Calc!C64 | L64: =Calc!F64 | M64: =Verification!E64 | N64: =Calc!I64 | O64: =AVERAGE(J64:N64) | P64: =RANK.EQ(O64,$O$2:$O$113,0) | Q64: Full-time staffing missing/unknown scored 0; Volunteer staffing missing/unknown scored 0
A65: medRxiv | B65: Cold Spring Harbor Laboratory | C65: Repository service | D65: Actual system proven in operational environment | E65: Actively Maintained | I65: Through solution provider or third party vendor | J65: =Calc!B65 | K65: =Calc!C65 | L65: =Calc!F65 | M65: =Verification!E65 | N65: =Calc!I65 | O65: =AVERAGE(J65:N65) | P65: =RANK.EQ(O65,$O$2:$O$113,0) | Q65: Full-time staffing missing/unknown scored 0; Volunteer staffing missing/unknown scored 0
A66: Metadata Encoding and Transmission Standard (METS) | B66: METS Editorial Board | C66: Standard, specification or protocol | D66: Actual system proven in operational environment | E66: Actively Maintained | F66: 0 | G66: 1-5 | H66: Library of Congress provides hosting support for the METS schema; the METS editorial board functions as an independent community group. | I66: Not applicable | J66: =Calc!B66 | K66: =Calc!C66 | L66: =Calc!F66 | M66: =Verification!E66 | N66: =Calc!I66 | O66: =AVERAGE(J66:N66) | P66: =RANK.EQ(O66,$O$2:$O$113,0) | Q66: Review affiliation coding; override available; Service-delivery field not applicable/unknown scored 0
A67: Mirador | B67: Project Mirador | C67: Annotations system | Media viewer/player | D67: Actual system proven in operational environment | E67: Actively Maintained | I67: Not applicable | J67: =Calc!B67 | K67: =Calc!C67 | L67: =Calc!F67 | M67: =Verification!E67 | N67: =Calc!I67 | O67: =AVERAGE(J67:N67) | P67: =RANK.EQ(O67,$O$2:$O$113,0) | Q67: Full-time staffing missing/unknown scored 0; Volunteer staffing missing/unknown scored 0; Service-delivery field not applicable/unknown scored 0
A68: Mukurtu CMS | B68: Center for Digital Scholarship and Curation | C68: Archive information management system | Digital asset management system | D68: Actual system proven in operational environment | E68: Actively Maintained | I68: Through third party vendor only | J68: =Calc!B68 | K68: =Calc!C68 | L68: =Calc!F68 | M68: =Verification!E68 | N68: =Calc!I68 | O68: =AVERAGE(J68:N68) | P68: =RANK.EQ(O68,$O$2:$O$113,0) | Q68: Full-time staffing missing/unknown scored 0; Volunteer staffing missing/unknown scored 0
A69: MyCoRe | B69: MyCoRe Community | C69: Digital asset management system | Digital library, collection or exhibit platform | Repository software | D69: Actual system proven in operational environment | E69: Actively Maintained | F69: 1-5 | G69: 6-10 | H69: Regional Computer Center, Hamburg University | I69: Through solution provider only | J69: =Calc!B69 | K69: =Calc!C69 | L69: =Calc!F69 | M69: =Verification!E69 | N69: =Calc!I69 | O69: =AVERAGE(J69:N69) | P69: =RANK.EQ(O69,$O$2:$O$113,0) | Q69: Review affiliation coding; override available
A70: NumPy | B70: NumPy Community | C70: Computing library | Standard, specification or protocol | D70: Actual system proven in operational environment | E70: Actively Maintained | F70: 1-5 | G70: 6-10 | H70: NumFOCUS; UC Berkeley; Quansight; NVIDIA | I70: Not applicable | J70: =Calc!B70 | K70: =Calc!C70 | L70: =Calc!F70 | M70: =Verification!E70 | N70: =Calc!I70 | O70: =AVERAGE(J70:N70) | P70: =RANK.EQ(O70,$O$2:$O$113,0) | Q70: Review affiliation coding; override available; Service-delivery field not applicable/unknown scored 0
A71: OA.Report | B71: OA.Works | C71: Open access or subscription management tool | Research profiling system | D71: Actual system proven in operational environment | E71: Actively Maintained | F71: 6-10 | G71: 0 | H71: Code for Science & Society (fiscal sponsor of OA.Works) | I71: Through solution provider only | J71: =Calc!B71 | K71: =Calc!C71 | L71: =Calc!F71 | M71: =Verification!E71 | N71: =Calc!I71 | O71: =AVERAGE(J71:N71) | P71: =RANK.EQ(O71,$O$2:$O$113,0) | Q71: Review affiliation coding; override available
A72: OA Switchboard | B72: Stichting OA Switchboard | C72: Open access or subscription management tool | D72: Actual system proven in operational environment | E72: Actively Maintained | I72: Not applicable | J72: =Calc!B72 | K72: =Calc!C72 | L72: =Calc!F72 | M72: =Verification!E72 | N72: =Calc!I72 | O72: =AVERAGE(J72:N72) | P72: =RANK.EQ(O72,$O$2:$O$113,0) | Q72: Full-time staffing missing/unknown scored 0; Volunteer staffing missing/unknown scored 0; Service-delivery field not applicable/unknown scored 0
A73: Omeka | B73: Digital Scholar | C73: Digital library, collection or exhibit platform | D73: Actual system proven in operational environment | E73: Actively Maintained | I73: Through solution provider only | J73: =Calc!B73 | K73: =Calc!C73 | L73: =Calc!F73 | M73: =Verification!E73 | N73: =Calc!I73 | O73: =AVERAGE(J73:N73) | P73: =RANK.EQ(O73,$O$2:$O$113,0) | Q73: Full-time staffing missing/unknown scored 0; Volunteer staffing missing/unknown scored 0
A74: OpenAIRE Graph | B74: OpenAIRE | C74: Discovery system | Open scholarly dataset | D74: Actual system proven in operational environment | E74: Actively Maintained | H74: Athena Research Centre (ARC) The National Research Council of Italy Institute of Information Science and Technologies (ISTI-CNR) Interdisciplinary Centre for Mathematical and Computational Modelling at University of Warsaw (ICM) | I74: Not applicable | J74: =Calc!B74 | K74: =Calc!C74 | L74: =Calc!F74 | M74: =Verification!E74 | N74: =Calc!I74 | O74: =AVERAGE(J74:N74) | P74: =RANK.EQ(O74,$O$2:$O$113,0) | Q74: Full-time staffing missing/unknown scored 0; Volunteer staffing missing/unknown scored 0; Review affiliation coding; override available; Service-delivery field not applicable/unknown scored 0
A75: OpenAlex | B75: OurResearch | C75: Open scholarly dataset | D75: Actual system proven in operational environment | E75: Actively Maintained | I75: Not applicable | J75: =Calc!B75 | K75: =Calc!C75 | L75: =Calc!F75 | M75: =Verification!E75 | N75: =Calc!I75 | O75: =AVERAGE(J75:N75) | P75: =RANK.EQ(O75,$O$2:$O$113,0) | Q75: Full-time staffing missing/unknown scored 0; Volunteer staffing missing/unknown scored 0; Service-delivery field not applicable/unknown scored 0
A76: OpenAPC | B76: Bielefeld University | C76: Open scholarly dataset | D76: Actual system proven in operational environment | E76: Actively Maintained | F76: 1-5 | G76: 0 | H76: OpenAPC is located at Bielefeld University Library. The project was set up in collaboration with the DINI working group Electronic Publishing. Since 2021 it is part of OpenAIRE Nexus. | I76: Not applicable | J76: =Calc!B76 | K76: =Calc!C76 | L76: =Calc!F76 | M76: =Verification!E76 | N76: =Calc!I76 | O76: =AVERAGE(J76:N76) | P76: =RANK.EQ(O76,$O$2:$O$113,0) | Q76: Review affiliation coding; override available; Service-delivery field not applicable/unknown scored 0
A77: OpenCitations | B77: Research Centre for Open Scholarly Metadata, University of Bologna | C77: Open scholarly dataset | D77: Actual system proven in operational environment | E77: Actively Maintained | F77: 6-10 | G77: 1-5 | H77: Research Centre for Open Scholarly Metadata, University of Bologna | I77: Not applicable | J77: =Calc!B77 | K77: =Calc!C77 | L77: =Calc!F77 | M77: =Verification!E77 | N77: =Calc!I77 | O77: =AVERAGE(J77:N77) | P77: =RANK.EQ(O77,$O$2:$O$113,0) | Q77: Review affiliation coding; override available; Service-delivery field not applicable/unknown scored 0
A78: openCost | B78: openCost | C78: Open scholarly dataset | Standard, specification or protocol | D78: Actual system proven in operational environment | E78: Actively Maintained | H78: Bielefeld University Library, the German Electron Synchrotron DESY (Hamburg) and University Library of Regensburg | I78: Not applicable | J78: =Calc!B78 | K78: =Calc!C78 | L78: =Calc!F78 | M78: =Verification!E78 | N78: =Calc!I78 | O78: =AVERAGE(J78:N78) | P78: =RANK.EQ(O78,$O$2:$O$113,0) | Q78: Full-time staffing missing/unknown scored 0; Volunteer staffing missing/unknown scored 0; Review affiliation coding; override available; Service-delivery field not applicable/unknown scored 0
A79: Open Data Editor | B79: Open Knowledge Foundation | C79: Data collection or management tool | D79: Actual system proven in operational environment | E79: Actively Maintained | F79: 11-20 | G79: More than 20 | H79: Digital Public Goods Alliance, Open Knowledge Brazil, Open Knowledge Nepal, Escuela de Datos help disseminate the tool. | I79: Not applicable | J79: =Calc!B79 | K79: =Calc!C79 | L79: =Calc!F79 | M79: =Verification!E79 | N79: =Calc!I79 | O79: =AVERAGE(J79:N79) | P79: =RANK.EQ(O79,$O$2:$O$113,0) | Q79: Review affiliation coding; override available; Service-delivery field not applicable/unknown scored 0
A80: OpenEdition | B80: OpenEdition Center, Aix-Marseille University, the EHESS and Avignon University | C80: Discovery system | D80: Actual system proven in operational environment | E80: Unknown | I80: Not applicable | J80: =Calc!B80 | K80: =Calc!C80 | L80: =Calc!F80 | M80: =Verification!E80 | N80: =Calc!I80 | O80: =AVERAGE(J80:N80) | P80: =RANK.EQ(O80,$O$2:$O$113,0) | Q80: Full-time staffing missing/unknown scored 0; Volunteer staffing missing/unknown scored 0; Service-delivery field not applicable/unknown scored 0
A81: Open Journal Systems (OJS) | B81: Public Knowledge Project (PKP) | C81: Publishing system | D81: Actual system proven in operational environment | E81: Actively Maintained | I81: Through solution provider or third party vendor | J81: =Calc!B81 | K81: =Calc!C81 | L81: =Calc!F81 | M81: =Verification!E81 | N81: =Calc!I81 | O81: =AVERAGE(J81:N81) | P81: =RANK.EQ(O81,$O$2:$O$113,0) | Q81: Full-time staffing missing/unknown scored 0; Volunteer staffing missing/unknown scored 0
A82: Open Monograph Press (OMP) | B82: Public Knowledge Project (PKP) | C82: Publishing system | D82: Actual system proven in operational environment | E82: Actively Maintained | I82: Through solution provider or third party vendor | J82: =Calc!B82 | K82: =Calc!C82 | L82: =Calc!F82 | M82: =Verification!E82 | N82: =Calc!I82 | O82: =AVERAGE(J82:N82) | P82: =RANK.EQ(O82,$O$2:$O$113,0) | Q82: Full-time staffing missing/unknown scored 0; Volunteer staffing missing/unknown scored 0
A83: Open Preprint Systems (OPS) | B83: Public Knowledge Project (PKP) | C83: Publishing system | D83: Actual system proven in operational environment | E83: Actively Maintained | I83: Through solution provider or third party vendor | J83: =Calc!B83 | K83: =Calc!C83 | L83: =Calc!F83 | M83: =Verification!E83 | N83: =Calc!I83 | O83: =AVERAGE(J83:N83) | P83: =RANK.EQ(O83,$O$2:$O$113,0) | Q83: Full-time staffing missing/unknown scored 0; Volunteer staffing missing/unknown scored 0
A84: Openverse | B84: WordPress Foundation | C84: Discovery system | D84: Actual system proven in operational environment | E84: Actively Maintained | F84: 6-10 | G84: Unknown | H84: Openverse is part of the WordPress open source project: https://wordpress.org/ | I84: Not applicable | J84: =Calc!B84 | K84: =Calc!C84 | L84: =Calc!F84 | M84: =Verification!E84 | N84: =Calc!I84 | O84: =AVERAGE(J84:N84) | P84: =RANK.EQ(O84,$O$2:$O$113,0) | Q84: Review affiliation coding; override available; Service-delivery field not applicable/unknown scored 0
A85: O Portal Brasileiro de Publicações e Dados Científicos em Acesso Aberto (The Brazilian Open Access Publications and Scientific Data Portal) (Oasisbr) | B85: Instituto Brasileiro de Informação em Ciência e Tecnologia (Brazilian Institute of Information in Science and Technology) (Ibict) | C85: Repository service | D85: Actual system proven in operational environment | E85: Actively Maintained | I85: Not applicable | J85: =Calc!B85 | K85: =Calc!C85 | L85: =Calc!F85 | M85: =Verification!E85 | N85: =Calc!I85 | O85: =AVERAGE(J85:N85) | P85: =RANK.EQ(O85,$O$2:$O$113,0) | Q85: Full-time staffing missing/unknown scored 0; Volunteer staffing missing/unknown scored 0; Service-delivery field not applicable/unknown scored 0
A86: OSF (Open Science Framework) | B86: Center for Open Science, Inc. | C86: Repository service | Repository software | D86: Actual system proven in operational environment | E86: Actively Maintained | I86: Through solution provider only | J86: =Calc!B86 | K86: =Calc!C86 | L86: =Calc!F86 | M86: =Verification!E86 | N86: =Calc!I86 | O86: =AVERAGE(J86:N86) | P86: =RANK.EQ(O86,$O$2:$O$113,0) | Q86: Full-time staffing missing/unknown scored 0; Volunteer staffing missing/unknown scored 0
A87: Oxford Common File Layout | B87: Oxford Common File Layout (OCFL) | C87: Standard, specification or protocol | D87: Actual system proven in operational environment | E87: Actively Maintained | I87: Not applicable | J87: =Calc!B87 | K87: =Calc!C87 | L87: =Calc!F87 | M87: =Verification!E87 | N87: =Calc!I87 | O87: =AVERAGE(J87:N87) | P87: =RANK.EQ(O87,$O$2:$O$113,0) | Q87: Full-time staffing missing/unknown scored 0; Volunteer staffing missing/unknown scored 0; Service-delivery field not applicable/unknown scored 0
A88: Peer Community In | B88: PCI, Peer Community In | C88: Peer review system | D88: Actual system proven in operational environment | E88: Actively Maintained | I88: Not applicable | J88: =Calc!B88 | K88: =Calc!C88 | L88: =Calc!F88 | M88: =Verification!E88 | N88: =Calc!I88 | O88: =AVERAGE(J88:N88) | P88: =RANK.EQ(O88,$O$2:$O$113,0) | Q88: Full-time staffing missing/unknown scored 0; Volunteer staffing missing/unknown scored 0; Service-delivery field not applicable/unknown scored 0
A89: PKP Preservation Network | B89: Public Knowledge Project (PKP) | C89: Digital preservation service | D89: Actual system proven in operational environment | E89: Actively Maintained | F89: More than 20 | H89: See OJS for affiliations. | I89: Not applicable | J89: =Calc!B89 | K89: =Calc!C89 | L89: =Calc!F89 | M89: =Verification!E89 | N89: =Calc!I89 | O89: =AVERAGE(J89:N89) | P89: =RANK.EQ(O89,$O$2:$O$113,0) | Q89: Volunteer staffing missing/unknown scored 0; Review affiliation coding; override available; Service-delivery field not applicable/unknown scored 0
A90: PREreview | B90: Code for Science and Society | C90: Discovery system | Peer review system | D90: Actual system proven in operational environment | E90: Actively Maintained | F90: 1-5 | I90: Not applicable | J90: =Calc!B90 | K90: =Calc!C90 | L90: =Calc!F90 | M90: =Verification!E90 | N90: =Calc!I90 | O90: =AVERAGE(J90:N90) | P90: =RANK.EQ(O90,$O$2:$O$113,0) | Q90: Volunteer staffing missing/unknown scored 0; Service-delivery field not applicable/unknown scored 0
A91: Pressbooks | B91: Book Oven, Inc. | C91: Publishing system | D91: Actual system proven in operational environment | E91: Actively Maintained | I91: Through solution provider only | J91: =Calc!B91 | K91: =Calc!C91 | L91: =Calc!F91 | M91: =Verification!E91 | N91: =Calc!I91 | O91: =AVERAGE(J91:N91) | P91: =RANK.EQ(O91,$O$2:$O$113,0) | Q91: Full-time staffing missing/unknown scored 0; Volunteer staffing missing/unknown scored 0
A92: Public Access Submission System | B92: Eclipse Foundation | C92: Submissions system | D92: Actual system proven in operational environment | E92: Actively Maintained | I92: No services available | J92: =Calc!B92 | K92: =Calc!C92 | L92: =Calc!F92 | M92: =Verification!E92 | N92: =Calc!I92 | O92: =AVERAGE(J92:N92) | P92: =RANK.EQ(O92,$O$2:$O$113,0) | Q92: Full-time staffing missing/unknown scored 0; Volunteer staffing missing/unknown scored 0
A93: Public Utility Data Liberation (PUDL) | B93: Catalyst Cooperative | C93: Open scholarly dataset | Web archiving system | D93: Actual system proven in operational environment | E93: Actively Maintained | F93: 6-10 | G93: 0 | H93: RMI GridLab | I93: No services available | J93: =Calc!B93 | K93: =Calc!C93 | L93: =Calc!F93 | M93: =Verification!E93 | N93: =Calc!I93 | O93: =AVERAGE(J93:N93) | P93: =RANK.EQ(O93,$O$2:$O$113,0) | Q93: Review affiliation coding; override available
A94: PubPub | B94: Knowledge Futures | C94: Publishing system | D94: System complete and qualified | E94: Actively Maintained | I94: Through solution provider only | J94: =Calc!B94 | K94: =Calc!C94 | L94: =Calc!F94 | M94: =Verification!E94 | N94: =Calc!I94 | O94: =AVERAGE(J94:N94) | P94: =RANK.EQ(O94,$O$2:$O$113,0) | Q94: Full-time staffing missing/unknown scored 0; Volunteer staffing missing/unknown scored 0
A95: Pundit | B95: Net7 Srl | C95: Annotations system | D95: Actual system proven in operational environment | E95: Actively Maintained | F95: More than 20 | G95: 0 | H95: No affiliations | I95: Through solution provider only | J95: =Calc!B95 | K95: =Calc!C95 | L95: =Calc!F95 | M95: =Verification!E95 | N95: =Calc!I95 | O95: =AVERAGE(J95:N95) | P95: =RANK.EQ(O95,$O$2:$O$113,0) | Q95: Review affiliation coding; override available
A96: pyOpenSci | B96: Community Initiatives | C96: Research software community | D96: Actual system proven in operational environment | E96: Actively Maintained | F96: 1-5 | G96: More than 20 | H96: Community Initiatives is our Fiscal sponsor | I96: Not applicable | J96: =Calc!B96 | K96: =Calc!C96 | L96: =Calc!F96 | M96: =Verification!E96 | N96: =Calc!I96 | O96: =AVERAGE(J96:N96) | P96: =RANK.EQ(O96,$O$2:$O$113,0) | Q96: Review affiliation coding; override available; Service-delivery field not applicable/unknown scored 0
A97: Renku | B97: Swiss Data Science Center | C97: Data management planning tool or service | Discovery system | Research software community | D97: Actual system proven in operational environment | E97: Actively Maintained | F97: 11-20 | G97: 1-5 | H97: The Renku platform at renkulab.io (“Renku”) is managed jointly by the Ecole Polytechnique Fédérale de Lausanne (« EPFL ») and the Eidgenössische Technische Hochschule Zürich (« ETHZ »), Rämistrasse 101, 8092 Zürich, Switzerland. | I97: Through solution provider or third party vendor | J97: =Calc!B97 | K97: =Calc!C97 | L97: =Calc!F97 | M97: =Verification!E97 | N97: =Calc!I97 | O97: =AVERAGE(J97:N97) | P97: =RANK.EQ(O97,$O$2:$O$113,0) | Q97: Review affiliation coding; override available
A98: RePEc | B98: RePEc | C98: Discovery system | Index or directory | D98: Actual system proven in operational environment | E98: Minimally Maintained | F98: 0 | H98: Since 2010‒10‒01, RePEc has been an independent project of the Open Library Society. | I98: Not applicable | J98: =Calc!B98 | K98: =Calc!C98 | L98: =Calc!F98 | M98: =Verification!E98 | N98: =Calc!I98 | O98: =AVERAGE(J98:N98) | P98: =RANK.EQ(O98,$O$2:$O$113,0) | Q98: Volunteer staffing missing/unknown scored 0; Review affiliation coding; override available; Service-delivery field not applicable/unknown scored 0
A99: Research Organization Registry (ROR) | B99: California Digital Library, Crossref, DataCite | C99: Persistent identifier service | D99: Actual system proven in operational environment | E99: Actively Maintained | I99: Not applicable | J99: =Calc!B99 | K99: =Calc!C99 | L99: =Calc!F99 | M99: =Verification!E99 | N99: =Calc!I99 | O99: =AVERAGE(J99:N99) | P99: =RANK.EQ(O99,$O$2:$O$113,0) | Q99: Full-time staffing missing/unknown scored 0; Volunteer staffing missing/unknown scored 0; Service-delivery field not applicable/unknown scored 0
A100: Rogue Scholar | B100: The Rogue Scholar | C100: Digital preservation system | Discovery system | D100: Actual system proven in operational environment | E100: Actively Maintained | I100: Not applicable | J100: =Calc!B100 | K100: =Calc!C100 | L100: =Calc!F100 | M100: =Verification!E100 | N100: =Calc!I100 | O100: =AVERAGE(J100:N100) | P100: =RANK.EQ(O100,$O$2:$O$113,0) | Q100: Full-time staffing missing/unknown scored 0; Volunteer staffing missing/unknown scored 0; Service-delivery field not applicable/unknown scored 0
...

Sheet Metric Rules
A1: Code | B1: Metric | C1: Source field(s) | D1: Weight | E1: Scoring criteria | F1: Unavailable-data treatment | G1: Interpretation / caution
A2: M1 | B2: Technology readiness | C2: 079 | D2: 0.2 | E2: Nine-stage source scale: score = level / 9 x 100. Observed: Actual system proven in operational environment=100; System complete and qualified=88.89; Technology validated in relevant environment=55.56. | F2: Unknown, blank, or unrecognized=0. | G2: Ordinal normalization on the source readiness scale; current data are concentrated at the highest level.
A3: M2 | B3: Maintenance status | C3: 080 | D3: 0.2 | E3: Actively Maintained=100; Minimally Maintained=50; Inactive/not maintained=0. | F3: Unknown or blank=0. | G3: Current responses are highly concentrated at actively maintained.
A4: H1 | B4: Human-resource capacity | C4: 054 + 055 | D4: 0.2 | E4: Score each field: 0 people=0; 1-5=25; 6-10=50; 11-20=75; >20=100. H1=(full-time score+volunteer score)/2. | F4: Unknown or blank in either field=0 for that field; H1 remains the average of both fields. | G4: Ordinal ranges, not exact headcounts. Paid and volunteer staffing each contribute half of H1.
A5: I2 | B5: Institutional affiliations and support | C5: 058 | D5: 0.2 | E5: Formal host or explicit operational/financial support=100; substantive affiliation/membership without stated operational support=50; explicit absence/placeholders=0. | F5: Blank or unknown=0. Free-text provisional coding can be overridden on Verification sheet with 0, 50, or 100. | G5: Narrative coding needs consistent review; an override changes the Scoring sheet formula after recalculation in Excel.
A6: O1 | B6: Hosted/service-delivery capacity | C6: 076 | D6: 0.2 | E6: Any 'Through ...' hosted/service route=100; No services available=0. | F6: Not applicable, unknown, or blank=0. | G6: Measures reported service availability, not quality, uptime, affordability, or control.

Sheet Methodology
A1: Methodology and interpretation | B1: Details
A2: Metric selection | B2: Five measures are retained: technology readiness, maintenance, combined staffing, institutional affiliations/support, and hosted/service-delivery capacity. M3 Infrastructure age and I1 Formal organizational host are excluded. Funding, legal form, SCOSS, and provider-list fields remain descriptive, not scored.
A3: Equal weighting | B3: Each of the five metrics receives 20%. Equal weighting is a transparent analytic choice; it is not estimated from the observed data or claimed to establish equal causal importance.
A4: Final formula | B4: Organizational Capacity Score = (M1 + M2 + H1 + I2 + O1) / 5. Each metric is first placed on a 0-100 scale.
A5: Missing-data rule | B5: No coverage or eligibility threshold is applied. Blank, unknown, not applicable, or unrecognized values score 0, as requested. The denominator remains five for every infrastructure.
A6: Interpretation | B6: The zero-filled score reflects recorded capacity and data availability together. A zero for a missing field does not prove the underlying capacity is absent. Publish metric-level values and data-quality notes with the total.
A7: Human resources | B7: Full-time and volunteer staffing are subfields of one metric. Each is scored 0/25/50/75/100 by reported category; their two sub-scores are averaged. Missing/unknown subfields score zero. The category scale is ordinal.
A8: Affiliation coding | B8: Field 058 is free text. A provisional deterministic rule assigns 100 only where explicit hosting/support language is present; other substantive affiliation text receives 50; explicit absence/placeholders/blank receive 0. Review and numeric overrides (0, 50, 100) are available in Verification.
A9: Source data | B9: The workbook contains 112 source entries copied from the Organizational Capacity verification sheet and includes the source Field_Guide. The source data are preserved as a separate sheet.
A10: No performance bands | B10: No 70-point cutoff or high/medium/low categories are applied.
A11: Limitations | B11: Technology readiness and maintenance responses show little variation. Staffing and affiliation information is incomplete or narrative. Hosted/service delivery is not a direct measure of quality. These constraints should be stated when interpreting comparisons.

Sheet Parameters
A1: Code | B1: Metric | C1: Source field(s) | D1: Exact weight | E1: Displayed weight | F1: Scale
A2: M1 | B2: Technology readiness | C2: 079_technology_readiness | D2: 0.2 | E2: 20.00% | F2: 0-100
A3: M2 | B3: Maintenance status | C3: 080_maintenance_status | D3: 0.2 | E3: 20.00% | F3: 0-100
A4: H1 | B4: Human-resource capacity | C4: 054_staffing_full_time + 055_staffing_volunteer | D4: 0.2 | E4: 20.00% | F4: 0-100
A5: I2 | B5: Institutional affiliations and support | C5: 058_affiliations | D5: 0.2 | E5: 20.00% | F5: 0-100
A6: O1 | B6: Hosted/service-delivery capacity | C6: 076_saas_options | D6: 0.2 | E6: 20.00% | F6: 0-100
A7: Total | D7: 1 | E7: 100.00%
A9: Zero-fill policy | B9: All unavailable, unknown, not applicable, or unrecognized values score 0; denominator stays five.
A10: Coverage threshold | B10: None

Sheet Verification
A1: Service | B1: Raw 058 affiliation text | C1: Provisional I2 score | D1: Override I2 (0/50/100) | E1: Final I2 score | F1: Reviewer notes
A2: 2i2c | C2: 0 | E2: =IF(ISNUMBER(D2),D2,C2) | F2: Enter 0, 50, or 100 only when correcting the provisional text coding.
A3: Academic Preservation Trust (APTrust) | B3: University of Virginia | C3: 50 | E3: =IF(ISNUMBER(D3),D3,C3) | F3: Enter 0, 50, or 100 only when correcting the provisional text coding.
A4: AfricArXiv | B4: Access 2 Perspectives coordinates AfricArXiv’s operations. This includes managing day-to-day activities, overseeing submission processes, ensuring quality control, and facilitating the integration of AfricArXiv with other scholarly services | C4: 100 | E4: =IF(ISNUMBER(D4),D4,C4) | F4: Enter 0, 50, or 100 only when correcting the provisional text coding.
A5: Arches Heritage Data Management Platform | B5: Getty Conservation Institute Farallon Geographics | C5: 50 | E5: =IF(ISNUMBER(D5),D5,C5) | F5: Enter 0, 50, or 100 only when correcting the provisional text coding.
A6: Archipelago Commons | C6: 0 | E6: =IF(ISNUMBER(D6),D6,C6) | F6: Enter 0, 50, or 100 only when correcting the provisional text coding.
A7: Archival Resource Key | C7: 0 | E7: =IF(ISNUMBER(D7),D7,C7) | F7: Enter 0, 50, or 100 only when correcting the provisional text coding.
A8: Archivematica | B8: No Affiliations | C8: 0 | E8: =IF(ISNUMBER(D8),D8,C8) | F8: Enter 0, 50, or 100 only when correcting the provisional text coding.
A9: ArchivesSpace | B9: New York University and the University of California San Diego are the founding partners and have permanent seats on the Board; Lyrasis is the organizational home | C9: 100 | E9: =IF(ISNUMBER(D9),D9,C9) | F9: Enter 0, 50, or 100 only when correcting the provisional text coding.
A10: ARGOS | B10: Athena Research Center (ARC) Communication & Information Technologies Experts (CITE) | C10: 50 | E10: =IF(ISNUMBER(D10),D10,C10) | F10: Enter 0, 50, or 100 only when correcting the provisional text coding.
A11: arXiv | C11: 0 | E11: =IF(ISNUMBER(D11),D11,C11) | F11: Enter 0, 50, or 100 only when correcting the provisional text coding.
A12: AtoM | B12: No affiliations | C12: 0 | E12: =IF(ISNUMBER(D12),D12,C12) | F12: Enter 0, 50, or 100 only when correcting the provisional text coding.
A13: Avalon Media System | B13: Indiana University Libraries | C13: 50 | E13: =IF(ISNUMBER(D13),D13,C13) | F13: Enter 0, 50, or 100 only when correcting the provisional text coding.
A14: Biodiversity Heritage Library | B14: BHL’s fiscal sponsor is the Council on Library and Information Resources (CLIR). | C14: 100 | E14: =IF(ISNUMBER(D14),D14,C14) | F14: Enter 0, 50, or 100 only when correcting the provisional text coding.
A15: bioRxiv | C15: 0 | E15: =IF(ISNUMBER(D15),D15,C15) | F15: Enter 0, 50, or 100 only when correcting the provisional text coding.
A16: BitCurator Environment | B16: BitCurator Consortium is administratively hosted by the Open Library Foundation. | C16: 100 | E16: =IF(ISNUMBER(D16),D16,C16) | F16: Enter 0, 50, or 100 only when correcting the provisional text coding.
A17: Blacklight | B17: See website | C17: 0 | E17: =IF(ISNUMBER(D17),D17,C17) | F17: Enter 0, 50, or 100 only when correcting the provisional text coding.
A18: BrCRIS | C18: 0 | E18: =IF(ISNUMBER(D18),D18,C18) | F18: Enter 0, 50, or 100 only when correcting the provisional text coding.
A19: Browsertrix | B19: No affiliations have direct involvement in governing or running our products except us. We are members of the International Internet Preservation Consortium (IIPC). | C19: 50 | E19: =IF(ISNUMBER(D19),D19,C19) | F19: Enter 0, 50, or 100 only when correcting the provisional text coding.
A20: CLOCKSS | B20: n/a | C20: 0 | E20: =IF(ISNUMBER(D20),D20,C20) | F20: Enter 0, 50, or 100 only when correcting the provisional text coding.
A21: COAR International Repository Directory (IRD) | B21: Responsible Organisations: https://ird.coar-repositories.org/about?lang=en | C21: 50 | E21: =IF(ISNUMBER(D21),D21,C21) | F21: Enter 0, 50, or 100 only when correcting the provisional text coding.
A22: COAR Notify | B22: No affiliations. | C22: 0 | E22: =IF(ISNUMBER(D22),D22,C22) | F22: Enter 0, 50, or 100 only when correcting the provisional text coding.
A23: CollectiveAccess | B23: No affiliations | C23: 0 | E23: =IF(ISNUMBER(D23),D23,C23) | F23: Enter 0, 50, or 100 only when correcting the provisional text coding.
A24: CORE | C24: 0 | E24: =IF(ISNUMBER(D24),D24,C24) | F24: Enter 0, 50, or 100 only when correcting the provisional text coding.
A25: COUNTER Code of Practice | C25: 0 | E25: =IF(ISNUMBER(D25),D25,C25) | F25: Enter 0, 50, or 100 only when correcting the provisional text coding.
A26: Creative Commons Licenses | C26: 0 | E26: =IF(ISNUMBER(D26),D26,C26) | F26: Enter 0, 50, or 100 only when correcting the provisional text coding.
A27: Crossref Metadata Retrieval | C27: 0 | E27: =IF(ISNUMBER(D27),D27,C27) | F27: Enter 0, 50, or 100 only when correcting the provisional text coding.
A28: D4Science Infrastructure | B28: D4Science is managed by the Italian National Research Council (CNR). Its headquarters are hosted by CNR's Institute of Information Science and Technologies "A. Faedo" (CNR-ISTI) in Pisa, Tuscany, Italy. | C28: 100 | E28: =IF(ISNUMBER(D28),D28,C28) | F28: Enter 0, 50, or 100 only when correcting the provisional text coding.
A29: DART (Digital Archivist's Resource Tool) | B29: University of Virginia | C29: 50 | E29: =IF(ISNUMBER(D29),D29,C29) | F29: Enter 0, 50, or 100 only when correcting the provisional text coding.
A30: Database Information System | B30: DBIS is operated by the University Library of Regensburg. | C30: 50 | E30: =IF(ISNUMBER(D30),D30,C30) | F30: Enter 0, 50, or 100 only when correcting the provisional text coding.
A31: Data Citation Corpus | B31: DataCite leads the development of the Data Citation Corpus as part of Make Data Count activities. | C31: 50 | E31: =IF(ISNUMBER(D31),D31,C31) | F31: Enter 0, 50, or 100 only when correcting the provisional text coding.
A32: DataCite | C32: 0 | E32: =IF(ISNUMBER(D32),D32,C32) | F32: Enter 0, 50, or 100 only when correcting the provisional text coding.
A33: Data Stewardship Wizard | B33: Czech Technical University in Prague / ELIXIR-CZ Codevence Solutions | C33: 50 | E33: =IF(ISNUMBER(D33),D33,C33) | F33: Enter 0, 50, or 100 only when correcting the provisional text coding.
A34: Dataverse | C34: 0 | E34: =IF(ISNUMBER(D34),D34,C34) | F34: Enter 0, 50, or 100 only when correcting the provisional text coding.
A35: DLCM Backend | B35: University of Geneva (https://www.unige.ch/) HEG, HES-SO (https://www.hesge.ch/heg/en) UNIFR (https://www.unifr.ch/home/en/) BFH (https://www.bfh.ch/en/) OLOS (https://olos.swiss/) | C35: 50 | E35: =IF(ISNUMBER(D35),D35,C35) | F35: Enter 0, 50, or 100 only when correcting the provisional text coding.
A36: DLCM Portal | B36: University of Geneva (https://www.unige.ch/)HEG, HES-SO (https://www.hesge.ch/heg/en)UNIFR (https://www.unifr.ch/home/en/)BFH (https://www.bfh.ch/en/)OLOS (https://olos.swiss/) | C36: 50 | E36: =IF(ISNUMBER(D36),D36,C36) | F36: Enter 0, 50, or 100 only when correcting the provisional text coding.
A37: DMP Tool | C37: 0 | E37: =IF(ISNUMBER(D37),D37,C37) | F37: Enter 0, 50, or 100 only when correcting the provisional text coding.
A38: DOAJ (Directory of Open Access Journals) | C38: 0 | E38: =IF(ISNUMBER(D38),D38,C38) | F38: Enter 0, 50, or 100 only when correcting the provisional text coding.
A39: dokieli | C39: 0 | E39: =IF(ISNUMBER(D39),D39,C39) | F39: Enter 0, 50, or 100 only when correcting the provisional text coding.
A40: Dryad | C40: 0 | E40: =IF(ISNUMBER(D40),D40,C40) | F40: Enter 0, 50, or 100 only when correcting the provisional text coding.
A41: DSpace | C41: 0 | E41: =IF(ISNUMBER(D41),D41,C41) | F41: Enter 0, 50, or 100 only when correcting the provisional text coding.
A42: DuraCloud | B42: N/A | C42: 0 | E42: =IF(ISNUMBER(D42),D42,C42) | F42: Enter 0, 50, or 100 only when correcting the provisional text coding.
A43: Episciences | B43: The financing of the CCSD is jointly ensured by its supervising bodies (CNRS, Inria, INRAE) ; the French Ministry of higher education and research (MESR) Inria and Institut Fourier bring a specific support to Episciences by their contribution to the editorial support of the journals. The IT infrastructure of Episciences is shared with HAL and Sciencesconf. Long-term preservation of content published on Episciences is ensured by C.I.N.E.S. (Centre Informatique National de l’Enseignement Supérieur). | C43: 50 | E43: =IF(ISNUMBER(D43),D43,C43) | F43: Enter 0, 50, or 100 only when correcting the provisional text coding.
A44: EPrints | B44: ECS Partners Ltd | C44: 50 | E44: =IF(ISNUMBER(D44),D44,C44) | F44: Enter 0, 50, or 100 only when correcting the provisional text coding.
A45: Érudit | C45: 0 | E45: =IF(ISNUMBER(D45),D45,C45) | F45: Enter 0, 50, or 100 only when correcting the provisional text coding.
A46: Europe PMC | C46: 0 | E46: =IF(ISNUMBER(D46),D46,C46) | F46: Enter 0, 50, or 100 only when correcting the provisional text coding.
A47: FAIR Wizard | B47: Codevence Solutions s.r.o. | C47: 50 | E47: =IF(ISNUMBER(D47),D47,C47) | F47: Enter 0, 50, or 100 only when correcting the provisional text coding.
A48: Fedora | C48: 0 | E48: =IF(ISNUMBER(D48),D48,C48) | F48: Enter 0, 50, or 100 only when correcting the provisional text coding.
A49: fido | B49: Artefactual | C49: 50 | E49: =IF(ISNUMBER(D49),D49,C49) | F49: Enter 0, 50, or 100 only when correcting the provisional text coding.
A50: Fulcrum | C50: 0 | E50: =IF(ISNUMBER(D50),D50,C50) | F50: Enter 0, 50, or 100 only when correcting the provisional text coding.
A51: Galaxy | B51: It's an open source project with many affiliations. | C51: 50 | E51: =IF(ISNUMBER(D51),D51,C51) | F51: Enter 0, 50, or 100 only when correcting the provisional text coding.
A52: GeoServer | B52: https://www.osgeo.org https://www.geosolutionsgroup.com/ https://www.afrigis.co.za/ https://www.geocat.net/ https://camptocamp.com/ | C52: 50 | E52: =IF(ISNUMBER(D52),D52,C52) | F52: Enter 0, 50, or 100 only when correcting the provisional text coding.
A53: Hyku | C53: 0 | E53: =IF(ISNUMBER(D53),D53,C53) | F53: Enter 0, 50, or 100 only when correcting the provisional text coding.
A54: Hyrax | B54: No affiliations | C54: 0 | E54: =IF(ISNUMBER(D54),D54,C54) | F54: Enter 0, 50, or 100 only when correcting the provisional text coding.
A55: IIIF | C55: 0 | E55: =IF(ISNUMBER(D55),D55,C55) | F55: Enter 0, 50, or 100 only when correcting the provisional text coding.
A56: ImpactU | B56: ImpactU is created and coordinated by CoLaV at the Universidad de Antioquia, the Universidad del Valle, the Universidad Externado de Colombia and the Universidad Autonoma Latinoamericana. It is in the process of constituting a national consortium authorized by ASCUN which will democratize ownership between all the Colombian institutions interested in membership. | C56: 50 | E56: =IF(ISNUMBER(D56),D56,C56) | F56: Enter 0, 50, or 100 only when correcting the provisional text coding.
A57: International Generic Sample Number (IGSN) | B57: DataCite e.V. SESAR GFZ Data Services Kiel University IGSN Service Lithodat Pty Ltd Commonwealth Scientific and Industrial Research Organisation Institut Français de Recherche pour l'Exploitation de la Mer | C57: 50 | E57: =IF(ISNUMBER(D57),D57,C57) | F57: Enter 0, 50, or 100 only when correcting the provisional text coding.
A58: InvenioRDM | C58: 0 | E58: =IF(ISNUMBER(D58),D58,C58) | F58: Enter 0, 50, or 100 only when correcting the provisional text coding.
A59: iRODS | B59: Executive Board Members (Premier Level) | C59: 50 | E59: =IF(ISNUMBER(D59),D59,C59) | F59: Enter 0, 50, or 100 only when correcting the provisional text coding.
A60: Islandora | C60: 0 | E60: =IF(ISNUMBER(D60),D60,C60) | F60: Enter 0, 50, or 100 only when correcting the provisional text coding.
A61: Janeway | C61: 0 | E61: =IF(ISNUMBER(D61),D61,C61) | F61: Enter 0, 50, or 100 only when correcting the provisional text coding.
A62: JHOVE | B62: <a href="https://openpreservation.org/membership/meet-our-members/" target="_blank">OPF Membership</a> | C62: 50 | E62: =IF(ISNUMBER(D62),D62,C62) | F62: Enter 0, 50, or 100 only when correcting the provisional text coding.
A63: LA Referencia | C63: 0 | E63: =IF(ISNUMBER(D63),D63,C63) | F63: Enter 0, 50, or 100 only when correcting the provisional text coding.
A64: Manifold | C64: 0 | E64: =IF(ISNUMBER(D64),D64,C64) | F64: Enter 0, 50, or 100 only when correcting the provisional text coding.
A65: medRxiv | C65: 0 | E65: =IF(ISNUMBER(D65),D65,C65) | F65: Enter 0, 50, or 100 only when correcting the provisional text coding.
A66: Metadata Encoding and Transmission Standard (METS) | B66: Library of Congress provides hosting support for the METS schema; the METS editorial board functions as an independent community group. | C66: 50 | E66: =IF(ISNUMBER(D66),D66,C66) | F66: Enter 0, 50, or 100 only when correcting the provisional text coding.
A67: Mirador | C67: 0 | E67: =IF(ISNUMBER(D67),D67,C67) | F67: Enter 0, 50, or 100 only when correcting the provisional text coding.
A68: Mukurtu CMS | C68: 0 | E68: =IF(ISNUMBER(D68),D68,C68) | F68: Enter 0, 50, or 100 only when correcting the provisional text coding.
A69: MyCoRe | B69: Regional Computer Center, Hamburg University | C69: 50 | E69: =IF(ISNUMBER(D69),D69,C69) | F69: Enter 0, 50, or 100 only when correcting the provisional text coding.
A70: NumPy | B70: NumFOCUS; UC Berkeley; Quansight; NVIDIA | C70: 50 | E70: =IF(ISNUMBER(D70),D70,C70) | F70: Enter 0, 50, or 100 only when correcting the provisional text coding.
A71: OA.Report | B71: Code for Science & Society (fiscal sponsor of OA.Works) | C71: 100 | E71: =IF(ISNUMBER(D71),D71,C71) | F71: Enter 0, 50, or 100 only when correcting the provisional text coding.
A72: OA Switchboard | C72: 0 | E72: =IF(ISNUMBER(D72),D72,C72) | F72: Enter 0, 50, or 100 only when correcting the provisional text coding.
A73: Omeka | C73: 0 | E73: =IF(ISNUMBER(D73),D73,C73) | F73: Enter 0, 50, or 100 only when correcting the provisional text coding.
A74: OpenAIRE Graph | B74: Athena Research Centre (ARC) The National Research Council of Italy Institute of Information Science and Technologies (ISTI-CNR) Interdisciplinary Centre for Mathematical and Computational Modelling at University of Warsaw (ICM) | C74: 50 | E74: =IF(ISNUMBER(D74),D74,C74) | F74: Enter 0, 50, or 100 only when correcting the provisional text coding.
A75: OpenAlex | C75: 0 | E75: =IF(ISNUMBER(D75),D75,C75) | F75: Enter 0, 50, or 100 only when correcting the provisional text coding.
A76: OpenAPC | B76: OpenAPC is located at Bielefeld University Library. The project was set up in collaboration with the DINI working group Electronic Publishing. Since 2021 it is part of OpenAIRE Nexus. | C76: 50 | E76: =IF(ISNUMBER(D76),D76,C76) | F76: Enter 0, 50, or 100 only when correcting the provisional text coding.
A77: OpenCitations | B77: Research Centre for Open Scholarly Metadata, University of Bologna | C77: 50 | E77: =IF(ISNUMBER(D77),D77,C77) | F77: Enter 0, 50, or 100 only when correcting the provisional text coding.
A78: openCost | B78: Bielefeld University Library, the German Electron Synchrotron DESY (Hamburg) and University Library of Regensburg | C78: 50 | E78: =IF(ISNUMBER(D78),D78,C78) | F78: Enter 0, 50, or 100 only when correcting the provisional text coding.
A79: Open Data Editor | B79: Digital Public Goods Alliance, Open Knowledge Brazil, Open Knowledge Nepal, Escuela de Datos help disseminate the tool. | C79: 50 | E79: =IF(ISNUMBER(D79),D79,C79) | F79: Enter 0, 50, or 100 only when correcting the provisional text coding.
A80: OpenEdition | C80: 0 | E80: =IF(ISNUMBER(D80),D80,C80) | F80: Enter 0, 50, or 100 only when correcting the provisional text coding.
A81: Open Journal Systems (OJS) | C81: 0 | E81: =IF(ISNUMBER(D81),D81,C81) | F81: Enter 0, 50, or 100 only when correcting the provisional text coding.
A82: Open Monograph Press (OMP) | C82: 0 | E82: =IF(ISNUMBER(D82),D82,C82) | F82: Enter 0, 50, or 100 only when correcting the provisional text coding.
A83: Open Preprint Systems (OPS) | C83: 0 | E83: =IF(ISNUMBER(D83),D83,C83) | F83: Enter 0, 50, or 100 only when correcting the provisional text coding.
A84: Openverse | B84: Openverse is part of the WordPress open source project: https://wordpress.org/ | C84: 50 | E84: =IF(ISNUMBER(D84),D84,C84) | F84: Enter 0, 50, or 100 only when correcting the provisional text coding.
A85: O Portal Brasileiro de Publicações e Dados Científicos em Acesso Aberto (The Brazilian Open Access Publications and Scientific Data Portal) (Oasisbr) | C85: 0 | E85: =IF(ISNUMBER(D85),D85,C85) | F85: Enter 0, 50, or 100 only when correcting the provisional text coding.
A86: OSF (Open Science Framework) | C86: 0 | E86: =IF(ISNUMBER(D86),D86,C86) | F86: Enter 0, 50, or 100 only when correcting the provisional text coding.
A87: Oxford Common File Layout | C87: 0 | E87: =IF(ISNUMBER(D87),D87,C87) | F87: Enter 0, 50, or 100 only when correcting the provisional text coding.
A88: Peer Community In | C88: 0 | E88: =IF(ISNUMBER(D88),D88,C88) | F88: Enter 0, 50, or 100 only when correcting the provisional text coding.
A89: PKP Preservation Network | B89: See OJS for affiliations. | C89: 50 | E89: =IF(ISNUMBER(D89),D89,C89) | F89: Enter 0, 50, or 100 only when correcting the provisional text coding.
A90: PREreview | C90: 0 | E90: =IF(ISNUMBER(D90),D90,C90) | F90: Enter 0, 50, or 100 only when correcting the provisional text coding.
A91: Pressbooks | C91: 0 | E91: =IF(ISNUMBER(D91),D91,C91) | F91: Enter 0, 50, or 100 only when correcting the provisional text coding.
A92: Public Access Submission System | C92: 0 | E92: =IF(ISNUMBER(D92),D92,C92) | F92: Enter 0, 50, or 100 only when correcting the provisional text coding.
A93: Public Utility Data Liberation (PUDL) | B93: RMI GridLab | C93: 50 | E93: =IF(ISNUMBER(D93),D93,C93) | F93: Enter 0, 50, or 100 only when correcting the provisional text coding.
A94: PubPub | C94: 0 | E94: =IF(ISNUMBER(D94),D94,C94) | F94: Enter 0, 50, or 100 only when correcting the provisional text coding.
A95: Pundit | B95: No affiliations | C95: 0 | E95: =IF(ISNUMBER(D95),D95,C95) | F95: Enter 0, 50, or 100 only when correcting the provisional text coding.
A96: pyOpenSci | B96: Community Initiatives is our Fiscal sponsor | C96: 100 | E96: =IF(ISNUMBER(D96),D96,C96) | F96: Enter 0, 50, or 100 only when correcting the provisional text coding.
A97: Renku | B97: The Renku platform at renkulab.io (“Renku”) is managed jointly by the Ecole Polytechnique Fédérale de Lausanne (« EPFL ») and the Eidgenössische Technische Hochschule Zürich (« ETHZ »), Rämistrasse 101, 8092 Zürich, Switzerland. | C97: 50 | E97: =IF(ISNUMBER(D97),D97,C97) | F97: Enter 0, 50, or 100 only when correcting the provisional text coding.
A98: RePEc | B98: Since 2010‒10‒01, RePEc has been an independent project of the Open Library Society. | C98: 50 | E98: =IF(ISNUMBER(D98),D98,C98) | F98: Enter 0, 50, or 100 only when correcting the provisional text coding.
A99: Research Organization Registry (ROR) | C99: 0 | E99: =IF(ISNUMBER(D99),D99,C99) | F99: Enter 0, 50, or 100 only when correcting the provisional text coding.
A100: Rogue Scholar | C100: 0 | E100: =IF(ISNUMBER(D100),D100,C100) | F100: Enter 0, 50, or 100 only when correcting the provisional text coding.
...

Sheet Affiliation Coding
A1: Service | B1: Raw 058 affiliation text | C1: Provisional score | D1: Coding rationale | E1: Override score | F1: Final score | G1: Review note
A2: 2i2c | C2: 0 | D2: Blank: zero under the agreed unavailable-data rule | F2: =Verification!E2 | G2: Use the override in Verification; this sheet mirrors the active score.
A3: Academic Preservation Trust (APTrust) | B3: University of Virginia | C3: 50 | D3: Substantive affiliation or membership reported; level of operational support not established | F3: =Verification!E3 | G3: Use the override in Verification; this sheet mirrors the active score.
A4: AfricArXiv | B4: Access 2 Perspectives coordinates AfricArXiv’s operations. This includes managing day-to-day activities, overseeing submission processes, ensuring quality control, and facilitating the integration of AfricArXiv with other scholarly services | C4: 100 | D4: Explicit host or operational/financial support language | F4: =Verification!E4 | G4: Use the override in Verification; this sheet mirrors the active score.
A5: Arches Heritage Data Management Platform | B5: Getty Conservation Institute Farallon Geographics | C5: 50 | D5: Substantive affiliation or membership reported; level of operational support not established | F5: =Verification!E5 | G5: Use the override in Verification; this sheet mirrors the active score.
A6: Archipelago Commons | C6: 0 | D6: Blank: zero under the agreed unavailable-data rule | F6: =Verification!E6 | G6: Use the override in Verification; this sheet mirrors the active score.
A7: Archival Resource Key | C7: 0 | D7: Blank: zero under the agreed unavailable-data rule | F7: =Verification!E7 | G7: Use the override in Verification; this sheet mirrors the active score.
A8: Archivematica | B8: No Affiliations | C8: 0 | D8: Explicit absence or placeholder | F8: =Verification!E8 | G8: Use the override in Verification; this sheet mirrors the active score.
A9: ArchivesSpace | B9: New York University and the University of California San Diego are the founding partners and have permanent seats on the Board; Lyrasis is the organizational home | C9: 100 | D9: Explicit host or operational/financial support language | F9: =Verification!E9 | G9: Use the override in Verification; this sheet mirrors the active score.
A10: ARGOS | B10: Athena Research Center (ARC) Communication & Information Technologies Experts (CITE) | C10: 50 | D10: Substantive affiliation or membership reported; level of operational support not established | F10: =Verification!E10 | G10: Use the override in Verification; this sheet mirrors the active score.
A11: arXiv | C11: 0 | D11: Blank: zero under the agreed unavailable-data rule | F11: =Verification!E11 | G11: Use the override in Verification; this sheet mirrors the active score.
A12: AtoM | B12: No affiliations | C12: 0 | D12: Explicit absence or placeholder | F12: =Verification!E12 | G12: Use the override in Verification; this sheet mirrors the active score.
A13: Avalon Media System | B13: Indiana University Libraries | C13: 50 | D13: Substantive affiliation or membership reported; level of operational support not established | F13: =Verification!E13 | G13: Use the override in Verification; this sheet mirrors the active score.
A14: Biodiversity Heritage Library | B14: BHL’s fiscal sponsor is the Council on Library and Information Resources (CLIR). | C14: 100 | D14: Explicit host or operational/financial support language | F14: =Verification!E14 | G14: Use the override in Verification; this sheet mirrors the active score.
A15: bioRxiv | C15: 0 | D15: Blank: zero under the agreed unavailable-data rule | F15: =Verification!E15 | G15: Use the override in Verification; this sheet mirrors the active score.
A16: BitCurator Environment | B16: BitCurator Consortium is administratively hosted by the Open Library Foundation. | C16: 100 | D16: Explicit host or operational/financial support language | F16: =Verification!E16 | G16: Use the override in Verification; this sheet mirrors the active score.
A17: Blacklight | B17: See website | C17: 0 | D17: Explicit absence or placeholder | F17: =Verification!E17 | G17: Use the override in Verification; this sheet mirrors the active score.
A18: BrCRIS | C18: 0 | D18: Blank: zero under the agreed unavailable-data rule | F18: =Verification!E18 | G18: Use the override in Verification; this sheet mirrors the active score.
A19: Browsertrix | B19: No affiliations have direct involvement in governing or running our products except us. We are members of the International Internet Preservation Consortium (IIPC). | C19: 50 | D19: Substantive affiliation or membership reported; level of operational support not established | F19: =Verification!E19 | G19: Use the override in Verification; this sheet mirrors the active score.
A20: CLOCKSS | B20: n/a | C20: 0 | D20: Explicit absence or placeholder | F20: =Verification!E20 | G20: Use the override in Verification; this sheet mirrors the active score.
A21: COAR International Repository Directory (IRD) | B21: Responsible Organisations: https://ird.coar-repositories.org/about?lang=en | C21: 50 | D21: Substantive affiliation or membership reported; level of operational support not established | F21: =Verification!E21 | G21: Use the override in Verification; this sheet mirrors the active score.
A22: COAR Notify | B22: No affiliations. | C22: 0 | D22: Explicit absence or placeholder | F22: =Verification!E22 | G22: Use the override in Verification; this sheet mirrors the active score.
A23: CollectiveAccess | B23: No affiliations | C23: 0 | D23: Explicit absence or placeholder | F23: =Verification!E23 | G23: Use the override in Verification; this sheet mirrors the active score.
A24: CORE | C24: 0 | D24: Blank: zero under the agreed unavailable-data rule | F24: =Verification!E24 | G24: Use the override in Verification; this sheet mirrors the active score.
A25: COUNTER Code of Practice | C25: 0 | D25: Blank: zero under the agreed unavailable-data rule | F25: =Verification!E25 | G25: Use the override in Verification; this sheet mirrors the active score.
A26: Creative Commons Licenses | C26: 0 | D26: Blank: zero under the agreed unavailable-data rule | F26: =Verification!E26 | G26: Use the override in Verification; this sheet mirrors the active score.
A27: Crossref Metadata Retrieval | C27: 0 | D27: Blank: zero under the agreed unavailable-data rule | F27: =Verification!E27 | G27: Use the override in Verification; this sheet mirrors the active score.
A28: D4Science Infrastructure | B28: D4Science is managed by the Italian National Research Council (CNR). Its headquarters are hosted by CNR's Institute of Information Science and Technologies "A. Faedo" (CNR-ISTI) in Pisa, Tuscany, Italy. | C28: 100 | D28: Explicit host or operational/financial support language | F28: =Verification!E28 | G28: Use the override in Verification; this sheet mirrors the active score.
A29: DART (Digital Archivist's Resource Tool) | B29: University of Virginia | C29: 50 | D29: Substantive affiliation or membership reported; level of operational support not established | F29: =Verification!E29 | G29: Use the override in Verification; this sheet mirrors the active score.
A30: Database Information System | B30: DBIS is operated by the University Library of Regensburg. | C30: 50 | D30: Substantive affiliation or membership reported; level of operational support not established | F30: =Verification!E30 | G30: Use the override in Verification; this sheet mirrors the active score.
A31: Data Citation Corpus | B31: DataCite leads the development of the Data Citation Corpus as part of Make Data Count activities. | C31: 50 | D31: Substantive affiliation or membership reported; level of operational support not established | F31: =Verification!E31 | G31: Use the override in Verification; this sheet mirrors the active score.
A32: DataCite | C32: 0 | D32: Blank: zero under the agreed unavailable-data rule | F32: =Verification!E32 | G32: Use the override in Verification; this sheet mirrors the active score.
A33: Data Stewardship Wizard | B33: Czech Technical University in Prague / ELIXIR-CZ Codevence Solutions | C33: 50 | D33: Substantive affiliation or membership reported; level of operational support not established | F33: =Verification!E33 | G33: Use the override in Verification; this sheet mirrors the active score.
A34: Dataverse | C34: 0 | D34: Blank: zero under the agreed unavailable-data rule | F34: =Verification!E34 | G34: Use the override in Verification; this sheet mirrors the active score.
A35: DLCM Backend | B35: University of Geneva (https://www.unige.ch/) HEG, HES-SO (https://www.hesge.ch/heg/en) UNIFR (https://www.unifr.ch/home/en/) BFH (https://www.bfh.ch/en/) OLOS (https://olos.swiss/) | C35: 50 | D35: Substantive affiliation or membership reported; level of operational support not established | F35: =Verification!E35 | G35: Use the override in Verification; this sheet mirrors the active score.
A36: DLCM Portal | B36: University of Geneva (https://www.unige.ch/)HEG, HES-SO (https://www.hesge.ch/heg/en)UNIFR (https://www.unifr.ch/home/en/)BFH (https://www.bfh.ch/en/)OLOS (https://olos.swiss/) | C36: 50 | D36: Substantive affiliation or membership reported; level of operational support not established | F36: =Verification!E36 | G36: Use the override in Verification; this sheet mirrors the active score.
A37: DMP Tool | C37: 0 | D37: Blank: zero under the agreed unavailable-data rule | F37: =Verification!E37 | G37: Use the override in Verification; this sheet mirrors the active score.
A38: DOAJ (Directory of Open Access Journals) | C38: 0 | D38: Blank: zero under the agreed unavailable-data rule | F38: =Verification!E38 | G38: Use the override in Verification; this sheet mirrors the active score.
A39: dokieli | C39: 0 | D39: Blank: zero under the agreed unavailable-data rule | F39: =Verification!E39 | G39: Use the override in Verification; this sheet mirrors the active score.
A40: Dryad | C40: 0 | D40: Blank: zero under the agreed unavailable-data rule | F40: =Verification!E40 | G40: Use the override in Verification; this sheet mirrors the active score.
A41: DSpace | C41: 0 | D41: Blank: zero under the agreed unavailable-data rule | F41: =Verification!E41 | G41: Use the override in Verification; this sheet mirrors the active score.
A42: DuraCloud | B42: N/A | C42: 0 | D42: Explicit absence or placeholder | F42: =Verification!E42 | G42: Use the override in Verification; this sheet mirrors the active score.
A43: Episciences | B43: The financing of the CCSD is jointly ensured by its supervising bodies (CNRS, Inria, INRAE) ; the French Ministry of higher education and research (MESR) Inria and Institut Fourier bring a specific support to Episciences by their contribution to the editorial support of the journals. The IT infrastructure of Episciences is shared with HAL and Sciencesconf. Long-term preservation of content published on Episciences is ensured by C.I.N.E.S. (Centre Informatique National de l’Enseignement Supérieur). | C43: 50 | D43: Substantive affiliation or membership reported; level of operational support not established | F43: =Verification!E43 | G43: Use the override in Verification; this sheet mirrors the active score.
A44: EPrints | B44: ECS Partners Ltd | C44: 50 | D44: Substantive affiliation or membership reported; level of operational support not established | F44: =Verification!E44 | G44: Use the override in Verification; this sheet mirrors the active score.
A45: Érudit | C45: 0 | D45: Blank: zero under the agreed unavailable-data rule | F45: =Verification!E45 | G45: Use the override in Verification; this sheet mirrors the active score.
A46: Europe PMC | C46: 0 | D46: Blank: zero under the agreed unavailable-data rule | F46: =Verification!E46 | G46: Use the override in Verification; this sheet mirrors the active score.
A47: FAIR Wizard | B47: Codevence Solutions s.r.o. | C47: 50 | D47: Substantive affiliation or membership reported; level of operational support not established | F47: =Verification!E47 | G47: Use the override in Verification; this sheet mirrors the active score.
A48: Fedora | C48: 0 | D48: Blank: zero under the agreed unavailable-data rule | F48: =Verification!E48 | G48: Use the override in Verification; this sheet mirrors the active score.
A49: fido | B49: Artefactual | C49: 50 | D49: Substantive affiliation or membership reported; level of operational support not established | F49: =Verification!E49 | G49: Use the override in Verification; this sheet mirrors the active score.
A50: Fulcrum | C50: 0 | D50: Blank: zero under the agreed unavailable-data rule | F50: =Verification!E50 | G50: Use the override in Verification; this sheet mirrors the active score.
A51: Galaxy | B51: It's an open source project with many affiliations. | C51: 50 | D51: Substantive affiliation or membership reported; level of operational support not established | F51: =Verification!E51 | G51: Use the override in Verification; this sheet mirrors the active score.
A52: GeoServer | B52: https://www.osgeo.org https://www.geosolutionsgroup.com/ https://www.afrigis.co.za/ https://www.geocat.net/ https://camptocamp.com/ | C52: 50 | D52: Substantive affiliation or membership reported; level of operational support not established | F52: =Verification!E52 | G52: Use the override in Verification; this sheet mirrors the active score.
A53: Hyku | C53: 0 | D53: Blank: zero under the agreed unavailable-data rule | F53: =Verification!E53 | G53: Use the override in Verification; this sheet mirrors the active score.
A54: Hyrax | B54: No affiliations | C54: 0 | D54: Explicit absence or placeholder | F54: =Verification!E54 | G54: Use the override in Verification; this sheet mirrors the active score.
A55: IIIF | C55: 0 | D55: Blank: zero under the agreed unavailable-data rule | F55: =Verification!E55 | G55: Use the override in Verification; this sheet mirrors the active score.
A56: ImpactU | B56: ImpactU is created and coordinated by CoLaV at the Universidad de Antioquia, the Universidad del Valle, the Universidad Externado de Colombia and the Universidad Autonoma Latinoamericana. It is in the process of constituting a national consortium authorized by ASCUN which will democratize ownership between all the Colombian institutions interested in membership. | C56: 50 | D56: Substantive affiliation or membership reported; level of operational support not established | F56: =Verification!E56 | G56: Use the override in Verification; this sheet mirrors the active score.
A57: International Generic Sample Number (IGSN) | B57: DataCite e.V. SESAR GFZ Data Services Kiel University IGSN Service Lithodat Pty Ltd Commonwealth Scientific and Industrial Research Organisation Institut Français de Recherche pour l'Exploitation de la Mer | C57: 50 | D57: Substantive affiliation or membership reported; level of operational support not established | F57: =Verification!E57 | G57: Use the override in Verification; this sheet mirrors the active score.
A58: InvenioRDM | C58: 0 | D58: Blank: zero under the agreed unavailable-data rule | F58: =Verification!E58 | G58: Use the override in Verification; this sheet mirrors the active score.
A59: iRODS | B59: Executive Board Members (Premier Level) | C59: 50 | D59: Substantive affiliation or membership reported; level of operational support not established | F59: =Verification!E59 | G59: Use the override in Verification; this sheet mirrors the active score.
A60: Islandora | C60: 0 | D60: Blank: zero under the agreed unavailable-data rule | F60: =Verification!E60 | G60: Use the override in Verification; this sheet mirrors the active score.
A61: Janeway | C61: 0 | D61: Blank: zero under the agreed unavailable-data rule | F61: =Verification!E61 | G61: Use the override in Verification; this sheet mirrors the active score.
A62: JHOVE | B62: <a href="https://openpreservation.org/membership/meet-our-members/" target="_blank">OPF Membership</a> | C62: 50 | D62: Substantive affiliation or membership reported; level of operational support not established | F62: =Verification!E62 | G62: Use the override in Verification; this sheet mirrors the active score.
A63: LA Referencia | C63: 0 | D63: Blank: zero under the agreed unavailable-data rule | F63: =Verification!E63 | G63: Use the override in Verification; this sheet mirrors the active score.
A64: Manifold | C64: 0 | D64: Blank: zero under the agreed unavailable-data rule | F64: =Verification!E64 | G64: Use the override in Verification; this sheet mirrors the active score.
A65: medRxiv | C65: 0 | D65: Blank: zero under the agreed unavailable-data rule | F65: =Verification!E65 | G65: Use the override in Verification; this sheet mirrors the active score.
A66: Metadata Encoding and Transmission Standard (METS) | B66: Library of Congress provides hosting support for the METS schema; the METS editorial board functions as an independent community group. | C66: 50 | D66: Substantive affiliation or membership reported; level of operational support not established | F66: =Verification!E66 | G66: Use the override in Verification; this sheet mirrors the active score.
A67: Mirador | C67: 0 | D67: Blank: zero under the agreed unavailable-data rule | F67: =Verification!E67 | G67: Use the override in Verification; this sheet mirrors the active score.
A68: Mukurtu CMS | C68: 0 | D68: Blank: zero under the agreed unavailable-data rule | F68: =Verification!E68 | G68: Use the override in Verification; this sheet mirrors the active score.
A69: MyCoRe | B69: Regional Computer Center, Hamburg University | C69: 50 | D69: Substantive affiliation or membership reported; level of operational support not established | F69: =Verification!E69 | G69: Use the override in Verification; this sheet mirrors the active score.
A70: NumPy | B70: NumFOCUS; UC Berkeley; Quansight; NVIDIA | C70: 50 | D70: Substantive affiliation or membership reported; level of operational support not established | F70: =Verification!E70 | G70: Use the override in Verification; this sheet mirrors the active score.
A71: OA.Report | B71: Code for Science & Society (fiscal sponsor of OA.Works) | C71: 100 | D71: Explicit host or operational/financial support language | F71: =Verification!E71 | G71: Use the override in Verification; this sheet mirrors the active score.
A72: OA Switchboard | C72: 0 | D72: Blank: zero under the agreed unavailable-data rule | F72: =Verification!E72 | G72: Use the override in Verification; this sheet mirrors the active score.
A73: Omeka | C73: 0 | D73: Blank: zero under the agreed unavailable-data rule | F73: =Verification!E73 | G73: Use the override in Verification; this sheet mirrors the active score.
A74: OpenAIRE Graph | B74: Athena Research Centre (ARC) The National Research Council of Italy Institute of Information Science and Technologies (ISTI-CNR) Interdisciplinary Centre for Mathematical and Computational Modelling at University of Warsaw (ICM) | C74: 50 | D74: Substantive affiliation or membership reported; level of operational support not established | F74: =Verification!E74 | G74: Use the override in Verification; this sheet mirrors the active score.
A75: OpenAlex | C75: 0 | D75: Blank: zero under the agreed unavailable-data rule | F75: =Verification!E75 | G75: Use the override in Verification; this sheet mirrors the active score.
A76: OpenAPC | B76: OpenAPC is located at Bielefeld University Library. The project was set up in collaboration with the DINI working group Electronic Publishing. Since 2021 it is part of OpenAIRE Nexus. | C76: 50 | D76: Substantive affiliation or membership reported; level of operational support not established | F76: =Verification!E76 | G76: Use the override in Verification; this sheet mirrors the active score.
A77: OpenCitations | B77: Research Centre for Open Scholarly Metadata, University of Bologna | C77: 50 | D77: Substantive affiliation or membership reported; level of operational support not established | F77: =Verification!E77 | G77: Use the override in Verification; this sheet mirrors the active score.
A78: openCost | B78: Bielefeld University Library, the German Electron Synchrotron DESY (Hamburg) and University Library of Regensburg | C78: 50 | D78: Substantive affiliation or membership reported; level of operational support not established | F78: =Verification!E78 | G78: Use the override in Verification; this sheet mirrors the active score.
A79: Open Data Editor | B79: Digital Public Goods Alliance, Open Knowledge Brazil, Open Knowledge Nepal, Escuela de Datos help disseminate the tool. | C79: 50 | D79: Substantive affiliation or membership reported; level of operational support not established | F79: =Verification!E79 | G79: Use the override in Verification; this sheet mirrors the active score.
A80: OpenEdition | C80: 0 | D80: Blank: zero under the agreed unavailable-data rule | F80: =Verification!E80 | G80: Use the override in Verification; this sheet mirrors the active score.
A81: Open Journal Systems (OJS) | C81: 0 | D81: Blank: zero under the agreed unavailable-data rule | F81: =Verification!E81 | G81: Use the override in Verification; this sheet mirrors the active score.
A82: Open Monograph Press (OMP) | C82: 0 | D82: Blank: zero under the agreed unavailable-data rule | F82: =Verification!E82 | G82: Use the override in Verification; this sheet mirrors the active score.
A83: Open Preprint Systems (OPS) | C83: 0 | D83: Blank: zero under the agreed unavailable-data rule | F83: =Verification!E83 | G83: Use the override in Verification; this sheet mirrors the active score.
A84: Openverse | B84: Openverse is part of the WordPress open source project: https://wordpress.org/ | C84: 50 | D84: Substantive affiliation or membership reported; level of operational support not established | F84: =Verification!E84 | G84: Use the override in Verification; this sheet mirrors the active score.
A85: O Portal Brasileiro de Publicações e Dados Científicos em Acesso Aberto (The Brazilian Open Access Publications and Scientific Data Portal) (Oasisbr) | C85: 0 | D85: Blank: zero under the agreed unavailable-data rule | F85: =Verification!E85 | G85: Use the override in Verification; this sheet mirrors the active score.
A86: OSF (Open Science Framework) | C86: 0 | D86: Blank: zero under the agreed unavailable-data rule | F86: =Verification!E86 | G86: Use the override in Verification; this sheet mirrors the active score.
A87: Oxford Common File Layout | C87: 0 | D87: Blank: zero under the agreed unavailable-data rule | F87: =Verification!E87 | G87: Use the override in Verification; this sheet mirrors the active score.
A88: Peer Community In | C88: 0 | D88: Blank: zero under the agreed unavailable-data rule | F88: =Verification!E88 | G88: Use the override in Verification; this sheet mirrors the active score.
A89: PKP Preservation Network | B89: See OJS for affiliations. | C89: 50 | D89: Substantive affiliation or membership reported; level of operational support not established | F89: =Verification!E89 | G89: Use the override in Verification; this sheet mirrors the active score.
A90: PREreview | C90: 0 | D90: Blank: zero under the agreed unavailable-data rule | F90: =Verification!E90 | G90: Use the override in Verification; this sheet mirrors the active score.
A91: Pressbooks | C91: 0 | D91: Blank: zero under the agreed unavailable-data rule | F91: =Verification!E91 | G91: Use the override in Verification; this sheet mirrors the active score.
A92: Public Access Submission System | C92: 0 | D92: Blank: zero under the agreed unavailable-data rule | F92: =Verification!E92 | G92: Use the override in Verification; this sheet mirrors the active score.
A93: Public Utility Data Liberation (PUDL) | B93: RMI GridLab | C93: 50 | D93: Substantive affiliation or membership reported; level of operational support not established | F93: =Verification!E93 | G93: Use the override in Verification; this sheet mirrors the active score.
A94: PubPub | C94: 0 | D94: Blank: zero under the agreed unavailable-data rule | F94: =Verification!E94 | G94: Use the override in Verification; this sheet mirrors the active score.
A95: Pundit | B95: No affiliations | C95: 0 | D95: Explicit absence or placeholder | F95: =Verification!E95 | G95: Use the override in Verification; this sheet mirrors the active score.
A96: pyOpenSci | B96: Community Initiatives is our Fiscal sponsor | C96: 100 | D96: Explicit host or operational/financial support language | F96: =Verification!E96 | G96: Use the override in Verification; this sheet mirrors the active score.
A97: Renku | B97: The Renku platform at renkulab.io (“Renku”) is managed jointly by the Ecole Polytechnique Fédérale de Lausanne (« EPFL ») and the Eidgenössische Technische Hochschule Zürich (« ETHZ »), Rämistrasse 101, 8092 Zürich, Switzerland. | C97: 50 | D97: Substantive affiliation or membership reported; level of operational support not established | F97: =Verification!E97 | G97: Use the override in Verification; this sheet mirrors the active score.
A98: RePEc | B98: Since 2010‒10‒01, RePEc has been an independent project of the Open Library Society. | C98: 50 | D98: Substantive affiliation or membership reported; level of operational support not established | F98: =Verification!E98 | G98: Use the override in Verification; this sheet mirrors the active score.
A99: Research Organization Registry (ROR) | C99: 0 | D99: Blank: zero under the agreed unavailable-data rule | F99: =Verification!E99 | G99: Use the override in Verification; this sheet mirrors the active score.
A100: Rogue Scholar | C100: 0 | D100: Blank: zero under the agreed unavailable-data rule | F100: =Verification!E100 | G100: Use the override in Verification; this sheet mirrors the active score.
...

Sheet Calc
A1: Service | B1: M1 Technology readiness | C1: M2 Maintenance | D1: Full-time staffing subscore | E1: Volunteer staffing subscore | F1: H1 Human resources | G1: I2 Provisional affiliations | H1: I2 rationale | I1: O1 Service delivery | J1: Python-checked total | K1: Scoring flags
A2: 2i2c | B2: 100 | C2: 100 | D2: 0 | E2: 0 | F2: 0 | G2: 0 | H2: Blank: zero under the agreed unavailable-data rule | I2: 0 | J2: 40 | K2: Full-time staffing missing/unknown scored 0; Volunteer staffing missing/unknown scored 0; Service-delivery field not applicable/unknown scored 0
A3: Academic Preservation Trust (APTrust) | B3: 100 | C3: 100 | D3: 25 | E3: 0 | F3: 12.5 | G3: 50 | H3: Substantive affiliation or membership reported; level of operational support not established | I3: 100 | J3: 72.5 | K3: Volunteer staffing missing/unknown scored 0; Review affiliation coding; override available
A4: AfricArXiv | B4: 100 | C4: 100 | D4: 25 | E4: 25 | F4: 25 | G4: 100 | H4: Explicit host or operational/financial support language | I4: 0 | J4: 65 | K4: Review affiliation coding; override available; Service-delivery field not applicable/unknown scored 0
A5: Arches Heritage Data Management Platform | B5: 100 | C5: 100 | D5: 0 | E5: 0 | F5: 0 | G5: 50 | H5: Substantive affiliation or membership reported; level of operational support not established | I5: 100 | J5: 70 | K5: Full-time staffing missing/unknown scored 0; Volunteer staffing missing/unknown scored 0; Review affiliation coding; override available
A6: Archipelago Commons | B6: 100 | C6: 100 | D6: 0 | E6: 0 | F6: 0 | G6: 0 | H6: Blank: zero under the agreed unavailable-data rule | I6: 100 | J6: 60 | K6: Full-time staffing missing/unknown scored 0; Volunteer staffing missing/unknown scored 0
A7: Archival Resource Key | B7: 55.555556 | C7: 100 | D7: 0 | E7: 0 | F7: 0 | G7: 0 | H7: Blank: zero under the agreed unavailable-data rule | I7: 0 | J7: 31.111111 | K7: Full-time staffing missing/unknown scored 0; Volunteer staffing missing/unknown scored 0; Service-delivery field not applicable/unknown scored 0
A8: Archivematica | B8: 100 | C8: 100 | D8: 100 | E8: 0 | F8: 50 | G8: 0 | H8: Explicit absence or placeholder | I8: 100 | J8: 70 | K8: Volunteer staffing missing/unknown scored 0; Review affiliation coding; override available
A9: ArchivesSpace | B9: 100 | C9: 100 | D9: 50 | E9: 0 | F9: 25 | G9: 100 | H9: Explicit host or operational/financial support language | I9: 100 | J9: 85 | K9: Volunteer staffing missing/unknown scored 0; Review affiliation coding; override available
A10: ARGOS | B10: 100 | C10: 100 | D10: 0 | E10: 0 | F10: 0 | G10: 50 | H10: Substantive affiliation or membership reported; level of operational support not established | I10: 100 | J10: 70 | K10: Full-time staffing missing/unknown scored 0; Volunteer staffing missing/unknown scored 0; Review affiliation coding; override available
A11: arXiv | B11: 100 | C11: 100 | D11: 0 | E11: 0 | F11: 0 | G11: 0 | H11: Blank: zero under the agreed unavailable-data rule | I11: 0 | J11: 40 | K11: Full-time staffing missing/unknown scored 0; Volunteer staffing missing/unknown scored 0; Service-delivery field not applicable/unknown scored 0
A12: AtoM | B12: 100 | C12: 100 | D12: 100 | E12: 0 | F12: 50 | G12: 0 | H12: Explicit absence or placeholder | I12: 100 | J12: 70 | K12: Review affiliation coding; override available
A13: Avalon Media System | B13: 100 | C13: 100 | D13: 25 | E13: 0 | F13: 12.5 | G13: 50 | H13: Substantive affiliation or membership reported; level of operational support not established | I13: 0 | J13: 52.5 | K13: Volunteer staffing missing/unknown scored 0; Review affiliation coding; override available
... A36: DLCM Portal | B36: 100 | C36: 100 | D36: 25 | E36: 25 | F36: 25 | G36: 50 | H36: Substantive affiliation or membership reported; level of operational support not established | I36: 100 | J36: 75 | K36: Review affiliation coding; override available
A37: DMP Tool | B37: 100 | C37: 100 | D37: 25 | E37: 0 | F37: 12.5 | G37: 0 | H37: Blank: zero under the agreed unavailable-data rule | I37: 100 | J37: 62.5
A38: DOAJ (Directory of Open Access Journals) | B38: 100 | C38: 100 | D38: 0 | E38: 0 | F38: 0 | G38: 0 | H38: Blank: zero under the agreed unavailable-data rule | I38: 0 | J38: 40 | K38: Full-time staffing missing/unknown scored 0; Volunteer staffing missing/unknown scored 0; Service-delivery field not applicable/unknown scored 0
A39: dokieli | B39: 55.555556 | C39: 100 | D39: 0 | E39: 0 | F39: 0 | G39: 0 | H39: Blank: zero under the agreed unavailable-data rule | I39: 0 | J39: 31.111111 | K39: Full-time staffing missing/unknown scored 0; Volunteer staffing missing/unknown scored 0; Service-delivery field not applicable/unknown scored 0
A40: Dryad | B40: 100 | C40: 100 | D40: 0 | E40: 0 | F40: 0 | G40: 0 | H40: Blank: zero under the agreed unavailable-data rule | I40: 0 | J40: 40 | K40: Full-time staffing missing/unknown scored 0; Volunteer staffing missing/unknown scored 0; Service-delivery field not applicable/unknown scored 0
A41: DSpace | B41: 100 | C41: 100 | D41: 25 | E41: 0 | F41: 12.5 | G41: 0 | H41: Blank: zero under the agreed unavailable-data rule | I41: 100 | J41: 62.5
A42: DuraCloud | B42: 100 | C42: 100 | D42: 0 | E42: 0 | F42: 0 | G42: 0 | H42: Explicit absence or placeholder | I42: 100 | J42: 60 | K42: Full-time staffing missing/unknown scored 0; Volunteer staffing missing/unknown scored 0; Review affiliation coding; override available
A43: Episciences | B43: 100 | C43: 100 | D43: 25 | E43: 100 | F43: 62.5 | G43: 50 | H43: Substantive affiliation or membership reported; level of operational support not established | I43: 0 | J43: 62.5 | K43: Review affiliation coding; override available; Service-delivery field not applicable/unknown scored 0
A44: EPrints | B44: 100 | C44: 100 | D44: 0 | E44: 0 | F44: 0 | G44: 50 | H44: Substantive affiliation or membership reported; level of operational support not established | I44: 100 | J44: 70 | K44: Full-time staffing missing/unknown scored 0; Volunteer staffing missing/unknown scored 0; Review affiliation coding; override available
A45: Érudit | B45: 100 | C45: 100 | D45: 0 | E45: 0 | F45: 0 | G45: 0 | H45: Blank: zero under the agreed unavailable-data rule | I45: 0 | J45: 40 | K45: Full-time staffing missing/unknown scored 0; Volunteer staffing missing/unknown scored 0; Service-delivery field not applicable/unknown scored 0
A46: Europe PMC | B46: 100 | C46: 100 | D46: 75 | E46: 0 | F46: 37.5 | G46: 0 | H46: Blank: zero under the agreed unavailable-data rule | I46: 0 | J46: 47.5 | K46: Volunteer staffing missing/unknown scored 0; Service-delivery field not applicable/unknown scored 0
A47: FAIR Wizard | B47: 100 | C47: 100 | D47: 25 | E47: 0 | F47: 12.5 | G47: 50 | H47: Substantive affiliation or membership reported; level of operational support not established | I47: 100 | J47: 72.5 | K47: Volunteer staffing missing/unknown scored 0; Review affiliation coding; override available
A48: Fedora | B48: 100 | C48: 100 | D48: 25 | E48: 0 | F48: 12.5 | G48: 0 | H48: Blank: zero under the agreed unavailable-data rule | I48: 100 | J48: 62.5
A49: fido | B49: 100 | C49: 100 | D49: 50 | E49: 0 | F49: 25 | G49: 50 | H49: Substantive affiliation or membership reported; level of operational support not established | I49: 0 | J49: 55 | K49: Volunteer staffing missing/unknown scored 0; Review affiliation coding; override available; Service-delivery field not applicable/unknown scored 0
A50: Fulcrum | B50: 100 | C50: 100 | D50: 0 | E50: 0 | F50: 0 | G50: 0 | H50: Blank: zero under the agreed unavailable-data rule | I50: 100 | J50: 60 | K50: Full-time staffing missing/unknown scored 0; Volunteer staffing missing/unknown scored 0
A51: Galaxy | B51: 100 | C51: 100 | D51: 100 | E51: 100 | F51: 100 | G51: 50 | H51: Substantive affiliation or membership reported; level of operational support not established | I51: 100 | J51: 90 | K51: Review affiliation coding; override available
A52: GeoServer | B52: 100 | C52: 100 | D52: 0 | E52: 100 | F52: 50 | G52: 50 | H52: Substantive affiliation or membership reported; level of operational support not established | I52: 100 | J52: 80 | K52: Review affiliation coding; override available
A53: Hyku | B53: 100 | C53: 100 | D53: 25 | E53: 25 | F53: 25 | G53: 0 | H53: Blank: zero under the agreed unavailable-data rule | I53: 100 | J53: 65
A54: Hyrax | B54: 100 | C54: 100 | D54: 25 | E54: 25 | F54: 25 | G54: 0 | H54: Explicit absence or placeholder | I54: 100 | J54: 65 | K54: Review affiliation coding; override available
A55: IIIF | B55: 100 | C55: 100 | D55: 0 | E55: 0 | F55: 0 | G55: 0 | H55: Blank: zero under the agreed unavailable-data rule | I55: 0 | J55: 40 | K55: Full-time staffing missing/unknown scored 0; Volunteer staffing missing/unknown scored 0; Service-delivery field not applicable/unknown scored 0
A56: ImpactU | B56: 100 | C56: 100 | D56: 0 | E56: 0 | F56: 0 | G56: 50 | H56: Substantive affiliation or membership reported; level of operational support not established | I56: 100 | J56: 70 | K56: Full-time staffing missing/unknown scored 0; Volunteer staffing missing/unknown scored 0; Review affiliation coding; override available
A57: International Generic Sample Number (IGSN) | B57: 100 | C57: 100 | D57: 25 | E57: 75 | F57: 50 | G57: 50 | H57: Substantive affiliation or membership reported; level of operational support not established | I57: 100 | J57: 80 | K57: Review affiliation coding; override available
A58: InvenioRDM | B58: 88.888889 | C58: 100 | D58: 0 | E58: 0 | F58: 0 | G58: 0 | H58: Blank: zero under the agreed unavailable-data rule | I58: 0 | J58: 37.777778 | K58: Full-time staffing missing/unknown scored 0; Volunteer staffing missing/unknown scored 0
A59: iRODS | B59: 100 | C59: 100 | D59: 50 | E59: 0 | F59: 25 | G59: 50 | H59: Substantive affiliation or membership reported; level of operational support not established | I59: 100 | J59: 75 | K59: Review affiliation coding; override available
A60: Islandora | B60: 100 | C60: 100 | D60: 0 | E60: 0 | F60: 0 | G60: 0 | H60: Blank: zero under the agreed unavailable-data rule | I60: 100 | J60: 60 | K60: Full-time staffing missing/unknown scored 0; Volunteer staffing missing/unknown scored 0
A61: Janeway | B61: 100 | C61: 100 | D61: 0 | E61: 0 | F61: 0 | G61: 0 | H61: Blank: zero under the agreed unavailable-data rule | I61: 100 | J61: 60 | K61: Full-time staffing missing/unknown scored 0; Volunteer staffing missing/unknown scored 0
A62: JHOVE | B62: 100 | C62: 100 | D62: 25 | E62: 0 | F62: 12.5 | G62: 50 | H62: Substantive affiliation or membership reported; level of operational support not established | I62: 0 | J62: 52.5 | K62: Review affiliation coding; override available
A63: LA Referencia | B63: 100 | C63: 100 | D63: 0 | E63: 0 | F63: 0 | G63: 0 | H63: Blank: zero under the agreed unavailable-data rule | I63: 0 | J63: 40 | K63: Full-time staffing missing/unknown scored 0; Volunteer staffing missing/unknown scored 0; Service-delivery field not applicable/unknown scored 0
A64: Manifold | B64: 100 | C64: 100 | D64: 0 | E64: 0 | F64: 0 | G64: 0 | H64: Blank: zero under the agreed unavailable-data rule | I64: 100 | J64: 60 | K64: Full-time staffing missing/unknown scored 0; Volunteer staffing missing/unknown scored 0
A65: medRxiv | B65: 100 | C65: 100 | D65: 0 | E65: 0 | F65: 0 | G65: 0 | H65: Blank: zero under the agreed unavailable-data rule | I65: 100 | J65: 60 | K65: Full-time staffing missing/unknown scored 0; Volunteer staffing missing/unknown scored 0
... A113: Zotero | B113: 100 | C113: 100 | D113: 0 | E113: 0 | F113: 0 | G113: 0 | H113: Explicit absence or placeholder | I113: 100 | J113: 60 | K113: Full-time staffing missing/unknown scored 0; Volunteer staffing missing/unknown scored 0; Review affiliation coding; override available

Sheet Data
A1: 001_service_name | B1: 008_provider_name | C1: 010_website | D1: 013_location | E1: 014_solution_category | F1: 019_open_code_repository_url | G1: 017_funding_needs | H1: 051_business_form | I1: 951_business_form_other | J1: 052_nonprofit_status | K1: 053_shareholders | L1: 054_staffing_full_time | M1: 055_staffing_volunteer | N1: 056_launch_date | O1: 057_organizational_history | P1: 058_affiliations | Q1: 059_founders | R1: 061_primary_funding_source | S1: 961_primary_funding_source_other | T1: 076_saas_options | U1: 077_registered_service_providers | V1: 079_technology_readiness | W1: 080_maintenance_status | X1: 099_scoss | Y1: verification_status | Z1: verification_notes
A2: 2i2c | B2: Code for Science and Society | C2: https://2i2c.org/ | D2: US | E2: Authoring tool | F2: https://github.com/2i2c-org/infrastructure | G2: <p>2i2c aims to identify a self-sustaining cost recovery model with ongoing service fees for communities that it partners with in managing cloud infrastructure. We also pursue several other funding streams to advance our mission in open infrastructure for open science.</p> <p>Below are a few areas where we are actively seeking funding.</p> <p> <ul> <li> Cloud and service costs for one or more communities that cannot afford the full price of a monthly service. <li> Development projects to enhance open source technology that is critical for open science and education. <li> Broader community and technical support for the key open source communities in which we participate. <li> Organizational service development funding runway to explore and refine our model for sustainably serving infrastructure. </ul> </p> | H2: Fiscal sponsorship (non-profit) | K2: FALSE | N2: 2020-01-01 | O2: <p>2i2c was created by its current Steering Council, who also act as its founding partners. This group roughly came from three projects that similarly operated cloud infrastructure for interactive computing:</p> <p> <ul> <li> The Berkeley DataHub is an institution-wide JupyterHub that was led in-part by Yuvi Panda, Chris Holdgraf, Cathryn Carson, and Fernando Perez. <li> The Syzygy project (<a href="https://syzygy.ca">https://syzygy.ca</a>) is a network of JupyterHubs for Canadian universities that was led in-part by Jim Colliander. <li> The Pangeo project (<a href="https://pangeo.io">https://pangeo.io</a>) is a community platform for Big Data geoscience that is built on a JupyterHub and cloud computing, and is led in-part by Ryan Abernathey. </ul> </p> <p>Each of these projects demonstrated considerable value for the communities it served, but it was also clear that this model was unsustainable for most other communities of practice due to difficulties in hiring for cloud engineering skills.</p> <p>As a result, communities tended to use proprietary services that weren't aligned with the values many of us identified with (e.g., community-driven infrastructure, values-based organizations, non-profit structures, etc).</p> <p>We created 2i2c in order to have a mission-driven and community-focused organization that could design and manage cloud infrastructure on behalf of communities of practice, but that framed the partnership as a collaboration based around shared responsibility and transparency rather than a pure "consumer / producer relationship". We also wanted to ensure that 2i2c would commit to making upstream contributions and support as part of its key mission, in order to avoid the extractive relationship many organizations have with open source.</p> | R2: Contributions | T2: Not applicable | V2: Actual system proven in operational environment | W2: Actively Maintained | X2: FALSE
A3: Academic Preservation Trust (APTrust) | B3: Academic Preservation Trust (APTrust) | C3: https://aptrust.org | D3: US | E3: Digital preservation service | F3: https://github.com/APTrust/registry | G3: Investment in APTrust allows us to hire dedicated staff with decent jobs. It allows us to further our mission by enhancing, extending, and maintaining our services for our members. Investments allow us to implement our Associate Membership model to extend APTrust services to organizations of all sizes. | H3: Fiscal sponsorship (academic institution) | K3: FALSE | L3: 1-5 | N3: 2014-01-01 | O3: https://aptrust.org/about/background/ | P3: University of Virginia | Q3: University of Virginia, Duke University, Emory University, Johns Hopkins University, University of Maryland, University of North Carolina at Chapel Hill, and North Carolina State University, Columbia University, University of Michigan, University of Notre Dame, Stanford University, Syracuse University | R3: Program service revenue | T3: Through solution provider only | V3: Actual system proven in operational environment | W3: Actively Maintained | X3: FALSE
A4: AfricArXiv | B4: UbuntuNet Alliance | C4: https://africarxiv.org/ | D4: MW | E4: Repository service | G4: Investment can empower AfricArXiv to advance African research accessibility and visibility by enhancing its digital infrastructure, supporting multilingual resources, and strengthening global partnerships. Funding can improve user interfaces, optimize searchability, and enable translation into indigenous languages, broadening reach. Capacity-building initiatives, such as workshops, grants, and digital literacy programs, can empower researchers and democratize access to publishing. Sustainable revenue models through membership, sponsorships, and donations ensure long-term viability. Additionally, as we have shown previously, investment in peer review, community-building tools, and public outreach can boost AfricArXiv’s credibility, fostering impactful and inclusive African scholarship. | H4: Fiscal sponsorship (non-profit) | K4: FALSE | L4: 1-5 | M4: 1-5 | N4: 2018-01-01 | O4: AfricArXiv Reports, articles, presentations, and datasets that the team created for the AfricArXiv community. are available at https://africarxiv.ubuntunet.net/handle/1/1535 | P4: Access 2 Perspectives coordinates AfricArXiv’s operations. This includes managing day-to-day activities, overseeing submission processes, ensuring quality control, and facilitating the integration of AfricArXiv with other scholarly services | Q4: Dr. Johanna Havemann (concept and coordination) Justin Ahinon (technical assistance and community engagement) | R4: Contributions | T4: Not applicable | V4: Actual system proven in operational environment | W4: Actively Maintained | X4: FALSE
A5: Arches Heritage Data Management Platform | B5: Getty Conservation Institute (GCI) | C5: https://archesproject.org | D5: US | E5: Data management planning tool or service | F5: https://github.com/archesproject | H5: Non-profit organization | J5: 501(c)3 | K5: FALSE | N5: 2013-01-01 | O5: https://www.archesproject.org/archestimeline/ | P5: Getty Conservation Institute Farallon Geographics | Q5: Getty Conservation Institute World Monuments Fund | R5: Contributions | T5: Through third party vendor only | U5: https://www.archesproject.org/service-providers/ | V5: Actual system proven in operational environment | W5: Actively Maintained | X5: FALSE
A6: Archipelago Commons | B6: Metropolitan New York Library Council | C6: https://docs.archipelago.nyc/ | D6: US | E6: Digital library, collection or exhibit platform | Repository software | F6: https://github.com/esmero/ | G6: Stable funding provided via METRO and managed services. | H6: Fiscal sponsorship (non-profit) | Non-profit organization | K6: FALSE | N6: 2018-01-01 | O6: <a href="https://metro.org/about" target="_blank">https://metro.org/about</a> | R6: Other | T6: Through solution provider or third party vendor | V6: Actual system proven in operational environment | W6: Actively Maintained | X6: FALSE
A7: Archival Resource Key | B7: ARK Alliance | C7: https://arks.org/ | D7: US | E7: Standard, specification or protocol | F7: https://github.com/arks-org | H7: Volunteer community | K7: FALSE | N7: 2001-01-01 | O7: In 2018, the California Digital Library and DuraSpace announced a collaboration, initially named ARKs-in-the-Open and then the ARK Alliance, to build an international community around ARKs and their use in open scholarship. | R7: Other | T7: Not applicable | V7: Technology validated in relevant environment | W7: Actively Maintained | X7: FALSE
A8: Archivematica | B8: Artefactual | C8: https://www.archivematica.org/ | D8: CA | E8: Digital preservation system | F8: https://github.com/artefactual/archivematica | G8: Artefactual is entirely self-funded. We are here for the long term, we are not focused on profit for investors. We focus on slow and steady growth. This leads us to favour long term partnerships over transactional relationships. Revenue from our services support investment in our solution and supporting us through a subscription service to AtoM or Archivematica helps us continue to work on open source software. | H8: Commercial (for-profit) | K8: TRUE | L8: More than 20 | N8: 2009-01-01 | O8: Artefactual Systems was established as a digital preservation consulting company. In 2007, Artefactual received funding from the International Council of Archives (ICA) to develop an open-source archival descriptive software application that used ICA’s various standards and AtoM was born. In 2009, Artefactual began work on an open-source digital preservation plug-in for AtoM based on the Open Archival Information System (OAIS), which quickly became an application on its own, called Archivematica. AtoM and Archivematica are now used around the world as open-source options for people who want to provide access to and preserve cultural memory. | P8: No Affiliations | Q8: Artefactual Systems Inc. | R8: Program service revenue | T8: Through solution provider or third party vendor | U8: https://www.artefactual.com/pricing | V8: Actual system proven in operational environment | W8: Actively Maintained | X8: FALSE
A9: ArchivesSpace | B9: ArchivesSpace | C9: https://archivesspace.org/ | D9: US | E9: Archive information management system | Discovery system | F9: https://github.com/archivesspace/archivesspace | G9: accelerated feature development, improvements to the technical stack, integrations with other applications used in archives, anti-racism and inclusion improvements, expanded engagement and support offerings for the community, expansion of user community, sustainability overall | H9: Other | I9: ArchivesSpace is an independent membership-supported entity whose organizational home is at Lyrasis - this means ArchivesSpace pays Lyrasis for various services | K9: FALSE | L9: 6-10 | N9: 2013-01-01 | O9: https://archivesspace.org/about/history | P9: New York University and the University of California San Diego are the founding partners and have permanent seats on the Board; Lyrasis is the organizational home | Q9: New York University University of Illinois Urbana-Champaign University of California San Diego Andrew W. Mellon Foundation | R9: Other | S9: membership | T9: Through third party vendor only | U9: <a href="https://archivesspace.org/service-providers" target="_blank">Service provider list</a> | V9: Actual system proven in operational environment | W9: Actively Maintained | X9: FALSE
A10: ARGOS | B10: OpenAIRE | C10: https://argos.openaire.eu/ | E10: Data management planning tool or service | F10: https://github.com/OpenCDMP/OpenCDMP | H10: Non-profit organization | K10: FALSE | N10: 2018-01-01 | O10: For nearly two decades, OpenAIRE has been collaborating closely with the European Commission to advance and promote Open Science principles on a global scale. These principles are founded in the belief that the free flow of knowledge is not only essential for advancing scientific discovery, but also crucial for our societies to thrive. The popularity and adoption of Open Science has increased the availability of scientific and scholarly content. Scientific publications have traditionally been the main focus of Open Access, but datasets, protocols, methodologies, software, and workflows are becoming more openly available and accessible. Built on the OpenCDMP open-source software initiatied in collaboration with EUDAT and then refactored by CITE, ARGOS was created to support researchers in producing machine-actionable and openly available FAIR DMPs. Since its launch, ARGOS has evolved from a lightweight DMP editor into a fully integrated service within the OpenAIRE ecosystem and EOSC, offering export formats, semantic tagging, and interoperability with trusted research infrastructures like Zenodo and the OpenAIRE Research Graph. It is now widely adopted in European and national Open Science projects to support responsible research data management. | P10: Athena Research Center (ARC) Communication & Information Technologies Experts (CITE) | Q10: OpenAIRE | R10: Program service revenue | T10: Through solution provider only | V10: Actual system proven in operational environment | W10: Actively Maintained | X10: FALSE
A11: arXiv | B11: Cornell University | C11: https://arxiv.org/ | D11: US | E11: Repository service | F11: https://github.com/arXiv | G11: <p>arXiv strives to serve the global scientific community, and funding is needed to both support arXiv’s exponential growth and foster new initiatives that will ensure arXiv remains a pioneer in open science communications, making it more useful for researchers. Funding needs include increasing headcount to catch up to arXiv’s growth and manage new projects (hiring developers for tech modernization, hiring editorial staff to keep up with the increasing submission rate, hiring user support staff to field user questions and concerns in a timely manner, etc.)</p> <p>In the spirit of equitable access to research, arXiv is dedicated to making sure research is accessible for all. Funding to support arXiv’s accessibility efforts, which include transposing LaTeX to HTML format to increase readability for vision-impaired researchers, is needed to help the project progress. Other new initiatives that funding would support include arXiv’s tech modernization and migration, which will allow arXiv to sustainably grow and scale while remaining a stable platform, as well as expanding to new subject categories, creating tools to improve moderation, and increasing interoperability with new arXivLabs projects (<a href="https://info.arxiv.org/labs/" target="_blank">https://info.arxiv.org/labs/</a>).</p> | H11: Fiscal sponsorship (academic institution) | K11: FALSE | N11: 1991-01-01 | O11: History available from these sources: <li><a href="https://info.arxiv.org/new/index.html" target="_blank">https://info.arxiv.org/new/index.html</a> (1997-2020) <li><a href="https://info.arxiv.org/new/94-96.html" target="_blank">https://info.arxiv.org/new/94-96.html</a> <li><a href="https://info.arxiv.org/new/91-94.html" target="_blank">https://info.arxiv.org/new/91-94.html</a> | R11: Program service revenue | T11: Not applicable | V11: Actual system proven in operational environment | W11: Actively Maintained | X11: FALSE
A12: AtoM | B12: Artefactual | C12: https://www.accesstomemory.org/en/ | D12: CA | E12: Archive information management system | F12: https://github.com/artefactual/atom | G12: Artefactual is entirely self-funded. We are here for the long term, we are not focused on profit for investors. We focus on slow and steady growth. This leads us to favour long term partnerships over transactional relationships. Revenue from our services support investment in our solution and supporting us through a subscription service to AtoM or Archivematica helps us continue to work on open source software. | H12: Commercial (for-profit) | K12: TRUE | L12: More than 20 | M12: Unknown | N12: 2007-01-01 | O12: Artefactual Systems was established as a digital preservation consulting company. In 2007, Artefactual received funding from the International Council of Archives (ICA) to develop an open-source archival descriptive software application that used ICA’s various standards and AtoM was born. In 2009, Artefactual began work on an open-source digital preservation plug-in for AtoM based on the Open Archival Information System (OAIS), which quickly became an application on its own, called Archivematica. AtoM and Archivematica are now used around the world as open-source options for people who want to provide access to and preserve cultural memory. | P12: No affiliations | Q12: Peter Van Garderen https://vangarderen.net/ | R12: Program service revenue | T12: Through solution provider or third party vendor | U12: https://www.artefactual.com/pricing | V12: Actual system proven in operational environment | W12: Actively Maintained | X12: FALSE
A13: Avalon Media System | B13: Indiana University Libraries | C13: https://avalon.samvera.org/ | D13: US | E13: Digital library, collection or exhibit platform | Repository software | F13: https://github.com/avalonmediasystem/avalon | G13: Institutions, organizations, funders, and consortia can help advance Avalon via in-kind development of Avalon features; by becoming a Samvera Partner; through grant-funded activities; and by pledging funds or development time to contribute to Avalon development sprints. | H13: Non-profit organization | J13: 501(c)6 | K13: FALSE | L13: 1-5 | N13: 2013-01-01 | O13: Avalon Media System is an open source platform for managing and providing access to digital audio and moving image content, originally developed by Indiana University Libraries and Northwestern University Libraries, and now primarily developed and supported by Indiana University Libraries. Currently in production use by at least a dozen institutions, Avalon is a product of the Samvera open source community and both utilizes and participates in the development of shared components within the Samvera framework. Avalon development has been supported with grant funding from both the Institute of Museum and Library Services and the Mellon Foundation. | P13: Indiana University Libraries | Q13: Indiana University Libraries Northwestern University Libraries | R13: Other | S13: Institutional funding from Indiana University Libraries | T13: No services available | V13: Actual system proven in operational environment | W13: Actively Maintained | X13: FALSE
A14: Biodiversity Heritage Library | B14: BHL Consortium | C14: https://www.biodiversitylibrary.org/ | D14: US | E14: Digital library, collection or exhibit platform | Open scholarly dataset | Repository service | F14: https://github.com/gbhl/bhl-us | H14: Fiscal sponsorship (non-profit) | K14: FALSE | L14: 1-5 | N14: 2007-01-01 | O14: https://about.biodiversitylibrary.org/about/history-of-bhl/ | P14: BHL’s fiscal sponsor is the Council on Library and Information Resources (CLIR). | R14: Contributions | T14: Not applicable | V14: Actual system proven in operational environment | W14: Actively Maintained | X14: FALSE
A15: bioRxiv | B15: Cold Spring Harbor Laboratory | C15: https://www.biorxiv.org/ | D15: US | E15: Repository service | G15: The Chan Zuckerberg Initiative and Cold Spring Harbor Laboratory provide support for the operation of the servers at their current scale. Diversifying and extending this base of support will enable (1) vigorous promotion and advocacy for the use of preprints in underserved disciplines and research communities worldwide that will increase the volume of preprints; (2) integration with more journals to provide authors with more choices for manuscript transfer; (3) the development of automated tools to assist manuscript screening at scale; (4) the application of technologies that enhance the accessibility of preprints among broader audiences; (5) the adoption of new and improved technologies that enable the servers to operate more cost-effectively as they continue to grow. | H15: Fiscal sponsorship (non-profit) | K15: FALSE | N15: 2013-01-01 | O15: No change | R15: Contributions | T15: Not applicable | V15: Actual system proven in operational environment | W15: Actively Maintained | X15: FALSE
A16: BitCurator Environment | B16: BitCurator Consortium | C16: https://bitcuratorconsortium.org/ | E16: Digital preservation tool | F16: https://github.com/bitcurator/bitcurator-salt | H16: Fiscal sponsorship (non-profit) | K16: FALSE | L16: 0 | M16: 6-10 | N16: 2012-01-01 | O16: https://bitcuratorconsortium.org/about/#history | P16: BitCurator Consortium is administratively hosted by the Open Library Foundation. | Q16: School of Information and Library Science at the University of North Carolina, Chapel Hill Maryland Institute for Technology in the Humanities | R16: Program service revenue | T16: No services available | V16: Actual system proven in operational environment | W16: Actively Maintained | X16: FALSE
A17: Blacklight | B17: Blacklight | C17: https://projectblacklight.org/ | D17: US | E17: Discovery system | Integrated Library System (ILS) or Library Services Platform (LSP) | F17: https://github.com/projectblacklight | H17: Fiscal sponsorship (academic institution) | K17: FALSE | L17: 6-10 | N17: 2006-01-01 | O17: Started as an academic project at UVA, based on the work of Jerry McGann and Bethany Nowviskie's Center for Patacriticism, Blacklight became an open source generalized discovery platform with a loose governance structure. | P17: See website | R17: Contributions | T17: Through solution provider only | V17: Actual system proven in operational environment | W17: Actively Maintained | X17: FALSE
A18: BrCRIS | B18: IBICT | C18: https://brcris.ibict.br/ | D18: BR | E18: Discovery system | Research profiling system | F18: https://github.com/projetos-codic-ibict | H18: Non-profit organization | K18: FALSE | N18: 2014-01-01 | O18: <p>The origins of IBICT date back to the early 1950s, when UNESCO suggested that the Getúlio Vargas Foundation (FGV) promote the creation of a national bibliographic centre in Brazil. Unesco's action at the time was decisive for the emergence of institutions of this kind in different countries. The initial choice of FGV was due to the fact that it was carrying out important activities in the area of bibliography and documentation.</p> <p>At the time, the National Research Council (CNPq) was also being created, one of whose functions was to "maintain relations with national and foreign institutions for the exchange of technical and scientific documentation". Through a joint CNPq/FGV proposal, the Brazilian Institute of Bibliography and Documentation (IBBD) was created on 27 February 1954, by Decree of the President of the Republic No. 35,124, and became part of the CNPq's organisational structure.</p> <p>The 1970s were marked by a reorganisation of science and technology activities in the country. The National Research Council was transformed into the National Council for Scientific and Technological Development, expanding its power, transforming it into a foundation and linking it to the Planning Secretariat and the Presidency of the Republic. Like the CNPq, the IBBD underwent a transformation, including a change of name to the Brazilian Institute of Information in Science and Technology (IBICT), with the publication of CNPq Executive Resolution 20/76. IBICT was then consolidated as the body that would coordinate S&T information activities in Brazil.</p> <p>Since then, IBICT has also worked to promote the popularisation of scientific and technological information. Examples of this initiative are the "Science at Five" project, launched in 1987; a year later, the S&T Film Database; and, in 1993, the "Appropriate Technologies Programme".</p> <p>Since 1975, IBICT has been acting as the National Centre of the ISSN Network, for assigning the international standard number to serial publications. From 1980, IBICT established itself as the Brazilian ISSN Centre and became the only member in Brazil to assign the ISSN code.</p> <p>One of IBICT's first services, the National Collective Catalogue of Serial Publications (CCN), was created in 1954 by the then IBBD as a conventional card catalogue, providing information in person, by telephone or by correspondence. Since then, the service has kept pace with the evolution of technology, passing through the printed edition, microfiche and finally to its current electronic version.</p> <p>The Bibliographic Commutation Programme (Comut), established by Ministerial Order 456 of 5 August 1980, is one of IBICT's traditional products, which makes it possible to obtain copies of technical scientific documents available in the collections of the main Brazilian libraries and international information services.</p> <p>Today, IBICT is a reference in projects aimed at the movement for free access to knowledge. An example of this commitment is the Brazilian Digital Library of Theses and Dissertations (BDTD), launched in 2002, which uses the most modern open file technologies and integrates information systems for theses and dissertations from Brazilian teaching and research institutions. The BDBTD has a collection of more than 126,000 theses and dissertations from 90 educational institutions. This makes it the largest library of its kind in the world in terms of the number of records of theses and dissertations from a single country.</p> <p>Also part of IBICT's recent history is the launch of CanalCiência, a portal for the dissemination of science and the popularisation of science, in 2002, which uses audiovisual media as a resource for including young people in the Information Society. It is worth noting that CanalCiência was nominated for the World Summit on the Information Society award as the best example of electronic content and creativity in this category.</p> <p>In 2005, as well as improving its traditional services, IBICT expanded its activities to include other segments of society lacking organised information on the Web that were not yet part of its user community. To this end, it created the Social Inclusion Programme and began to use its expertise in organising, storing and disseminating information to support public policies aimed at the social field, particularly with regard to implementing direct actions in the field of information and digital learning.</p> | R18: Other | T18: Not applicable | V18: Actual system proven in operational environment | W18: Actively Maintained | X18: FALSE
A19: Browsertrix | B19: Webrecorder | C19: https://webrecorder.net/browsertrix/ | D19: US | E19: Digital library, collection or exhibit platform | Web archiving system | F19: https://github.com/webrecorder/browsertrix | H19: Commercial (for-profit) | K19: TRUE | L19: 1-5 | M19: 0 | N19: 2023-01-01 | O19: A brief timeline of Webrecorder's key accomplishments can be found on https://webrecorder.net/about/ | P19: No affiliations have direct involvement in governing or running our products except us. We are members of the International Internet Preservation Consortium (IIPC). | Q19: Ilya Kreymer | R19: Program service revenue | T19: Through solution provider or third party vendor | V19: Actual system proven in operational environment | W19: Actively Maintained | X19: FALSE
A20: CLOCKSS | B20: CLOCKSS | C20: https://clockss.org | D20: US | E20: Digital preservation service | F20: https://github.com/lockss | G20: We would like to extend our preservation services to smaller publishers around the world, and to extend our collections to include more diverse and inclusive perspectives. | H20: Non-profit organization | J20: 501(c)3 | K20: FALSE | L20: 1-5 | M20: 0 | N20: 2008-01-01 | O20: CLOCKSS was spun out from Stanford University and the LOCKSS Program as an independent 501(c)(3) in 2008. | P20: n/a | R20: Program service revenue | T20: Through solution provider or third party vendor | V20: Actual system proven in operational environment | W20: Actively Maintained | X20: FALSE
A21: COAR International Repository Directory (IRD) | B21: COAR | C21: https://ird.coar-repositories.org/ | E21: Index or directory | F21: https://github.com/antleaf/IRD | H21: Non-profit organization | K21: FALSE | L21: 1-5 | N21: 2025-01-01 | O21: A comprehensive and accurate directory of repositories has become increasingly important in the current scholarly communications landscape to support compliance with a growing number of open science policy requirements and to enable the development of value added services on top of repositories. However, the existing directories do not provide an accurate picture of the repository landscape, meaning the information is often obsolete and not maintained as the repository evolves. In July 2025, COAR will officially launched the COAR International Repository Directory (IRD). The difference between the COAR IRD and other directories is that it is community curated. Rather than relying on a centralised staff based at the directory to update records, the responsibility for curation of the IRD is distributed to responsible organisations. https://coar-repositories.org/what-we-do/coar-international-repository-directory/ | P21: Responsible Organisations: https://ird.coar-repositories.org/about?lang=en | Q21: COAR https://coar-repositories.org/ | R21: Contributions | T21: Not applicable | V21: Actual system proven in operational environment | W21: Actively Maintained | X21: FALSE
A22: COAR Notify | B22: COAR | C22: https://coar-notify.net/ | E22: Standard, specification or protocol | F22: https://github.com/coar-notify/coar-notify.net | H22: Non-profit organization | K22: FALSE | N22: 2021-01-01 | O22: COAR-Notify builds on previous work of COAR to advance the vision first outlined in the COAR Next Generation Repositories Initiative – to position repositories as the foundation for a distributed, globally networked infrastructure for scholarly communication, on top of which layers of value added services will be deployed – and further articulated in the Pubfair White Paper, which describes a distributed framework for open publishing services. In 2020, COAR published a generic technical model to enable the linking of preprints and other repository resources with external services. The technical model – which was developed based on a number of use cases provided by preprint servers, repositories, peer review services and overlay journals – applies a distributed, message-oriented approach based on W3C Linked Data Notifications (LDN). In 2021, COAR officialy launched the Notify project. https://coar-repositories.org/news-updates/coar-launches-the-notify-project/ | P22: No affiliations. | Q22: COAR https://coar-repositories.org/ Arcadia https://arcadiafund.org.uk/ | R22: Contributions | T22: Through solution provider or third party vendor | V22: Actual system proven in operational environment | W22: Actively Maintained | X22: FALSE
A23: CollectiveAccess | B23: Whirl-i-Gig | C23: https://www.collectiveaccess.org/ | D23: US | E23: Archive information management system | Digital asset management system | Digital library, collection or exhibit platform | F23: https://github.com/collectiveaccess | H23: Commercial (for-profit) | K23: FALSE | L23: 6-10 | M23: 0 | N23: 2003-01-01 | O23: Whirl-i-Gig, CollectiveAccess’s primary developer, freely distributes everything it develops under the GNU General Public License as part of CollectiveAccess, and offers consulting and development services to clients to ensure they get the most out of the software. Whirl-i-Gig works directly with end-users who require assistance in realizing their projects. | P23: No affiliations | Q23: Whirl-i-Gig | R23: Program service revenue | T23: Through solution provider or third party vendor | V23: Actual system proven in operational environment | W23: Actively Maintained | X23: FALSE
A24: CORE | B24: The Open University | C24: https://core.ac.uk/ | D24: GB | E24: Discovery system | F24: https://github.com/oacore | G24: <p>As of 2023, the annual budget of CORE is around £600k. The cost of CORE is growing due to increases in server infrastructure costs, the growth of OA content and the need to index it, the growth of CORE"s users (currently ~ 30 million per month), and increases in the cost of human resources. The cost of CORE is expected to reach about £1m per annum within the next 5 years. </p> </p>CORE, a community governed not-for-profit service, is currently supported by organisations utilising its data services and HEI Members. Membership contributions currently account for about 30% of CORE's income. </p> </p>CORE relies on the Open research community to remain sustainable. The CORE leadership, including all of our governance groups, are grateful to our members, paying users and sponsors for financial support.</p> | H24: Fiscal sponsorship (academic institution) | K24: FALSE | N24: 2010-01-01 | O24: <p>The first version of CORE was created in 2010 by Petr Knoth as part of his PhD work with the aim to make it easier to access and text mine very large amounts of research publications. The value of the aggregation was first demonstrated by developing a content recommendation system for research papers. Since its start, CORE has received financial support from a range of funders including Jisc, the European Commission and for the provision of services to both public and private organisations. </p> <p>CORE has been indexing research content from across the world; in 2017, it was calculated that it reached documents from 102 countries in 52 languages. While it has the status of the UK's national aggregator from repositories, it indexes metadata and full-text outputs from repositories and journals from across the world. </p> <p>CORE operates as a one step search tool for UK's open access research outputs, facilitating discoverability, use and reuse. The importance of the service has been widely recognised by Jisc, which suggested that CORE should preserve the required resources to sustain its operation and explore an international sustainability model.</p> <p>In 2018, CORE said it was the world's largest aggregator of open access research papers. Based on the open access fundamental principles, as they were described in the Budapest Open Access Initiative, its open access content not only must be openly available to download and read, but it must also allow its reuse, both by humans and machines. As a result, there was a need to exploit the content reuse, which could be made possible with the implementation of a technical infrastructure. The CORE project started with the goal of connecting metadata and full-text outputs offering, through content aggregation, value-added services, and by opening new opportunities in the research process.</p> <p>In September 2022, Jisc informed the Open University that they will not be able to extend their funding towards CORE beyond July 2023. This triggered a rigorous response from UK HEIs, represented in particular by the United Kingdom Council of Open Research and Repositories (UKCORR), who requested that Jisc “reconsider, and ideally reverse, its decision to suspend CORE’s funding” and stated that an event where CORE becomes financially unviable and is eventually retired “would be disastrous for the reputation of open research in the UK.” </p> <p>In response to this situation, on 1st December 2022, CORE launched a voluntary paid Membership Programme for CORE data providers, many of whom are HEIs. By the end of March 2023, 20 HEIs joined this programme including some of the most prestigious, such as the University of Oxford and University of Cambridge. The CORE membership programme has been designed with the goal of providing sufficient income to fully compensate for the loss of Jisc funds; increasing the diversity of income sources and achieving long-term sustainability of CORE.</p> | R24: Other | T24: Not applicable | V24: Actual system proven in operational environment | W24: Actively Maintained | X24: FALSE
A25: COUNTER Code of Practice | B25: COUNTER Metrics | C25: https://www.countermetrics.org/ | D25: GB | E25: Standard, specification or protocol | F25: https://cop5.countermetrics.org/en/5.1/index.html | G25: We know that implementing the Code of Practice can be challenging for smaller groups, either as report providers (publishers) or report consumers (libraries). Additional funding would enable us to develop new tools to help these groups implement the standard, as well as allowing us to provide more support through our outreach and education initiatives. | H25: Non-profit organization | K25: FALSE | N25: 2003-01-01 | O25: <p>We release updates to the Code of Practice on average every five years, though some small clarifications and backwards-compatible features may be released in the interim if the community requires it. </p> <p>Since launch, COUNTER has been led by three Project Directors: Peter Shepherd, Lorraine Estelle, and now Tasha Mellins-Cohen. We are not for profit and not for sale. There's an article in Serials, the UKSG journal, describing our foundation: <a href="https://serials.uksg.org/articles/10.1629/15161" target="_blank">https://serials.uksg.org/articles/10.1629/15161</a> The history of our Board of Directors and finances can be accessed from Companies House: <a href="https://find-and-update.company-information.service.gov.uk/company/04865179" target="_blank">https://find-and-update.company-information.service.gov.uk/company/04865179</a></p> | R25: Contributions | T25: Not applicable | V25: Actual system proven in operational environment | W25: Actively Maintained | X25: FALSE
A26: Creative Commons Licenses | B26: Creative Commons | C26: https://creativecommons.org/ | D26: US | E26: Standard, specification or protocol | F26: https://github.com/creativecommons | G26: <p>Creative Commons needs foundations, corporations, and individuals to sustain our core operations and license infrastructure. This is a critical need. The CC Licenses and our CC0 public domain tool are core infrastructure for the open web and open access. They serve a global public interest with many well-known platforms, institutions, and individuals utilizing the CC Licenses to offer and access freely available knowledge. </p> <p>Now more than ever, society needs open knowledge to have any chance at addressing the world’s most pressing challenges. We need open research and data to address the climate crisis; open images, audio, and reporting accessible to journalists confronting financial constraints and the challenges of “fake news;” freely available museum and library collections, because art and culture are often central to social change efforts; and open educational resources so K-12 schools, college students, and everyday learners can access affordable textbooks and other curriculum. Access to knowledge is key to a robust public commons and promoting an engaged citizenry; but in order to do this right, we need to have functional tools at the ready that real people can actually use.</p> <p>Creative Commons’ legal tools are core open infrastructure, yet most people are unaware that the infrastructure behind the CC Licenses has had no underlying revenue stream to sustain regular maintenance or upgrades. Over the last 20 years, we’ve built up a “technical debt,” a backlog of work our small nonprofit organization hasn’t had the capacity to address. With proper funding, Creative Commons can resolve immediate technical shortcomings while establishing an agile and streamlined maintenance routine that will allow the CC Licenses to thrive and evolve with a rapidly changing digital landscape.</p> | H26: Non-profit organization | K26: FALSE | N26: 2001-01-01 | O26: <a href="https://creativecommons.org/timeline" target="_blank">https://creativecommons.org/timeline</a> | R26: Contributions | T26: Not applicable | V26: System complete and qualified | W26: Actively Maintained | X26: FALSE
A27: Crossref Metadata Retrieval | B27: Crossref | C27: http://www.crossref.org/services/metadata-retrieval | D27: US | E27: Open scholarly dataset | F27: https://gitlab.com/crossref | G27: The Metadata Retrieval service, which includes APIs, and search and matching tools, is funded primarily by reinvesting Crossref membership and content registration revenue. It's all open data, but many organisations also subscribe to a premium service that gives them higher rate limits, monthly data dumps, and greater predictability. As Crossref is well-sustained financially, they fund several other infrastructure projects and are always open to collaborating or co-funding. | H27: Non-profit organization | K27: FALSE | N27: 2000-01-01 | O27: <a href="https://www.crossref.org/community/about/history/" target="_blank">https://www.crossref.org/community/about/history/</a> <p>Crossref was initially incorporated in January 2000 as Publishers International Linking Association, Inc. (PILA). The technical foundations were created in a prototype project by Academic Press, Wiley, and the DOI-X project. The Crossref system went live in June 2000 with several community loans, paid back the loans and reached sustainability in 2004. Over the years, Crossref has moved beyond its founding service to link references between articles, to include sevaral additional services, such as Crossmark for retractions and corrections, Similarity Check for text-based plagiarism screening, and more resource types beyond articles and references, most notably in 2018 with the introduction of the Crossref Grant System to link funders and their grants with the rest of the research ecosystem.</p> | R27: Program service revenue | T27: Not applicable | V27: Actual system proven in operational environment | W27: Actively Maintained | X27: FALSE
A28: D4Science Infrastructure | B28: National Research Council of Italy | C28: https://www.d4science.org/ | D28: IT | E28: Computing framework | Informal scholarly communications | Repository service | F28: https://code-repo.d4science.org/ | H28: Non-profit organization | K28: FALSE | L28: 6-10 | M28: More than 20 | N28: 2004-01-01 | O28: https://www.d4science.org/about-us | P28: D4Science is managed by the Italian National Research Council (CNR). Its headquarters are hosted by CNR's Institute of Information Science and Technologies "A. Faedo" (CNR-ISTI) in Pisa, Tuscany, Italy. | R28: Program service revenue | T28: Through solution provider only | V28: Actual system proven in operational environment | W28: Actively Maintained | X28: FALSE
A29: DART (Digital Archivist's Resource Tool) | B29: Academic Preservation Trust (APTrust) | C29: https://aptrust.github.io/dart-docs/ | D29: US | E29: Digital preservation tool | F29: https://github.com/aptrust/dart/ | H29: Fiscal sponsorship (academic institution) | K29: FALSE | L29: 1-5 | N29: 2018-01-01 | O29: https://aptrust.org/about/background/ | P29: University of Virginia | Q29: University of Virginia University of North Carolina Syracuse University University of Notre Dame Johns Hopkins University North Carolina State University University of Maryland Emory University | R29: Program service revenue | T29: No services available | V29: Actual system proven in operational environment | W29: Actively Maintained | X29: FALSE
A30: Database Information System | B30: University Library of Regensburg | C30: https://dbis.ur.de/?lang=en | D30: DE | E30: Discovery system | Index or directory | F30: https://github.com/ub-regensburg/dbis | H30: Fiscal sponsorship (academic institution) | K30: FALSE | N30: 2002-01-01 | O30: The DFG-funded project "Expansion, consolidation and optimization of the nationwide database information system DBIS" aimed to adapt the Database Information System (DBIS), established in 2002 at the University Library of Regensburg, to current and future needs of the scientific community. DBIS is a key research tool for scholarly databases, used by 400+ institutions. The project results include modernized, user-friendly interfaces, a frontend optimized for researchers and students, and a newly designed administration. Interfaces for data exchange with other systems were developed, enabling better integration of DBIS with national and international information infrastructures. The new version of DBIS went live in October 2024. The successful completion of the project ensures that DBIS will remain a central tool for researching scholarly databases, meeting the needs of a digitalized and globally connected academic landscape. Source: https://epub.uni-regensburg.de/76489/ | P30: DBIS is operated by the University Library of Regensburg. | R30: Other | S30: University Library of Regensburg | T30: Through solution provider or third party vendor | V30: Actual system proven in operational environment | W30: Actively Maintained | X30: FALSE
A31: Data Citation Corpus | B31: Make Data Count | C31: https://makedatacount.org/find-a-tool/#section-1 | E31: Discovery system | Open scholarly dataset | F31: https://github.com/Make-Data-Count-Community/corpus-data-file | H31: Non-profit organization | K31: FALSE | M31: 11-20 | N31: 2024-01-01 | O31: Make Data Count started in 2015 through a collaboration between the California Digital Library, the Public Library of Science, and the Data Observation Network for Earth that led to a survey into preferences for metrics of the impact of data. The results from this research informed Make Data Count's next projects on workflows to capture data citations via repositories and journals, and the standardization of data downloads and views, through partnerships with DataCite and COUNTER. Over the years, Make Data Count has has worked with repositories to develop and implement recommended practices, and with bibliometricians to better understand data-usage practices among researchers. Make Data Count has partnered with DataCite to develop and deploy infrastructure to capture, store and share data-usage measures. The Data Citation Corpus aims to substantially scale the data usage information available to the community by providing data-citation insights at an unprecedented scale. | P31: DataCite leads the development of the Data Citation Corpus as part of Make Data Count activities. | R31: Contributions | T31: Not applicable | V31: Technology validated in relevant environment | W31: Actively Maintained | X31: TRUE
A32: DataCite | B32: DataCite | C32: https://datacite.org/ | D32: DE | E32: Discovery system | Persistent identifier service | F32: https://github.com/datacite | G32: In 2023, DataCite launched the Global Access Program to enable communities worldwide to make their research outputs discoverable. DataCite is seeking additional funding to continue the Global Access Program as well as its Global Access Fund that provides funding to organizations in regions and communities currently underrepresented in the global open science infrastructure landscape. The core services are sustained through the global membership. | H32: Non-profit organization | K32: FALSE | N32: 2009-01-01 | O32: We were founded as an international membership association in December of 2009 with a charitable status registered in Hannover, Germany and have not changed our organizational structure. | R32: Contributions | T32: Not applicable | V32: Actual system proven in operational environment | W32: Actively Maintained | X32: FALSE
A33: Data Stewardship Wizard | B33: DSW Team | C33: https://ds-wizard.org/ | D33: CZ | E33: Data management planning tool or service | F33: https://github.com/ds-wizard | H33: Fiscal sponsorship (non-profit) | K33: FALSE | N33: 2018-01-01 | O33: https://ds-wizard.org/dsw-story | P33: Czech Technical University in Prague / ELIXIR-CZ Codevence Solutions | R33: Contributions | T33: Through third party vendor only | U33: https://ds-wizard.org/get-started#providers | V33: Actual system proven in operational environment | W33: Actively Maintained | X33: FALSE
A34: Dataverse | B34: Harvard University Institute for Quantitative Social Science (IQSS) | C34: https://dataverse.org/ | D34: US | E34: Repository software | F34: https://github.com/IQSS/dataverse | H34: Fiscal sponsorship (academic institution) | K34: FALSE | N34: 2007-01-01 | O34: The Dataverse Project is being developed at Harvard's Institute for Quantitative Social Science (IQSS), along with many collaborators and contributors worldwide. The Dataverse Project was built on our experience with our earlier Virtual Data Center (VDC) project, which spanned 1997-2006 as a collaboration between the Harvard-MIT Data Center (now part of IQSS) and the Harvard University Library. Precursors to the VDC date to 1987, comprising such entities as pre-web software to automatically transfer cataloging information by FTP to other sites across campus automatically at designated times, and before that to a stand-alone software guide to local data. | R34: Other | T34: Through third party vendor only | V34: Actual system proven in operational environment | W34: Actively Maintained | X34: FALSE
A35: DLCM Backend | B35: DLCM Technology | C35: https://gitlab.unige.ch/dlcm/community/dlcm-backend | D35: CH | E35: Archive information management system | Digital preservation system | F35: https://gitlab.unige.ch/dlcm/community/dlcm-backend | G35: More membership | H35: Fiscal sponsorship (academic institution) | K35: FALSE | L35: 1-5 | M35: 1-5 | N35: 2017-01-01 | O35: - 2015-2018: The first phase was the DLCM project which allows to develop the prototype of the solution - 2018-2020: The second phase with DLCM 2.0 allows to finalize the development of the solution with the backends (server part) and the user web portal (client part) - 2019: first implementation of DLCM solution at University of Geneva with Yareta service - 2021: second implementation of DLCM solution with the SaaS offer OLOS.swiss - 2024: third implementation at ULB (Université Libre de Bruxelles) | P35: University of Geneva (https://www.unige.ch/) HEG, HES-SO (https://www.hesge.ch/heg/en) UNIFR (https://www.unifr.ch/home/en/) BFH (https://www.bfh.ch/en/) OLOS (https://olos.swiss/) | Q35: HEG (https://www.hesge.ch/heg/en) UNIFR (https://www.unifr.ch/home/en/) HES-SO (https://www.hes-so.ch) | R35: Program service revenue | T35: Through third party vendor only | U35: https://olos.swiss/ | V35: Actual system proven in operational environment | W35: Actively Maintained | X35: FALSE
A36: DLCM Portal | B36: DLCM Technology | C36: https://gitlab.unige.ch/dlcm/ui/dlcm-portal | D36: CH | E36: Archive information management system | Digital preservation system | Software preservation service | F36: https://gitlab.unige.ch/dlcm/ui/dlcm-portal | G36: More membership | H36: Fiscal sponsorship (academic institution) | K36: FALSE | L36: 1-5 | M36: 1-5 | N36: 2017-01-01 | O36: - 2015-2018: The first phase was the DLCM project which allows to develop the prototype of the solution- 2018-2020: The second phase with DLCM 2.0 allows to finalize the development of the solution with the backends (server part) and the user web portal (client part)- 2019: first implementation of DLCM solution at University of Geneva with Yareta service- 2021: second implementation of DLCM solution with the SaaS offer OLOS.swiss- 2024: third implementation at ULB (Université Libre de Bruxelles) | P36: University of Geneva (https://www.unige.ch/)HEG, HES-SO (https://www.hesge.ch/heg/en)UNIFR (https://www.unifr.ch/home/en/)BFH (https://www.bfh.ch/en/)OLOS (https://olos.swiss/) | Q36: HEG (https://www.hesge.ch/heg/en)UNIFR (https://www.unifr.ch/home/en/)HES-SO (https://www.hes-so.ch) | R36: Program service revenue | T36: Through third party vendor only | U36: https://olos.swiss/ | V36: Actual system proven in operational environment | W36: Actively Maintained | X36: FALSE
A37: DMP Tool | B37: California Digital Library | C37: https://dmptool.org/ | D37: US | E37: Data management planning tool or service | F37: https://github.com/cdluc3/dmptool/wiki | H37: Fiscal sponsorship (academic institution) | K37: FALSE | L37: 1-5 | M37: 0 | N37: 2011-01-01 | O37: [Please fill in] | R37: Other | S37: Funded as a department within the University of California Office of the President We also receive some grants for new development. | T37: Through solution provider only | V37: Actual system proven in operational environment | W37: Actively Maintained | X37: FALSE
A38: DOAJ (Directory of Open Access Journals) | B38: DOAJ Foundation | C38: https://doaj.org/ | D38: DK | E38: Discovery system | Index or directory | Open scholarly dataset | F38: https://github.com/DOAJ | G38: <p>Developing enhanced support for diamond journals, including:</p> <ul> <li> preservation, <li> enhanced visibility <li> guidance and help for publishers and editors </ul> <p>Global support for journal publishers and editors through:</p> <ul> <li> an extended Ambassador program <li> the appointment of regional co-ordinators <li> new solutions for multilingual metadata and website </ul> <p>Investment in our technical infrastructure to:</p> <ul> <li> use machine learning to automate processes and enable our team to focus on high-value activities. <li> develop our capabilities to ingest articles from journals instead of relying on journal staff to send content to us. <li> strengthen DOAJ’s coverage of trusted journals significantly by supporting integrations and collaboration with global indexes, e.g. Redalyc, Scielo, Latindex, to enhance the visibility of trusted OA globally through library discovery systems and other tools. </ul> | H38: Non-profit organization | I38: Danish Foundation | K38: FALSE | N38: 2003-01-01 | O38: <p>On 12th May 2003, DOAJ was launched by Lars Bjørnshauge. It was run as a service of Lund University Libraries.</p> <p>DOAJ grew over the years and in 2013, it moved to become an independent service managed by IS4OA CIC of which Lars is a director.</p> <p>In 2022, IS4OA created a Danish branch to ease an eventual transition of DOAJ out of post-Brexit UK. </p> <p> In 2025 the administration of DOAJ moved from Infrastructure Services for Open Access (C.I.C.) to DOAJ Fonden, which is a Foundation registered in Denmark. </p> | R38: Contributions | T38: Not applicable | V38: Actual system proven in operational environment | W38: Actively Maintained | X38: TRUE
A39: dokieli | B39: dokieli | C39: https://dokie.li/ | E39: Annotations system | Authoring tool | Informal scholarly communications | F39: https://github.com/linkeddata/dokieli | G39: <li> Hiring of developers and designers to make improvements to the UX and accessibility. <li> To further education and outreach initiatives. <li> To improve the developer experience by improving the codebase and tests to grow the open source community around the project. | H39: Volunteer community | K39: FALSE | N39: 2015-01-01 | R39: Contributions | T39: Unknown | V39: Technology validated in relevant environment | W39: Actively Maintained | X39: FALSE
A40: Dryad | B40: Dryad | C40: https://datadryad.org/ | D40: US | E40: Repository service | F40: https://github.com/CDL-Dryad/dryad-app | H40: Non-profit organization | K40: FALSE | N40: 2008-01-01 | O40: https://datadryad.org/stash/about#origins | R40: Program service revenue | T40: Not applicable | V40: Actual system proven in operational environment | W40: Actively Maintained | X40: FALSE
A41: DSpace | B41: Lyrasis | C41: https://dspace.org/ | D41: US | E41: Repository software | F41: https://github.com/DSpace/DSpace | G41: DSpace software is financially supported by the community: membership dues, certified partners and service providers, and various fundraising efforts. Membership dollars and representation are critical to DSpace. More info on benefits and impact of membership is available at: <a href="https://dspace.lyrasis.org/membership/" target="_blank">https://dspace.org/membership/</a>. Launched in March 2022, the DSpace Development Fund enables contributions to help support features prioritized by DSpace Leadership. While the best way to support DSpace is still through membership, the DSpace Development Fund provides an alternative path to supporting the critical development work and sustainability of DSpace. Learn more about the development fund and what has already been accomplished through it on this <a href="https://wiki.lyrasis.org/display/DSPACE/Announcement%3A+DSpace+Development+Fund" target="_blank">wiki page</a>. | H41: Other | I41: As an Organizational Home, Lyrasis provides many resources and services to help grow, support and amplify DSpace. Partnership with Lyrasis enables DSpace to focus on program-specific needs and priorities, free from the burden of building common types of infrastructure that are necessary for long term success and sustainability. Some of these services include, but are not limited to; fiscal services, internal IT support, human resources and other critical supportive infrastructure. While Lyrasis serves as the Organizational Home to DSpace, DSpace operates independently and has its own model to support individual sustainability. Membership to DSpace is separate from membership to Lyrasis. | J41: 501(c)3 | K41: FALSE | L41: 1-5 | M41: Unknown | N41: 2002-01-01 | O41: The first public version of DSpace was released in November 2002, a joint effort between developers from MIT and HP Labs. After the first user group meeting in March 2004, a group of interested institutions formed the DSpace Federation, determining the governance of future software development by adopting the Apache Foundation's community development model and establishing the DSpace Committer Group. In July 2007 HP and MIT jointly formed the DSpace Foundation, a not-for-profit organization providing leadership and support. In May 2009 collaboration projects and growing synergies between the DSpace Foundation and the Fedora Commons organization led them to join in the not-for-profit DuraSpace to pursue their common mission. DuraSpace and Lyrasis merged in July 2019. Currently Lyrasis provides guidance to the DSpace software and user community as the Organizational Home. The Governance and the DSpace working groups lead the community work and maintenance of the software. | Q41: MIT, HP Labs | R41: Other | S41: Membership dues, certified partners and service providers. | T41: Through solution provider or third party vendor | V41: Actual system proven in operational environment | W41: Actively Maintained | X41: TRUE
A42: DuraCloud | B42: Lyrasis | C42: https://lyrasis.org/duracloud/ | D42: US | E42: Digital preservation service | Digital preservation system | Digital preservation tool | F42: https://github.com/duracloud/duracloud | H42: Fiscal sponsorship (non-profit) | K42: FALSE | N42: 2009-01-01 | O42: N/A | P42: N/A | R42: Program service revenue | T42: Through solution provider only | V42: Actual system proven in operational environment | W42: Actively Maintained | X42: FALSE
A43: Episciences | B43: Center for Direct Scientific Communication (CCSD) | C43: https://www.episciences.org/ | D43: FR | E43: Peer review system | Publishing system | Submissions system | F43: https://github.com/CCSDForge/episciences | G43: - Developing new services (IT development) - Supporting copy editing services for the journals - Supporting the users - Outreach and engagement - Finding new funding sources | H43: Fiscal sponsorship (academic institution) | K43: FALSE | L43: 1-5 | M43: More than 20 | N43: 2013-01-01 | O43: https://www.episciences.org/governance/ https://www.ccsd.cnrs.fr/en/governance/ | P43: The financing of the CCSD is jointly ensured by its supervising bodies (CNRS, Inria, INRAE) ; the French Ministry of higher education and research (MESR) Inria and Institut Fourier bring a specific support to Episciences by their contribution to the editorial support of the journals. The IT infrastructure of Episciences is shared with HAL and Sciencesconf. Long-term preservation of content published on Episciences is ensured by C.I.N.E.S. (Centre Informatique National de l’Enseignement Supérieur). | Q43: - CNRS (Research organism) - Inria (Research organism) - Institut Fourier (Research unit) - Jean-Pierre Demailly (Researcher) | R43: Contributions | T43: Not applicable | V43: Actual system proven in operational environment | W43: Actively Maintained | X43: TRUE
A44: EPrints | B44: EPrints Services | C44: https://www.eprints.org/ | D44: GB | E44: Repository software | F44: https://github.com/eprints/eprints3.4 | H44: Fiscal sponsorship (academic institution) | K44: FALSE | N44: 2000-01-01 | O44: The software is open source. Primarily maintained and organised by EPrints Services, based in the University of Southampton. Other community members contribute to either the core software or to extension components. | P44: ECS Partners Ltd | Q44: University of Southampton | R44: Program service revenue | T44: Through solution provider only | V44: Actual system proven in operational environment | W44: Actively Maintained | X44: FALSE
A45: Érudit | B45: Érudit | C45: https://www.erudit.org/ | D45: CA | E45: Discovery system | Publishing system | Repository software | F45: https://github.com/erudit/eruditorg | H45: Fiscal sponsorship (academic institution) | K45: FALSE | N45: 1998-01-01 | O45: <p>1998: The original version of the Érudit platform is launched by Presses de l’Université de Montréal (PUM)</p> <p>2000: Creation of the Groupe interuniversitaire pour l’édition numérique (GIEN) to oversee Érudit. It is comprised of the Université de Montréal’s information and communication technologies department, the provincial scientific information network, the Presses de l’Université de Montréal, the Presses de l’Université Laval, the dissemination department of the research and creation branch of the Université du Québec à Montréal and the Université Laval library. </p> <p>2004: Creation of the Érudit consortium, in the form of a general partnership, whose partners are Université de Montréal, Université Laval and Université du Québec à Montréal.</p> <p>2013: Consolidation of the Dissertations section through an agreement signed with four Canadian Universities: UQAM, UQAT, UQTR, UQAC.</p> <p>2015: The Partnership in support of open access to scholarly journals is established between 107 Canadian journals and 53 university libraries, in collaboration with the CRKN.</p> <p>2018: Launch of Coalition Publica, an initiative of Érudit and PKP to bring together Canadian scholarly journal publishers, academic libraries and researchers.</p> <p>Complete timeline: <a href="https://apropos.erudit.org/ligne-du-temps/?lang=en" target="_blank">https://apropos.erudit.org/ligne-du-temps/?lang=en</a></p> | R45: Program service revenue | T45: Not applicable | V45: Actual system proven in operational environment | W45: Actively Maintained | X45: FALSE
A46: Europe PMC | B46: EMBL European Bioinformatics Institute (EMBL-EBI) | C46: https://europepmc.org/ | D46: GB | E46: Digital preservation system | Discovery system | Repository service | F46: https://github.com/EuropePMC | G46: Europe PMC is funded by 35 funders contributing to one grant and funder contributions are based on the annual research spend by the funding organisation (<a href="https://europepmc.org/BecomeFunder" target="_blank">https://europepmc.org/BecomeFunder</a>). The next grant renewal cycle is in 2026. Europe PMC is also supported by in-kind contributions from EMBL-EBI. Funding enables the infrastructure and maintenance of service to be continued and for new features and developments to be added to the roadmap to support the mission. | H46: Other | K46: FALSE | L46: 11-20 | N46: 2007-01-01 | O46: The Europe PMC was originally launched as UKPMC in 2007 to provide a stable, permanent, and free-to-access online digital archive of the full-text, peer-reviewed research publications. UKPMC formed a part of a network of PMC International repositories with PubMed Central USA and PMC Canada. UKPMC was established by a consortium of UK biomedical research funding bodies to enable compliance with open access policies. UKPMC was developed by the University of Manchester (Mimas and the National Centre for Text Mining (NaCTeM)), the European Bioinformatics Institute (EMBl-EBI) and the British Library, in close collaboration with the NCBI. The UKPMC archive was supplemented by the CiteXplore citations database run by EMBL-EBI. In November 2012 UKPMC was rebranded as Europe PubMed Central (Europe PMC) after three European funders joined UKPMC. In 2013 CiteXplore was subsumed under Europe PubMed Central. Since April 2016 EMBL-EBI is the sole organisation responsible for developing Europe PMC. | R46: Contributions | T46: Not applicable | V46: Actual system proven in operational environment | W46: Actively Maintained | X46: FALSE
A47: FAIR Wizard | B47: Codevence Solution s.r.o. | C47: https://fair-wizard.com/ | D47: CZ | E47: Data management planning tool or service | H47: Commercial (for-profit) | K47: TRUE | L47: 1-5 | N47: 2021-01-01 | O47: Founded in 2019 in Prague, Codevence began by developing tools and platforms that support FAIR data practices and Open Science. It soon expanded into research data stewardship, contributing to open-source solutions and helping institutions strengthen their data workflows. Building on this expertise, Codevence created FAIR Wizard, an enterprise extension of the Data Stewardship Wizard that introduces automation, integrations, and analytical insight. The company also contributes to international initiatives, including the OSTrails project, which supports cross-infrastructure collaboration and FAIR-by-design research ecosystems. Today, Codevence works with organisations across Europe, Africa, the United States, and Australia, including national bodies developing coordinated DMP solutions. It continues to advance responsible research data management through adaptable, governance-ready tools that improve the quality and long-term value of research outputs. | P47: Codevence Solutions s.r.o. | R47: Program service revenue | T47: Through solution provider only | V47: Actual system proven in operational environment | W47: Actively Maintained | X47: FALSE
A48: Fedora | B48: Lyrasis | C48: https://fedorarepository.org/ | D48: US | E48: Repository software | F48: https://github.com/fcrepo/fcrepo | G48: Fedora is funded entirely by membership contributions from institutions. This funding supports program staff who work to develop, teach, engage and support all active Fedora users. Membership represents the only source of unrestricted income for program initiatives and is the only method for which the program can continue to provide essential support for staff and operations. Without membership income, the program’s sustainability would be at risk, along with the preservation of the vital content contained within the repositories of our users. | H48: Other | I48: As an Organizational Home, Lyrasis provides many resources and services to help grow, support and amplify Fedora. Partnership with Lyrasis enables Fedora to focus on program-specific needs and priorities, free from the burden of building common types of infrastructure that are necessary for long term success and sustainability. Some of these services include, but are not limited to; fiscal services, internal IT support, human resources and other critical supportive infrastructure. While Lyrasis serves as the Organizational Home to Fedora, Fedora operates independently and has its own model to support individual sustainability. Membership to Fedora is separate from membership to Lyrasis. | J48: 501(c)3 | K48: FALSE | L48: 1-5 | M48: Unknown | N48: 2001-01-01 | O48: Originally conceptualized in 1997 as a repository architecture at Cornell University, FEDORA (Flexible, Extensive, Digital Object Repository Architecture) was first implemented at the University of Virginia as a prototype digital library system. From there, interest in the architecture’s application grew and in 2007 the non-profit organization Fedora Commons was established with funds received from the Gordon and Betty Moore Foundation. In 2009, DSpace Foundation and Fedora Commons joined together in a merger under the organizational name DuraSpace. And in 2019, Lyrasis and DuraSpace merged organizations and Fedora was added to an expanded portfolio of programs under the DuraSpace Community Supported Programs Division. | R48: Other | S48: Member-supported | T48: Through third party vendor only | V48: Actual system proven in operational environment | W48: Actively Maintained | X48: FALSE
A49: fido | B49: Open Preservation Foundation | C49: https://openpreservation.org/tools/fido | D49: GB | E49: Digital preservation tool | F49: https://github.com/openpreserve/fido | H49: Non-profit organization | J49: Company limited by guarantee | K49: FALSE | L49: 6-10 | N49: 2010-01-01 | O49: The OPF was established in 2010 to sustain the outcomes of an EU-funded R&D project called Planets. The Foundation’s goal was to build on the project’s collaborative, practical approach to digital preservation. In 2014 the OPF changed its name from the Open Planets Foundation to the Open Preservation Foundation to reflect evolution and relevance within a growing field. The OPF is an independent, not-for-profit membership organisation, welcoming digital preservation practitioners from around the world to our community. Collaboration and sustainability remain at the heart of what we do, serving our members and the community by providing practical digital preservation solutions and facilitating best practices. We work to enable shared solutions for digital preservation, leading collaborative efforts to create and develop sustainable, open-source software, resources and standards. This enables organisations to evaluate and process digital content while documenting and mitigating risk. | P49: Artefactual | Q49: British Library | R49: Other | S49: Membership subscription fees | T49: Not applicable | V49: Actual system proven in operational environment | W49: Actively Maintained | X49: FALSE
A50: Fulcrum | B50: Michigan Publishing | C50: https://www.fulcrum.org/ | D50: US | E50: Publishing system | F50: https://github.com/mlibrary/heliotrope | G50: <p><b>Discoverability:</b> As steward of large collections of ebooks focused on disciplinary areas such as archaeology and performing arts, the Fulcrum team is eager to improve its full-text search capabilities - especially in ways that provide value to specific disciplines.</p> <p><b>Accessibility:</b> Accessibility is a concern for backlist collections on Fulcrum - the platform is built around EPUB3 but a lot of legacy content is in PDF form; the costs of conversion are substantial. Being a leader in accessible platforms as well as accessible content is an aspiration for Fulcrum.</p> <p><b>Durability:</b> Working with other platforms to ensure that the types of multimodal publications that are facilitated by services such as Fulcrum can be preserved in terms of their functionality as well as content is a priority, as the fragility of the digital cultural record and the mismatch between authors expectations of longevity and the reality of the stewardship promise that libraries and publishers are making is of concern.</p> | H50: Fiscal sponsorship (academic institution) | K50: FALSE | N50: 2015-01-01 | O50: Fulcrum was established in 2015 with funding from the Andrew W. Mellon Foundation. After several rounds of development funding, the platform became self-sustaining in 2021. | R50: Program service revenue | T50: Through solution provider only | V50: Actual system proven in operational environment | W50: Actively Maintained | X50: FALSE
A51: Galaxy | B51: The Galaxy community | C51: https://galaxyproject.org/ | E51: Computing framework | Discovery system | F51: https://github.com/galaxyproject/ | H51: Fiscal sponsorship (academic institution) | K51: FALSE | L51: More than 20 | M51: More than 20 | N51: 2005-01-01 | O51: Founded in 2005 Galaxy now serves 500,000 users. | P51: It's an open source project with many affiliations. | R51: Contributions | T51: Through solution provider or third party vendor | V51: Actual system proven in operational environment | W51: Actively Maintained | X51: FALSE
A52: GeoServer | B52: Open Source Geospatial Foundation | C52: https://geoserver.org | E52: Geospatial data tool or platform | F52: https://github.com/geoserver/geoserver | G52: We have ongoing funding needs to cover operational expenses, Open Geospatial Consortium "CITE" certification on the protocols implemented, and increasing expenses due to security vulnerability reporting and regulation in both Europe and the United States. We have a sponsorship program, and yearly objectives, the above list represents ongoing expenses. | H52: Non-profit organization | K52: FALSE | L52: 0 | M52: More than 20 | N52: 2001-01-01 | O52: https://docs.geoserver.org/latest/en/user/introduction/history.html | P52: https://www.osgeo.org https://www.geosolutionsgroup.com/ https://www.afrigis.co.za/ https://www.geocat.net/ https://camptocamp.com/ | Q52: The Open Planning Project (TOPP) | R52: Contributions | T52: Through third party vendor only | U52: https://geoserver.org/support/ | V52: Actual system proven in operational environment | W52: Actively Maintained | X52: FALSE
A53: Hyku | B53: Samvera | C53: https://hyku.samvera.org/ | D53: US | E53: Repository software | F53: https://github.com/samvera/hyku | G53: Institutions, organizations, funders, and consortia can help advance Hyku via in-kind development of Hyku features; by becoming a Samvera Partner; through grant-funded activities; and by pledging funds or development time to contribute Hyku community development sprints. | H53: Fiscal sponsorship (non-profit) | J53: 501(c)6 | K53: FALSE | L53: 1-5 | M53: 1-5 | N53: 2015-01-01 | O53: Hyku is a digital repository application for managing cultural heritage content, which began as the Hydra-in-a-Box project. Based on Hyrax, it offers an easy-to-install, easy-to-configure, feature-rich solution supporting next-generation web technologies. Hyku reduces barriers to effective asset management and preservation for collections and content types of many kinds, and is supported by a vibrant and ever-growing open source community. Though initially developed as an institutional repository platform, Hyku has grown significantly since it's inception in 2015. To date, Hyku has been used to support OER resources, ETDs, digital collections, research data, and conference and event materials. | R53: Contributions | T53: Through third party vendor only | U53: See service providers at https://samvera.org/the-community/service-providers | V53: Actual system proven in operational environment | W53: Actively Maintained | X53: FALSE
A54: Hyrax | B54: Samvera | C54: https://hyrax.samvera.org/ | D54: US | E54: Repository software | F54: https://github.com/samvera/hyrax | G54: Institutions, organizations, funders, and consortia can help advance Hyrax via one-time or ongoing donations; in-kind development of Hyrax features from the roadmap; by becoming a Samvera Partner and paying annual dues in support of the community; through grant-funded activities; and by pledging funds or development time to contribute to Hyrax community maintenance or feature development sprints. | H54: Fiscal sponsorship (non-profit) | K54: FALSE | L54: 1-5 | M54: 1-5 | N54: 2018-01-01 | O54: Hyrax was originally created as part of Project Hydra, now known as the Samvera Community. Hyrax was created from earlier OSS repository components including Sufia and Curation Concerns. | P54: No affiliations | Q54: Stanford University University of Hull University of Virginia | R54: Contributions | T54: Through third party vendor only | U54: https://samvera.org/the-community/service-providers | V54: Actual system proven in operational environment | W54: Actively Maintained | X54: FALSE
A55: IIIF | B55: IIIF Consortium | C55: https://iiif.io/ | D55: US | E55: Standard, specification or protocol | F55: https://github.com/IIIF | G55: <p>As the IIIF Consortium expands its operations and operations, we primarily are exploring funding opportunities around training/translation, and ttravel support for the volunteer specification editors and technical group co-chairs.</p> <p>We have a robust set of online and in-person training offerings, and we make all the <a href="https://training.iiif.io/" target="_blank">training materials</a> we use available openly so that anyone can make use of them at their own pace. We also offer a relatively low-cost paid online training option that features extensive instructor support, which has proven incredibly popular. However, we're reaching the limit of what our sole instructor can offer in a given year; likewise we're also eager to translate our existing training materials into a wide variety of languages including Spanish, Japanese, Portuguese, and French, among others, so that we can extend the reach of our open access training materials.</p> <p>We have also done important work toward addressing gender imbalances in structures like the IIIF Editorial Committee and the co-chairs of our Technical Specification Groups. With this, however, we are encountering an increasing need to financially support travel for the newer editors and co-chairs who tend to be less senior and have less financial support from their institutions to travel to Editor and TSG meetings—especially for meetings abroad. Though we have made important strides in making online meetings a primary means of IIIF business, there remains the fact that the writing of open standards and specifications is most efficiently done via focused in-person meetings. In order to foster a more diverse and sustainable Editorial Committee and set of technical group co-chairs, the IIIF Consortium is exploring funding options that would allow us to continue this important work without sacrificing the efficiency of in-person meetings to move the specifications forward.</p> | H55: Fiscal sponsorship (non-profit) | K55: FALSE | N55: 2011-01-01 | O55: <p>The Image API was proposed in late 2011 as a collaboration between The British Library, Stanford University, the Bodleian Libraries (Oxford University), the Bibliothèque nationale de France, Nasjonalbiblioteket (National Library of Norway), Los Alamos National Laboratory Research Library, and Cornell University. Version 1.0 was published in 2012. Version 1.0 of the Presentation API was published in 2013 and of the Search API in 2016. (from <a href="https://en.wikipedia.org/wiki/International_Image_Interoperability_Framework" target="_blank">https://en.wikipedia.org/wiki/International_Image_Interoperability_Framework</a>) <p>Version 3.0 of the search and presentation APIs were published in 2020.</p> <p>The IIIF Consortium was founded in 2015 to support the work of the community, and provide governance structures: <a href="https://iiif.io/community/consortium/" target="_blank"> https://iiif.io/community/consortium/</a></p> <p>Started as a Consortium with 11 members, and has grown to 65 as of this year.</p> | R55: Contributions | T55: Not applicable | U55: We don't formally vet or require particular levels of IIIF compliance, but we do feature community partners that we're aware of in a few different places. | V55: Actual system proven in operational environment | W55: Actively Maintained | X55: FALSE
A56: ImpactU | B56: Universidad de Antioquia and other Colombian universities | C56: https://impactu.colav.co/ | D56: CO | E56: Open scholarly dataset | Research profiling system | F56: https://github.com/colav/impactu | H56: Fiscal sponsorship (academic institution) | K56: FALSE | N56: 2024-01-01 | O56: Please provide a brief organizational history. | P56: ImpactU is created and coordinated by CoLaV at the Universidad de Antioquia, the Universidad del Valle, the Universidad Externado de Colombia and the Universidad Autonoma Latinoamericana. It is in the process of constituting a national consortium authorized by ASCUN which will democratize ownership between all the Colombian institutions interested in membership. | R56: Contributions | T56: Through solution provider or third party vendor | V56: Actual system proven in operational environment | W56: Actively Maintained | X56: FALSE
A57: International Generic Sample Number (IGSN) | B57: International Generic Sample Number Organization e.V. | C57: https://ev.igsn.org | D57: DE | E57: Persistent identifier service | F57: https://github.com/IGSN | H57: Non-profit organization | K57: FALSE | L57: 1-5 | M57: 11-20 | N57: 2011-01-01 | O57: The IGSN was developed as part of SESAR with the support of the National Science Foundation at the Lamont–Doherty Earth Observatory. The project was initiated and managed by the Geoinformatics for Geochemistry Program under the direction of Kerstin Lehnert to address data curation obstacles such as different samples that share the same name and samples that are renamed as they move between laboratories and thus generating analyses that are published under different aliases. As a result, metadata that ensures unique identification is often missing, and this causes irritation for future reuse of data from a sample or the sample itself. Sample databases, such as the SESAR database, are designed to address these issues. https://en.wikipedia.org/wiki/International_Generic_Sample_Number | P57: DataCite e.V. SESAR GFZ Data Services Kiel University IGSN Service Lithodat Pty Ltd Commonwealth Scientific and Industrial Research Organisation Institut Français de Recherche pour l'Exploitation de la Mer | Q57: Lamont-Doherty Earth Observatory, Columbia University of New York Helmholtz Centre Potsdam German Research Centre for Geosciences GFZ Scripps Oceanographic Institution City College New York LacCore National Lacustrine Core Facility Commonwealth Scientific and Industrial Research Organisation Oregon State University Boise State University Arizona State Geologic Survey GEOMAR Helmholtz Centre for Ocean Research Kiel European Geosciences Union | R57: Contributions | T57: Through solution provider only | U57: https://ev.igsn.org/resources/igsn-agents-and-registration | V57: Actual system proven in operational environment | W57: Actively Maintained | X57: FALSE
A58: InvenioRDM | B58: CERN | C58: https://inveniosoftware.org/products/rdm/ | E58: Repository software | F58: https://github.com/inveniosoftware | G58: InvenioRDM is currently funded by the participating institutions and through grants to the participating. Primary funding needs is related to core maintenance activities such as improving the upgrade experience and system administration documentation. | H58: Volunteer community | K58: FALSE | N58: 2018-01-01 | O58: InvenioRDM has been an open source community since the beginning. | R58: Contributions | T58: No services available | V58: System complete and qualified | W58: Actively Maintained | X58: FALSE
