Workbook

Sheet Method
A1: OISI Component 3 - Organizational Capacity: scoring workbook
A2: Source: OISI_112_Organizational_Capacity_Verification.xlsx (112 services, Infra Finder v3) + 03_Organizational_Capacity_OISI.docx (specification).
A4: HOW A SCORE IS BUILT
A5: 1. 079 technology readiness: TRL ratio (TRL5 0.56, TRL8 0.89, TRL9 1.00). 080 maintenance: Active 1, Minimal 0.5, Unknown NA.
A6: 2. 056 age: (as-of year minus launch year), capped at 15 years and divided by the cap, so age gives a small bounded credit (5%).
A7: 3. 058 affiliations: manual code (column H) - 1 named affiliation/support, 0 explicit "No affiliations", blank if not provided or uninformative. Count of affiliations is not rewarded. 099 SCOSS: TRUE 1 / FALSE 0.
A8: 4. 076 SaaS: any hosted channel 1, none 0, Not applicable / Unknown NA. 077 providers: 1 if a provider list exists; 0 if 076 lists third-party vendors but no provider list; otherwise NA. 077 sits in ONE sub-component (Operational) to meet the no-double-counting rule.
A9: 5. Sub-component = weighted mean of observed metrics, but only if >= 50% of its applicable weight is observed. Component = 100 x weighted mean of available sub-components (Maturity 50, Institutional 30, Operational 20).
A10: 6. Published only if completeness (observed / applicable weight) >= 70% and at least 2 sub-components exist. "Sub-components used" shows each repo's basis (M, I, O). RESULT: 109 of 112 repos (97%) get a score (v1 spec design: 85). Withheld: Europe PMC, OpenEdition and ROR, which lack enough observed data across sub-components. Set Parameters!B37 = 1 to publish Maturity-only scores anyway.
A12: DECISIONS YOU SHOULD CONFIRM BEFORE PUBLISHING
A13: A. 077 placement. Spec lists 077 in both Institutional Support (10%) and Operational Capacity (10%) and requires one. I kept it in Operational. Parameters!F12 switches placement (rho 0.96 if moved).
A14: E. SPEC AMENDMENT - new metric 051 institutional host (10 pts, Institutional Support). Your spec lists business form as descriptive only. I scored it because it is the most complete (106/112 usable) variable describing institutional backing: non-profit or fiscal sponsorship 1, commercial 0.5, volunteer community 0, Other NA. 058 drops from 15 to 10 pts. Set Parameters!H10 = 0 to return to the original spec; Sensitivity compares both (rho 0.81).
... A23: - verification_status / verification_notes are empty, so every value is self-reported Infra Finder data, not independently verified.

Sheet Parameters
A1: OISI Component 3 - Organizational Capacity: scoring parameters
A2: Blue = editable input. Every score on the "Scores" sheet recalculates from these cells.
A4: Category label | B4: Score (0-1) | C4: Variable / rationale | E4: Variable | F4: Sub-component | G4: Weight (pts of 100) | H4: Column in data? (1/0) | I4: Effective weight | J4: Justification
A5: Actual system proven in operational environment | B5: =9/9 -> 1 | C5: 079: TRL 9 | E5: 079_technology_readiness | F5: Maturity | G5: 20 | H5: 1 | I5: =G5*H5 -> 20 | J5: Core. 95% of repos are at the top category: near-constant (see Diagnostics).
A6: System complete and qualified | B6: =8/9 -> 0.88888889 | C6: 079: TRL 8 | E6: 080_maintenance_status | F6: Maturity | G6: 25 | H6: 1 | I6: =G6*H6 -> 25 | J6: Core. 97% Actively Maintained: near-constant. Unknown = NA.
A7: Technology validated in relevant environment | B7: =5/9 -> 0.55555556 | C7: 079: TRL 5 (ratio TRL/9 keeps the ordinal spacing) | E7: 056_launch_date | F7: Maturity | G7: 5 | H7: 1 | I7: =G7*H7 -> 5 | J7: Age normalised and capped (Settings) so old age cannot dominate. Year-only precision.
A8: Actively Maintained | B8: 1 | C8: 080 | E8: 058_affiliations | F8: Institutional | G8: 10 | H8: 1 | I8: =G8*H8 -> 10 | J8: Presence of a named affiliation (manual code, column H); number of affiliations is NOT rewarded.
A9: Minimally Maintained | B9: 0.5 | C9: 080: intermediate score (spec); value is a judgement | E9: 099_scoss | F9: Institutional | G9: 5 | H9: 1 | I9: =G9*H9 -> 5 | J9: SCOSS TRUE=1, FALSE=0. Only 7 repos TRUE.
A10: TRUE | B10: 1 | C10: 099 SCOSS participation | E10: 051_business_form | F10: Institutional | G10: 10 | H10: 1 | I10: =G10*H10 -> 10 | J10: NEW (amends spec): institutional host = non-profit / fiscal sponsorship 1, commercial 0.5, volunteer 0, Other NA. 95% coverage (106/112; Other = NA), fixes the Institutional gap left by sparse 058.
A11: FALSE | B11: 0 | C11: 099 no participation | E11: 076_saas_options | F11: Operational | G11: 10 | H11: 1 | I11: =G11*H11 -> 10 | J11: Any hosted/SaaS channel = 1; none = 0; Not applicable / Unknown = NA.
A12: No services available | B12: 0 | C12: 076 | E12: 077_registered_service_providers | F12: Operational | G12: 10 | H12: 1 | I12: =G12*H12 -> 10 | J12: Single placement (spec requires no double counting). Operational: provider ecosystem is a service-delivery feature. Change here to test Institutional.
A13: Through solution provider only | B13: 1 | C13: 076: availability scored, not provider type
A14: Through solution provider or third party vendor | B14: 1 | C14: 076 | E14: Sub-component | F14: Weight
A15: Through third party vendor only | B15: 1 | C15: 076 | E15: Maturity | F15: 0.5
A16: Unknown | B16: NA | C16: missing | E16: Institutional | F16: 0.3
A17: Not applicable | B17: NA | C17: missing / structurally not applicable | E17: Operational | F17: 0.2
A18: Non-profit organization | B18: 1 | C18: 051 institutional host: formal non-profit | E18: Check: sum | F18: =SUM(F15:F17) -> 1
A19: Fiscal sponsorship (academic institution) | B19: 1 | C19: 051: hosted by an academic institution
A20: Fiscal sponsorship (non-profit) | B20: 1 | C20: 051: hosted by a non-profit
A21: Fiscal sponsorship (non-profit) | Non-profit organization | B21: 1 | C21: 051
A22: Commercial (for-profit) | B22: 0.5 | C22: 051: organisational backing, but not public/institutional host (judgement)
A23: Volunteer community | B23: 0 | C23: 051: no legal/institutional host
A26: Third-party service categories (077 applicable when 076 is one of these)
A27: Through solution provider or third party vendor
A28: Through third party vendor only
A31: Settings
A32: As-of year for infrastructure age | B32: 2026
A33: Age cap (years): full credit at or above this age | B33: 15
A34: Blank 058_affiliations scored as (0 or NA) | B34: NA
A35: Minimum completeness to publish a score | B35: 0.7
A36: Minimum share of a sub-component's applicable weight that must be observed | B36: 0.5
A37: Minimum number of sub-components needed | B37: 2
A39: Design notes. (1) Blank 058 stays NA (not 0) because the field has an explicit absence value ("No affiliations", 10 repos): blank therefore means not provided. This differs from the Governance component, where the blank-as-absent rule was used because no explicit absence value existed. (2) A sub-component is scored only if >= 50% of its applicable weight is observed (prevents scoring a sub-component on SCOSS alone). (3) 077 is scored 1 if a provider list exists; 0 if third-party vendors are listed in 076 but no provider list is given; NA otherwise (where no third-party ecosystem is expected).

Sheet Scores
A1: Service | B1: Provider | C1: Solution category | D1: 079 Technology readiness | E1: 080 Maintenance status | F1: 056 Launch date | G1: 058 Affiliations (text) | H1: 058 manual code (1 named / 0 none / blank n.a.) | I1: 099 SCOSS | J1: 076 SaaS options | K1: 077 Registered service providers | L1: 051 Business form (institutional host, scored) | M1: 061 Primary funding (descriptive) | N1: 054 Staffing FT (descriptive) | O1: 055 Staffing volunteer (descriptive) | P1: s079 | Q1: s080 | R1: s056 | S1: s058 | T1: s099 | U1: s051 | V1: s076 | W1: s077 | X1: app076 | Y1: app077 | Z1: Maturity (0-1) | AA1: Institutional (0-1) | AB1: Operational (0-1) | AC1: Weight observed | AD1: Weight applicable | AE1: Completeness | AF1: Sub-components used | AG1: Org capacity score (0-100) | AH1: Rank
A2: 2i2c | B2: Code for Science and Society | C2: Authoring tool | D2: Actual system proven in operational environment | E2: Actively Maintained | F2: 2020-01-01 | I2: FALSE | J2: Not applicable | L2: Fiscal sponsorship (non-profit) | M2: Contributions | P2: =IFERROR(IF(ISNUMBER(INDEX(Parameters!$B$5:$B$23,MATCH(D2,Parameters!$A$5:$A$23,0))),INDEX(Parameters!$B$5:$B$23,MATCH(D2,Parameters!$A$5:$A$23,0)),""),"") -> 1 | Q2: =IFERROR(IF(ISNUMBER(INDEX(Parameters!$B$5:$B$23,MATCH(E2,Parameters!$A$5:$A$23,0))),INDEX(Parameters!$B$5:$B$23,MATCH(E2,Parameters!$A$5:$A$23,0)),""),"") -> 1 | R2: =IF(F2="","",IFERROR(MIN(Parameters!$B$33,MAX(0,Parameters!$B$32-VALUE(LEFT(F2,4))))/Parameters!$B$33,"")) -> 0.4 | S2: =IF(ISNUMBER(H2),H2,IF(G2="",IF(ISNUMBER(Parameters!$B$34),Parameters!$B$34,""),"")) | T2: =IFERROR(IF(ISNUMBER(INDEX(Parameters!$B$5:$B$23,MATCH(I2,Parameters!$A$5:$A$23,0))),INDEX(Parameters!$B$5:$B$23,MATCH(I2,Parameters!$A$5:$A$23,0)),""),"") -> 0 | U2: =IFERROR(IF(ISNUMBER(INDEX(Parameters!$B$5:$B$23,MATCH(L2,Parameters!$A$5:$A$23,0))),INDEX(Parameters!$B$5:$B$23,MATCH(L2,Parameters!$A$5:$A$23,0)),""),"") -> 1 | V2: =IFERROR(IF(ISNUMBER(INDEX(Parameters!$B$5:$B$23,MATCH(J2,Parameters!$A$5:$A$23,0))),INDEX(Parameters!$B$5:$B$23,MATCH(J2,Parameters!$A$5:$A$23,0)),""),"") | W2: =IF(K2<>"",1,IF(COUNTIF(Parameters!$A$27:$A$28,J2)>0,0,"")) | X2: =IF(J2="Not applicable",0,1) -> 0 | Y2: =IF(OR(K2<>"",COUNTIF(Parameters!$A$27:$A$28,J2)>0),1,0) -> 0 | Z2: =IF(((Parameters!$F$5=Parameters!$E$15)*Parameters!$I$5*1+(Parameters!$F$6=Parameters!$E$15)*Parameters!$I$6*1+(Parameters!$F$7=Parameters!$E$15)*Parameters!$I$7*1+(Parameters!$F$8=Parameters!$E$15)*Parameters!$I$8*1+(Parameters!$F$9=Parameters!$E$15)*Parameters!$I$9*1+(Parameters!$F$10=Parameters!$E$15)*Parameters!$I$10*1+(Parameters!$F$11=Parameters!$E$15)*Parameters!$I$11*X2+(Parameters!$F$12=Parameters!$E$15)*Parameters!$I$12*Y2)=0,"",IF(AND(((Parameters!$F$5=Parameters!$E$15)*Parameters!$I$5*ISNUMBER(P2)+(Parameters!$F$6=Parameters!$E$15)*Parameters!$I$6*ISNUMBER(Q2)+(Parameters!$F$7=Parameters!$E$15)*Parameters!$I$7*ISNUMBER(R2)+(Parameters!$F$8=Parameters!$E$15)*Parameters!$I$8*ISNUMBER(S2)+(Parameters!$F$9=Parameters!$E$15)*Parameters!$I$9*ISNUMBER(T2)+(Parameters!$F$10=Parameters!$E$15)*Parameters!$I$10*ISNUMBER(U2)+(Parameters!$F$11=Parameters!$E$15)*Parameters!$I$11*ISNUMBER(V2)+(Parameters!$F$12=Parameters!$E$15)*Parameters!$I$12*ISNUMBER(W2))>0,((Parameters!$F$5=Parameters!$E$15)*Parameters!$I$5*ISNUMBER(P2)+(Parameters!$F$6=Parameters!$E$15)*Parameters!$I$6*ISNUMBER(Q2)+(Parameters!$F$7=Parameters!$E$15)*Parameters!$I$7*ISNUMBER(R2)+(Parameters!$F$8=Parameters!$E$15)*Parameters!$I$8*ISNUMBER(S2)+(Parameters!$F$9=Parameters!$E$15)*Parameters!$I$9*ISNUMBER(T2)+(Parameters!$F$10=Parameters!$E$15)*Parameters!$I$10*ISNUMBER(U2)+(Parameters!$F$11=Parameters!$E$15)*Parameters!$I$11*ISNUMBER(V2)+(Parameters!$F$12=Parameters!$E$15)*Parameters!$I$12*ISNUMBER(W2))/((Parameters!$F$5=Parameters!$E$15)*Parameters!$I$5*1+(Parameters!$F$6=Parameters!$E$15)*Parameters!$I$6*1+(Parameters!$F$7=Parameters!$E$15)*Parameters!$I$7*1+(Parameters!$F$8=Parameters!$E$15)*Parameters!$I$8*1+(Parameters!$F$9=Parameters!$E$15)*Parameters!$I$9*1+(Parameters!$F$10=Parameters!$E$15)*Parameters!$I$10*1+(Parameters!$F$11=Parameters!$E$15)*Parameters!$I$11*X2+(Parameters!$F$12=Parameters!$E$15)*Parameters!$I$12*Y2)>=Parameters!$B$36),((Parameters!$F$5=Parameters!$E$15)*Parameters!$I$5*N(P2)+(Parameters!$F$6=Parameters!$E$15)*Parameters!$I$6*N(Q2)+(Parameters!$F$7=Parameters!$E$15)*Parameters!$I$7*N(R2)+(Parameters!$F$8=Parameters!$E$15)*Parameters!$I$8*N(S2)+(Parameters!$F$9=Parameters!$E$15)*Parameters!$I$9*N(T2)+(Parameters!$F$10=Parameters!$E$15)*Parameters!$I$10*N(U2)+(Parameters!$F$11=Parameters!$E$15)*Parameters!$I$11*N(V2)+(Parameters!$F$12=Parameters!$E$15)*Parameters!$I$12*N(W2))/((Parameters!$F$5=Parameters!$E$15)*Parameters!$I$5*ISNUMBER(P2)+(Parameters!$F$6=Parameters!$E$15)*Parameters!$I$6*ISNUMBER(Q2)+(Parameters!$F$7=Parameters!$E$15)*Parameters!$I$7*ISNUMBER(R2)+(Parameters!$F$8=Parameters!$E$15)*Parameters!$I$8*ISNUMBER(S2)+(Parameters!$F$9=Parameters!$E$15)*Parameters!$I$9*ISNUMBER(T2)+(Parameters!$F$10=Parameters!$E$15)*Parameters!$I$10*ISNUMBER(U2)+(Parameters!$F$11=Parameters!$E$15)*Parameters!$I$11*ISNUMBER(V2)+(Parameters!$F$12=Parameters!$E$15)*Parameters!$I$12*ISNUMBER(W2)),"")) -> 0.94 | AA2: =IF(((Parameters!$F$5=Parameters!$E$16)*Parameters!$I$5*1+(Parameters!$F$6=Parameters!$E$16)*Parameters!$I$6*1+(Parameters!$F$7=Parameters!$E$16)*Parameters!$I$7*1+(Parameters!$F$8=Parameters!$E$16)*Parameters!$I$8*1+(Parameters!$F$9=Parameters!$E$16)*Parameters!$I$9*1+(Parameters!$F$10=Parameters!$E$16)*Parameters!$I$10*1+(Parameters!$F$11=Parameters!$E$16)*Parameters!$I$11*X2+(Parameters!$F$12=Parameters!$E$16)*Parameters!$I$12*Y2)=0,"",IF(AND(((Parameters!$F$5=Parameters!$E$16)*Parameters!$I$5*ISNUMBER(P2)+(Parameters!$F$6=Parameters!$E$16)*Parameters!$I$6*ISNUMBER(Q2)+(Parameters!$F$7=Parameters!$E$16)*Parameters!$I$7*ISNUMBER(R2)+(Parameters!$F$8=Parameters!$E$16)*Parameters!$I$8*ISNUMBER(S2)+(Parameters!$F$9=Parameters!$E$16)*Parameters!$I$9*ISNUMBER(T2)+(Parameters!$F$10=Parameters!$E$16)*Parameters!$I$10*ISNUMBER(U2)+(Parameters!$F$11=Parameters!$E$16)*Parameters!$I$11*ISNUMBER(V2)+(Parameters!$F$12=Parameters!$E$16)*Parameters!$I$12*ISNUMBER(W2))>0,((Parameters!$F$5=Parameters!$E$16)*Parameters!$I$5*ISNUMBER(P2)+(Parameters!$F$6=Parameters!$E$16)*Parameters!$I$6*ISNUMBER(Q2)+(Parameters!$F$7=Parameters!$E$16)*Parameters!$I$7*ISNUMBER(R2)+(Parameters!$F$8=Parameters!$E$16)*Parameters!$I$8*ISNUMBER(S2)+(Parameters!$F$9=Parameters!$E$16)*Parameters!$I$9*ISNUMBER(T2)+(Parameters!$F$10=Parameters!$E$16)*Parameters!$I$10*ISNUMBER(U2)+(Parameters!$F$11=Parameters!$E$16)*Parameters!$I$11*ISNUMBER(V2)+(Parameters!$F$12=Parameters!$E$16)*Parameters!$I$12*ISNUMBER(W2))/((Parameters!$F$5=Parameters!$E$16)*Parameters!$I$5*1+(Parameters!$F$6=Parameters!$E$16)*Parameters!$I$6*1+(Parameters!$F$7=Parameters!$E$16)*Parameters!$I$7*1+(Parameters!$F$8=Parameters!$E$16)*Parameters!$I$8*1+(Parameters!$F$9=Parameters!$E$16)*Parameters!$I$9*1+(Parameters!$F$10=Parameters!$E$16)*Parameters!$I$10*1+(Parameters!$F$11=Parameters!$E$16)*Parameters!$I$11*X2+(Parameters!$F$12=Parameters!$E$16)*Parameters!$I$12*Y2)>=Parameters!$B$36),((Parameters!$F$5=Parameters!$E$16)*Parameters!$I$5*N(P2)+(Parameters!$F$6=Parameters!$E$16)*Parameters!$I$6*N(Q2)+(Parameters!$F$7=Parameters!$E$16)*Parameters!$I$7*N(R2)+(Parameters!$F$8=Parameters!$E$16)*Parameters!$I$8*N(S2)+(Parameters!$F$9=Parameters!$E$16)*Parameters!$I$9*N(T2)+(Parameters!$F$10=Parameters!$E$16)*Parameters!$I$10*N(U2)+(Parameters!$F$11=Parameters!$E$16)*Parameters!$I$11*N(V2)+(Parameters!$F$12=Parameters!$E$16)*Parameters!$I$12*N(W2))/((Parameters!$F$5=Parameters!$E$16)*Parameters!$I$5*ISNUMBER(P2)+(Parameters!$F$6=Parameters!$E$16)*Parameters!$I$6*ISNUMBER(Q2)+(Parameters!$F$7=Parameters!$E$16)*Parameters!$I$7*ISNUMBER(R2)+(Parameters!$F$8=Parameters!$E$16)*Parameters!$I$8*ISNUMBER(S2)+(Parameters!$F$9=Parameters!$E$16)*Parameters!$I$9*ISNUMBER(T2)+(Parameters!$F$10=Parameters!$E$16)*Parameters!$I$10*ISNUMBER(U2)+(Parameters!$F$11=Parameters!$E$16)*Parameters!$I$11*ISNUMBER(V2)+(Parameters!$F$12=Parameters!$E$16)*Parameters!$I$12*ISNUMBER(W2)),"")) -> 0.66666667 | AB2: =IF(((Parameters!$F$5=Parameters!$E$17)*Parameters!$I$5*1+(Parameters!$F$6=Parameters!$E$17)*Parameters!$I$6*1+(Parameters!$F$7=Parameters!$E$17)*Parameters!$I$7*1+(Parameters!$F$8=Parameters!$E$17)*Parameters!$I$8*1+(Parameters!$F$9=Parameters!$E$17)*Parameters!$I$9*1+(Parameters!$F$10=Parameters!$E$17)*Parameters!$I$10*1+(Parameters!$F$11=Parameters!$E$17)*Parameters!$I$11*X2+(Parameters!$F$12=Parameters!$E$17)*Parameters!$I$12*Y2)=0,"",IF(AND(((Parameters!$F$5=Parameters!$E$17)*Parameters!$I$5*ISNUMBER(P2)+(Parameters!$F$6=Parameters!$E$17)*Parameters!$I$6*ISNUMBER(Q2)+(Parameters!$F$7=Parameters!$E$17)*Parameters!$I$7*ISNUMBER(R2)+(Parameters!$F$8=Parameters!$E$17)*Parameters!$I$8*ISNUMBER(S2)+(Parameters!$F$9=Parameters!$E$17)*Parameters!$I$9*ISNUMBER(T2)+(Parameters!$F$10=Parameters!$E$17)*Parameters!$I$10*ISNUMBER(U2)+(Parameters!$F$11=Parameters!$E$17)*Parameters!$I$11*ISNUMBER(V2)+(Parameters!$F$12=Parameters!$E$17)*Parameters!$I$12*ISNUMBER(W2))>0,((Parameters!$F$5=Parameters!$E$17)*Parameters!$I$5*ISNUMBER(P2)+(Parameters!$F$6=Parameters!$E$17)*Parameters!$I$6*ISNUMBER(Q2)+(Parameters!$F$7=Parameters!$E$17)*Parameters!$I$7*ISNUMBER(R2)+(Parameters!$F$8=Parameters!$E$17)*Parameters!$I$8*ISNUMBER(S2)+(Parameters!$F$9=Parameters!$E$17)*Parameters!$I$9*ISNUMBER(T2)+(Parameters!$F$10=Parameters!$E$17)*Parameters!$I$10*ISNUMBER(U2)+(Parameters!$F$11=Parameters!$E$17)*Parameters!$I$11*ISNUMBER(V2)+(Parameters!$F$12=Parameters!$E$17)*Parameters!$I$12*ISNUMBER(W2))/((Parameters!$F$5=Parameters!$E$17)*Parameters!$I$5*1+(Parameters!$F$6=Parameters!$E$17)*Parameters!$I$6*1+(Parameters!$F$7=Parameters!$E$17)*Parameters!$I$7*1+(Parameters!$F$8=Parameters!$E$17)*Parameters!$I$8*1+(Parameters!$F$9=Parameters!$E$17)*Parameters!$I$9*1+(Parameters!$F$10=Parameters!$E$17)*Parameters!$I$10*1+(Parameters!$F$11=Parameters!$E$17)*Parameters!$I$11*X2+(Parameters!$F$12=Parameters!$E$17)*Parameters!$I$12*Y2)>=Parameters!$B$36),((Parameters!$F$5=Parameters!$E$17)*Parameters!$I$5*N(P2)+(Parameters!$F$6=Parameters!$E$17)*Parameters!$I$6*N(Q2)+(Parameters!$F$7=Parameters!$E$17)*Parameters!$I$7*N(R2)+(Parameters!$F$8=Parameters!$E$17)*Parameters!$I$8*N(S2)+(Parameters!$F$9=Parameters!$E$17)*Parameters!$I$9*N(T2)+(Parameters!$F$10=Parameters!$E$17)*Parameters!$I$10*N(U2)+(Parameters!$F$11=Parameters!$E$17)*Parameters!$I$11*N(V2)+(Parameters!$F$12=Parameters!$E$17)*Parameters!$I$12*N(W2))/((Parameters!$F$5=Parameters!$E$17)*Parameters!$I$5*ISNUMBER(P2)+(Parameters!$F$6=Parameters!$E$17)*Parameters!$I$6*ISNUMBER(Q2)+(Parameters!$F$7=Parameters!$E$17)*Parameters!$I$7*ISNUMBER(R2)+(Parameters!$F$8=Parameters!$E$17)*Parameters!$I$8*ISNUMBER(S2)+(Parameters!$F$9=Parameters!$E$17)*Parameters!$I$9*ISNUMBER(T2)+(Parameters!$F$10=Parameters!$E$17)*Parameters!$I$10*ISNUMBER(U2)+(Parameters!$F$11=Parameters!$E$17)*Parameters!$I$11*ISNUMBER(V2)+(Parameters!$F$12=Parameters!$E$17)*Parameters!$I$12*ISNUMBER(W2)),"")) | AC2: =Parameters!$I$5*ISNUMBER(P2)+Parameters!$I$6*ISNUMBER(Q2)+Parameters!$I$7*ISNUMBER(R2)+Parameters!$I$8*ISNUMBER(S2)+Parameters!$I$9*ISNUMBER(T2)+Parameters!$I$10*ISNUMBER(U2)+Parameters!$I$11*ISNUMBER(V2)+Parameters!$I$12*ISNUMBER(W2) -> 65 | AD2: =Parameters!$I$5*1+Parameters!$I$6*1+Parameters!$I$7*1+Parameters!$I$8*1+Parameters!$I$9*1+Parameters!$I$10*1+Parameters!$I$11*X2+Parameters!$I$12*Y2 -> 75 | AE2: =IF(AD2=0,"",AC2/AD2) -> 0.86666667 | AF2: =IF(ISNUMBER(Z2),"M","")&IF(ISNUMBER(AA2),"I","")&IF(ISNUMBER(AB2),"O","") -> MI | AG2: =IF(AND(ISNUMBER(AE2),ISNUMBER(Z2)+ISNUMBER(AA2)+ISNUMBER(AB2)>=Parameters!$B$37),IF(AE2>=Parameters!$B$35,100*(Parameters!$F$15*N(Z2)+Parameters!$F$16*N(AA2)+Parameters!$F$17*N(AB2))/(Parameters!$F$15*ISNUMBER(Z2)+Parameters!$F$16*ISNUMBER(AA2)+Parameters!$F$17*ISNUMBER(AB2)),""),"") -> 83.75 | AH2: =IF(ISNUMBER(AG2),RANK(AG2,$AG$2:$AG$113),"") -> 65
A3: Academic Preservation Trust (APTrust) | B3: Academic Preservation Trust (APTrust) | C3: Digital preservation service | D3: Actual system proven in operational environment | E3: Actively Maintained | F3: 2014-01-01 | G3: University of Virginia | H3: 1 | I3: FALSE | J3: Through solution provider only | L3: Fiscal sponsorship (academic institution) | M3: Program service revenue | N3: 1-5 | P3: =IFERROR(IF(ISNUMBER(INDEX(Parameters!$B$5:$B$23,MATCH(D3,Parameters!$A$5:$A$23,0))),INDEX(Parameters!$B$5:$B$23,MATCH(D3,Parameters!$A$5:$A$23,0)),""),"") -> 1 | Q3: =IFERROR(IF(ISNUMBER(INDEX(Parameters!$B$5:$B$23,MATCH(E3,Parameters!$A$5:$A$23,0))),INDEX(Parameters!$B$5:$B$23,MATCH(E3,Parameters!$A$5:$A$23,0)),""),"") -> 1 | R3: =IF(F3="","",IFERROR(MIN(Parameters!$B$33,MAX(0,Parameters!$B$32-VALUE(LEFT(F3,4))))/Parameters!$B$33,"")) -> 0.8 | S3: =IF(ISNUMBER(H3),H3,IF(G3="",IF(ISNUMBER(Parameters!$B$34),Parameters!$B$34,""),"")) -> 1 | T3: =IFERROR(IF(ISNUMBER(INDEX(Parameters!$B$5:$B$23,MATCH(I3,Parameters!$A$5:$A$23,0))),INDEX(Parameters!$B$5:$B$23,MATCH(I3,Parameters!$A$5:$A$23,0)),""),"") -> 0 | U3: =IFERROR(IF(ISNUMBER(INDEX(Parameters!$B$5:$B$23,MATCH(L3,Parameters!$A$5:$A$23,0))),INDEX(Parameters!$B$5:$B$23,MATCH(L3,Parameters!$A$5:$A$23,0)),""),"") -> 1 | V3: =IFERROR(IF(ISNUMBER(INDEX(Parameters!$B$5:$B$23,MATCH(J3,Parameters!$A$5:$A$23,0))),INDEX(Parameters!$B$5:$B$23,MATCH(J3,Parameters!$A$5:$A$23,0)),""),"") -> 1 | W3: =IF(K3<>"",1,IF(COUNTIF(Parameters!$A$27:$A$28,J3)>0,0,"")) | X3: =IF(J3="Not applicable",0,1) -> 1 | Y3: =IF(OR(K3<>"",COUNTIF(Parameters!$A$27:$A$28,J3)>0),1,0) -> 0 | Z3: =IF(((Parameters!$F$5=Parameters!$E$15)*Parameters!$I$5*1+(Parameters!$F$6=Parameters!$E$15)*Parameters!$I$6*1+(Parameters!$F$7=Parameters!$E$15)*Parameters!$I$7*1+(Parameters!$F$8=Parameters!$E$15)*Parameters!$I$8*1+(Parameters!$F$9=Parameters!$E$15)*Parameters!$I$9*1+(Parameters!$F$10=Parameters!$E$15)*Parameters!$I$10*1+(Parameters!$F$11=Parameters!$E$15)*Parameters!$I$11*X3+(Parameters!$F$12=Parameters!$E$15)*Parameters!$I$12*Y3)=0,"",IF(AND(((Parameters!$F$5=Parameters!$E$15)*Parameters!$I$5*ISNUMBER(P3)+(Parameters!$F$6=Parameters!$E$15)*Parameters!$I$6*ISNUMBER(Q3)+(Parameters!$F$7=Parameters!$E$15)*Parameters!$I$7*ISNUMBER(R3)+(Parameters!$F$8=Parameters!$E$15)*Parameters!$I$8*ISNUMBER(S3)+(Parameters!$F$9=Parameters!$E$15)*Parameters!$I$9*ISNUMBER(T3)+(Parameters!$F$10=Parameters!$E$15)*Parameters!$I$10*ISNUMBER(U3)+(Parameters!$F$11=Parameters!$E$15)*Parameters!$I$11*ISNUMBER(V3)+(Parameters!$F$12=Parameters!$E$15)*Parameters!$I$12*ISNUMBER(W3))>0,((Parameters!$F$5=Parameters!$E$15)*Parameters!$I$5*ISNUMBER(P3)+(Parameters!$F$6=Parameters!$E$15)*Parameters!$I$6*ISNUMBER(Q3)+(Parameters!$F$7=Parameters!$E$15)*Parameters!$I$7*ISNUMBER(R3)+(Parameters!$F$8=Parameters!$E$15)*Parameters!$I$8*ISNUMBER(S3)+(Parameters!$F$9=Parameters!$E$15)*Parameters!$I$9*ISNUMBER(T3)+(Parameters!$F$10=Parameters!$E$15)*Parameters!$I$10*ISNUMBER(U3)+(Parameters!$F$11=Parameters!$E$15)*Parameters!$I$11*ISNUMBER(V3)+(Parameters!$F$12=Parameters!$E$15)*Parameters!$I$12*ISNUMBER(W3))/((Parameters!$F$5=Parameters!$E$15)*Parameters!$I$5*1+(Parameters!$F$6=Parameters!$E$15)*Parameters!$I$6*1+(Parameters!$F$7=Parameters!$E$15)*Parameters!$I$7*1+(Parameters!$F$8=Parameters!$E$15)*Parameters!$I$8*1+(Parameters!$F$9=Parameters!$E$15)*Parameters!$I$9*1+(Parameters!$F$10=Parameters!$E$15)*Parameters!$I$10*1+(Parameters!$F$11=Parameters!$E$15)*Parameters!$I$11*X3+(Parameters!$F$12=Parameters!$E$15)*Parameters!$I$12*Y3)>=Parameters!$B$36),((Parameters!$F$5=Parameters!$E$15)*Parameters!$I$5*N(P3)+(Parameters!$F$6=Parameters!$E$15)*Parameters!$I$6*N(Q3)+(Parameters!$F$7=Parameters!$E$15)*Parameters!$I$7*N(R3)+(Parameters!$F$8=Parameters!$E$15)*Parameters!$I$8*N(S3)+(Parameters!$F$9=Parameters!$E$15)*Parameters!$I$9*N(T3)+(Parameters!$F$10=Parameters!$E$15)*Parameters!$I$10*N(U3)+(Parameters!$F$11=Parameters!$E$15)*Parameters!$I$11*N(V3)+(Parameters!$F$12=Parameters!$E$15)*Parameters!$I$12*N(W3))/((Parameters!$F$5=Parameters!$E$15)*Parameters!$I$5*ISNUMBER(P3)+(Parameters!$F$6=Parameters!$E$15)*Parameters!$I$6*ISNUMBER(Q3)+(Parameters!$F$7=Parameters!$E$15)*Parameters!$I$7*ISNUMBER(R3)+(Parameters!$F$8=Parameters!$E$15)*Parameters!$I$8*ISNUMBER(S3)+(Parameters!$F$9=Parameters!$E$15)*Parameters!$I$9*ISNUMBER(T3)+(Parameters!$F$10=Parameters!$E$15)*Parameters!$I$10*ISNUMBER(U3)+(Parameters!$F$11=Parameters!$E$15)*Parameters!$I$11*ISNUMBER(V3)+(Parameters!$F$12=Parameters!$E$15)*Parameters!$I$12*ISNUMBER(W3)),"")) -> 0.98 | AA3: =IF(((Parameters!$F$5=Parameters!$E$16)*Parameters!$I$5*1+(Parameters!$F$6=Parameters!$E$16)*Parameters!$I$6*1+(Parameters!$F$7=Parameters!$E$16)*Parameters!$I$7*1+(Parameters!$F$8=Parameters!$E$16)*Parameters!$I$8*1+(Parameters!$F$9=Parameters!$E$16)*Parameters!$I$9*1+(Parameters!$F$10=Parameters!$E$16)*Parameters!$I$10*1+(Parameters!$F$11=Parameters!$E$16)*Parameters!$I$11*X3+(Parameters!$F$12=Parameters!$E$16)*Parameters!$I$12*Y3)=0,"",IF(AND(((Parameters!$F$5=Parameters!$E$16)*Parameters!$I$5*ISNUMBER(P3)+(Parameters!$F$6=Parameters!$E$16)*Parameters!$I$6*ISNUMBER(Q3)+(Parameters!$F$7=Parameters!$E$16)*Parameters!$I$7*ISNUMBER(R3)+(Parameters!$F$8=Parameters!$E$16)*Parameters!$I$8*ISNUMBER(S3)+(Parameters!$F$9=Parameters!$E$16)*Parameters!$I$9*ISNUMBER(T3)+(Parameters!$F$10=Parameters!$E$16)*Parameters!$I$10*ISNUMBER(U3)+(Parameters!$F$11=Parameters!$E$16)*Parameters!$I$11*ISNUMBER(V3)+(Parameters!$F$12=Parameters!$E$16)*Parameters!$I$12*ISNUMBER(W3))>0,((Parameters!$F$5=Parameters!$E$16)*Parameters!$I$5*ISNUMBER(P3)+(Parameters!$F$6=Parameters!$E$16)*Parameters!$I$6*ISNUMBER(Q3)+(Parameters!$F$7=Parameters!$E$16)*Parameters!$I$7*ISNUMBER(R3)+(Parameters!$F$8=Parameters!$E$16)*Parameters!$I$8*ISNUMBER(S3)+(Parameters!$F$9=Parameters!$E$16)*Parameters!$I$9*ISNUMBER(T3)+(Parameters!$F$10=Parameters!$E$16)*Parameters!$I$10*ISNUMBER(U3)+(Parameters!$F$11=Parameters!$E$16)*Parameters!$I$11*ISNUMBER(V3)+(Parameters!$F$12=Parameters!$E$16)*Parameters!$I$12*ISNUMBER(W3))/((Parameters!$F$5=Parameters!$E$16)*Parameters!$I$5*1+(Parameters!$F$6=Parameters!$E$16)*Parameters!$I$6*1+(Parameters!$F$7=Parameters!$E$16)*Parameters!$I$7*1+(Parameters!$F$8=Parameters!$E$16)*Parameters!$I$8*1+(Parameters!$F$9=Parameters!$E$16)*Parameters!$I$9*1+(Parameters!$F$10=Parameters!$E$16)*Parameters!$I$10*1+(Parameters!$F$11=Parameters!$E$16)*Parameters!$I$11*X3+(Parameters!$F$12=Parameters!$E$16)*Parameters!$I$12*Y3)>=Parameters!$B$36),((Parameters!$F$5=Parameters!$E$16)*Parameters!$I$5*N(P3)+(Parameters!$F$6=Parameters!$E$16)*Parameters!$I$6*N(Q3)+(Parameters!$F$7=Parameters!$E$16)*Parameters!$I$7*N(R3)+(Parameters!$F$8=Parameters!$E$16)*Parameters!$I$8*N(S3)+(Parameters!$F$9=Parameters!$E$16)*Parameters!$I$9*N(T3)+(Parameters!$F$10=Parameters!$E$16)*Parameters!$I$10*N(U3)+(Parameters!$F$11=Parameters!$E$16)*Parameters!$I$11*N(V3)+(Parameters!$F$12=Parameters!$E$16)*Parameters!$I$12*N(W3))/((Parameters!$F$5=Parameters!$E$16)*Parameters!$I$5*ISNUMBER(P3)+(Parameters!$F$6=Parameters!$E$16)*Parameters!$I$6*ISNUMBER(Q3)+(Parameters!$F$7=Parameters!$E$16)*Parameters!$I$7*ISNUMBER(R3)+(Parameters!$F$8=Parameters!$E$16)*Parameters!$I$8*ISNUMBER(S3)+(Parameters!$F$9=Parameters!$E$16)*Parameters!$I$9*ISNUMBER(T3)+(Parameters!$F$10=Parameters!$E$16)*Parameters!$I$10*ISNUMBER(U3)+(Parameters!$F$11=Parameters!$E$16)*Parameters!$I$11*ISNUMBER(V3)+(Parameters!$F$12=Parameters!$E$16)*Parameters!$I$12*ISNUMBER(W3)),"")) -> 0.8 | AB3: =IF(((Parameters!$F$5=Parameters!$E$17)*Parameters!$I$5*1+(Parameters!$F$6=Parameters!$E$17)*Parameters!$I$6*1+(Parameters!$F$7=Parameters!$E$17)*Parameters!$I$7*1+(Parameters!$F$8=Parameters!$E$17)*Parameters!$I$8*1+(Parameters!$F$9=Parameters!$E$17)*Parameters!$I$9*1+(Parameters!$F$10=Parameters!$E$17)*Parameters!$I$10*1+(Parameters!$F$11=Parameters!$E$17)*Parameters!$I$11*X3+(Parameters!$F$12=Parameters!$E$17)*Parameters!$I$12*Y3)=0,"",IF(AND(((Parameters!$F$5=Parameters!$E$17)*Parameters!$I$5*ISNUMBER(P3)+(Parameters!$F$6=Parameters!$E$17)*Parameters!$I$6*ISNUMBER(Q3)+(Parameters!$F$7=Parameters!$E$17)*Parameters!$I$7*ISNUMBER(R3)+(Parameters!$F$8=Parameters!$E$17)*Parameters!$I$8*ISNUMBER(S3)+(Parameters!$F$9=Parameters!$E$17)*Parameters!$I$9*ISNUMBER(T3)+(Parameters!$F$10=Parameters!$E$17)*Parameters!$I$10*ISNUMBER(U3)+(Parameters!$F$11=Parameters!$E$17)*Parameters!$I$11*ISNUMBER(V3)+(Parameters!$F$12=Parameters!$E$17)*Parameters!$I$12*ISNUMBER(W3))>0,((Parameters!$F$5=Parameters!$E$17)*Parameters!$I$5*ISNUMBER(P3)+(Parameters!$F$6=Parameters!$E$17)*Parameters!$I$6*ISNUMBER(Q3)+(Parameters!$F$7=Parameters!$E$17)*Parameters!$I$7*ISNUMBER(R3)+(Parameters!$F$8=Parameters!$E$17)*Parameters!$I$8*ISNUMBER(S3)+(Parameters!$F$9=Parameters!$E$17)*Parameters!$I$9*ISNUMBER(T3)+(Parameters!$F$10=Parameters!$E$17)*Parameters!$I$10*ISNUMBER(U3)+(Parameters!$F$11=Parameters!$E$17)*Parameters!$I$11*ISNUMBER(V3)+(Parameters!$F$12=Parameters!$E$17)*Parameters!$I$12*ISNUMBER(W3))/((Parameters!$F$5=Parameters!$E$17)*Parameters!$I$5*1+(Parameters!$F$6=Parameters!$E$17)*Parameters!$I$6*1+(Parameters!$F$7=Parameters!$E$17)*Parameters!$I$7*1+(Parameters!$F$8=Parameters!$E$17)*Parameters!$I$8*1+(Parameters!$F$9=Parameters!$E$17)*Parameters!$I$9*1+(Parameters!$F$10=Parameters!$E$17)*Parameters!$I$10*1+(Parameters!$F$11=Parameters!$E$17)*Parameters!$I$11*X3+(Parameters!$F$12=Parameters!$E$17)*Parameters!$I$12*Y3)>=Parameters!$B$36),((Parameters!$F$5=Parameters!$E$17)*Parameters!$I$5*N(P3)+(Parameters!$F$6=Parameters!$E$17)*Parameters!$I$6*N(Q3)+(Parameters!$F$7=Parameters!$E$17)*Parameters!$I$7*N(R3)+(Parameters!$F$8=Parameters!$E$17)*Parameters!$I$8*N(S3)+(Parameters!$F$9=Parameters!$E$17)*Parameters!$I$9*N(T3)+(Parameters!$F$10=Parameters!$E$17)*Parameters!$I$10*N(U3)+(Parameters!$F$11=Parameters!$E$17)*Parameters!$I$11*N(V3)+(Parameters!$F$12=Parameters!$E$17)*Parameters!$I$12*N(W3))/((Parameters!$F$5=Parameters!$E$17)*Parameters!$I$5*ISNUMBER(P3)+(Parameters!$F$6=Parameters!$E$17)*Parameters!$I$6*ISNUMBER(Q3)+(Parameters!$F$7=Parameters!$E$17)*Parameters!$I$7*ISNUMBER(R3)+(Parameters!$F$8=Parameters!$E$17)*Parameters!$I$8*ISNUMBER(S3)+(Parameters!$F$9=Parameters!$E$17)*Parameters!$I$9*ISNUMBER(T3)+(Parameters!$F$10=Parameters!$E$17)*Parameters!$I$10*ISNUMBER(U3)+(Parameters!$F$11=Parameters!$E$17)*Parameters!$I$11*ISNUMBER(V3)+(Parameters!$F$12=Parameters!$E$17)*Parameters!$I$12*ISNUMBER(W3)),"")) -> 1 | AC3: =Parameters!$I$5*ISNUMBER(P3)+Parameters!$I$6*ISNUMBER(Q3)+Parameters!$I$7*ISNUMBER(R3)+Parameters!$I$8*ISNUMBER(S3)+Parameters!$I$9*ISNUMBER(T3)+Parameters!$I$10*ISNUMBER(U3)+Parameters!$I$11*ISNUMBER(V3)+Parameters!$I$12*ISNUMBER(W3) -> 85 | AD3: =Parameters!$I$5*1+Parameters!$I$6*1+Parameters!$I$7*1+Parameters!$I$8*1+Parameters!$I$9*1+Parameters!$I$10*1+Parameters!$I$11*X3+Parameters!$I$12*Y3 -> 85 | AE3: =IF(AD3=0,"",AC3/AD3) -> 1 | AF3: =IF(ISNUMBER(Z3),"M","")&IF(ISNUMBER(AA3),"I","")&IF(ISNUMBER(AB3),"O","") -> MIO | AG3: =IF(AND(ISNUMBER(AE3),ISNUMBER(Z3)+ISNUMBER(AA3)+ISNUMBER(AB3)>=Parameters!$B$37),IF(AE3>=Parameters!$B$35,100*(Parameters!$F$15*N(Z3)+Parameters!$F$16*N(AA3)+Parameters!$F$17*N(AB3))/(Parameters!$F$15*ISNUMBER(Z3)+Parameters!$F$16*ISNUMBER(AA3)+Parameters!$F$17*ISNUMBER(AB3)),""),"") -> 93 | AH3: =IF(ISNUMBER(AG3),RANK(AG3,$AG$2:$AG$113),"") -> 13
A4: AfricArXiv | B4: UbuntuNet Alliance | C4: Repository service | D4: Actual system proven in operational environment | E4: Actively Maintained | F4: 2018-01-01 | G4: Access 2 Perspectives coordinates AfricArXiv’s operations. This includes managing day-to-day activities, overseeing submission processes, ensuring quality control, and facilitating the integration of AfricArXiv with other scholarly services | H4: 1 | I4: FALSE | J4: Not applicable | L4: Fiscal sponsorship (non-profit) | M4: Contributions | N4: 1-5 | O4: 1-5 | P4: =IFERROR(IF(ISNUMBER(INDEX(Parameters!$B$5:$B$23,MATCH(D4,Parameters!$A$5:$A$23,0))),INDEX(Parameters!$B$5:$B$23,MATCH(D4,Parameters!$A$5:$A$23,0)),""),"") -> 1 | Q4: =IFERROR(IF(ISNUMBER(INDEX(Parameters!$B$5:$B$23,MATCH(E4,Parameters!$A$5:$A$23,0))),INDEX(Parameters!$B$5:$B$23,MATCH(E4,Parameters!$A$5:$A$23,0)),""),"") -> 1 | R4: =IF(F4="","",IFERROR(MIN(Parameters!$B$33,MAX(0,Parameters!$B$32-VALUE(LEFT(F4,4))))/Parameters!$B$33,"")) -> 0.53333333 | S4: =IF(ISNUMBER(H4),H4,IF(G4="",IF(ISNUMBER(Parameters!$B$34),Parameters!$B$34,""),"")) -> 1 | T4: =IFERROR(IF(ISNUMBER(INDEX(Parameters!$B$5:$B$23,MATCH(I4,Parameters!$A$5:$A$23,0))),INDEX(Parameters!$B$5:$B$23,MATCH(I4,Parameters!$A$5:$A$23,0)),""),"") -> 0 | U4: =IFERROR(IF(ISNUMBER(INDEX(Parameters!$B$5:$B$23,MATCH(L4,Parameters!$A$5:$A$23,0))),INDEX(Parameters!$B$5:$B$23,MATCH(L4,Parameters!$A$5:$A$23,0)),""),"") -> 1 | V4: =IFERROR(IF(ISNUMBER(INDEX(Parameters!$B$5:$B$23,MATCH(J4,Parameters!$A$5:$A$23,0))),INDEX(Parameters!$B$5:$B$23,MATCH(J4,Parameters!$A$5:$A$23,0)),""),"") | W4: =IF(K4<>"",1,IF(COUNTIF(Parameters!$A$27:$A$28,J4)>0,0,"")) | X4: =IF(J4="Not applicable",0,1) -> 0 | Y4: =IF(OR(K4<>"",COUNTIF(Parameters!$A$27:$A$28,J4)>0),1,0) -> 0 | Z4: =IF(((Parameters!$F$5=Parameters!$E$15)*Parameters!$I$5*1+(Parameters!$F$6=Parameters!$E$15)*Parameters!$I$6*1+(Parameters!$F$7=Parameters!$E$15)*Parameters!$I$7*1+(Parameters!$F$8=Parameters!$E$15)*Parameters!$I$8*1+(Parameters!$F$9=Parameters!$E$15)*Parameters!$I$9*1+(Parameters!$F$10=Parameters!$E$15)*Parameters!$I$10*1+(Parameters!$F$11=Parameters!$E$15)*Parameters!$I$11*X4+(Parameters!$F$12=Parameters!$E$15)*Parameters!$I$12*Y4)=0,"",IF(AND(((Parameters!$F$5=Parameters!$E$15)*Parameters!$I$5*ISNUMBER(P4)+(Parameters!$F$6=Parameters!$E$15)*Parameters!$I$6*ISNUMBER(Q4)+(Parameters!$F$7=Parameters!$E$15)*Parameters!$I$7*ISNUMBER(R4)+(Parameters!$F$8=Parameters!$E$15)*Parameters!$I$8*ISNUMBER(S4)+(Parameters!$F$9=Parameters!$E$15)*Parameters!$I$9*ISNUMBER(T4)+(Parameters!$F$10=Parameters!$E$15)*Parameters!$I$10*ISNUMBER(U4)+(Parameters!$F$11=Parameters!$E$15)*Parameters!$I$11*ISNUMBER(V4)+(Parameters!$F$12=Parameters!$E$15)*Parameters!$I$12*ISNUMBER(W4))>0,((Parameters!$F$5=Parameters!$E$15)*Parameters!$I$5*ISNUMBER(P4)+(Parameters!$F$6=Parameters!$E$15)*Parameters!$I$6*ISNUMBER(Q4)+(Parameters!$F$7=Parameters!$E$15)*Parameters!$I$7*ISNUMBER(R4)+(Parameters!$F$8=Parameters!$E$15)*Parameters!$I$8*ISNUMBER(S4)+(Parameters!$F$9=Parameters!$E$15)*Parameters!$I$9*ISNUMBER(T4)+(Parameters!$F$10=Parameters!$E$15)*Parameters!$I$10*ISNUMBER(U4)+(Parameters!$F$11=Parameters!$E$15)*Parameters!$I$11*ISNUMBER(V4)+(Parameters!$F$12=Parameters!$E$15)*Parameters!$I$12*ISNUMBER(W4))/((Parameters!$F$5=Parameters!$E$15)*Parameters!$I$5*1+(Parameters!$F$6=Parameters!$E$15)*Parameters!$I$6*1+(Parameters!$F$7=Parameters!$E$15)*Parameters!$I$7*1+(Parameters!$F$8=Parameters!$E$15)*Parameters!$I$8*1+(Parameters!$F$9=Parameters!$E$15)*Parameters!$I$9*1+(Parameters!$F$10=Parameters!$E$15)*Parameters!$I$10*1+(Parameters!$F$11=Parameters!$E$15)*Parameters!$I$11*X4+(Parameters!$F$12=Parameters!$E$15)*Parameters!$I$12*Y4)>=Parameters!$B$36),((Parameters!$F$5=Parameters!$E$15)*Parameters!$I$5*N(P4)+(Parameters!$F$6=Parameters!$E$15)*Parameters!$I$6*N(Q4)+(Parameters!$F$7=Parameters!$E$15)*Parameters!$I$7*N(R4)+(Parameters!$F$8=Parameters!$E$15)*Parameters!$I$8*N(S4)+(Parameters!$F$9=Parameters!$E$15)*Parameters!$I$9*N(T4)+(Parameters!$F$10=Parameters!$E$15)*Parameters!$I$10*N(U4)+(Parameters!$F$11=Parameters!$E$15)*Parameters!$I$11*N(V4)+(Parameters!$F$12=Parameters!$E$15)*Parameters!$I$12*N(W4))/((Parameters!$F$5=Parameters!$E$15)*Parameters!$I$5*ISNUMBER(P4)+(Parameters!$F$6=Parameters!$E$15)*Parameters!$I$6*ISNUMBER(Q4)+(Parameters!$F$7=Parameters!$E$15)*Parameters!$I$7*ISNUMBER(R4)+(Parameters!$F$8=Parameters!$E$15)*Parameters!$I$8*ISNUMBER(S4)+(Parameters!$F$9=Parameters!$E$15)*Parameters!$I$9*ISNUMBER(T4)+(Parameters!$F$10=Parameters!$E$15)*Parameters!$I$10*ISNUMBER(U4)+(Parameters!$F$11=Parameters!$E$15)*Parameters!$I$11*ISNUMBER(V4)+(Parameters!$F$12=Parameters!$E$15)*Parameters!$I$12*ISNUMBER(W4)),"")) -> 0.95333333 | AA4: =IF(((Parameters!$F$5=Parameters!$E$16)*Parameters!$I$5*1+(Parameters!$F$6=Parameters!$E$16)*Parameters!$I$6*1+(Parameters!$F$7=Parameters!$E$16)*Parameters!$I$7*1+(Parameters!$F$8=Parameters!$E$16)*Parameters!$I$8*1+(Parameters!$F$9=Parameters!$E$16)*Parameters!$I$9*1+(Parameters!$F$10=Parameters!$E$16)*Parameters!$I$10*1+(Parameters!$F$11=Parameters!$E$16)*Parameters!$I$11*X4+(Parameters!$F$12=Parameters!$E$16)*Parameters!$I$12*Y4)=0,"",IF(AND(((Parameters!$F$5=Parameters!$E$16)*Parameters!$I$5*ISNUMBER(P4)+(Parameters!$F$6=Parameters!$E$16)*Parameters!$I$6*ISNUMBER(Q4)+(Parameters!$F$7=Parameters!$E$16)*Parameters!$I$7*ISNUMBER(R4)+(Parameters!$F$8=Parameters!$E$16)*Parameters!$I$8*ISNUMBER(S4)+(Parameters!$F$9=Parameters!$E$16)*Parameters!$I$9*ISNUMBER(T4)+(Parameters!$F$10=Parameters!$E$16)*Parameters!$I$10*ISNUMBER(U4)+(Parameters!$F$11=Parameters!$E$16)*Parameters!$I$11*ISNUMBER(V4)+(Parameters!$F$12=Parameters!$E$16)*Parameters!$I$12*ISNUMBER(W4))>0,((Parameters!$F$5=Parameters!$E$16)*Parameters!$I$5*ISNUMBER(P4)+(Parameters!$F$6=Parameters!$E$16)*Parameters!$I$6*ISNUMBER(Q4)+(Parameters!$F$7=Parameters!$E$16)*Parameters!$I$7*ISNUMBER(R4)+(Parameters!$F$8=Parameters!$E$16)*Parameters!$I$8*ISNUMBER(S4)+(Parameters!$F$9=Parameters!$E$16)*Parameters!$I$9*ISNUMBER(T4)+(Parameters!$F$10=Parameters!$E$16)*Parameters!$I$10*ISNUMBER(U4)+(Parameters!$F$11=Parameters!$E$16)*Parameters!$I$11*ISNUMBER(V4)+(Parameters!$F$12=Parameters!$E$16)*Parameters!$I$12*ISNUMBER(W4))/((Parameters!$F$5=Parameters!$E$16)*Parameters!$I$5*1+(Parameters!$F$6=Parameters!$E$16)*Parameters!$I$6*1+(Parameters!$F$7=Parameters!$E$16)*Parameters!$I$7*1+(Parameters!$F$8=Parameters!$E$16)*Parameters!$I$8*1+(Parameters!$F$9=Parameters!$E$16)*Parameters!$I$9*1+(Parameters!$F$10=Parameters!$E$16)*Parameters!$I$10*1+(Parameters!$F$11=Parameters!$E$16)*Parameters!$I$11*X4+(Parameters!$F$12=Parameters!$E$16)*Parameters!$I$12*Y4)>=Parameters!$B$36),((Parameters!$F$5=Parameters!$E$16)*Parameters!$I$5*N(P4)+(Parameters!$F$6=Parameters!$E$16)*Parameters!$I$6*N(Q4)+(Parameters!$F$7=Parameters!$E$16)*Parameters!$I$7*N(R4)+(Parameters!$F$8=Parameters!$E$16)*Parameters!$I$8*N(S4)+(Parameters!$F$9=Parameters!$E$16)*Parameters!$I$9*N(T4)+(Parameters!$F$10=Parameters!$E$16)*Parameters!$I$10*N(U4)+(Parameters!$F$11=Parameters!$E$16)*Parameters!$I$11*N(V4)+(Parameters!$F$12=Parameters!$E$16)*Parameters!$I$12*N(W4))/((Parameters!$F$5=Parameters!$E$16)*Parameters!$I$5*ISNUMBER(P4)+(Parameters!$F$6=Parameters!$E$16)*Parameters!$I$6*ISNUMBER(Q4)+(Parameters!$F$7=Parameters!$E$16)*Parameters!$I$7*ISNUMBER(R4)+(Parameters!$F$8=Parameters!$E$16)*Parameters!$I$8*ISNUMBER(S4)+(Parameters!$F$9=Parameters!$E$16)*Parameters!$I$9*ISNUMBER(T4)+(Parameters!$F$10=Parameters!$E$16)*Parameters!$I$10*ISNUMBER(U4)+(Parameters!$F$11=Parameters!$E$16)*Parameters!$I$11*ISNUMBER(V4)+(Parameters!$F$12=Parameters!$E$16)*Parameters!$I$12*ISNUMBER(W4)),"")) -> 0.8 | AB4: =IF(((Parameters!$F$5=Parameters!$E$17)*Parameters!$I$5*1+(Parameters!$F$6=Parameters!$E$17)*Parameters!$I$6*1+(Parameters!$F$7=Parameters!$E$17)*Parameters!$I$7*1+(Parameters!$F$8=Parameters!$E$17)*Parameters!$I$8*1+(Parameters!$F$9=Parameters!$E$17)*Parameters!$I$9*1+(Parameters!$F$10=Parameters!$E$17)*Parameters!$I$10*1+(Parameters!$F$11=Parameters!$E$17)*Parameters!$I$11*X4+(Parameters!$F$12=Parameters!$E$17)*Parameters!$I$12*Y4)=0,"",IF(AND(((Parameters!$F$5=Parameters!$E$17)*Parameters!$I$5*ISNUMBER(P4)+(Parameters!$F$6=Parameters!$E$17)*Parameters!$I$6*ISNUMBER(Q4)+(Parameters!$F$7=Parameters!$E$17)*Parameters!$I$7*ISNUMBER(R4)+(Parameters!$F$8=Parameters!$E$17)*Parameters!$I$8*ISNUMBER(S4)+(Parameters!$F$9=Parameters!$E$17)*Parameters!$I$9*ISNUMBER(T4)+(Parameters!$F$10=Parameters!$E$17)*Parameters!$I$10*ISNUMBER(U4)+(Parameters!$F$11=Parameters!$E$17)*Parameters!$I$11*ISNUMBER(V4)+(Parameters!$F$12=Parameters!$E$17)*Parameters!$I$12*ISNUMBER(W4))>0,((Parameters!$F$5=Parameters!$E$17)*Parameters!$I$5*ISNUMBER(P4)+(Parameters!$F$6=Parameters!$E$17)*Parameters!$I$6*ISNUMBER(Q4)+(Parameters!$F$7=Parameters!$E$17)*Parameters!$I$7*ISNUMBER(R4)+(Parameters!$F$8=Parameters!$E$17)*Parameters!$I$8*ISNUMBER(S4)+(Parameters!$F$9=Parameters!$E$17)*Parameters!$I$9*ISNUMBER(T4)+(Parameters!$F$10=Parameters!$E$17)*Parameters!$I$10*ISNUMBER(U4)+(Parameters!$F$11=Parameters!$E$17)*Parameters!$I$11*ISNUMBER(V4)+(Parameters!$F$12=Parameters!$E$17)*Parameters!$I$12*ISNUMBER(W4))/((Parameters!$F$5=Parameters!$E$17)*Parameters!$I$5*1+(Parameters!$F$6=Parameters!$E$17)*Parameters!$I$6*1+(Parameters!$F$7=Parameters!$E$17)*Parameters!$I$7*1+(Parameters!$F$8=Parameters!$E$17)*Parameters!$I$8*1+(Parameters!$F$9=Parameters!$E$17)*Parameters!$I$9*1+(Parameters!$F$10=Parameters!$E$17)*Parameters!$I$10*1+(Parameters!$F$11=Parameters!$E$17)*Parameters!$I$11*X4+(Parameters!$F$12=Parameters!$E$17)*Parameters!$I$12*Y4)>=Parameters!$B$36),((Parameters!$F$5=Parameters!$E$17)*Parameters!$I$5*N(P4)+(Parameters!$F$6=Parameters!$E$17)*Parameters!$I$6*N(Q4)+(Parameters!$F$7=Parameters!$E$17)*Parameters!$I$7*N(R4)+(Parameters!$F$8=Parameters!$E$17)*Parameters!$I$8*N(S4)+(Parameters!$F$9=Parameters!$E$17)*Parameters!$I$9*N(T4)+(Parameters!$F$10=Parameters!$E$17)*Parameters!$I$10*N(U4)+(Parameters!$F$11=Parameters!$E$17)*Parameters!$I$11*N(V4)+(Parameters!$F$12=Parameters!$E$17)*Parameters!$I$12*N(W4))/((Parameters!$F$5=Parameters!$E$17)*Parameters!$I$5*ISNUMBER(P4)+(Parameters!$F$6=Parameters!$E$17)*Parameters!$I$6*ISNUMBER(Q4)+(Parameters!$F$7=Parameters!$E$17)*Parameters!$I$7*ISNUMBER(R4)+(Parameters!$F$8=Parameters!$E$17)*Parameters!$I$8*ISNUMBER(S4)+(Parameters!$F$9=Parameters!$E$17)*Parameters!$I$9*ISNUMBER(T4)+(Parameters!$F$10=Parameters!$E$17)*Parameters!$I$10*ISNUMBER(U4)+(Parameters!$F$11=Parameters!$E$17)*Parameters!$I$11*ISNUMBER(V4)+(Parameters!$F$12=Parameters!$E$17)*Parameters!$I$12*ISNUMBER(W4)),"")) | AC4: =Parameters!$I$5*ISNUMBER(P4)+Parameters!$I$6*ISNUMBER(Q4)+Parameters!$I$7*ISNUMBER(R4)+Parameters!$I$8*ISNUMBER(S4)+Parameters!$I$9*ISNUMBER(T4)+Parameters!$I$10*ISNUMBER(U4)+Parameters!$I$11*ISNUMBER(V4)+Parameters!$I$12*ISNUMBER(W4) -> 75 | AD4: =Parameters!$I$5*1+Parameters!$I$6*1+Parameters!$I$7*1+Parameters!$I$8*1+Parameters!$I$9*1+Parameters!$I$10*1+Parameters!$I$11*X4+Parameters!$I$12*Y4 -> 75 | AE4: =IF(AD4=0,"",AC4/AD4) -> 1 | AF4: =IF(ISNUMBER(Z4),"M","")&IF(ISNUMBER(AA4),"I","")&IF(ISNUMBER(AB4),"O","") -> MI | AG4: =IF(AND(ISNUMBER(AE4),ISNUMBER(Z4)+ISNUMBER(AA4)+ISNUMBER(AB4)>=Parameters!$B$37),IF(AE4>=Parameters!$B$35,100*(Parameters!$F$15*N(Z4)+Parameters!$F$16*N(AA4)+Parameters!$F$17*N(AB4))/(Parameters!$F$15*ISNUMBER(Z4)+Parameters!$F$16*ISNUMBER(AA4)+Parameters!$F$17*ISNUMBER(AB4)),""),"") -> 89.583333 | AH4: =IF(ISNUMBER(AG4),RANK(AG4,$AG$2:$AG$113),"") -> 31
A5: Arches Heritage Data Management Platform | B5: Getty Conservation Institute (GCI) | C5: Data management planning tool or service | D5: Actual system proven in operational environment | E5: Actively Maintained | F5: 2013-01-01 | G5: Getty Conservation Institute Farallon Geographics | H5: 1 | I5: FALSE | J5: Through third party vendor only | K5: https://www.archesproject.org/service-providers/ | L5: Non-profit organization | M5: Contributions | P5: =IFERROR(IF(ISNUMBER(INDEX(Parameters!$B$5:$B$23,MATCH(D5,Parameters!$A$5:$A$23,0))),INDEX(Parameters!$B$5:$B$23,MATCH(D5,Parameters!$A$5:$A$23,0)),""),"") -> 1 | Q5: =IFERROR(IF(ISNUMBER(INDEX(Parameters!$B$5:$B$23,MATCH(E5,Parameters!$A$5:$A$23,0))),INDEX(Parameters!$B$5:$B$23,MATCH(E5,Parameters!$A$5:$A$23,0)),""),"") -> 1 | R5: =IF(F5="","",IFERROR(MIN(Parameters!$B$33,MAX(0,Parameters!$B$32-VALUE(LEFT(F5,4))))/Parameters!$B$33,"")) -> 0.86666667 | S5: =IF(ISNUMBER(H5),H5,IF(G5="",IF(ISNUMBER(Parameters!$B$34),Parameters!$B$34,""),"")) -> 1 | T5: =IFERROR(IF(ISNUMBER(INDEX(Parameters!$B$5:$B$23,MATCH(I5,Parameters!$A$5:$A$23,0))),INDEX(Parameters!$B$5:$B$23,MATCH(I5,Parameters!$A$5:$A$23,0)),""),"") -> 0 | U5: =IFERROR(IF(ISNUMBER(INDEX(Parameters!$B$5:$B$23,MATCH(L5,Parameters!$A$5:$A$23,0))),INDEX(Parameters!$B$5:$B$23,MATCH(L5,Parameters!$A$5:$A$23,0)),""),"") -> 1 | V5: =IFERROR(IF(ISNUMBER(INDEX(Parameters!$B$5:$B$23,MATCH(J5,Parameters!$A$5:$A$23,0))),INDEX(Parameters!$B$5:$B$23,MATCH(J5,Parameters!$A$5:$A$23,0)),""),"") -> 1 | W5: =IF(K5<>"",1,IF(COUNTIF(Parameters!$A$27:$A$28,J5)>0,0,"")) -> 1 | X5: =IF(J5="Not applicable",0,1) -> 1 | Y5: =IF(OR(K5<>"",COUNTIF(Parameters!$A$27:$A$28,J5)>0),1,0) -> 1 | Z5: =IF(((Parameters!$F$5=Parameters!$E$15)*Parameters!$I$5*1+(Parameters!$F$6=Parameters!$E$15)*Parameters!$I$6*1+(Parameters!$F$7=Parameters!$E$15)*Parameters!$I$7*1+(Parameters!$F$8=Parameters!$E$15)*Parameters!$I$8*1+(Parameters!$F$9=Parameters!$E$15)*Parameters!$I$9*1+(Parameters!$F$10=Parameters!$E$15)*Parameters!$I$10*1+(Parameters!$F$11=Parameters!$E$15)*Parameters!$I$11*X5+(Parameters!$F$12=Parameters!$E$15)*Parameters!$I$12*Y5)=0,"",IF(AND(((Parameters!$F$5=Parameters!$E$15)*Parameters!$I$5*ISNUMBER(P5)+(Parameters!$F$6=Parameters!$E$15)*Parameters!$I$6*ISNUMBER(Q5)+(Parameters!$F$7=Parameters!$E$15)*Parameters!$I$7*ISNUMBER(R5)+(Parameters!$F$8=Parameters!$E$15)*Parameters!$I$8*ISNUMBER(S5)+(Parameters!$F$9=Parameters!$E$15)*Parameters!$I$9*ISNUMBER(T5)+(Parameters!$F$10=Parameters!$E$15)*Parameters!$I$10*ISNUMBER(U5)+(Parameters!$F$11=Parameters!$E$15)*Parameters!$I$11*ISNUMBER(V5)+(Parameters!$F$12=Parameters!$E$15)*Parameters!$I$12*ISNUMBER(W5))>0,((Parameters!$F$5=Parameters!$E$15)*Parameters!$I$5*ISNUMBER(P5)+(Parameters!$F$6=Parameters!$E$15)*Parameters!$I$6*ISNUMBER(Q5)+(Parameters!$F$7=Parameters!$E$15)*Parameters!$I$7*ISNUMBER(R5)+(Parameters!$F$8=Parameters!$E$15)*Parameters!$I$8*ISNUMBER(S5)+(Parameters!$F$9=Parameters!$E$15)*Parameters!$I$9*ISNUMBER(T5)+(Parameters!$F$10=Parameters!$E$15)*Parameters!$I$10*ISNUMBER(U5)+(Parameters!$F$11=Parameters!$E$15)*Parameters!$I$11*ISNUMBER(V5)+(Parameters!$F$12=Parameters!$E$15)*Parameters!$I$12*ISNUMBER(W5))/((Parameters!$F$5=Parameters!$E$15)*Parameters!$I$5*1+(Parameters!$F$6=Parameters!$E$15)*Parameters!$I$6*1+(Parameters!$F$7=Parameters!$E$15)*Parameters!$I$7*1+(Parameters!$F$8=Parameters!$E$15)*Parameters!$I$8*1+(Parameters!$F$9=Parameters!$E$15)*Parameters!$I$9*1+(Parameters!$F$10=Parameters!$E$15)*Parameters!$I$10*1+(Parameters!$F$11=Parameters!$E$15)*Parameters!$I$11*X5+(Parameters!$F$12=Parameters!$E$15)*Parameters!$I$12*Y5)>=Parameters!$B$36),((Parameters!$F$5=Parameters!$E$15)*Parameters!$I$5*N(P5)+(Parameters!$F$6=Parameters!$E$15)*Parameters!$I$6*N(Q5)+(Parameters!$F$7=Parameters!$E$15)*Parameters!$I$7*N(R5)+(Parameters!$F$8=Parameters!$E$15)*Parameters!$I$8*N(S5)+(Parameters!$F$9=Parameters!$E$15)*Parameters!$I$9*N(T5)+(Parameters!$F$10=Parameters!$E$15)*Parameters!$I$10*N(U5)+(Parameters!$F$11=Parameters!$E$15)*Parameters!$I$11*N(V5)+(Parameters!$F$12=Parameters!$E$15)*Parameters!$I$12*N(W5))/((Parameters!$F$5=Parameters!$E$15)*Parameters!$I$5*ISNUMBER(P5)+(Parameters!$F$6=Parameters!$E$15)*Parameters!$I$6*ISNUMBER(Q5)+(Parameters!$F$7=Parameters!$E$15)*Parameters!$I$7*ISNUMBER(R5)+(Parameters!$F$8=Parameters!$E$15)*Parameters!$I$8*ISNUMBER(S5)+(Parameters!$F$9=Parameters!$E$15)*Parameters!$I$9*ISNUMBER(T5)+(Parameters!$F$10=Parameters!$E$15)*Parameters!$I$10*ISNUMBER(U5)+(Parameters!$F$11=Parameters!$E$15)*Parameters!$I$11*ISNUMBER(V5)+(Parameters!$F$12=Parameters!$E$15)*Parameters!$I$12*ISNUMBER(W5)),"")) -> 0.98666667 | AA5: =IF(((Parameters!$F$5=Parameters!$E$16)*Parameters!$I$5*1+(Parameters!$F$6=Parameters!$E$16)*Parameters!$I$6*1+(Parameters!$F$7=Parameters!$E$16)*Parameters!$I$7*1+(Parameters!$F$8=Parameters!$E$16)*Parameters!$I$8*1+(Parameters!$F$9=Parameters!$E$16)*Parameters!$I$9*1+(Parameters!$F$10=Parameters!$E$16)*Parameters!$I$10*1+(Parameters!$F$11=Parameters!$E$16)*Parameters!$I$11*X5+(Parameters!$F$12=Parameters!$E$16)*Parameters!$I$12*Y5)=0,"",IF(AND(((Parameters!$F$5=Parameters!$E$16)*Parameters!$I$5*ISNUMBER(P5)+(Parameters!$F$6=Parameters!$E$16)*Parameters!$I$6*ISNUMBER(Q5)+(Parameters!$F$7=Parameters!$E$16)*Parameters!$I$7*ISNUMBER(R5)+(Parameters!$F$8=Parameters!$E$16)*Parameters!$I$8*ISNUMBER(S5)+(Parameters!$F$9=Parameters!$E$16)*Parameters!$I$9*ISNUMBER(T5)+(Parameters!$F$10=Parameters!$E$16)*Parameters!$I$10*ISNUMBER(U5)+(Parameters!$F$11=Parameters!$E$16)*Parameters!$I$11*ISNUMBER(V5)+(Parameters!$F$12=Parameters!$E$16)*Parameters!$I$12*ISNUMBER(W5))>0,((Parameters!$F$5=Parameters!$E$16)*Parameters!$I$5*ISNUMBER(P5)+(Parameters!$F$6=Parameters!$E$16)*Parameters!$I$6*ISNUMBER(Q5)+(Parameters!$F$7=Parameters!$E$16)*Parameters!$I$7*ISNUMBER(R5)+(Parameters!$F$8=Parameters!$E$16)*Parameters!$I$8*ISNUMBER(S5)+(Parameters!$F$9=Parameters!$E$16)*Parameters!$I$9*ISNUMBER(T5)+(Parameters!$F$10=Parameters!$E$16)*Parameters!$I$10*ISNUMBER(U5)+(Parameters!$F$11=Parameters!$E$16)*Parameters!$I$11*ISNUMBER(V5)+(Parameters!$F$12=Parameters!$E$16)*Parameters!$I$12*ISNUMBER(W5))/((Parameters!$F$5=Parameters!$E$16)*Parameters!$I$5*1+(Parameters!$F$6=Parameters!$E$16)*Parameters!$I$6*1+(Parameters!$F$7=Parameters!$E$16)*Parameters!$I$7*1+(Parameters!$F$8=Parameters!$E$16)*Parameters!$I$8*1+(Parameters!$F$9=Parameters!$E$16)*Parameters!$I$9*1+(Parameters!$F$10=Parameters!$E$16)*Parameters!$I$10*1+(Parameters!$F$11=Parameters!$E$16)*Parameters!$I$11*X5+(Parameters!$F$12=Parameters!$E$16)*Parameters!$I$12*Y5)>=Parameters!$B$36),((Parameters!$F$5=Parameters!$E$16)*Parameters!$I$5*N(P5)+(Parameters!$F$6=Parameters!$E$16)*Parameters!$I$6*N(Q5)+(Parameters!$F$7=Parameters!$E$16)*Parameters!$I$7*N(R5)+(Parameters!$F$8=Parameters!$E$16)*Parameters!$I$8*N(S5)+(Parameters!$F$9=Parameters!$E$16)*Parameters!$I$9*N(T5)+(Parameters!$F$10=Parameters!$E$16)*Parameters!$I$10*N(U5)+(Parameters!$F$11=Parameters!$E$16)*Parameters!$I$11*N(V5)+(Parameters!$F$12=Parameters!$E$16)*Parameters!$I$12*N(W5))/((Parameters!$F$5=Parameters!$E$16)*Parameters!$I$5*ISNUMBER(P5)+(Parameters!$F$6=Parameters!$E$16)*Parameters!$I$6*ISNUMBER(Q5)+(Parameters!$F$7=Parameters!$E$16)*Parameters!$I$7*ISNUMBER(R5)+(Parameters!$F$8=Parameters!$E$16)*Parameters!$I$8*ISNUMBER(S5)+(Parameters!$F$9=Parameters!$E$16)*Parameters!$I$9*ISNUMBER(T5)+(Parameters!$F$10=Parameters!$E$16)*Parameters!$I$10*ISNUMBER(U5)+(Parameters!$F$11=Parameters!$E$16)*Parameters!$I$11*ISNUMBER(V5)+(Parameters!$F$12=Parameters!$E$16)*Parameters!$I$12*ISNUMBER(W5)),"")) -> 0.8 | AB5: =IF(((Parameters!$F$5=Parameters!$E$17)*Parameters!$I$5*1+(Parameters!$F$6=Parameters!$E$17)*Parameters!$I$6*1+(Parameters!$F$7=Parameters!$E$17)*Parameters!$I$7*1+(Parameters!$F$8=Parameters!$E$17)*Parameters!$I$8*1+(Parameters!$F$9=Parameters!$E$17)*Parameters!$I$9*1+(Parameters!$F$10=Parameters!$E$17)*Parameters!$I$10*1+(Parameters!$F$11=Parameters!$E$17)*Parameters!$I$11*X5+(Parameters!$F$12=Parameters!$E$17)*Parameters!$I$12*Y5)=0,"",IF(AND(((Parameters!$F$5=Parameters!$E$17)*Parameters!$I$5*ISNUMBER(P5)+(Parameters!$F$6=Parameters!$E$17)*Parameters!$I$6*ISNUMBER(Q5)+(Parameters!$F$7=Parameters!$E$17)*Parameters!$I$7*ISNUMBER(R5)+(Parameters!$F$8=Parameters!$E$17)*Parameters!$I$8*ISNUMBER(S5)+(Parameters!$F$9=Parameters!$E$17)*Parameters!$I$9*ISNUMBER(T5)+(Parameters!$F$10=Parameters!$E$17)*Parameters!$I$10*ISNUMBER(U5)+(Parameters!$F$11=Parameters!$E$17)*Parameters!$I$11*ISNUMBER(V5)+(Parameters!$F$12=Parameters!$E$17)*Parameters!$I$12*ISNUMBER(W5))>0,((Parameters!$F$5=Parameters!$E$17)*Parameters!$I$5*ISNUMBER(P5)+(Parameters!$F$6=Parameters!$E$17)*Parameters!$I$6*ISNUMBER(Q5)+(Parameters!$F$7=Parameters!$E$17)*Parameters!$I$7*ISNUMBER(R5)+(Parameters!$F$8=Parameters!$E$17)*Parameters!$I$8*ISNUMBER(S5)+(Parameters!$F$9=Parameters!$E$17)*Parameters!$I$9*ISNUMBER(T5)+(Parameters!$F$10=Parameters!$E$17)*Parameters!$I$10*ISNUMBER(U5)+(Parameters!$F$11=Parameters!$E$17)*Parameters!$I$11*ISNUMBER(V5)+(Parameters!$F$12=Parameters!$E$17)*Parameters!$I$12*ISNUMBER(W5))/((Parameters!$F$5=Parameters!$E$17)*Parameters!$I$5*1+(Parameters!$F$6=Parameters!$E$17)*Parameters!$I$6*1+(Parameters!$F$7=Parameters!$E$17)*Parameters!$I$7*1+(Parameters!$F$8=Parameters!$E$17)*Parameters!$I$8*1+(Parameters!$F$9=Parameters!$E$17)*Parameters!$I$9*1+(Parameters!$F$10=Parameters!$E$17)*Parameters!$I$10*1+(Parameters!$F$11=Parameters!$E$17)*Parameters!$I$11*X5+(Parameters!$F$12=Parameters!$E$17)*Parameters!$I$12*Y5)>=Parameters!$B$36),((Parameters!$F$5=Parameters!$E$17)*Parameters!$I$5*N(P5)+(Parameters!$F$6=Parameters!$E$17)*Parameters!$I$6*N(Q5)+(Parameters!$F$7=Parameters!$E$17)*Parameters!$I$7*N(R5)+(Parameters!$F$8=Parameters!$E$17)*Parameters!$I$8*N(S5)+(Parameters!$F$9=Parameters!$E$17)*Parameters!$I$9*N(T5)+(Parameters!$F$10=Parameters!$E$17)*Parameters!$I$10*N(U5)+(Parameters!$F$11=Parameters!$E$17)*Parameters!$I$11*N(V5)+(Parameters!$F$12=Parameters!$E$17)*Parameters!$I$12*N(W5))/((Parameters!$F$5=Parameters!$E$17)*Parameters!$I$5*ISNUMBER(P5)+(Parameters!$F$6=Parameters!$E$17)*Parameters!$I$6*ISNUMBER(Q5)+(Parameters!$F$7=Parameters!$E$17)*Parameters!$I$7*ISNUMBER(R5)+(Parameters!$F$8=Parameters!$E$17)*Parameters!$I$8*ISNUMBER(S5)+(Parameters!$F$9=Parameters!$E$17)*Parameters!$I$9*ISNUMBER(T5)+(Parameters!$F$10=Parameters!$E$17)*Parameters!$I$10*ISNUMBER(U5)+(Parameters!$F$11=Parameters!$E$17)*Parameters!$I$11*ISNUMBER(V5)+(Parameters!$F$12=Parameters!$E$17)*Parameters!$I$12*ISNUMBER(W5)),"")) -> 1 | AC5: =Parameters!$I$5*ISNUMBER(P5)+Parameters!$I$6*ISNUMBER(Q5)+Parameters!$I$7*ISNUMBER(R5)+Parameters!$I$8*ISNUMBER(S5)+Parameters!$I$9*ISNUMBER(T5)+Parameters!$I$10*ISNUMBER(U5)+Parameters!$I$11*ISNUMBER(V5)+Parameters!$I$12*ISNUMBER(W5) -> 95 | AD5: =Parameters!$I$5*1+Parameters!$I$6*1+Parameters!$I$7*1+Parameters!$I$8*1+Parameters!$I$9*1+Parameters!$I$10*1+Parameters!$I$11*X5+Parameters!$I$12*Y5 -> 95 | AE5: =IF(AD5=0,"",AC5/AD5) -> 1 | AF5: =IF(ISNUMBER(Z5),"M","")&IF(ISNUMBER(AA5),"I","")&IF(ISNUMBER(AB5),"O","") -> MIO | AG5: =IF(AND(ISNUMBER(AE5),ISNUMBER(Z5)+ISNUMBER(AA5)+ISNUMBER(AB5)>=Parameters!$B$37),IF(AE5>=Parameters!$B$35,100*(Parameters!$F$15*N(Z5)+Parameters!$F$16*N(AA5)+Parameters!$F$17*N(AB5))/(Parameters!$F$15*ISNUMBER(Z5)+Parameters!$F$16*ISNUMBER(AA5)+Parameters!$F$17*ISNUMBER(AB5)),""),"") -> 93.333333 | AH5: =IF(ISNUMBER(AG5),RANK(AG5,$AG$2:$AG$113),"") -> 12
A6: Archipelago Commons | B6: Metropolitan New York Library Council | C6: Digital library, collection or exhibit platform | Repository software | D6: Actual system proven in operational environment | E6: Actively Maintained | F6: 2018-01-01 | I6: FALSE | J6: Through solution provider or third party vendor | L6: Fiscal sponsorship (non-profit) | Non-profit organization | M6: Other | P6: =IFERROR(IF(ISNUMBER(INDEX(Parameters!$B$5:$B$23,MATCH(D6,Parameters!$A$5:$A$23,0))),INDEX(Parameters!$B$5:$B$23,MATCH(D6,Parameters!$A$5:$A$23,0)),""),"") -> 1 | Q6: =IFERROR(IF(ISNUMBER(INDEX(Parameters!$B$5:$B$23,MATCH(E6,Parameters!$A$5:$A$23,0))),INDEX(Parameters!$B$5:$B$23,MATCH(E6,Parameters!$A$5:$A$23,0)),""),"") -> 1 | R6: =IF(F6="","",IFERROR(MIN(Parameters!$B$33,MAX(0,Parameters!$B$32-VALUE(LEFT(F6,4))))/Parameters!$B$33,"")) -> 0.53333333 | S6: =IF(ISNUMBER(H6),H6,IF(G6="",IF(ISNUMBER(Parameters!$B$34),Parameters!$B$34,""),"")) | T6: =IFERROR(IF(ISNUMBER(INDEX(Parameters!$B$5:$B$23,MATCH(I6,Parameters!$A$5:$A$23,0))),INDEX(Parameters!$B$5:$B$23,MATCH(I6,Parameters!$A$5:$A$23,0)),""),"") -> 0 | U6: =IFERROR(IF(ISNUMBER(INDEX(Parameters!$B$5:$B$23,MATCH(L6,Parameters!$A$5:$A$23,0))),INDEX(Parameters!$B$5:$B$23,MATCH(L6,Parameters!$A$5:$A$23,0)),""),"") -> 1 | V6: =IFERROR(IF(ISNUMBER(INDEX(Parameters!$B$5:$B$23,MATCH(J6,Parameters!$A$5:$A$23,0))),INDEX(Parameters!$B$5:$B$23,MATCH(J6,Parameters!$A$5:$A$23,0)),""),"") -> 1 | W6: =IF(K6<>"",1,IF(COUNTIF(Parameters!$A$27:$A$28,J6)>0,0,"")) -> 0 | X6: =IF(J6="Not applicable",0,1) -> 1 | Y6: =IF(OR(K6<>"",COUNTIF(Parameters!$A$27:$A$28,J6)>0),1,0) -> 1 | Z6: =IF(((Parameters!$F$5=Parameters!$E$15)*Parameters!$I$5*1+(Parameters!$F$6=Parameters!$E$15)*Parameters!$I$6*1+(Parameters!$F$7=Parameters!$E$15)*Parameters!$I$7*1+(Parameters!$F$8=Parameters!$E$15)*Parameters!$I$8*1+(Parameters!$F$9=Parameters!$E$15)*Parameters!$I$9*1+(Parameters!$F$10=Parameters!$E$15)*Parameters!$I$10*1+(Parameters!$F$11=Parameters!$E$15)*Parameters!$I$11*X6+(Parameters!$F$12=Parameters!$E$15)*Parameters!$I$12*Y6)=0,"",IF(AND(((Parameters!$F$5=Parameters!$E$15)*Parameters!$I$5*ISNUMBER(P6)+(Parameters!$F$6=Parameters!$E$15)*Parameters!$I$6*ISNUMBER(Q6)+(Parameters!$F$7=Parameters!$E$15)*Parameters!$I$7*ISNUMBER(R6)+(Parameters!$F$8=Parameters!$E$15)*Parameters!$I$8*ISNUMBER(S6)+(Parameters!$F$9=Parameters!$E$15)*Parameters!$I$9*ISNUMBER(T6)+(Parameters!$F$10=Parameters!$E$15)*Parameters!$I$10*ISNUMBER(U6)+(Parameters!$F$11=Parameters!$E$15)*Parameters!$I$11*ISNUMBER(V6)+(Parameters!$F$12=Parameters!$E$15)*Parameters!$I$12*ISNUMBER(W6))>0,((Parameters!$F$5=Parameters!$E$15)*Parameters!$I$5*ISNUMBER(P6)+(Parameters!$F$6=Parameters!$E$15)*Parameters!$I$6*ISNUMBER(Q6)+(Parameters!$F$7=Parameters!$E$15)*Parameters!$I$7*ISNUMBER(R6)+(Parameters!$F$8=Parameters!$E$15)*Parameters!$I$8*ISNUMBER(S6)+(Parameters!$F$9=Parameters!$E$15)*Parameters!$I$9*ISNUMBER(T6)+(Parameters!$F$10=Parameters!$E$15)*Parameters!$I$10*ISNUMBER(U6)+(Parameters!$F$11=Parameters!$E$15)*Parameters!$I$11*ISNUMBER(V6)+(Parameters!$F$12=Parameters!$E$15)*Parameters!$I$12*ISNUMBER(W6))/((Parameters!$F$5=Parameters!$E$15)*Parameters!$I$5*1+(Parameters!$F$6=Parameters!$E$15)*Parameters!$I$6*1+(Parameters!$F$7=Parameters!$E$15)*Parameters!$I$7*1+(Parameters!$F$8=Parameters!$E$15)*Parameters!$I$8*1+(Parameters!$F$9=Parameters!$E$15)*Parameters!$I$9*1+(Parameters!$F$10=Parameters!$E$15)*Parameters!$I$10*1+(Parameters!$F$11=Parameters!$E$15)*Parameters!$I$11*X6+(Parameters!$F$12=Parameters!$E$15)*Parameters!$I$12*Y6)>=Parameters!$B$36),((Parameters!$F$5=Parameters!$E$15)*Parameters!$I$5*N(P6)+(Parameters!$F$6=Parameters!$E$15)*Parameters!$I$6*N(Q6)+(Parameters!$F$7=Parameters!$E$15)*Parameters!$I$7*N(R6)+(Parameters!$F$8=Parameters!$E$15)*Parameters!$I$8*N(S6)+(Parameters!$F$9=Parameters!$E$15)*Parameters!$I$9*N(T6)+(Parameters!$F$10=Parameters!$E$15)*Parameters!$I$10*N(U6)+(Parameters!$F$11=Parameters!$E$15)*Parameters!$I$11*N(V6)+(Parameters!$F$12=Parameters!$E$15)*Parameters!$I$12*N(W6))/((Parameters!$F$5=Parameters!$E$15)*Parameters!$I$5*ISNUMBER(P6)+(Parameters!$F$6=Parameters!$E$15)*Parameters!$I$6*ISNUMBER(Q6)+(Parameters!$F$7=Parameters!$E$15)*Parameters!$I$7*ISNUMBER(R6)+(Parameters!$F$8=Parameters!$E$15)*Parameters!$I$8*ISNUMBER(S6)+(Parameters!$F$9=Parameters!$E$15)*Parameters!$I$9*ISNUMBER(T6)+(Parameters!$F$10=Parameters!$E$15)*Parameters!$I$10*ISNUMBER(U6)+(Parameters!$F$11=Parameters!$E$15)*Parameters!$I$11*ISNUMBER(V6)+(Parameters!$F$12=Parameters!$E$15)*Parameters!$I$12*ISNUMBER(W6)),"")) -> 0.95333333 | AA6: =IF(((Parameters!$F$5=Parameters!$E$16)*Parameters!$I$5*1+(Parameters!$F$6=Parameters!$E$16)*Parameters!$I$6*1+(Parameters!$F$7=Parameters!$E$16)*Parameters!$I$7*1+(Parameters!$F$8=Parameters!$E$16)*Parameters!$I$8*1+(Parameters!$F$9=Parameters!$E$16)*Parameters!$I$9*1+(Parameters!$F$10=Parameters!$E$16)*Parameters!$I$10*1+(Parameters!$F$11=Parameters!$E$16)*Parameters!$I$11*X6+(Parameters!$F$12=Parameters!$E$16)*Parameters!$I$12*Y6)=0,"",IF(AND(((Parameters!$F$5=Parameters!$E$16)*Parameters!$I$5*ISNUMBER(P6)+(Parameters!$F$6=Parameters!$E$16)*Parameters!$I$6*ISNUMBER(Q6)+(Parameters!$F$7=Parameters!$E$16)*Parameters!$I$7*ISNUMBER(R6)+(Parameters!$F$8=Parameters!$E$16)*Parameters!$I$8*ISNUMBER(S6)+(Parameters!$F$9=Parameters!$E$16)*Parameters!$I$9*ISNUMBER(T6)+(Parameters!$F$10=Parameters!$E$16)*Parameters!$I$10*ISNUMBER(U6)+(Parameters!$F$11=Parameters!$E$16)*Parameters!$I$11*ISNUMBER(V6)+(Parameters!$F$12=Parameters!$E$16)*Parameters!$I$12*ISNUMBER(W6))>0,((Parameters!$F$5=Parameters!$E$16)*Parameters!$I$5*ISNUMBER(P6)+(Parameters!$F$6=Parameters!$E$16)*Parameters!$I$6*ISNUMBER(Q6)+(Parameters!$F$7=Parameters!$E$16)*Parameters!$I$7*ISNUMBER(R6)+(Parameters!$F$8=Parameters!$E$16)*Parameters!$I$8*ISNUMBER(S6)+(Parameters!$F$9=Parameters!$E$16)*Parameters!$I$9*ISNUMBER(T6)+(Parameters!$F$10=Parameters!$E$16)*Parameters!$I$10*ISNUMBER(U6)+(Parameters!$F$11=Parameters!$E$16)*Parameters!$I$11*ISNUMBER(V6)+(Parameters!$F$12=Parameters!$E$16)*Parameters!$I$12*ISNUMBER(W6))/((Parameters!$F$5=Parameters!$E$16)*Parameters!$I$5*1+(Parameters!$F$6=Parameters!$E$16)*Parameters!$I$6*1+(Parameters!$F$7=Parameters!$E$16)*Parameters!$I$7*1+(Parameters!$F$8=Parameters!$E$16)*Parameters!$I$8*1+(Parameters!$F$9=Parameters!$E$16)*Parameters!$I$9*1+(Parameters!$F$10=Parameters!$E$16)*Parameters!$I$10*1+(Parameters!$F$11=Parameters!$E$16)*Parameters!$I$11*X6+(Parameters!$F$12=Parameters!$E$16)*Parameters!$I$12*Y6)>=Parameters!$B$36),((Parameters!$F$5=Parameters!$E$16)*Parameters!$I$5*N(P6)+(Parameters!$F$6=Parameters!$E$16)*Parameters!$I$6*N(Q6)+(Parameters!$F$7=Parameters!$E$16)*Parameters!$I$7*N(R6)+(Parameters!$F$8=Parameters!$E$16)*Parameters!$I$8*N(S6)+(Parameters!$F$9=Parameters!$E$16)*Parameters!$I$9*N(T6)+(Parameters!$F$10=Parameters!$E$16)*Parameters!$I$10*N(U6)+(Parameters!$F$11=Parameters!$E$16)*Parameters!$I$11*N(V6)+(Parameters!$F$12=Parameters!$E$16)*Parameters!$I$12*N(W6))/((Parameters!$F$5=Parameters!$E$16)*Parameters!$I$5*ISNUMBER(P6)+(Parameters!$F$6=Parameters!$E$16)*Parameters!$I$6*ISNUMBER(Q6)+(Parameters!$F$7=Parameters!$E$16)*Parameters!$I$7*ISNUMBER(R6)+(Parameters!$F$8=Parameters!$E$16)*Parameters!$I$8*ISNUMBER(S6)+(Parameters!$F$9=Parameters!$E$16)*Parameters!$I$9*ISNUMBER(T6)+(Parameters!$F$10=Parameters!$E$16)*Parameters!$I$10*ISNUMBER(U6)+(Parameters!$F$11=Parameters!$E$16)*Parameters!$I$11*ISNUMBER(V6)+(Parameters!$F$12=Parameters!$E$16)*Parameters!$I$12*ISNUMBER(W6)),"")) -> 0.66666667 | AB6: =IF(((Parameters!$F$5=Parameters!$E$17)*Parameters!$I$5*1+(Parameters!$F$6=Parameters!$E$17)*Parameters!$I$6*1+(Parameters!$F$7=Parameters!$E$17)*Parameters!$I$7*1+(Parameters!$F$8=Parameters!$E$17)*Parameters!$I$8*1+(Parameters!$F$9=Parameters!$E$17)*Parameters!$I$9*1+(Parameters!$F$10=Parameters!$E$17)*Parameters!$I$10*1+(Parameters!$F$11=Parameters!$E$17)*Parameters!$I$11*X6+(Parameters!$F$12=Parameters!$E$17)*Parameters!$I$12*Y6)=0,"",IF(AND(((Parameters!$F$5=Parameters!$E$17)*Parameters!$I$5*ISNUMBER(P6)+(Parameters!$F$6=Parameters!$E$17)*Parameters!$I$6*ISNUMBER(Q6)+(Parameters!$F$7=Parameters!$E$17)*Parameters!$I$7*ISNUMBER(R6)+(Parameters!$F$8=Parameters!$E$17)*Parameters!$I$8*ISNUMBER(S6)+(Parameters!$F$9=Parameters!$E$17)*Parameters!$I$9*ISNUMBER(T6)+(Parameters!$F$10=Parameters!$E$17)*Parameters!$I$10*ISNUMBER(U6)+(Parameters!$F$11=Parameters!$E$17)*Parameters!$I$11*ISNUMBER(V6)+(Parameters!$F$12=Parameters!$E$17)*Parameters!$I$12*ISNUMBER(W6))>0,((Parameters!$F$5=Parameters!$E$17)*Parameters!$I$5*ISNUMBER(P6)+(Parameters!$F$6=Parameters!$E$17)*Parameters!$I$6*ISNUMBER(Q6)+(Parameters!$F$7=Parameters!$E$17)*Parameters!$I$7*ISNUMBER(R6)+(Parameters!$F$8=Parameters!$E$17)*Parameters!$I$8*ISNUMBER(S6)+(Parameters!$F$9=Parameters!$E$17)*Parameters!$I$9*ISNUMBER(T6)+(Parameters!$F$10=Parameters!$E$17)*Parameters!$I$10*ISNUMBER(U6)+(Parameters!$F$11=Parameters!$E$17)*Parameters!$I$11*ISNUMBER(V6)+(Parameters!$F$12=Parameters!$E$17)*Parameters!$I$12*ISNUMBER(W6))/((Parameters!$F$5=Parameters!$E$17)*Parameters!$I$5*1+(Parameters!$F$6=Parameters!$E$17)*Parameters!$I$6*1+(Parameters!$F$7=Parameters!$E$17)*Parameters!$I$7*1+(Parameters!$F$8=Parameters!$E$17)*Parameters!$I$8*1+(Parameters!$F$9=Parameters!$E$17)*Parameters!$I$9*1+(Parameters!$F$10=Parameters!$E$17)*Parameters!$I$10*1+(Parameters!$F$11=Parameters!$E$17)*Parameters!$I$11*X6+(Parameters!$F$12=Parameters!$E$17)*Parameters!$I$12*Y6)>=Parameters!$B$36),((Parameters!$F$5=Parameters!$E$17)*Parameters!$I$5*N(P6)+(Parameters!$F$6=Parameters!$E$17)*Parameters!$I$6*N(Q6)+(Parameters!$F$7=Parameters!$E$17)*Parameters!$I$7*N(R6)+(Parameters!$F$8=Parameters!$E$17)*Parameters!$I$8*N(S6)+(Parameters!$F$9=Parameters!$E$17)*Parameters!$I$9*N(T6)+(Parameters!$F$10=Parameters!$E$17)*Parameters!$I$10*N(U6)+(Parameters!$F$11=Parameters!$E$17)*Parameters!$I$11*N(V6)+(Parameters!$F$12=Parameters!$E$17)*Parameters!$I$12*N(W6))/((Parameters!$F$5=Parameters!$E$17)*Parameters!$I$5*ISNUMBER(P6)+(Parameters!$F$6=Parameters!$E$17)*Parameters!$I$6*ISNUMBER(Q6)+(Parameters!$F$7=Parameters!$E$17)*Parameters!$I$7*ISNUMBER(R6)+(Parameters!$F$8=Parameters!$E$17)*Parameters!$I$8*ISNUMBER(S6)+(Parameters!$F$9=Parameters!$E$17)*Parameters!$I$9*ISNUMBER(T6)+(Parameters!$F$10=Parameters!$E$17)*Parameters!$I$10*ISNUMBER(U6)+(Parameters!$F$11=Parameters!$E$17)*Parameters!$I$11*ISNUMBER(V6)+(Parameters!$F$12=Parameters!$E$17)*Parameters!$I$12*ISNUMBER(W6)),"")) -> 0.5 | AC6: =Parameters!$I$5*ISNUMBER(P6)+Parameters!$I$6*ISNUMBER(Q6)+Parameters!$I$7*ISNUMBER(R6)+Parameters!$I$8*ISNUMBER(S6)+Parameters!$I$9*ISNUMBER(T6)+Parameters!$I$10*ISNUMBER(U6)+Parameters!$I$11*ISNUMBER(V6)+Parameters!$I$12*ISNUMBER(W6) -> 85 | AD6: =Parameters!$I$5*1+Parameters!$I$6*1+Parameters!$I$7*1+Parameters!$I$8*1+Parameters!$I$9*1+Parameters!$I$10*1+Parameters!$I$11*X6+Parameters!$I$12*Y6 -> 95 | AE6: =IF(AD6=0,"",AC6/AD6) -> 0.89473684 | AF6: =IF(ISNUMBER(Z6),"M","")&IF(ISNUMBER(AA6),"I","")&IF(ISNUMBER(AB6),"O","") -> MIO | AG6: =IF(AND(ISNUMBER(AE6),ISNUMBER(Z6)+ISNUMBER(AA6)+ISNUMBER(AB6)>=Parameters!$B$37),IF(AE6>=Parameters!$B$35,100*(Parameters!$F$15*N(Z6)+Parameters!$F$16*N(AA6)+Parameters!$F$17*N(AB6))/(Parameters!$F$15*ISNUMBER(Z6)+Parameters!$F$16*ISNUMBER(AA6)+Parameters!$F$17*ISNUMBER(AB6)),""),"") -> 77.666667 | AH6: =IF(ISNUMBER(AG6),RANK(AG6,$AG$2:$AG$113),"") -> 83
A7: Archival Resource Key | B7: ARK Alliance | C7: Standard, specification or protocol | D7: Technology validated in relevant environment | E7: Actively Maintained | F7: 2001-01-01 | I7: FALSE | J7: Not applicable | L7: Volunteer community | M7: Other | P7: =IFERROR(IF(ISNUMBER(INDEX(Parameters!$B$5:$B$23,MATCH(D7,Parameters!$A$5:$A$23,0))),INDEX(Parameters!$B$5:$B$23,MATCH(D7,Parameters!$A$5:$A$23,0)),""),"") -> 0.55555556 | Q7: =IFERROR(IF(ISNUMBER(INDEX(Parameters!$B$5:$B$23,MATCH(E7,Parameters!$A$5:$A$23,0))),INDEX(Parameters!$B$5:$B$23,MATCH(E7,Parameters!$A$5:$A$23,0)),""),"") -> 1 | R7: =IF(F7="","",IFERROR(MIN(Parameters!$B$33,MAX(0,Parameters!$B$32-VALUE(LEFT(F7,4))))/Parameters!$B$33,"")) -> 1 | S7: =IF(ISNUMBER(H7),H7,IF(G7="",IF(ISNUMBER(Parameters!$B$34),Parameters!$B$34,""),"")) | T7: =IFERROR(IF(ISNUMBER(INDEX(Parameters!$B$5:$B$23,MATCH(I7,Parameters!$A$5:$A$23,0))),INDEX(Parameters!$B$5:$B$23,MATCH(I7,Parameters!$A$5:$A$23,0)),""),"") -> 0 | U7: =IFERROR(IF(ISNUMBER(INDEX(Parameters!$B$5:$B$23,MATCH(L7,Parameters!$A$5:$A$23,0))),INDEX(Parameters!$B$5:$B$23,MATCH(L7,Parameters!$A$5:$A$23,0)),""),"") -> 0 | V7: =IFERROR(IF(ISNUMBER(INDEX(Parameters!$B$5:$B$23,MATCH(J7,Parameters!$A$5:$A$23,0))),INDEX(Parameters!$B$5:$B$23,MATCH(J7,Parameters!$A$5:$A$23,0)),""),"") | W7: =IF(K7<>"",1,IF(COUNTIF(Parameters!$A$27:$A$28,J7)>0,0,"")) | X7: =IF(J7="Not applicable",0,1) -> 0 | Y7: =IF(OR(K7<>"",COUNTIF(Parameters!$A$27:$A$28,J7)>0),1,0) -> 0 | Z7: =IF(((Parameters!$F$5=Parameters!$E$15)*Parameters!$I$5*1+(Parameters!$F$6=Parameters!$E$15)*Parameters!$I$6*1+(Parameters!$F$7=Parameters!$E$15)*Parameters!$I$7*1+(Parameters!$F$8=Parameters!$E$15)*Parameters!$I$8*1+(Parameters!$F$9=Parameters!$E$15)*Parameters!$I$9*1+(Parameters!$F$10=Parameters!$E$15)*Parameters!$I$10*1+(Parameters!$F$11=Parameters!$E$15)*Parameters!$I$11*X7+(Parameters!$F$12=Parameters!$E$15)*Parameters!$I$12*Y7)=0,"",IF(AND(((Parameters!$F$5=Parameters!$E$15)*Parameters!$I$5*ISNUMBER(P7)+(Parameters!$F$6=Parameters!$E$15)*Parameters!$I$6*ISNUMBER(Q7)+(Parameters!$F$7=Parameters!$E$15)*Parameters!$I$7*ISNUMBER(R7)+(Parameters!$F$8=Parameters!$E$15)*Parameters!$I$8*ISNUMBER(S7)+(Parameters!$F$9=Parameters!$E$15)*Parameters!$I$9*ISNUMBER(T7)+(Parameters!$F$10=Parameters!$E$15)*Parameters!$I$10*ISNUMBER(U7)+(Parameters!$F$11=Parameters!$E$15)*Parameters!$I$11*ISNUMBER(V7)+(Parameters!$F$12=Parameters!$E$15)*Parameters!$I$12*ISNUMBER(W7))>0,((Parameters!$F$5=Parameters!$E$15)*Parameters!$I$5*ISNUMBER(P7)+(Parameters!$F$6=Parameters!$E$15)*Parameters!$I$6*ISNUMBER(Q7)+(Parameters!$F$7=Parameters!$E$15)*Parameters!$I$7*ISNUMBER(R7)+(Parameters!$F$8=Parameters!$E$15)*Parameters!$I$8*ISNUMBER(S7)+(Parameters!$F$9=Parameters!$E$15)*Parameters!$I$9*ISNUMBER(T7)+(Parameters!$F$10=Parameters!$E$15)*Parameters!$I$10*ISNUMBER(U7)+(Parameters!$F$11=Parameters!$E$15)*Parameters!$I$11*ISNUMBER(V7)+(Parameters!$F$12=Parameters!$E$15)*Parameters!$I$12*ISNUMBER(W7))/((Parameters!$F$5=Parameters!$E$15)*Parameters!$I$5*1+(Parameters!$F$6=Parameters!$E$15)*Parameters!$I$6*1+(Parameters!$F$7=Parameters!$E$15)*Parameters!$I$7*1+(Parameters!$F$8=Parameters!$E$15)*Parameters!$I$8*1+(Parameters!$F$9=Parameters!$E$15)*Parameters!$I$9*1+(Parameters!$F$10=Parameters!$E$15)*Parameters!$I$10*1+(Parameters!$F$11=Parameters!$E$15)*Parameters!$I$11*X7+(Parameters!$F$12=Parameters!$E$15)*Parameters!$I$12*Y7)>=Parameters!$B$36),((Parameters!$F$5=Parameters!$E$15)*Parameters!$I$5*N(P7)+(Parameters!$F$6=Parameters!$E$15)*Parameters!$I$6*N(Q7)+(Parameters!$F$7=Parameters!$E$15)*Parameters!$I$7*N(R7)+(Parameters!$F$8=Parameters!$E$15)*Parameters!$I$8*N(S7)+(Parameters!$F$9=Parameters!$E$15)*Parameters!$I$9*N(T7)+(Parameters!$F$10=Parameters!$E$15)*Parameters!$I$10*N(U7)+(Parameters!$F$11=Parameters!$E$15)*Parameters!$I$11*N(V7)+(Parameters!$F$12=Parameters!$E$15)*Parameters!$I$12*N(W7))/((Parameters!$F$5=Parameters!$E$15)*Parameters!$I$5*ISNUMBER(P7)+(Parameters!$F$6=Parameters!$E$15)*Parameters!$I$6*ISNUMBER(Q7)+(Parameters!$F$7=Parameters!$E$15)*Parameters!$I$7*ISNUMBER(R7)+(Parameters!$F$8=Parameters!$E$15)*Parameters!$I$8*ISNUMBER(S7)+(Parameters!$F$9=Parameters!$E$15)*Parameters!$I$9*ISNUMBER(T7)+(Parameters!$F$10=Parameters!$E$15)*Parameters!$I$10*ISNUMBER(U7)+(Parameters!$F$11=Parameters!$E$15)*Parameters!$I$11*ISNUMBER(V7)+(Parameters!$F$12=Parameters!$E$15)*Parameters!$I$12*ISNUMBER(W7)),"")) -> 0.82222222 | AA7: =IF(((Parameters!$F$5=Parameters!$E$16)*Parameters!$I$5*1+(Parameters!$F$6=Parameters!$E$16)*Parameters!$I$6*1+(Parameters!$F$7=Parameters!$E$16)*Parameters!$I$7*1+(Parameters!$F$8=Parameters!$E$16)*Parameters!$I$8*1+(Parameters!$F$9=Parameters!$E$16)*Parameters!$I$9*1+(Parameters!$F$10=Parameters!$E$16)*Parameters!$I$10*1+(Parameters!$F$11=Parameters!$E$16)*Parameters!$I$11*X7+(Parameters!$F$12=Parameters!$E$16)*Parameters!$I$12*Y7)=0,"",IF(AND(((Parameters!$F$5=Parameters!$E$16)*Parameters!$I$5*ISNUMBER(P7)+(Parameters!$F$6=Parameters!$E$16)*Parameters!$I$6*ISNUMBER(Q7)+(Parameters!$F$7=Parameters!$E$16)*Parameters!$I$7*ISNUMBER(R7)+(Parameters!$F$8=Parameters!$E$16)*Parameters!$I$8*ISNUMBER(S7)+(Parameters!$F$9=Parameters!$E$16)*Parameters!$I$9*ISNUMBER(T7)+(Parameters!$F$10=Parameters!$E$16)*Parameters!$I$10*ISNUMBER(U7)+(Parameters!$F$11=Parameters!$E$16)*Parameters!$I$11*ISNUMBER(V7)+(Parameters!$F$12=Parameters!$E$16)*Parameters!$I$12*ISNUMBER(W7))>0,((Parameters!$F$5=Parameters!$E$16)*Parameters!$I$5*ISNUMBER(P7)+(Parameters!$F$6=Parameters!$E$16)*Parameters!$I$6*ISNUMBER(Q7)+(Parameters!$F$7=Parameters!$E$16)*Parameters!$I$7*ISNUMBER(R7)+(Parameters!$F$8=Parameters!$E$16)*Parameters!$I$8*ISNUMBER(S7)+(Parameters!$F$9=Parameters!$E$16)*Parameters!$I$9*ISNUMBER(T7)+(Parameters!$F$10=Parameters!$E$16)*Parameters!$I$10*ISNUMBER(U7)+(Parameters!$F$11=Parameters!$E$16)*Parameters!$I$11*ISNUMBER(V7)+(Parameters!$F$12=Parameters!$E$16)*Parameters!$I$12*ISNUMBER(W7))/((Parameters!$F$5=Parameters!$E$16)*Parameters!$I$5*1+(Parameters!$F$6=Parameters!$E$16)*Parameters!$I$6*1+(Parameters!$F$7=Parameters!$E$16)*Parameters!$I$7*1+(Parameters!$F$8=Parameters!$E$16)*Parameters!$I$8*1+(Parameters!$F$9=Parameters!$E$16)*Parameters!$I$9*1+(Parameters!$F$10=Parameters!$E$16)*Parameters!$I$10*1+(Parameters!$F$11=Parameters!$E$16)*Parameters!$I$11*X7+(Parameters!$F$12=Parameters!$E$16)*Parameters!$I$12*Y7)>=Parameters!$B$36),((Parameters!$F$5=Parameters!$E$16)*Parameters!$I$5*N(P7)+(Parameters!$F$6=Parameters!$E$16)*Parameters!$I$6*N(Q7)+(Parameters!$F$7=Parameters!$E$16)*Parameters!$I$7*N(R7)+(Parameters!$F$8=Parameters!$E$16)*Parameters!$I$8*N(S7)+(Parameters!$F$9=Parameters!$E$16)*Parameters!$I$9*N(T7)+(Parameters!$F$10=Parameters!$E$16)*Parameters!$I$10*N(U7)+(Parameters!$F$11=Parameters!$E$16)*Parameters!$I$11*N(V7)+(Parameters!$F$12=Parameters!$E$16)*Parameters!$I$12*N(W7))/((Parameters!$F$5=Parameters!$E$16)*Parameters!$I$5*ISNUMBER(P7)+(Parameters!$F$6=Parameters!$E$16)*Parameters!$I$6*ISNUMBER(Q7)+(Parameters!$F$7=Parameters!$E$16)*Parameters!$I$7*ISNUMBER(R7)+(Parameters!$F$8=Parameters!$E$16)*Parameters!$I$8*ISNUMBER(S7)+(Parameters!$F$9=Parameters!$E$16)*Parameters!$I$9*ISNUMBER(T7)+(Parameters!$F$10=Parameters!$E$16)*Parameters!$I$10*ISNUMBER(U7)+(Parameters!$F$11=Parameters!$E$16)*Parameters!$I$11*ISNUMBER(V7)+(Parameters!$F$12=Parameters!$E$16)*Parameters!$I$12*ISNUMBER(W7)),"")) -> 0 | AB7: =IF(((Parameters!$F$5=Parameters!$E$17)*Parameters!$I$5*1+(Parameters!$F$6=Parameters!$E$17)*Parameters!$I$6*1+(Parameters!$F$7=Parameters!$E$17)*Parameters!$I$7*1+(Parameters!$F$8=Parameters!$E$17)*Parameters!$I$8*1+(Parameters!$F$9=Parameters!$E$17)*Parameters!$I$9*1+(Parameters!$F$10=Parameters!$E$17)*Parameters!$I$10*1+(Parameters!$F$11=Parameters!$E$17)*Parameters!$I$11*X7+(Parameters!$F$12=Parameters!$E$17)*Parameters!$I$12*Y7)=0,"",IF(AND(((Parameters!$F$5=Parameters!$E$17)*Parameters!$I$5*ISNUMBER(P7)+(Parameters!$F$6=Parameters!$E$17)*Parameters!$I$6*ISNUMBER(Q7)+(Parameters!$F$7=Parameters!$E$17)*Parameters!$I$7*ISNUMBER(R7)+(Parameters!$F$8=Parameters!$E$17)*Parameters!$I$8*ISNUMBER(S7)+(Parameters!$F$9=Parameters!$E$17)*Parameters!$I$9*ISNUMBER(T7)+(Parameters!$F$10=Parameters!$E$17)*Parameters!$I$10*ISNUMBER(U7)+(Parameters!$F$11=Parameters!$E$17)*Parameters!$I$11*ISNUMBER(V7)+(Parameters!$F$12=Parameters!$E$17)*Parameters!$I$12*ISNUMBER(W7))>0,((Parameters!$F$5=Parameters!$E$17)*Parameters!$I$5*ISNUMBER(P7)+(Parameters!$F$6=Parameters!$E$17)*Parameters!$I$6*ISNUMBER(Q7)+(Parameters!$F$7=Parameters!$E$17)*Parameters!$I$7*ISNUMBER(R7)+(Parameters!$F$8=Parameters!$E$17)*Parameters!$I$8*ISNUMBER(S7)+(Parameters!$F$9=Parameters!$E$17)*Parameters!$I$9*ISNUMBER(T7)+(Parameters!$F$10=Parameters!$E$17)*Parameters!$I$10*ISNUMBER(U7)+(Parameters!$F$11=Parameters!$E$17)*Parameters!$I$11*ISNUMBER(V7)+(Parameters!$F$12=Parameters!$E$17)*Parameters!$I$12*ISNUMBER(W7))/((Parameters!$F$5=Parameters!$E$17)*Parameters!$I$5*1+(Parameters!$F$6=Parameters!$E$17)*Parameters!$I$6*1+(Parameters!$F$7=Parameters!$E$17)*Parameters!$I$7*1+(Parameters!$F$8=Parameters!$E$17)*Parameters!$I$8*1+(Parameters!$F$9=Parameters!$E$17)*Parameters!$I$9*1+(Parameters!$F$10=Parameters!$E$17)*Parameters!$I$10*1+(Parameters!$F$11=Parameters!$E$17)*Parameters!$I$11*X7+(Parameters!$F$12=Parameters!$E$17)*Parameters!$I$12*Y7)>=Parameters!$B$36),((Parameters!$F$5=Parameters!$E$17)*Parameters!$I$5*N(P7)+(Parameters!$F$6=Parameters!$E$17)*Parameters!$I$6*N(Q7)+(Parameters!$F$7=Parameters!$E$17)*Parameters!$I$7*N(R7)+(Parameters!$F$8=Parameters!$E$17)*Parameters!$I$8*N(S7)+(Parameters!$F$9=Parameters!$E$17)*Parameters!$I$9*N(T7)+(Parameters!$F$10=Parameters!$E$17)*Parameters!$I$10*N(U7)+(Parameters!$F$11=Parameters!$E$17)*Parameters!$I$11*N(V7)+(Parameters!$F$12=Parameters!$E$17)*Parameters!$I$12*N(W7))/((Parameters!$F$5=Parameters!$E$17)*Parameters!$I$5*ISNUMBER(P7)+(Parameters!$F$6=Parameters!$E$17)*Parameters!$I$6*ISNUMBER(Q7)+(Parameters!$F$7=Parameters!$E$17)*Parameters!$I$7*ISNUMBER(R7)+(Parameters!$F$8=Parameters!$E$17)*Parameters!$I$8*ISNUMBER(S7)+(Parameters!$F$9=Parameters!$E$17)*Parameters!$I$9*ISNUMBER(T7)+(Parameters!$F$10=Parameters!$E$17)*Parameters!$I$10*ISNUMBER(U7)+(Parameters!$F$11=Parameters!$E$17)*Parameters!$I$11*ISNUMBER(V7)+(Parameters!$F$12=Parameters!$E$17)*Parameters!$I$12*ISNUMBER(W7)),"")) | AC7: =Parameters!$I$5*ISNUMBER(P7)+Parameters!$I$6*ISNUMBER(Q7)+Parameters!$I$7*ISNUMBER(R7)+Parameters!$I$8*ISNUMBER(S7)+Parameters!$I$9*ISNUMBER(T7)+Parameters!$I$10*ISNUMBER(U7)+Parameters!$I$11*ISNUMBER(V7)+Parameters!$I$12*ISNUMBER(W7) -> 65 | AD7: =Parameters!$I$5*1+Parameters!$I$6*1+Parameters!$I$7*1+Parameters!$I$8*1+Parameters!$I$9*1+Parameters!$I$10*1+Parameters!$I$11*X7+Parameters!$I$12*Y7 -> 75 | AE7: =IF(AD7=0,"",AC7/AD7) -> 0.86666667 | AF7: =IF(ISNUMBER(Z7),"M","")&IF(ISNUMBER(AA7),"I","")&IF(ISNUMBER(AB7),"O","") -> MI | AG7: =IF(AND(ISNUMBER(AE7),ISNUMBER(Z7)+ISNUMBER(AA7)+ISNUMBER(AB7)>=Parameters!$B$37),IF(AE7>=Parameters!$B$35,100*(Parameters!$F$15*N(Z7)+Parameters!$F$16*N(AA7)+Parameters!$F$17*N(AB7))/(Parameters!$F$15*ISNUMBER(Z7)+Parameters!$F$16*ISNUMBER(AA7)+Parameters!$F$17*ISNUMBER(AB7)),""),"") -> 51.388889 | AH7: =IF(ISNUMBER(AG7),RANK(AG7,$AG$2:$AG$113),"") -> 107
A8: Archivematica | B8: Artefactual | C8: Digital preservation system | D8: Actual system proven in operational environment | E8: Actively Maintained | F8: 2009-01-01 | G8: No Affiliations | H8: 0 | I8: FALSE | J8: Through solution provider or third party vendor | K8: https://www.artefactual.com/pricing | L8: Commercial (for-profit) | M8: Program service revenue | N8: More than 20 | P8: =IFERROR(IF(ISNUMBER(INDEX(Parameters!$B$5:$B$23,MATCH(D8,Parameters!$A$5:$A$23,0))),INDEX(Parameters!$B$5:$B$23,MATCH(D8,Parameters!$A$5:$A$23,0)),""),"") -> 1 | Q8: =IFERROR(IF(ISNUMBER(INDEX(Parameters!$B$5:$B$23,MATCH(E8,Parameters!$A$5:$A$23,0))),INDEX(Parameters!$B$5:$B$23,MATCH(E8,Parameters!$A$5:$A$23,0)),""),"") -> 1 | R8: =IF(F8="","",IFERROR(MIN(Parameters!$B$33,MAX(0,Parameters!$B$32-VALUE(LEFT(F8,4))))/Parameters!$B$33,"")) -> 1 | S8: =IF(ISNUMBER(H8),H8,IF(G8="",IF(ISNUMBER(Parameters!$B$34),Parameters!$B$34,""),"")) -> 0 | T8: =IFERROR(IF(ISNUMBER(INDEX(Parameters!$B$5:$B$23,MATCH(I8,Parameters!$A$5:$A$23,0))),INDEX(Parameters!$B$5:$B$23,MATCH(I8,Parameters!$A$5:$A$23,0)),""),"") -> 0 | U8: =IFERROR(IF(ISNUMBER(INDEX(Parameters!$B$5:$B$23,MATCH(L8,Parameters!$A$5:$A$23,0))),INDEX(Parameters!$B$5:$B$23,MATCH(L8,Parameters!$A$5:$A$23,0)),""),"") -> 0.5 | V8: =IFERROR(IF(ISNUMBER(INDEX(Parameters!$B$5:$B$23,MATCH(J8,Parameters!$A$5:$A$23,0))),INDEX(Parameters!$B$5:$B$23,MATCH(J8,Parameters!$A$5:$A$23,0)),""),"") -> 1 | W8: =IF(K8<>"",1,IF(COUNTIF(Parameters!$A$27:$A$28,J8)>0,0,"")) -> 1 | X8: =IF(J8="Not applicable",0,1) -> 1 | Y8: =IF(OR(K8<>"",COUNTIF(Parameters!$A$27:$A$28,J8)>0),1,0) -> 1 | Z8: =IF(((Parameters!$F$5=Parameters!$E$15)*Parameters!$I$5*1+(Parameters!$F$6=Parameters!$E$15)*Parameters!$I$6*1+(Parameters!$F$7=Parameters!$E$15)*Parameters!$I$7*1+(Parameters!$F$8=Parameters!$E$15)*Parameters!$I$8*1+(Parameters!$F$9=Parameters!$E$15)*Parameters!$I$9*1+(Parameters!$F$10=Parameters!$E$15)*Parameters!$I$10*1+(Parameters!$F$11=Parameters!$E$15)*Parameters!$I$11*X8+(Parameters!$F$12=Parameters!$E$15)*Parameters!$I$12*Y8)=0,"",IF(AND(((Parameters!$F$5=Parameters!$E$15)*Parameters!$I$5*ISNUMBER(P8)+(Parameters!$F$6=Parameters!$E$15)*Parameters!$I$6*ISNUMBER(Q8)+(Parameters!$F$7=Parameters!$E$15)*Parameters!$I$7*ISNUMBER(R8)+(Parameters!$F$8=Parameters!$E$15)*Parameters!$I$8*ISNUMBER(S8)+(Parameters!$F$9=Parameters!$E$15)*Parameters!$I$9*ISNUMBER(T8)+(Parameters!$F$10=Parameters!$E$15)*Parameters!$I$10*ISNUMBER(U8)+(Parameters!$F$11=Parameters!$E$15)*Parameters!$I$11*ISNUMBER(V8)+(Parameters!$F$12=Parameters!$E$15)*Parameters!$I$12*ISNUMBER(W8))>0,((Parameters!$F$5=Parameters!$E$15)*Parameters!$I$5*ISNUMBER(P8)+(Parameters!$F$6=Parameters!$E$15)*Parameters!$I$6*ISNUMBER(Q8)+(Parameters!$F$7=Parameters!$E$15)*Parameters!$I$7*ISNUMBER(R8)+(Parameters!$F$8=Parameters!$E$15)*Parameters!$I$8*ISNUMBER(S8)+(Parameters!$F$9=Parameters!$E$15)*Parameters!$I$9*ISNUMBER(T8)+(Parameters!$F$10=Parameters!$E$15)*Parameters!$I$10*ISNUMBER(U8)+(Parameters!$F$11=Parameters!$E$15)*Parameters!$I$11*ISNUMBER(V8)+(Parameters!$F$12=Parameters!$E$15)*Parameters!$I$12*ISNUMBER(W8))/((Parameters!$F$5=Parameters!$E$15)*Parameters!$I$5*1+(Parameters!$F$6=Parameters!$E$15)*Parameters!$I$6*1+(Parameters!$F$7=Parameters!$E$15)*Parameters!$I$7*1+(Parameters!$F$8=Parameters!$E$15)*Parameters!$I$8*1+(Parameters!$F$9=Parameters!$E$15)*Parameters!$I$9*1+(Parameters!$F$10=Parameters!$E$15)*Parameters!$I$10*1+(Parameters!$F$11=Parameters!$E$15)*Parameters!$I$11*X8+(Parameters!$F$12=Parameters!$E$15)*Parameters!$I$12*Y8)>=Parameters!$B$36),((Parameters!$F$5=Parameters!$E$15)*Parameters!$I$5*N(P8)+(Parameters!$F$6=Parameters!$E$15)*Parameters!$I$6*N(Q8)+(Parameters!$F$7=Parameters!$E$15)*Parameters!$I$7*N(R8)+(Parameters!$F$8=Parameters!$E$15)*Parameters!$I$8*N(S8)+(Parameters!$F$9=Parameters!$E$15)*Parameters!$I$9*N(T8)+(Parameters!$F$10=Parameters!$E$15)*Parameters!$I$10*N(U8)+(Parameters!$F$11=Parameters!$E$15)*Parameters!$I$11*N(V8)+(Parameters!$F$12=Parameters!$E$15)*Parameters!$I$12*N(W8))/((Parameters!$F$5=Parameters!$E$15)*Parameters!$I$5*ISNUMBER(P8)+(Parameters!$F$6=Parameters!$E$15)*Parameters!$I$6*ISNUMBER(Q8)+(Parameters!$F$7=Parameters!$E$15)*Parameters!$I$7*ISNUMBER(R8)+(Parameters!$F$8=Parameters!$E$15)*Parameters!$I$8*ISNUMBER(S8)+(Parameters!$F$9=Parameters!$E$15)*Parameters!$I$9*ISNUMBER(T8)+(Parameters!$F$10=Parameters!$E$15)*Parameters!$I$10*ISNUMBER(U8)+(Parameters!$F$11=Parameters!$E$15)*Parameters!$I$11*ISNUMBER(V8)+(Parameters!$F$12=Parameters!$E$15)*Parameters!$I$12*ISNUMBER(W8)),"")) -> 1 | AA8: =IF(((Parameters!$F$5=Parameters!$E$16)*Parameters!$I$5*1+(Parameters!$F$6=Parameters!$E$16)*Parameters!$I$6*1+(Parameters!$F$7=Parameters!$E$16)*Parameters!$I$7*1+(Parameters!$F$8=Parameters!$E$16)*Parameters!$I$8*1+(Parameters!$F$9=Parameters!$E$16)*Parameters!$I$9*1+(Parameters!$F$10=Parameters!$E$16)*Parameters!$I$10*1+(Parameters!$F$11=Parameters!$E$16)*Parameters!$I$11*X8+(Parameters!$F$12=Parameters!$E$16)*Parameters!$I$12*Y8)=0,"",IF(AND(((Parameters!$F$5=Parameters!$E$16)*Parameters!$I$5*ISNUMBER(P8)+(Parameters!$F$6=Parameters!$E$16)*Parameters!$I$6*ISNUMBER(Q8)+(Parameters!$F$7=Parameters!$E$16)*Parameters!$I$7*ISNUMBER(R8)+(Parameters!$F$8=Parameters!$E$16)*Parameters!$I$8*ISNUMBER(S8)+(Parameters!$F$9=Parameters!$E$16)*Parameters!$I$9*ISNUMBER(T8)+(Parameters!$F$10=Parameters!$E$16)*Parameters!$I$10*ISNUMBER(U8)+(Parameters!$F$11=Parameters!$E$16)*Parameters!$I$11*ISNUMBER(V8)+(Parameters!$F$12=Parameters!$E$16)*Parameters!$I$12*ISNUMBER(W8))>0,((Parameters!$F$5=Parameters!$E$16)*Parameters!$I$5*ISNUMBER(P8)+(Parameters!$F$6=Parameters!$E$16)*Parameters!$I$6*ISNUMBER(Q8)+(Parameters!$F$7=Parameters!$E$16)*Parameters!$I$7*ISNUMBER(R8)+(Parameters!$F$8=Parameters!$E$16)*Parameters!$I$8*ISNUMBER(S8)+(Parameters!$F$9=Parameters!$E$16)*Parameters!$I$9*ISNUMBER(T8)+(Parameters!$F$10=Parameters!$E$16)*Parameters!$I$10*ISNUMBER(U8)+(Parameters!$F$11=Parameters!$E$16)*Parameters!$I$11*ISNUMBER(V8)+(Parameters!$F$12=Parameters!$E$16)*Parameters!$I$12*ISNUMBER(W8))/((Parameters!$F$5=Parameters!$E$16)*Parameters!$I$5*1+(Parameters!$F$6=Parameters!$E$16)*Parameters!$I$6*1+(Parameters!$F$7=Parameters!$E$16)*Parameters!$I$7*1+(Parameters!$F$8=Parameters!$E$16)*Parameters!$I$8*1+(Parameters!$F$9=Parameters!$E$16)*Parameters!$I$9*1+(Parameters!$F$10=Parameters!$E$16)*Parameters!$I$10*1+(Parameters!$F$11=Parameters!$E$16)*Parameters!$I$11*X8+(Parameters!$F$12=Parameters!$E$16)*Parameters!$I$12*Y8)>=Parameters!$B$36),((Parameters!$F$5=Parameters!$E$16)*Parameters!$I$5*N(P8)+(Parameters!$F$6=Parameters!$E$16)*Parameters!$I$6*N(Q8)+(Parameters!$F$7=Parameters!$E$16)*Parameters!$I$7*N(R8)+(Parameters!$F$8=Parameters!$E$16)*Parameters!$I$8*N(S8)+(Parameters!$F$9=Parameters!$E$16)*Parameters!$I$9*N(T8)+(Parameters!$F$10=Parameters!$E$16)*Parameters!$I$10*N(U8)+(Parameters!$F$11=Parameters!$E$16)*Parameters!$I$11*N(V8)+(Parameters!$F$12=Parameters!$E$16)*Parameters!$I$12*N(W8))/((Parameters!$F$5=Parameters!$E$16)*Parameters!$I$5*ISNUMBER(P8)+(Parameters!$F$6=Parameters!$E$16)*Parameters!$I$6*ISNUMBER(Q8)+(Parameters!$F$7=Parameters!$E$16)*Parameters!$I$7*ISNUMBER(R8)+(Parameters!$F$8=Parameters!$E$16)*Parameters!$I$8*ISNUMBER(S8)+(Parameters!$F$9=Parameters!$E$16)*Parameters!$I$9*ISNUMBER(T8)+(Parameters!$F$10=Parameters!$E$16)*Parameters!$I$10*ISNUMBER(U8)+(Parameters!$F$11=Parameters!$E$16)*Parameters!$I$11*ISNUMBER(V8)+(Parameters!$F$12=Parameters!$E$16)*Parameters!$I$12*ISNUMBER(W8)),"")) -> 0.2 | AB8: =IF(((Parameters!$F$5=Parameters!$E$17)*Parameters!$I$5*1+(Parameters!$F$6=Parameters!$E$17)*Parameters!$I$6*1+(Parameters!$F$7=Parameters!$E$17)*Parameters!$I$7*1+(Parameters!$F$8=Parameters!$E$17)*Parameters!$I$8*1+(Parameters!$F$9=Parameters!$E$17)*Parameters!$I$9*1+(Parameters!$F$10=Parameters!$E$17)*Parameters!$I$10*1+(Parameters!$F$11=Parameters!$E$17)*Parameters!$I$11*X8+(Parameters!$F$12=Parameters!$E$17)*Parameters!$I$12*Y8)=0,"",IF(AND(((Parameters!$F$5=Parameters!$E$17)*Parameters!$I$5*ISNUMBER(P8)+(Parameters!$F$6=Parameters!$E$17)*Parameters!$I$6*ISNUMBER(Q8)+(Parameters!$F$7=Parameters!$E$17)*Parameters!$I$7*ISNUMBER(R8)+(Parameters!$F$8=Parameters!$E$17)*Parameters!$I$8*ISNUMBER(S8)+(Parameters!$F$9=Parameters!$E$17)*Parameters!$I$9*ISNUMBER(T8)+(Parameters!$F$10=Parameters!$E$17)*Parameters!$I$10*ISNUMBER(U8)+(Parameters!$F$11=Parameters!$E$17)*Parameters!$I$11*ISNUMBER(V8)+(Parameters!$F$12=Parameters!$E$17)*Parameters!$I$12*ISNUMBER(W8))>0,((Parameters!$F$5=Parameters!$E$17)*Parameters!$I$5*ISNUMBER(P8)+(Parameters!$F$6=Parameters!$E$17)*Parameters!$I$6*ISNUMBER(Q8)+(Parameters!$F$7=Parameters!$E$17)*Parameters!$I$7*ISNUMBER(R8)+(Parameters!$F$8=Parameters!$E$17)*Parameters!$I$8*ISNUMBER(S8)+(Parameters!$F$9=Parameters!$E$17)*Parameters!$I$9*ISNUMBER(T8)+(Parameters!$F$10=Parameters!$E$17)*Parameters!$I$10*ISNUMBER(U8)+(Parameters!$F$11=Parameters!$E$17)*Parameters!$I$11*ISNUMBER(V8)+(Parameters!$F$12=Parameters!$E$17)*Parameters!$I$12*ISNUMBER(W8))/((Parameters!$F$5=Parameters!$E$17)*Parameters!$I$5*1+(Parameters!$F$6=Parameters!$E$17)*Parameters!$I$6*1+(Parameters!$F$7=Parameters!$E$17)*Parameters!$I$7*1+(Parameters!$F$8=Parameters!$E$17)*Parameters!$I$8*1+(Parameters!$F$9=Parameters!$E$17)*Parameters!$I$9*1+(Parameters!$F$10=Parameters!$E$17)*Parameters!$I$10*1+(Parameters!$F$11=Parameters!$E$17)*Parameters!$I$11*X8+(Parameters!$F$12=Parameters!$E$17)*Parameters!$I$12*Y8)>=Parameters!$B$36),((Parameters!$F$5=Parameters!$E$17)*Parameters!$I$5*N(P8)+(Parameters!$F$6=Parameters!$E$17)*Parameters!$I$6*N(Q8)+(Parameters!$F$7=Parameters!$E$17)*Parameters!$I$7*N(R8)+(Parameters!$F$8=Parameters!$E$17)*Parameters!$I$8*N(S8)+(Parameters!$F$9=Parameters!$E$17)*Parameters!$I$9*N(T8)+(Parameters!$F$10=Parameters!$E$17)*Parameters!$I$10*N(U8)+(Parameters!$F$11=Parameters!$E$17)*Parameters!$I$11*N(V8)+(Parameters!$F$12=Parameters!$E$17)*Parameters!$I$12*N(W8))/((Parameters!$F$5=Parameters!$E$17)*Parameters!$I$5*ISNUMBER(P8)+(Parameters!$F$6=Parameters!$E$17)*Parameters!$I$6*ISNUMBER(Q8)+(Parameters!$F$7=Parameters!$E$17)*Parameters!$I$7*ISNUMBER(R8)+(Parameters!$F$8=Parameters!$E$17)*Parameters!$I$8*ISNUMBER(S8)+(Parameters!$F$9=Parameters!$E$17)*Parameters!$I$9*ISNUMBER(T8)+(Parameters!$F$10=Parameters!$E$17)*Parameters!$I$10*ISNUMBER(U8)+(Parameters!$F$11=Parameters!$E$17)*Parameters!$I$11*ISNUMBER(V8)+(Parameters!$F$12=Parameters!$E$17)*Parameters!$I$12*ISNUMBER(W8)),"")) -> 1 | AC8: =Parameters!$I$5*ISNUMBER(P8)+Parameters!$I$6*ISNUMBER(Q8)+Parameters!$I$7*ISNUMBER(R8)+Parameters!$I$8*ISNUMBER(S8)+Parameters!$I$9*ISNUMBER(T8)+Parameters!$I$10*ISNUMBER(U8)+Parameters!$I$11*ISNUMBER(V8)+Parameters!$I$12*ISNUMBER(W8) -> 95 | AD8: =Parameters!$I$5*1+Parameters!$I$6*1+Parameters!$I$7*1+Parameters!$I$8*1+Parameters!$I$9*1+Parameters!$I$10*1+Parameters!$I$11*X8+Parameters!$I$12*Y8 -> 95 | AE8: =IF(AD8=0,"",AC8/AD8) -> 1 | AF8: =IF(ISNUMBER(Z8),"M","")&IF(ISNUMBER(AA8),"I","")&IF(ISNUMBER(AB8),"O","") -> MIO | AG8: =IF(AND(ISNUMBER(AE8),ISNUMBER(Z8)+ISNUMBER(AA8)+ISNUMBER(AB8)>=Parameters!$B$37),IF(AE8>=Parameters!$B$35,100*(Parameters!$F$15*N(Z8)+Parameters!$F$16*N(AA8)+Parameters!$F$17*N(AB8))/(Parameters!$F$15*ISNUMBER(Z8)+Parameters!$F$16*ISNUMBER(AA8)+Parameters!$F$17*ISNUMBER(AB8)),""),"") -> 76 | AH8: =IF(ISNUMBER(AG8),RANK(AG8,$AG$2:$AG$113),"") -> 88
A9: ArchivesSpace | B9: ArchivesSpace | C9: Archive information management system | Discovery system | D9: Actual system proven in operational environment | E9: Actively Maintained | F9: 2013-01-01 | G9: New York University and the University of California San Diego are the founding partners and have permanent seats on the Board; Lyrasis is the organizational home | H9: 1 | I9: FALSE | J9: Through third party vendor only | K9: <a href="https://archivesspace.org/service-providers" target="_blank">Service provider list</a> | L9: Other | M9: Other | N9: 6-10 | P9: =IFERROR(IF(ISNUMBER(INDEX(Parameters!$B$5:$B$23,MATCH(D9,Parameters!$A$5:$A$23,0))),INDEX(Parameters!$B$5:$B$23,MATCH(D9,Parameters!$A$5:$A$23,0)),""),"") -> 1 | Q9: =IFERROR(IF(ISNUMBER(INDEX(Parameters!$B$5:$B$23,MATCH(E9,Parameters!$A$5:$A$23,0))),INDEX(Parameters!$B$5:$B$23,MATCH(E9,Parameters!$A$5:$A$23,0)),""),"") -> 1 | R9: =IF(F9="","",IFERROR(MIN(Parameters!$B$33,MAX(0,Parameters!$B$32-VALUE(LEFT(F9,4))))/Parameters!$B$33,"")) -> 0.86666667 | S9: =IF(ISNUMBER(H9),H9,IF(G9="",IF(ISNUMBER(Parameters!$B$34),Parameters!$B$34,""),"")) -> 1 | T9: =IFERROR(IF(ISNUMBER(INDEX(Parameters!$B$5:$B$23,MATCH(I9,Parameters!$A$5:$A$23,0))),INDEX(Parameters!$B$5:$B$23,MATCH(I9,Parameters!$A$5:$A$23,0)),""),"") -> 0 | U9: =IFERROR(IF(ISNUMBER(INDEX(Parameters!$B$5:$B$23,MATCH(L9,Parameters!$A$5:$A$23,0))),INDEX(Parameters!$B$5:$B$23,MATCH(L9,Parameters!$A$5:$A$23,0)),""),"") | V9: =IFERROR(IF(ISNUMBER(INDEX(Parameters!$B$5:$B$23,MATCH(J9,Parameters!$A$5:$A$23,0))),INDEX(Parameters!$B$5:$B$23,MATCH(J9,Parameters!$A$5:$A$23,0)),""),"") -> 1 | W9: =IF(K9<>"",1,IF(COUNTIF(Parameters!$A$27:$A$28,J9)>0,0,"")) -> 1 | X9: =IF(J9="Not applicable",0,1) -> 1 | Y9: =IF(OR(K9<>"",COUNTIF(Parameters!$A$27:$A$28,J9)>0),1,0) -> 1 | Z9: =IF(((Parameters!$F$5=Parameters!$E$15)*Parameters!$I$5*1+(Parameters!$F$6=Parameters!$E$15)*Parameters!$I$6*1+(Parameters!$F$7=Parameters!$E$15)*Parameters!$I$7*1+(Parameters!$F$8=Parameters!$E$15)*Parameters!$I$8*1+(Parameters!$F$9=Parameters!$E$15)*Parameters!$I$9*1+(Parameters!$F$10=Parameters!$E$15)*Parameters!$I$10*1+(Parameters!$F$11=Parameters!$E$15)*Parameters!$I$11*X9+(Parameters!$F$12=Parameters!$E$15)*Parameters!$I$12*Y9)=0,"",IF(AND(((Parameters!$F$5=Parameters!$E$15)*Parameters!$I$5*ISNUMBER(P9)+(Parameters!$F$6=Parameters!$E$15)*Parameters!$I$6*ISNUMBER(Q9)+(Parameters!$F$7=Parameters!$E$15)*Parameters!$I$7*ISNUMBER(R9)+(Parameters!$F$8=Parameters!$E$15)*Parameters!$I$8*ISNUMBER(S9)+(Parameters!$F$9=Parameters!$E$15)*Parameters!$I$9*ISNUMBER(T9)+(Parameters!$F$10=Parameters!$E$15)*Parameters!$I$10*ISNUMBER(U9)+(Parameters!$F$11=Parameters!$E$15)*Parameters!$I$11*ISNUMBER(V9)+(Parameters!$F$12=Parameters!$E$15)*Parameters!$I$12*ISNUMBER(W9))>0,((Parameters!$F$5=Parameters!$E$15)*Parameters!$I$5*ISNUMBER(P9)+(Parameters!$F$6=Parameters!$E$15)*Parameters!$I$6*ISNUMBER(Q9)+(Parameters!$F$7=Parameters!$E$15)*Parameters!$I$7*ISNUMBER(R9)+(Parameters!$F$8=Parameters!$E$15)*Parameters!$I$8*ISNUMBER(S9)+(Parameters!$F$9=Parameters!$E$15)*Parameters!$I$9*ISNUMBER(T9)+(Parameters!$F$10=Parameters!$E$15)*Parameters!$I$10*ISNUMBER(U9)+(Parameters!$F$11=Parameters!$E$15)*Parameters!$I$11*ISNUMBER(V9)+(Parameters!$F$12=Parameters!$E$15)*Parameters!$I$12*ISNUMBER(W9))/((Parameters!$F$5=Parameters!$E$15)*Parameters!$I$5*1+(Parameters!$F$6=Parameters!$E$15)*Parameters!$I$6*1+(Parameters!$F$7=Parameters!$E$15)*Parameters!$I$7*1+(Parameters!$F$8=Parameters!$E$15)*Parameters!$I$8*1+(Parameters!$F$9=Parameters!$E$15)*Parameters!$I$9*1+(Parameters!$F$10=Parameters!$E$15)*Parameters!$I$10*1+(Parameters!$F$11=Parameters!$E$15)*Parameters!$I$11*X9+(Parameters!$F$12=Parameters!$E$15)*Parameters!$I$12*Y9)>=Parameters!$B$36),((Parameters!$F$5=Parameters!$E$15)*Parameters!$I$5*N(P9)+(Parameters!$F$6=Parameters!$E$15)*Parameters!$I$6*N(Q9)+(Parameters!$F$7=Parameters!$E$15)*Parameters!$I$7*N(R9)+(Parameters!$F$8=Parameters!$E$15)*Parameters!$I$8*N(S9)+(Parameters!$F$9=Parameters!$E$15)*Parameters!$I$9*N(T9)+(Parameters!$F$10=Parameters!$E$15)*Parameters!$I$10*N(U9)+(Parameters!$F$11=Parameters!$E$15)*Parameters!$I$11*N(V9)+(Parameters!$F$12=Parameters!$E$15)*Parameters!$I$12*N(W9))/((Parameters!$F$5=Parameters!$E$15)*Parameters!$I$5*ISNUMBER(P9)+(Parameters!$F$6=Parameters!$E$15)*Parameters!$I$6*ISNUMBER(Q9)+(Parameters!$F$7=Parameters!$E$15)*Parameters!$I$7*ISNUMBER(R9)+(Parameters!$F$8=Parameters!$E$15)*Parameters!$I$8*ISNUMBER(S9)+(Parameters!$F$9=Parameters!$E$15)*Parameters!$I$9*ISNUMBER(T9)+(Parameters!$F$10=Parameters!$E$15)*Parameters!$I$10*ISNUMBER(U9)+(Parameters!$F$11=Parameters!$E$15)*Parameters!$I$11*ISNUMBER(V9)+(Parameters!$F$12=Parameters!$E$15)*Parameters!$I$12*ISNUMBER(W9)),"")) -> 0.98666667 | AA9: =IF(((Parameters!$F$5=Parameters!$E$16)*Parameters!$I$5*1+(Parameters!$F$6=Parameters!$E$16)*Parameters!$I$6*1+(Parameters!$F$7=Parameters!$E$16)*Parameters!$I$7*1+(Parameters!$F$8=Parameters!$E$16)*Parameters!$I$8*1+(Parameters!$F$9=Parameters!$E$16)*Parameters!$I$9*1+(Parameters!$F$10=Parameters!$E$16)*Parameters!$I$10*1+(Parameters!$F$11=Parameters!$E$16)*Parameters!$I$11*X9+(Parameters!$F$12=Parameters!$E$16)*Parameters!$I$12*Y9)=0,"",IF(AND(((Parameters!$F$5=Parameters!$E$16)*Parameters!$I$5*ISNUMBER(P9)+(Parameters!$F$6=Parameters!$E$16)*Parameters!$I$6*ISNUMBER(Q9)+(Parameters!$F$7=Parameters!$E$16)*Parameters!$I$7*ISNUMBER(R9)+(Parameters!$F$8=Parameters!$E$16)*Parameters!$I$8*ISNUMBER(S9)+(Parameters!$F$9=Parameters!$E$16)*Parameters!$I$9*ISNUMBER(T9)+(Parameters!$F$10=Parameters!$E$16)*Parameters!$I$10*ISNUMBER(U9)+(Parameters!$F$11=Parameters!$E$16)*Parameters!$I$11*ISNUMBER(V9)+(Parameters!$F$12=Parameters!$E$16)*Parameters!$I$12*ISNUMBER(W9))>0,((Parameters!$F$5=Parameters!$E$16)*Parameters!$I$5*ISNUMBER(P9)+(Parameters!$F$6=Parameters!$E$16)*Parameters!$I$6*ISNUMBER(Q9)+(Parameters!$F$7=Parameters!$E$16)*Parameters!$I$7*ISNUMBER(R9)+(Parameters!$F$8=Parameters!$E$16)*Parameters!$I$8*ISNUMBER(S9)+(Parameters!$F$9=Parameters!$E$16)*Parameters!$I$9*ISNUMBER(T9)+(Parameters!$F$10=Parameters!$E$16)*Parameters!$I$10*ISNUMBER(U9)+(Parameters!$F$11=Parameters!$E$16)*Parameters!$I$11*ISNUMBER(V9)+(Parameters!$F$12=Parameters!$E$16)*Parameters!$I$12*ISNUMBER(W9))/((Parameters!$F$5=Parameters!$E$16)*Parameters!$I$5*1+(Parameters!$F$6=Parameters!$E$16)*Parameters!$I$6*1+(Parameters!$F$7=Parameters!$E$16)*Parameters!$I$7*1+(Parameters!$F$8=Parameters!$E$16)*Parameters!$I$8*1+(Parameters!$F$9=Parameters!$E$16)*Parameters!$I$9*1+(Parameters!$F$10=Parameters!$E$16)*Parameters!$I$10*1+(Parameters!$F$11=Parameters!$E$16)*Parameters!$I$11*X9+(Parameters!$F$12=Parameters!$E$16)*Parameters!$I$12*Y9)>=Parameters!$B$36),((Parameters!$F$5=Parameters!$E$16)*Parameters!$I$5*N(P9)+(Parameters!$F$6=Parameters!$E$16)*Parameters!$I$6*N(Q9)+(Parameters!$F$7=Parameters!$E$16)*Parameters!$I$7*N(R9)+(Parameters!$F$8=Parameters!$E$16)*Parameters!$I$8*N(S9)+(Parameters!$F$9=Parameters!$E$16)*Parameters!$I$9*N(T9)+(Parameters!$F$10=Parameters!$E$16)*Parameters!$I$10*N(U9)+(Parameters!$F$11=Parameters!$E$16)*Parameters!$I$11*N(V9)+(Parameters!$F$12=Parameters!$E$16)*Parameters!$I$12*N(W9))/((Parameters!$F$5=Parameters!$E$16)*Parameters!$I$5*ISNUMBER(P9)+(Parameters!$F$6=Parameters!$E$16)*Parameters!$I$6*ISNUMBER(Q9)+(Parameters!$F$7=Parameters!$E$16)*Parameters!$I$7*ISNUMBER(R9)+(Parameters!$F$8=Parameters!$E$16)*Parameters!$I$8*ISNUMBER(S9)+(Parameters!$F$9=Parameters!$E$16)*Parameters!$I$9*ISNUMBER(T9)+(Parameters!$F$10=Parameters!$E$16)*Parameters!$I$10*ISNUMBER(U9)+(Parameters!$F$11=Parameters!$E$16)*Parameters!$I$11*ISNUMBER(V9)+(Parameters!$F$12=Parameters!$E$16)*Parameters!$I$12*ISNUMBER(W9)),"")) -> 0.66666667 | AB9: =IF(((Parameters!$F$5=Parameters!$E$17)*Parameters!$I$5*1+(Parameters!$F$6=Parameters!$E$17)*Parameters!$I$6*1+(Parameters!$F$7=Parameters!$E$17)*Parameters!$I$7*1+(Parameters!$F$8=Parameters!$E$17)*Parameters!$I$8*1+(Parameters!$F$9=Parameters!$E$17)*Parameters!$I$9*1+(Parameters!$F$10=Parameters!$E$17)*Parameters!$I$10*1+(Parameters!$F$11=Parameters!$E$17)*Parameters!$I$11*X9+(Parameters!$F$12=Parameters!$E$17)*Parameters!$I$12*Y9)=0,"",IF(AND(((Parameters!$F$5=Parameters!$E$17)*Parameters!$I$5*ISNUMBER(P9)+(Parameters!$F$6=Parameters!$E$17)*Parameters!$I$6*ISNUMBER(Q9)+(Parameters!$F$7=Parameters!$E$17)*Parameters!$I$7*ISNUMBER(R9)+(Parameters!$F$8=Parameters!$E$17)*Parameters!$I$8*ISNUMBER(S9)+(Parameters!$F$9=Parameters!$E$17)*Parameters!$I$9*ISNUMBER(T9)+(Parameters!$F$10=Parameters!$E$17)*Parameters!$I$10*ISNUMBER(U9)+(Parameters!$F$11=Parameters!$E$17)*Parameters!$I$11*ISNUMBER(V9)+(Parameters!$F$12=Parameters!$E$17)*Parameters!$I$12*ISNUMBER(W9))>0,((Parameters!$F$5=Parameters!$E$17)*Parameters!$I$5*ISNUMBER(P9)+(Parameters!$F$6=Parameters!$E$17)*Parameters!$I$6*ISNUMBER(Q9)+(Parameters!$F$7=Parameters!$E$17)*Parameters!$I$7*ISNUMBER(R9)+(Parameters!$F$8=Parameters!$E$17)*Parameters!$I$8*ISNUMBER(S9)+(Parameters!$F$9=Parameters!$E$17)*Parameters!$I$9*ISNUMBER(T9)+(Parameters!$F$10=Parameters!$E$17)*Parameters!$I$10*ISNUMBER(U9)+(Parameters!$F$11=Parameters!$E$17)*Parameters!$I$11*ISNUMBER(V9)+(Parameters!$F$12=Parameters!$E$17)*Parameters!$I$12*ISNUMBER(W9))/((Parameters!$F$5=Parameters!$E$17)*Parameters!$I$5*1+(Parameters!$F$6=Parameters!$E$17)*Parameters!$I$6*1+(Parameters!$F$7=Parameters!$E$17)*Parameters!$I$7*1+(Parameters!$F$8=Parameters!$E$17)*Parameters!$I$8*1+(Parameters!$F$9=Parameters!$E$17)*Parameters!$I$9*1+(Parameters!$F$10=Parameters!$E$17)*Parameters!$I$10*1+(Parameters!$F$11=Parameters!$E$17)*Parameters!$I$11*X9+(Parameters!$F$12=Parameters!$E$17)*Parameters!$I$12*Y9)>=Parameters!$B$36),((Parameters!$F$5=Parameters!$E$17)*Parameters!$I$5*N(P9)+(Parameters!$F$6=Parameters!$E$17)*Parameters!$I$6*N(Q9)+(Parameters!$F$7=Parameters!$E$17)*Parameters!$I$7*N(R9)+(Parameters!$F$8=Parameters!$E$17)*Parameters!$I$8*N(S9)+(Parameters!$F$9=Parameters!$E$17)*Parameters!$I$9*N(T9)+(Parameters!$F$10=Parameters!$E$17)*Parameters!$I$10*N(U9)+(Parameters!$F$11=Parameters!$E$17)*Parameters!$I$11*N(V9)+(Parameters!$F$12=Parameters!$E$17)*Parameters!$I$12*N(W9))/((Parameters!$F$5=Parameters!$E$17)*Parameters!$I$5*ISNUMBER(P9)+(Parameters!$F$6=Parameters!$E$17)*Parameters!$I$6*ISNUMBER(Q9)+(Parameters!$F$7=Parameters!$E$17)*Parameters!$I$7*ISNUMBER(R9)+(Parameters!$F$8=Parameters!$E$17)*Parameters!$I$8*ISNUMBER(S9)+(Parameters!$F$9=Parameters!$E$17)*Parameters!$I$9*ISNUMBER(T9)+(Parameters!$F$10=Parameters!$E$17)*Parameters!$I$10*ISNUMBER(U9)+(Parameters!$F$11=Parameters!$E$17)*Parameters!$I$11*ISNUMBER(V9)+(Parameters!$F$12=Parameters!$E$17)*Parameters!$I$12*ISNUMBER(W9)),"")) -> 1 | AC9: =Parameters!$I$5*ISNUMBER(P9)+Parameters!$I$6*ISNUMBER(Q9)+Parameters!$I$7*ISNUMBER(R9)+Parameters!$I$8*ISNUMBER(S9)+Parameters!$I$9*ISNUMBER(T9)+Parameters!$I$10*ISNUMBER(U9)+Parameters!$I$11*ISNUMBER(V9)+Parameters!$I$12*ISNUMBER(W9) -> 85 | AD9: =Parameters!$I$5*1+Parameters!$I$6*1+Parameters!$I$7*1+Parameters!$I$8*1+Parameters!$I$9*1+Parameters!$I$10*1+Parameters!$I$11*X9+Parameters!$I$12*Y9 -> 95 | AE9: =IF(AD9=0,"",AC9/AD9) -> 0.89473684 | AF9: =IF(ISNUMBER(Z9),"M","")&IF(ISNUMBER(AA9),"I","")&IF(ISNUMBER(AB9),"O","") -> MIO | AG9: =IF(AND(ISNUMBER(AE9),ISNUMBER(Z9)+ISNUMBER(AA9)+ISNUMBER(AB9)>=Parameters!$B$37),IF(AE9>=Parameters!$B$35,100*(Parameters!$F$15*N(Z9)+Parameters!$F$16*N(AA9)+Parameters!$F$17*N(AB9))/(Parameters!$F$15*ISNUMBER(Z9)+Parameters!$F$16*ISNUMBER(AA9)+Parameters!$F$17*ISNUMBER(AB9)),""),"") -> 89.333333 | AH9: =IF(ISNUMBER(AG9),RANK(AG9,$AG$2:$AG$113),"") -> 35
A10: ARGOS | B10: OpenAIRE | C10: Data management planning tool or service | D10: Actual system proven in operational environment | E10: Actively Maintained | F10: 2018-01-01 | G10: Athena Research Center (ARC) Communication & Information Technologies Experts (CITE) | H10: 1 | I10: FALSE | J10: Through solution provider only | L10: Non-profit organization | M10: Program service revenue | P10: =IFERROR(IF(ISNUMBER(INDEX(Parameters!$B$5:$B$23,MATCH(D10,Parameters!$A$5:$A$23,0))),INDEX(Parameters!$B$5:$B$23,MATCH(D10,Parameters!$A$5:$A$23,0)),""),"") -> 1 | Q10: =IFERROR(IF(ISNUMBER(INDEX(Parameters!$B$5:$B$23,MATCH(E10,Parameters!$A$5:$A$23,0))),INDEX(Parameters!$B$5:$B$23,MATCH(E10,Parameters!$A$5:$A$23,0)),""),"") -> 1 | R10: =IF(F10="","",IFERROR(MIN(Parameters!$B$33,MAX(0,Parameters!$B$32-VALUE(LEFT(F10,4))))/Parameters!$B$33,"")) -> 0.53333333 | S10: =IF(ISNUMBER(H10),H10,IF(G10="",IF(ISNUMBER(Parameters!$B$34),Parameters!$B$34,""),"")) -> 1 | T10: =IFERROR(IF(ISNUMBER(INDEX(Parameters!$B$5:$B$23,MATCH(I10,Parameters!$A$5:$A$23,0))),INDEX(Parameters!$B$5:$B$23,MATCH(I10,Parameters!$A$5:$A$23,0)),""),"") -> 0 | U10: =IFERROR(IF(ISNUMBER(INDEX(Parameters!$B$5:$B$23,MATCH(L10,Parameters!$A$5:$A$23,0))),INDEX(Parameters!$B$5:$B$23,MATCH(L10,Parameters!$A$5:$A$23,0)),""),"") -> 1 | V10: =IFERROR(IF(ISNUMBER(INDEX(Parameters!$B$5:$B$23,MATCH(J10,Parameters!$A$5:$A$23,0))),INDEX(Parameters!$B$5:$B$23,MATCH(J10,Parameters!$A$5:$A$23,0)),""),"") -> 1 | W10: =IF(K10<>"",1,IF(COUNTIF(Parameters!$A$27:$A$28,J10)>0,0,"")) | X10: =IF(J10="Not applicable",0,1) -> 1 | Y10: =IF(OR(K10<>"",COUNTIF(Parameters!$A$27:$A$28,J10)>0),1,0) -> 0 | Z10: =IF(((Parameters!$F$5=Parameters!$E$15)*Parameters!$I$5*1+(Parameters!$F$6=Parameters!$E$15)*Parameters!$I$6*1+(Parameters!$F$7=Parameters!$E$15)*Parameters!$I$7*1+(Parameters!$F$8=Parameters!$E$15)*Parameters!$I$8*1+(Parameters!$F$9=Parameters!$E$15)*Parameters!$I$9*1+(Parameters!$F$10=Parameters!$E$15)*Parameters!$I$10*1+(Parameters!$F$11=Parameters!$E$15)*Parameters!$I$11*X10+(Parameters!$F$12=Parameters!$E$15)*Parameters!$I$12*Y10)=0,"",IF(AND(((Parameters!$F$5=Parameters!$E$15)*Parameters!$I$5*ISNUMBER(P10)+(Parameters!$F$6=Parameters!$E$15)*Parameters!$I$6*ISNUMBER(Q10)+(Parameters!$F$7=Parameters!$E$15)*Parameters!$I$7*ISNUMBER(R10)+(Parameters!$F$8=Parameters!$E$15)*Parameters!$I$8*ISNUMBER(S10)+(Parameters!$F$9=Parameters!$E$15)*Parameters!$I$9*ISNUMBER(T10)+(Parameters!$F$10=Parameters!$E$15)*Parameters!$I$10*ISNUMBER(U10)+(Parameters!$F$11=Parameters!$E$15)*Parameters!$I$11*ISNUMBER(V10)+(Parameters!$F$12=Parameters!$E$15)*Parameters!$I$12*ISNUMBER(W10))>0,((Parameters!$F$5=Parameters!$E$15)*Parameters!$I$5*ISNUMBER(P10)+(Parameters!$F$6=Parameters!$E$15)*Parameters!$I$6*ISNUMBER(Q10)+(Parameters!$F$7=Parameters!$E$15)*Parameters!$I$7*ISNUMBER(R10)+(Parameters!$F$8=Parameters!$E$15)*Parameters!$I$8*ISNUMBER(S10)+(Parameters!$F$9=Parameters!$E$15)*Parameters!$I$9*ISNUMBER(T10)+(Parameters!$F$10=Parameters!$E$15)*Parameters!$I$10*ISNUMBER(U10)+(Parameters!$F$11=Parameters!$E$15)*Parameters!$I$11*ISNUMBER(V10)+(Parameters!$F$12=Parameters!$E$15)*Parameters!$I$12*ISNUMBER(W10))/((Parameters!$F$5=Parameters!$E$15)*Parameters!$I$5*1+(Parameters!$F$6=Parameters!$E$15)*Parameters!$I$6*1+(Parameters!$F$7=Parameters!$E$15)*Parameters!$I$7*1+(Parameters!$F$8=Parameters!$E$15)*Parameters!$I$8*1+(Parameters!$F$9=Parameters!$E$15)*Parameters!$I$9*1+(Parameters!$F$10=Parameters!$E$15)*Parameters!$I$10*1+(Parameters!$F$11=Parameters!$E$15)*Parameters!$I$11*X10+(Parameters!$F$12=Parameters!$E$15)*Parameters!$I$12*Y10)>=Parameters!$B$36),((Parameters!$F$5=Parameters!$E$15)*Parameters!$I$5*N(P10)+(Parameters!$F$6=Parameters!$E$15)*Parameters!$I$6*N(Q10)+(Parameters!$F$7=Parameters!$E$15)*Parameters!$I$7*N(R10)+(Parameters!$F$8=Parameters!$E$15)*Parameters!$I$8*N(S10)+(Parameters!$F$9=Parameters!$E$15)*Parameters!$I$9*N(T10)+(Parameters!$F$10=Parameters!$E$15)*Parameters!$I$10*N(U10)+(Parameters!$F$11=Parameters!$E$15)*Parameters!$I$11*N(V10)+(Parameters!$F$12=Parameters!$E$15)*Parameters!$I$12*N(W10))/((Parameters!$F$5=Parameters!$E$15)*Parameters!$I$5*ISNUMBER(P10)+(Parameters!$F$6=Parameters!$E$15)*Parameters!$I$6*ISNUMBER(Q10)+(Parameters!$F$7=Parameters!$E$15)*Parameters!$I$7*ISNUMBER(R10)+(Parameters!$F$8=Parameters!$E$15)*Parameters!$I$8*ISNUMBER(S10)+(Parameters!$F$9=Parameters!$E$15)*Parameters!$I$9*ISNUMBER(T10)+(Parameters!$F$10=Parameters!$E$15)*Parameters!$I$10*ISNUMBER(U10)+(Parameters!$F$11=Parameters!$E$15)*Parameters!$I$11*ISNUMBER(V10)+(Parameters!$F$12=Parameters!$E$15)*Parameters!$I$12*ISNUMBER(W10)),"")) -> 0.95333333 | AA10: =IF(((Parameters!$F$5=Parameters!$E$16)*Parameters!$I$5*1+(Parameters!$F$6=Parameters!$E$16)*Parameters!$I$6*1+(Parameters!$F$7=Parameters!$E$16)*Parameters!$I$7*1+(Parameters!$F$8=Parameters!$E$16)*Parameters!$I$8*1+(Parameters!$F$9=Parameters!$E$16)*Parameters!$I$9*1+(Parameters!$F$10=Parameters!$E$16)*Parameters!$I$10*1+(Parameters!$F$11=Parameters!$E$16)*Parameters!$I$11*X10+(Parameters!$F$12=Parameters!$E$16)*Parameters!$I$12*Y10)=0,"",IF(AND(((Parameters!$F$5=Parameters!$E$16)*Parameters!$I$5*ISNUMBER(P10)+(Parameters!$F$6=Parameters!$E$16)*Parameters!$I$6*ISNUMBER(Q10)+(Parameters!$F$7=Parameters!$E$16)*Parameters!$I$7*ISNUMBER(R10)+(Parameters!$F$8=Parameters!$E$16)*Parameters!$I$8*ISNUMBER(S10)+(Parameters!$F$9=Parameters!$E$16)*Parameters!$I$9*ISNUMBER(T10)+(Parameters!$F$10=Parameters!$E$16)*Parameters!$I$10*ISNUMBER(U10)+(Parameters!$F$11=Parameters!$E$16)*Parameters!$I$11*ISNUMBER(V10)+(Parameters!$F$12=Parameters!$E$16)*Parameters!$I$12*ISNUMBER(W10))>0,((Parameters!$F$5=Parameters!$E$16)*Parameters!$I$5*ISNUMBER(P10)+(Parameters!$F$6=Parameters!$E$16)*Parameters!$I$6*ISNUMBER(Q10)+(Parameters!$F$7=Parameters!$E$16)*Parameters!$I$7*ISNUMBER(R10)+(Parameters!$F$8=Parameters!$E$16)*Parameters!$I$8*ISNUMBER(S10)+(Parameters!$F$9=Parameters!$E$16)*Parameters!$I$9*ISNUMBER(T10)+(Parameters!$F$10=Parameters!$E$16)*Parameters!$I$10*ISNUMBER(U10)+(Parameters!$F$11=Parameters!$E$16)*Parameters!$I$11*ISNUMBER(V10)+(Parameters!$F$12=Parameters!$E$16)*Parameters!$I$12*ISNUMBER(W10))/((Parameters!$F$5=Parameters!$E$16)*Parameters!$I$5*1+(Parameters!$F$6=Parameters!$E$16)*Parameters!$I$6*1+(Parameters!$F$7=Parameters!$E$16)*Parameters!$I$7*1+(Parameters!$F$8=Parameters!$E$16)*Parameters!$I$8*1+(Parameters!$F$9=Parameters!$E$16)*Parameters!$I$9*1+(Parameters!$F$10=Parameters!$E$16)*Parameters!$I$10*1+(Parameters!$F$11=Parameters!$E$16)*Parameters!$I$11*X10+(Parameters!$F$12=Parameters!$E$16)*Parameters!$I$12*Y10)>=Parameters!$B$36),((Parameters!$F$5=Parameters!$E$16)*Parameters!$I$5*N(P10)+(Parameters!$F$6=Parameters!$E$16)*Parameters!$I$6*N(Q10)+(Parameters!$F$7=Parameters!$E$16)*Parameters!$I$7*N(R10)+(Parameters!$F$8=Parameters!$E$16)*Parameters!$I$8*N(S10)+(Parameters!$F$9=Parameters!$E$16)*Parameters!$I$9*N(T10)+(Parameters!$F$10=Parameters!$E$16)*Parameters!$I$10*N(U10)+(Parameters!$F$11=Parameters!$E$16)*Parameters!$I$11*N(V10)+(Parameters!$F$12=Parameters!$E$16)*Parameters!$I$12*N(W10))/((Parameters!$F$5=Parameters!$E$16)*Parameters!$I$5*ISNUMBER(P10)+(Parameters!$F$6=Parameters!$E$16)*Parameters!$I$6*ISNUMBER(Q10)+(Parameters!$F$7=Parameters!$E$16)*Parameters!$I$7*ISNUMBER(R10)+(Parameters!$F$8=Parameters!$E$16)*Parameters!$I$8*ISNUMBER(S10)+(Parameters!$F$9=Parameters!$E$16)*Parameters!$I$9*ISNUMBER(T10)+(Parameters!$F$10=Parameters!$E$16)*Parameters!$I$10*ISNUMBER(U10)+(Parameters!$F$11=Parameters!$E$16)*Parameters!$I$11*ISNUMBER(V10)+(Parameters!$F$12=Parameters!$E$16)*Parameters!$I$12*ISNUMBER(W10)),"")) -> 0.8 | AB10: =IF(((Parameters!$F$5=Parameters!$E$17)*Parameters!$I$5*1+(Parameters!$F$6=Parameters!$E$17)*Parameters!$I$6*1+(Parameters!$F$7=Parameters!$E$17)*Parameters!$I$7*1+(Parameters!$F$8=Parameters!$E$17)*Parameters!$I$8*1+(Parameters!$F$9=Parameters!$E$17)*Parameters!$I$9*1+(Parameters!$F$10=Parameters!$E$17)*Parameters!$I$10*1+(Parameters!$F$11=Parameters!$E$17)*Parameters!$I$11*X10+(Parameters!$F$12=Parameters!$E$17)*Parameters!$I$12*Y10)=0,"",IF(AND(((Parameters!$F$5=Parameters!$E$17)*Parameters!$I$5*ISNUMBER(P10)+(Parameters!$F$6=Parameters!$E$17)*Parameters!$I$6*ISNUMBER(Q10)+(Parameters!$F$7=Parameters!$E$17)*Parameters!$I$7*ISNUMBER(R10)+(Parameters!$F$8=Parameters!$E$17)*Parameters!$I$8*ISNUMBER(S10)+(Parameters!$F$9=Parameters!$E$17)*Parameters!$I$9*ISNUMBER(T10)+(Parameters!$F$10=Parameters!$E$17)*Parameters!$I$10*ISNUMBER(U10)+(Parameters!$F$11=Parameters!$E$17)*Parameters!$I$11*ISNUMBER(V10)+(Parameters!$F$12=Parameters!$E$17)*Parameters!$I$12*ISNUMBER(W10))>0,((Parameters!$F$5=Parameters!$E$17)*Parameters!$I$5*ISNUMBER(P10)+(Parameters!$F$6=Parameters!$E$17)*Parameters!$I$6*ISNUMBER(Q10)+(Parameters!$F$7=Parameters!$E$17)*Parameters!$I$7*ISNUMBER(R10)+(Parameters!$F$8=Parameters!$E$17)*Parameters!$I$8*ISNUMBER(S10)+(Parameters!$F$9=Parameters!$E$17)*Parameters!$I$9*ISNUMBER(T10)+(Parameters!$F$10=Parameters!$E$17)*Parameters!$I$10*ISNUMBER(U10)+(Parameters!$F$11=Parameters!$E$17)*Parameters!$I$11*ISNUMBER(V10)+(Parameters!$F$12=Parameters!$E$17)*Parameters!$I$12*ISNUMBER(W10))/((Parameters!$F$5=Parameters!$E$17)*Parameters!$I$5*1+(Parameters!$F$6=Parameters!$E$17)*Parameters!$I$6*1+(Parameters!$F$7=Parameters!$E$17)*Parameters!$I$7*1+(Parameters!$F$8=Parameters!$E$17)*Parameters!$I$8*1+(Parameters!$F$9=Parameters!$E$17)*Parameters!$I$9*1+(Parameters!$F$10=Parameters!$E$17)*Parameters!$I$10*1+(Parameters!$F$11=Parameters!$E$17)*Parameters!$I$11*X10+(Parameters!$F$12=Parameters!$E$17)*Parameters!$I$12*Y10)>=Parameters!$B$36),((Parameters!$F$5=Parameters!$E$17)*Parameters!$I$5*N(P10)+(Parameters!$F$6=Parameters!$E$17)*Parameters!$I$6*N(Q10)+(Parameters!$F$7=Parameters!$E$17)*Parameters!$I$7*N(R10)+(Parameters!$F$8=Parameters!$E$17)*Parameters!$I$8*N(S10)+(Parameters!$F$9=Parameters!$E$17)*Parameters!$I$9*N(T10)+(Parameters!$F$10=Parameters!$E$17)*Parameters!$I$10*N(U10)+(Parameters!$F$11=Parameters!$E$17)*Parameters!$I$11*N(V10)+(Parameters!$F$12=Parameters!$E$17)*Parameters!$I$12*N(W10))/((Parameters!$F$5=Parameters!$E$17)*Parameters!$I$5*ISNUMBER(P10)+(Parameters!$F$6=Parameters!$E$17)*Parameters!$I$6*ISNUMBER(Q10)+(Parameters!$F$7=Parameters!$E$17)*Parameters!$I$7*ISNUMBER(R10)+(Parameters!$F$8=Parameters!$E$17)*Parameters!$I$8*ISNUMBER(S10)+(Parameters!$F$9=Parameters!$E$17)*Parameters!$I$9*ISNUMBER(T10)+(Parameters!$F$10=Parameters!$E$17)*Parameters!$I$10*ISNUMBER(U10)+(Parameters!$F$11=Parameters!$E$17)*Parameters!$I$11*ISNUMBER(V10)+(Parameters!$F$12=Parameters!$E$17)*Parameters!$I$12*ISNUMBER(W10)),"")) -> 1 | AC10: =Parameters!$I$5*ISNUMBER(P10)+Parameters!$I$6*ISNUMBER(Q10)+Parameters!$I$7*ISNUMBER(R10)+Parameters!$I$8*ISNUMBER(S10)+Parameters!$I$9*ISNUMBER(T10)+Parameters!$I$10*ISNUMBER(U10)+Parameters!$I$11*ISNUMBER(V10)+Parameters!$I$12*ISNUMBER(W10) -> 85 | AD10: =Parameters!$I$5*1+Parameters!$I$6*1+Parameters!$I$7*1+Parameters!$I$8*1+Parameters!$I$9*1+Parameters!$I$10*1+Parameters!$I$11*X10+Parameters!$I$12*Y10 -> 85 | AE10: =IF(AD10=0,"",AC10/AD10) -> 1 | AF10: =IF(ISNUMBER(Z10),"M","")&IF(ISNUMBER(AA10),"I","")&IF(ISNUMBER(AB10),"O","") -> MIO | AG10: =IF(AND(ISNUMBER(AE10),ISNUMBER(Z10)+ISNUMBER(AA10)+ISNUMBER(AB10)>=Parameters!$B$37),IF(AE10>=Parameters!$B$35,100*(Parameters!$F$15*N(Z10)+Parameters!$F$16*N(AA10)+Parameters!$F$17*N(AB10))/(Parameters!$F$15*ISNUMBER(Z10)+Parameters!$F$16*ISNUMBER(AA10)+Parameters!$F$17*ISNUMBER(AB10)),""),"") -> 91.666667 | AH10: =IF(ISNUMBER(AG10),RANK(AG10,$AG$2:$AG$113),"") -> 19
A11: arXiv | B11: Cornell University | C11: Repository service | D11: Actual system proven in operational environment | E11: Actively Maintained | F11: 1991-01-01 | I11: FALSE | J11: Not applicable | L11: Fiscal sponsorship (academic institution) | M11: Program service revenue | P11: =IFERROR(IF(ISNUMBER(INDEX(Parameters!$B$5:$B$23,MATCH(D11,Parameters!$A$5:$A$23,0))),INDEX(Parameters!$B$5:$B$23,MATCH(D11,Parameters!$A$5:$A$23,0)),""),"") -> 1 | Q11: =IFERROR(IF(ISNUMBER(INDEX(Parameters!$B$5:$B$23,MATCH(E11,Parameters!$A$5:$A$23,0))),INDEX(Parameters!$B$5:$B$23,MATCH(E11,Parameters!$A$5:$A$23,0)),""),"") -> 1 | R11: =IF(F11="","",IFERROR(MIN(Parameters!$B$33,MAX(0,Parameters!$B$32-VALUE(LEFT(F11,4))))/Parameters!$B$33,"")) -> 1 | S11: =IF(ISNUMBER(H11),H11,IF(G11="",IF(ISNUMBER(Parameters!$B$34),Parameters!$B$34,""),"")) | T11: =IFERROR(IF(ISNUMBER(INDEX(Parameters!$B$5:$B$23,MATCH(I11,Parameters!$A$5:$A$23,0))),INDEX(Parameters!$B$5:$B$23,MATCH(I11,Parameters!$A$5:$A$23,0)),""),"") -> 0 | U11: =IFERROR(IF(ISNUMBER(INDEX(Parameters!$B$5:$B$23,MATCH(L11,Parameters!$A$5:$A$23,0))),INDEX(Parameters!$B$5:$B$23,MATCH(L11,Parameters!$A$5:$A$23,0)),""),"") -> 1 | V11: =IFERROR(IF(ISNUMBER(INDEX(Parameters!$B$5:$B$23,MATCH(J11,Parameters!$A$5:$A$23,0))),INDEX(Parameters!$B$5:$B$23,MATCH(J11,Parameters!$A$5:$A$23,0)),""),"") | W11: =IF(K11<>"",1,IF(COUNTIF(Parameters!$A$27:$A$28,J11)>0,0,"")) | X11: =IF(J11="Not applicable",0,1) -> 0 | Y11: =IF(OR(K11<>"",COUNTIF(Parameters!$A$27:$A$28,J11)>0),1,0) -> 0 | Z11: =IF(((Parameters!$F$5=Parameters!$E$15)*Parameters!$I$5*1+(Parameters!$F$6=Parameters!$E$15)*Parameters!$I$6*1+(Parameters!$F$7=Parameters!$E$15)*Parameters!$I$7*1+(Parameters!$F$8=Parameters!$E$15)*Parameters!$I$8*1+(Parameters!$F$9=Parameters!$E$15)*Parameters!$I$9*1+(Parameters!$F$10=Parameters!$E$15)*Parameters!$I$10*1+(Parameters!$F$11=Parameters!$E$15)*Parameters!$I$11*X11+(Parameters!$F$12=Parameters!$E$15)*Parameters!$I$12*Y11)=0,"",IF(AND(((Parameters!$F$5=Parameters!$E$15)*Parameters!$I$5*ISNUMBER(P11)+(Parameters!$F$6=Parameters!$E$15)*Parameters!$I$6*ISNUMBER(Q11)+(Parameters!$F$7=Parameters!$E$15)*Parameters!$I$7*ISNUMBER(R11)+(Parameters!$F$8=Parameters!$E$15)*Parameters!$I$8*ISNUMBER(S11)+(Parameters!$F$9=Parameters!$E$15)*Parameters!$I$9*ISNUMBER(T11)+(Parameters!$F$10=Parameters!$E$15)*Parameters!$I$10*ISNUMBER(U11)+(Parameters!$F$11=Parameters!$E$15)*Parameters!$I$11*ISNUMBER(V11)+(Parameters!$F$12=Parameters!$E$15)*Parameters!$I$12*ISNUMBER(W11))>0,((Parameters!$F$5=Parameters!$E$15)*Parameters!$I$5*ISNUMBER(P11)+(Parameters!$F$6=Parameters!$E$15)*Parameters!$I$6*ISNUMBER(Q11)+(Parameters!$F$7=Parameters!$E$15)*Parameters!$I$7*ISNUMBER(R11)+(Parameters!$F$8=Parameters!$E$15)*Parameters!$I$8*ISNUMBER(S11)+(Parameters!$F$9=Parameters!$E$15)*Parameters!$I$9*ISNUMBER(T11)+(Parameters!$F$10=Parameters!$E$15)*Parameters!$I$10*ISNUMBER(U11)+(Parameters!$F$11=Parameters!$E$15)*Parameters!$I$11*ISNUMBER(V11)+(Parameters!$F$12=Parameters!$E$15)*Parameters!$I$12*ISNUMBER(W11))/((Parameters!$F$5=Parameters!$E$15)*Parameters!$I$5*1+(Parameters!$F$6=Parameters!$E$15)*Parameters!$I$6*1+(Parameters!$F$7=Parameters!$E$15)*Parameters!$I$7*1+(Parameters!$F$8=Parameters!$E$15)*Parameters!$I$8*1+(Parameters!$F$9=Parameters!$E$15)*Parameters!$I$9*1+(Parameters!$F$10=Parameters!$E$15)*Parameters!$I$10*1+(Parameters!$F$11=Parameters!$E$15)*Parameters!$I$11*X11+(Parameters!$F$12=Parameters!$E$15)*Parameters!$I$12*Y11)>=Parameters!$B$36),((Parameters!$F$5=Parameters!$E$15)*Parameters!$I$5*N(P11)+(Parameters!$F$6=Parameters!$E$15)*Parameters!$I$6*N(Q11)+(Parameters!$F$7=Parameters!$E$15)*Parameters!$I$7*N(R11)+(Parameters!$F$8=Parameters!$E$15)*Parameters!$I$8*N(S11)+(Parameters!$F$9=Parameters!$E$15)*Parameters!$I$9*N(T11)+(Parameters!$F$10=Parameters!$E$15)*Parameters!$I$10*N(U11)+(Parameters!$F$11=Parameters!$E$15)*Parameters!$I$11*N(V11)+(Parameters!$F$12=Parameters!$E$15)*Parameters!$I$12*N(W11))/((Parameters!$F$5=Parameters!$E$15)*Parameters!$I$5*ISNUMBER(P11)+(Parameters!$F$6=Parameters!$E$15)*Parameters!$I$6*ISNUMBER(Q11)+(Parameters!$F$7=Parameters!$E$15)*Parameters!$I$7*ISNUMBER(R11)+(Parameters!$F$8=Parameters!$E$15)*Parameters!$I$8*ISNUMBER(S11)+(Parameters!$F$9=Parameters!$E$15)*Parameters!$I$9*ISNUMBER(T11)+(Parameters!$F$10=Parameters!$E$15)*Parameters!$I$10*ISNUMBER(U11)+(Parameters!$F$11=Parameters!$E$15)*Parameters!$I$11*ISNUMBER(V11)+(Parameters!$F$12=Parameters!$E$15)*Parameters!$I$12*ISNUMBER(W11)),"")) -> 1 | AA11: =IF(((Parameters!$F$5=Parameters!$E$16)*Parameters!$I$5*1+(Parameters!$F$6=Parameters!$E$16)*Parameters!$I$6*1+(Parameters!$F$7=Parameters!$E$16)*Parameters!$I$7*1+(Parameters!$F$8=Parameters!$E$16)*Parameters!$I$8*1+(Parameters!$F$9=Parameters!$E$16)*Parameters!$I$9*1+(Parameters!$F$10=Parameters!$E$16)*Parameters!$I$10*1+(Parameters!$F$11=Parameters!$E$16)*Parameters!$I$11*X11+(Parameters!$F$12=Parameters!$E$16)*Parameters!$I$12*Y11)=0,"",IF(AND(((Parameters!$F$5=Parameters!$E$16)*Parameters!$I$5*ISNUMBER(P11)+(Parameters!$F$6=Parameters!$E$16)*Parameters!$I$6*ISNUMBER(Q11)+(Parameters!$F$7=Parameters!$E$16)*Parameters!$I$7*ISNUMBER(R11)+(Parameters!$F$8=Parameters!$E$16)*Parameters!$I$8*ISNUMBER(S11)+(Parameters!$F$9=Parameters!$E$16)*Parameters!$I$9*ISNUMBER(T11)+(Parameters!$F$10=Parameters!$E$16)*Parameters!$I$10*ISNUMBER(U11)+(Parameters!$F$11=Parameters!$E$16)*Parameters!$I$11*ISNUMBER(V11)+(Parameters!$F$12=Parameters!$E$16)*Parameters!$I$12*ISNUMBER(W11))>0,((Parameters!$F$5=Parameters!$E$16)*Parameters!$I$5*ISNUMBER(P11)+(Parameters!$F$6=Parameters!$E$16)*Parameters!$I$6*ISNUMBER(Q11)+(Parameters!$F$7=Parameters!$E$16)*Parameters!$I$7*ISNUMBER(R11)+(Parameters!$F$8=Parameters!$E$16)*Parameters!$I$8*ISNUMBER(S11)+(Parameters!$F$9=Parameters!$E$16)*Parameters!$I$9*ISNUMBER(T11)+(Parameters!$F$10=Parameters!$E$16)*Parameters!$I$10*ISNUMBER(U11)+(Parameters!$F$11=Parameters!$E$16)*Parameters!$I$11*ISNUMBER(V11)+(Parameters!$F$12=Parameters!$E$16)*Parameters!$I$12*ISNUMBER(W11))/((Parameters!$F$5=Parameters!$E$16)*Parameters!$I$5*1+(Parameters!$F$6=Parameters!$E$16)*Parameters!$I$6*1+(Parameters!$F$7=Parameters!$E$16)*Parameters!$I$7*1+(Parameters!$F$8=Parameters!$E$16)*Parameters!$I$8*1+(Parameters!$F$9=Parameters!$E$16)*Parameters!$I$9*1+(Parameters!$F$10=Parameters!$E$16)*Parameters!$I$10*1+(Parameters!$F$11=Parameters!$E$16)*Parameters!$I$11*X11+(Parameters!$F$12=Parameters!$E$16)*Parameters!$I$12*Y11)>=Parameters!$B$36),((Parameters!$F$5=Parameters!$E$16)*Parameters!$I$5*N(P11)+(Parameters!$F$6=Parameters!$E$16)*Parameters!$I$6*N(Q11)+(Parameters!$F$7=Parameters!$E$16)*Parameters!$I$7*N(R11)+(Parameters!$F$8=Parameters!$E$16)*Parameters!$I$8*N(S11)+(Parameters!$F$9=Parameters!$E$16)*Parameters!$I$9*N(T11)+(Parameters!$F$10=Parameters!$E$16)*Parameters!$I$10*N(U11)+(Parameters!$F$11=Parameters!$E$16)*Parameters!$I$11*N(V11)+(Parameters!$F$12=Parameters!$E$16)*Parameters!$I$12*N(W11))/((Parameters!$F$5=Parameters!$E$16)*Parameters!$I$5*ISNUMBER(P11)+(Parameters!$F$6=Parameters!$E$16)*Parameters!$I$6*ISNUMBER(Q11)+(Parameters!$F$7=Parameters!$E$16)*Parameters!$I$7*ISNUMBER(R11)+(Parameters!$F$8=Parameters!$E$16)*Parameters!$I$8*ISNUMBER(S11)+(Parameters!$F$9=Parameters!$E$16)*Parameters!$I$9*ISNUMBER(T11)+(Parameters!$F$10=Parameters!$E$16)*Parameters!$I$10*ISNUMBER(U11)+(Parameters!$F$11=Parameters!$E$16)*Parameters!$I$11*ISNUMBER(V11)+(Parameters!$F$12=Parameters!$E$16)*Parameters!$I$12*ISNUMBER(W11)),"")) -> 0.66666667 | AB11: =IF(((Parameters!$F$5=Parameters!$E$17)*Parameters!$I$5*1+(Parameters!$F$6=Parameters!$E$17)*Parameters!$I$6*1+(Parameters!$F$7=Parameters!$E$17)*Parameters!$I$7*1+(Parameters!$F$8=Parameters!$E$17)*Parameters!$I$8*1+(Parameters!$F$9=Parameters!$E$17)*Parameters!$I$9*1+(Parameters!$F$10=Parameters!$E$17)*Parameters!$I$10*1+(Parameters!$F$11=Parameters!$E$17)*Parameters!$I$11*X11+(Parameters!$F$12=Parameters!$E$17)*Parameters!$I$12*Y11)=0,"",IF(AND(((Parameters!$F$5=Parameters!$E$17)*Parameters!$I$5*ISNUMBER(P11)+(Parameters!$F$6=Parameters!$E$17)*Parameters!$I$6*ISNUMBER(Q11)+(Parameters!$F$7=Parameters!$E$17)*Parameters!$I$7*ISNUMBER(R11)+(Parameters!$F$8=Parameters!$E$17)*Parameters!$I$8*ISNUMBER(S11)+(Parameters!$F$9=Parameters!$E$17)*Parameters!$I$9*ISNUMBER(T11)+(Parameters!$F$10=Parameters!$E$17)*Parameters!$I$10*ISNUMBER(U11)+(Parameters!$F$11=Parameters!$E$17)*Parameters!$I$11*ISNUMBER(V11)+(Parameters!$F$12=Parameters!$E$17)*Parameters!$I$12*ISNUMBER(W11))>0,((Parameters!$F$5=Parameters!$E$17)*Parameters!$I$5*ISNUMBER(P11)+(Parameters!$F$6=Parameters!$E$17)*Parameters!$I$6*ISNUMBER(Q11)+(Parameters!$F$7=Parameters!$E$17)*Parameters!$I$7*ISNUMBER(R11)+(Parameters!$F$8=Parameters!$E$17)*Parameters!$I$8*ISNUMBER(S11)+(Parameters!$F$9=Parameters!$E$17)*Parameters!$I$9*ISNUMBER(T11)+(Parameters!$F$10=Parameters!$E$17)*Parameters!$I$10*ISNUMBER(U11)+(Parameters!$F$11=Parameters!$E$17)*Parameters!$I$11*ISNUMBER(V11)+(Parameters!$F$12=Parameters!$E$17)*Parameters!$I$12*ISNUMBER(W11))/((Parameters!$F$5=Parameters!$E$17)*Parameters!$I$5*1+(Parameters!$F$6=Parameters!$E$17)*Parameters!$I$6*1+(Parameters!$F$7=Parameters!$E$17)*Parameters!$I$7*1+(Parameters!$F$8=Parameters!$E$17)*Parameters!$I$8*1+(Parameters!$F$9=Parameters!$E$17)*Parameters!$I$9*1+(Parameters!$F$10=Parameters!$E$17)*Parameters!$I$10*1+(Parameters!$F$11=Parameters!$E$17)*Parameters!$I$11*X11+(Parameters!$F$12=Parameters!$E$17)*Parameters!$I$12*Y11)>=Parameters!$B$36),((Parameters!$F$5=Parameters!$E$17)*Parameters!$I$5*N(P11)+(Parameters!$F$6=Parameters!$E$17)*Parameters!$I$6*N(Q11)+(Parameters!$F$7=Parameters!$E$17)*Parameters!$I$7*N(R11)+(Parameters!$F$8=Parameters!$E$17)*Parameters!$I$8*N(S11)+(Parameters!$F$9=Parameters!$E$17)*Parameters!$I$9*N(T11)+(Parameters!$F$10=Parameters!$E$17)*Parameters!$I$10*N(U11)+(Parameters!$F$11=Parameters!$E$17)*Parameters!$I$11*N(V11)+(Parameters!$F$12=Parameters!$E$17)*Parameters!$I$12*N(W11))/((Parameters!$F$5=Parameters!$E$17)*Parameters!$I$5*ISNUMBER(P11)+(Parameters!$F$6=Parameters!$E$17)*Parameters!$I$6*ISNUMBER(Q11)+(Parameters!$F$7=Parameters!$E$17)*Parameters!$I$7*ISNUMBER(R11)+(Parameters!$F$8=Parameters!$E$17)*Parameters!$I$8*ISNUMBER(S11)+(Parameters!$F$9=Parameters!$E$17)*Parameters!$I$9*ISNUMBER(T11)+(Parameters!$F$10=Parameters!$E$17)*Parameters!$I$10*ISNUMBER(U11)+(Parameters!$F$11=Parameters!$E$17)*Parameters!$I$11*ISNUMBER(V11)+(Parameters!$F$12=Parameters!$E$17)*Parameters!$I$12*ISNUMBER(W11)),"")) | AC11: =Parameters!$I$5*ISNUMBER(P11)+Parameters!$I$6*ISNUMBER(Q11)+Parameters!$I$7*ISNUMBER(R11)+Parameters!$I$8*ISNUMBER(S11)+Parameters!$I$9*ISNUMBER(T11)+Parameters!$I$10*ISNUMBER(U11)+Parameters!$I$11*ISNUMBER(V11)+Parameters!$I$12*ISNUMBER(W11) -> 65 | AD11: =Parameters!$I$5*1+Parameters!$I$6*1+Parameters!$I$7*1+Parameters!$I$8*1+Parameters!$I$9*1+Parameters!$I$10*1+Parameters!$I$11*X11+Parameters!$I$12*Y11 -> 75 | AE11: =IF(AD11=0,"",AC11/AD11) -> 0.86666667 | AF11: =IF(ISNUMBER(Z11),"M","")&IF(ISNUMBER(AA11),"I","")&IF(ISNUMBER(AB11),"O","") -> MI | AG11: =IF(AND(ISNUMBER(AE11),ISNUMBER(Z11)+ISNUMBER(AA11)+ISNUMBER(AB11)>=Parameters!$B$37),IF(AE11>=Parameters!$B$35,100*(Parameters!$F$15*N(Z11)+Parameters!$F$16*N(AA11)+Parameters!$F$17*N(AB11))/(Parameters!$F$15*ISNUMBER(Z11)+Parameters!$F$16*ISNUMBER(AA11)+Parameters!$F$17*ISNUMBER(AB11)),""),"") -> 87.5 | AH11: =IF(ISNUMBER(AG11),RANK(AG11,$AG$2:$AG$113),"") -> 40
A12: AtoM | B12: Artefactual | C12: Archive information management system | D12: Actual system proven in operational environment | E12: Actively Maintained | F12: 2007-01-01 | G12: No affiliations | H12: 0 | I12: FALSE | J12: Through solution provider or third party vendor | K12: https://www.artefactual.com/pricing | L12: Commercial (for-profit) | M12: Program service revenue | N12: More than 20 | O12: Unknown | P12: =IFERROR(IF(ISNUMBER(INDEX(Parameters!$B$5:$B$23,MATCH(D12,Parameters!$A$5:$A$23,0))),INDEX(Parameters!$B$5:$B$23,MATCH(D12,Parameters!$A$5:$A$23,0)),""),"") -> 1 | Q12: =IFERROR(IF(ISNUMBER(INDEX(Parameters!$B$5:$B$23,MATCH(E12,Parameters!$A$5:$A$23,0))),INDEX(Parameters!$B$5:$B$23,MATCH(E12,Parameters!$A$5:$A$23,0)),""),"") -> 1 | R12: =IF(F12="","",IFERROR(MIN(Parameters!$B$33,MAX(0,Parameters!$B$32-VALUE(LEFT(F12,4))))/Parameters!$B$33,"")) -> 1 | S12: =IF(ISNUMBER(H12),H12,IF(G12="",IF(ISNUMBER(Parameters!$B$34),Parameters!$B$34,""),"")) -> 0 | T12: =IFERROR(IF(ISNUMBER(INDEX(Parameters!$B$5:$B$23,MATCH(I12,Parameters!$A$5:$A$23,0))),INDEX(Parameters!$B$5:$B$23,MATCH(I12,Parameters!$A$5:$A$23,0)),""),"") -> 0 | U12: =IFERROR(IF(ISNUMBER(INDEX(Parameters!$B$5:$B$23,MATCH(L12,Parameters!$A$5:$A$23,0))),INDEX(Parameters!$B$5:$B$23,MATCH(L12,Parameters!$A$5:$A$23,0)),""),"") -> 0.5 | V12: =IFERROR(IF(ISNUMBER(INDEX(Parameters!$B$5:$B$23,MATCH(J12,Parameters!$A$5:$A$23,0))),INDEX(Parameters!$B$5:$B$23,MATCH(J12,Parameters!$A$5:$A$23,0)),""),"") -> 1 | W12: =IF(K12<>"",1,IF(COUNTIF(Parameters!$A$27:$A$28,J12)>0,0,"")) -> 1 | X12: =IF(J12="Not applicable",0,1) -> 1 | Y12: =IF(OR(K12<>"",COUNTIF(Parameters!$A$27:$A$28,J12)>0),1,0) -> 1 | Z12: =IF(((Parameters!$F$5=Parameters!$E$15)*Parameters!$I$5*1+(Parameters!$F$6=Parameters!$E$15)*Parameters!$I$6*1+(Parameters!$F$7=Parameters!$E$15)*Parameters!$I$7*1+(Parameters!$F$8=Parameters!$E$15)*Parameters!$I$8*1+(Parameters!$F$9=Parameters!$E$15)*Parameters!$I$9*1+(Parameters!$F$10=Parameters!$E$15)*Parameters!$I$10*1+(Parameters!$F$11=Parameters!$E$15)*Parameters!$I$11*X12+(Parameters!$F$12=Parameters!$E$15)*Parameters!$I$12*Y12)=0,"",IF(AND(((Parameters!$F$5=Parameters!$E$15)*Parameters!$I$5*ISNUMBER(P12)+(Parameters!$F$6=Parameters!$E$15)*Parameters!$I$6*ISNUMBER(Q12)+(Parameters!$F$7=Parameters!$E$15)*Parameters!$I$7*ISNUMBER(R12)+(Parameters!$F$8=Parameters!$E$15)*Parameters!$I$8*ISNUMBER(S12)+(Parameters!$F$9=Parameters!$E$15)*Parameters!$I$9*ISNUMBER(T12)+(Parameters!$F$10=Parameters!$E$15)*Parameters!$I$10*ISNUMBER(U12)+(Parameters!$F$11=Parameters!$E$15)*Parameters!$I$11*ISNUMBER(V12)+(Parameters!$F$12=Parameters!$E$15)*Parameters!$I$12*ISNUMBER(W12))>0,((Parameters!$F$5=Parameters!$E$15)*Parameters!$I$5*ISNUMBER(P12)+(Parameters!$F$6=Parameters!$E$15)*Parameters!$I$6*ISNUMBER(Q12)+(Parameters!$F$7=Parameters!$E$15)*Parameters!$I$7*ISNUMBER(R12)+(Parameters!$F$8=Parameters!$E$15)*Parameters!$I$8*ISNUMBER(S12)+(Parameters!$F$9=Parameters!$E$15)*Parameters!$I$9*ISNUMBER(T12)+(Parameters!$F$10=Parameters!$E$15)*Parameters!$I$10*ISNUMBER(U12)+(Parameters!$F$11=Parameters!$E$15)*Parameters!$I$11*ISNUMBER(V12)+(Parameters!$F$12=Parameters!$E$15)*Parameters!$I$12*ISNUMBER(W12))/((Parameters!$F$5=Parameters!$E$15)*Parameters!$I$5*1+(Parameters!$F$6=Parameters!$E$15)*Parameters!$I$6*1+(Parameters!$F$7=Parameters!$E$15)*Parameters!$I$7*1+(Parameters!$F$8=Parameters!$E$15)*Parameters!$I$8*1+(Parameters!$F$9=Parameters!$E$15)*Parameters!$I$9*1+(Parameters!$F$10=Parameters!$E$15)*Parameters!$I$10*1+(Parameters!$F$11=Parameters!$E$15)*Parameters!$I$11*X12+(Parameters!$F$12=Parameters!$E$15)*Parameters!$I$12*Y12)>=Parameters!$B$36),((Parameters!$F$5=Parameters!$E$15)*Parameters!$I$5*N(P12)+(Parameters!$F$6=Parameters!$E$15)*Parameters!$I$6*N(Q12)+(Parameters!$F$7=Parameters!$E$15)*Parameters!$I$7*N(R12)+(Parameters!$F$8=Parameters!$E$15)*Parameters!$I$8*N(S12)+(Parameters!$F$9=Parameters!$E$15)*Parameters!$I$9*N(T12)+(Parameters!$F$10=Parameters!$E$15)*Parameters!$I$10*N(U12)+(Parameters!$F$11=Parameters!$E$15)*Parameters!$I$11*N(V12)+(Parameters!$F$12=Parameters!$E$15)*Parameters!$I$12*N(W12))/((Parameters!$F$5=Parameters!$E$15)*Parameters!$I$5*ISNUMBER(P12)+(Parameters!$F$6=Parameters!$E$15)*Parameters!$I$6*ISNUMBER(Q12)+(Parameters!$F$7=Parameters!$E$15)*Parameters!$I$7*ISNUMBER(R12)+(Parameters!$F$8=Parameters!$E$15)*Parameters!$I$8*ISNUMBER(S12)+(Parameters!$F$9=Parameters!$E$15)*Parameters!$I$9*ISNUMBER(T12)+(Parameters!$F$10=Parameters!$E$15)*Parameters!$I$10*ISNUMBER(U12)+(Parameters!$F$11=Parameters!$E$15)*Parameters!$I$11*ISNUMBER(V12)+(Parameters!$F$12=Parameters!$E$15)*Parameters!$I$12*ISNUMBER(W12)),"")) -> 1 | AA12: =IF(((Parameters!$F$5=Parameters!$E$16)*Parameters!$I$5*1+(Parameters!$F$6=Parameters!$E$16)*Parameters!$I$6*1+(Parameters!$F$7=Parameters!$E$16)*Parameters!$I$7*1+(Parameters!$F$8=Parameters!$E$16)*Parameters!$I$8*1+(Parameters!$F$9=Parameters!$E$16)*Parameters!$I$9*1+(Parameters!$F$10=Parameters!$E$16)*Parameters!$I$10*1+(Parameters!$F$11=Parameters!$E$16)*Parameters!$I$11*X12+(Parameters!$F$12=Parameters!$E$16)*Parameters!$I$12*Y12)=0,"",IF(AND(((Parameters!$F$5=Parameters!$E$16)*Parameters!$I$5*ISNUMBER(P12)+(Parameters!$F$6=Parameters!$E$16)*Parameters!$I$6*ISNUMBER(Q12)+(Parameters!$F$7=Parameters!$E$16)*Parameters!$I$7*ISNUMBER(R12)+(Parameters!$F$8=Parameters!$E$16)*Parameters!$I$8*ISNUMBER(S12)+(Parameters!$F$9=Parameters!$E$16)*Parameters!$I$9*ISNUMBER(T12)+(Parameters!$F$10=Parameters!$E$16)*Parameters!$I$10*ISNUMBER(U12)+(Parameters!$F$11=Parameters!$E$16)*Parameters!$I$11*ISNUMBER(V12)+(Parameters!$F$12=Parameters!$E$16)*Parameters!$I$12*ISNUMBER(W12))>0,((Parameters!$F$5=Parameters!$E$16)*Parameters!$I$5*ISNUMBER(P12)+(Parameters!$F$6=Parameters!$E$16)*Parameters!$I$6*ISNUMBER(Q12)+(Parameters!$F$7=Parameters!$E$16)*Parameters!$I$7*ISNUMBER(R12)+(Parameters!$F$8=Parameters!$E$16)*Parameters!$I$8*ISNUMBER(S12)+(Parameters!$F$9=Parameters!$E$16)*Parameters!$I$9*ISNUMBER(T12)+(Parameters!$F$10=Parameters!$E$16)*Parameters!$I$10*ISNUMBER(U12)+(Parameters!$F$11=Parameters!$E$16)*Parameters!$I$11*ISNUMBER(V12)+(Parameters!$F$12=Parameters!$E$16)*Parameters!$I$12*ISNUMBER(W12))/((Parameters!$F$5=Parameters!$E$16)*Parameters!$I$5*1+(Parameters!$F$6=Parameters!$E$16)*Parameters!$I$6*1+(Parameters!$F$7=Parameters!$E$16)*Parameters!$I$7*1+(Parameters!$F$8=Parameters!$E$16)*Parameters!$I$8*1+(Parameters!$F$9=Parameters!$E$16)*Parameters!$I$9*1+(Parameters!$F$10=Parameters!$E$16)*Parameters!$I$10*1+(Parameters!$F$11=Parameters!$E$16)*Parameters!$I$11*X12+(Parameters!$F$12=Parameters!$E$16)*Parameters!$I$12*Y12)>=Parameters!$B$36),((Parameters!$F$5=Parameters!$E$16)*Parameters!$I$5*N(P12)+(Parameters!$F$6=Parameters!$E$16)*Parameters!$I$6*N(Q12)+(Parameters!$F$7=Parameters!$E$16)*Parameters!$I$7*N(R12)+(Parameters!$F$8=Parameters!$E$16)*Parameters!$I$8*N(S12)+(Parameters!$F$9=Parameters!$E$16)*Parameters!$I$9*N(T12)+(Parameters!$F$10=Parameters!$E$16)*Parameters!$I$10*N(U12)+(Parameters!$F$11=Parameters!$E$16)*Parameters!$I$11*N(V12)+(Parameters!$F$12=Parameters!$E$16)*Parameters!$I$12*N(W12))/((Parameters!$F$5=Parameters!$E$16)*Parameters!$I$5*ISNUMBER(P12)+(Parameters!$F$6=Parameters!$E$16)*Parameters!$I$6*ISNUMBER(Q12)+(Parameters!$F$7=Parameters!$E$16)*Parameters!$I$7*ISNUMBER(R12)+(Parameters!$F$8=Parameters!$E$16)*Parameters!$I$8*ISNUMBER(S12)+(Parameters!$F$9=Parameters!$E$16)*Parameters!$I$9*ISNUMBER(T12)+(Parameters!$F$10=Parameters!$E$16)*Parameters!$I$10*ISNUMBER(U12)+(Parameters!$F$11=Parameters!$E$16)*Parameters!$I$11*ISNUMBER(V12)+(Parameters!$F$12=Parameters!$E$16)*Parameters!$I$12*ISNUMBER(W12)),"")) -> 0.2 | AB12: =IF(((Parameters!$F$5=Parameters!$E$17)*Parameters!$I$5*1+(Parameters!$F$6=Parameters!$E$17)*Parameters!$I$6*1+(Parameters!$F$7=Parameters!$E$17)*Parameters!$I$7*1+(Parameters!$F$8=Parameters!$E$17)*Parameters!$I$8*1+(Parameters!$F$9=Parameters!$E$17)*Parameters!$I$9*1+(Parameters!$F$10=Parameters!$E$17)*Parameters!$I$10*1+(Parameters!$F$11=Parameters!$E$17)*Parameters!$I$11*X12+(Parameters!$F$12=Parameters!$E$17)*Parameters!$I$12*Y12)=0,"",IF(AND(((Parameters!$F$5=Parameters!$E$17)*Parameters!$I$5*ISNUMBER(P12)+(Parameters!$F$6=Parameters!$E$17)*Parameters!$I$6*ISNUMBER(Q12)+(Parameters!$F$7=Parameters!$E$17)*Parameters!$I$7*ISNUMBER(R12)+(Parameters!$F$8=Parameters!$E$17)*Parameters!$I$8*ISNUMBER(S12)+(Parameters!$F$9=Parameters!$E$17)*Parameters!$I$9*ISNUMBER(T12)+(Parameters!$F$10=Parameters!$E$17)*Parameters!$I$10*ISNUMBER(U12)+(Parameters!$F$11=Parameters!$E$17)*Parameters!$I$11*ISNUMBER(V12)+(Parameters!$F$12=Parameters!$E$17)*Parameters!$I$12*ISNUMBER(W12))>0,((Parameters!$F$5=Parameters!$E$17)*Parameters!$I$5*ISNUMBER(P12)+(Parameters!$F$6=Parameters!$E$17)*Parameters!$I$6*ISNUMBER(Q12)+(Parameters!$F$7=Parameters!$E$17)*Parameters!$I$7*ISNUMBER(R12)+(Parameters!$F$8=Parameters!$E$17)*Parameters!$I$8*ISNUMBER(S12)+(Parameters!$F$9=Parameters!$E$17)*Parameters!$I$9*ISNUMBER(T12)+(Parameters!$F$10=Parameters!$E$17)*Parameters!$I$10*ISNUMBER(U12)+(Parameters!$F$11=Parameters!$E$17)*Parameters!$I$11*ISNUMBER(V12)+(Parameters!$F$12=Parameters!$E$17)*Parameters!$I$12*ISNUMBER(W12))/((Parameters!$F$5=Parameters!$E$17)*Parameters!$I$5*1+(Parameters!$F$6=Parameters!$E$17)*Parameters!$I$6*1+(Parameters!$F$7=Parameters!$E$17)*Parameters!$I$7*1+(Parameters!$F$8=Parameters!$E$17)*Parameters!$I$8*1+(Parameters!$F$9=Parameters!$E$17)*Parameters!$I$9*1+(Parameters!$F$10=Parameters!$E$17)*Parameters!$I$10*1+(Parameters!$F$11=Parameters!$E$17)*Parameters!$I$11*X12+(Parameters!$F$12=Parameters!$E$17)*Parameters!$I$12*Y12)>=Parameters!$B$36),((Parameters!$F$5=Parameters!$E$17)*Parameters!$I$5*N(P12)+(Parameters!$F$6=Parameters!$E$17)*Parameters!$I$6*N(Q12)+(Parameters!$F$7=Parameters!$E$17)*Parameters!$I$7*N(R12)+(Parameters!$F$8=Parameters!$E$17)*Parameters!$I$8*N(S12)+(Parameters!$F$9=Parameters!$E$17)*Parameters!$I$9*N(T12)+(Parameters!$F$10=Parameters!$E$17)*Parameters!$I$10*N(U12)+(Parameters!$F$11=Parameters!$E$17)*Parameters!$I$11*N(V12)+(Parameters!$F$12=Parameters!$E$17)*Parameters!$I$12*N(W12))/((Parameters!$F$5=Parameters!$E$17)*Parameters!$I$5*ISNUMBER(P12)+(Parameters!$F$6=Parameters!$E$17)*Parameters!$I$6*ISNUMBER(Q12)+(Parameters!$F$7=Parameters!$E$17)*Parameters!$I$7*ISNUMBER(R12)+(Parameters!$F$8=Parameters!$E$17)*Parameters!$I$8*ISNUMBER(S12)+(Parameters!$F$9=Parameters!$E$17)*Parameters!$I$9*ISNUMBER(T12)+(Parameters!$F$10=Parameters!$E$17)*Parameters!$I$10*ISNUMBER(U12)+(Parameters!$F$11=Parameters!$E$17)*Parameters!$I$11*ISNUMBER(V12)+(Parameters!$F$12=Parameters!$E$17)*Parameters!$I$12*ISNUMBER(W12)),"")) -> 1 | AC12: =Parameters!$I$5*ISNUMBER(P12)+Parameters!$I$6*ISNUMBER(Q12)+Parameters!$I$7*ISNUMBER(R12)+Parameters!$I$8*ISNUMBER(S12)+Parameters!$I$9*ISNUMBER(T12)+Parameters!$I$10*ISNUMBER(U12)+Parameters!$I$11*ISNUMBER(V12)+Parameters!$I$12*ISNUMBER(W12) -> 95 | AD12: =Parameters!$I$5*1+Parameters!$I$6*1+Parameters!$I$7*1+Parameters!$I$8*1+Parameters!$I$9*1+Parameters!$I$10*1+Parameters!$I$11*X12+Parameters!$I$12*Y12 -> 95 | AE12: =IF(AD12=0,"",AC12/AD12) -> 1 | AF12: =IF(ISNUMBER(Z12),"M","")&IF(ISNUMBER(AA12),"I","")&IF(ISNUMBER(AB12),"O","") -> MIO | AG12: =IF(AND(ISNUMBER(AE12),ISNUMBER(Z12)+ISNUMBER(AA12)+ISNUMBER(AB12)>=Parameters!$B$37),IF(AE12>=Parameters!$B$35,100*(Parameters!$F$15*N(Z12)+Parameters!$F$16*N(AA12)+Parameters!$F$17*N(AB12))/(Parameters!$F$15*ISNUMBER(Z12)+Parameters!$F$16*ISNUMBER(AA12)+Parameters!$F$17*ISNUMBER(AB12)),""),"") -> 76 | AH12: =IF(ISNUMBER(AG12),RANK(AG12,$AG$2:$AG$113),"") -> 88
A13: Avalon Media System | B13: Indiana University Libraries | C13: Digital library, collection or exhibit platform | Repository software | D13: Actual system proven in operational environment | E13: Actively Maintained | F13: 2013-01-01 | G13: Indiana University Libraries | H13: 1 | I13: FALSE | J13: No services available | L13: Non-profit organization | M13: Other | N13: 1-5 | P13: =IFERROR(IF(ISNUMBER(INDEX(Parameters!$B$5:$B$23,MATCH(D13,Parameters!$A$5:$A$23,0))),INDEX(Parameters!$B$5:$B$23,MATCH(D13,Parameters!$A$5:$A$23,0)),""),"") -> 1 | Q13: =IFERROR(IF(ISNUMBER(INDEX(Parameters!$B$5:$B$23,MATCH(E13,Parameters!$A$5:$A$23,0))),INDEX(Parameters!$B$5:$B$23,MATCH(E13,Parameters!$A$5:$A$23,0)),""),"") -> 1 | R13: =IF(F13="","",IFERROR(MIN(Parameters!$B$33,MAX(0,Parameters!$B$32-VALUE(LEFT(F13,4))))/Parameters!$B$33,"")) -> 0.86666667 | S13: =IF(ISNUMBER(H13),H13,IF(G13="",IF(ISNUMBER(Parameters!$B$34),Parameters!$B$34,""),"")) -> 1 | T13: =IFERROR(IF(ISNUMBER(INDEX(Parameters!$B$5:$B$23,MATCH(I13,Parameters!$A$5:$A$23,0))),INDEX(Parameters!$B$5:$B$23,MATCH(I13,Parameters!$A$5:$A$23,0)),""),"") -> 0 | U13: =IFERROR(IF(ISNUMBER(INDEX(Parameters!$B$5:$B$23,MATCH(L13,Parameters!$A$5:$A$23,0))),INDEX(Parameters!$B$5:$B$23,MATCH(L13,Parameters!$A$5:$A$23,0)),""),"") -> 1 | V13: =IFERROR(IF(ISNUMBER(INDEX(Parameters!$B$5:$B$23,MATCH(J13,Parameters!$A$5:$A$23,0))),INDEX(Parameters!$B$5:$B$23,MATCH(J13,Parameters!$A$5:$A$23,0)),""),"") -> 0 | W13: =IF(K13<>"",1,IF(COUNTIF(Parameters!$A$27:$A$28,J13)>0,0,"")) | X13: =IF(J13="Not applicable",0,1) -> 1 | Y13: =IF(OR(K13<>"",COUNTIF(Parameters!$A$27:$A$28,J13)>0),1,0) -> 0 | Z13: =IF(((Parameters!$F$5=Parameters!$E$15)*Parameters!$I$5*1+(Parameters!$F$6=Parameters!$E$15)*Parameters!$I$6*1+(Parameters!$F$7=Parameters!$E$15)*Parameters!$I$7*1+(Parameters!$F$8=Parameters!$E$15)*Parameters!$I$8*1+(Parameters!$F$9=Parameters!$E$15)*Parameters!$I$9*1+(Parameters!$F$10=Parameters!$E$15)*Parameters!$I$10*1+(Parameters!$F$11=Parameters!$E$15)*Parameters!$I$11*X13+(Parameters!$F$12=Parameters!$E$15)*Parameters!$I$12*Y13)=0,"",IF(AND(((Parameters!$F$5=Parameters!$E$15)*Parameters!$I$5*ISNUMBER(P13)+(Parameters!$F$6=Parameters!$E$15)*Parameters!$I$6*ISNUMBER(Q13)+(Parameters!$F$7=Parameters!$E$15)*Parameters!$I$7*ISNUMBER(R13)+(Parameters!$F$8=Parameters!$E$15)*Parameters!$I$8*ISNUMBER(S13)+(Parameters!$F$9=Parameters!$E$15)*Parameters!$I$9*ISNUMBER(T13)+(Parameters!$F$10=Parameters!$E$15)*Parameters!$I$10*ISNUMBER(U13)+(Parameters!$F$11=Parameters!$E$15)*Parameters!$I$11*ISNUMBER(V13)+(Parameters!$F$12=Parameters!$E$15)*Parameters!$I$12*ISNUMBER(W13))>0,((Parameters!$F$5=Parameters!$E$15)*Parameters!$I$5*ISNUMBER(P13)+(Parameters!$F$6=Parameters!$E$15)*Parameters!$I$6*ISNUMBER(Q13)+(Parameters!$F$7=Parameters!$E$15)*Parameters!$I$7*ISNUMBER(R13)+(Parameters!$F$8=Parameters!$E$15)*Parameters!$I$8*ISNUMBER(S13)+(Parameters!$F$9=Parameters!$E$15)*Parameters!$I$9*ISNUMBER(T13)+(Parameters!$F$10=Parameters!$E$15)*Parameters!$I$10*ISNUMBER(U13)+(Parameters!$F$11=Parameters!$E$15)*Parameters!$I$11*ISNUMBER(V13)+(Parameters!$F$12=Parameters!$E$15)*Parameters!$I$12*ISNUMBER(W13))/((Parameters!$F$5=Parameters!$E$15)*Parameters!$I$5*1+(Parameters!$F$6=Parameters!$E$15)*Parameters!$I$6*1+(Parameters!$F$7=Parameters!$E$15)*Parameters!$I$7*1+(Parameters!$F$8=Parameters!$E$15)*Parameters!$I$8*1+(Parameters!$F$9=Parameters!$E$15)*Parameters!$I$9*1+(Parameters!$F$10=Parameters!$E$15)*Parameters!$I$10*1+(Parameters!$F$11=Parameters!$E$15)*Parameters!$I$11*X13+(Parameters!$F$12=Parameters!$E$15)*Parameters!$I$12*Y13)>=Parameters!$B$36),((Parameters!$F$5=Parameters!$E$15)*Parameters!$I$5*N(P13)+(Parameters!$F$6=Parameters!$E$15)*Parameters!$I$6*N(Q13)+(Parameters!$F$7=Parameters!$E$15)*Parameters!$I$7*N(R13)+(Parameters!$F$8=Parameters!$E$15)*Parameters!$I$8*N(S13)+(Parameters!$F$9=Parameters!$E$15)*Parameters!$I$9*N(T13)+(Parameters!$F$10=Parameters!$E$15)*Parameters!$I$10*N(U13)+(Parameters!$F$11=Parameters!$E$15)*Parameters!$I$11*N(V13)+(Parameters!$F$12=Parameters!$E$15)*Parameters!$I$12*N(W13))/((Parameters!$F$5=Parameters!$E$15)*Parameters!$I$5*ISNUMBER(P13)+(Parameters!$F$6=Parameters!$E$15)*Parameters!$I$6*ISNUMBER(Q13)+(Parameters!$F$7=Parameters!$E$15)*Parameters!$I$7*ISNUMBER(R13)+(Parameters!$F$8=Parameters!$E$15)*Parameters!$I$8*ISNUMBER(S13)+(Parameters!$F$9=Parameters!$E$15)*Parameters!$I$9*ISNUMBER(T13)+(Parameters!$F$10=Parameters!$E$15)*Parameters!$I$10*ISNUMBER(U13)+(Parameters!$F$11=Parameters!$E$15)*Parameters!$I$11*ISNUMBER(V13)+(Parameters!$F$12=Parameters!$E$15)*Parameters!$I$12*ISNUMBER(W13)),"")) -> 0.98666667 | AA13: =IF(((Parameters!$F$5=Parameters!$E$16)*Parameters!$I$5*1+(Parameters!$F$6=Parameters!$E$16)*Parameters!$I$6*1+(Parameters!$F$7=Parameters!$E$16)*Parameters!$I$7*1+(Parameters!$F$8=Parameters!$E$16)*Parameters!$I$8*1+(Parameters!$F$9=Parameters!$E$16)*Parameters!$I$9*1+(Parameters!$F$10=Parameters!$E$16)*Parameters!$I$10*1+(Parameters!$F$11=Parameters!$E$16)*Parameters!$I$11*X13+(Parameters!$F$12=Parameters!$E$16)*Parameters!$I$12*Y13)=0,"",IF(AND(((Parameters!$F$5=Parameters!$E$16)*Parameters!$I$5*ISNUMBER(P13)+(Parameters!$F$6=Parameters!$E$16)*Parameters!$I$6*ISNUMBER(Q13)+(Parameters!$F$7=Parameters!$E$16)*Parameters!$I$7*ISNUMBER(R13)+(Parameters!$F$8=Parameters!$E$16)*Parameters!$I$8*ISNUMBER(S13)+(Parameters!$F$9=Parameters!$E$16)*Parameters!$I$9*ISNUMBER(T13)+(Parameters!$F$10=Parameters!$E$16)*Parameters!$I$10*ISNUMBER(U13)+(Parameters!$F$11=Parameters!$E$16)*Parameters!$I$11*ISNUMBER(V13)+(Parameters!$F$12=Parameters!$E$16)*Parameters!$I$12*ISNUMBER(W13))>0,((Parameters!$F$5=Parameters!$E$16)*Parameters!$I$5*ISNUMBER(P13)+(Parameters!$F$6=Parameters!$E$16)*Parameters!$I$6*ISNUMBER(Q13)+(Parameters!$F$7=Parameters!$E$16)*Parameters!$I$7*ISNUMBER(R13)+(Parameters!$F$8=Parameters!$E$16)*Parameters!$I$8*ISNUMBER(S13)+(Parameters!$F$9=Parameters!$E$16)*Parameters!$I$9*ISNUMBER(T13)+(Parameters!$F$10=Parameters!$E$16)*Parameters!$I$10*ISNUMBER(U13)+(Parameters!$F$11=Parameters!$E$16)*Parameters!$I$11*ISNUMBER(V13)+(Parameters!$F$12=Parameters!$E$16)*Parameters!$I$12*ISNUMBER(W13))/((Parameters!$F$5=Parameters!$E$16)*Parameters!$I$5*1+(Parameters!$F$6=Parameters!$E$16)*Parameters!$I$6*1+(Parameters!$F$7=Parameters!$E$16)*Parameters!$I$7*1+(Parameters!$F$8=Parameters!$E$16)*Parameters!$I$8*1+(Parameters!$F$9=Parameters!$E$16)*Parameters!$I$9*1+(Parameters!$F$10=Parameters!$E$16)*Parameters!$I$10*1+(Parameters!$F$11=Parameters!$E$16)*Parameters!$I$11*X13+(Parameters!$F$12=Parameters!$E$16)*Parameters!$I$12*Y13)>=Parameters!$B$36),((Parameters!$F$5=Parameters!$E$16)*Parameters!$I$5*N(P13)+(Parameters!$F$6=Parameters!$E$16)*Parameters!$I$6*N(Q13)+(Parameters!$F$7=Parameters!$E$16)*Parameters!$I$7*N(R13)+(Parameters!$F$8=Parameters!$E$16)*Parameters!$I$8*N(S13)+(Parameters!$F$9=Parameters!$E$16)*Parameters!$I$9*N(T13)+(Parameters!$F$10=Parameters!$E$16)*Parameters!$I$10*N(U13)+(Parameters!$F$11=Parameters!$E$16)*Parameters!$I$11*N(V13)+(Parameters!$F$12=Parameters!$E$16)*Parameters!$I$12*N(W13))/((Parameters!$F$5=Parameters!$E$16)*Parameters!$I$5*ISNUMBER(P13)+(Parameters!$F$6=Parameters!$E$16)*Parameters!$I$6*ISNUMBER(Q13)+(Parameters!$F$7=Parameters!$E$16)*Parameters!$I$7*ISNUMBER(R13)+(Parameters!$F$8=Parameters!$E$16)*Parameters!$I$8*ISNUMBER(S13)+(Parameters!$F$9=Parameters!$E$16)*Parameters!$I$9*ISNUMBER(T13)+(Parameters!$F$10=Parameters!$E$16)*Parameters!$I$10*ISNUMBER(U13)+(Parameters!$F$11=Parameters!$E$16)*Parameters!$I$11*ISNUMBER(V13)+(Parameters!$F$12=Parameters!$E$16)*Parameters!$I$12*ISNUMBER(W13)),"")) -> 0.8 | AB13: =IF(((Parameters!$F$5=Parameters!$E$17)*Parameters!$I$5*1+(Parameters!$F$6=Parameters!$E$17)*Parameters!$I$6*1+(Parameters!$F$7=Parameters!$E$17)*Parameters!$I$7*1+(Parameters!$F$8=Parameters!$E$17)*Parameters!$I$8*1+(Parameters!$F$9=Parameters!$E$17)*Parameters!$I$9*1+(Parameters!$F$10=Parameters!$E$17)*Parameters!$I$10*1+(Parameters!$F$11=Parameters!$E$17)*Parameters!$I$11*X13+(Parameters!$F$12=Parameters!$E$17)*Parameters!$I$12*Y13)=0,"",IF(AND(((Parameters!$F$5=Parameters!$E$17)*Parameters!$I$5*ISNUMBER(P13)+(Parameters!$F$6=Parameters!$E$17)*Parameters!$I$6*ISNUMBER(Q13)+(Parameters!$F$7=Parameters!$E$17)*Parameters!$I$7*ISNUMBER(R13)+(Parameters!$F$8=Parameters!$E$17)*Parameters!$I$8*ISNUMBER(S13)+(Parameters!$F$9=Parameters!$E$17)*Parameters!$I$9*ISNUMBER(T13)+(Parameters!$F$10=Parameters!$E$17)*Parameters!$I$10*ISNUMBER(U13)+(Parameters!$F$11=Parameters!$E$17)*Parameters!$I$11*ISNUMBER(V13)+(Parameters!$F$12=Parameters!$E$17)*Parameters!$I$12*ISNUMBER(W13))>0,((Parameters!$F$5=Parameters!$E$17)*Parameters!$I$5*ISNUMBER(P13)+(Parameters!$F$6=Parameters!$E$17)*Parameters!$I$6*ISNUMBER(Q13)+(Parameters!$F$7=Parameters!$E$17)*Parameters!$I$7*ISNUMBER(R13)+(Parameters!$F$8=Parameters!$E$17)*Parameters!$I$8*ISNUMBER(S13)+(Parameters!$F$9=Parameters!$E$17)*Parameters!$I$9*ISNUMBER(T13)+(Parameters!$F$10=Parameters!$E$17)*Parameters!$I$10*ISNUMBER(U13)+(Parameters!$F$11=Parameters!$E$17)*Parameters!$I$11*ISNUMBER(V13)+(Parameters!$F$12=Parameters!$E$17)*Parameters!$I$12*ISNUMBER(W13))/((Parameters!$F$5=Parameters!$E$17)*Parameters!$I$5*1+(Parameters!$F$6=Parameters!$E$17)*Parameters!$I$6*1+(Parameters!$F$7=Parameters!$E$17)*Parameters!$I$7*1+(Parameters!$F$8=Parameters!$E$17)*Parameters!$I$8*1+(Parameters!$F$9=Parameters!$E$17)*Parameters!$I$9*1+(Parameters!$F$10=Parameters!$E$17)*Parameters!$I$10*1+(Parameters!$F$11=Parameters!$E$17)*Parameters!$I$11*X13+(Parameters!$F$12=Parameters!$E$17)*Parameters!$I$12*Y13)>=Parameters!$B$36),((Parameters!$F$5=Parameters!$E$17)*Parameters!$I$5*N(P13)+(Parameters!$F$6=Parameters!$E$17)*Parameters!$I$6*N(Q13)+(Parameters!$F$7=Parameters!$E$17)*Parameters!$I$7*N(R13)+(Parameters!$F$8=Parameters!$E$17)*Parameters!$I$8*N(S13)+(Parameters!$F$9=Parameters!$E$17)*Parameters!$I$9*N(T13)+(Parameters!$F$10=Parameters!$E$17)*Parameters!$I$10*N(U13)+(Parameters!$F$11=Parameters!$E$17)*Parameters!$I$11*N(V13)+(Parameters!$F$12=Parameters!$E$17)*Parameters!$I$12*N(W13))/((Parameters!$F$5=Parameters!$E$17)*Parameters!$I$5*ISNUMBER(P13)+(Parameters!$F$6=Parameters!$E$17)*Parameters!$I$6*ISNUMBER(Q13)+(Parameters!$F$7=Parameters!$E$17)*Parameters!$I$7*ISNUMBER(R13)+(Parameters!$F$8=Parameters!$E$17)*Parameters!$I$8*ISNUMBER(S13)+(Parameters!$F$9=Parameters!$E$17)*Parameters!$I$9*ISNUMBER(T13)+(Parameters!$F$10=Parameters!$E$17)*Parameters!$I$10*ISNUMBER(U13)+(Parameters!$F$11=Parameters!$E$17)*Parameters!$I$11*ISNUMBER(V13)+(Parameters!$F$12=Parameters!$E$17)*Parameters!$I$12*ISNUMBER(W13)),"")) -> 0 | AC13: =Parameters!$I$5*ISNUMBER(P13)+Parameters!$I$6*ISNUMBER(Q13)+Parameters!$I$7*ISNUMBER(R13)+Parameters!$I$8*ISNUMBER(S13)+Parameters!$I$9*ISNUMBER(T13)+Parameters!$I$10*ISNUMBER(U13)+Parameters!$I$11*ISNUMBER(V13)+Parameters!$I$12*ISNUMBER(W13) -> 85 | AD13: =Parameters!$I$5*1+Parameters!$I$6*1+Parameters!$I$7*1+Parameters!$I$8*1+Parameters!$I$9*1+Parameters!$I$10*1+Parameters!$I$11*X13+Parameters!$I$12*Y13 -> 85 | AE13: =IF(AD13=0,"",AC13/AD13) -> 1 | AF13: =IF(ISNUMBER(Z13),"M","")&IF(ISNUMBER(AA13),"I","")&IF(ISNUMBER(AB13),"O","") -> MIO | AG13: =IF(AND(ISNUMBER(AE13),ISNUMBER(Z13)+ISNUMBER(AA13)+ISNUMBER(AB13)>=Parameters!$B$37),IF(AE13>=Parameters!$B$35,100*(Parameters!$F$15*N(Z13)+Parameters!$F$16*N(AA13)+Parameters!$F$17*N(AB13))/(Parameters!$F$15*ISNUMBER(Z13)+Parameters!$F$16*ISNUMBER(AA13)+Parameters!$F$17*ISNUMBER(AB13)),""),"") -> 73.333333 | AH13: =IF(ISNUMBER(AG13),RANK(AG13,$AG$2:$AG$113),"") -> 96
A14: Biodiversity Heritage Library | B14: BHL Consortium | C14: Digital library, collection or exhibit platform | Open scholarly dataset | Repository service | D14: Actual system proven in operational environment | E14: Actively Maintained | F14: 2007-01-01 | G14: BHL’s fiscal sponsor is the Council on Library and Information Resources (CLIR). | H14: 1 | I14: FALSE | J14: Not applicable | L14: Fiscal sponsorship (non-profit) | M14: Contributions | N14: 1-5 | P14: =IFERROR(IF(ISNUMBER(INDEX(Parameters!$B$5:$B$23,MATCH(D14,Parameters!$A$5:$A$23,0))),INDEX(Parameters!$B$5:$B$23,MATCH(D14,Parameters!$A$5:$A$23,0)),""),"") -> 1 | Q14: =IFERROR(IF(ISNUMBER(INDEX(Parameters!$B$5:$B$23,MATCH(E14,Parameters!$A$5:$A$23,0))),INDEX(Parameters!$B$5:$B$23,MATCH(E14,Parameters!$A$5:$A$23,0)),""),"") -> 1 | R14: =IF(F14="","",IFERROR(MIN(Parameters!$B$33,MAX(0,Parameters!$B$32-VALUE(LEFT(F14,4))))/Parameters!$B$33,"")) -> 1 | S14: =IF(ISNUMBER(H14),H14,IF(G14="",IF(ISNUMBER(Parameters!$B$34),Parameters!$B$34,""),"")) -> 1 | T14: =IFERROR(IF(ISNUMBER(INDEX(Parameters!$B$5:$B$23,MATCH(I14,Parameters!$A$5:$A$23,0))),INDEX(Parameters!$B$5:$B$23,MATCH(I14,Parameters!$A$5:$A$23,0)),""),"") -> 0 | U14: =IFERROR(IF(ISNUMBER(INDEX(Parameters!$B$5:$B$23,MATCH(L14,Parameters!$A$5:$A$23,0))),INDEX(Parameters!$B$5:$B$23,MATCH(L14,Parameters!$A$5:$A$23,0)),""),"") -> 1 | V14: =IFERROR(IF(ISNUMBER(INDEX(Parameters!$B$5:$B$23,MATCH(J14,Parameters!$A$5:$A$23,0))),INDEX(Parameters!$B$5:$B$23,MATCH(J14,Parameters!$A$5:$A$23,0)),""),"") | W14: =IF(K14<>"",1,IF(COUNTIF(Parameters!$A$27:$A$28,J14)>0,0,"")) | X14: =IF(J14="Not applicable",0,1) -> 0 | Y14: =IF(OR(K14<>"",COUNTIF(Parameters!$A$27:$A$28,J14)>0),1,0) -> 0 | Z14: =IF(((Parameters!$F$5=Parameters!$E$15)*Parameters!$I$5*1+(Parameters!$F$6=Parameters!$E$15)*Parameters!$I$6*1+(Parameters!$F$7=Parameters!$E$15)*Parameters!$I$7*1+(Parameters!$F$8=Parameters!$E$15)*Parameters!$I$8*1+(Parameters!$F$9=Parameters!$E$15)*Parameters!$I$9*1+(Parameters!$F$10=Parameters!$E$15)*Parameters!$I$10*1+(Parameters!$F$11=Parameters!$E$15)*Parameters!$I$11*X14+(Parameters!$F$12=Parameters!$E$15)*Parameters!$I$12*Y14)=0,"",IF(AND(((Parameters!$F$5=Parameters!$E$15)*Parameters!$I$5*ISNUMBER(P14)+(Parameters!$F$6=Parameters!$E$15)*Parameters!$I$6*ISNUMBER(Q14)+(Parameters!$F$7=Parameters!$E$15)*Parameters!$I$7*ISNUMBER(R14)+(Parameters!$F$8=Parameters!$E$15)*Parameters!$I$8*ISNUMBER(S14)+(Parameters!$F$9=Parameters!$E$15)*Parameters!$I$9*ISNUMBER(T14)+(Parameters!$F$10=Parameters!$E$15)*Parameters!$I$10*ISNUMBER(U14)+(Parameters!$F$11=Parameters!$E$15)*Parameters!$I$11*ISNUMBER(V14)+(Parameters!$F$12=Parameters!$E$15)*Parameters!$I$12*ISNUMBER(W14))>0,((Parameters!$F$5=Parameters!$E$15)*Parameters!$I$5*ISNUMBER(P14)+(Parameters!$F$6=Parameters!$E$15)*Parameters!$I$6*ISNUMBER(Q14)+(Parameters!$F$7=Parameters!$E$15)*Parameters!$I$7*ISNUMBER(R14)+(Parameters!$F$8=Parameters!$E$15)*Parameters!$I$8*ISNUMBER(S14)+(Parameters!$F$9=Parameters!$E$15)*Parameters!$I$9*ISNUMBER(T14)+(Parameters!$F$10=Parameters!$E$15)*Parameters!$I$10*ISNUMBER(U14)+(Parameters!$F$11=Parameters!$E$15)*Parameters!$I$11*ISNUMBER(V14)+(Parameters!$F$12=Parameters!$E$15)*Parameters!$I$12*ISNUMBER(W14))/((Parameters!$F$5=Parameters!$E$15)*Parameters!$I$5*1+(Parameters!$F$6=Parameters!$E$15)*Parameters!$I$6*1+(Parameters!$F$7=Parameters!$E$15)*Parameters!$I$7*1+(Parameters!$F$8=Parameters!$E$15)*Parameters!$I$8*1+(Parameters!$F$9=Parameters!$E$15)*Parameters!$I$9*1+(Parameters!$F$10=Parameters!$E$15)*Parameters!$I$10*1+(Parameters!$F$11=Parameters!$E$15)*Parameters!$I$11*X14+(Parameters!$F$12=Parameters!$E$15)*Parameters!$I$12*Y14)>=Parameters!$B$36),((Parameters!$F$5=Parameters!$E$15)*Parameters!$I$5*N(P14)+(Parameters!$F$6=Parameters!$E$15)*Parameters!$I$6*N(Q14)+(Parameters!$F$7=Parameters!$E$15)*Parameters!$I$7*N(R14)+(Parameters!$F$8=Parameters!$E$15)*Parameters!$I$8*N(S14)+(Parameters!$F$9=Parameters!$E$15)*Parameters!$I$9*N(T14)+(Parameters!$F$10=Parameters!$E$15)*Parameters!$I$10*N(U14)+(Parameters!$F$11=Parameters!$E$15)*Parameters!$I$11*N(V14)+(Parameters!$F$12=Parameters!$E$15)*Parameters!$I$12*N(W14))/((Parameters!$F$5=Parameters!$E$15)*Parameters!$I$5*ISNUMBER(P14)+(Parameters!$F$6=Parameters!$E$15)*Parameters!$I$6*ISNUMBER(Q14)+(Parameters!$F$7=Parameters!$E$15)*Parameters!$I$7*ISNUMBER(R14)+(Parameters!$F$8=Parameters!$E$15)*Parameters!$I$8*ISNUMBER(S14)+(Parameters!$F$9=Parameters!$E$15)*Parameters!$I$9*ISNUMBER(T14)+(Parameters!$F$10=Parameters!$E$15)*Parameters!$I$10*ISNUMBER(U14)+(Parameters!$F$11=Parameters!$E$15)*Parameters!$I$11*ISNUMBER(V14)+(Parameters!$F$12=Parameters!$E$15)*Parameters!$I$12*ISNUMBER(W14)),"")) -> 1 | AA14: =IF(((Parameters!$F$5=Parameters!$E$16)*Parameters!$I$5*1+(Parameters!$F$6=Parameters!$E$16)*Parameters!$I$6*1+(Parameters!$F$7=Parameters!$E$16)*Parameters!$I$7*1+(Parameters!$F$8=Parameters!$E$16)*Parameters!$I$8*1+(Parameters!$F$9=Parameters!$E$16)*Parameters!$I$9*1+(Parameters!$F$10=Parameters!$E$16)*Parameters!$I$10*1+(Parameters!$F$11=Parameters!$E$16)*Parameters!$I$11*X14+(Parameters!$F$12=Parameters!$E$16)*Parameters!$I$12*Y14)=0,"",IF(AND(((Parameters!$F$5=Parameters!$E$16)*Parameters!$I$5*ISNUMBER(P14)+(Parameters!$F$6=Parameters!$E$16)*Parameters!$I$6*ISNUMBER(Q14)+(Parameters!$F$7=Parameters!$E$16)*Parameters!$I$7*ISNUMBER(R14)+(Parameters!$F$8=Parameters!$E$16)*Parameters!$I$8*ISNUMBER(S14)+(Parameters!$F$9=Parameters!$E$16)*Parameters!$I$9*ISNUMBER(T14)+(Parameters!$F$10=Parameters!$E$16)*Parameters!$I$10*ISNUMBER(U14)+(Parameters!$F$11=Parameters!$E$16)*Parameters!$I$11*ISNUMBER(V14)+(Parameters!$F$12=Parameters!$E$16)*Parameters!$I$12*ISNUMBER(W14))>0,((Parameters!$F$5=Parameters!$E$16)*Parameters!$I$5*ISNUMBER(P14)+(Parameters!$F$6=Parameters!$E$16)*Parameters!$I$6*ISNUMBER(Q14)+(Parameters!$F$7=Parameters!$E$16)*Parameters!$I$7*ISNUMBER(R14)+(Parameters!$F$8=Parameters!$E$16)*Parameters!$I$8*ISNUMBER(S14)+(Parameters!$F$9=Parameters!$E$16)*Parameters!$I$9*ISNUMBER(T14)+(Parameters!$F$10=Parameters!$E$16)*Parameters!$I$10*ISNUMBER(U14)+(Parameters!$F$11=Parameters!$E$16)*Parameters!$I$11*ISNUMBER(V14)+(Parameters!$F$12=Parameters!$E$16)*Parameters!$I$12*ISNUMBER(W14))/((Parameters!$F$5=Parameters!$E$16)*Parameters!$I$5*1+(Parameters!$F$6=Parameters!$E$16)*Parameters!$I$6*1+(Parameters!$F$7=Parameters!$E$16)*Parameters!$I$7*1+(Parameters!$F$8=Parameters!$E$16)*Parameters!$I$8*1+(Parameters!$F$9=Parameters!$E$16)*Parameters!$I$9*1+(Parameters!$F$10=Parameters!$E$16)*Parameters!$I$10*1+(Parameters!$F$11=Parameters!$E$16)*Parameters!$I$11*X14+(Parameters!$F$12=Parameters!$E$16)*Parameters!$I$12*Y14)>=Parameters!$B$36),((Parameters!$F$5=Parameters!$E$16)*Parameters!$I$5*N(P14)+(Parameters!$F$6=Parameters!$E$16)*Parameters!$I$6*N(Q14)+(Parameters!$F$7=Parameters!$E$16)*Parameters!$I$7*N(R14)+(Parameters!$F$8=Parameters!$E$16)*Parameters!$I$8*N(S14)+(Parameters!$F$9=Parameters!$E$16)*Parameters!$I$9*N(T14)+(Parameters!$F$10=Parameters!$E$16)*Parameters!$I$10*N(U14)+(Parameters!$F$11=Parameters!$E$16)*Parameters!$I$11*N(V14)+(Parameters!$F$12=Parameters!$E$16)*Parameters!$I$12*N(W14))/((Parameters!$F$5=Parameters!$E$16)*Parameters!$I$5*ISNUMBER(P14)+(Parameters!$F$6=Parameters!$E$16)*Parameters!$I$6*ISNUMBER(Q14)+(Parameters!$F$7=Parameters!$E$16)*Parameters!$I$7*ISNUMBER(R14)+(Parameters!$F$8=Parameters!$E$16)*Parameters!$I$8*ISNUMBER(S14)+(Parameters!$F$9=Parameters!$E$16)*Parameters!$I$9*ISNUMBER(T14)+(Parameters!$F$10=Parameters!$E$16)*Parameters!$I$10*ISNUMBER(U14)+(Parameters!$F$11=Parameters!$E$16)*Parameters!$I$11*ISNUMBER(V14)+(Parameters!$F$12=Parameters!$E$16)*Parameters!$I$12*ISNUMBER(W14)),"")) -> 0.8 | AB14: =IF(((Parameters!$F$5=Parameters!$E$17)*Parameters!$I$5*1+(Parameters!$F$6=Parameters!$E$17)*Parameters!$I$6*1+(Parameters!$F$7=Parameters!$E$17)*Parameters!$I$7*1+(Parameters!$F$8=Parameters!$E$17)*Parameters!$I$8*1+(Parameters!$F$9=Parameters!$E$17)*Parameters!$I$9*1+(Parameters!$F$10=Parameters!$E$17)*Parameters!$I$10*1+(Parameters!$F$11=Parameters!$E$17)*Parameters!$I$11*X14+(Parameters!$F$12=Parameters!$E$17)*Parameters!$I$12*Y14)=0,"",IF(AND(((Parameters!$F$5=Parameters!$E$17)*Parameters!$I$5*ISNUMBER(P14)+(Parameters!$F$6=Parameters!$E$17)*Parameters!$I$6*ISNUMBER(Q14)+(Parameters!$F$7=Parameters!$E$17)*Parameters!$I$7*ISNUMBER(R14)+(Parameters!$F$8=Parameters!$E$17)*Parameters!$I$8*ISNUMBER(S14)+(Parameters!$F$9=Parameters!$E$17)*Parameters!$I$9*ISNUMBER(T14)+(Parameters!$F$10=Parameters!$E$17)*Parameters!$I$10*ISNUMBER(U14)+(Parameters!$F$11=Parameters!$E$17)*Parameters!$I$11*ISNUMBER(V14)+(Parameters!$F$12=Parameters!$E$17)*Parameters!$I$12*ISNUMBER(W14))>0,((Parameters!$F$5=Parameters!$E$17)*Parameters!$I$5*ISNUMBER(P14)+(Parameters!$F$6=Parameters!$E$17)*Parameters!$I$6*ISNUMBER(Q14)+(Parameters!$F$7=Parameters!$E$17)*Parameters!$I$7*ISNUMBER(R14)+(Parameters!$F$8=Parameters!$E$17)*Parameters!$I$8*ISNUMBER(S14)+(Parameters!$F$9=Parameters!$E$17)*Parameters!$I$9*ISNUMBER(T14)+(Parameters!$F$10=Parameters!$E$17)*Parameters!$I$10*ISNUMBER(U14)+(Parameters!$F$11=Parameters!$E$17)*Parameters!$I$11*ISNUMBER(V14)+(Parameters!$F$12=Parameters!$E$17)*Parameters!$I$12*ISNUMBER(W14))/((Parameters!$F$5=Parameters!$E$17)*Parameters!$I$5*1+(Parameters!$F$6=Parameters!$E$17)*Parameters!$I$6*1+(Parameters!$F$7=Parameters!$E$17)*Parameters!$I$7*1+(Parameters!$F$8=Parameters!$E$17)*Parameters!$I$8*1+(Parameters!$F$9=Parameters!$E$17)*Parameters!$I$9*1+(Parameters!$F$10=Parameters!$E$17)*Parameters!$I$10*1+(Parameters!$F$11=Parameters!$E$17)*Parameters!$I$11*X14+(Parameters!$F$12=Parameters!$E$17)*Parameters!$I$12*Y14)>=Parameters!$B$36),((Parameters!$F$5=Parameters!$E$17)*Parameters!$I$5*N(P14)+(Parameters!$F$6=Parameters!$E$17)*Parameters!$I$6*N(Q14)+(Parameters!$F$7=Parameters!$E$17)*Parameters!$I$7*N(R14)+(Parameters!$F$8=Parameters!$E$17)*Parameters!$I$8*N(S14)+(Parameters!$F$9=Parameters!$E$17)*Parameters!$I$9*N(T14)+(Parameters!$F$10=Parameters!$E$17)*Parameters!$I$10*N(U14)+(Parameters!$F$11=Parameters!$E$17)*Parameters!$I$11*N(V14)+(Parameters!$F$12=Parameters!$E$17)*Parameters!$I$12*N(W14))/((Parameters!$F$5=Parameters!$E$17)*Parameters!$I$5*ISNUMBER(P14)+(Parameters!$F$6=Parameters!$E$17)*Parameters!$I$6*ISNUMBER(Q14)+(Parameters!$F$7=Parameters!$E$17)*Parameters!$I$7*ISNUMBER(R14)+(Parameters!$F$8=Parameters!$E$17)*Parameters!$I$8*ISNUMBER(S14)+(Parameters!$F$9=Parameters!$E$17)*Parameters!$I$9*ISNUMBER(T14)+(Parameters!$F$10=Parameters!$E$17)*Parameters!$I$10*ISNUMBER(U14)+(Parameters!$F$11=Parameters!$E$17)*Parameters!$I$11*ISNUMBER(V14)+(Parameters!$F$12=Parameters!$E$17)*Parameters!$I$12*ISNUMBER(W14)),"")) | AC14: =Parameters!$I$5*ISNUMBER(P14)+Parameters!$I$6*ISNUMBER(Q14)+Parameters!$I$7*ISNUMBER(R14)+Parameters!$I$8*ISNUMBER(S14)+Parameters!$I$9*ISNUMBER(T14)+Parameters!$I$10*ISNUMBER(U14)+Parameters!$I$11*ISNUMBER(V14)+Parameters!$I$12*ISNUMBER(W14) -> 75 | AD14: =Parameters!$I$5*1+Parameters!$I$6*1+Parameters!$I$7*1+Parameters!$I$8*1+Parameters!$I$9*1+Parameters!$I$10*1+Parameters!$I$11*X14+Parameters!$I$12*Y14 -> 75 | AE14: =IF(AD14=0,"",AC14/AD14) -> 1 | AF14: =IF(ISNUMBER(Z14),"M","")&IF(ISNUMBER(AA14),"I","")&IF(ISNUMBER(AB14),"O","") -> MI | AG14: =IF(AND(ISNUMBER(AE14),ISNUMBER(Z14)+ISNUMBER(AA14)+ISNUMBER(AB14)>=Parameters!$B$37),IF(AE14>=Parameters!$B$35,100*(Parameters!$F$15*N(Z14)+Parameters!$F$16*N(AA14)+Parameters!$F$17*N(AB14))/(Parameters!$F$15*ISNUMBER(Z14)+Parameters!$F$16*ISNUMBER(AA14)+Parameters!$F$17*ISNUMBER(AB14)),""),"") -> 92.5 | AH14: =IF(ISNUMBER(AG14),RANK(AG14,$AG$2:$AG$113),"") -> 14
A15: bioRxiv | B15: Cold Spring Harbor Laboratory | C15: Repository service | D15: Actual system proven in operational environment | E15: Actively Maintained | F15: 2013-01-01 | I15: FALSE | J15: Not applicable | L15: Fiscal sponsorship (non-profit) | M15: Contributions | P15: =IFERROR(IF(ISNUMBER(INDEX(Parameters!$B$5:$B$23,MATCH(D15,Parameters!$A$5:$A$23,0))),INDEX(Parameters!$B$5:$B$23,MATCH(D15,Parameters!$A$5:$A$23,0)),""),"") -> 1 | Q15: =IFERROR(IF(ISNUMBER(INDEX(Parameters!$B$5:$B$23,MATCH(E15,Parameters!$A$5:$A$23,0))),INDEX(Parameters!$B$5:$B$23,MATCH(E15,Parameters!$A$5:$A$23,0)),""),"") -> 1 | R15: =IF(F15="","",IFERROR(MIN(Parameters!$B$33,MAX(0,Parameters!$B$32-VALUE(LEFT(F15,4))))/Parameters!$B$33,"")) -> 0.86666667 | S15: =IF(ISNUMBER(H15),H15,IF(G15="",IF(ISNUMBER(Parameters!$B$34),Parameters!$B$34,""),"")) | T15: =IFERROR(IF(ISNUMBER(INDEX(Parameters!$B$5:$B$23,MATCH(I15,Parameters!$A$5:$A$23,0))),INDEX(Parameters!$B$5:$B$23,MATCH(I15,Parameters!$A$5:$A$23,0)),""),"") -> 0 | U15: =IFERROR(IF(ISNUMBER(INDEX(Parameters!$B$5:$B$23,MATCH(L15,Parameters!$A$5:$A$23,0))),INDEX(Parameters!$B$5:$B$23,MATCH(L15,Parameters!$A$5:$A$23,0)),""),"") -> 1 | V15: =IFERROR(IF(ISNUMBER(INDEX(Parameters!$B$5:$B$23,MATCH(J15,Parameters!$A$5:$A$23,0))),INDEX(Parameters!$B$5:$B$23,MATCH(J15,Parameters!$A$5:$A$23,0)),""),"") | W15: =IF(K15<>"",1,IF(COUNTIF(Parameters!$A$27:$A$28,J15)>0,0,"")) | X15: =IF(J15="Not applicable",0,1) -> 0 | Y15: =IF(OR(K15<>"",COUNTIF(Parameters!$A$27:$A$28,J15)>0),1,0) -> 0 | Z15: =IF(((Parameters!$F$5=Parameters!$E$15)*Parameters!$I$5*1+(Parameters!$F$6=Parameters!$E$15)*Parameters!$I$6*1+(Parameters!$F$7=Parameters!$E$15)*Parameters!$I$7*1+(Parameters!$F$8=Parameters!$E$15)*Parameters!$I$8*1+(Parameters!$F$9=Parameters!$E$15)*Parameters!$I$9*1+(Parameters!$F$10=Parameters!$E$15)*Parameters!$I$10*1+(Parameters!$F$11=Parameters!$E$15)*Parameters!$I$11*X15+(Parameters!$F$12=Parameters!$E$15)*Parameters!$I$12*Y15)=0,"",IF(AND(((Parameters!$F$5=Parameters!$E$15)*Parameters!$I$5*ISNUMBER(P15)+(Parameters!$F$6=Parameters!$E$15)*Parameters!$I$6*ISNUMBER(Q15)+(Parameters!$F$7=Parameters!$E$15)*Parameters!$I$7*ISNUMBER(R15)+(Parameters!$F$8=Parameters!$E$15)*Parameters!$I$8*ISNUMBER(S15)+(Parameters!$F$9=Parameters!$E$15)*Parameters!$I$9*ISNUMBER(T15)+(Parameters!$F$10=Parameters!$E$15)*Parameters!$I$10*ISNUMBER(U15)+(Parameters!$F$11=Parameters!$E$15)*Parameters!$I$11*ISNUMBER(V15)+(Parameters!$F$12=Parameters!$E$15)*Parameters!$I$12*ISNUMBER(W15))>0,((Parameters!$F$5=Parameters!$E$15)*Parameters!$I$5*ISNUMBER(P15)+(Parameters!$F$6=Parameters!$E$15)*Parameters!$I$6*ISNUMBER(Q15)+(Parameters!$F$7=Parameters!$E$15)*Parameters!$I$7*ISNUMBER(R15)+(Parameters!$F$8=Parameters!$E$15)*Parameters!$I$8*ISNUMBER(S15)+(Parameters!$F$9=Parameters!$E$15)*Parameters!$I$9*ISNUMBER(T15)+(Parameters!$F$10=Parameters!$E$15)*Parameters!$I$10*ISNUMBER(U15)+(Parameters!$F$11=Parameters!$E$15)*Parameters!$I$11*ISNUMBER(V15)+(Parameters!$F$12=Parameters!$E$15)*Parameters!$I$12*ISNUMBER(W15))/((Parameters!$F$5=Parameters!$E$15)*Parameters!$I$5*1+(Parameters!$F$6=Parameters!$E$15)*Parameters!$I$6*1+(Parameters!$F$7=Parameters!$E$15)*Parameters!$I$7*1+(Parameters!$F$8=Parameters!$E$15)*Parameters!$I$8*1+(Parameters!$F$9=Parameters!$E$15)*Parameters!$I$9*1+(Parameters!$F$10=Parameters!$E$15)*Parameters!$I$10*1+(Parameters!$F$11=Parameters!$E$15)*Parameters!$I$11*X15+(Parameters!$F$12=Parameters!$E$15)*Parameters!$I$12*Y15)>=Parameters!$B$36),((Parameters!$F$5=Parameters!$E$15)*Parameters!$I$5*N(P15)+(Parameters!$F$6=Parameters!$E$15)*Parameters!$I$6*N(Q15)+(Parameters!$F$7=Parameters!$E$15)*Parameters!$I$7*N(R15)+(Parameters!$F$8=Parameters!$E$15)*Parameters!$I$8*N(S15)+(Parameters!$F$9=Parameters!$E$15)*Parameters!$I$9*N(T15)+(Parameters!$F$10=Parameters!$E$15)*Parameters!$I$10*N(U15)+(Parameters!$F$11=Parameters!$E$15)*Parameters!$I$11*N(V15)+(Parameters!$F$12=Parameters!$E$15)*Parameters!$I$12*N(W15))/((Parameters!$F$5=Parameters!$E$15)*Parameters!$I$5*ISNUMBER(P15)+(Parameters!$F$6=Parameters!$E$15)*Parameters!$I$6*ISNUMBER(Q15)+(Parameters!$F$7=Parameters!$E$15)*Parameters!$I$7*ISNUMBER(R15)+(Parameters!$F$8=Parameters!$E$15)*Parameters!$I$8*ISNUMBER(S15)+(Parameters!$F$9=Parameters!$E$15)*Parameters!$I$9*ISNUMBER(T15)+(Parameters!$F$10=Parameters!$E$15)*Parameters!$I$10*ISNUMBER(U15)+(Parameters!$F$11=Parameters!$E$15)*Parameters!$I$11*ISNUMBER(V15)+(Parameters!$F$12=Parameters!$E$15)*Parameters!$I$12*ISNUMBER(W15)),"")) -> 0.98666667 | AA15: =IF(((Parameters!$F$5=Parameters!$E$16)*Parameters!$I$5*1+(Parameters!$F$6=Parameters!$E$16)*Parameters!$I$6*1+(Parameters!$F$7=Parameters!$E$16)*Parameters!$I$7*1+(Parameters!$F$8=Parameters!$E$16)*Parameters!$I$8*1+(Parameters!$F$9=Parameters!$E$16)*Parameters!$I$9*1+(Parameters!$F$10=Parameters!$E$16)*Parameters!$I$10*1+(Parameters!$F$11=Parameters!$E$16)*Parameters!$I$11*X15+(Parameters!$F$12=Parameters!$E$16)*Parameters!$I$12*Y15)=0,"",IF(AND(((Parameters!$F$5=Parameters!$E$16)*Parameters!$I$5*ISNUMBER(P15)+(Parameters!$F$6=Parameters!$E$16)*Parameters!$I$6*ISNUMBER(Q15)+(Parameters!$F$7=Parameters!$E$16)*Parameters!$I$7*ISNUMBER(R15)+(Parameters!$F$8=Parameters!$E$16)*Parameters!$I$8*ISNUMBER(S15)+(Parameters!$F$9=Parameters!$E$16)*Parameters!$I$9*ISNUMBER(T15)+(Parameters!$F$10=Parameters!$E$16)*Parameters!$I$10*ISNUMBER(U15)+(Parameters!$F$11=Parameters!$E$16)*Parameters!$I$11*ISNUMBER(V15)+(Parameters!$F$12=Parameters!$E$16)*Parameters!$I$12*ISNUMBER(W15))>0,((Parameters!$F$5=Parameters!$E$16)*Parameters!$I$5*ISNUMBER(P15)+(Parameters!$F$6=Parameters!$E$16)*Parameters!$I$6*ISNUMBER(Q15)+(Parameters!$F$7=Parameters!$E$16)*Parameters!$I$7*ISNUMBER(R15)+(Parameters!$F$8=Parameters!$E$16)*Parameters!$I$8*ISNUMBER(S15)+(Parameters!$F$9=Parameters!$E$16)*Parameters!$I$9*ISNUMBER(T15)+(Parameters!$F$10=Parameters!$E$16)*Parameters!$I$10*ISNUMBER(U15)+(Parameters!$F$11=Parameters!$E$16)*Parameters!$I$11*ISNUMBER(V15)+(Parameters!$F$12=Parameters!$E$16)*Parameters!$I$12*ISNUMBER(W15))/((Parameters!$F$5=Parameters!$E$16)*Parameters!$I$5*1+(Parameters!$F$6=Parameters!$E$16)*Parameters!$I$6*1+(Parameters!$F$7=Parameters!$E$16)*Parameters!$I$7*1+(Parameters!$F$8=Parameters!$E$16)*Parameters!$I$8*1+(Parameters!$F$9=Parameters!$E$16)*Parameters!$I$9*1+(Parameters!$F$10=Parameters!$E$16)*Parameters!$I$10*1+(Parameters!$F$11=Parameters!$E$16)*Parameters!$I$11*X15+(Parameters!$F$12=Parameters!$E$16)*Parameters!$I$12*Y15)>=Parameters!$B$36),((Parameters!$F$5=Parameters!$E$16)*Parameters!$I$5*N(P15)+(Parameters!$F$6=Parameters!$E$16)*Parameters!$I$6*N(Q15)+(Parameters!$F$7=Parameters!$E$16)*Parameters!$I$7*N(R15)+(Parameters!$F$8=Parameters!$E$16)*Parameters!$I$8*N(S15)+(Parameters!$F$9=Parameters!$E$16)*Parameters!$I$9*N(T15)+(Parameters!$F$10=Parameters!$E$16)*Parameters!$I$10*N(U15)+(Parameters!$F$11=Parameters!$E$16)*Parameters!$I$11*N(V15)+(Parameters!$F$12=Parameters!$E$16)*Parameters!$I$12*N(W15))/((Parameters!$F$5=Parameters!$E$16)*Parameters!$I$5*ISNUMBER(P15)+(Parameters!$F$6=Parameters!$E$16)*Parameters!$I$6*ISNUMBER(Q15)+(Parameters!$F$7=Parameters!$E$16)*Parameters!$I$7*ISNUMBER(R15)+(Parameters!$F$8=Parameters!$E$16)*Parameters!$I$8*ISNUMBER(S15)+(Parameters!$F$9=Parameters!$E$16)*Parameters!$I$9*ISNUMBER(T15)+(Parameters!$F$10=Parameters!$E$16)*Parameters!$I$10*ISNUMBER(U15)+(Parameters!$F$11=Parameters!$E$16)*Parameters!$I$11*ISNUMBER(V15)+(Parameters!$F$12=Parameters!$E$16)*Parameters!$I$12*ISNUMBER(W15)),"")) -> 0.66666667 | AB15: =IF(((Parameters!$F$5=Parameters!$E$17)*Parameters!$I$5*1+(Parameters!$F$6=Parameters!$E$17)*Parameters!$I$6*1+(Parameters!$F$7=Parameters!$E$17)*Parameters!$I$7*1+(Parameters!$F$8=Parameters!$E$17)*Parameters!$I$8*1+(Parameters!$F$9=Parameters!$E$17)*Parameters!$I$9*1+(Parameters!$F$10=Parameters!$E$17)*Parameters!$I$10*1+(Parameters!$F$11=Parameters!$E$17)*Parameters!$I$11*X15+(Parameters!$F$12=Parameters!$E$17)*Parameters!$I$12*Y15)=0,"",IF(AND(((Parameters!$F$5=Parameters!$E$17)*Parameters!$I$5*ISNUMBER(P15)+(Parameters!$F$6=Parameters!$E$17)*Parameters!$I$6*ISNUMBER(Q15)+(Parameters!$F$7=Parameters!$E$17)*Parameters!$I$7*ISNUMBER(R15)+(Parameters!$F$8=Parameters!$E$17)*Parameters!$I$8*ISNUMBER(S15)+(Parameters!$F$9=Parameters!$E$17)*Parameters!$I$9*ISNUMBER(T15)+(Parameters!$F$10=Parameters!$E$17)*Parameters!$I$10*ISNUMBER(U15)+(Parameters!$F$11=Parameters!$E$17)*Parameters!$I$11*ISNUMBER(V15)+(Parameters!$F$12=Parameters!$E$17)*Parameters!$I$12*ISNUMBER(W15))>0,((Parameters!$F$5=Parameters!$E$17)*Parameters!$I$5*ISNUMBER(P15)+(Parameters!$F$6=Parameters!$E$17)*Parameters!$I$6*ISNUMBER(Q15)+(Parameters!$F$7=Parameters!$E$17)*Parameters!$I$7*ISNUMBER(R15)+(Parameters!$F$8=Parameters!$E$17)*Parameters!$I$8*ISNUMBER(S15)+(Parameters!$F$9=Parameters!$E$17)*Parameters!$I$9*ISNUMBER(T15)+(Parameters!$F$10=Parameters!$E$17)*Parameters!$I$10*ISNUMBER(U15)+(Parameters!$F$11=Parameters!$E$17)*Parameters!$I$11*ISNUMBER(V15)+(Parameters!$F$12=Parameters!$E$17)*Parameters!$I$12*ISNUMBER(W15))/((Parameters!$F$5=Parameters!$E$17)*Parameters!$I$5*1+(Parameters!$F$6=Parameters!$E$17)*Parameters!$I$6*1+(Parameters!$F$7=Parameters!$E$17)*Parameters!$I$7*1+(Parameters!$F$8=Parameters!$E$17)*Parameters!$I$8*1+(Parameters!$F$9=Parameters!$E$17)*Parameters!$I$9*1+(Parameters!$F$10=Parameters!$E$17)*Parameters!$I$10*1+(Parameters!$F$11=Parameters!$E$17)*Parameters!$I$11*X15+(Parameters!$F$12=Parameters!$E$17)*Parameters!$I$12*Y15)>=Parameters!$B$36),((Parameters!$F$5=Parameters!$E$17)*Parameters!$I$5*N(P15)+(Parameters!$F$6=Parameters!$E$17)*Parameters!$I$6*N(Q15)+(Parameters!$F$7=Parameters!$E$17)*Parameters!$I$7*N(R15)+(Parameters!$F$8=Parameters!$E$17)*Parameters!$I$8*N(S15)+(Parameters!$F$9=Parameters!$E$17)*Parameters!$I$9*N(T15)+(Parameters!$F$10=Parameters!$E$17)*Parameters!$I$10*N(U15)+(Parameters!$F$11=Parameters!$E$17)*Parameters!$I$11*N(V15)+(Parameters!$F$12=Parameters!$E$17)*Parameters!$I$12*N(W15))/((Parameters!$F$5=Parameters!$E$17)*Parameters!$I$5*ISNUMBER(P15)+(Parameters!$F$6=Parameters!$E$17)*Parameters!$I$6*ISNUMBER(Q15)+(Parameters!$F$7=Parameters!$E$17)*Parameters!$I$7*ISNUMBER(R15)+(Parameters!$F$8=Parameters!$E$17)*Parameters!$I$8*ISNUMBER(S15)+(Parameters!$F$9=Parameters!$E$17)*Parameters!$I$9*ISNUMBER(T15)+(Parameters!$F$10=Parameters!$E$17)*Parameters!$I$10*ISNUMBER(U15)+(Parameters!$F$11=Parameters!$E$17)*Parameters!$I$11*ISNUMBER(V15)+(Parameters!$F$12=Parameters!$E$17)*Parameters!$I$12*ISNUMBER(W15)),"")) | AC15: =Parameters!$I$5*ISNUMBER(P15)+Parameters!$I$6*ISNUMBER(Q15)+Parameters!$I$7*ISNUMBER(R15)+Parameters!$I$8*ISNUMBER(S15)+Parameters!$I$9*ISNUMBER(T15)+Parameters!$I$10*ISNUMBER(U15)+Parameters!$I$11*ISNUMBER(V15)+Parameters!$I$12*ISNUMBER(W15) -> 65 | AD15: =Parameters!$I$5*1+Parameters!$I$6*1+Parameters!$I$7*1+Parameters!$I$8*1+Parameters!$I$9*1+Parameters!$I$10*1+Parameters!$I$11*X15+Parameters!$I$12*Y15 -> 75 | AE15: =IF(AD15=0,"",AC15/AD15) -> 0.86666667 | AF15: =IF(ISNUMBER(Z15),"M","")&IF(ISNUMBER(AA15),"I","")&IF(ISNUMBER(AB15),"O","") -> MI | AG15: =IF(AND(ISNUMBER(AE15),ISNUMBER(Z15)+ISNUMBER(AA15)+ISNUMBER(AB15)>=Parameters!$B$37),IF(AE15>=Parameters!$B$35,100*(Parameters!$F$15*N(Z15)+Parameters!$F$16*N(AA15)+Parameters!$F$17*N(AB15))/(Parameters!$F$15*ISNUMBER(Z15)+Parameters!$F$16*ISNUMBER(AA15)+Parameters!$F$17*ISNUMBER(AB15)),""),"") -> 86.666667 | AH15: =IF(ISNUMBER(AG15),RANK(AG15,$AG$2:$AG$113),"") -> 52
A16: BitCurator Environment | B16: BitCurator Consortium | C16: Digital preservation tool | D16: Actual system proven in operational environment | E16: Actively Maintained | F16: 2012-01-01 | G16: BitCurator Consortium is administratively hosted by the Open Library Foundation. | H16: 1 | I16: FALSE | J16: No services available | L16: Fiscal sponsorship (non-profit) | M16: Program service revenue | N16: 0 | O16: 6-10 | P16: =IFERROR(IF(ISNUMBER(INDEX(Parameters!$B$5:$B$23,MATCH(D16,Parameters!$A$5:$A$23,0))),INDEX(Parameters!$B$5:$B$23,MATCH(D16,Parameters!$A$5:$A$23,0)),""),"") -> 1 | Q16: =IFERROR(IF(ISNUMBER(INDEX(Parameters!$B$5:$B$23,MATCH(E16,Parameters!$A$5:$A$23,0))),INDEX(Parameters!$B$5:$B$23,MATCH(E16,Parameters!$A$5:$A$23,0)),""),"") -> 1 | R16: =IF(F16="","",IFERROR(MIN(Parameters!$B$33,MAX(0,Parameters!$B$32-VALUE(LEFT(F16,4))))/Parameters!$B$33,"")) -> 0.93333333 | S16: =IF(ISNUMBER(H16),H16,IF(G16="",IF(ISNUMBER(Parameters!$B$34),Parameters!$B$34,""),"")) -> 1 | T16: =IFERROR(IF(ISNUMBER(INDEX(Parameters!$B$5:$B$23,MATCH(I16,Parameters!$A$5:$A$23,0))),INDEX(Parameters!$B$5:$B$23,MATCH(I16,Parameters!$A$5:$A$23,0)),""),"") -> 0 | U16: =IFERROR(IF(ISNUMBER(INDEX(Parameters!$B$5:$B$23,MATCH(L16,Parameters!$A$5:$A$23,0))),INDEX(Parameters!$B$5:$B$23,MATCH(L16,Parameters!$A$5:$A$23,0)),""),"") -> 1 | V16: =IFERROR(IF(ISNUMBER(INDEX(Parameters!$B$5:$B$23,MATCH(J16,Parameters!$A$5:$A$23,0))),INDEX(Parameters!$B$5:$B$23,MATCH(J16,Parameters!$A$5:$A$23,0)),""),"") -> 0 | W16: =IF(K16<>"",1,IF(COUNTIF(Parameters!$A$27:$A$28,J16)>0,0,"")) | X16: =IF(J16="Not applicable",0,1) -> 1 | Y16: =IF(OR(K16<>"",COUNTIF(Parameters!$A$27:$A$28,J16)>0),1,0) -> 0 | Z16: =IF(((Parameters!$F$5=Parameters!$E$15)*Parameters!$I$5*1+(Parameters!$F$6=Parameters!$E$15)*Parameters!$I$6*1+(Parameters!$F$7=Parameters!$E$15)*Parameters!$I$7*1+(Parameters!$F$8=Parameters!$E$15)*Parameters!$I$8*1+(Parameters!$F$9=Parameters!$E$15)*Parameters!$I$9*1+(Parameters!$F$10=Parameters!$E$15)*Parameters!$I$10*1+(Parameters!$F$11=Parameters!$E$15)*Parameters!$I$11*X16+(Parameters!$F$12=Parameters!$E$15)*Parameters!$I$12*Y16)=0,"",IF(AND(((Parameters!$F$5=Parameters!$E$15)*Parameters!$I$5*ISNUMBER(P16)+(Parameters!$F$6=Parameters!$E$15)*Parameters!$I$6*ISNUMBER(Q16)+(Parameters!$F$7=Parameters!$E$15)*Parameters!$I$7*ISNUMBER(R16)+(Parameters!$F$8=Parameters!$E$15)*Parameters!$I$8*ISNUMBER(S16)+(Parameters!$F$9=Parameters!$E$15)*Parameters!$I$9*ISNUMBER(T16)+(Parameters!$F$10=Parameters!$E$15)*Parameters!$I$10*ISNUMBER(U16)+(Parameters!$F$11=Parameters!$E$15)*Parameters!$I$11*ISNUMBER(V16)+(Parameters!$F$12=Parameters!$E$15)*Parameters!$I$12*ISNUMBER(W16))>0,((Parameters!$F$5=Parameters!$E$15)*Parameters!$I$5*ISNUMBER(P16)+(Parameters!$F$6=Parameters!$E$15)*Parameters!$I$6*ISNUMBER(Q16)+(Parameters!$F$7=Parameters!$E$15)*Parameters!$I$7*ISNUMBER(R16)+(Parameters!$F$8=Parameters!$E$15)*Parameters!$I$8*ISNUMBER(S16)+(Parameters!$F$9=Parameters!$E$15)*Parameters!$I$9*ISNUMBER(T16)+(Parameters!$F$10=Parameters!$E$15)*Parameters!$I$10*ISNUMBER(U16)+(Parameters!$F$11=Parameters!$E$15)*Parameters!$I$11*ISNUMBER(V16)+(Parameters!$F$12=Parameters!$E$15)*Parameters!$I$12*ISNUMBER(W16))/((Parameters!$F$5=Parameters!$E$15)*Parameters!$I$5*1+(Parameters!$F$6=Parameters!$E$15)*Parameters!$I$6*1+(Parameters!$F$7=Parameters!$E$15)*Parameters!$I$7*1+(Parameters!$F$8=Parameters!$E$15)*Parameters!$I$8*1+(Parameters!$F$9=Parameters!$E$15)*Parameters!$I$9*1+(Parameters!$F$10=Parameters!$E$15)*Parameters!$I$10*1+(Parameters!$F$11=Parameters!$E$15)*Parameters!$I$11*X16+(Parameters!$F$12=Parameters!$E$15)*Parameters!$I$12*Y16)>=Parameters!$B$36),((Parameters!$F$5=Parameters!$E$15)*Parameters!$I$5*N(P16)+(Parameters!$F$6=Parameters!$E$15)*Parameters!$I$6*N(Q16)+(Parameters!$F$7=Parameters!$E$15)*Parameters!$I$7*N(R16)+(Parameters!$F$8=Parameters!$E$15)*Parameters!$I$8*N(S16)+(Parameters!$F$9=Parameters!$E$15)*Parameters!$I$9*N(T16)+(Parameters!$F$10=Parameters!$E$15)*Parameters!$I$10*N(U16)+(Parameters!$F$11=Parameters!$E$15)*Parameters!$I$11*N(V16)+(Parameters!$F$12=Parameters!$E$15)*Parameters!$I$12*N(W16))/((Parameters!$F$5=Parameters!$E$15)*Parameters!$I$5*ISNUMBER(P16)+(Parameters!$F$6=Parameters!$E$15)*Parameters!$I$6*ISNUMBER(Q16)+(Parameters!$F$7=Parameters!$E$15)*Parameters!$I$7*ISNUMBER(R16)+(Parameters!$F$8=Parameters!$E$15)*Parameters!$I$8*ISNUMBER(S16)+(Parameters!$F$9=Parameters!$E$15)*Parameters!$I$9*ISNUMBER(T16)+(Parameters!$F$10=Parameters!$E$15)*Parameters!$I$10*ISNUMBER(U16)+(Parameters!$F$11=Parameters!$E$15)*Parameters!$I$11*ISNUMBER(V16)+(Parameters!$F$12=Parameters!$E$15)*Parameters!$I$12*ISNUMBER(W16)),"")) -> 0.99333333 | AA16: =IF(((Parameters!$F$5=Parameters!$E$16)*Parameters!$I$5*1+(Parameters!$F$6=Parameters!$E$16)*Parameters!$I$6*1+(Parameters!$F$7=Parameters!$E$16)*Parameters!$I$7*1+(Parameters!$F$8=Parameters!$E$16)*Parameters!$I$8*1+(Parameters!$F$9=Parameters!$E$16)*Parameters!$I$9*1+(Parameters!$F$10=Parameters!$E$16)*Parameters!$I$10*1+(Parameters!$F$11=Parameters!$E$16)*Parameters!$I$11*X16+(Parameters!$F$12=Parameters!$E$16)*Parameters!$I$12*Y16)=0,"",IF(AND(((Parameters!$F$5=Parameters!$E$16)*Parameters!$I$5*ISNUMBER(P16)+(Parameters!$F$6=Parameters!$E$16)*Parameters!$I$6*ISNUMBER(Q16)+(Parameters!$F$7=Parameters!$E$16)*Parameters!$I$7*ISNUMBER(R16)+(Parameters!$F$8=Parameters!$E$16)*Parameters!$I$8*ISNUMBER(S16)+(Parameters!$F$9=Parameters!$E$16)*Parameters!$I$9*ISNUMBER(T16)+(Parameters!$F$10=Parameters!$E$16)*Parameters!$I$10*ISNUMBER(U16)+(Parameters!$F$11=Parameters!$E$16)*Parameters!$I$11*ISNUMBER(V16)+(Parameters!$F$12=Parameters!$E$16)*Parameters!$I$12*ISNUMBER(W16))>0,((Parameters!$F$5=Parameters!$E$16)*Parameters!$I$5*ISNUMBER(P16)+(Parameters!$F$6=Parameters!$E$16)*Parameters!$I$6*ISNUMBER(Q16)+(Parameters!$F$7=Parameters!$E$16)*Parameters!$I$7*ISNUMBER(R16)+(Parameters!$F$8=Parameters!$E$16)*Parameters!$I$8*ISNUMBER(S16)+(Parameters!$F$9=Parameters!$E$16)*Parameters!$I$9*ISNUMBER(T16)+(Parameters!$F$10=Parameters!$E$16)*Parameters!$I$10*ISNUMBER(U16)+(Parameters!$F$11=Parameters!$E$16)*Parameters!$I$11*ISNUMBER(V16)+(Parameters!$F$12=Parameters!$E$16)*Parameters!$I$12*ISNUMBER(W16))/((Parameters!$F$5=Parameters!$E$16)*Parameters!$I$5*1+(Parameters!$F$6=Parameters!$E$16)*Parameters!$I$6*1+(Parameters!$F$7=Parameters!$E$16)*Parameters!$I$7*1+(Parameters!$F$8=Parameters!$E$16)*Parameters!$I$8*1+(Parameters!$F$9=Parameters!$E$16)*Parameters!$I$9*1+(Parameters!$F$10=Parameters!$E$16)*Parameters!$I$10*1+(Parameters!$F$11=Parameters!$E$16)*Parameters!$I$11*X16+(Parameters!$F$12=Parameters!$E$16)*Parameters!$I$12*Y16)>=Parameters!$B$36),((Parameters!$F$5=Parameters!$E$16)*Parameters!$I$5*N(P16)+(Parameters!$F$6=Parameters!$E$16)*Parameters!$I$6*N(Q16)+(Parameters!$F$7=Parameters!$E$16)*Parameters!$I$7*N(R16)+(Parameters!$F$8=Parameters!$E$16)*Parameters!$I$8*N(S16)+(Parameters!$F$9=Parameters!$E$16)*Parameters!$I$9*N(T16)+(Parameters!$F$10=Parameters!$E$16)*Parameters!$I$10*N(U16)+(Parameters!$F$11=Parameters!$E$16)*Parameters!$I$11*N(V16)+(Parameters!$F$12=Parameters!$E$16)*Parameters!$I$12*N(W16))/((Parameters!$F$5=Parameters!$E$16)*Parameters!$I$5*ISNUMBER(P16)+(Parameters!$F$6=Parameters!$E$16)*Parameters!$I$6*ISNUMBER(Q16)+(Parameters!$F$7=Parameters!$E$16)*Parameters!$I$7*ISNUMBER(R16)+(Parameters!$F$8=Parameters!$E$16)*Parameters!$I$8*ISNUMBER(S16)+(Parameters!$F$9=Parameters!$E$16)*Parameters!$I$9*ISNUMBER(T16)+(Parameters!$F$10=Parameters!$E$16)*Parameters!$I$10*ISNUMBER(U16)+(Parameters!$F$11=Parameters!$E$16)*Parameters!$I$11*ISNUMBER(V16)+(Parameters!$F$12=Parameters!$E$16)*Parameters!$I$12*ISNUMBER(W16)),"")) -> 0.8 | AB16: =IF(((Parameters!$F$5=Parameters!$E$17)*Parameters!$I$5*1+(Parameters!$F$6=Parameters!$E$17)*Parameters!$I$6*1+(Parameters!$F$7=Parameters!$E$17)*Parameters!$I$7*1+(Parameters!$F$8=Parameters!$E$17)*Parameters!$I$8*1+(Parameters!$F$9=Parameters!$E$17)*Parameters!$I$9*1+(Parameters!$F$10=Parameters!$E$17)*Parameters!$I$10*1+(Parameters!$F$11=Parameters!$E$17)*Parameters!$I$11*X16+(Parameters!$F$12=Parameters!$E$17)*Parameters!$I$12*Y16)=0,"",IF(AND(((Parameters!$F$5=Parameters!$E$17)*Parameters!$I$5*ISNUMBER(P16)+(Parameters!$F$6=Parameters!$E$17)*Parameters!$I$6*ISNUMBER(Q16)+(Parameters!$F$7=Parameters!$E$17)*Parameters!$I$7*ISNUMBER(R16)+(Parameters!$F$8=Parameters!$E$17)*Parameters!$I$8*ISNUMBER(S16)+(Parameters!$F$9=Parameters!$E$17)*Parameters!$I$9*ISNUMBER(T16)+(Parameters!$F$10=Parameters!$E$17)*Parameters!$I$10*ISNUMBER(U16)+(Parameters!$F$11=Parameters!$E$17)*Parameters!$I$11*ISNUMBER(V16)+(Parameters!$F$12=Parameters!$E$17)*Parameters!$I$12*ISNUMBER(W16))>0,((Parameters!$F$5=Parameters!$E$17)*Parameters!$I$5*ISNUMBER(P16)+(Parameters!$F$6=Parameters!$E$17)*Parameters!$I$6*ISNUMBER(Q16)+(Parameters!$F$7=Parameters!$E$17)*Parameters!$I$7*ISNUMBER(R16)+(Parameters!$F$8=Parameters!$E$17)*Parameters!$I$8*ISNUMBER(S16)+(Parameters!$F$9=Parameters!$E$17)*Parameters!$I$9*ISNUMBER(T16)+(Parameters!$F$10=Parameters!$E$17)*Parameters!$I$10*ISNUMBER(U16)+(Parameters!$F$11=Parameters!$E$17)*Parameters!$I$11*ISNUMBER(V16)+(Parameters!$F$12=Parameters!$E$17)*Parameters!$I$12*ISNUMBER(W16))/((Parameters!$F$5=Parameters!$E$17)*Parameters!$I$5*1+(Parameters!$F$6=Parameters!$E$17)*Parameters!$I$6*1+(Parameters!$F$7=Parameters!$E$17)*Parameters!$I$7*1+(Parameters!$F$8=Parameters!$E$17)*Parameters!$I$8*1+(Parameters!$F$9=Parameters!$E$17)*Parameters!$I$9*1+(Parameters!$F$10=Parameters!$E$17)*Parameters!$I$10*1+(Parameters!$F$11=Parameters!$E$17)*Parameters!$I$11*X16+(Parameters!$F$12=Parameters!$E$17)*Parameters!$I$12*Y16)>=Parameters!$B$36),((Parameters!$F$5=Parameters!$E$17)*Parameters!$I$5*N(P16)+(Parameters!$F$6=Parameters!$E$17)*Parameters!$I$6*N(Q16)+(Parameters!$F$7=Parameters!$E$17)*Parameters!$I$7*N(R16)+(Parameters!$F$8=Parameters!$E$17)*Parameters!$I$8*N(S16)+(Parameters!$F$9=Parameters!$E$17)*Parameters!$I$9*N(T16)+(Parameters!$F$10=Parameters!$E$17)*Parameters!$I$10*N(U16)+(Parameters!$F$11=Parameters!$E$17)*Parameters!$I$11*N(V16)+(Parameters!$F$12=Parameters!$E$17)*Parameters!$I$12*N(W16))/((Parameters!$F$5=Parameters!$E$17)*Parameters!$I$5*ISNUMBER(P16)+(Parameters!$F$6=Parameters!$E$17)*Parameters!$I$6*ISNUMBER(Q16)+(Parameters!$F$7=Parameters!$E$17)*Parameters!$I$7*ISNUMBER(R16)+(Parameters!$F$8=Parameters!$E$17)*Parameters!$I$8*ISNUMBER(S16)+(Parameters!$F$9=Parameters!$E$17)*Parameters!$I$9*ISNUMBER(T16)+(Parameters!$F$10=Parameters!$E$17)*Parameters!$I$10*ISNUMBER(U16)+(Parameters!$F$11=Parameters!$E$17)*Parameters!$I$11*ISNUMBER(V16)+(Parameters!$F$12=Parameters!$E$17)*Parameters!$I$12*ISNUMBER(W16)),"")) -> 0 | AC16: =Parameters!$I$5*ISNUMBER(P16)+Parameters!$I$6*ISNUMBER(Q16)+Parameters!$I$7*ISNUMBER(R16)+Parameters!$I$8*ISNUMBER(S16)+Parameters!$I$9*ISNUMBER(T16)+Parameters!$I$10*ISNUMBER(U16)+Parameters!$I$11*ISNUMBER(V16)+Parameters!$I$12*ISNUMBER(W16) -> 85 | AD16: =Parameters!$I$5*1+Parameters!$I$6*1+Parameters!$I$7*1+Parameters!$I$8*1+Parameters!$I$9*1+Parameters!$I$10*1+Parameters!$I$11*X16+Parameters!$I$12*Y16 -> 85 | AE16: =IF(AD16=0,"",AC16/AD16) -> 1 | AF16: =IF(ISNUMBER(Z16),"M","")&IF(ISNUMBER(AA16),"I","")&IF(ISNUMBER(AB16),"O","") -> MIO | AG16: =IF(AND(ISNUMBER(AE16),ISNUMBER(Z16)+ISNUMBER(AA16)+ISNUMBER(AB16)>=Parameters!$B$37),IF(AE16>=Parameters!$B$35,100*(Parameters!$F$15*N(Z16)+Parameters!$F$16*N(AA16)+Parameters!$F$17*N(AB16))/(Parameters!$F$15*ISNUMBER(Z16)+Parameters!$F$16*ISNUMBER(AA16)+Parameters!$F$17*ISNUMBER(AB16)),""),"") -> 73.666667 | AH16: =IF(ISNUMBER(AG16),RANK(AG16,$AG$2:$AG$113),"") -> 95
A17: Blacklight | B17: Blacklight | C17: Discovery system | Integrated Library System (ILS) or Library Services Platform (LSP) | D17: Actual system proven in operational environment | E17: Actively Maintained | F17: 2006-01-01 | G17: See website | I17: FALSE | J17: Through solution provider only | L17: Fiscal sponsorship (academic institution) | M17: Contributions | N17: 6-10 | P17: =IFERROR(IF(ISNUMBER(INDEX(Parameters!$B$5:$B$23,MATCH(D17,Parameters!$A$5:$A$23,0))),INDEX(Parameters!$B$5:$B$23,MATCH(D17,Parameters!$A$5:$A$23,0)),""),"") -> 1 | Q17: =IFERROR(IF(ISNUMBER(INDEX(Parameters!$B$5:$B$23,MATCH(E17,Parameters!$A$5:$A$23,0))),INDEX(Parameters!$B$5:$B$23,MATCH(E17,Parameters!$A$5:$A$23,0)),""),"") -> 1 | R17: =IF(F17="","",IFERROR(MIN(Parameters!$B$33,MAX(0,Parameters!$B$32-VALUE(LEFT(F17,4))))/Parameters!$B$33,"")) -> 1 | S17: =IF(ISNUMBER(H17),H17,IF(G17="",IF(ISNUMBER(Parameters!$B$34),Parameters!$B$34,""),"")) | T17: =IFERROR(IF(ISNUMBER(INDEX(Parameters!$B$5:$B$23,MATCH(I17,Parameters!$A$5:$A$23,0))),INDEX(Parameters!$B$5:$B$23,MATCH(I17,Parameters!$A$5:$A$23,0)),""),"") -> 0 | U17: =IFERROR(IF(ISNUMBER(INDEX(Parameters!$B$5:$B$23,MATCH(L17,Parameters!$A$5:$A$23,0))),INDEX(Parameters!$B$5:$B$23,MATCH(L17,Parameters!$A$5:$A$23,0)),""),"") -> 1 | V17: =IFERROR(IF(ISNUMBER(INDEX(Parameters!$B$5:$B$23,MATCH(J17,Parameters!$A$5:$A$23,0))),INDEX(Parameters!$B$5:$B$23,MATCH(J17,Parameters!$A$5:$A$23,0)),""),"") -> 1 | W17: =IF(K17<>"",1,IF(COUNTIF(Parameters!$A$27:$A$28,J17)>0,0,"")) | X17: =IF(J17="Not applicable",0,1) -> 1 | Y17: =IF(OR(K17<>"",COUNTIF(Parameters!$A$27:$A$28,J17)>0),1,0) -> 0 | Z17: =IF(((Parameters!$F$5=Parameters!$E$15)*Parameters!$I$5*1+(Parameters!$F$6=Parameters!$E$15)*Parameters!$I$6*1+(Parameters!$F$7=Parameters!$E$15)*Parameters!$I$7*1+(Parameters!$F$8=Parameters!$E$15)*Parameters!$I$8*1+(Parameters!$F$9=Parameters!$E$15)*Parameters!$I$9*1+(Parameters!$F$10=Parameters!$E$15)*Parameters!$I$10*1+(Parameters!$F$11=Parameters!$E$15)*Parameters!$I$11*X17+(Parameters!$F$12=Parameters!$E$15)*Parameters!$I$12*Y17)=0,"",IF(AND(((Parameters!$F$5=Parameters!$E$15)*Parameters!$I$5*ISNUMBER(P17)+(Parameters!$F$6=Parameters!$E$15)*Parameters!$I$6*ISNUMBER(Q17)+(Parameters!$F$7=Parameters!$E$15)*Parameters!$I$7*ISNUMBER(R17)+(Parameters!$F$8=Parameters!$E$15)*Parameters!$I$8*ISNUMBER(S17)+(Parameters!$F$9=Parameters!$E$15)*Parameters!$I$9*ISNUMBER(T17)+(Parameters!$F$10=Parameters!$E$15)*Parameters!$I$10*ISNUMBER(U17)+(Parameters!$F$11=Parameters!$E$15)*Parameters!$I$11*ISNUMBER(V17)+(Parameters!$F$12=Parameters!$E$15)*Parameters!$I$12*ISNUMBER(W17))>0,((Parameters!$F$5=Parameters!$E$15)*Parameters!$I$5*ISNUMBER(P17)+(Parameters!$F$6=Parameters!$E$15)*Parameters!$I$6*ISNUMBER(Q17)+(Parameters!$F$7=Parameters!$E$15)*Parameters!$I$7*ISNUMBER(R17)+(Parameters!$F$8=Parameters!$E$15)*Parameters!$I$8*ISNUMBER(S17)+(Parameters!$F$9=Parameters!$E$15)*Parameters!$I$9*ISNUMBER(T17)+(Parameters!$F$10=Parameters!$E$15)*Parameters!$I$10*ISNUMBER(U17)+(Parameters!$F$11=Parameters!$E$15)*Parameters!$I$11*ISNUMBER(V17)+(Parameters!$F$12=Parameters!$E$15)*Parameters!$I$12*ISNUMBER(W17))/((Parameters!$F$5=Parameters!$E$15)*Parameters!$I$5*1+(Parameters!$F$6=Parameters!$E$15)*Parameters!$I$6*1+(Parameters!$F$7=Parameters!$E$15)*Parameters!$I$7*1+(Parameters!$F$8=Parameters!$E$15)*Parameters!$I$8*1+(Parameters!$F$9=Parameters!$E$15)*Parameters!$I$9*1+(Parameters!$F$10=Parameters!$E$15)*Parameters!$I$10*1+(Parameters!$F$11=Parameters!$E$15)*Parameters!$I$11*X17+(Parameters!$F$12=Parameters!$E$15)*Parameters!$I$12*Y17)>=Parameters!$B$36),((Parameters!$F$5=Parameters!$E$15)*Parameters!$I$5*N(P17)+(Parameters!$F$6=Parameters!$E$15)*Parameters!$I$6*N(Q17)+(Parameters!$F$7=Parameters!$E$15)*Parameters!$I$7*N(R17)+(Parameters!$F$8=Parameters!$E$15)*Parameters!$I$8*N(S17)+(Parameters!$F$9=Parameters!$E$15)*Parameters!$I$9*N(T17)+(Parameters!$F$10=Parameters!$E$15)*Parameters!$I$10*N(U17)+(Parameters!$F$11=Parameters!$E$15)*Parameters!$I$11*N(V17)+(Parameters!$F$12=Parameters!$E$15)*Parameters!$I$12*N(W17))/((Parameters!$F$5=Parameters!$E$15)*Parameters!$I$5*ISNUMBER(P17)+(Parameters!$F$6=Parameters!$E$15)*Parameters!$I$6*ISNUMBER(Q17)+(Parameters!$F$7=Parameters!$E$15)*Parameters!$I$7*ISNUMBER(R17)+(Parameters!$F$8=Parameters!$E$15)*Parameters!$I$8*ISNUMBER(S17)+(Parameters!$F$9=Parameters!$E$15)*Parameters!$I$9*ISNUMBER(T17)+(Parameters!$F$10=Parameters!$E$15)*Parameters!$I$10*ISNUMBER(U17)+(Parameters!$F$11=Parameters!$E$15)*Parameters!$I$11*ISNUMBER(V17)+(Parameters!$F$12=Parameters!$E$15)*Parameters!$I$12*ISNUMBER(W17)),"")) -> 1 | AA17: =IF(((Parameters!$F$5=Parameters!$E$16)*Parameters!$I$5*1+(Parameters!$F$6=Parameters!$E$16)*Parameters!$I$6*1+(Parameters!$F$7=Parameters!$E$16)*Parameters!$I$7*1+(Parameters!$F$8=Parameters!$E$16)*Parameters!$I$8*1+(Parameters!$F$9=Parameters!$E$16)*Parameters!$I$9*1+(Parameters!$F$10=Parameters!$E$16)*Parameters!$I$10*1+(Parameters!$F$11=Parameters!$E$16)*Parameters!$I$11*X17+(Parameters!$F$12=Parameters!$E$16)*Parameters!$I$12*Y17)=0,"",IF(AND(((Parameters!$F$5=Parameters!$E$16)*Parameters!$I$5*ISNUMBER(P17)+(Parameters!$F$6=Parameters!$E$16)*Parameters!$I$6*ISNUMBER(Q17)+(Parameters!$F$7=Parameters!$E$16)*Parameters!$I$7*ISNUMBER(R17)+(Parameters!$F$8=Parameters!$E$16)*Parameters!$I$8*ISNUMBER(S17)+(Parameters!$F$9=Parameters!$E$16)*Parameters!$I$9*ISNUMBER(T17)+(Parameters!$F$10=Parameters!$E$16)*Parameters!$I$10*ISNUMBER(U17)+(Parameters!$F$11=Parameters!$E$16)*Parameters!$I$11*ISNUMBER(V17)+(Parameters!$F$12=Parameters!$E$16)*Parameters!$I$12*ISNUMBER(W17))>0,((Parameters!$F$5=Parameters!$E$16)*Parameters!$I$5*ISNUMBER(P17)+(Parameters!$F$6=Parameters!$E$16)*Parameters!$I$6*ISNUMBER(Q17)+(Parameters!$F$7=Parameters!$E$16)*Parameters!$I$7*ISNUMBER(R17)+(Parameters!$F$8=Parameters!$E$16)*Parameters!$I$8*ISNUMBER(S17)+(Parameters!$F$9=Parameters!$E$16)*Parameters!$I$9*ISNUMBER(T17)+(Parameters!$F$10=Parameters!$E$16)*Parameters!$I$10*ISNUMBER(U17)+(Parameters!$F$11=Parameters!$E$16)*Parameters!$I$11*ISNUMBER(V17)+(Parameters!$F$12=Parameters!$E$16)*Parameters!$I$12*ISNUMBER(W17))/((Parameters!$F$5=Parameters!$E$16)*Parameters!$I$5*1+(Parameters!$F$6=Parameters!$E$16)*Parameters!$I$6*1+(Parameters!$F$7=Parameters!$E$16)*Parameters!$I$7*1+(Parameters!$F$8=Parameters!$E$16)*Parameters!$I$8*1+(Parameters!$F$9=Parameters!$E$16)*Parameters!$I$9*1+(Parameters!$F$10=Parameters!$E$16)*Parameters!$I$10*1+(Parameters!$F$11=Parameters!$E$16)*Parameters!$I$11*X17+(Parameters!$F$12=Parameters!$E$16)*Parameters!$I$12*Y17)>=Parameters!$B$36),((Parameters!$F$5=Parameters!$E$16)*Parameters!$I$5*N(P17)+(Parameters!$F$6=Parameters!$E$16)*Parameters!$I$6*N(Q17)+(Parameters!$F$7=Parameters!$E$16)*Parameters!$I$7*N(R17)+(Parameters!$F$8=Parameters!$E$16)*Parameters!$I$8*N(S17)+(Parameters!$F$9=Parameters!$E$16)*Parameters!$I$9*N(T17)+(Parameters!$F$10=Parameters!$E$16)*Parameters!$I$10*N(U17)+(Parameters!$F$11=Parameters!$E$16)*Parameters!$I$11*N(V17)+(Parameters!$F$12=Parameters!$E$16)*Parameters!$I$12*N(W17))/((Parameters!$F$5=Parameters!$E$16)*Parameters!$I$5*ISNUMBER(P17)+(Parameters!$F$6=Parameters!$E$16)*Parameters!$I$6*ISNUMBER(Q17)+(Parameters!$F$7=Parameters!$E$16)*Parameters!$I$7*ISNUMBER(R17)+(Parameters!$F$8=Parameters!$E$16)*Parameters!$I$8*ISNUMBER(S17)+(Parameters!$F$9=Parameters!$E$16)*Parameters!$I$9*ISNUMBER(T17)+(Parameters!$F$10=Parameters!$E$16)*Parameters!$I$10*ISNUMBER(U17)+(Parameters!$F$11=Parameters!$E$16)*Parameters!$I$11*ISNUMBER(V17)+(Parameters!$F$12=Parameters!$E$16)*Parameters!$I$12*ISNUMBER(W17)),"")) -> 0.66666667 | AB17: =IF(((Parameters!$F$5=Parameters!$E$17)*Parameters!$I$5*1+(Parameters!$F$6=Parameters!$E$17)*Parameters!$I$6*1+(Parameters!$F$7=Parameters!$E$17)*Parameters!$I$7*1+(Parameters!$F$8=Parameters!$E$17)*Parameters!$I$8*1+(Parameters!$F$9=Parameters!$E$17)*Parameters!$I$9*1+(Parameters!$F$10=Parameters!$E$17)*Parameters!$I$10*1+(Parameters!$F$11=Parameters!$E$17)*Parameters!$I$11*X17+(Parameters!$F$12=Parameters!$E$17)*Parameters!$I$12*Y17)=0,"",IF(AND(((Parameters!$F$5=Parameters!$E$17)*Parameters!$I$5*ISNUMBER(P17)+(Parameters!$F$6=Parameters!$E$17)*Parameters!$I$6*ISNUMBER(Q17)+(Parameters!$F$7=Parameters!$E$17)*Parameters!$I$7*ISNUMBER(R17)+(Parameters!$F$8=Parameters!$E$17)*Parameters!$I$8*ISNUMBER(S17)+(Parameters!$F$9=Parameters!$E$17)*Parameters!$I$9*ISNUMBER(T17)+(Parameters!$F$10=Parameters!$E$17)*Parameters!$I$10*ISNUMBER(U17)+(Parameters!$F$11=Parameters!$E$17)*Parameters!$I$11*ISNUMBER(V17)+(Parameters!$F$12=Parameters!$E$17)*Parameters!$I$12*ISNUMBER(W17))>0,((Parameters!$F$5=Parameters!$E$17)*Parameters!$I$5*ISNUMBER(P17)+(Parameters!$F$6=Parameters!$E$17)*Parameters!$I$6*ISNUMBER(Q17)+(Parameters!$F$7=Parameters!$E$17)*Parameters!$I$7*ISNUMBER(R17)+(Parameters!$F$8=Parameters!$E$17)*Parameters!$I$8*ISNUMBER(S17)+(Parameters!$F$9=Parameters!$E$17)*Parameters!$I$9*ISNUMBER(T17)+(Parameters!$F$10=Parameters!$E$17)*Parameters!$I$10*ISNUMBER(U17)+(Parameters!$F$11=Parameters!$E$17)*Parameters!$I$11*ISNUMBER(V17)+(Parameters!$F$12=Parameters!$E$17)*Parameters!$I$12*ISNUMBER(W17))/((Parameters!$F$5=Parameters!$E$17)*Parameters!$I$5*1+(Parameters!$F$6=Parameters!$E$17)*Parameters!$I$6*1+(Parameters!$F$7=Parameters!$E$17)*Parameters!$I$7*1+(Parameters!$F$8=Parameters!$E$17)*Parameters!$I$8*1+(Parameters!$F$9=Parameters!$E$17)*Parameters!$I$9*1+(Parameters!$F$10=Parameters!$E$17)*Parameters!$I$10*1+(Parameters!$F$11=Parameters!$E$17)*Parameters!$I$11*X17+(Parameters!$F$12=Parameters!$E$17)*Parameters!$I$12*Y17)>=Parameters!$B$36),((Parameters!$F$5=Parameters!$E$17)*Parameters!$I$5*N(P17)+(Parameters!$F$6=Parameters!$E$17)*Parameters!$I$6*N(Q17)+(Parameters!$F$7=Parameters!$E$17)*Parameters!$I$7*N(R17)+(Parameters!$F$8=Parameters!$E$17)*Parameters!$I$8*N(S17)+(Parameters!$F$9=Parameters!$E$17)*Parameters!$I$9*N(T17)+(Parameters!$F$10=Parameters!$E$17)*Parameters!$I$10*N(U17)+(Parameters!$F$11=Parameters!$E$17)*Parameters!$I$11*N(V17)+(Parameters!$F$12=Parameters!$E$17)*Parameters!$I$12*N(W17))/((Parameters!$F$5=Parameters!$E$17)*Parameters!$I$5*ISNUMBER(P17)+(Parameters!$F$6=Parameters!$E$17)*Parameters!$I$6*ISNUMBER(Q17)+(Parameters!$F$7=Parameters!$E$17)*Parameters!$I$7*ISNUMBER(R17)+(Parameters!$F$8=Parameters!$E$17)*Parameters!$I$8*ISNUMBER(S17)+(Parameters!$F$9=Parameters!$E$17)*Parameters!$I$9*ISNUMBER(T17)+(Parameters!$F$10=Parameters!$E$17)*Parameters!$I$10*ISNUMBER(U17)+(Parameters!$F$11=Parameters!$E$17)*Parameters!$I$11*ISNUMBER(V17)+(Parameters!$F$12=Parameters!$E$17)*Parameters!$I$12*ISNUMBER(W17)),"")) -> 1 | AC17: =Parameters!$I$5*ISNUMBER(P17)+Parameters!$I$6*ISNUMBER(Q17)+Parameters!$I$7*ISNUMBER(R17)+Parameters!$I$8*ISNUMBER(S17)+Parameters!$I$9*ISNUMBER(T17)+Parameters!$I$10*ISNUMBER(U17)+Parameters!$I$11*ISNUMBER(V17)+Parameters!$I$12*ISNUMBER(W17) -> 75 | AD17: =Parameters!$I$5*1+Parameters!$I$6*1+Parameters!$I$7*1+Parameters!$I$8*1+Parameters!$I$9*1+Parameters!$I$10*1+Parameters!$I$11*X17+Parameters!$I$12*Y17 -> 85 | AE17: =IF(AD17=0,"",AC17/AD17) -> 0.88235294 | AF17: =IF(ISNUMBER(Z17),"M","")&IF(ISNUMBER(AA17),"I","")&IF(ISNUMBER(AB17),"O","") -> MIO | AG17: =IF(AND(ISNUMBER(AE17),ISNUMBER(Z17)+ISNUMBER(AA17)+ISNUMBER(AB17)>=Parameters!$B$37),IF(AE17>=Parameters!$B$35,100*(Parameters!$F$15*N(Z17)+Parameters!$F$16*N(AA17)+Parameters!$F$17*N(AB17))/(Parameters!$F$15*ISNUMBER(Z17)+Parameters!$F$16*ISNUMBER(AA17)+Parameters!$F$17*ISNUMBER(AB17)),""),"") -> 90 | AH17: =IF(ISNUMBER(AG17),RANK(AG17,$AG$2:$AG$113),"") -> 25
