Workbook

Sheet Method
A1: OISI Component 2 - Governance Practices: scoring workbook
A2: Source: OISI_112_Governance_Practices_Verification.xlsm (112 services from Infra Finder v3) + 02_Governance_Practices_OISI.docx (specification).
A4: HOW A SCORE IS BUILT
A5: 1. Each status variable -> 0-1 via the ladder on Parameters (Implemented 1, In progress 0.67, Considering 0.33, Not planning 0). Unknown / Not applicable = NA (missing, not zero).
A6: 2. Presence variables (050 board structure, 046 values frameworks) -> 1 if any value is listed, else the blank rule on Parameters (default 0).
A7: 3. Sub-component score = weighted mean of its metrics that are observed (weights renormalised over non-missing metrics).
A8: 4. Component score = 100 x weighted mean of sub-components that are observed (Formal 40%, Participatory 25%, Transparency 35%).
A9: 5. A score is published only if completeness (observed weight / total weight in the data) >= 70% AND Formal and Transparency both have a value.
A10: 6. Evidence confidence (0-100%) = share of a repo's "Implemented" claims that carry an evidence URL. It is a reliability flag, NOT part of the score.
A12: THREE ISSUES YOU SHOULD DECIDE BEFORE PUBLISHING
A13: A. 048_community_governance_status now comes from OISI_112_Community_Engagement_Verification.xlsx (rows matched by order and service name, 112/112). Values: Formal 52, Ad hoc 35, blank 25. The spec's explicit None never appears, so blank is treated as absent (0) by default - the strongest assumption in the model; switch on Parameters!B21.
A14: B. 100_board_level is only 13% complete (15/112), so it is reported descriptively and its 5 points go to 048 (Participatory = 048 alone), as your spec allows.
... A21: - The scale is ordinal and self-reported; treat score differences of a few points as ties.

Sheet Parameters
A1: OISI Component 2 - Governance Practices: scoring parameters
A2: Blue = editable input. Every score in the "Scores" sheet recalculates from these cells.
A4: Status label | B4: Score (0-1) | C4: Used by | E4: Variable | F4: Sub-component | G4: Weight (pts of 100) | H4: Column in data? (1/0) | I4: Effective weight | J4: Justification / status
A5: Implemented/available | B5: 1 | C5: status metrics | E5: 024_governance_structure_status | F5: Formal | G5: 12 | H5: 1 | I5: =G5*H5 -> 12 | J5: Core: documented governance structure. 100% coverage.
A6: No direct costs | B6: 1 | C6: 033 only (per working rule) | E6: 026_governance_records_status | F6: Formal | G6: 12 | H6: 1 | I6: =G6*H6 -> 12 | J6: Core: public decision records = accountability evidence. 100% coverage.
A7: In progress | B7: 0.67 | C7: status metrics | E7: 108_bylaws_status | F7: Formal | G7: 8 | H7: 1 | I7: =G7*H7 -> 8 | J7: Core: formal rules. 26% Unknown -> NA, renormalised.
A8: Considering | B8: 0.33 | C8: status metrics | E8: 050_board_structure | F8: Formal | G8: 8 | H8: 1 | I8: =G8*H8 -> 8 | J8: Presence of any board/steering body. Type kept descriptive (no ranking of types).
A9: Not planning | B9: 0 | C9: status metrics | E9: 048_community_governance_status | F9: Participatory | G9: 20 | H9: 1 | I9: =G9*H9 -> 20 | J9: From OISI_112_Community_Engagement_Verification.xlsx (matched by row and service name). Formal 1 / Ad hoc 0.5 / blank = setting B21.
A10: Unknown | B10: NA | C10: treated as missing | E10: 100_board_level | F10: Participatory | G10: 5 | H10: 0 | I10: =G10*H10 -> 0 | J10: Descriptive only: 15/112 complete (13%). Its 5 pts go to 048 per working rule.
A11: Not applicable | B11: NA | C11: treated as missing | E11: 029_web_accessibility_status | F11: Transparency | G11: 7 | H11: 1 | I11: =G11*H11 -> 7 | J11: Core. 031 applicability retained as context.
A12: Formal | B12: 1 | C12: 048 (not in current file) | E12: 033_transparent_pricing_status | F12: Transparency | G12: 7 | H12: 1 | I12: =G12*H12 -> 7 | J12: Core, but 95% at ceiling: low discrimination (see Diagnostics).
A13: Ad hoc | B13: 0.5 | C13: 048 (not in current file) | E13: 035_commitment_to_equity_status | F13: Transparency | G13: 7 | H13: 1 | I13: =G13*H13 -> 7 | J13: Core.
A14: None | B14: 0 | C14: 048 (not in current file) | E14: 044_commitment_to_privacy_status | F14: Transparency | G14: 7 | H14: 1 | I14: =G14*H14 -> 7 | J14: Core.
E15: 046_values_frameworks | F15: Transparency | G15: 7 | H15: 1 | I15: =G15*H15 -> 7 | J15: Presence of >=1 named framework. Blank treated as absent (see setting below).
A17: Settings | E17: Sub-component | F17: Weight
A18: Blank 050_board_structure scored as (0 or NA) | B18: 0 | E18: Formal | F18: 0.4
A19: Blank 046_values_frameworks scored as (0 or NA) | B19: 0 | E19: Participatory | F19: 0.25
A20: Minimum completeness to publish a score | B20: 0.7 | E20: Transparency | F20: 0.35
A21: Blank 048_community_governance_status scored as (0 or NA) | B21: 0 | E21: Check: sum | F21: =SUM(F18:F20) -> 1
A22: Why blank = 0 for 050, 046 and 048 (deviation from the working "blank = NA" rule): these fields have no explicit absent option. For 050 and 046 every observed value would be 1 (zero variance). For 048 the file has only Formal (52) and Ad hoc (35) plus 25 blanks; the spec's None category never appears, so blank is the only way absence is recorded. Evidence: 76% of blank-048 repos have a governance structure that is not Implemented (vs 21% of the rest), only 1 of 25 gives a 048 URL (vs 55 of 87), and 54% of blank-050 repos report Not planning bylaws vs 9%. Switch B18/B19/B21 to NA to see the effect (Sensitivity sheet).

Sheet Scores
A1: Service | B1: Provider | C1: Solution category | D1: 024 Governance structure | E1: 026 Governance records | F1: 108 Bylaws | G1: 050 Board structure | H1: 100 Board level (descriptive) | I1: 048 Community governance | J1: 029 Web accessibility | K1: 033 Transparent pricing | L1: 035 Equity commitment | M1: 044 Privacy commitment | N1: 046 Values frameworks | O1: 025 URL | P1: 028 URL | Q1: 030 URL | R1: 034 URL | S1: 036 URL | T1: 045 URL | U1: 049 URL | V1: s024 | W1: s026 | X1: s108 | Y1: s050 | Z1: s048 | AA1: s029 | AB1: s033 | AC1: s035 | AD1: s044 | AE1: s046 | AF1: Formal (0-1) | AG1: Participatory (0-1) | AH1: Transparency (0-1) | AI1: Weight observed | AJ1: Completeness | AK1: Governance score (0-100) | AL1: Rank | AM1: Evidence confidence
A2: ArchivesSpace | B2: ArchivesSpace | C2: Archive information management system | Discovery system | D2: Implemented/available | E2: Implemented/available | F2: Implemented/available | G2: Advisory board or steering committee | I2: Formal | J2: Implemented/available | K2: Implemented/available | L2: Implemented/available | M2: Implemented/available | N2: It Takes a Village Open Source Software Sustainability toolkit | O2: https://archivesspace.org/governance-board-and-councils | P2: https://archivesspace.atlassian.net/wiki/spaces/AC/overview | Q2: https://archivesspace.org/application/accessibility-vpat | R2: https://archivesspace.org/membership/member-benefits | S2: https://archivesspace.org/about/anti-racism-inclusion-initiatives | T2: https://archivesspace.org/about/lyrasis-privacy-policy | U2: https://archivesspace.org/governance-board-and-councils | V2: =IFERROR(IF(ISNUMBER(INDEX(Parameters!$B$5:$B$14,MATCH(D2,Parameters!$A$5:$A$14,0))),INDEX(Parameters!$B$5:$B$14,MATCH(D2,Parameters!$A$5:$A$14,0)),""),"") -> 1 | W2: =IFERROR(IF(ISNUMBER(INDEX(Parameters!$B$5:$B$14,MATCH(E2,Parameters!$A$5:$A$14,0))),INDEX(Parameters!$B$5:$B$14,MATCH(E2,Parameters!$A$5:$A$14,0)),""),"") -> 1 | X2: =IFERROR(IF(ISNUMBER(INDEX(Parameters!$B$5:$B$14,MATCH(F2,Parameters!$A$5:$A$14,0))),INDEX(Parameters!$B$5:$B$14,MATCH(F2,Parameters!$A$5:$A$14,0)),""),"") -> 1 | Y2: =IF(G2<>"",1,IF(ISNUMBER(Parameters!$B$18),Parameters!$B$18,"")) -> 1 | Z2: =IF(I2<>"",IFERROR(IF(ISNUMBER(INDEX(Parameters!$B$5:$B$14,MATCH(I2,Parameters!$A$5:$A$14,0))),INDEX(Parameters!$B$5:$B$14,MATCH(I2,Parameters!$A$5:$A$14,0)),""),""),IF(ISNUMBER(Parameters!$B$21),Parameters!$B$21,"")) -> 1 | AA2: =IFERROR(IF(ISNUMBER(INDEX(Parameters!$B$5:$B$14,MATCH(J2,Parameters!$A$5:$A$14,0))),INDEX(Parameters!$B$5:$B$14,MATCH(J2,Parameters!$A$5:$A$14,0)),""),"") -> 1 | AB2: =IFERROR(IF(ISNUMBER(INDEX(Parameters!$B$5:$B$14,MATCH(K2,Parameters!$A$5:$A$14,0))),INDEX(Parameters!$B$5:$B$14,MATCH(K2,Parameters!$A$5:$A$14,0)),""),"") -> 1 | AC2: =IFERROR(IF(ISNUMBER(INDEX(Parameters!$B$5:$B$14,MATCH(L2,Parameters!$A$5:$A$14,0))),INDEX(Parameters!$B$5:$B$14,MATCH(L2,Parameters!$A$5:$A$14,0)),""),"") -> 1 | AD2: =IFERROR(IF(ISNUMBER(INDEX(Parameters!$B$5:$B$14,MATCH(M2,Parameters!$A$5:$A$14,0))),INDEX(Parameters!$B$5:$B$14,MATCH(M2,Parameters!$A$5:$A$14,0)),""),"") -> 1 | AE2: =IF(N2<>"",1,IF(ISNUMBER(Parameters!$B$19),Parameters!$B$19,"")) -> 1 | AF2: =IF((Parameters!$I$5*ISNUMBER(V2)+Parameters!$I$6*ISNUMBER(W2)+Parameters!$I$7*ISNUMBER(X2)+Parameters!$I$8*ISNUMBER(Y2))=0,"",(Parameters!$I$5*N(V2)+Parameters!$I$6*N(W2)+Parameters!$I$7*N(X2)+Parameters!$I$8*N(Y2))/(Parameters!$I$5*ISNUMBER(V2)+Parameters!$I$6*ISNUMBER(W2)+Parameters!$I$7*ISNUMBER(X2)+Parameters!$I$8*ISNUMBER(Y2))) -> 1 | AG2: =IF((Parameters!$I$9*ISNUMBER(Z2))=0,"",(Parameters!$I$9*N(Z2))/(Parameters!$I$9*ISNUMBER(Z2))) -> 1 | AH2: =IF((Parameters!$I$11*ISNUMBER(AA2)+Parameters!$I$12*ISNUMBER(AB2)+Parameters!$I$13*ISNUMBER(AC2)+Parameters!$I$14*ISNUMBER(AD2)+Parameters!$I$15*ISNUMBER(AE2))=0,"",(Parameters!$I$11*N(AA2)+Parameters!$I$12*N(AB2)+Parameters!$I$13*N(AC2)+Parameters!$I$14*N(AD2)+Parameters!$I$15*N(AE2))/(Parameters!$I$11*ISNUMBER(AA2)+Parameters!$I$12*ISNUMBER(AB2)+Parameters!$I$13*ISNUMBER(AC2)+Parameters!$I$14*ISNUMBER(AD2)+Parameters!$I$15*ISNUMBER(AE2))) -> 1 | AI2: =Parameters!$I$5*ISNUMBER(V2)+Parameters!$I$6*ISNUMBER(W2)+Parameters!$I$7*ISNUMBER(X2)+Parameters!$I$8*ISNUMBER(Y2)+Parameters!$I$9*ISNUMBER(Z2)+Parameters!$I$11*ISNUMBER(AA2)+Parameters!$I$12*ISNUMBER(AB2)+Parameters!$I$13*ISNUMBER(AC2)+Parameters!$I$14*ISNUMBER(AD2)+Parameters!$I$15*ISNUMBER(AE2) -> 95 | AJ2: =IF((Parameters!$I$5+Parameters!$I$6+Parameters!$I$7+Parameters!$I$8+Parameters!$I$9+Parameters!$I$11+Parameters!$I$12+Parameters!$I$13+Parameters!$I$14+Parameters!$I$15)=0,"",AI2/(Parameters!$I$5+Parameters!$I$6+Parameters!$I$7+Parameters!$I$8+Parameters!$I$9+Parameters!$I$11+Parameters!$I$12+Parameters!$I$13+Parameters!$I$14+Parameters!$I$15)) -> 1 | AK2: =IF(AND(ISNUMBER(AF2),ISNUMBER(AH2),OR(NOT((Parameters!$I$9)>0),ISNUMBER(AG2)),AJ2>=Parameters!$B$20),100*(Parameters!$F$18*N(AF2)+Parameters!$F$19*N(AG2)+Parameters!$F$20*N(AH2))/(Parameters!$F$18*ISNUMBER(AF2)+Parameters!$F$19*ISNUMBER(AG2)+Parameters!$F$20*ISNUMBER(AH2)),"") -> 100 | AL2: =IF(ISNUMBER(AK2),RANK(AK2,$AK$2:$AK$113),"") -> 1 | AM2: =IF(((D2="Implemented/available")+(E2="Implemented/available")+(J2="Implemented/available")+(K2="Implemented/available")+(L2="Implemented/available")+(M2="Implemented/available"))=0,"",(AND(D2="Implemented/available",O2<>"")+AND(E2="Implemented/available",P2<>"")+AND(J2="Implemented/available",Q2<>"")+AND(K2="Implemented/available",R2<>"")+AND(L2="Implemented/available",S2<>"")+AND(M2="Implemented/available",T2<>""))/((D2="Implemented/available")+(E2="Implemented/available")+(J2="Implemented/available")+(K2="Implemented/available")+(L2="Implemented/available")+(M2="Implemented/available"))) -> 1
A3: DOAJ (Directory of Open Access Journals) | B3: DOAJ Foundation | C3: Discovery system | Index or directory | Open scholarly dataset | D3: Implemented/available | E3: Implemented/available | F3: Implemented/available | G3: Advisory board or steering committee | Other | I3: Formal | J3: Implemented/available | K3: Implemented/available | L3: Implemented/available | M3: Implemented/available | N3: FOREST Framework for Values-Driven Scholarly Communication | Helsinki Initiative on Multilingualism | Joint Statement of Principles of the Coalition for Diversity and Inclusion in Scholarly Communication (C4DISC) | Principles for Open Scholarly Infrastructure (POSI) | San Francisco Declaration on Research Assessment (DORA) | O3: https://doaj.org/about/advisory-board-council/ | P3: https://doaj.org/about/advisory-board-council/ | R3: https://doaj.org/support/ | S3: https://doaj.org/about/#diversity-equity-and-inclusion | T3: https://doaj.org/privacy/ | U3: https://doaj.org/about/advisory-board-council/ | V3: =IFERROR(IF(ISNUMBER(INDEX(Parameters!$B$5:$B$14,MATCH(D3,Parameters!$A$5:$A$14,0))),INDEX(Parameters!$B$5:$B$14,MATCH(D3,Parameters!$A$5:$A$14,0)),""),"") -> 1 | W3: =IFERROR(IF(ISNUMBER(INDEX(Parameters!$B$5:$B$14,MATCH(E3,Parameters!$A$5:$A$14,0))),INDEX(Parameters!$B$5:$B$14,MATCH(E3,Parameters!$A$5:$A$14,0)),""),"") -> 1 | X3: =IFERROR(IF(ISNUMBER(INDEX(Parameters!$B$5:$B$14,MATCH(F3,Parameters!$A$5:$A$14,0))),INDEX(Parameters!$B$5:$B$14,MATCH(F3,Parameters!$A$5:$A$14,0)),""),"") -> 1 | Y3: =IF(G3<>"",1,IF(ISNUMBER(Parameters!$B$18),Parameters!$B$18,"")) -> 1 | Z3: =IF(I3<>"",IFERROR(IF(ISNUMBER(INDEX(Parameters!$B$5:$B$14,MATCH(I3,Parameters!$A$5:$A$14,0))),INDEX(Parameters!$B$5:$B$14,MATCH(I3,Parameters!$A$5:$A$14,0)),""),""),IF(ISNUMBER(Parameters!$B$21),Parameters!$B$21,"")) -> 1 | AA3: =IFERROR(IF(ISNUMBER(INDEX(Parameters!$B$5:$B$14,MATCH(J3,Parameters!$A$5:$A$14,0))),INDEX(Parameters!$B$5:$B$14,MATCH(J3,Parameters!$A$5:$A$14,0)),""),"") -> 1 | AB3: =IFERROR(IF(ISNUMBER(INDEX(Parameters!$B$5:$B$14,MATCH(K3,Parameters!$A$5:$A$14,0))),INDEX(Parameters!$B$5:$B$14,MATCH(K3,Parameters!$A$5:$A$14,0)),""),"") -> 1 | AC3: =IFERROR(IF(ISNUMBER(INDEX(Parameters!$B$5:$B$14,MATCH(L3,Parameters!$A$5:$A$14,0))),INDEX(Parameters!$B$5:$B$14,MATCH(L3,Parameters!$A$5:$A$14,0)),""),"") -> 1 | AD3: =IFERROR(IF(ISNUMBER(INDEX(Parameters!$B$5:$B$14,MATCH(M3,Parameters!$A$5:$A$14,0))),INDEX(Parameters!$B$5:$B$14,MATCH(M3,Parameters!$A$5:$A$14,0)),""),"") -> 1 | AE3: =IF(N3<>"",1,IF(ISNUMBER(Parameters!$B$19),Parameters!$B$19,"")) -> 1 | AF3: =IF((Parameters!$I$5*ISNUMBER(V3)+Parameters!$I$6*ISNUMBER(W3)+Parameters!$I$7*ISNUMBER(X3)+Parameters!$I$8*ISNUMBER(Y3))=0,"",(Parameters!$I$5*N(V3)+Parameters!$I$6*N(W3)+Parameters!$I$7*N(X3)+Parameters!$I$8*N(Y3))/(Parameters!$I$5*ISNUMBER(V3)+Parameters!$I$6*ISNUMBER(W3)+Parameters!$I$7*ISNUMBER(X3)+Parameters!$I$8*ISNUMBER(Y3))) -> 1 | AG3: =IF((Parameters!$I$9*ISNUMBER(Z3))=0,"",(Parameters!$I$9*N(Z3))/(Parameters!$I$9*ISNUMBER(Z3))) -> 1 | AH3: =IF((Parameters!$I$11*ISNUMBER(AA3)+Parameters!$I$12*ISNUMBER(AB3)+Parameters!$I$13*ISNUMBER(AC3)+Parameters!$I$14*ISNUMBER(AD3)+Parameters!$I$15*ISNUMBER(AE3))=0,"",(Parameters!$I$11*N(AA3)+Parameters!$I$12*N(AB3)+Parameters!$I$13*N(AC3)+Parameters!$I$14*N(AD3)+Parameters!$I$15*N(AE3))/(Parameters!$I$11*ISNUMBER(AA3)+Parameters!$I$12*ISNUMBER(AB3)+Parameters!$I$13*ISNUMBER(AC3)+Parameters!$I$14*ISNUMBER(AD3)+Parameters!$I$15*ISNUMBER(AE3))) -> 1 | AI3: =Parameters!$I$5*ISNUMBER(V3)+Parameters!$I$6*ISNUMBER(W3)+Parameters!$I$7*ISNUMBER(X3)+Parameters!$I$8*ISNUMBER(Y3)+Parameters!$I$9*ISNUMBER(Z3)+Parameters!$I$11*ISNUMBER(AA3)+Parameters!$I$12*ISNUMBER(AB3)+Parameters!$I$13*ISNUMBER(AC3)+Parameters!$I$14*ISNUMBER(AD3)+Parameters!$I$15*ISNUMBER(AE3) -> 95 | AJ3: =IF((Parameters!$I$5+Parameters!$I$6+Parameters!$I$7+Parameters!$I$8+Parameters!$I$9+Parameters!$I$11+Parameters!$I$12+Parameters!$I$13+Parameters!$I$14+Parameters!$I$15)=0,"",AI3/(Parameters!$I$5+Parameters!$I$6+Parameters!$I$7+Parameters!$I$8+Parameters!$I$9+Parameters!$I$11+Parameters!$I$12+Parameters!$I$13+Parameters!$I$14+Parameters!$I$15)) -> 1 | AK3: =IF(AND(ISNUMBER(AF3),ISNUMBER(AH3),OR(NOT((Parameters!$I$9)>0),ISNUMBER(AG3)),AJ3>=Parameters!$B$20),100*(Parameters!$F$18*N(AF3)+Parameters!$F$19*N(AG3)+Parameters!$F$20*N(AH3))/(Parameters!$F$18*ISNUMBER(AF3)+Parameters!$F$19*ISNUMBER(AG3)+Parameters!$F$20*ISNUMBER(AH3)),"") -> 100 | AL3: =IF(ISNUMBER(AK3),RANK(AK3,$AK$2:$AK$113),"") -> 1 | AM3: =IF(((D3="Implemented/available")+(E3="Implemented/available")+(J3="Implemented/available")+(K3="Implemented/available")+(L3="Implemented/available")+(M3="Implemented/available"))=0,"",(AND(D3="Implemented/available",O3<>"")+AND(E3="Implemented/available",P3<>"")+AND(J3="Implemented/available",Q3<>"")+AND(K3="Implemented/available",R3<>"")+AND(L3="Implemented/available",S3<>"")+AND(M3="Implemented/available",T3<>""))/((D3="Implemented/available")+(E3="Implemented/available")+(J3="Implemented/available")+(K3="Implemented/available")+(L3="Implemented/available")+(M3="Implemented/available"))) -> 0.83333333
A4: DSpace | B4: Lyrasis | C4: Repository software | D4: Implemented/available | E4: Implemented/available | F4: Implemented/available | G4: Advisory board or steering committee | I4: Formal | J4: Implemented/available | K4: Implemented/available | L4: Implemented/available | M4: Implemented/available | N4: It Takes a Village Open Source Software Sustainability toolkit | O4: https://dspace.org/governance/ | P4: https://wiki.lyrasis.org/display/DSPACE/Leadership+Group | Q4: https://dspace.org/accessibility/ | R4: https://dspace.org/membership/ | S4: https://lyrasis.org/job-bank/ | T4: https://demo.dspace.org/info/privacy | U4: https://dspace.org/governance | V4: =IFERROR(IF(ISNUMBER(INDEX(Parameters!$B$5:$B$14,MATCH(D4,Parameters!$A$5:$A$14,0))),INDEX(Parameters!$B$5:$B$14,MATCH(D4,Parameters!$A$5:$A$14,0)),""),"") -> 1 | W4: =IFERROR(IF(ISNUMBER(INDEX(Parameters!$B$5:$B$14,MATCH(E4,Parameters!$A$5:$A$14,0))),INDEX(Parameters!$B$5:$B$14,MATCH(E4,Parameters!$A$5:$A$14,0)),""),"") -> 1 | X4: =IFERROR(IF(ISNUMBER(INDEX(Parameters!$B$5:$B$14,MATCH(F4,Parameters!$A$5:$A$14,0))),INDEX(Parameters!$B$5:$B$14,MATCH(F4,Parameters!$A$5:$A$14,0)),""),"") -> 1 | Y4: =IF(G4<>"",1,IF(ISNUMBER(Parameters!$B$18),Parameters!$B$18,"")) -> 1 | Z4: =IF(I4<>"",IFERROR(IF(ISNUMBER(INDEX(Parameters!$B$5:$B$14,MATCH(I4,Parameters!$A$5:$A$14,0))),INDEX(Parameters!$B$5:$B$14,MATCH(I4,Parameters!$A$5:$A$14,0)),""),""),IF(ISNUMBER(Parameters!$B$21),Parameters!$B$21,"")) -> 1 | AA4: =IFERROR(IF(ISNUMBER(INDEX(Parameters!$B$5:$B$14,MATCH(J4,Parameters!$A$5:$A$14,0))),INDEX(Parameters!$B$5:$B$14,MATCH(J4,Parameters!$A$5:$A$14,0)),""),"") -> 1 | AB4: =IFERROR(IF(ISNUMBER(INDEX(Parameters!$B$5:$B$14,MATCH(K4,Parameters!$A$5:$A$14,0))),INDEX(Parameters!$B$5:$B$14,MATCH(K4,Parameters!$A$5:$A$14,0)),""),"") -> 1 | AC4: =IFERROR(IF(ISNUMBER(INDEX(Parameters!$B$5:$B$14,MATCH(L4,Parameters!$A$5:$A$14,0))),INDEX(Parameters!$B$5:$B$14,MATCH(L4,Parameters!$A$5:$A$14,0)),""),"") -> 1 | AD4: =IFERROR(IF(ISNUMBER(INDEX(Parameters!$B$5:$B$14,MATCH(M4,Parameters!$A$5:$A$14,0))),INDEX(Parameters!$B$5:$B$14,MATCH(M4,Parameters!$A$5:$A$14,0)),""),"") -> 1 | AE4: =IF(N4<>"",1,IF(ISNUMBER(Parameters!$B$19),Parameters!$B$19,"")) -> 1 | AF4: =IF((Parameters!$I$5*ISNUMBER(V4)+Parameters!$I$6*ISNUMBER(W4)+Parameters!$I$7*ISNUMBER(X4)+Parameters!$I$8*ISNUMBER(Y4))=0,"",(Parameters!$I$5*N(V4)+Parameters!$I$6*N(W4)+Parameters!$I$7*N(X4)+Parameters!$I$8*N(Y4))/(Parameters!$I$5*ISNUMBER(V4)+Parameters!$I$6*ISNUMBER(W4)+Parameters!$I$7*ISNUMBER(X4)+Parameters!$I$8*ISNUMBER(Y4))) -> 1 | AG4: =IF((Parameters!$I$9*ISNUMBER(Z4))=0,"",(Parameters!$I$9*N(Z4))/(Parameters!$I$9*ISNUMBER(Z4))) -> 1 | AH4: =IF((Parameters!$I$11*ISNUMBER(AA4)+Parameters!$I$12*ISNUMBER(AB4)+Parameters!$I$13*ISNUMBER(AC4)+Parameters!$I$14*ISNUMBER(AD4)+Parameters!$I$15*ISNUMBER(AE4))=0,"",(Parameters!$I$11*N(AA4)+Parameters!$I$12*N(AB4)+Parameters!$I$13*N(AC4)+Parameters!$I$14*N(AD4)+Parameters!$I$15*N(AE4))/(Parameters!$I$11*ISNUMBER(AA4)+Parameters!$I$12*ISNUMBER(AB4)+Parameters!$I$13*ISNUMBER(AC4)+Parameters!$I$14*ISNUMBER(AD4)+Parameters!$I$15*ISNUMBER(AE4))) -> 1 | AI4: =Parameters!$I$5*ISNUMBER(V4)+Parameters!$I$6*ISNUMBER(W4)+Parameters!$I$7*ISNUMBER(X4)+Parameters!$I$8*ISNUMBER(Y4)+Parameters!$I$9*ISNUMBER(Z4)+Parameters!$I$11*ISNUMBER(AA4)+Parameters!$I$12*ISNUMBER(AB4)+Parameters!$I$13*ISNUMBER(AC4)+Parameters!$I$14*ISNUMBER(AD4)+Parameters!$I$15*ISNUMBER(AE4) -> 95 | AJ4: =IF((Parameters!$I$5+Parameters!$I$6+Parameters!$I$7+Parameters!$I$8+Parameters!$I$9+Parameters!$I$11+Parameters!$I$12+Parameters!$I$13+Parameters!$I$14+Parameters!$I$15)=0,"",AI4/(Parameters!$I$5+Parameters!$I$6+Parameters!$I$7+Parameters!$I$8+Parameters!$I$9+Parameters!$I$11+Parameters!$I$12+Parameters!$I$13+Parameters!$I$14+Parameters!$I$15)) -> 1 | AK4: =IF(AND(ISNUMBER(AF4),ISNUMBER(AH4),OR(NOT((Parameters!$I$9)>0),ISNUMBER(AG4)),AJ4>=Parameters!$B$20),100*(Parameters!$F$18*N(AF4)+Parameters!$F$19*N(AG4)+Parameters!$F$20*N(AH4))/(Parameters!$F$18*ISNUMBER(AF4)+Parameters!$F$19*ISNUMBER(AG4)+Parameters!$F$20*ISNUMBER(AH4)),"") -> 100 | AL4: =IF(ISNUMBER(AK4),RANK(AK4,$AK$2:$AK$113),"") -> 1 | AM4: =IF(((D4="Implemented/available")+(E4="Implemented/available")+(J4="Implemented/available")+(K4="Implemented/available")+(L4="Implemented/available")+(M4="Implemented/available"))=0,"",(AND(D4="Implemented/available",O4<>"")+AND(E4="Implemented/available",P4<>"")+AND(J4="Implemented/available",Q4<>"")+AND(K4="Implemented/available",R4<>"")+AND(L4="Implemented/available",S4<>"")+AND(M4="Implemented/available",T4<>""))/((D4="Implemented/available")+(E4="Implemented/available")+(J4="Implemented/available")+(K4="Implemented/available")+(L4="Implemented/available")+(M4="Implemented/available"))) -> 1
A5: VuFind® | B5: Open Library Foundation | C5: Discovery system | D5: Implemented/available | E5: Implemented/available | F5: Implemented/available | G5: Advisory board or steering committee | I5: Formal | J5: Implemented/available | K5: No direct costs | L5: Implemented/available | M5: Implemented/available | N5: It Takes a Village Open Source Software Sustainability toolkit | O5: https://github.com/vufind-org/vufind/blob/dev/GOVERNANCE.md | P5: https://vufind.org/wiki/community:pmc_meetings | Q5: https://vufind.org/wiki/accessibility | S5: https://github.com/vufind-org/vufind/blob/dev/CODE_OF_CONDUCT.md | T5: https://vufind.org/wiki/configuration:user_privacy | U5: https://github.com/vufind-org/vufind/blob/dev/GOVERNANCE.md | V5: =IFERROR(IF(ISNUMBER(INDEX(Parameters!$B$5:$B$14,MATCH(D5,Parameters!$A$5:$A$14,0))),INDEX(Parameters!$B$5:$B$14,MATCH(D5,Parameters!$A$5:$A$14,0)),""),"") -> 1 | W5: =IFERROR(IF(ISNUMBER(INDEX(Parameters!$B$5:$B$14,MATCH(E5,Parameters!$A$5:$A$14,0))),INDEX(Parameters!$B$5:$B$14,MATCH(E5,Parameters!$A$5:$A$14,0)),""),"") -> 1 | X5: =IFERROR(IF(ISNUMBER(INDEX(Parameters!$B$5:$B$14,MATCH(F5,Parameters!$A$5:$A$14,0))),INDEX(Parameters!$B$5:$B$14,MATCH(F5,Parameters!$A$5:$A$14,0)),""),"") -> 1 | Y5: =IF(G5<>"",1,IF(ISNUMBER(Parameters!$B$18),Parameters!$B$18,"")) -> 1 | Z5: =IF(I5<>"",IFERROR(IF(ISNUMBER(INDEX(Parameters!$B$5:$B$14,MATCH(I5,Parameters!$A$5:$A$14,0))),INDEX(Parameters!$B$5:$B$14,MATCH(I5,Parameters!$A$5:$A$14,0)),""),""),IF(ISNUMBER(Parameters!$B$21),Parameters!$B$21,"")) -> 1 | AA5: =IFERROR(IF(ISNUMBER(INDEX(Parameters!$B$5:$B$14,MATCH(J5,Parameters!$A$5:$A$14,0))),INDEX(Parameters!$B$5:$B$14,MATCH(J5,Parameters!$A$5:$A$14,0)),""),"") -> 1 | AB5: =IFERROR(IF(ISNUMBER(INDEX(Parameters!$B$5:$B$14,MATCH(K5,Parameters!$A$5:$A$14,0))),INDEX(Parameters!$B$5:$B$14,MATCH(K5,Parameters!$A$5:$A$14,0)),""),"") -> 1 | AC5: =IFERROR(IF(ISNUMBER(INDEX(Parameters!$B$5:$B$14,MATCH(L5,Parameters!$A$5:$A$14,0))),INDEX(Parameters!$B$5:$B$14,MATCH(L5,Parameters!$A$5:$A$14,0)),""),"") -> 1 | AD5: =IFERROR(IF(ISNUMBER(INDEX(Parameters!$B$5:$B$14,MATCH(M5,Parameters!$A$5:$A$14,0))),INDEX(Parameters!$B$5:$B$14,MATCH(M5,Parameters!$A$5:$A$14,0)),""),"") -> 1 | AE5: =IF(N5<>"",1,IF(ISNUMBER(Parameters!$B$19),Parameters!$B$19,"")) -> 1 | AF5: =IF((Parameters!$I$5*ISNUMBER(V5)+Parameters!$I$6*ISNUMBER(W5)+Parameters!$I$7*ISNUMBER(X5)+Parameters!$I$8*ISNUMBER(Y5))=0,"",(Parameters!$I$5*N(V5)+Parameters!$I$6*N(W5)+Parameters!$I$7*N(X5)+Parameters!$I$8*N(Y5))/(Parameters!$I$5*ISNUMBER(V5)+Parameters!$I$6*ISNUMBER(W5)+Parameters!$I$7*ISNUMBER(X5)+Parameters!$I$8*ISNUMBER(Y5))) -> 1 | AG5: =IF((Parameters!$I$9*ISNUMBER(Z5))=0,"",(Parameters!$I$9*N(Z5))/(Parameters!$I$9*ISNUMBER(Z5))) -> 1 | AH5: =IF((Parameters!$I$11*ISNUMBER(AA5)+Parameters!$I$12*ISNUMBER(AB5)+Parameters!$I$13*ISNUMBER(AC5)+Parameters!$I$14*ISNUMBER(AD5)+Parameters!$I$15*ISNUMBER(AE5))=0,"",(Parameters!$I$11*N(AA5)+Parameters!$I$12*N(AB5)+Parameters!$I$13*N(AC5)+Parameters!$I$14*N(AD5)+Parameters!$I$15*N(AE5))/(Parameters!$I$11*ISNUMBER(AA5)+Parameters!$I$12*ISNUMBER(AB5)+Parameters!$I$13*ISNUMBER(AC5)+Parameters!$I$14*ISNUMBER(AD5)+Parameters!$I$15*ISNUMBER(AE5))) -> 1 | AI5: =Parameters!$I$5*ISNUMBER(V5)+Parameters!$I$6*ISNUMBER(W5)+Parameters!$I$7*ISNUMBER(X5)+Parameters!$I$8*ISNUMBER(Y5)+Parameters!$I$9*ISNUMBER(Z5)+Parameters!$I$11*ISNUMBER(AA5)+Parameters!$I$12*ISNUMBER(AB5)+Parameters!$I$13*ISNUMBER(AC5)+Parameters!$I$14*ISNUMBER(AD5)+Parameters!$I$15*ISNUMBER(AE5) -> 95 | AJ5: =IF((Parameters!$I$5+Parameters!$I$6+Parameters!$I$7+Parameters!$I$8+Parameters!$I$9+Parameters!$I$11+Parameters!$I$12+Parameters!$I$13+Parameters!$I$14+Parameters!$I$15)=0,"",AI5/(Parameters!$I$5+Parameters!$I$6+Parameters!$I$7+Parameters!$I$8+Parameters!$I$9+Parameters!$I$11+Parameters!$I$12+Parameters!$I$13+Parameters!$I$14+Parameters!$I$15)) -> 1 | AK5: =IF(AND(ISNUMBER(AF5),ISNUMBER(AH5),OR(NOT((Parameters!$I$9)>0),ISNUMBER(AG5)),AJ5>=Parameters!$B$20),100*(Parameters!$F$18*N(AF5)+Parameters!$F$19*N(AG5)+Parameters!$F$20*N(AH5))/(Parameters!$F$18*ISNUMBER(AF5)+Parameters!$F$19*ISNUMBER(AG5)+Parameters!$F$20*ISNUMBER(AH5)),"") -> 100 | AL5: =IF(ISNUMBER(AK5),RANK(AK5,$AK$2:$AK$113),"") -> 1 | AM5: =IF(((D5="Implemented/available")+(E5="Implemented/available")+(J5="Implemented/available")+(K5="Implemented/available")+(L5="Implemented/available")+(M5="Implemented/available"))=0,"",(AND(D5="Implemented/available",O5<>"")+AND(E5="Implemented/available",P5<>"")+AND(J5="Implemented/available",Q5<>"")+AND(K5="Implemented/available",R5<>"")+AND(L5="Implemented/available",S5<>"")+AND(M5="Implemented/available",T5<>""))/((D5="Implemented/available")+(E5="Implemented/available")+(J5="Implemented/available")+(K5="Implemented/available")+(L5="Implemented/available")+(M5="Implemented/available"))) -> 1
A6: COUNTER Code of Practice | B6: COUNTER Metrics | C6: Standard, specification or protocol | D6: Implemented/available | E6: Implemented/available | F6: Implemented/available | G6: Multi-board governance | I6: Formal | J6: Implemented/available | K6: Implemented/available | L6: In progress | M6: Implemented/available | N6: Principles for Open Scholarly Infrastructure (POSI) | O6: https://www.countermetrics.org/about/people/ | P6: https://www.countermetrics.org/category/agm-minutes/ | Q6: https://www.countermetrics.org/accessibility/ | R6: https://www.countermetrics.org/members/ | T6: https://www.countermetrics.org/privacy-data-protection/ | U6: https://find-and-update.company-information.service.gov.uk/company/04865179/filing-history | V6: =IFERROR(IF(ISNUMBER(INDEX(Parameters!$B$5:$B$14,MATCH(D6,Parameters!$A$5:$A$14,0))),INDEX(Parameters!$B$5:$B$14,MATCH(D6,Parameters!$A$5:$A$14,0)),""),"") -> 1 | W6: =IFERROR(IF(ISNUMBER(INDEX(Parameters!$B$5:$B$14,MATCH(E6,Parameters!$A$5:$A$14,0))),INDEX(Parameters!$B$5:$B$14,MATCH(E6,Parameters!$A$5:$A$14,0)),""),"") -> 1 | X6: =IFERROR(IF(ISNUMBER(INDEX(Parameters!$B$5:$B$14,MATCH(F6,Parameters!$A$5:$A$14,0))),INDEX(Parameters!$B$5:$B$14,MATCH(F6,Parameters!$A$5:$A$14,0)),""),"") -> 1 | Y6: =IF(G6<>"",1,IF(ISNUMBER(Parameters!$B$18),Parameters!$B$18,"")) -> 1 | Z6: =IF(I6<>"",IFERROR(IF(ISNUMBER(INDEX(Parameters!$B$5:$B$14,MATCH(I6,Parameters!$A$5:$A$14,0))),INDEX(Parameters!$B$5:$B$14,MATCH(I6,Parameters!$A$5:$A$14,0)),""),""),IF(ISNUMBER(Parameters!$B$21),Parameters!$B$21,"")) -> 1 | AA6: =IFERROR(IF(ISNUMBER(INDEX(Parameters!$B$5:$B$14,MATCH(J6,Parameters!$A$5:$A$14,0))),INDEX(Parameters!$B$5:$B$14,MATCH(J6,Parameters!$A$5:$A$14,0)),""),"") -> 1 | AB6: =IFERROR(IF(ISNUMBER(INDEX(Parameters!$B$5:$B$14,MATCH(K6,Parameters!$A$5:$A$14,0))),INDEX(Parameters!$B$5:$B$14,MATCH(K6,Parameters!$A$5:$A$14,0)),""),"") -> 1 | AC6: =IFERROR(IF(ISNUMBER(INDEX(Parameters!$B$5:$B$14,MATCH(L6,Parameters!$A$5:$A$14,0))),INDEX(Parameters!$B$5:$B$14,MATCH(L6,Parameters!$A$5:$A$14,0)),""),"") -> 0.67 | AD6: =IFERROR(IF(ISNUMBER(INDEX(Parameters!$B$5:$B$14,MATCH(M6,Parameters!$A$5:$A$14,0))),INDEX(Parameters!$B$5:$B$14,MATCH(M6,Parameters!$A$5:$A$14,0)),""),"") -> 1 | AE6: =IF(N6<>"",1,IF(ISNUMBER(Parameters!$B$19),Parameters!$B$19,"")) -> 1 | AF6: =IF((Parameters!$I$5*ISNUMBER(V6)+Parameters!$I$6*ISNUMBER(W6)+Parameters!$I$7*ISNUMBER(X6)+Parameters!$I$8*ISNUMBER(Y6))=0,"",(Parameters!$I$5*N(V6)+Parameters!$I$6*N(W6)+Parameters!$I$7*N(X6)+Parameters!$I$8*N(Y6))/(Parameters!$I$5*ISNUMBER(V6)+Parameters!$I$6*ISNUMBER(W6)+Parameters!$I$7*ISNUMBER(X6)+Parameters!$I$8*ISNUMBER(Y6))) -> 1 | AG6: =IF((Parameters!$I$9*ISNUMBER(Z6))=0,"",(Parameters!$I$9*N(Z6))/(Parameters!$I$9*ISNUMBER(Z6))) -> 1 | AH6: =IF((Parameters!$I$11*ISNUMBER(AA6)+Parameters!$I$12*ISNUMBER(AB6)+Parameters!$I$13*ISNUMBER(AC6)+Parameters!$I$14*ISNUMBER(AD6)+Parameters!$I$15*ISNUMBER(AE6))=0,"",(Parameters!$I$11*N(AA6)+Parameters!$I$12*N(AB6)+Parameters!$I$13*N(AC6)+Parameters!$I$14*N(AD6)+Parameters!$I$15*N(AE6))/(Parameters!$I$11*ISNUMBER(AA6)+Parameters!$I$12*ISNUMBER(AB6)+Parameters!$I$13*ISNUMBER(AC6)+Parameters!$I$14*ISNUMBER(AD6)+Parameters!$I$15*ISNUMBER(AE6))) -> 0.934 | AI6: =Parameters!$I$5*ISNUMBER(V6)+Parameters!$I$6*ISNUMBER(W6)+Parameters!$I$7*ISNUMBER(X6)+Parameters!$I$8*ISNUMBER(Y6)+Parameters!$I$9*ISNUMBER(Z6)+Parameters!$I$11*ISNUMBER(AA6)+Parameters!$I$12*ISNUMBER(AB6)+Parameters!$I$13*ISNUMBER(AC6)+Parameters!$I$14*ISNUMBER(AD6)+Parameters!$I$15*ISNUMBER(AE6) -> 95 | AJ6: =IF((Parameters!$I$5+Parameters!$I$6+Parameters!$I$7+Parameters!$I$8+Parameters!$I$9+Parameters!$I$11+Parameters!$I$12+Parameters!$I$13+Parameters!$I$14+Parameters!$I$15)=0,"",AI6/(Parameters!$I$5+Parameters!$I$6+Parameters!$I$7+Parameters!$I$8+Parameters!$I$9+Parameters!$I$11+Parameters!$I$12+Parameters!$I$13+Parameters!$I$14+Parameters!$I$15)) -> 1 | AK6: =IF(AND(ISNUMBER(AF6),ISNUMBER(AH6),OR(NOT((Parameters!$I$9)>0),ISNUMBER(AG6)),AJ6>=Parameters!$B$20),100*(Parameters!$F$18*N(AF6)+Parameters!$F$19*N(AG6)+Parameters!$F$20*N(AH6))/(Parameters!$F$18*ISNUMBER(AF6)+Parameters!$F$19*ISNUMBER(AG6)+Parameters!$F$20*ISNUMBER(AH6)),"") -> 97.69 | AL6: =IF(ISNUMBER(AK6),RANK(AK6,$AK$2:$AK$113),"") -> 5 | AM6: =IF(((D6="Implemented/available")+(E6="Implemented/available")+(J6="Implemented/available")+(K6="Implemented/available")+(L6="Implemented/available")+(M6="Implemented/available"))=0,"",(AND(D6="Implemented/available",O6<>"")+AND(E6="Implemented/available",P6<>"")+AND(J6="Implemented/available",Q6<>"")+AND(K6="Implemented/available",R6<>"")+AND(L6="Implemented/available",S6<>"")+AND(M6="Implemented/available",T6<>""))/((D6="Implemented/available")+(E6="Implemented/available")+(J6="Implemented/available")+(K6="Implemented/available")+(L6="Implemented/available")+(M6="Implemented/available"))) -> 1
A7: Crossref Metadata Retrieval | B7: Crossref | C7: Open scholarly dataset | D7: Implemented/available | E7: Implemented/available | F7: Implemented/available | G7: Multi-board governance | I7: Formal | J7: In progress | K7: Implemented/available | L7: Implemented/available | M7: Implemented/available | N7: Principles for Open Scholarly Infrastructure (POSI) | O7: https://www.crossref.org/board-and-governance/ | P7: https://www.crossref.org/board-and-governance/ | R7: https://www.crossref.org/fees/ | S7: https://www.crossref.org/gem/ | T7: https://www.crossref.org/operations-and-sustainability/privacy/ | U7: https://www.crossref.org/board-and-governance/bylaws/ | V7: =IFERROR(IF(ISNUMBER(INDEX(Parameters!$B$5:$B$14,MATCH(D7,Parameters!$A$5:$A$14,0))),INDEX(Parameters!$B$5:$B$14,MATCH(D7,Parameters!$A$5:$A$14,0)),""),"") -> 1 | W7: =IFERROR(IF(ISNUMBER(INDEX(Parameters!$B$5:$B$14,MATCH(E7,Parameters!$A$5:$A$14,0))),INDEX(Parameters!$B$5:$B$14,MATCH(E7,Parameters!$A$5:$A$14,0)),""),"") -> 1 | X7: =IFERROR(IF(ISNUMBER(INDEX(Parameters!$B$5:$B$14,MATCH(F7,Parameters!$A$5:$A$14,0))),INDEX(Parameters!$B$5:$B$14,MATCH(F7,Parameters!$A$5:$A$14,0)),""),"") -> 1 | Y7: =IF(G7<>"",1,IF(ISNUMBER(Parameters!$B$18),Parameters!$B$18,"")) -> 1 | Z7: =IF(I7<>"",IFERROR(IF(ISNUMBER(INDEX(Parameters!$B$5:$B$14,MATCH(I7,Parameters!$A$5:$A$14,0))),INDEX(Parameters!$B$5:$B$14,MATCH(I7,Parameters!$A$5:$A$14,0)),""),""),IF(ISNUMBER(Parameters!$B$21),Parameters!$B$21,"")) -> 1 | AA7: =IFERROR(IF(ISNUMBER(INDEX(Parameters!$B$5:$B$14,MATCH(J7,Parameters!$A$5:$A$14,0))),INDEX(Parameters!$B$5:$B$14,MATCH(J7,Parameters!$A$5:$A$14,0)),""),"") -> 0.67 | AB7: =IFERROR(IF(ISNUMBER(INDEX(Parameters!$B$5:$B$14,MATCH(K7,Parameters!$A$5:$A$14,0))),INDEX(Parameters!$B$5:$B$14,MATCH(K7,Parameters!$A$5:$A$14,0)),""),"") -> 1 | AC7: =IFERROR(IF(ISNUMBER(INDEX(Parameters!$B$5:$B$14,MATCH(L7,Parameters!$A$5:$A$14,0))),INDEX(Parameters!$B$5:$B$14,MATCH(L7,Parameters!$A$5:$A$14,0)),""),"") -> 1 | AD7: =IFERROR(IF(ISNUMBER(INDEX(Parameters!$B$5:$B$14,MATCH(M7,Parameters!$A$5:$A$14,0))),INDEX(Parameters!$B$5:$B$14,MATCH(M7,Parameters!$A$5:$A$14,0)),""),"") -> 1 | AE7: =IF(N7<>"",1,IF(ISNUMBER(Parameters!$B$19),Parameters!$B$19,"")) -> 1 | AF7: =IF((Parameters!$I$5*ISNUMBER(V7)+Parameters!$I$6*ISNUMBER(W7)+Parameters!$I$7*ISNUMBER(X7)+Parameters!$I$8*ISNUMBER(Y7))=0,"",(Parameters!$I$5*N(V7)+Parameters!$I$6*N(W7)+Parameters!$I$7*N(X7)+Parameters!$I$8*N(Y7))/(Parameters!$I$5*ISNUMBER(V7)+Parameters!$I$6*ISNUMBER(W7)+Parameters!$I$7*ISNUMBER(X7)+Parameters!$I$8*ISNUMBER(Y7))) -> 1 | AG7: =IF((Parameters!$I$9*ISNUMBER(Z7))=0,"",(Parameters!$I$9*N(Z7))/(Parameters!$I$9*ISNUMBER(Z7))) -> 1 | AH7: =IF((Parameters!$I$11*ISNUMBER(AA7)+Parameters!$I$12*ISNUMBER(AB7)+Parameters!$I$13*ISNUMBER(AC7)+Parameters!$I$14*ISNUMBER(AD7)+Parameters!$I$15*ISNUMBER(AE7))=0,"",(Parameters!$I$11*N(AA7)+Parameters!$I$12*N(AB7)+Parameters!$I$13*N(AC7)+Parameters!$I$14*N(AD7)+Parameters!$I$15*N(AE7))/(Parameters!$I$11*ISNUMBER(AA7)+Parameters!$I$12*ISNUMBER(AB7)+Parameters!$I$13*ISNUMBER(AC7)+Parameters!$I$14*ISNUMBER(AD7)+Parameters!$I$15*ISNUMBER(AE7))) -> 0.934 | AI7: =Parameters!$I$5*ISNUMBER(V7)+Parameters!$I$6*ISNUMBER(W7)+Parameters!$I$7*ISNUMBER(X7)+Parameters!$I$8*ISNUMBER(Y7)+Parameters!$I$9*ISNUMBER(Z7)+Parameters!$I$11*ISNUMBER(AA7)+Parameters!$I$12*ISNUMBER(AB7)+Parameters!$I$13*ISNUMBER(AC7)+Parameters!$I$14*ISNUMBER(AD7)+Parameters!$I$15*ISNUMBER(AE7) -> 95 | AJ7: =IF((Parameters!$I$5+Parameters!$I$6+Parameters!$I$7+Parameters!$I$8+Parameters!$I$9+Parameters!$I$11+Parameters!$I$12+Parameters!$I$13+Parameters!$I$14+Parameters!$I$15)=0,"",AI7/(Parameters!$I$5+Parameters!$I$6+Parameters!$I$7+Parameters!$I$8+Parameters!$I$9+Parameters!$I$11+Parameters!$I$12+Parameters!$I$13+Parameters!$I$14+Parameters!$I$15)) -> 1 | AK7: =IF(AND(ISNUMBER(AF7),ISNUMBER(AH7),OR(NOT((Parameters!$I$9)>0),ISNUMBER(AG7)),AJ7>=Parameters!$B$20),100*(Parameters!$F$18*N(AF7)+Parameters!$F$19*N(AG7)+Parameters!$F$20*N(AH7))/(Parameters!$F$18*ISNUMBER(AF7)+Parameters!$F$19*ISNUMBER(AG7)+Parameters!$F$20*ISNUMBER(AH7)),"") -> 97.69 | AL7: =IF(ISNUMBER(AK7),RANK(AK7,$AK$2:$AK$113),"") -> 5 | AM7: =IF(((D7="Implemented/available")+(E7="Implemented/available")+(J7="Implemented/available")+(K7="Implemented/available")+(L7="Implemented/available")+(M7="Implemented/available"))=0,"",(AND(D7="Implemented/available",O7<>"")+AND(E7="Implemented/available",P7<>"")+AND(J7="Implemented/available",Q7<>"")+AND(K7="Implemented/available",R7<>"")+AND(L7="Implemented/available",S7<>"")+AND(M7="Implemented/available",T7<>""))/((D7="Implemented/available")+(E7="Implemented/available")+(J7="Implemented/available")+(K7="Implemented/available")+(L7="Implemented/available")+(M7="Implemented/available"))) -> 1
A8: PKP Preservation Network | B8: Public Knowledge Project (PKP) | C8: Digital preservation service | D8: Implemented/available | E8: Implemented/available | F8: Implemented/available | G8: Multi-board governance | I8: Formal | J8: Implemented/available | K8: No direct costs | L8: In progress | M8: Implemented/available | N8: Principles for Open Scholarly Infrastructure (POSI) | O8: https://pkp.sfu.ca/about/governance/ | P8: https://pkp.sfu.ca/interest-groups/ | Q8: https://pkp.sfu.ca/general-accessibility-statement/ | T8: https://pkp.sfu.ca/privacy-policy/ | U8: http://www.sfu.ca/policies/gazette/board.html | V8: =IFERROR(IF(ISNUMBER(INDEX(Parameters!$B$5:$B$14,MATCH(D8,Parameters!$A$5:$A$14,0))),INDEX(Parameters!$B$5:$B$14,MATCH(D8,Parameters!$A$5:$A$14,0)),""),"") -> 1 | W8: =IFERROR(IF(ISNUMBER(INDEX(Parameters!$B$5:$B$14,MATCH(E8,Parameters!$A$5:$A$14,0))),INDEX(Parameters!$B$5:$B$14,MATCH(E8,Parameters!$A$5:$A$14,0)),""),"") -> 1 | X8: =IFERROR(IF(ISNUMBER(INDEX(Parameters!$B$5:$B$14,MATCH(F8,Parameters!$A$5:$A$14,0))),INDEX(Parameters!$B$5:$B$14,MATCH(F8,Parameters!$A$5:$A$14,0)),""),"") -> 1 | Y8: =IF(G8<>"",1,IF(ISNUMBER(Parameters!$B$18),Parameters!$B$18,"")) -> 1 | Z8: =IF(I8<>"",IFERROR(IF(ISNUMBER(INDEX(Parameters!$B$5:$B$14,MATCH(I8,Parameters!$A$5:$A$14,0))),INDEX(Parameters!$B$5:$B$14,MATCH(I8,Parameters!$A$5:$A$14,0)),""),""),IF(ISNUMBER(Parameters!$B$21),Parameters!$B$21,"")) -> 1 | AA8: =IFERROR(IF(ISNUMBER(INDEX(Parameters!$B$5:$B$14,MATCH(J8,Parameters!$A$5:$A$14,0))),INDEX(Parameters!$B$5:$B$14,MATCH(J8,Parameters!$A$5:$A$14,0)),""),"") -> 1 | AB8: =IFERROR(IF(ISNUMBER(INDEX(Parameters!$B$5:$B$14,MATCH(K8,Parameters!$A$5:$A$14,0))),INDEX(Parameters!$B$5:$B$14,MATCH(K8,Parameters!$A$5:$A$14,0)),""),"") -> 1 | AC8: =IFERROR(IF(ISNUMBER(INDEX(Parameters!$B$5:$B$14,MATCH(L8,Parameters!$A$5:$A$14,0))),INDEX(Parameters!$B$5:$B$14,MATCH(L8,Parameters!$A$5:$A$14,0)),""),"") -> 0.67 | AD8: =IFERROR(IF(ISNUMBER(INDEX(Parameters!$B$5:$B$14,MATCH(M8,Parameters!$A$5:$A$14,0))),INDEX(Parameters!$B$5:$B$14,MATCH(M8,Parameters!$A$5:$A$14,0)),""),"") -> 1 | AE8: =IF(N8<>"",1,IF(ISNUMBER(Parameters!$B$19),Parameters!$B$19,"")) -> 1 | AF8: =IF((Parameters!$I$5*ISNUMBER(V8)+Parameters!$I$6*ISNUMBER(W8)+Parameters!$I$7*ISNUMBER(X8)+Parameters!$I$8*ISNUMBER(Y8))=0,"",(Parameters!$I$5*N(V8)+Parameters!$I$6*N(W8)+Parameters!$I$7*N(X8)+Parameters!$I$8*N(Y8))/(Parameters!$I$5*ISNUMBER(V8)+Parameters!$I$6*ISNUMBER(W8)+Parameters!$I$7*ISNUMBER(X8)+Parameters!$I$8*ISNUMBER(Y8))) -> 1 | AG8: =IF((Parameters!$I$9*ISNUMBER(Z8))=0,"",(Parameters!$I$9*N(Z8))/(Parameters!$I$9*ISNUMBER(Z8))) -> 1 | AH8: =IF((Parameters!$I$11*ISNUMBER(AA8)+Parameters!$I$12*ISNUMBER(AB8)+Parameters!$I$13*ISNUMBER(AC8)+Parameters!$I$14*ISNUMBER(AD8)+Parameters!$I$15*ISNUMBER(AE8))=0,"",(Parameters!$I$11*N(AA8)+Parameters!$I$12*N(AB8)+Parameters!$I$13*N(AC8)+Parameters!$I$14*N(AD8)+Parameters!$I$15*N(AE8))/(Parameters!$I$11*ISNUMBER(AA8)+Parameters!$I$12*ISNUMBER(AB8)+Parameters!$I$13*ISNUMBER(AC8)+Parameters!$I$14*ISNUMBER(AD8)+Parameters!$I$15*ISNUMBER(AE8))) -> 0.934 | AI8: =Parameters!$I$5*ISNUMBER(V8)+Parameters!$I$6*ISNUMBER(W8)+Parameters!$I$7*ISNUMBER(X8)+Parameters!$I$8*ISNUMBER(Y8)+Parameters!$I$9*ISNUMBER(Z8)+Parameters!$I$11*ISNUMBER(AA8)+Parameters!$I$12*ISNUMBER(AB8)+Parameters!$I$13*ISNUMBER(AC8)+Parameters!$I$14*ISNUMBER(AD8)+Parameters!$I$15*ISNUMBER(AE8) -> 95 | AJ8: =IF((Parameters!$I$5+Parameters!$I$6+Parameters!$I$7+Parameters!$I$8+Parameters!$I$9+Parameters!$I$11+Parameters!$I$12+Parameters!$I$13+Parameters!$I$14+Parameters!$I$15)=0,"",AI8/(Parameters!$I$5+Parameters!$I$6+Parameters!$I$7+Parameters!$I$8+Parameters!$I$9+Parameters!$I$11+Parameters!$I$12+Parameters!$I$13+Parameters!$I$14+Parameters!$I$15)) -> 1 | AK8: =IF(AND(ISNUMBER(AF8),ISNUMBER(AH8),OR(NOT((Parameters!$I$9)>0),ISNUMBER(AG8)),AJ8>=Parameters!$B$20),100*(Parameters!$F$18*N(AF8)+Parameters!$F$19*N(AG8)+Parameters!$F$20*N(AH8))/(Parameters!$F$18*ISNUMBER(AF8)+Parameters!$F$19*ISNUMBER(AG8)+Parameters!$F$20*ISNUMBER(AH8)),"") -> 97.69 | AL8: =IF(ISNUMBER(AK8),RANK(AK8,$AK$2:$AK$113),"") -> 5 | AM8: =IF(((D8="Implemented/available")+(E8="Implemented/available")+(J8="Implemented/available")+(K8="Implemented/available")+(L8="Implemented/available")+(M8="Implemented/available"))=0,"",(AND(D8="Implemented/available",O8<>"")+AND(E8="Implemented/available",P8<>"")+AND(J8="Implemented/available",Q8<>"")+AND(K8="Implemented/available",R8<>"")+AND(L8="Implemented/available",S8<>"")+AND(M8="Implemented/available",T8<>""))/((D8="Implemented/available")+(E8="Implemented/available")+(J8="Implemented/available")+(K8="Implemented/available")+(L8="Implemented/available")+(M8="Implemented/available"))) -> 1
A9: Fedora | B9: Lyrasis | C9: Repository software | D9: Implemented/available | E9: Implemented/available | F9: Implemented/available | G9: Advisory board or steering committee | H9: Other | I9: Formal | J9: Considering | K9: Implemented/available | L9: Implemented/available | M9: Implemented/available | N9: It Takes a Village Open Source Software Sustainability toolkit | O9: https://wiki.lyrasis.org/display/FF/Project+Governance | P9: https://wiki.lyrasis.org/display/FF/Meetings | R9: https://fedorarepository.org/membership | S9: https://lyrasis.org/job-bank/ | T9: https://fedorarepository.org/privacy-policy/ | U9: https://wiki.lyrasis.org/display/FF/Project+Governance | V9: =IFERROR(IF(ISNUMBER(INDEX(Parameters!$B$5:$B$14,MATCH(D9,Parameters!$A$5:$A$14,0))),INDEX(Parameters!$B$5:$B$14,MATCH(D9,Parameters!$A$5:$A$14,0)),""),"") -> 1 | W9: =IFERROR(IF(ISNUMBER(INDEX(Parameters!$B$5:$B$14,MATCH(E9,Parameters!$A$5:$A$14,0))),INDEX(Parameters!$B$5:$B$14,MATCH(E9,Parameters!$A$5:$A$14,0)),""),"") -> 1 | X9: =IFERROR(IF(ISNUMBER(INDEX(Parameters!$B$5:$B$14,MATCH(F9,Parameters!$A$5:$A$14,0))),INDEX(Parameters!$B$5:$B$14,MATCH(F9,Parameters!$A$5:$A$14,0)),""),"") -> 1 | Y9: =IF(G9<>"",1,IF(ISNUMBER(Parameters!$B$18),Parameters!$B$18,"")) -> 1 | Z9: =IF(I9<>"",IFERROR(IF(ISNUMBER(INDEX(Parameters!$B$5:$B$14,MATCH(I9,Parameters!$A$5:$A$14,0))),INDEX(Parameters!$B$5:$B$14,MATCH(I9,Parameters!$A$5:$A$14,0)),""),""),IF(ISNUMBER(Parameters!$B$21),Parameters!$B$21,"")) -> 1 | AA9: =IFERROR(IF(ISNUMBER(INDEX(Parameters!$B$5:$B$14,MATCH(J9,Parameters!$A$5:$A$14,0))),INDEX(Parameters!$B$5:$B$14,MATCH(J9,Parameters!$A$5:$A$14,0)),""),"") -> 0.33 | AB9: =IFERROR(IF(ISNUMBER(INDEX(Parameters!$B$5:$B$14,MATCH(K9,Parameters!$A$5:$A$14,0))),INDEX(Parameters!$B$5:$B$14,MATCH(K9,Parameters!$A$5:$A$14,0)),""),"") -> 1 | AC9: =IFERROR(IF(ISNUMBER(INDEX(Parameters!$B$5:$B$14,MATCH(L9,Parameters!$A$5:$A$14,0))),INDEX(Parameters!$B$5:$B$14,MATCH(L9,Parameters!$A$5:$A$14,0)),""),"") -> 1 | AD9: =IFERROR(IF(ISNUMBER(INDEX(Parameters!$B$5:$B$14,MATCH(M9,Parameters!$A$5:$A$14,0))),INDEX(Parameters!$B$5:$B$14,MATCH(M9,Parameters!$A$5:$A$14,0)),""),"") -> 1 | AE9: =IF(N9<>"",1,IF(ISNUMBER(Parameters!$B$19),Parameters!$B$19,"")) -> 1 | AF9: =IF((Parameters!$I$5*ISNUMBER(V9)+Parameters!$I$6*ISNUMBER(W9)+Parameters!$I$7*ISNUMBER(X9)+Parameters!$I$8*ISNUMBER(Y9))=0,"",(Parameters!$I$5*N(V9)+Parameters!$I$6*N(W9)+Parameters!$I$7*N(X9)+Parameters!$I$8*N(Y9))/(Parameters!$I$5*ISNUMBER(V9)+Parameters!$I$6*ISNUMBER(W9)+Parameters!$I$7*ISNUMBER(X9)+Parameters!$I$8*ISNUMBER(Y9))) -> 1 | AG9: =IF((Parameters!$I$9*ISNUMBER(Z9))=0,"",(Parameters!$I$9*N(Z9))/(Parameters!$I$9*ISNUMBER(Z9))) -> 1 | AH9: =IF((Parameters!$I$11*ISNUMBER(AA9)+Parameters!$I$12*ISNUMBER(AB9)+Parameters!$I$13*ISNUMBER(AC9)+Parameters!$I$14*ISNUMBER(AD9)+Parameters!$I$15*ISNUMBER(AE9))=0,"",(Parameters!$I$11*N(AA9)+Parameters!$I$12*N(AB9)+Parameters!$I$13*N(AC9)+Parameters!$I$14*N(AD9)+Parameters!$I$15*N(AE9))/(Parameters!$I$11*ISNUMBER(AA9)+Parameters!$I$12*ISNUMBER(AB9)+Parameters!$I$13*ISNUMBER(AC9)+Parameters!$I$14*ISNUMBER(AD9)+Parameters!$I$15*ISNUMBER(AE9))) -> 0.866 | AI9: =Parameters!$I$5*ISNUMBER(V9)+Parameters!$I$6*ISNUMBER(W9)+Parameters!$I$7*ISNUMBER(X9)+Parameters!$I$8*ISNUMBER(Y9)+Parameters!$I$9*ISNUMBER(Z9)+Parameters!$I$11*ISNUMBER(AA9)+Parameters!$I$12*ISNUMBER(AB9)+Parameters!$I$13*ISNUMBER(AC9)+Parameters!$I$14*ISNUMBER(AD9)+Parameters!$I$15*ISNUMBER(AE9) -> 95 | AJ9: =IF((Parameters!$I$5+Parameters!$I$6+Parameters!$I$7+Parameters!$I$8+Parameters!$I$9+Parameters!$I$11+Parameters!$I$12+Parameters!$I$13+Parameters!$I$14+Parameters!$I$15)=0,"",AI9/(Parameters!$I$5+Parameters!$I$6+Parameters!$I$7+Parameters!$I$8+Parameters!$I$9+Parameters!$I$11+Parameters!$I$12+Parameters!$I$13+Parameters!$I$14+Parameters!$I$15)) -> 1 | AK9: =IF(AND(ISNUMBER(AF9),ISNUMBER(AH9),OR(NOT((Parameters!$I$9)>0),ISNUMBER(AG9)),AJ9>=Parameters!$B$20),100*(Parameters!$F$18*N(AF9)+Parameters!$F$19*N(AG9)+Parameters!$F$20*N(AH9))/(Parameters!$F$18*ISNUMBER(AF9)+Parameters!$F$19*ISNUMBER(AG9)+Parameters!$F$20*ISNUMBER(AH9)),"") -> 95.31 | AL9: =IF(ISNUMBER(AK9),RANK(AK9,$AK$2:$AK$113),"") -> 8 | AM9: =IF(((D9="Implemented/available")+(E9="Implemented/available")+(J9="Implemented/available")+(K9="Implemented/available")+(L9="Implemented/available")+(M9="Implemented/available"))=0,"",(AND(D9="Implemented/available",O9<>"")+AND(E9="Implemented/available",P9<>"")+AND(J9="Implemented/available",Q9<>"")+AND(K9="Implemented/available",R9<>"")+AND(L9="Implemented/available",S9<>"")+AND(M9="Implemented/available",T9<>""))/((D9="Implemented/available")+(E9="Implemented/available")+(J9="Implemented/available")+(K9="Implemented/available")+(L9="Implemented/available")+(M9="Implemented/available"))) -> 1
A10: Hyku | B10: Samvera | C10: Repository software | D10: Implemented/available | E10: Implemented/available | F10: Implemented/available | G10: Advisory board or steering committee | I10: Formal | J10: Implemented/available | K10: No direct costs | L10: Considering | M10: Implemented/available | N10: COAR Next Generation Repositories Principles | It Takes a Village Open Source Software Sustainability toolkit | O10: https://samvera.atlassian.net/wiki/spaces/samvera/pages/1387986974/Samvera+Bylaws | P10: https://samvera.atlassian.net/wiki/spaces/samvera/pages/426512038/Notes+from+Samvera+Board+meetings+and+calls | Q10: https://repo.samvera.org/concern/generic_works/19cc96b4-6e98-4dba-b908-91e3439cad44 | T10: https://repo.samvera.org/concern/generic_works/66c8c363-ac35-4e65-bb3d-2631b7c80ff6?locale=en | U10: https://samvera.atlassian.net/wiki/spaces/samvera/pages/1387986974/Samvera+Bylaws | V10: =IFERROR(IF(ISNUMBER(INDEX(Parameters!$B$5:$B$14,MATCH(D10,Parameters!$A$5:$A$14,0))),INDEX(Parameters!$B$5:$B$14,MATCH(D10,Parameters!$A$5:$A$14,0)),""),"") -> 1 | W10: =IFERROR(IF(ISNUMBER(INDEX(Parameters!$B$5:$B$14,MATCH(E10,Parameters!$A$5:$A$14,0))),INDEX(Parameters!$B$5:$B$14,MATCH(E10,Parameters!$A$5:$A$14,0)),""),"") -> 1 | X10: =IFERROR(IF(ISNUMBER(INDEX(Parameters!$B$5:$B$14,MATCH(F10,Parameters!$A$5:$A$14,0))),INDEX(Parameters!$B$5:$B$14,MATCH(F10,Parameters!$A$5:$A$14,0)),""),"") -> 1 | Y10: =IF(G10<>"",1,IF(ISNUMBER(Parameters!$B$18),Parameters!$B$18,"")) -> 1 | Z10: =IF(I10<>"",IFERROR(IF(ISNUMBER(INDEX(Parameters!$B$5:$B$14,MATCH(I10,Parameters!$A$5:$A$14,0))),INDEX(Parameters!$B$5:$B$14,MATCH(I10,Parameters!$A$5:$A$14,0)),""),""),IF(ISNUMBER(Parameters!$B$21),Parameters!$B$21,"")) -> 1 | AA10: =IFERROR(IF(ISNUMBER(INDEX(Parameters!$B$5:$B$14,MATCH(J10,Parameters!$A$5:$A$14,0))),INDEX(Parameters!$B$5:$B$14,MATCH(J10,Parameters!$A$5:$A$14,0)),""),"") -> 1 | AB10: =IFERROR(IF(ISNUMBER(INDEX(Parameters!$B$5:$B$14,MATCH(K10,Parameters!$A$5:$A$14,0))),INDEX(Parameters!$B$5:$B$14,MATCH(K10,Parameters!$A$5:$A$14,0)),""),"") -> 1 | AC10: =IFERROR(IF(ISNUMBER(INDEX(Parameters!$B$5:$B$14,MATCH(L10,Parameters!$A$5:$A$14,0))),INDEX(Parameters!$B$5:$B$14,MATCH(L10,Parameters!$A$5:$A$14,0)),""),"") -> 0.33 | AD10: =IFERROR(IF(ISNUMBER(INDEX(Parameters!$B$5:$B$14,MATCH(M10,Parameters!$A$5:$A$14,0))),INDEX(Parameters!$B$5:$B$14,MATCH(M10,Parameters!$A$5:$A$14,0)),""),"") -> 1 | AE10: =IF(N10<>"",1,IF(ISNUMBER(Parameters!$B$19),Parameters!$B$19,"")) -> 1 | AF10: =IF((Parameters!$I$5*ISNUMBER(V10)+Parameters!$I$6*ISNUMBER(W10)+Parameters!$I$7*ISNUMBER(X10)+Parameters!$I$8*ISNUMBER(Y10))=0,"",(Parameters!$I$5*N(V10)+Parameters!$I$6*N(W10)+Parameters!$I$7*N(X10)+Parameters!$I$8*N(Y10))/(Parameters!$I$5*ISNUMBER(V10)+Parameters!$I$6*ISNUMBER(W10)+Parameters!$I$7*ISNUMBER(X10)+Parameters!$I$8*ISNUMBER(Y10))) -> 1 | AG10: =IF((Parameters!$I$9*ISNUMBER(Z10))=0,"",(Parameters!$I$9*N(Z10))/(Parameters!$I$9*ISNUMBER(Z10))) -> 1 | AH10: =IF((Parameters!$I$11*ISNUMBER(AA10)+Parameters!$I$12*ISNUMBER(AB10)+Parameters!$I$13*ISNUMBER(AC10)+Parameters!$I$14*ISNUMBER(AD10)+Parameters!$I$15*ISNUMBER(AE10))=0,"",(Parameters!$I$11*N(AA10)+Parameters!$I$12*N(AB10)+Parameters!$I$13*N(AC10)+Parameters!$I$14*N(AD10)+Parameters!$I$15*N(AE10))/(Parameters!$I$11*ISNUMBER(AA10)+Parameters!$I$12*ISNUMBER(AB10)+Parameters!$I$13*ISNUMBER(AC10)+Parameters!$I$14*ISNUMBER(AD10)+Parameters!$I$15*ISNUMBER(AE10))) -> 0.866 | AI10: =Parameters!$I$5*ISNUMBER(V10)+Parameters!$I$6*ISNUMBER(W10)+Parameters!$I$7*ISNUMBER(X10)+Parameters!$I$8*ISNUMBER(Y10)+Parameters!$I$9*ISNUMBER(Z10)+Parameters!$I$11*ISNUMBER(AA10)+Parameters!$I$12*ISNUMBER(AB10)+Parameters!$I$13*ISNUMBER(AC10)+Parameters!$I$14*ISNUMBER(AD10)+Parameters!$I$15*ISNUMBER(AE10) -> 95 | AJ10: =IF((Parameters!$I$5+Parameters!$I$6+Parameters!$I$7+Parameters!$I$8+Parameters!$I$9+Parameters!$I$11+Parameters!$I$12+Parameters!$I$13+Parameters!$I$14+Parameters!$I$15)=0,"",AI10/(Parameters!$I$5+Parameters!$I$6+Parameters!$I$7+Parameters!$I$8+Parameters!$I$9+Parameters!$I$11+Parameters!$I$12+Parameters!$I$13+Parameters!$I$14+Parameters!$I$15)) -> 1 | AK10: =IF(AND(ISNUMBER(AF10),ISNUMBER(AH10),OR(NOT((Parameters!$I$9)>0),ISNUMBER(AG10)),AJ10>=Parameters!$B$20),100*(Parameters!$F$18*N(AF10)+Parameters!$F$19*N(AG10)+Parameters!$F$20*N(AH10))/(Parameters!$F$18*ISNUMBER(AF10)+Parameters!$F$19*ISNUMBER(AG10)+Parameters!$F$20*ISNUMBER(AH10)),"") -> 95.31 | AL10: =IF(ISNUMBER(AK10),RANK(AK10,$AK$2:$AK$113),"") -> 8 | AM10: =IF(((D10="Implemented/available")+(E10="Implemented/available")+(J10="Implemented/available")+(K10="Implemented/available")+(L10="Implemented/available")+(M10="Implemented/available"))=0,"",(AND(D10="Implemented/available",O10<>"")+AND(E10="Implemented/available",P10<>"")+AND(J10="Implemented/available",Q10<>"")+AND(K10="Implemented/available",R10<>"")+AND(L10="Implemented/available",S10<>"")+AND(M10="Implemented/available",T10<>""))/((D10="Implemented/available")+(E10="Implemented/available")+(J10="Implemented/available")+(K10="Implemented/available")+(L10="Implemented/available")+(M10="Implemented/available"))) -> 1
A11: OpenAIRE Graph | B11: OpenAIRE | C11: Discovery system | Open scholarly dataset | D11: Implemented/available | E11: Unknown | F11: Implemented/available | G11: Advisory board or steering committee | I11: Formal | J11: Considering | K11: No direct costs | L11: Implemented/available | M11: Implemented/available | N11: Principles for Open Scholarly Infrastructure (POSI) | O11: https://www.openaire.eu/organisation-2 | S11: https://www.openaire.eu/openaire-gep | T11: https://www.openaire.eu/privacy-policy | U11: https://www.openaire.eu/organisation-2 | V11: =IFERROR(IF(ISNUMBER(INDEX(Parameters!$B$5:$B$14,MATCH(D11,Parameters!$A$5:$A$14,0))),INDEX(Parameters!$B$5:$B$14,MATCH(D11,Parameters!$A$5:$A$14,0)),""),"") -> 1 | W11: =IFERROR(IF(ISNUMBER(INDEX(Parameters!$B$5:$B$14,MATCH(E11,Parameters!$A$5:$A$14,0))),INDEX(Parameters!$B$5:$B$14,MATCH(E11,Parameters!$A$5:$A$14,0)),""),"") | X11: =IFERROR(IF(ISNUMBER(INDEX(Parameters!$B$5:$B$14,MATCH(F11,Parameters!$A$5:$A$14,0))),INDEX(Parameters!$B$5:$B$14,MATCH(F11,Parameters!$A$5:$A$14,0)),""),"") -> 1 | Y11: =IF(G11<>"",1,IF(ISNUMBER(Parameters!$B$18),Parameters!$B$18,"")) -> 1 | Z11: =IF(I11<>"",IFERROR(IF(ISNUMBER(INDEX(Parameters!$B$5:$B$14,MATCH(I11,Parameters!$A$5:$A$14,0))),INDEX(Parameters!$B$5:$B$14,MATCH(I11,Parameters!$A$5:$A$14,0)),""),""),IF(ISNUMBER(Parameters!$B$21),Parameters!$B$21,"")) -> 1 | AA11: =IFERROR(IF(ISNUMBER(INDEX(Parameters!$B$5:$B$14,MATCH(J11,Parameters!$A$5:$A$14,0))),INDEX(Parameters!$B$5:$B$14,MATCH(J11,Parameters!$A$5:$A$14,0)),""),"") -> 0.33 | AB11: =IFERROR(IF(ISNUMBER(INDEX(Parameters!$B$5:$B$14,MATCH(K11,Parameters!$A$5:$A$14,0))),INDEX(Parameters!$B$5:$B$14,MATCH(K11,Parameters!$A$5:$A$14,0)),""),"") -> 1 | AC11: =IFERROR(IF(ISNUMBER(INDEX(Parameters!$B$5:$B$14,MATCH(L11,Parameters!$A$5:$A$14,0))),INDEX(Parameters!$B$5:$B$14,MATCH(L11,Parameters!$A$5:$A$14,0)),""),"") -> 1 | AD11: =IFERROR(IF(ISNUMBER(INDEX(Parameters!$B$5:$B$14,MATCH(M11,Parameters!$A$5:$A$14,0))),INDEX(Parameters!$B$5:$B$14,MATCH(M11,Parameters!$A$5:$A$14,0)),""),"") -> 1 | AE11: =IF(N11<>"",1,IF(ISNUMBER(Parameters!$B$19),Parameters!$B$19,"")) -> 1 | AF11: =IF((Parameters!$I$5*ISNUMBER(V11)+Parameters!$I$6*ISNUMBER(W11)+Parameters!$I$7*ISNUMBER(X11)+Parameters!$I$8*ISNUMBER(Y11))=0,"",(Parameters!$I$5*N(V11)+Parameters!$I$6*N(W11)+Parameters!$I$7*N(X11)+Parameters!$I$8*N(Y11))/(Parameters!$I$5*ISNUMBER(V11)+Parameters!$I$6*ISNUMBER(W11)+Parameters!$I$7*ISNUMBER(X11)+Parameters!$I$8*ISNUMBER(Y11))) -> 1 | AG11: =IF((Parameters!$I$9*ISNUMBER(Z11))=0,"",(Parameters!$I$9*N(Z11))/(Parameters!$I$9*ISNUMBER(Z11))) -> 1 | AH11: =IF((Parameters!$I$11*ISNUMBER(AA11)+Parameters!$I$12*ISNUMBER(AB11)+Parameters!$I$13*ISNUMBER(AC11)+Parameters!$I$14*ISNUMBER(AD11)+Parameters!$I$15*ISNUMBER(AE11))=0,"",(Parameters!$I$11*N(AA11)+Parameters!$I$12*N(AB11)+Parameters!$I$13*N(AC11)+Parameters!$I$14*N(AD11)+Parameters!$I$15*N(AE11))/(Parameters!$I$11*ISNUMBER(AA11)+Parameters!$I$12*ISNUMBER(AB11)+Parameters!$I$13*ISNUMBER(AC11)+Parameters!$I$14*ISNUMBER(AD11)+Parameters!$I$15*ISNUMBER(AE11))) -> 0.866 | AI11: =Parameters!$I$5*ISNUMBER(V11)+Parameters!$I$6*ISNUMBER(W11)+Parameters!$I$7*ISNUMBER(X11)+Parameters!$I$8*ISNUMBER(Y11)+Parameters!$I$9*ISNUMBER(Z11)+Parameters!$I$11*ISNUMBER(AA11)+Parameters!$I$12*ISNUMBER(AB11)+Parameters!$I$13*ISNUMBER(AC11)+Parameters!$I$14*ISNUMBER(AD11)+Parameters!$I$15*ISNUMBER(AE11) -> 83 | AJ11: =IF((Parameters!$I$5+Parameters!$I$6+Parameters!$I$7+Parameters!$I$8+Parameters!$I$9+Parameters!$I$11+Parameters!$I$12+Parameters!$I$13+Parameters!$I$14+Parameters!$I$15)=0,"",AI11/(Parameters!$I$5+Parameters!$I$6+Parameters!$I$7+Parameters!$I$8+Parameters!$I$9+Parameters!$I$11+Parameters!$I$12+Parameters!$I$13+Parameters!$I$14+Parameters!$I$15)) -> 0.87368421 | AK11: =IF(AND(ISNUMBER(AF11),ISNUMBER(AH11),OR(NOT((Parameters!$I$9)>0),ISNUMBER(AG11)),AJ11>=Parameters!$B$20),100*(Parameters!$F$18*N(AF11)+Parameters!$F$19*N(AG11)+Parameters!$F$20*N(AH11))/(Parameters!$F$18*ISNUMBER(AF11)+Parameters!$F$19*ISNUMBER(AG11)+Parameters!$F$20*ISNUMBER(AH11)),"") -> 95.31 | AL11: =IF(ISNUMBER(AK11),RANK(AK11,$AK$2:$AK$113),"") -> 8 | AM11: =IF(((D11="Implemented/available")+(E11="Implemented/available")+(J11="Implemented/available")+(K11="Implemented/available")+(L11="Implemented/available")+(M11="Implemented/available"))=0,"",(AND(D11="Implemented/available",O11<>"")+AND(E11="Implemented/available",P11<>"")+AND(J11="Implemented/available",Q11<>"")+AND(K11="Implemented/available",R11<>"")+AND(L11="Implemented/available",S11<>"")+AND(M11="Implemented/available",T11<>""))/((D11="Implemented/available")+(E11="Implemented/available")+(J11="Implemented/available")+(K11="Implemented/available")+(L11="Implemented/available")+(M11="Implemented/available"))) -> 1
A12: Hyrax | B12: Samvera | C12: Repository software | D12: Implemented/available | E12: Implemented/available | F12: Implemented/available | G12: Advisory board or steering committee | H12: Provider | I12: Formal | J12: In progress | K12: No direct costs | L12: In progress | M12: In progress | N12: It Takes a Village Open Source Software Sustainability toolkit | O12: https://samvera.atlassian.net/wiki/spaces/samvera/pages/1387986974/Samvera+Bylaws | P12: https://samvera.atlassian.net/wiki/spaces/samvera/pages/426512038/Notes+from+Samvera+Board+meetings+and+calls | U12: https://samvera.atlassian.net/wiki/spaces/samvera/pages/1387986974/Samvera+Bylaws | V12: =IFERROR(IF(ISNUMBER(INDEX(Parameters!$B$5:$B$14,MATCH(D12,Parameters!$A$5:$A$14,0))),INDEX(Parameters!$B$5:$B$14,MATCH(D12,Parameters!$A$5:$A$14,0)),""),"") -> 1 | W12: =IFERROR(IF(ISNUMBER(INDEX(Parameters!$B$5:$B$14,MATCH(E12,Parameters!$A$5:$A$14,0))),INDEX(Parameters!$B$5:$B$14,MATCH(E12,Parameters!$A$5:$A$14,0)),""),"") -> 1 | X12: =IFERROR(IF(ISNUMBER(INDEX(Parameters!$B$5:$B$14,MATCH(F12,Parameters!$A$5:$A$14,0))),INDEX(Parameters!$B$5:$B$14,MATCH(F12,Parameters!$A$5:$A$14,0)),""),"") -> 1 | Y12: =IF(G12<>"",1,IF(ISNUMBER(Parameters!$B$18),Parameters!$B$18,"")) -> 1 | Z12: =IF(I12<>"",IFERROR(IF(ISNUMBER(INDEX(Parameters!$B$5:$B$14,MATCH(I12,Parameters!$A$5:$A$14,0))),INDEX(Parameters!$B$5:$B$14,MATCH(I12,Parameters!$A$5:$A$14,0)),""),""),IF(ISNUMBER(Parameters!$B$21),Parameters!$B$21,"")) -> 1 | AA12: =IFERROR(IF(ISNUMBER(INDEX(Parameters!$B$5:$B$14,MATCH(J12,Parameters!$A$5:$A$14,0))),INDEX(Parameters!$B$5:$B$14,MATCH(J12,Parameters!$A$5:$A$14,0)),""),"") -> 0.67 | AB12: =IFERROR(IF(ISNUMBER(INDEX(Parameters!$B$5:$B$14,MATCH(K12,Parameters!$A$5:$A$14,0))),INDEX(Parameters!$B$5:$B$14,MATCH(K12,Parameters!$A$5:$A$14,0)),""),"") -> 1 | AC12: =IFERROR(IF(ISNUMBER(INDEX(Parameters!$B$5:$B$14,MATCH(L12,Parameters!$A$5:$A$14,0))),INDEX(Parameters!$B$5:$B$14,MATCH(L12,Parameters!$A$5:$A$14,0)),""),"") -> 0.67 | AD12: =IFERROR(IF(ISNUMBER(INDEX(Parameters!$B$5:$B$14,MATCH(M12,Parameters!$A$5:$A$14,0))),INDEX(Parameters!$B$5:$B$14,MATCH(M12,Parameters!$A$5:$A$14,0)),""),"") -> 0.67 | AE12: =IF(N12<>"",1,IF(ISNUMBER(Parameters!$B$19),Parameters!$B$19,"")) -> 1 | AF12: =IF((Parameters!$I$5*ISNUMBER(V12)+Parameters!$I$6*ISNUMBER(W12)+Parameters!$I$7*ISNUMBER(X12)+Parameters!$I$8*ISNUMBER(Y12))=0,"",(Parameters!$I$5*N(V12)+Parameters!$I$6*N(W12)+Parameters!$I$7*N(X12)+Parameters!$I$8*N(Y12))/(Parameters!$I$5*ISNUMBER(V12)+Parameters!$I$6*ISNUMBER(W12)+Parameters!$I$7*ISNUMBER(X12)+Parameters!$I$8*ISNUMBER(Y12))) -> 1 | AG12: =IF((Parameters!$I$9*ISNUMBER(Z12))=0,"",(Parameters!$I$9*N(Z12))/(Parameters!$I$9*ISNUMBER(Z12))) -> 1 | AH12: =IF((Parameters!$I$11*ISNUMBER(AA12)+Parameters!$I$12*ISNUMBER(AB12)+Parameters!$I$13*ISNUMBER(AC12)+Parameters!$I$14*ISNUMBER(AD12)+Parameters!$I$15*ISNUMBER(AE12))=0,"",(Parameters!$I$11*N(AA12)+Parameters!$I$12*N(AB12)+Parameters!$I$13*N(AC12)+Parameters!$I$14*N(AD12)+Parameters!$I$15*N(AE12))/(Parameters!$I$11*ISNUMBER(AA12)+Parameters!$I$12*ISNUMBER(AB12)+Parameters!$I$13*ISNUMBER(AC12)+Parameters!$I$14*ISNUMBER(AD12)+Parameters!$I$15*ISNUMBER(AE12))) -> 0.802 | AI12: =Parameters!$I$5*ISNUMBER(V12)+Parameters!$I$6*ISNUMBER(W12)+Parameters!$I$7*ISNUMBER(X12)+Parameters!$I$8*ISNUMBER(Y12)+Parameters!$I$9*ISNUMBER(Z12)+Parameters!$I$11*ISNUMBER(AA12)+Parameters!$I$12*ISNUMBER(AB12)+Parameters!$I$13*ISNUMBER(AC12)+Parameters!$I$14*ISNUMBER(AD12)+Parameters!$I$15*ISNUMBER(AE12) -> 95 | AJ12: =IF((Parameters!$I$5+Parameters!$I$6+Parameters!$I$7+Parameters!$I$8+Parameters!$I$9+Parameters!$I$11+Parameters!$I$12+Parameters!$I$13+Parameters!$I$14+Parameters!$I$15)=0,"",AI12/(Parameters!$I$5+Parameters!$I$6+Parameters!$I$7+Parameters!$I$8+Parameters!$I$9+Parameters!$I$11+Parameters!$I$12+Parameters!$I$13+Parameters!$I$14+Parameters!$I$15)) -> 1 | AK12: =IF(AND(ISNUMBER(AF12),ISNUMBER(AH12),OR(NOT((Parameters!$I$9)>0),ISNUMBER(AG12)),AJ12>=Parameters!$B$20),100*(Parameters!$F$18*N(AF12)+Parameters!$F$19*N(AG12)+Parameters!$F$20*N(AH12))/(Parameters!$F$18*ISNUMBER(AF12)+Parameters!$F$19*ISNUMBER(AG12)+Parameters!$F$20*ISNUMBER(AH12)),"") -> 93.07 | AL12: =IF(ISNUMBER(AK12),RANK(AK12,$AK$2:$AK$113),"") -> 11 | AM12: =IF(((D12="Implemented/available")+(E12="Implemented/available")+(J12="Implemented/available")+(K12="Implemented/available")+(L12="Implemented/available")+(M12="Implemented/available"))=0,"",(AND(D12="Implemented/available",O12<>"")+AND(E12="Implemented/available",P12<>"")+AND(J12="Implemented/available",Q12<>"")+AND(K12="Implemented/available",R12<>"")+AND(L12="Implemented/available",S12<>"")+AND(M12="Implemented/available",T12<>""))/((D12="Implemented/available")+(E12="Implemented/available")+(J12="Implemented/available")+(K12="Implemented/available")+(L12="Implemented/available")+(M12="Implemented/available"))) -> 1
A13: Érudit | B13: Érudit | C13: Discovery system | Publishing system | Repository software | D13: Implemented/available | E13: Implemented/available | F13: Implemented/available | G13: Multi-board governance | I13: Formal | J13: Implemented/available | K13: No direct costs | L13: Implemented/available | M13: Implemented/available | O13: https://apropos.erudit.org/direction-et-conseils/?lang=en | P13: https://apropos.erudit.org/rapports-annuels/?lang=en | Q13: https://apropos.erudit.org/accessibility-statement/?lang=en | S13: https://apropos.erudit.org/equity-diversity-inclusion/?lang=en | T13: https://www.iubenda.com/privacy-policy/79766356 | U13: https://apropos.erudit.org/direction-et-conseils/?lang=en | V13: =IFERROR(IF(ISNUMBER(INDEX(Parameters!$B$5:$B$14,MATCH(D13,Parameters!$A$5:$A$14,0))),INDEX(Parameters!$B$5:$B$14,MATCH(D13,Parameters!$A$5:$A$14,0)),""),"") -> 1 | W13: =IFERROR(IF(ISNUMBER(INDEX(Parameters!$B$5:$B$14,MATCH(E13,Parameters!$A$5:$A$14,0))),INDEX(Parameters!$B$5:$B$14,MATCH(E13,Parameters!$A$5:$A$14,0)),""),"") -> 1 | X13: =IFERROR(IF(ISNUMBER(INDEX(Parameters!$B$5:$B$14,MATCH(F13,Parameters!$A$5:$A$14,0))),INDEX(Parameters!$B$5:$B$14,MATCH(F13,Parameters!$A$5:$A$14,0)),""),"") -> 1 | Y13: =IF(G13<>"",1,IF(ISNUMBER(Parameters!$B$18),Parameters!$B$18,"")) -> 1 | Z13: =IF(I13<>"",IFERROR(IF(ISNUMBER(INDEX(Parameters!$B$5:$B$14,MATCH(I13,Parameters!$A$5:$A$14,0))),INDEX(Parameters!$B$5:$B$14,MATCH(I13,Parameters!$A$5:$A$14,0)),""),""),IF(ISNUMBER(Parameters!$B$21),Parameters!$B$21,"")) -> 1 | AA13: =IFERROR(IF(ISNUMBER(INDEX(Parameters!$B$5:$B$14,MATCH(J13,Parameters!$A$5:$A$14,0))),INDEX(Parameters!$B$5:$B$14,MATCH(J13,Parameters!$A$5:$A$14,0)),""),"") -> 1 | AB13: =IFERROR(IF(ISNUMBER(INDEX(Parameters!$B$5:$B$14,MATCH(K13,Parameters!$A$5:$A$14,0))),INDEX(Parameters!$B$5:$B$14,MATCH(K13,Parameters!$A$5:$A$14,0)),""),"") -> 1 | AC13: =IFERROR(IF(ISNUMBER(INDEX(Parameters!$B$5:$B$14,MATCH(L13,Parameters!$A$5:$A$14,0))),INDEX(Parameters!$B$5:$B$14,MATCH(L13,Parameters!$A$5:$A$14,0)),""),"") -> 1 | AD13: =IFERROR(IF(ISNUMBER(INDEX(Parameters!$B$5:$B$14,MATCH(M13,Parameters!$A$5:$A$14,0))),INDEX(Parameters!$B$5:$B$14,MATCH(M13,Parameters!$A$5:$A$14,0)),""),"") -> 1 | AE13: =IF(N13<>"",1,IF(ISNUMBER(Parameters!$B$19),Parameters!$B$19,"")) -> 0 | AF13: =IF((Parameters!$I$5*ISNUMBER(V13)+Parameters!$I$6*ISNUMBER(W13)+Parameters!$I$7*ISNUMBER(X13)+Parameters!$I$8*ISNUMBER(Y13))=0,"",(Parameters!$I$5*N(V13)+Parameters!$I$6*N(W13)+Parameters!$I$7*N(X13)+Parameters!$I$8*N(Y13))/(Parameters!$I$5*ISNUMBER(V13)+Parameters!$I$6*ISNUMBER(W13)+Parameters!$I$7*ISNUMBER(X13)+Parameters!$I$8*ISNUMBER(Y13))) -> 1 | AG13: =IF((Parameters!$I$9*ISNUMBER(Z13))=0,"",(Parameters!$I$9*N(Z13))/(Parameters!$I$9*ISNUMBER(Z13))) -> 1 | AH13: =IF((Parameters!$I$11*ISNUMBER(AA13)+Parameters!$I$12*ISNUMBER(AB13)+Parameters!$I$13*ISNUMBER(AC13)+Parameters!$I$14*ISNUMBER(AD13)+Parameters!$I$15*ISNUMBER(AE13))=0,"",(Parameters!$I$11*N(AA13)+Parameters!$I$12*N(AB13)+Parameters!$I$13*N(AC13)+Parameters!$I$14*N(AD13)+Parameters!$I$15*N(AE13))/(Parameters!$I$11*ISNUMBER(AA13)+Parameters!$I$12*ISNUMBER(AB13)+Parameters!$I$13*ISNUMBER(AC13)+Parameters!$I$14*ISNUMBER(AD13)+Parameters!$I$15*ISNUMBER(AE13))) -> 0.8 | AI13: =Parameters!$I$5*ISNUMBER(V13)+Parameters!$I$6*ISNUMBER(W13)+Parameters!$I$7*ISNUMBER(X13)+Parameters!$I$8*ISNUMBER(Y13)+Parameters!$I$9*ISNUMBER(Z13)+Parameters!$I$11*ISNUMBER(AA13)+Parameters!$I$12*ISNUMBER(AB13)+Parameters!$I$13*ISNUMBER(AC13)+Parameters!$I$14*ISNUMBER(AD13)+Parameters!$I$15*ISNUMBER(AE13) -> 95 | AJ13: =IF((Parameters!$I$5+Parameters!$I$6+Parameters!$I$7+Parameters!$I$8+Parameters!$I$9+Parameters!$I$11+Parameters!$I$12+Parameters!$I$13+Parameters!$I$14+Parameters!$I$15)=0,"",AI13/(Parameters!$I$5+Parameters!$I$6+Parameters!$I$7+Parameters!$I$8+Parameters!$I$9+Parameters!$I$11+Parameters!$I$12+Parameters!$I$13+Parameters!$I$14+Parameters!$I$15)) -> 1 | AK13: =IF(AND(ISNUMBER(AF13),ISNUMBER(AH13),OR(NOT((Parameters!$I$9)>0),ISNUMBER(AG13)),AJ13>=Parameters!$B$20),100*(Parameters!$F$18*N(AF13)+Parameters!$F$19*N(AG13)+Parameters!$F$20*N(AH13))/(Parameters!$F$18*ISNUMBER(AF13)+Parameters!$F$19*ISNUMBER(AG13)+Parameters!$F$20*ISNUMBER(AH13)),"") -> 93 | AL13: =IF(ISNUMBER(AK13),RANK(AK13,$AK$2:$AK$113),"") -> 12 | AM13: =IF(((D13="Implemented/available")+(E13="Implemented/available")+(J13="Implemented/available")+(K13="Implemented/available")+(L13="Implemented/available")+(M13="Implemented/available"))=0,"",(AND(D13="Implemented/available",O13<>"")+AND(E13="Implemented/available",P13<>"")+AND(J13="Implemented/available",Q13<>"")+AND(K13="Implemented/available",R13<>"")+AND(L13="Implemented/available",S13<>"")+AND(M13="Implemented/available",T13<>""))/((D13="Implemented/available")+(E13="Implemented/available")+(J13="Implemented/available")+(K13="Implemented/available")+(L13="Implemented/available")+(M13="Implemented/available"))) -> 1
A14: Europe PMC | B14: EMBL European Bioinformatics Institute (EMBL-EBI) | C14: Digital preservation system | Discovery system | Repository service | D14: Implemented/available | E14: Implemented/available | F14: Implemented/available | G14: Advisory board or steering committee | I14: Formal | J14: Implemented/available | K14: No direct costs | L14: Implemented/available | M14: Implemented/available | O14: https://europepmc.org/Governance | P14: https://europepmc.org/Governance | Q14: https://europepmc.org/Accessibility | S14: https://www.ebi.ac.uk/about/equality-in-science | T14: https://europepmc.org/PrivacyNotice | U14: https://europepmc.org/Governance | V14: =IFERROR(IF(ISNUMBER(INDEX(Parameters!$B$5:$B$14,MATCH(D14,Parameters!$A$5:$A$14,0))),INDEX(Parameters!$B$5:$B$14,MATCH(D14,Parameters!$A$5:$A$14,0)),""),"") -> 1 | W14: =IFERROR(IF(ISNUMBER(INDEX(Parameters!$B$5:$B$14,MATCH(E14,Parameters!$A$5:$A$14,0))),INDEX(Parameters!$B$5:$B$14,MATCH(E14,Parameters!$A$5:$A$14,0)),""),"") -> 1 | X14: =IFERROR(IF(ISNUMBER(INDEX(Parameters!$B$5:$B$14,MATCH(F14,Parameters!$A$5:$A$14,0))),INDEX(Parameters!$B$5:$B$14,MATCH(F14,Parameters!$A$5:$A$14,0)),""),"") -> 1 | Y14: =IF(G14<>"",1,IF(ISNUMBER(Parameters!$B$18),Parameters!$B$18,"")) -> 1 | Z14: =IF(I14<>"",IFERROR(IF(ISNUMBER(INDEX(Parameters!$B$5:$B$14,MATCH(I14,Parameters!$A$5:$A$14,0))),INDEX(Parameters!$B$5:$B$14,MATCH(I14,Parameters!$A$5:$A$14,0)),""),""),IF(ISNUMBER(Parameters!$B$21),Parameters!$B$21,"")) -> 1 | AA14: =IFERROR(IF(ISNUMBER(INDEX(Parameters!$B$5:$B$14,MATCH(J14,Parameters!$A$5:$A$14,0))),INDEX(Parameters!$B$5:$B$14,MATCH(J14,Parameters!$A$5:$A$14,0)),""),"") -> 1 | AB14: =IFERROR(IF(ISNUMBER(INDEX(Parameters!$B$5:$B$14,MATCH(K14,Parameters!$A$5:$A$14,0))),INDEX(Parameters!$B$5:$B$14,MATCH(K14,Parameters!$A$5:$A$14,0)),""),"") -> 1 | AC14: =IFERROR(IF(ISNUMBER(INDEX(Parameters!$B$5:$B$14,MATCH(L14,Parameters!$A$5:$A$14,0))),INDEX(Parameters!$B$5:$B$14,MATCH(L14,Parameters!$A$5:$A$14,0)),""),"") -> 1 | AD14: =IFERROR(IF(ISNUMBER(INDEX(Parameters!$B$5:$B$14,MATCH(M14,Parameters!$A$5:$A$14,0))),INDEX(Parameters!$B$5:$B$14,MATCH(M14,Parameters!$A$5:$A$14,0)),""),"") -> 1 | AE14: =IF(N14<>"",1,IF(ISNUMBER(Parameters!$B$19),Parameters!$B$19,"")) -> 0 | AF14: =IF((Parameters!$I$5*ISNUMBER(V14)+Parameters!$I$6*ISNUMBER(W14)+Parameters!$I$7*ISNUMBER(X14)+Parameters!$I$8*ISNUMBER(Y14))=0,"",(Parameters!$I$5*N(V14)+Parameters!$I$6*N(W14)+Parameters!$I$7*N(X14)+Parameters!$I$8*N(Y14))/(Parameters!$I$5*ISNUMBER(V14)+Parameters!$I$6*ISNUMBER(W14)+Parameters!$I$7*ISNUMBER(X14)+Parameters!$I$8*ISNUMBER(Y14))) -> 1 | AG14: =IF((Parameters!$I$9*ISNUMBER(Z14))=0,"",(Parameters!$I$9*N(Z14))/(Parameters!$I$9*ISNUMBER(Z14))) -> 1 | AH14: =IF((Parameters!$I$11*ISNUMBER(AA14)+Parameters!$I$12*ISNUMBER(AB14)+Parameters!$I$13*ISNUMBER(AC14)+Parameters!$I$14*ISNUMBER(AD14)+Parameters!$I$15*ISNUMBER(AE14))=0,"",(Parameters!$I$11*N(AA14)+Parameters!$I$12*N(AB14)+Parameters!$I$13*N(AC14)+Parameters!$I$14*N(AD14)+Parameters!$I$15*N(AE14))/(Parameters!$I$11*ISNUMBER(AA14)+Parameters!$I$12*ISNUMBER(AB14)+Parameters!$I$13*ISNUMBER(AC14)+Parameters!$I$14*ISNUMBER(AD14)+Parameters!$I$15*ISNUMBER(AE14))) -> 0.8 | AI14: =Parameters!$I$5*ISNUMBER(V14)+Parameters!$I$6*ISNUMBER(W14)+Parameters!$I$7*ISNUMBER(X14)+Parameters!$I$8*ISNUMBER(Y14)+Parameters!$I$9*ISNUMBER(Z14)+Parameters!$I$11*ISNUMBER(AA14)+Parameters!$I$12*ISNUMBER(AB14)+Parameters!$I$13*ISNUMBER(AC14)+Parameters!$I$14*ISNUMBER(AD14)+Parameters!$I$15*ISNUMBER(AE14) -> 95 | AJ14: =IF((Parameters!$I$5+Parameters!$I$6+Parameters!$I$7+Parameters!$I$8+Parameters!$I$9+Parameters!$I$11+Parameters!$I$12+Parameters!$I$13+Parameters!$I$14+Parameters!$I$15)=0,"",AI14/(Parameters!$I$5+Parameters!$I$6+Parameters!$I$7+Parameters!$I$8+Parameters!$I$9+Parameters!$I$11+Parameters!$I$12+Parameters!$I$13+Parameters!$I$14+Parameters!$I$15)) -> 1 | AK14: =IF(AND(ISNUMBER(AF14),ISNUMBER(AH14),OR(NOT((Parameters!$I$9)>0),ISNUMBER(AG14)),AJ14>=Parameters!$B$20),100*(Parameters!$F$18*N(AF14)+Parameters!$F$19*N(AG14)+Parameters!$F$20*N(AH14))/(Parameters!$F$18*ISNUMBER(AF14)+Parameters!$F$19*ISNUMBER(AG14)+Parameters!$F$20*ISNUMBER(AH14)),"") -> 93 | AL14: =IF(ISNUMBER(AK14),RANK(AK14,$AK$2:$AK$113),"") -> 12 | AM14: =IF(((D14="Implemented/available")+(E14="Implemented/available")+(J14="Implemented/available")+(K14="Implemented/available")+(L14="Implemented/available")+(M14="Implemented/available"))=0,"",(AND(D14="Implemented/available",O14<>"")+AND(E14="Implemented/available",P14<>"")+AND(J14="Implemented/available",Q14<>"")+AND(K14="Implemented/available",R14<>"")+AND(L14="Implemented/available",S14<>"")+AND(M14="Implemented/available",T14<>""))/((D14="Implemented/available")+(E14="Implemented/available")+(J14="Implemented/available")+(K14="Implemented/available")+(L14="Implemented/available")+(M14="Implemented/available"))) -> 1
A15: OA.Report | B15: OA.Works | C15: Open access or subscription management tool | Research profiling system | D15: Implemented/available | E15: Implemented/available | F15: Implemented/available | G15: Advisory board or steering committee | I15: Formal | J15: Implemented/available | K15: In progress | L15: Considering | M15: Implemented/available | N15: Principles for Open Scholarly Infrastructure (POSI) | O15: https://oa.works/about/governance/ | P15: https://drive.google.com/drive/folders/1BRmxtsdw5_IIcyRCFoLPSNLs070vbl3T?usp=sharing | Q15: https://about.oa.report/help/accessibility-statement | T15: https://oa.works/policies/privacy/ | U15: https://oa.works/about/governance/articles-of-governance/ | V15: =IFERROR(IF(ISNUMBER(INDEX(Parameters!$B$5:$B$14,MATCH(D15,Parameters!$A$5:$A$14,0))),INDEX(Parameters!$B$5:$B$14,MATCH(D15,Parameters!$A$5:$A$14,0)),""),"") -> 1 | W15: =IFERROR(IF(ISNUMBER(INDEX(Parameters!$B$5:$B$14,MATCH(E15,Parameters!$A$5:$A$14,0))),INDEX(Parameters!$B$5:$B$14,MATCH(E15,Parameters!$A$5:$A$14,0)),""),"") -> 1 | X15: =IFERROR(IF(ISNUMBER(INDEX(Parameters!$B$5:$B$14,MATCH(F15,Parameters!$A$5:$A$14,0))),INDEX(Parameters!$B$5:$B$14,MATCH(F15,Parameters!$A$5:$A$14,0)),""),"") -> 1 | Y15: =IF(G15<>"",1,IF(ISNUMBER(Parameters!$B$18),Parameters!$B$18,"")) -> 1 | Z15: =IF(I15<>"",IFERROR(IF(ISNUMBER(INDEX(Parameters!$B$5:$B$14,MATCH(I15,Parameters!$A$5:$A$14,0))),INDEX(Parameters!$B$5:$B$14,MATCH(I15,Parameters!$A$5:$A$14,0)),""),""),IF(ISNUMBER(Parameters!$B$21),Parameters!$B$21,"")) -> 1 | AA15: =IFERROR(IF(ISNUMBER(INDEX(Parameters!$B$5:$B$14,MATCH(J15,Parameters!$A$5:$A$14,0))),INDEX(Parameters!$B$5:$B$14,MATCH(J15,Parameters!$A$5:$A$14,0)),""),"") -> 1 | AB15: =IFERROR(IF(ISNUMBER(INDEX(Parameters!$B$5:$B$14,MATCH(K15,Parameters!$A$5:$A$14,0))),INDEX(Parameters!$B$5:$B$14,MATCH(K15,Parameters!$A$5:$A$14,0)),""),"") -> 0.67 | AC15: =IFERROR(IF(ISNUMBER(INDEX(Parameters!$B$5:$B$14,MATCH(L15,Parameters!$A$5:$A$14,0))),INDEX(Parameters!$B$5:$B$14,MATCH(L15,Parameters!$A$5:$A$14,0)),""),"") -> 0.33 | AD15: =IFERROR(IF(ISNUMBER(INDEX(Parameters!$B$5:$B$14,MATCH(M15,Parameters!$A$5:$A$14,0))),INDEX(Parameters!$B$5:$B$14,MATCH(M15,Parameters!$A$5:$A$14,0)),""),"") -> 1 | AE15: =IF(N15<>"",1,IF(ISNUMBER(Parameters!$B$19),Parameters!$B$19,"")) -> 1 | AF15: =IF((Parameters!$I$5*ISNUMBER(V15)+Parameters!$I$6*ISNUMBER(W15)+Parameters!$I$7*ISNUMBER(X15)+Parameters!$I$8*ISNUMBER(Y15))=0,"",(Parameters!$I$5*N(V15)+Parameters!$I$6*N(W15)+Parameters!$I$7*N(X15)+Parameters!$I$8*N(Y15))/(Parameters!$I$5*ISNUMBER(V15)+Parameters!$I$6*ISNUMBER(W15)+Parameters!$I$7*ISNUMBER(X15)+Parameters!$I$8*ISNUMBER(Y15))) -> 1 | AG15: =IF((Parameters!$I$9*ISNUMBER(Z15))=0,"",(Parameters!$I$9*N(Z15))/(Parameters!$I$9*ISNUMBER(Z15))) -> 1 | AH15: =IF((Parameters!$I$11*ISNUMBER(AA15)+Parameters!$I$12*ISNUMBER(AB15)+Parameters!$I$13*ISNUMBER(AC15)+Parameters!$I$14*ISNUMBER(AD15)+Parameters!$I$15*ISNUMBER(AE15))=0,"",(Parameters!$I$11*N(AA15)+Parameters!$I$12*N(AB15)+Parameters!$I$13*N(AC15)+Parameters!$I$14*N(AD15)+Parameters!$I$15*N(AE15))/(Parameters!$I$11*ISNUMBER(AA15)+Parameters!$I$12*ISNUMBER(AB15)+Parameters!$I$13*ISNUMBER(AC15)+Parameters!$I$14*ISNUMBER(AD15)+Parameters!$I$15*ISNUMBER(AE15))) -> 0.8 | AI15: =Parameters!$I$5*ISNUMBER(V15)+Parameters!$I$6*ISNUMBER(W15)+Parameters!$I$7*ISNUMBER(X15)+Parameters!$I$8*ISNUMBER(Y15)+Parameters!$I$9*ISNUMBER(Z15)+Parameters!$I$11*ISNUMBER(AA15)+Parameters!$I$12*ISNUMBER(AB15)+Parameters!$I$13*ISNUMBER(AC15)+Parameters!$I$14*ISNUMBER(AD15)+Parameters!$I$15*ISNUMBER(AE15) -> 95 | AJ15: =IF((Parameters!$I$5+Parameters!$I$6+Parameters!$I$7+Parameters!$I$8+Parameters!$I$9+Parameters!$I$11+Parameters!$I$12+Parameters!$I$13+Parameters!$I$14+Parameters!$I$15)=0,"",AI15/(Parameters!$I$5+Parameters!$I$6+Parameters!$I$7+Parameters!$I$8+Parameters!$I$9+Parameters!$I$11+Parameters!$I$12+Parameters!$I$13+Parameters!$I$14+Parameters!$I$15)) -> 1 | AK15: =IF(AND(ISNUMBER(AF15),ISNUMBER(AH15),OR(NOT((Parameters!$I$9)>0),ISNUMBER(AG15)),AJ15>=Parameters!$B$20),100*(Parameters!$F$18*N(AF15)+Parameters!$F$19*N(AG15)+Parameters!$F$20*N(AH15))/(Parameters!$F$18*ISNUMBER(AF15)+Parameters!$F$19*ISNUMBER(AG15)+Parameters!$F$20*ISNUMBER(AH15)),"") -> 93 | AL15: =IF(ISNUMBER(AK15),RANK(AK15,$AK$2:$AK$113),"") -> 12 | AM15: =IF(((D15="Implemented/available")+(E15="Implemented/available")+(J15="Implemented/available")+(K15="Implemented/available")+(L15="Implemented/available")+(M15="Implemented/available"))=0,"",(AND(D15="Implemented/available",O15<>"")+AND(E15="Implemented/available",P15<>"")+AND(J15="Implemented/available",Q15<>"")+AND(K15="Implemented/available",R15<>"")+AND(L15="Implemented/available",S15<>"")+AND(M15="Implemented/available",T15<>""))/((D15="Implemented/available")+(E15="Implemented/available")+(J15="Implemented/available")+(K15="Implemented/available")+(L15="Implemented/available")+(M15="Implemented/available"))) -> 1
A16: VIVO | B16: Lyrasis | C16: Discovery system | Research profiling system | Standard, specification or protocol | D16: Implemented/available | E16: Implemented/available | F16: Implemented/available | G16: Advisory board or steering committee | I16: Formal | J16: In progress | K16: No direct costs | L16: Considering | M16: Implemented/available | N16: It Takes a Village Open Source Software Sustainability toolkit | O16: https://vivoweb.org/governance/ | P16: https://wiki.lyrasis.org/display/VIVO/VIVO+Project+Governance | T16: https://vivoweb.org/privacy-policy/ | U16: https://wiki.lyrasis.org/display/VIVO/VIVO+Project+Charter+v+1.1 | V16: =IFERROR(IF(ISNUMBER(INDEX(Parameters!$B$5:$B$14,MATCH(D16,Parameters!$A$5:$A$14,0))),INDEX(Parameters!$B$5:$B$14,MATCH(D16,Parameters!$A$5:$A$14,0)),""),"") -> 1 | W16: =IFERROR(IF(ISNUMBER(INDEX(Parameters!$B$5:$B$14,MATCH(E16,Parameters!$A$5:$A$14,0))),INDEX(Parameters!$B$5:$B$14,MATCH(E16,Parameters!$A$5:$A$14,0)),""),"") -> 1 | X16: =IFERROR(IF(ISNUMBER(INDEX(Parameters!$B$5:$B$14,MATCH(F16,Parameters!$A$5:$A$14,0))),INDEX(Parameters!$B$5:$B$14,MATCH(F16,Parameters!$A$5:$A$14,0)),""),"") -> 1 | Y16: =IF(G16<>"",1,IF(ISNUMBER(Parameters!$B$18),Parameters!$B$18,"")) -> 1 | Z16: =IF(I16<>"",IFERROR(IF(ISNUMBER(INDEX(Parameters!$B$5:$B$14,MATCH(I16,Parameters!$A$5:$A$14,0))),INDEX(Parameters!$B$5:$B$14,MATCH(I16,Parameters!$A$5:$A$14,0)),""),""),IF(ISNUMBER(Parameters!$B$21),Parameters!$B$21,"")) -> 1 | AA16: =IFERROR(IF(ISNUMBER(INDEX(Parameters!$B$5:$B$14,MATCH(J16,Parameters!$A$5:$A$14,0))),INDEX(Parameters!$B$5:$B$14,MATCH(J16,Parameters!$A$5:$A$14,0)),""),"") -> 0.67 | AB16: =IFERROR(IF(ISNUMBER(INDEX(Parameters!$B$5:$B$14,MATCH(K16,Parameters!$A$5:$A$14,0))),INDEX(Parameters!$B$5:$B$14,MATCH(K16,Parameters!$A$5:$A$14,0)),""),"") -> 1 | AC16: =IFERROR(IF(ISNUMBER(INDEX(Parameters!$B$5:$B$14,MATCH(L16,Parameters!$A$5:$A$14,0))),INDEX(Parameters!$B$5:$B$14,MATCH(L16,Parameters!$A$5:$A$14,0)),""),"") -> 0.33 | AD16: =IFERROR(IF(ISNUMBER(INDEX(Parameters!$B$5:$B$14,MATCH(M16,Parameters!$A$5:$A$14,0))),INDEX(Parameters!$B$5:$B$14,MATCH(M16,Parameters!$A$5:$A$14,0)),""),"") -> 1 | AE16: =IF(N16<>"",1,IF(ISNUMBER(Parameters!$B$19),Parameters!$B$19,"")) -> 1 | AF16: =IF((Parameters!$I$5*ISNUMBER(V16)+Parameters!$I$6*ISNUMBER(W16)+Parameters!$I$7*ISNUMBER(X16)+Parameters!$I$8*ISNUMBER(Y16))=0,"",(Parameters!$I$5*N(V16)+Parameters!$I$6*N(W16)+Parameters!$I$7*N(X16)+Parameters!$I$8*N(Y16))/(Parameters!$I$5*ISNUMBER(V16)+Parameters!$I$6*ISNUMBER(W16)+Parameters!$I$7*ISNUMBER(X16)+Parameters!$I$8*ISNUMBER(Y16))) -> 1 | AG16: =IF((Parameters!$I$9*ISNUMBER(Z16))=0,"",(Parameters!$I$9*N(Z16))/(Parameters!$I$9*ISNUMBER(Z16))) -> 1 | AH16: =IF((Parameters!$I$11*ISNUMBER(AA16)+Parameters!$I$12*ISNUMBER(AB16)+Parameters!$I$13*ISNUMBER(AC16)+Parameters!$I$14*ISNUMBER(AD16)+Parameters!$I$15*ISNUMBER(AE16))=0,"",(Parameters!$I$11*N(AA16)+Parameters!$I$12*N(AB16)+Parameters!$I$13*N(AC16)+Parameters!$I$14*N(AD16)+Parameters!$I$15*N(AE16))/(Parameters!$I$11*ISNUMBER(AA16)+Parameters!$I$12*ISNUMBER(AB16)+Parameters!$I$13*ISNUMBER(AC16)+Parameters!$I$14*ISNUMBER(AD16)+Parameters!$I$15*ISNUMBER(AE16))) -> 0.8 | AI16: =Parameters!$I$5*ISNUMBER(V16)+Parameters!$I$6*ISNUMBER(W16)+Parameters!$I$7*ISNUMBER(X16)+Parameters!$I$8*ISNUMBER(Y16)+Parameters!$I$9*ISNUMBER(Z16)+Parameters!$I$11*ISNUMBER(AA16)+Parameters!$I$12*ISNUMBER(AB16)+Parameters!$I$13*ISNUMBER(AC16)+Parameters!$I$14*ISNUMBER(AD16)+Parameters!$I$15*ISNUMBER(AE16) -> 95 | AJ16: =IF((Parameters!$I$5+Parameters!$I$6+Parameters!$I$7+Parameters!$I$8+Parameters!$I$9+Parameters!$I$11+Parameters!$I$12+Parameters!$I$13+Parameters!$I$14+Parameters!$I$15)=0,"",AI16/(Parameters!$I$5+Parameters!$I$6+Parameters!$I$7+Parameters!$I$8+Parameters!$I$9+Parameters!$I$11+Parameters!$I$12+Parameters!$I$13+Parameters!$I$14+Parameters!$I$15)) -> 1 | AK16: =IF(AND(ISNUMBER(AF16),ISNUMBER(AH16),OR(NOT((Parameters!$I$9)>0),ISNUMBER(AG16)),AJ16>=Parameters!$B$20),100*(Parameters!$F$18*N(AF16)+Parameters!$F$19*N(AG16)+Parameters!$F$20*N(AH16))/(Parameters!$F$18*ISNUMBER(AF16)+Parameters!$F$19*ISNUMBER(AG16)+Parameters!$F$20*ISNUMBER(AH16)),"") -> 93 | AL16: =IF(ISNUMBER(AK16),RANK(AK16,$AK$2:$AK$113),"") -> 12 | AM16: =IF(((D16="Implemented/available")+(E16="Implemented/available")+(J16="Implemented/available")+(K16="Implemented/available")+(L16="Implemented/available")+(M16="Implemented/available"))=0,"",(AND(D16="Implemented/available",O16<>"")+AND(E16="Implemented/available",P16<>"")+AND(J16="Implemented/available",Q16<>"")+AND(K16="Implemented/available",R16<>"")+AND(L16="Implemented/available",S16<>"")+AND(M16="Implemented/available",T16<>""))/((D16="Implemented/available")+(E16="Implemented/available")+(J16="Implemented/available")+(K16="Implemented/available")+(L16="Implemented/available")+(M16="Implemented/available"))) -> 1
A17: arXiv | B17: Cornell University | C17: Repository service | D17: Implemented/available | E17: Implemented/available | F17: Implemented/available | G17: Multi-board governance | I17: Formal | J17: Implemented/available | K17: Implemented/available | L17: Unknown | M17: Implemented/available | O17: https://info.arxiv.org/about/governance.html | P17: https://info.arxiv.org/about/reports/index.html | Q17: https://info.arxiv.org/help/web_accessibility.html | R17: https://info.arxiv.org/about/funding.html | T17: https://info.arxiv.org/help/policies/privacy_policy.html | U17: https://info.arxiv.org/about/arXiv_bylaws.html | V17: =IFERROR(IF(ISNUMBER(INDEX(Parameters!$B$5:$B$14,MATCH(D17,Parameters!$A$5:$A$14,0))),INDEX(Parameters!$B$5:$B$14,MATCH(D17,Parameters!$A$5:$A$14,0)),""),"") -> 1 | W17: =IFERROR(IF(ISNUMBER(INDEX(Parameters!$B$5:$B$14,MATCH(E17,Parameters!$A$5:$A$14,0))),INDEX(Parameters!$B$5:$B$14,MATCH(E17,Parameters!$A$5:$A$14,0)),""),"") -> 1 | X17: =IFERROR(IF(ISNUMBER(INDEX(Parameters!$B$5:$B$14,MATCH(F17,Parameters!$A$5:$A$14,0))),INDEX(Parameters!$B$5:$B$14,MATCH(F17,Parameters!$A$5:$A$14,0)),""),"") -> 1 | Y17: =IF(G17<>"",1,IF(ISNUMBER(Parameters!$B$18),Parameters!$B$18,"")) -> 1 | Z17: =IF(I17<>"",IFERROR(IF(ISNUMBER(INDEX(Parameters!$B$5:$B$14,MATCH(I17,Parameters!$A$5:$A$14,0))),INDEX(Parameters!$B$5:$B$14,MATCH(I17,Parameters!$A$5:$A$14,0)),""),""),IF(ISNUMBER(Parameters!$B$21),Parameters!$B$21,"")) -> 1 | AA17: =IFERROR(IF(ISNUMBER(INDEX(Parameters!$B$5:$B$14,MATCH(J17,Parameters!$A$5:$A$14,0))),INDEX(Parameters!$B$5:$B$14,MATCH(J17,Parameters!$A$5:$A$14,0)),""),"") -> 1 | AB17: =IFERROR(IF(ISNUMBER(INDEX(Parameters!$B$5:$B$14,MATCH(K17,Parameters!$A$5:$A$14,0))),INDEX(Parameters!$B$5:$B$14,MATCH(K17,Parameters!$A$5:$A$14,0)),""),"") -> 1 | AC17: =IFERROR(IF(ISNUMBER(INDEX(Parameters!$B$5:$B$14,MATCH(L17,Parameters!$A$5:$A$14,0))),INDEX(Parameters!$B$5:$B$14,MATCH(L17,Parameters!$A$5:$A$14,0)),""),"") | AD17: =IFERROR(IF(ISNUMBER(INDEX(Parameters!$B$5:$B$14,MATCH(M17,Parameters!$A$5:$A$14,0))),INDEX(Parameters!$B$5:$B$14,MATCH(M17,Parameters!$A$5:$A$14,0)),""),"") -> 1 | AE17: =IF(N17<>"",1,IF(ISNUMBER(Parameters!$B$19),Parameters!$B$19,"")) -> 0 | AF17: =IF((Parameters!$I$5*ISNUMBER(V17)+Parameters!$I$6*ISNUMBER(W17)+Parameters!$I$7*ISNUMBER(X17)+Parameters!$I$8*ISNUMBER(Y17))=0,"",(Parameters!$I$5*N(V17)+Parameters!$I$6*N(W17)+Parameters!$I$7*N(X17)+Parameters!$I$8*N(Y17))/(Parameters!$I$5*ISNUMBER(V17)+Parameters!$I$6*ISNUMBER(W17)+Parameters!$I$7*ISNUMBER(X17)+Parameters!$I$8*ISNUMBER(Y17))) -> 1 | AG17: =IF((Parameters!$I$9*ISNUMBER(Z17))=0,"",(Parameters!$I$9*N(Z17))/(Parameters!$I$9*ISNUMBER(Z17))) -> 1 | AH17: =IF((Parameters!$I$11*ISNUMBER(AA17)+Parameters!$I$12*ISNUMBER(AB17)+Parameters!$I$13*ISNUMBER(AC17)+Parameters!$I$14*ISNUMBER(AD17)+Parameters!$I$15*ISNUMBER(AE17))=0,"",(Parameters!$I$11*N(AA17)+Parameters!$I$12*N(AB17)+Parameters!$I$13*N(AC17)+Parameters!$I$14*N(AD17)+Parameters!$I$15*N(AE17))/(Parameters!$I$11*ISNUMBER(AA17)+Parameters!$I$12*ISNUMBER(AB17)+Parameters!$I$13*ISNUMBER(AC17)+Parameters!$I$14*ISNUMBER(AD17)+Parameters!$I$15*ISNUMBER(AE17))) -> 0.75 | AI17: =Parameters!$I$5*ISNUMBER(V17)+Parameters!$I$6*ISNUMBER(W17)+Parameters!$I$7*ISNUMBER(X17)+Parameters!$I$8*ISNUMBER(Y17)+Parameters!$I$9*ISNUMBER(Z17)+Parameters!$I$11*ISNUMBER(AA17)+Parameters!$I$12*ISNUMBER(AB17)+Parameters!$I$13*ISNUMBER(AC17)+Parameters!$I$14*ISNUMBER(AD17)+Parameters!$I$15*ISNUMBER(AE17) -> 88 | AJ17: =IF((Parameters!$I$5+Parameters!$I$6+Parameters!$I$7+Parameters!$I$8+Parameters!$I$9+Parameters!$I$11+Parameters!$I$12+Parameters!$I$13+Parameters!$I$14+Parameters!$I$15)=0,"",AI17/(Parameters!$I$5+Parameters!$I$6+Parameters!$I$7+Parameters!$I$8+Parameters!$I$9+Parameters!$I$11+Parameters!$I$12+Parameters!$I$13+Parameters!$I$14+Parameters!$I$15)) -> 0.92631579 | AK17: =IF(AND(ISNUMBER(AF17),ISNUMBER(AH17),OR(NOT((Parameters!$I$9)>0),ISNUMBER(AG17)),AJ17>=Parameters!$B$20),100*(Parameters!$F$18*N(AF17)+Parameters!$F$19*N(AG17)+Parameters!$F$20*N(AH17))/(Parameters!$F$18*ISNUMBER(AF17)+Parameters!$F$19*ISNUMBER(AG17)+Parameters!$F$20*ISNUMBER(AH17)),"") -> 91.25 | AL17: =IF(ISNUMBER(AK17),RANK(AK17,$AK$2:$AK$113),"") -> 16 | AM17: =IF(((D17="Implemented/available")+(E17="Implemented/available")+(J17="Implemented/available")+(K17="Implemented/available")+(L17="Implemented/available")+(M17="Implemented/available"))=0,"",(AND(D17="Implemented/available",O17<>"")+AND(E17="Implemented/available",P17<>"")+AND(J17="Implemented/available",Q17<>"")+AND(K17="Implemented/available",R17<>"")+AND(L17="Implemented/available",S17<>"")+AND(M17="Implemented/available",T17<>""))/((D17="Implemented/available")+(E17="Implemented/available")+(J17="Implemented/available")+(K17="Implemented/available")+(L17="Implemented/available")+(M17="Implemented/available"))) -> 1
A18: IIIF | B18: IIIF Consortium | C18: Standard, specification or protocol | D18: Implemented/available | E18: Implemented/available | F18: Implemented/available | G18: Advisory board or steering committee | I18: Formal | J18: Not applicable | K18: Implemented/available | L18: Implemented/available | M18: Implemented/available | O18: https://iiif.io/community/consortium/consortium_committees/ | P18: https://iiif.io/community/consortium/mou/ | R18: https://iiif.io/community/consortium/join/ | S18: https://iiif.io/community/consortium/next_steps/ | T18: https://iiif.io/privacy/ | U18: https://iiif.io/community/coordinating-committee/ | V18: =IFERROR(IF(ISNUMBER(INDEX(Parameters!$B$5:$B$14,MATCH(D18,Parameters!$A$5:$A$14,0))),INDEX(Parameters!$B$5:$B$14,MATCH(D18,Parameters!$A$5:$A$14,0)),""),"") -> 1 | W18: =IFERROR(IF(ISNUMBER(INDEX(Parameters!$B$5:$B$14,MATCH(E18,Parameters!$A$5:$A$14,0))),INDEX(Parameters!$B$5:$B$14,MATCH(E18,Parameters!$A$5:$A$14,0)),""),"") -> 1 | X18: =IFERROR(IF(ISNUMBER(INDEX(Parameters!$B$5:$B$14,MATCH(F18,Parameters!$A$5:$A$14,0))),INDEX(Parameters!$B$5:$B$14,MATCH(F18,Parameters!$A$5:$A$14,0)),""),"") -> 1 | Y18: =IF(G18<>"",1,IF(ISNUMBER(Parameters!$B$18),Parameters!$B$18,"")) -> 1 | Z18: =IF(I18<>"",IFERROR(IF(ISNUMBER(INDEX(Parameters!$B$5:$B$14,MATCH(I18,Parameters!$A$5:$A$14,0))),INDEX(Parameters!$B$5:$B$14,MATCH(I18,Parameters!$A$5:$A$14,0)),""),""),IF(ISNUMBER(Parameters!$B$21),Parameters!$B$21,"")) -> 1 | AA18: =IFERROR(IF(ISNUMBER(INDEX(Parameters!$B$5:$B$14,MATCH(J18,Parameters!$A$5:$A$14,0))),INDEX(Parameters!$B$5:$B$14,MATCH(J18,Parameters!$A$5:$A$14,0)),""),"") | AB18: =IFERROR(IF(ISNUMBER(INDEX(Parameters!$B$5:$B$14,MATCH(K18,Parameters!$A$5:$A$14,0))),INDEX(Parameters!$B$5:$B$14,MATCH(K18,Parameters!$A$5:$A$14,0)),""),"") -> 1 | AC18: =IFERROR(IF(ISNUMBER(INDEX(Parameters!$B$5:$B$14,MATCH(L18,Parameters!$A$5:$A$14,0))),INDEX(Parameters!$B$5:$B$14,MATCH(L18,Parameters!$A$5:$A$14,0)),""),"") -> 1 | AD18: =IFERROR(IF(ISNUMBER(INDEX(Parameters!$B$5:$B$14,MATCH(M18,Parameters!$A$5:$A$14,0))),INDEX(Parameters!$B$5:$B$14,MATCH(M18,Parameters!$A$5:$A$14,0)),""),"") -> 1 | AE18: =IF(N18<>"",1,IF(ISNUMBER(Parameters!$B$19),Parameters!$B$19,"")) -> 0 | AF18: =IF((Parameters!$I$5*ISNUMBER(V18)+Parameters!$I$6*ISNUMBER(W18)+Parameters!$I$7*ISNUMBER(X18)+Parameters!$I$8*ISNUMBER(Y18))=0,"",(Parameters!$I$5*N(V18)+Parameters!$I$6*N(W18)+Parameters!$I$7*N(X18)+Parameters!$I$8*N(Y18))/(Parameters!$I$5*ISNUMBER(V18)+Parameters!$I$6*ISNUMBER(W18)+Parameters!$I$7*ISNUMBER(X18)+Parameters!$I$8*ISNUMBER(Y18))) -> 1 | AG18: =IF((Parameters!$I$9*ISNUMBER(Z18))=0,"",(Parameters!$I$9*N(Z18))/(Parameters!$I$9*ISNUMBER(Z18))) -> 1 | AH18: =IF((Parameters!$I$11*ISNUMBER(AA18)+Parameters!$I$12*ISNUMBER(AB18)+Parameters!$I$13*ISNUMBER(AC18)+Parameters!$I$14*ISNUMBER(AD18)+Parameters!$I$15*ISNUMBER(AE18))=0,"",(Parameters!$I$11*N(AA18)+Parameters!$I$12*N(AB18)+Parameters!$I$13*N(AC18)+Parameters!$I$14*N(AD18)+Parameters!$I$15*N(AE18))/(Parameters!$I$11*ISNUMBER(AA18)+Parameters!$I$12*ISNUMBER(AB18)+Parameters!$I$13*ISNUMBER(AC18)+Parameters!$I$14*ISNUMBER(AD18)+Parameters!$I$15*ISNUMBER(AE18))) -> 0.75 | AI18: =Parameters!$I$5*ISNUMBER(V18)+Parameters!$I$6*ISNUMBER(W18)+Parameters!$I$7*ISNUMBER(X18)+Parameters!$I$8*ISNUMBER(Y18)+Parameters!$I$9*ISNUMBER(Z18)+Parameters!$I$11*ISNUMBER(AA18)+Parameters!$I$12*ISNUMBER(AB18)+Parameters!$I$13*ISNUMBER(AC18)+Parameters!$I$14*ISNUMBER(AD18)+Parameters!$I$15*ISNUMBER(AE18) -> 88 | AJ18: =IF((Parameters!$I$5+Parameters!$I$6+Parameters!$I$7+Parameters!$I$8+Parameters!$I$9+Parameters!$I$11+Parameters!$I$12+Parameters!$I$13+Parameters!$I$14+Parameters!$I$15)=0,"",AI18/(Parameters!$I$5+Parameters!$I$6+Parameters!$I$7+Parameters!$I$8+Parameters!$I$9+Parameters!$I$11+Parameters!$I$12+Parameters!$I$13+Parameters!$I$14+Parameters!$I$15)) -> 0.92631579 | AK18: =IF(AND(ISNUMBER(AF18),ISNUMBER(AH18),OR(NOT((Parameters!$I$9)>0),ISNUMBER(AG18)),AJ18>=Parameters!$B$20),100*(Parameters!$F$18*N(AF18)+Parameters!$F$19*N(AG18)+Parameters!$F$20*N(AH18))/(Parameters!$F$18*ISNUMBER(AF18)+Parameters!$F$19*ISNUMBER(AG18)+Parameters!$F$20*ISNUMBER(AH18)),"") -> 91.25 | AL18: =IF(ISNUMBER(AK18),RANK(AK18,$AK$2:$AK$113),"") -> 16 | AM18: =IF(((D18="Implemented/available")+(E18="Implemented/available")+(J18="Implemented/available")+(K18="Implemented/available")+(L18="Implemented/available")+(M18="Implemented/available"))=0,"",(AND(D18="Implemented/available",O18<>"")+AND(E18="Implemented/available",P18<>"")+AND(J18="Implemented/available",Q18<>"")+AND(K18="Implemented/available",R18<>"")+AND(L18="Implemented/available",S18<>"")+AND(M18="Implemented/available",T18<>""))/((D18="Implemented/available")+(E18="Implemented/available")+(J18="Implemented/available")+(K18="Implemented/available")+(L18="Implemented/available")+(M18="Implemented/available"))) -> 1
A19: DataCite | B19: DataCite | C19: Discovery system | Persistent identifier service | D19: Implemented/available | E19: Implemented/available | F19: Implemented/available | G19: Advisory board or steering committee | I19: Formal | J19: In progress | K19: Implemented/available | L19: Implemented/available | M19: Implemented/available | O19: https://datacite.org/governance/ | P19: https://datacite.org/governance/ | R19: https://datacite.org/fee-model/ | S19: https://datacite.org/commitment-to-equity-and-inclusion/ | T19: https://datacite.org/privacy-policy/ | U19: https://datacite.org/wp-content/uploads/2023/06/Statutes_26April2022.pdf | V19: =IFERROR(IF(ISNUMBER(INDEX(Parameters!$B$5:$B$14,MATCH(D19,Parameters!$A$5:$A$14,0))),INDEX(Parameters!$B$5:$B$14,MATCH(D19,Parameters!$A$5:$A$14,0)),""),"") -> 1 | W19: =IFERROR(IF(ISNUMBER(INDEX(Parameters!$B$5:$B$14,MATCH(E19,Parameters!$A$5:$A$14,0))),INDEX(Parameters!$B$5:$B$14,MATCH(E19,Parameters!$A$5:$A$14,0)),""),"") -> 1 | X19: =IFERROR(IF(ISNUMBER(INDEX(Parameters!$B$5:$B$14,MATCH(F19,Parameters!$A$5:$A$14,0))),INDEX(Parameters!$B$5:$B$14,MATCH(F19,Parameters!$A$5:$A$14,0)),""),"") -> 1 | Y19: =IF(G19<>"",1,IF(ISNUMBER(Parameters!$B$18),Parameters!$B$18,"")) -> 1 | Z19: =IF(I19<>"",IFERROR(IF(ISNUMBER(INDEX(Parameters!$B$5:$B$14,MATCH(I19,Parameters!$A$5:$A$14,0))),INDEX(Parameters!$B$5:$B$14,MATCH(I19,Parameters!$A$5:$A$14,0)),""),""),IF(ISNUMBER(Parameters!$B$21),Parameters!$B$21,"")) -> 1 | AA19: =IFERROR(IF(ISNUMBER(INDEX(Parameters!$B$5:$B$14,MATCH(J19,Parameters!$A$5:$A$14,0))),INDEX(Parameters!$B$5:$B$14,MATCH(J19,Parameters!$A$5:$A$14,0)),""),"") -> 0.67 | AB19: =IFERROR(IF(ISNUMBER(INDEX(Parameters!$B$5:$B$14,MATCH(K19,Parameters!$A$5:$A$14,0))),INDEX(Parameters!$B$5:$B$14,MATCH(K19,Parameters!$A$5:$A$14,0)),""),"") -> 1 | AC19: =IFERROR(IF(ISNUMBER(INDEX(Parameters!$B$5:$B$14,MATCH(L19,Parameters!$A$5:$A$14,0))),INDEX(Parameters!$B$5:$B$14,MATCH(L19,Parameters!$A$5:$A$14,0)),""),"") -> 1 | AD19: =IFERROR(IF(ISNUMBER(INDEX(Parameters!$B$5:$B$14,MATCH(M19,Parameters!$A$5:$A$14,0))),INDEX(Parameters!$B$5:$B$14,MATCH(M19,Parameters!$A$5:$A$14,0)),""),"") -> 1 | AE19: =IF(N19<>"",1,IF(ISNUMBER(Parameters!$B$19),Parameters!$B$19,"")) -> 0 | AF19: =IF((Parameters!$I$5*ISNUMBER(V19)+Parameters!$I$6*ISNUMBER(W19)+Parameters!$I$7*ISNUMBER(X19)+Parameters!$I$8*ISNUMBER(Y19))=0,"",(Parameters!$I$5*N(V19)+Parameters!$I$6*N(W19)+Parameters!$I$7*N(X19)+Parameters!$I$8*N(Y19))/(Parameters!$I$5*ISNUMBER(V19)+Parameters!$I$6*ISNUMBER(W19)+Parameters!$I$7*ISNUMBER(X19)+Parameters!$I$8*ISNUMBER(Y19))) -> 1 | AG19: =IF((Parameters!$I$9*ISNUMBER(Z19))=0,"",(Parameters!$I$9*N(Z19))/(Parameters!$I$9*ISNUMBER(Z19))) -> 1 | AH19: =IF((Parameters!$I$11*ISNUMBER(AA19)+Parameters!$I$12*ISNUMBER(AB19)+Parameters!$I$13*ISNUMBER(AC19)+Parameters!$I$14*ISNUMBER(AD19)+Parameters!$I$15*ISNUMBER(AE19))=0,"",(Parameters!$I$11*N(AA19)+Parameters!$I$12*N(AB19)+Parameters!$I$13*N(AC19)+Parameters!$I$14*N(AD19)+Parameters!$I$15*N(AE19))/(Parameters!$I$11*ISNUMBER(AA19)+Parameters!$I$12*ISNUMBER(AB19)+Parameters!$I$13*ISNUMBER(AC19)+Parameters!$I$14*ISNUMBER(AD19)+Parameters!$I$15*ISNUMBER(AE19))) -> 0.734 | AI19: =Parameters!$I$5*ISNUMBER(V19)+Parameters!$I$6*ISNUMBER(W19)+Parameters!$I$7*ISNUMBER(X19)+Parameters!$I$8*ISNUMBER(Y19)+Parameters!$I$9*ISNUMBER(Z19)+Parameters!$I$11*ISNUMBER(AA19)+Parameters!$I$12*ISNUMBER(AB19)+Parameters!$I$13*ISNUMBER(AC19)+Parameters!$I$14*ISNUMBER(AD19)+Parameters!$I$15*ISNUMBER(AE19) -> 95 | AJ19: =IF((Parameters!$I$5+Parameters!$I$6+Parameters!$I$7+Parameters!$I$8+Parameters!$I$9+Parameters!$I$11+Parameters!$I$12+Parameters!$I$13+Parameters!$I$14+Parameters!$I$15)=0,"",AI19/(Parameters!$I$5+Parameters!$I$6+Parameters!$I$7+Parameters!$I$8+Parameters!$I$9+Parameters!$I$11+Parameters!$I$12+Parameters!$I$13+Parameters!$I$14+Parameters!$I$15)) -> 1 | AK19: =IF(AND(ISNUMBER(AF19),ISNUMBER(AH19),OR(NOT((Parameters!$I$9)>0),ISNUMBER(AG19)),AJ19>=Parameters!$B$20),100*(Parameters!$F$18*N(AF19)+Parameters!$F$19*N(AG19)+Parameters!$F$20*N(AH19))/(Parameters!$F$18*ISNUMBER(AF19)+Parameters!$F$19*ISNUMBER(AG19)+Parameters!$F$20*ISNUMBER(AH19)),"") -> 90.69 | AL19: =IF(ISNUMBER(AK19),RANK(AK19,$AK$2:$AK$113),"") -> 18 | AM19: =IF(((D19="Implemented/available")+(E19="Implemented/available")+(J19="Implemented/available")+(K19="Implemented/available")+(L19="Implemented/available")+(M19="Implemented/available"))=0,"",(AND(D19="Implemented/available",O19<>"")+AND(E19="Implemented/available",P19<>"")+AND(J19="Implemented/available",Q19<>"")+AND(K19="Implemented/available",R19<>"")+AND(L19="Implemented/available",S19<>"")+AND(M19="Implemented/available",T19<>""))/((D19="Implemented/available")+(E19="Implemented/available")+(J19="Implemented/available")+(K19="Implemented/available")+(L19="Implemented/available")+(M19="Implemented/available"))) -> 1
A20: Dryad | B20: Dryad | C20: Repository service | D20: Implemented/available | E20: Implemented/available | F20: Implemented/available | G20: Other | I20: Formal | J20: Implemented/available | K20: Implemented/available | L20: In progress | M20: Implemented/available | O20: https://datadryad.org/stash/about#our-board | P20: https://blog.datadryad.org/category/governance/ | R20: https://datadryad.org/stash/join_us#fees | T20: https://datadryad.org/stash/terms#privacy | U20: https://datadryad.org/docs/DryadBylaws.pdf | V20: =IFERROR(IF(ISNUMBER(INDEX(Parameters!$B$5:$B$14,MATCH(D20,Parameters!$A$5:$A$14,0))),INDEX(Parameters!$B$5:$B$14,MATCH(D20,Parameters!$A$5:$A$14,0)),""),"") -> 1 | W20: =IFERROR(IF(ISNUMBER(INDEX(Parameters!$B$5:$B$14,MATCH(E20,Parameters!$A$5:$A$14,0))),INDEX(Parameters!$B$5:$B$14,MATCH(E20,Parameters!$A$5:$A$14,0)),""),"") -> 1 | X20: =IFERROR(IF(ISNUMBER(INDEX(Parameters!$B$5:$B$14,MATCH(F20,Parameters!$A$5:$A$14,0))),INDEX(Parameters!$B$5:$B$14,MATCH(F20,Parameters!$A$5:$A$14,0)),""),"") -> 1 | Y20: =IF(G20<>"",1,IF(ISNUMBER(Parameters!$B$18),Parameters!$B$18,"")) -> 1 | Z20: =IF(I20<>"",IFERROR(IF(ISNUMBER(INDEX(Parameters!$B$5:$B$14,MATCH(I20,Parameters!$A$5:$A$14,0))),INDEX(Parameters!$B$5:$B$14,MATCH(I20,Parameters!$A$5:$A$14,0)),""),""),IF(ISNUMBER(Parameters!$B$21),Parameters!$B$21,"")) -> 1 | AA20: =IFERROR(IF(ISNUMBER(INDEX(Parameters!$B$5:$B$14,MATCH(J20,Parameters!$A$5:$A$14,0))),INDEX(Parameters!$B$5:$B$14,MATCH(J20,Parameters!$A$5:$A$14,0)),""),"") -> 1 | AB20: =IFERROR(IF(ISNUMBER(INDEX(Parameters!$B$5:$B$14,MATCH(K20,Parameters!$A$5:$A$14,0))),INDEX(Parameters!$B$5:$B$14,MATCH(K20,Parameters!$A$5:$A$14,0)),""),"") -> 1 | AC20: =IFERROR(IF(ISNUMBER(INDEX(Parameters!$B$5:$B$14,MATCH(L20,Parameters!$A$5:$A$14,0))),INDEX(Parameters!$B$5:$B$14,MATCH(L20,Parameters!$A$5:$A$14,0)),""),"") -> 0.67 | AD20: =IFERROR(IF(ISNUMBER(INDEX(Parameters!$B$5:$B$14,MATCH(M20,Parameters!$A$5:$A$14,0))),INDEX(Parameters!$B$5:$B$14,MATCH(M20,Parameters!$A$5:$A$14,0)),""),"") -> 1 | AE20: =IF(N20<>"",1,IF(ISNUMBER(Parameters!$B$19),Parameters!$B$19,"")) -> 0 | AF20: =IF((Parameters!$I$5*ISNUMBER(V20)+Parameters!$I$6*ISNUMBER(W20)+Parameters!$I$7*ISNUMBER(X20)+Parameters!$I$8*ISNUMBER(Y20))=0,"",(Parameters!$I$5*N(V20)+Parameters!$I$6*N(W20)+Parameters!$I$7*N(X20)+Parameters!$I$8*N(Y20))/(Parameters!$I$5*ISNUMBER(V20)+Parameters!$I$6*ISNUMBER(W20)+Parameters!$I$7*ISNUMBER(X20)+Parameters!$I$8*ISNUMBER(Y20))) -> 1 | AG20: =IF((Parameters!$I$9*ISNUMBER(Z20))=0,"",(Parameters!$I$9*N(Z20))/(Parameters!$I$9*ISNUMBER(Z20))) -> 1 | AH20: =IF((Parameters!$I$11*ISNUMBER(AA20)+Parameters!$I$12*ISNUMBER(AB20)+Parameters!$I$13*ISNUMBER(AC20)+Parameters!$I$14*ISNUMBER(AD20)+Parameters!$I$15*ISNUMBER(AE20))=0,"",(Parameters!$I$11*N(AA20)+Parameters!$I$12*N(AB20)+Parameters!$I$13*N(AC20)+Parameters!$I$14*N(AD20)+Parameters!$I$15*N(AE20))/(Parameters!$I$11*ISNUMBER(AA20)+Parameters!$I$12*ISNUMBER(AB20)+Parameters!$I$13*ISNUMBER(AC20)+Parameters!$I$14*ISNUMBER(AD20)+Parameters!$I$15*ISNUMBER(AE20))) -> 0.734 | AI20: =Parameters!$I$5*ISNUMBER(V20)+Parameters!$I$6*ISNUMBER(W20)+Parameters!$I$7*ISNUMBER(X20)+Parameters!$I$8*ISNUMBER(Y20)+Parameters!$I$9*ISNUMBER(Z20)+Parameters!$I$11*ISNUMBER(AA20)+Parameters!$I$12*ISNUMBER(AB20)+Parameters!$I$13*ISNUMBER(AC20)+Parameters!$I$14*ISNUMBER(AD20)+Parameters!$I$15*ISNUMBER(AE20) -> 95 | AJ20: =IF((Parameters!$I$5+Parameters!$I$6+Parameters!$I$7+Parameters!$I$8+Parameters!$I$9+Parameters!$I$11+Parameters!$I$12+Parameters!$I$13+Parameters!$I$14+Parameters!$I$15)=0,"",AI20/(Parameters!$I$5+Parameters!$I$6+Parameters!$I$7+Parameters!$I$8+Parameters!$I$9+Parameters!$I$11+Parameters!$I$12+Parameters!$I$13+Parameters!$I$14+Parameters!$I$15)) -> 1 | AK20: =IF(AND(ISNUMBER(AF20),ISNUMBER(AH20),OR(NOT((Parameters!$I$9)>0),ISNUMBER(AG20)),AJ20>=Parameters!$B$20),100*(Parameters!$F$18*N(AF20)+Parameters!$F$19*N(AG20)+Parameters!$F$20*N(AH20))/(Parameters!$F$18*ISNUMBER(AF20)+Parameters!$F$19*ISNUMBER(AG20)+Parameters!$F$20*ISNUMBER(AH20)),"") -> 90.69 | AL20: =IF(ISNUMBER(AK20),RANK(AK20,$AK$2:$AK$113),"") -> 18 | AM20: =IF(((D20="Implemented/available")+(E20="Implemented/available")+(J20="Implemented/available")+(K20="Implemented/available")+(L20="Implemented/available")+(M20="Implemented/available"))=0,"",(AND(D20="Implemented/available",O20<>"")+AND(E20="Implemented/available",P20<>"")+AND(J20="Implemented/available",Q20<>"")+AND(K20="Implemented/available",R20<>"")+AND(L20="Implemented/available",S20<>"")+AND(M20="Implemented/available",T20<>""))/((D20="Implemented/available")+(E20="Implemented/available")+(J20="Implemented/available")+(K20="Implemented/available")+(L20="Implemented/available")+(M20="Implemented/available"))) -> 0.8
A21: Galaxy | B21: The Galaxy community | C21: Computing framework | Discovery system | D21: Implemented/available | E21: Implemented/available | F21: Implemented/available | G21: Multi-board governance | I21: Formal | J21: In progress | K21: No direct costs | L21: Implemented/available | M21: Implemented/available | O21: https://galaxyproject.org/community/governance/ | P21: https://galaxyproject.org/community/wg/ | S21: https://galaxyproject.org/community/coc/ | T21: https://usegalaxy-eu.github.io/gdpr/ | U21: https://galaxyproject.org/community/governance/ | V21: =IFERROR(IF(ISNUMBER(INDEX(Parameters!$B$5:$B$14,MATCH(D21,Parameters!$A$5:$A$14,0))),INDEX(Parameters!$B$5:$B$14,MATCH(D21,Parameters!$A$5:$A$14,0)),""),"") -> 1 | W21: =IFERROR(IF(ISNUMBER(INDEX(Parameters!$B$5:$B$14,MATCH(E21,Parameters!$A$5:$A$14,0))),INDEX(Parameters!$B$5:$B$14,MATCH(E21,Parameters!$A$5:$A$14,0)),""),"") -> 1 | X21: =IFERROR(IF(ISNUMBER(INDEX(Parameters!$B$5:$B$14,MATCH(F21,Parameters!$A$5:$A$14,0))),INDEX(Parameters!$B$5:$B$14,MATCH(F21,Parameters!$A$5:$A$14,0)),""),"") -> 1 | Y21: =IF(G21<>"",1,IF(ISNUMBER(Parameters!$B$18),Parameters!$B$18,"")) -> 1 | Z21: =IF(I21<>"",IFERROR(IF(ISNUMBER(INDEX(Parameters!$B$5:$B$14,MATCH(I21,Parameters!$A$5:$A$14,0))),INDEX(Parameters!$B$5:$B$14,MATCH(I21,Parameters!$A$5:$A$14,0)),""),""),IF(ISNUMBER(Parameters!$B$21),Parameters!$B$21,"")) -> 1 | AA21: =IFERROR(IF(ISNUMBER(INDEX(Parameters!$B$5:$B$14,MATCH(J21,Parameters!$A$5:$A$14,0))),INDEX(Parameters!$B$5:$B$14,MATCH(J21,Parameters!$A$5:$A$14,0)),""),"") -> 0.67 | AB21: =IFERROR(IF(ISNUMBER(INDEX(Parameters!$B$5:$B$14,MATCH(K21,Parameters!$A$5:$A$14,0))),INDEX(Parameters!$B$5:$B$14,MATCH(K21,Parameters!$A$5:$A$14,0)),""),"") -> 1 | AC21: =IFERROR(IF(ISNUMBER(INDEX(Parameters!$B$5:$B$14,MATCH(L21,Parameters!$A$5:$A$14,0))),INDEX(Parameters!$B$5:$B$14,MATCH(L21,Parameters!$A$5:$A$14,0)),""),"") -> 1 | AD21: =IFERROR(IF(ISNUMBER(INDEX(Parameters!$B$5:$B$14,MATCH(M21,Parameters!$A$5:$A$14,0))),INDEX(Parameters!$B$5:$B$14,MATCH(M21,Parameters!$A$5:$A$14,0)),""),"") -> 1 | AE21: =IF(N21<>"",1,IF(ISNUMBER(Parameters!$B$19),Parameters!$B$19,"")) -> 0 | AF21: =IF((Parameters!$I$5*ISNUMBER(V21)+Parameters!$I$6*ISNUMBER(W21)+Parameters!$I$7*ISNUMBER(X21)+Parameters!$I$8*ISNUMBER(Y21))=0,"",(Parameters!$I$5*N(V21)+Parameters!$I$6*N(W21)+Parameters!$I$7*N(X21)+Parameters!$I$8*N(Y21))/(Parameters!$I$5*ISNUMBER(V21)+Parameters!$I$6*ISNUMBER(W21)+Parameters!$I$7*ISNUMBER(X21)+Parameters!$I$8*ISNUMBER(Y21))) -> 1 | AG21: =IF((Parameters!$I$9*ISNUMBER(Z21))=0,"",(Parameters!$I$9*N(Z21))/(Parameters!$I$9*ISNUMBER(Z21))) -> 1 | AH21: =IF((Parameters!$I$11*ISNUMBER(AA21)+Parameters!$I$12*ISNUMBER(AB21)+Parameters!$I$13*ISNUMBER(AC21)+Parameters!$I$14*ISNUMBER(AD21)+Parameters!$I$15*ISNUMBER(AE21))=0,"",(Parameters!$I$11*N(AA21)+Parameters!$I$12*N(AB21)+Parameters!$I$13*N(AC21)+Parameters!$I$14*N(AD21)+Parameters!$I$15*N(AE21))/(Parameters!$I$11*ISNUMBER(AA21)+Parameters!$I$12*ISNUMBER(AB21)+Parameters!$I$13*ISNUMBER(AC21)+Parameters!$I$14*ISNUMBER(AD21)+Parameters!$I$15*ISNUMBER(AE21))) -> 0.734 | AI21: =Parameters!$I$5*ISNUMBER(V21)+Parameters!$I$6*ISNUMBER(W21)+Parameters!$I$7*ISNUMBER(X21)+Parameters!$I$8*ISNUMBER(Y21)+Parameters!$I$9*ISNUMBER(Z21)+Parameters!$I$11*ISNUMBER(AA21)+Parameters!$I$12*ISNUMBER(AB21)+Parameters!$I$13*ISNUMBER(AC21)+Parameters!$I$14*ISNUMBER(AD21)+Parameters!$I$15*ISNUMBER(AE21) -> 95 | AJ21: =IF((Parameters!$I$5+Parameters!$I$6+Parameters!$I$7+Parameters!$I$8+Parameters!$I$9+Parameters!$I$11+Parameters!$I$12+Parameters!$I$13+Parameters!$I$14+Parameters!$I$15)=0,"",AI21/(Parameters!$I$5+Parameters!$I$6+Parameters!$I$7+Parameters!$I$8+Parameters!$I$9+Parameters!$I$11+Parameters!$I$12+Parameters!$I$13+Parameters!$I$14+Parameters!$I$15)) -> 1 | AK21: =IF(AND(ISNUMBER(AF21),ISNUMBER(AH21),OR(NOT((Parameters!$I$9)>0),ISNUMBER(AG21)),AJ21>=Parameters!$B$20),100*(Parameters!$F$18*N(AF21)+Parameters!$F$19*N(AG21)+Parameters!$F$20*N(AH21))/(Parameters!$F$18*ISNUMBER(AF21)+Parameters!$F$19*ISNUMBER(AG21)+Parameters!$F$20*ISNUMBER(AH21)),"") -> 90.69 | AL21: =IF(ISNUMBER(AK21),RANK(AK21,$AK$2:$AK$113),"") -> 18 | AM21: =IF(((D21="Implemented/available")+(E21="Implemented/available")+(J21="Implemented/available")+(K21="Implemented/available")+(L21="Implemented/available")+(M21="Implemented/available"))=0,"",(AND(D21="Implemented/available",O21<>"")+AND(E21="Implemented/available",P21<>"")+AND(J21="Implemented/available",Q21<>"")+AND(K21="Implemented/available",R21<>"")+AND(L21="Implemented/available",S21<>"")+AND(M21="Implemented/available",T21<>""))/((D21="Implemented/available")+(E21="Implemented/available")+(J21="Implemented/available")+(K21="Implemented/available")+(L21="Implemented/available")+(M21="Implemented/available"))) -> 1
A22: Open Journal Systems (OJS) | B22: Public Knowledge Project (PKP) | C22: Publishing system | D22: Implemented/available | E22: Implemented/available | F22: Implemented/available | G22: Multi-board governance | I22: Formal | J22: Implemented/available | K22: Implemented/available | L22: In progress | M22: Implemented/available | O22: https://pkp.sfu.ca/about/governance/ | P22: https://pkp.sfu.ca/interest-groups/ | Q22: https://pkp.sfu.ca/general-accessibility-statement/ | R22: https://pkp.sfu.ca/hosting-services/hosting/journals/ | S22: https://pkp.sfu.ca/code/ | T22: https://pkp.sfu.ca/privacy-policy/ | U22: http://www.sfu.ca/policies/gazette/board.html | V22: =IFERROR(IF(ISNUMBER(INDEX(Parameters!$B$5:$B$14,MATCH(D22,Parameters!$A$5:$A$14,0))),INDEX(Parameters!$B$5:$B$14,MATCH(D22,Parameters!$A$5:$A$14,0)),""),"") -> 1 | W22: =IFERROR(IF(ISNUMBER(INDEX(Parameters!$B$5:$B$14,MATCH(E22,Parameters!$A$5:$A$14,0))),INDEX(Parameters!$B$5:$B$14,MATCH(E22,Parameters!$A$5:$A$14,0)),""),"") -> 1 | X22: =IFERROR(IF(ISNUMBER(INDEX(Parameters!$B$5:$B$14,MATCH(F22,Parameters!$A$5:$A$14,0))),INDEX(Parameters!$B$5:$B$14,MATCH(F22,Parameters!$A$5:$A$14,0)),""),"") -> 1 | Y22: =IF(G22<>"",1,IF(ISNUMBER(Parameters!$B$18),Parameters!$B$18,"")) -> 1 | Z22: =IF(I22<>"",IFERROR(IF(ISNUMBER(INDEX(Parameters!$B$5:$B$14,MATCH(I22,Parameters!$A$5:$A$14,0))),INDEX(Parameters!$B$5:$B$14,MATCH(I22,Parameters!$A$5:$A$14,0)),""),""),IF(ISNUMBER(Parameters!$B$21),Parameters!$B$21,"")) -> 1 | AA22: =IFERROR(IF(ISNUMBER(INDEX(Parameters!$B$5:$B$14,MATCH(J22,Parameters!$A$5:$A$14,0))),INDEX(Parameters!$B$5:$B$14,MATCH(J22,Parameters!$A$5:$A$14,0)),""),"") -> 1 | AB22: =IFERROR(IF(ISNUMBER(INDEX(Parameters!$B$5:$B$14,MATCH(K22,Parameters!$A$5:$A$14,0))),INDEX(Parameters!$B$5:$B$14,MATCH(K22,Parameters!$A$5:$A$14,0)),""),"") -> 1 | AC22: =IFERROR(IF(ISNUMBER(INDEX(Parameters!$B$5:$B$14,MATCH(L22,Parameters!$A$5:$A$14,0))),INDEX(Parameters!$B$5:$B$14,MATCH(L22,Parameters!$A$5:$A$14,0)),""),"") -> 0.67 | AD22: =IFERROR(IF(ISNUMBER(INDEX(Parameters!$B$5:$B$14,MATCH(M22,Parameters!$A$5:$A$14,0))),INDEX(Parameters!$B$5:$B$14,MATCH(M22,Parameters!$A$5:$A$14,0)),""),"") -> 1 | AE22: =IF(N22<>"",1,IF(ISNUMBER(Parameters!$B$19),Parameters!$B$19,"")) -> 0 | AF22: =IF((Parameters!$I$5*ISNUMBER(V22)+Parameters!$I$6*ISNUMBER(W22)+Parameters!$I$7*ISNUMBER(X22)+Parameters!$I$8*ISNUMBER(Y22))=0,"",(Parameters!$I$5*N(V22)+Parameters!$I$6*N(W22)+Parameters!$I$7*N(X22)+Parameters!$I$8*N(Y22))/(Parameters!$I$5*ISNUMBER(V22)+Parameters!$I$6*ISNUMBER(W22)+Parameters!$I$7*ISNUMBER(X22)+Parameters!$I$8*ISNUMBER(Y22))) -> 1 | AG22: =IF((Parameters!$I$9*ISNUMBER(Z22))=0,"",(Parameters!$I$9*N(Z22))/(Parameters!$I$9*ISNUMBER(Z22))) -> 1 | AH22: =IF((Parameters!$I$11*ISNUMBER(AA22)+Parameters!$I$12*ISNUMBER(AB22)+Parameters!$I$13*ISNUMBER(AC22)+Parameters!$I$14*ISNUMBER(AD22)+Parameters!$I$15*ISNUMBER(AE22))=0,"",(Parameters!$I$11*N(AA22)+Parameters!$I$12*N(AB22)+Parameters!$I$13*N(AC22)+Parameters!$I$14*N(AD22)+Parameters!$I$15*N(AE22))/(Parameters!$I$11*ISNUMBER(AA22)+Parameters!$I$12*ISNUMBER(AB22)+Parameters!$I$13*ISNUMBER(AC22)+Parameters!$I$14*ISNUMBER(AD22)+Parameters!$I$15*ISNUMBER(AE22))) -> 0.734 | AI22: =Parameters!$I$5*ISNUMBER(V22)+Parameters!$I$6*ISNUMBER(W22)+Parameters!$I$7*ISNUMBER(X22)+Parameters!$I$8*ISNUMBER(Y22)+Parameters!$I$9*ISNUMBER(Z22)+Parameters!$I$11*ISNUMBER(AA22)+Parameters!$I$12*ISNUMBER(AB22)+Parameters!$I$13*ISNUMBER(AC22)+Parameters!$I$14*ISNUMBER(AD22)+Parameters!$I$15*ISNUMBER(AE22) -> 95 | AJ22: =IF((Parameters!$I$5+Parameters!$I$6+Parameters!$I$7+Parameters!$I$8+Parameters!$I$9+Parameters!$I$11+Parameters!$I$12+Parameters!$I$13+Parameters!$I$14+Parameters!$I$15)=0,"",AI22/(Parameters!$I$5+Parameters!$I$6+Parameters!$I$7+Parameters!$I$8+Parameters!$I$9+Parameters!$I$11+Parameters!$I$12+Parameters!$I$13+Parameters!$I$14+Parameters!$I$15)) -> 1 | AK22: =IF(AND(ISNUMBER(AF22),ISNUMBER(AH22),OR(NOT((Parameters!$I$9)>0),ISNUMBER(AG22)),AJ22>=Parameters!$B$20),100*(Parameters!$F$18*N(AF22)+Parameters!$F$19*N(AG22)+Parameters!$F$20*N(AH22))/(Parameters!$F$18*ISNUMBER(AF22)+Parameters!$F$19*ISNUMBER(AG22)+Parameters!$F$20*ISNUMBER(AH22)),"") -> 90.69 | AL22: =IF(ISNUMBER(AK22),RANK(AK22,$AK$2:$AK$113),"") -> 18 | AM22: =IF(((D22="Implemented/available")+(E22="Implemented/available")+(J22="Implemented/available")+(K22="Implemented/available")+(L22="Implemented/available")+(M22="Implemented/available"))=0,"",(AND(D22="Implemented/available",O22<>"")+AND(E22="Implemented/available",P22<>"")+AND(J22="Implemented/available",Q22<>"")+AND(K22="Implemented/available",R22<>"")+AND(L22="Implemented/available",S22<>"")+AND(M22="Implemented/available",T22<>""))/((D22="Implemented/available")+(E22="Implemented/available")+(J22="Implemented/available")+(K22="Implemented/available")+(L22="Implemented/available")+(M22="Implemented/available"))) -> 1
A23: Open Monograph Press (OMP) | B23: Public Knowledge Project (PKP) | C23: Publishing system | D23: Implemented/available | E23: Implemented/available | F23: Implemented/available | G23: Multi-board governance | I23: Formal | J23: Implemented/available | K23: Implemented/available | L23: In progress | M23: Implemented/available | O23: https://pkp.sfu.ca/about/governance/ | P23: https://pkp.sfu.ca/interest-groups/ | Q23: https://pkp.sfu.ca/general-accessibility-statement/ | R23: https://pkp.sfu.ca/hosting-services/hosting/monographs/ | S23: https://pkp.sfu.ca/code/ | T23: https://pkp.sfu.ca/privacy-policy/ | U23: http://www.sfu.ca/policies/gazette/board.html | V23: =IFERROR(IF(ISNUMBER(INDEX(Parameters!$B$5:$B$14,MATCH(D23,Parameters!$A$5:$A$14,0))),INDEX(Parameters!$B$5:$B$14,MATCH(D23,Parameters!$A$5:$A$14,0)),""),"") -> 1 | W23: =IFERROR(IF(ISNUMBER(INDEX(Parameters!$B$5:$B$14,MATCH(E23,Parameters!$A$5:$A$14,0))),INDEX(Parameters!$B$5:$B$14,MATCH(E23,Parameters!$A$5:$A$14,0)),""),"") -> 1 | X23: =IFERROR(IF(ISNUMBER(INDEX(Parameters!$B$5:$B$14,MATCH(F23,Parameters!$A$5:$A$14,0))),INDEX(Parameters!$B$5:$B$14,MATCH(F23,Parameters!$A$5:$A$14,0)),""),"") -> 1 | Y23: =IF(G23<>"",1,IF(ISNUMBER(Parameters!$B$18),Parameters!$B$18,"")) -> 1 | Z23: =IF(I23<>"",IFERROR(IF(ISNUMBER(INDEX(Parameters!$B$5:$B$14,MATCH(I23,Parameters!$A$5:$A$14,0))),INDEX(Parameters!$B$5:$B$14,MATCH(I23,Parameters!$A$5:$A$14,0)),""),""),IF(ISNUMBER(Parameters!$B$21),Parameters!$B$21,"")) -> 1 | AA23: =IFERROR(IF(ISNUMBER(INDEX(Parameters!$B$5:$B$14,MATCH(J23,Parameters!$A$5:$A$14,0))),INDEX(Parameters!$B$5:$B$14,MATCH(J23,Parameters!$A$5:$A$14,0)),""),"") -> 1 | AB23: =IFERROR(IF(ISNUMBER(INDEX(Parameters!$B$5:$B$14,MATCH(K23,Parameters!$A$5:$A$14,0))),INDEX(Parameters!$B$5:$B$14,MATCH(K23,Parameters!$A$5:$A$14,0)),""),"") -> 1 | AC23: =IFERROR(IF(ISNUMBER(INDEX(Parameters!$B$5:$B$14,MATCH(L23,Parameters!$A$5:$A$14,0))),INDEX(Parameters!$B$5:$B$14,MATCH(L23,Parameters!$A$5:$A$14,0)),""),"") -> 0.67 | AD23: =IFERROR(IF(ISNUMBER(INDEX(Parameters!$B$5:$B$14,MATCH(M23,Parameters!$A$5:$A$14,0))),INDEX(Parameters!$B$5:$B$14,MATCH(M23,Parameters!$A$5:$A$14,0)),""),"") -> 1 | AE23: =IF(N23<>"",1,IF(ISNUMBER(Parameters!$B$19),Parameters!$B$19,"")) -> 0 | AF23: =IF((Parameters!$I$5*ISNUMBER(V23)+Parameters!$I$6*ISNUMBER(W23)+Parameters!$I$7*ISNUMBER(X23)+Parameters!$I$8*ISNUMBER(Y23))=0,"",(Parameters!$I$5*N(V23)+Parameters!$I$6*N(W23)+Parameters!$I$7*N(X23)+Parameters!$I$8*N(Y23))/(Parameters!$I$5*ISNUMBER(V23)+Parameters!$I$6*ISNUMBER(W23)+Parameters!$I$7*ISNUMBER(X23)+Parameters!$I$8*ISNUMBER(Y23))) -> 1 | AG23: =IF((Parameters!$I$9*ISNUMBER(Z23))=0,"",(Parameters!$I$9*N(Z23))/(Parameters!$I$9*ISNUMBER(Z23))) -> 1 | AH23: =IF((Parameters!$I$11*ISNUMBER(AA23)+Parameters!$I$12*ISNUMBER(AB23)+Parameters!$I$13*ISNUMBER(AC23)+Parameters!$I$14*ISNUMBER(AD23)+Parameters!$I$15*ISNUMBER(AE23))=0,"",(Parameters!$I$11*N(AA23)+Parameters!$I$12*N(AB23)+Parameters!$I$13*N(AC23)+Parameters!$I$14*N(AD23)+Parameters!$I$15*N(AE23))/(Parameters!$I$11*ISNUMBER(AA23)+Parameters!$I$12*ISNUMBER(AB23)+Parameters!$I$13*ISNUMBER(AC23)+Parameters!$I$14*ISNUMBER(AD23)+Parameters!$I$15*ISNUMBER(AE23))) -> 0.734 | AI23: =Parameters!$I$5*ISNUMBER(V23)+Parameters!$I$6*ISNUMBER(W23)+Parameters!$I$7*ISNUMBER(X23)+Parameters!$I$8*ISNUMBER(Y23)+Parameters!$I$9*ISNUMBER(Z23)+Parameters!$I$11*ISNUMBER(AA23)+Parameters!$I$12*ISNUMBER(AB23)+Parameters!$I$13*ISNUMBER(AC23)+Parameters!$I$14*ISNUMBER(AD23)+Parameters!$I$15*ISNUMBER(AE23) -> 95 | AJ23: =IF((Parameters!$I$5+Parameters!$I$6+Parameters!$I$7+Parameters!$I$8+Parameters!$I$9+Parameters!$I$11+Parameters!$I$12+Parameters!$I$13+Parameters!$I$14+Parameters!$I$15)=0,"",AI23/(Parameters!$I$5+Parameters!$I$6+Parameters!$I$7+Parameters!$I$8+Parameters!$I$9+Parameters!$I$11+Parameters!$I$12+Parameters!$I$13+Parameters!$I$14+Parameters!$I$15)) -> 1 | AK23: =IF(AND(ISNUMBER(AF23),ISNUMBER(AH23),OR(NOT((Parameters!$I$9)>0),ISNUMBER(AG23)),AJ23>=Parameters!$B$20),100*(Parameters!$F$18*N(AF23)+Parameters!$F$19*N(AG23)+Parameters!$F$20*N(AH23))/(Parameters!$F$18*ISNUMBER(AF23)+Parameters!$F$19*ISNUMBER(AG23)+Parameters!$F$20*ISNUMBER(AH23)),"") -> 90.69 | AL23: =IF(ISNUMBER(AK23),RANK(AK23,$AK$2:$AK$113),"") -> 18 | AM23: =IF(((D23="Implemented/available")+(E23="Implemented/available")+(J23="Implemented/available")+(K23="Implemented/available")+(L23="Implemented/available")+(M23="Implemented/available"))=0,"",(AND(D23="Implemented/available",O23<>"")+AND(E23="Implemented/available",P23<>"")+AND(J23="Implemented/available",Q23<>"")+AND(K23="Implemented/available",R23<>"")+AND(L23="Implemented/available",S23<>"")+AND(M23="Implemented/available",T23<>""))/((D23="Implemented/available")+(E23="Implemented/available")+(J23="Implemented/available")+(K23="Implemented/available")+(L23="Implemented/available")+(M23="Implemented/available"))) -> 1
A24: Open Preprint Systems (OPS) | B24: Public Knowledge Project (PKP) | C24: Publishing system | D24: Implemented/available | E24: Implemented/available | F24: Implemented/available | G24: Multi-board governance | I24: Formal | J24: Implemented/available | K24: Implemented/available | L24: In progress | M24: Implemented/available | O24: https://pkp.sfu.ca/about/governance/ | P24: https://pkp.sfu.ca/about/governance/advisory/ | Q24: https://pkp.sfu.ca/general-accessibility-statement/ | R24: https://pkp.sfu.ca/hosting-services/hosting/preprints/ | S24: https://pkp.sfu.ca/code/ | T24: https://pkp.sfu.ca/privacy-policy/ | U24: https://pkp.sfu.ca/about/governance/advisory/ | V24: =IFERROR(IF(ISNUMBER(INDEX(Parameters!$B$5:$B$14,MATCH(D24,Parameters!$A$5:$A$14,0))),INDEX(Parameters!$B$5:$B$14,MATCH(D24,Parameters!$A$5:$A$14,0)),""),"") -> 1 | W24: =IFERROR(IF(ISNUMBER(INDEX(Parameters!$B$5:$B$14,MATCH(E24,Parameters!$A$5:$A$14,0))),INDEX(Parameters!$B$5:$B$14,MATCH(E24,Parameters!$A$5:$A$14,0)),""),"") -> 1 | X24: =IFERROR(IF(ISNUMBER(INDEX(Parameters!$B$5:$B$14,MATCH(F24,Parameters!$A$5:$A$14,0))),INDEX(Parameters!$B$5:$B$14,MATCH(F24,Parameters!$A$5:$A$14,0)),""),"") -> 1 | Y24: =IF(G24<>"",1,IF(ISNUMBER(Parameters!$B$18),Parameters!$B$18,"")) -> 1 | Z24: =IF(I24<>"",IFERROR(IF(ISNUMBER(INDEX(Parameters!$B$5:$B$14,MATCH(I24,Parameters!$A$5:$A$14,0))),INDEX(Parameters!$B$5:$B$14,MATCH(I24,Parameters!$A$5:$A$14,0)),""),""),IF(ISNUMBER(Parameters!$B$21),Parameters!$B$21,"")) -> 1 | AA24: =IFERROR(IF(ISNUMBER(INDEX(Parameters!$B$5:$B$14,MATCH(J24,Parameters!$A$5:$A$14,0))),INDEX(Parameters!$B$5:$B$14,MATCH(J24,Parameters!$A$5:$A$14,0)),""),"") -> 1 | AB24: =IFERROR(IF(ISNUMBER(INDEX(Parameters!$B$5:$B$14,MATCH(K24,Parameters!$A$5:$A$14,0))),INDEX(Parameters!$B$5:$B$14,MATCH(K24,Parameters!$A$5:$A$14,0)),""),"") -> 1 | AC24: =IFERROR(IF(ISNUMBER(INDEX(Parameters!$B$5:$B$14,MATCH(L24,Parameters!$A$5:$A$14,0))),INDEX(Parameters!$B$5:$B$14,MATCH(L24,Parameters!$A$5:$A$14,0)),""),"") -> 0.67 | AD24: =IFERROR(IF(ISNUMBER(INDEX(Parameters!$B$5:$B$14,MATCH(M24,Parameters!$A$5:$A$14,0))),INDEX(Parameters!$B$5:$B$14,MATCH(M24,Parameters!$A$5:$A$14,0)),""),"") -> 1 | AE24: =IF(N24<>"",1,IF(ISNUMBER(Parameters!$B$19),Parameters!$B$19,"")) -> 0 | AF24: =IF((Parameters!$I$5*ISNUMBER(V24)+Parameters!$I$6*ISNUMBER(W24)+Parameters!$I$7*ISNUMBER(X24)+Parameters!$I$8*ISNUMBER(Y24))=0,"",(Parameters!$I$5*N(V24)+Parameters!$I$6*N(W24)+Parameters!$I$7*N(X24)+Parameters!$I$8*N(Y24))/(Parameters!$I$5*ISNUMBER(V24)+Parameters!$I$6*ISNUMBER(W24)+Parameters!$I$7*ISNUMBER(X24)+Parameters!$I$8*ISNUMBER(Y24))) -> 1 | AG24: =IF((Parameters!$I$9*ISNUMBER(Z24))=0,"",(Parameters!$I$9*N(Z24))/(Parameters!$I$9*ISNUMBER(Z24))) -> 1 | AH24: =IF((Parameters!$I$11*ISNUMBER(AA24)+Parameters!$I$12*ISNUMBER(AB24)+Parameters!$I$13*ISNUMBER(AC24)+Parameters!$I$14*ISNUMBER(AD24)+Parameters!$I$15*ISNUMBER(AE24))=0,"",(Parameters!$I$11*N(AA24)+Parameters!$I$12*N(AB24)+Parameters!$I$13*N(AC24)+Parameters!$I$14*N(AD24)+Parameters!$I$15*N(AE24))/(Parameters!$I$11*ISNUMBER(AA24)+Parameters!$I$12*ISNUMBER(AB24)+Parameters!$I$13*ISNUMBER(AC24)+Parameters!$I$14*ISNUMBER(AD24)+Parameters!$I$15*ISNUMBER(AE24))) -> 0.734 | AI24: =Parameters!$I$5*ISNUMBER(V24)+Parameters!$I$6*ISNUMBER(W24)+Parameters!$I$7*ISNUMBER(X24)+Parameters!$I$8*ISNUMBER(Y24)+Parameters!$I$9*ISNUMBER(Z24)+Parameters!$I$11*ISNUMBER(AA24)+Parameters!$I$12*ISNUMBER(AB24)+Parameters!$I$13*ISNUMBER(AC24)+Parameters!$I$14*ISNUMBER(AD24)+Parameters!$I$15*ISNUMBER(AE24) -> 95 | AJ24: =IF((Parameters!$I$5+Parameters!$I$6+Parameters!$I$7+Parameters!$I$8+Parameters!$I$9+Parameters!$I$11+Parameters!$I$12+Parameters!$I$13+Parameters!$I$14+Parameters!$I$15)=0,"",AI24/(Parameters!$I$5+Parameters!$I$6+Parameters!$I$7+Parameters!$I$8+Parameters!$I$9+Parameters!$I$11+Parameters!$I$12+Parameters!$I$13+Parameters!$I$14+Parameters!$I$15)) -> 1 | AK24: =IF(AND(ISNUMBER(AF24),ISNUMBER(AH24),OR(NOT((Parameters!$I$9)>0),ISNUMBER(AG24)),AJ24>=Parameters!$B$20),100*(Parameters!$F$18*N(AF24)+Parameters!$F$19*N(AG24)+Parameters!$F$20*N(AH24))/(Parameters!$F$18*ISNUMBER(AF24)+Parameters!$F$19*ISNUMBER(AG24)+Parameters!$F$20*ISNUMBER(AH24)),"") -> 90.69 | AL24: =IF(ISNUMBER(AK24),RANK(AK24,$AK$2:$AK$113),"") -> 18 | AM24: =IF(((D24="Implemented/available")+(E24="Implemented/available")+(J24="Implemented/available")+(K24="Implemented/available")+(L24="Implemented/available")+(M24="Implemented/available"))=0,"",(AND(D24="Implemented/available",O24<>"")+AND(E24="Implemented/available",P24<>"")+AND(J24="Implemented/available",Q24<>"")+AND(K24="Implemented/available",R24<>"")+AND(L24="Implemented/available",S24<>"")+AND(M24="Implemented/available",T24<>""))/((D24="Implemented/available")+(E24="Implemented/available")+(J24="Implemented/available")+(K24="Implemented/available")+(L24="Implemented/available")+(M24="Implemented/available"))) -> 1
A25: Research Organization Registry (ROR) | B25: California Digital Library, Crossref, DataCite | C25: Persistent identifier service | D25: Implemented/available | E25: Implemented/available | F25: Implemented/available | G25: Advisory board or steering committee | I25: Formal | J25: Considering | K25: No direct costs | L25: Considering | M25: Implemented/available | N25: Principles for Open Scholarly Infrastructure (POSI) | O25: https://ror.org/about/#governance-model | P25: https://ror.org/about/#governance-model | R25: https://ror.org/about/#business-model | T25: https://ror.org/privacy/ | U25: https://ror.org/community/#steering-group | V25: =IFERROR(IF(ISNUMBER(INDEX(Parameters!$B$5:$B$14,MATCH(D25,Parameters!$A$5:$A$14,0))),INDEX(Parameters!$B$5:$B$14,MATCH(D25,Parameters!$A$5:$A$14,0)),""),"") -> 1 | W25: =IFERROR(IF(ISNUMBER(INDEX(Parameters!$B$5:$B$14,MATCH(E25,Parameters!$A$5:$A$14,0))),INDEX(Parameters!$B$5:$B$14,MATCH(E25,Parameters!$A$5:$A$14,0)),""),"") -> 1 | X25: =IFERROR(IF(ISNUMBER(INDEX(Parameters!$B$5:$B$14,MATCH(F25,Parameters!$A$5:$A$14,0))),INDEX(Parameters!$B$5:$B$14,MATCH(F25,Parameters!$A$5:$A$14,0)),""),"") -> 1 | Y25: =IF(G25<>"",1,IF(ISNUMBER(Parameters!$B$18),Parameters!$B$18,"")) -> 1 | Z25: =IF(I25<>"",IFERROR(IF(ISNUMBER(INDEX(Parameters!$B$5:$B$14,MATCH(I25,Parameters!$A$5:$A$14,0))),INDEX(Parameters!$B$5:$B$14,MATCH(I25,Parameters!$A$5:$A$14,0)),""),""),IF(ISNUMBER(Parameters!$B$21),Parameters!$B$21,"")) -> 1 | AA25: =IFERROR(IF(ISNUMBER(INDEX(Parameters!$B$5:$B$14,MATCH(J25,Parameters!$A$5:$A$14,0))),INDEX(Parameters!$B$5:$B$14,MATCH(J25,Parameters!$A$5:$A$14,0)),""),"") -> 0.33 | AB25: =IFERROR(IF(ISNUMBER(INDEX(Parameters!$B$5:$B$14,MATCH(K25,Parameters!$A$5:$A$14,0))),INDEX(Parameters!$B$5:$B$14,MATCH(K25,Parameters!$A$5:$A$14,0)),""),"") -> 1 | AC25: =IFERROR(IF(ISNUMBER(INDEX(Parameters!$B$5:$B$14,MATCH(L25,Parameters!$A$5:$A$14,0))),INDEX(Parameters!$B$5:$B$14,MATCH(L25,Parameters!$A$5:$A$14,0)),""),"") -> 0.33 | AD25: =IFERROR(IF(ISNUMBER(INDEX(Parameters!$B$5:$B$14,MATCH(M25,Parameters!$A$5:$A$14,0))),INDEX(Parameters!$B$5:$B$14,MATCH(M25,Parameters!$A$5:$A$14,0)),""),"") -> 1 | AE25: =IF(N25<>"",1,IF(ISNUMBER(Parameters!$B$19),Parameters!$B$19,"")) -> 1 | AF25: =IF((Parameters!$I$5*ISNUMBER(V25)+Parameters!$I$6*ISNUMBER(W25)+Parameters!$I$7*ISNUMBER(X25)+Parameters!$I$8*ISNUMBER(Y25))=0,"",(Parameters!$I$5*N(V25)+Parameters!$I$6*N(W25)+Parameters!$I$7*N(X25)+Parameters!$I$8*N(Y25))/(Parameters!$I$5*ISNUMBER(V25)+Parameters!$I$6*ISNUMBER(W25)+Parameters!$I$7*ISNUMBER(X25)+Parameters!$I$8*ISNUMBER(Y25))) -> 1 | AG25: =IF((Parameters!$I$9*ISNUMBER(Z25))=0,"",(Parameters!$I$9*N(Z25))/(Parameters!$I$9*ISNUMBER(Z25))) -> 1 | AH25: =IF((Parameters!$I$11*ISNUMBER(AA25)+Parameters!$I$12*ISNUMBER(AB25)+Parameters!$I$13*ISNUMBER(AC25)+Parameters!$I$14*ISNUMBER(AD25)+Parameters!$I$15*ISNUMBER(AE25))=0,"",(Parameters!$I$11*N(AA25)+Parameters!$I$12*N(AB25)+Parameters!$I$13*N(AC25)+Parameters!$I$14*N(AD25)+Parameters!$I$15*N(AE25))/(Parameters!$I$11*ISNUMBER(AA25)+Parameters!$I$12*ISNUMBER(AB25)+Parameters!$I$13*ISNUMBER(AC25)+Parameters!$I$14*ISNUMBER(AD25)+Parameters!$I$15*ISNUMBER(AE25))) -> 0.732 | AI25: =Parameters!$I$5*ISNUMBER(V25)+Parameters!$I$6*ISNUMBER(W25)+Parameters!$I$7*ISNUMBER(X25)+Parameters!$I$8*ISNUMBER(Y25)+Parameters!$I$9*ISNUMBER(Z25)+Parameters!$I$11*ISNUMBER(AA25)+Parameters!$I$12*ISNUMBER(AB25)+Parameters!$I$13*ISNUMBER(AC25)+Parameters!$I$14*ISNUMBER(AD25)+Parameters!$I$15*ISNUMBER(AE25) -> 95 | AJ25: =IF((Parameters!$I$5+Parameters!$I$6+Parameters!$I$7+Parameters!$I$8+Parameters!$I$9+Parameters!$I$11+Parameters!$I$12+Parameters!$I$13+Parameters!$I$14+Parameters!$I$15)=0,"",AI25/(Parameters!$I$5+Parameters!$I$6+Parameters!$I$7+Parameters!$I$8+Parameters!$I$9+Parameters!$I$11+Parameters!$I$12+Parameters!$I$13+Parameters!$I$14+Parameters!$I$15)) -> 1 | AK25: =IF(AND(ISNUMBER(AF25),ISNUMBER(AH25),OR(NOT((Parameters!$I$9)>0),ISNUMBER(AG25)),AJ25>=Parameters!$B$20),100*(Parameters!$F$18*N(AF25)+Parameters!$F$19*N(AG25)+Parameters!$F$20*N(AH25))/(Parameters!$F$18*ISNUMBER(AF25)+Parameters!$F$19*ISNUMBER(AG25)+Parameters!$F$20*ISNUMBER(AH25)),"") -> 90.62 | AL25: =IF(ISNUMBER(AK25),RANK(AK25,$AK$2:$AK$113),"") -> 24 | AM25: =IF(((D25="Implemented/available")+(E25="Implemented/available")+(J25="Implemented/available")+(K25="Implemented/available")+(L25="Implemented/available")+(M25="Implemented/available"))=0,"",(AND(D25="Implemented/available",O25<>"")+AND(E25="Implemented/available",P25<>"")+AND(J25="Implemented/available",Q25<>"")+AND(K25="Implemented/available",R25<>"")+AND(L25="Implemented/available",S25<>"")+AND(M25="Implemented/available",T25<>""))/((D25="Implemented/available")+(E25="Implemented/available")+(J25="Implemented/available")+(K25="Implemented/available")+(L25="Implemented/available")+(M25="Implemented/available"))) -> 1
A26: Archipelago Commons | B26: Metropolitan New York Library Council | C26: Digital library, collection or exhibit platform | Repository software | D26: Implemented/available | E26: In progress | F26: Implemented/available | G26: Advisory board or steering committee | I26: Formal | J26: Implemented/available | K26: In progress | L26: Implemented/available | M26: Considering | N26: Contributor Covenant Code of Conduct for Open Source and Other Digital Commons Communities | FAIR Guiding Principles for Scientific Data Management and Stewardship | Q26: https://docs.google.com/document/d/1IXLYykwTbYS34VqzU-4AOD47EKQC95WyKrmZOKZkz6s/edit?usp=sharing | S26: https://docs.archipelago.nyc/1.5.0/CODE_OF_CONDUCT/ | U26: https://metro.org/wp-content/uploads/2025/05/METROBylaws20242.pdf | V26: =IFERROR(IF(ISNUMBER(INDEX(Parameters!$B$5:$B$14,MATCH(D26,Parameters!$A$5:$A$14,0))),INDEX(Parameters!$B$5:$B$14,MATCH(D26,Parameters!$A$5:$A$14,0)),""),"") -> 1 | W26: =IFERROR(IF(ISNUMBER(INDEX(Parameters!$B$5:$B$14,MATCH(E26,Parameters!$A$5:$A$14,0))),INDEX(Parameters!$B$5:$B$14,MATCH(E26,Parameters!$A$5:$A$14,0)),""),"") -> 0.67 | X26: =IFERROR(IF(ISNUMBER(INDEX(Parameters!$B$5:$B$14,MATCH(F26,Parameters!$A$5:$A$14,0))),INDEX(Parameters!$B$5:$B$14,MATCH(F26,Parameters!$A$5:$A$14,0)),""),"") -> 1 | Y26: =IF(G26<>"",1,IF(ISNUMBER(Parameters!$B$18),Parameters!$B$18,"")) -> 1 | Z26: =IF(I26<>"",IFERROR(IF(ISNUMBER(INDEX(Parameters!$B$5:$B$14,MATCH(I26,Parameters!$A$5:$A$14,0))),INDEX(Parameters!$B$5:$B$14,MATCH(I26,Parameters!$A$5:$A$14,0)),""),""),IF(ISNUMBER(Parameters!$B$21),Parameters!$B$21,"")) -> 1 | AA26: =IFERROR(IF(ISNUMBER(INDEX(Parameters!$B$5:$B$14,MATCH(J26,Parameters!$A$5:$A$14,0))),INDEX(Parameters!$B$5:$B$14,MATCH(J26,Parameters!$A$5:$A$14,0)),""),"") -> 1 | AB26: =IFERROR(IF(ISNUMBER(INDEX(Parameters!$B$5:$B$14,MATCH(K26,Parameters!$A$5:$A$14,0))),INDEX(Parameters!$B$5:$B$14,MATCH(K26,Parameters!$A$5:$A$14,0)),""),"") -> 0.67 | AC26: =IFERROR(IF(ISNUMBER(INDEX(Parameters!$B$5:$B$14,MATCH(L26,Parameters!$A$5:$A$14,0))),INDEX(Parameters!$B$5:$B$14,MATCH(L26,Parameters!$A$5:$A$14,0)),""),"") -> 1 | AD26: =IFERROR(IF(ISNUMBER(INDEX(Parameters!$B$5:$B$14,MATCH(M26,Parameters!$A$5:$A$14,0))),INDEX(Parameters!$B$5:$B$14,MATCH(M26,Parameters!$A$5:$A$14,0)),""),"") -> 0.33 | AE26: =IF(N26<>"",1,IF(ISNUMBER(Parameters!$B$19),Parameters!$B$19,"")) -> 1 | AF26: =IF((Parameters!$I$5*ISNUMBER(V26)+Parameters!$I$6*ISNUMBER(W26)+Parameters!$I$7*ISNUMBER(X26)+Parameters!$I$8*ISNUMBER(Y26))=0,"",(Parameters!$I$5*N(V26)+Parameters!$I$6*N(W26)+Parameters!$I$7*N(X26)+Parameters!$I$8*N(Y26))/(Parameters!$I$5*ISNUMBER(V26)+Parameters!$I$6*ISNUMBER(W26)+Parameters!$I$7*ISNUMBER(X26)+Parameters!$I$8*ISNUMBER(Y26))) -> 0.901 | AG26: =IF((Parameters!$I$9*ISNUMBER(Z26))=0,"",(Parameters!$I$9*N(Z26))/(Parameters!$I$9*ISNUMBER(Z26))) -> 1 | AH26: =IF((Parameters!$I$11*ISNUMBER(AA26)+Parameters!$I$12*ISNUMBER(AB26)+Parameters!$I$13*ISNUMBER(AC26)+Parameters!$I$14*ISNUMBER(AD26)+Parameters!$I$15*ISNUMBER(AE26))=0,"",(Parameters!$I$11*N(AA26)+Parameters!$I$12*N(AB26)+Parameters!$I$13*N(AC26)+Parameters!$I$14*N(AD26)+Parameters!$I$15*N(AE26))/(Parameters!$I$11*ISNUMBER(AA26)+Parameters!$I$12*ISNUMBER(AB26)+Parameters!$I$13*ISNUMBER(AC26)+Parameters!$I$14*ISNUMBER(AD26)+Parameters!$I$15*ISNUMBER(AE26))) -> 0.8 | AI26: =Parameters!$I$5*ISNUMBER(V26)+Parameters!$I$6*ISNUMBER(W26)+Parameters!$I$7*ISNUMBER(X26)+Parameters!$I$8*ISNUMBER(Y26)+Parameters!$I$9*ISNUMBER(Z26)+Parameters!$I$11*ISNUMBER(AA26)+Parameters!$I$12*ISNUMBER(AB26)+Parameters!$I$13*ISNUMBER(AC26)+Parameters!$I$14*ISNUMBER(AD26)+Parameters!$I$15*ISNUMBER(AE26) -> 95 | AJ26: =IF((Parameters!$I$5+Parameters!$I$6+Parameters!$I$7+Parameters!$I$8+Parameters!$I$9+Parameters!$I$11+Parameters!$I$12+Parameters!$I$13+Parameters!$I$14+Parameters!$I$15)=0,"",AI26/(Parameters!$I$5+Parameters!$I$6+Parameters!$I$7+Parameters!$I$8+Parameters!$I$9+Parameters!$I$11+Parameters!$I$12+Parameters!$I$13+Parameters!$I$14+Parameters!$I$15)) -> 1 | AK26: =IF(AND(ISNUMBER(AF26),ISNUMBER(AH26),OR(NOT((Parameters!$I$9)>0),ISNUMBER(AG26)),AJ26>=Parameters!$B$20),100*(Parameters!$F$18*N(AF26)+Parameters!$F$19*N(AG26)+Parameters!$F$20*N(AH26))/(Parameters!$F$18*ISNUMBER(AF26)+Parameters!$F$19*ISNUMBER(AG26)+Parameters!$F$20*ISNUMBER(AH26)),"") -> 89.04 | AL26: =IF(ISNUMBER(AK26),RANK(AK26,$AK$2:$AK$113),"") -> 25 | AM26: =IF(((D26="Implemented/available")+(E26="Implemented/available")+(J26="Implemented/available")+(K26="Implemented/available")+(L26="Implemented/available")+(M26="Implemented/available"))=0,"",(AND(D26="Implemented/available",O26<>"")+AND(E26="Implemented/available",P26<>"")+AND(J26="Implemented/available",Q26<>"")+AND(K26="Implemented/available",R26<>"")+AND(L26="Implemented/available",S26<>"")+AND(M26="Implemented/available",T26<>""))/((D26="Implemented/available")+(E26="Implemented/available")+(J26="Implemented/available")+(K26="Implemented/available")+(L26="Implemented/available")+(M26="Implemented/available"))) -> 0.66666667
A27: OSF (Open Science Framework) | B27: Center for Open Science, Inc. | C27: Repository service | Repository software | D27: Implemented/available | E27: In progress | F27: Implemented/available | G27: Advisory board or steering committee | I27: Formal | J27: Implemented/available | K27: Implemented/available | L27: Implemented/available | M27: Implemented/available | O27: https://www.cos.io/about/board | Q27: https://help.osf.io/hc/en-us/articles/360019737894-FAQs#what-accessibility-standards-does-osf-adhere-to | R27: https://www.cos.io/products/osf-preprints | S27: https://www.cos.io/about/diversity-equity-and-inclusion-at-cos | T27: https://github.com/CenterForOpenScience/cos.io/blob/master/PRIVACY_POLICY.md | U27: https://osf.io/pjnse | V27: =IFERROR(IF(ISNUMBER(INDEX(Parameters!$B$5:$B$14,MATCH(D27,Parameters!$A$5:$A$14,0))),INDEX(Parameters!$B$5:$B$14,MATCH(D27,Parameters!$A$5:$A$14,0)),""),"") -> 1 | W27: =IFERROR(IF(ISNUMBER(INDEX(Parameters!$B$5:$B$14,MATCH(E27,Parameters!$A$5:$A$14,0))),INDEX(Parameters!$B$5:$B$14,MATCH(E27,Parameters!$A$5:$A$14,0)),""),"") -> 0.67 | X27: =IFERROR(IF(ISNUMBER(INDEX(Parameters!$B$5:$B$14,MATCH(F27,Parameters!$A$5:$A$14,0))),INDEX(Parameters!$B$5:$B$14,MATCH(F27,Parameters!$A$5:$A$14,0)),""),"") -> 1 | Y27: =IF(G27<>"",1,IF(ISNUMBER(Parameters!$B$18),Parameters!$B$18,"")) -> 1 | Z27: =IF(I27<>"",IFERROR(IF(ISNUMBER(INDEX(Parameters!$B$5:$B$14,MATCH(I27,Parameters!$A$5:$A$14,0))),INDEX(Parameters!$B$5:$B$14,MATCH(I27,Parameters!$A$5:$A$14,0)),""),""),IF(ISNUMBER(Parameters!$B$21),Parameters!$B$21,"")) -> 1 | AA27: =IFERROR(IF(ISNUMBER(INDEX(Parameters!$B$5:$B$14,MATCH(J27,Parameters!$A$5:$A$14,0))),INDEX(Parameters!$B$5:$B$14,MATCH(J27,Parameters!$A$5:$A$14,0)),""),"") -> 1 | AB27: =IFERROR(IF(ISNUMBER(INDEX(Parameters!$B$5:$B$14,MATCH(K27,Parameters!$A$5:$A$14,0))),INDEX(Parameters!$B$5:$B$14,MATCH(K27,Parameters!$A$5:$A$14,0)),""),"") -> 1 | AC27: =IFERROR(IF(ISNUMBER(INDEX(Parameters!$B$5:$B$14,MATCH(L27,Parameters!$A$5:$A$14,0))),INDEX(Parameters!$B$5:$B$14,MATCH(L27,Parameters!$A$5:$A$14,0)),""),"") -> 1 | AD27: =IFERROR(IF(ISNUMBER(INDEX(Parameters!$B$5:$B$14,MATCH(M27,Parameters!$A$5:$A$14,0))),INDEX(Parameters!$B$5:$B$14,MATCH(M27,Parameters!$A$5:$A$14,0)),""),"") -> 1 | AE27: =IF(N27<>"",1,IF(ISNUMBER(Parameters!$B$19),Parameters!$B$19,"")) -> 0 | AF27: =IF((Parameters!$I$5*ISNUMBER(V27)+Parameters!$I$6*ISNUMBER(W27)+Parameters!$I$7*ISNUMBER(X27)+Parameters!$I$8*ISNUMBER(Y27))=0,"",(Parameters!$I$5*N(V27)+Parameters!$I$6*N(W27)+Parameters!$I$7*N(X27)+Parameters!$I$8*N(Y27))/(Parameters!$I$5*ISNUMBER(V27)+Parameters!$I$6*ISNUMBER(W27)+Parameters!$I$7*ISNUMBER(X27)+Parameters!$I$8*ISNUMBER(Y27))) -> 0.901 | AG27: =IF((Parameters!$I$9*ISNUMBER(Z27))=0,"",(Parameters!$I$9*N(Z27))/(Parameters!$I$9*ISNUMBER(Z27))) -> 1 | AH27: =IF((Parameters!$I$11*ISNUMBER(AA27)+Parameters!$I$12*ISNUMBER(AB27)+Parameters!$I$13*ISNUMBER(AC27)+Parameters!$I$14*ISNUMBER(AD27)+Parameters!$I$15*ISNUMBER(AE27))=0,"",(Parameters!$I$11*N(AA27)+Parameters!$I$12*N(AB27)+Parameters!$I$13*N(AC27)+Parameters!$I$14*N(AD27)+Parameters!$I$15*N(AE27))/(Parameters!$I$11*ISNUMBER(AA27)+Parameters!$I$12*ISNUMBER(AB27)+Parameters!$I$13*ISNUMBER(AC27)+Parameters!$I$14*ISNUMBER(AD27)+Parameters!$I$15*ISNUMBER(AE27))) -> 0.8 | AI27: =Parameters!$I$5*ISNUMBER(V27)+Parameters!$I$6*ISNUMBER(W27)+Parameters!$I$7*ISNUMBER(X27)+Parameters!$I$8*ISNUMBER(Y27)+Parameters!$I$9*ISNUMBER(Z27)+Parameters!$I$11*ISNUMBER(AA27)+Parameters!$I$12*ISNUMBER(AB27)+Parameters!$I$13*ISNUMBER(AC27)+Parameters!$I$14*ISNUMBER(AD27)+Parameters!$I$15*ISNUMBER(AE27) -> 95 | AJ27: =IF((Parameters!$I$5+Parameters!$I$6+Parameters!$I$7+Parameters!$I$8+Parameters!$I$9+Parameters!$I$11+Parameters!$I$12+Parameters!$I$13+Parameters!$I$14+Parameters!$I$15)=0,"",AI27/(Parameters!$I$5+Parameters!$I$6+Parameters!$I$7+Parameters!$I$8+Parameters!$I$9+Parameters!$I$11+Parameters!$I$12+Parameters!$I$13+Parameters!$I$14+Parameters!$I$15)) -> 1 | AK27: =IF(AND(ISNUMBER(AF27),ISNUMBER(AH27),OR(NOT((Parameters!$I$9)>0),ISNUMBER(AG27)),AJ27>=Parameters!$B$20),100*(Parameters!$F$18*N(AF27)+Parameters!$F$19*N(AG27)+Parameters!$F$20*N(AH27))/(Parameters!$F$18*ISNUMBER(AF27)+Parameters!$F$19*ISNUMBER(AG27)+Parameters!$F$20*ISNUMBER(AH27)),"") -> 89.04 | AL27: =IF(ISNUMBER(AK27),RANK(AK27,$AK$2:$AK$113),"") -> 25 | AM27: =IF(((D27="Implemented/available")+(E27="Implemented/available")+(J27="Implemented/available")+(K27="Implemented/available")+(L27="Implemented/available")+(M27="Implemented/available"))=0,"",(AND(D27="Implemented/available",O27<>"")+AND(E27="Implemented/available",P27<>"")+AND(J27="Implemented/available",Q27<>"")+AND(K27="Implemented/available",R27<>"")+AND(L27="Implemented/available",S27<>"")+AND(M27="Implemented/available",T27<>""))/((D27="Implemented/available")+(E27="Implemented/available")+(J27="Implemented/available")+(K27="Implemented/available")+(L27="Implemented/available")+(M27="Implemented/available"))) -> 1
A28: Academic Preservation Trust (APTrust) | B28: Academic Preservation Trust (APTrust) | C28: Digital preservation service | D28: Implemented/available | E28: Implemented/available | F28: Implemented/available | G28: Multi-board governance | I28: Formal | J28: Considering | K28: Implemented/available | L28: Implemented/available | M28: Not planning | N28: It Takes a Village Open Source Software Sustainability toolkit | O28: https://aptrust.org/governance/ | P28: https://aptrust.org/resources/member-meetings/ | R28: https://aptrust.org/about/services-and-fees/ | S28: https://aptrust.org/resources/policies/#vision-mission-and-shared-values | U28: https://aptrust.org/resources/policies/#governance-manual | V28: =IFERROR(IF(ISNUMBER(INDEX(Parameters!$B$5:$B$14,MATCH(D28,Parameters!$A$5:$A$14,0))),INDEX(Parameters!$B$5:$B$14,MATCH(D28,Parameters!$A$5:$A$14,0)),""),"") -> 1 | W28: =IFERROR(IF(ISNUMBER(INDEX(Parameters!$B$5:$B$14,MATCH(E28,Parameters!$A$5:$A$14,0))),INDEX(Parameters!$B$5:$B$14,MATCH(E28,Parameters!$A$5:$A$14,0)),""),"") -> 1 | X28: =IFERROR(IF(ISNUMBER(INDEX(Parameters!$B$5:$B$14,MATCH(F28,Parameters!$A$5:$A$14,0))),INDEX(Parameters!$B$5:$B$14,MATCH(F28,Parameters!$A$5:$A$14,0)),""),"") -> 1 | Y28: =IF(G28<>"",1,IF(ISNUMBER(Parameters!$B$18),Parameters!$B$18,"")) -> 1 | Z28: =IF(I28<>"",IFERROR(IF(ISNUMBER(INDEX(Parameters!$B$5:$B$14,MATCH(I28,Parameters!$A$5:$A$14,0))),INDEX(Parameters!$B$5:$B$14,MATCH(I28,Parameters!$A$5:$A$14,0)),""),""),IF(ISNUMBER(Parameters!$B$21),Parameters!$B$21,"")) -> 1 | AA28: =IFERROR(IF(ISNUMBER(INDEX(Parameters!$B$5:$B$14,MATCH(J28,Parameters!$A$5:$A$14,0))),INDEX(Parameters!$B$5:$B$14,MATCH(J28,Parameters!$A$5:$A$14,0)),""),"") -> 0.33 | AB28: =IFERROR(IF(ISNUMBER(INDEX(Parameters!$B$5:$B$14,MATCH(K28,Parameters!$A$5:$A$14,0))),INDEX(Parameters!$B$5:$B$14,MATCH(K28,Parameters!$A$5:$A$14,0)),""),"") -> 1 | AC28: =IFERROR(IF(ISNUMBER(INDEX(Parameters!$B$5:$B$14,MATCH(L28,Parameters!$A$5:$A$14,0))),INDEX(Parameters!$B$5:$B$14,MATCH(L28,Parameters!$A$5:$A$14,0)),""),"") -> 1 | AD28: =IFERROR(IF(ISNUMBER(INDEX(Parameters!$B$5:$B$14,MATCH(M28,Parameters!$A$5:$A$14,0))),INDEX(Parameters!$B$5:$B$14,MATCH(M28,Parameters!$A$5:$A$14,0)),""),"") -> 0 | AE28: =IF(N28<>"",1,IF(ISNUMBER(Parameters!$B$19),Parameters!$B$19,"")) -> 1 | AF28: =IF((Parameters!$I$5*ISNUMBER(V28)+Parameters!$I$6*ISNUMBER(W28)+Parameters!$I$7*ISNUMBER(X28)+Parameters!$I$8*ISNUMBER(Y28))=0,"",(Parameters!$I$5*N(V28)+Parameters!$I$6*N(W28)+Parameters!$I$7*N(X28)+Parameters!$I$8*N(Y28))/(Parameters!$I$5*ISNUMBER(V28)+Parameters!$I$6*ISNUMBER(W28)+Parameters!$I$7*ISNUMBER(X28)+Parameters!$I$8*ISNUMBER(Y28))) -> 1 | AG28: =IF((Parameters!$I$9*ISNUMBER(Z28))=0,"",(Parameters!$I$9*N(Z28))/(Parameters!$I$9*ISNUMBER(Z28))) -> 1 | AH28: =IF((Parameters!$I$11*ISNUMBER(AA28)+Parameters!$I$12*ISNUMBER(AB28)+Parameters!$I$13*ISNUMBER(AC28)+Parameters!$I$14*ISNUMBER(AD28)+Parameters!$I$15*ISNUMBER(AE28))=0,"",(Parameters!$I$11*N(AA28)+Parameters!$I$12*N(AB28)+Parameters!$I$13*N(AC28)+Parameters!$I$14*N(AD28)+Parameters!$I$15*N(AE28))/(Parameters!$I$11*ISNUMBER(AA28)+Parameters!$I$12*ISNUMBER(AB28)+Parameters!$I$13*ISNUMBER(AC28)+Parameters!$I$14*ISNUMBER(AD28)+Parameters!$I$15*ISNUMBER(AE28))) -> 0.666 | AI28: =Parameters!$I$5*ISNUMBER(V28)+Parameters!$I$6*ISNUMBER(W28)+Parameters!$I$7*ISNUMBER(X28)+Parameters!$I$8*ISNUMBER(Y28)+Parameters!$I$9*ISNUMBER(Z28)+Parameters!$I$11*ISNUMBER(AA28)+Parameters!$I$12*ISNUMBER(AB28)+Parameters!$I$13*ISNUMBER(AC28)+Parameters!$I$14*ISNUMBER(AD28)+Parameters!$I$15*ISNUMBER(AE28) -> 95 | AJ28: =IF((Parameters!$I$5+Parameters!$I$6+Parameters!$I$7+Parameters!$I$8+Parameters!$I$9+Parameters!$I$11+Parameters!$I$12+Parameters!$I$13+Parameters!$I$14+Parameters!$I$15)=0,"",AI28/(Parameters!$I$5+Parameters!$I$6+Parameters!$I$7+Parameters!$I$8+Parameters!$I$9+Parameters!$I$11+Parameters!$I$12+Parameters!$I$13+Parameters!$I$14+Parameters!$I$15)) -> 1 | AK28: =IF(AND(ISNUMBER(AF28),ISNUMBER(AH28),OR(NOT((Parameters!$I$9)>0),ISNUMBER(AG28)),AJ28>=Parameters!$B$20),100*(Parameters!$F$18*N(AF28)+Parameters!$F$19*N(AG28)+Parameters!$F$20*N(AH28))/(Parameters!$F$18*ISNUMBER(AF28)+Parameters!$F$19*ISNUMBER(AG28)+Parameters!$F$20*ISNUMBER(AH28)),"") -> 88.31 | AL28: =IF(ISNUMBER(AK28),RANK(AK28,$AK$2:$AK$113),"") -> 27 | AM28: =IF(((D28="Implemented/available")+(E28="Implemented/available")+(J28="Implemented/available")+(K28="Implemented/available")+(L28="Implemented/available")+(M28="Implemented/available"))=0,"",(AND(D28="Implemented/available",O28<>"")+AND(E28="Implemented/available",P28<>"")+AND(J28="Implemented/available",Q28<>"")+AND(K28="Implemented/available",R28<>"")+AND(L28="Implemented/available",S28<>"")+AND(M28="Implemented/available",T28<>""))/((D28="Implemented/available")+(E28="Implemented/available")+(J28="Implemented/available")+(K28="Implemented/available")+(L28="Implemented/available")+(M28="Implemented/available"))) -> 1
A29: OpenCitations | B29: Research Centre for Open Scholarly Metadata, University of Bologna | C29: Open scholarly dataset | D29: Implemented/available | E29: In progress | F29: Implemented/available | G29: Advisory board or steering committee | I29: Formal | J29: Considering | K29: No direct costs | L29: Considering | M29: Implemented/available | N29: FAIR Guiding Principles for Scientific Data Management and Stewardship | Principles for Open Scholarly Infrastructure (POSI) | O29: https://opencitations.net/governance/ | T29: https://opencitations.net/privacy-policy/ | U29: https://opencitations.net/wp-content/uploads/pdf/oc_bodies.pdf | V29: =IFERROR(IF(ISNUMBER(INDEX(Parameters!$B$5:$B$14,MATCH(D29,Parameters!$A$5:$A$14,0))),INDEX(Parameters!$B$5:$B$14,MATCH(D29,Parameters!$A$5:$A$14,0)),""),"") -> 1 | W29: =IFERROR(IF(ISNUMBER(INDEX(Parameters!$B$5:$B$14,MATCH(E29,Parameters!$A$5:$A$14,0))),INDEX(Parameters!$B$5:$B$14,MATCH(E29,Parameters!$A$5:$A$14,0)),""),"") -> 0.67 | X29: =IFERROR(IF(ISNUMBER(INDEX(Parameters!$B$5:$B$14,MATCH(F29,Parameters!$A$5:$A$14,0))),INDEX(Parameters!$B$5:$B$14,MATCH(F29,Parameters!$A$5:$A$14,0)),""),"") -> 1 | Y29: =IF(G29<>"",1,IF(ISNUMBER(Parameters!$B$18),Parameters!$B$18,"")) -> 1 | Z29: =IF(I29<>"",IFERROR(IF(ISNUMBER(INDEX(Parameters!$B$5:$B$14,MATCH(I29,Parameters!$A$5:$A$14,0))),INDEX(Parameters!$B$5:$B$14,MATCH(I29,Parameters!$A$5:$A$14,0)),""),""),IF(ISNUMBER(Parameters!$B$21),Parameters!$B$21,"")) -> 1 | AA29: =IFERROR(IF(ISNUMBER(INDEX(Parameters!$B$5:$B$14,MATCH(J29,Parameters!$A$5:$A$14,0))),INDEX(Parameters!$B$5:$B$14,MATCH(J29,Parameters!$A$5:$A$14,0)),""),"") -> 0.33 | AB29: =IFERROR(IF(ISNUMBER(INDEX(Parameters!$B$5:$B$14,MATCH(K29,Parameters!$A$5:$A$14,0))),INDEX(Parameters!$B$5:$B$14,MATCH(K29,Parameters!$A$5:$A$14,0)),""),"") -> 1 | AC29: =IFERROR(IF(ISNUMBER(INDEX(Parameters!$B$5:$B$14,MATCH(L29,Parameters!$A$5:$A$14,0))),INDEX(Parameters!$B$5:$B$14,MATCH(L29,Parameters!$A$5:$A$14,0)),""),"") -> 0.33 | AD29: =IFERROR(IF(ISNUMBER(INDEX(Parameters!$B$5:$B$14,MATCH(M29,Parameters!$A$5:$A$14,0))),INDEX(Parameters!$B$5:$B$14,MATCH(M29,Parameters!$A$5:$A$14,0)),""),"") -> 1 | AE29: =IF(N29<>"",1,IF(ISNUMBER(Parameters!$B$19),Parameters!$B$19,"")) -> 1 | AF29: =IF((Parameters!$I$5*ISNUMBER(V29)+Parameters!$I$6*ISNUMBER(W29)+Parameters!$I$7*ISNUMBER(X29)+Parameters!$I$8*ISNUMBER(Y29))=0,"",(Parameters!$I$5*N(V29)+Parameters!$I$6*N(W29)+Parameters!$I$7*N(X29)+Parameters!$I$8*N(Y29))/(Parameters!$I$5*ISNUMBER(V29)+Parameters!$I$6*ISNUMBER(W29)+Parameters!$I$7*ISNUMBER(X29)+Parameters!$I$8*ISNUMBER(Y29))) -> 0.901 | AG29: =IF((Parameters!$I$9*ISNUMBER(Z29))=0,"",(Parameters!$I$9*N(Z29))/(Parameters!$I$9*ISNUMBER(Z29))) -> 1 | AH29: =IF((Parameters!$I$11*ISNUMBER(AA29)+Parameters!$I$12*ISNUMBER(AB29)+Parameters!$I$13*ISNUMBER(AC29)+Parameters!$I$14*ISNUMBER(AD29)+Parameters!$I$15*ISNUMBER(AE29))=0,"",(Parameters!$I$11*N(AA29)+Parameters!$I$12*N(AB29)+Parameters!$I$13*N(AC29)+Parameters!$I$14*N(AD29)+Parameters!$I$15*N(AE29))/(Parameters!$I$11*ISNUMBER(AA29)+Parameters!$I$12*ISNUMBER(AB29)+Parameters!$I$13*ISNUMBER(AC29)+Parameters!$I$14*ISNUMBER(AD29)+Parameters!$I$15*ISNUMBER(AE29))) -> 0.732 | AI29: =Parameters!$I$5*ISNUMBER(V29)+Parameters!$I$6*ISNUMBER(W29)+Parameters!$I$7*ISNUMBER(X29)+Parameters!$I$8*ISNUMBER(Y29)+Parameters!$I$9*ISNUMBER(Z29)+Parameters!$I$11*ISNUMBER(AA29)+Parameters!$I$12*ISNUMBER(AB29)+Parameters!$I$13*ISNUMBER(AC29)+Parameters!$I$14*ISNUMBER(AD29)+Parameters!$I$15*ISNUMBER(AE29) -> 95 | AJ29: =IF((Parameters!$I$5+Parameters!$I$6+Parameters!$I$7+Parameters!$I$8+Parameters!$I$9+Parameters!$I$11+Parameters!$I$12+Parameters!$I$13+Parameters!$I$14+Parameters!$I$15)=0,"",AI29/(Parameters!$I$5+Parameters!$I$6+Parameters!$I$7+Parameters!$I$8+Parameters!$I$9+Parameters!$I$11+Parameters!$I$12+Parameters!$I$13+Parameters!$I$14+Parameters!$I$15)) -> 1 | AK29: =IF(AND(ISNUMBER(AF29),ISNUMBER(AH29),OR(NOT((Parameters!$I$9)>0),ISNUMBER(AG29)),AJ29>=Parameters!$B$20),100*(Parameters!$F$18*N(AF29)+Parameters!$F$19*N(AG29)+Parameters!$F$20*N(AH29))/(Parameters!$F$18*ISNUMBER(AF29)+Parameters!$F$19*ISNUMBER(AG29)+Parameters!$F$20*ISNUMBER(AH29)),"") -> 86.66 | AL29: =IF(ISNUMBER(AK29),RANK(AK29,$AK$2:$AK$113),"") -> 28 | AM29: =IF(((D29="Implemented/available")+(E29="Implemented/available")+(J29="Implemented/available")+(K29="Implemented/available")+(L29="Implemented/available")+(M29="Implemented/available"))=0,"",(AND(D29="Implemented/available",O29<>"")+AND(E29="Implemented/available",P29<>"")+AND(J29="Implemented/available",Q29<>"")+AND(K29="Implemented/available",R29<>"")+AND(L29="Implemented/available",S29<>"")+AND(M29="Implemented/available",T29<>""))/((D29="Implemented/available")+(E29="Implemented/available")+(J29="Implemented/available")+(K29="Implemented/available")+(L29="Implemented/available")+(M29="Implemented/available"))) -> 1
A30: ARGOS | B30: OpenAIRE | C30: Data management planning tool or service | D30: Implemented/available | E30: Not planning | F30: Implemented/available | G30: Advisory board or steering committee | I30: Formal | J30: In progress | K30: Implemented/available | L30: Implemented/available | M30: Implemented/available | N30: FAIR Guiding Principles for Scientific Data Management and Stewardship | O30: https://www.openaire.eu/governance | R30: https://catalogue.openaire.eu/service/openaire.argos/subscriptions | S30: https://www.openaire.eu/openaire-gep | T30: https://www.openaire.eu/privacy-policy | U30: https://www.openaire.eu/organisation-2 | V30: =IFERROR(IF(ISNUMBER(INDEX(Parameters!$B$5:$B$14,MATCH(D30,Parameters!$A$5:$A$14,0))),INDEX(Parameters!$B$5:$B$14,MATCH(D30,Parameters!$A$5:$A$14,0)),""),"") -> 1 | W30: =IFERROR(IF(ISNUMBER(INDEX(Parameters!$B$5:$B$14,MATCH(E30,Parameters!$A$5:$A$14,0))),INDEX(Parameters!$B$5:$B$14,MATCH(E30,Parameters!$A$5:$A$14,0)),""),"") -> 0 | X30: =IFERROR(IF(ISNUMBER(INDEX(Parameters!$B$5:$B$14,MATCH(F30,Parameters!$A$5:$A$14,0))),INDEX(Parameters!$B$5:$B$14,MATCH(F30,Parameters!$A$5:$A$14,0)),""),"") -> 1 | Y30: =IF(G30<>"",1,IF(ISNUMBER(Parameters!$B$18),Parameters!$B$18,"")) -> 1 | Z30: =IF(I30<>"",IFERROR(IF(ISNUMBER(INDEX(Parameters!$B$5:$B$14,MATCH(I30,Parameters!$A$5:$A$14,0))),INDEX(Parameters!$B$5:$B$14,MATCH(I30,Parameters!$A$5:$A$14,0)),""),""),IF(ISNUMBER(Parameters!$B$21),Parameters!$B$21,"")) -> 1 | AA30: =IFERROR(IF(ISNUMBER(INDEX(Parameters!$B$5:$B$14,MATCH(J30,Parameters!$A$5:$A$14,0))),INDEX(Parameters!$B$5:$B$14,MATCH(J30,Parameters!$A$5:$A$14,0)),""),"") -> 0.67 | AB30: =IFERROR(IF(ISNUMBER(INDEX(Parameters!$B$5:$B$14,MATCH(K30,Parameters!$A$5:$A$14,0))),INDEX(Parameters!$B$5:$B$14,MATCH(K30,Parameters!$A$5:$A$14,0)),""),"") -> 1 | AC30: =IFERROR(IF(ISNUMBER(INDEX(Parameters!$B$5:$B$14,MATCH(L30,Parameters!$A$5:$A$14,0))),INDEX(Parameters!$B$5:$B$14,MATCH(L30,Parameters!$A$5:$A$14,0)),""),"") -> 1 | AD30: =IFERROR(IF(ISNUMBER(INDEX(Parameters!$B$5:$B$14,MATCH(M30,Parameters!$A$5:$A$14,0))),INDEX(Parameters!$B$5:$B$14,MATCH(M30,Parameters!$A$5:$A$14,0)),""),"") -> 1 | AE30: =IF(N30<>"",1,IF(ISNUMBER(Parameters!$B$19),Parameters!$B$19,"")) -> 1 | AF30: =IF((Parameters!$I$5*ISNUMBER(V30)+Parameters!$I$6*ISNUMBER(W30)+Parameters!$I$7*ISNUMBER(X30)+Parameters!$I$8*ISNUMBER(Y30))=0,"",(Parameters!$I$5*N(V30)+Parameters!$I$6*N(W30)+Parameters!$I$7*N(X30)+Parameters!$I$8*N(Y30))/(Parameters!$I$5*ISNUMBER(V30)+Parameters!$I$6*ISNUMBER(W30)+Parameters!$I$7*ISNUMBER(X30)+Parameters!$I$8*ISNUMBER(Y30))) -> 0.7 | AG30: =IF((Parameters!$I$9*ISNUMBER(Z30))=0,"",(Parameters!$I$9*N(Z30))/(Parameters!$I$9*ISNUMBER(Z30))) -> 1 | AH30: =IF((Parameters!$I$11*ISNUMBER(AA30)+Parameters!$I$12*ISNUMBER(AB30)+Parameters!$I$13*ISNUMBER(AC30)+Parameters!$I$14*ISNUMBER(AD30)+Parameters!$I$15*ISNUMBER(AE30))=0,"",(Parameters!$I$11*N(AA30)+Parameters!$I$12*N(AB30)+Parameters!$I$13*N(AC30)+Parameters!$I$14*N(AD30)+Parameters!$I$15*N(AE30))/(Parameters!$I$11*ISNUMBER(AA30)+Parameters!$I$12*ISNUMBER(AB30)+Parameters!$I$13*ISNUMBER(AC30)+Parameters!$I$14*ISNUMBER(AD30)+Parameters!$I$15*ISNUMBER(AE30))) -> 0.934 | AI30: =Parameters!$I$5*ISNUMBER(V30)+Parameters!$I$6*ISNUMBER(W30)+Parameters!$I$7*ISNUMBER(X30)+Parameters!$I$8*ISNUMBER(Y30)+Parameters!$I$9*ISNUMBER(Z30)+Parameters!$I$11*ISNUMBER(AA30)+Parameters!$I$12*ISNUMBER(AB30)+Parameters!$I$13*ISNUMBER(AC30)+Parameters!$I$14*ISNUMBER(AD30)+Parameters!$I$15*ISNUMBER(AE30) -> 95 | AJ30: =IF((Parameters!$I$5+Parameters!$I$6+Parameters!$I$7+Parameters!$I$8+Parameters!$I$9+Parameters!$I$11+Parameters!$I$12+Parameters!$I$13+Parameters!$I$14+Parameters!$I$15)=0,"",AI30/(Parameters!$I$5+Parameters!$I$6+Parameters!$I$7+Parameters!$I$8+Parameters!$I$9+Parameters!$I$11+Parameters!$I$12+Parameters!$I$13+Parameters!$I$14+Parameters!$I$15)) -> 1 | AK30: =IF(AND(ISNUMBER(AF30),ISNUMBER(AH30),OR(NOT((Parameters!$I$9)>0),ISNUMBER(AG30)),AJ30>=Parameters!$B$20),100*(Parameters!$F$18*N(AF30)+Parameters!$F$19*N(AG30)+Parameters!$F$20*N(AH30))/(Parameters!$F$18*ISNUMBER(AF30)+Parameters!$F$19*ISNUMBER(AG30)+Parameters!$F$20*ISNUMBER(AH30)),"") -> 85.69 | AL30: =IF(ISNUMBER(AK30),RANK(AK30,$AK$2:$AK$113),"") -> 29 | AM30: =IF(((D30="Implemented/available")+(E30="Implemented/available")+(J30="Implemented/available")+(K30="Implemented/available")+(L30="Implemented/available")+(M30="Implemented/available"))=0,"",(AND(D30="Implemented/available",O30<>"")+AND(E30="Implemented/available",P30<>"")+AND(J30="Implemented/available",Q30<>"")+AND(K30="Implemented/available",R30<>"")+AND(L30="Implemented/available",S30<>"")+AND(M30="Implemented/available",T30<>""))/((D30="Implemented/available")+(E30="Implemented/available")+(J30="Implemented/available")+(K30="Implemented/available")+(L30="Implemented/available")+(M30="Implemented/available"))) -> 1
A31: InvenioRDM | B31: CERN | C31: Repository software | D31: Implemented/available | E31: In progress | F31: Implemented/available | G31: Advisory board or steering committee | I31: Formal | J31: In progress | K31: No direct costs | L31: Implemented/available | M31: Not applicable | O31: https://inveniosoftware.org/governance/ | S31: https://inveniosoftware.org/governance/ | U31: https://inveniosoftware.org/governance/ | V31: =IFERROR(IF(ISNUMBER(INDEX(Parameters!$B$5:$B$14,MATCH(D31,Parameters!$A$5:$A$14,0))),INDEX(Parameters!$B$5:$B$14,MATCH(D31,Parameters!$A$5:$A$14,0)),""),"") -> 1 | W31: =IFERROR(IF(ISNUMBER(INDEX(Parameters!$B$5:$B$14,MATCH(E31,Parameters!$A$5:$A$14,0))),INDEX(Parameters!$B$5:$B$14,MATCH(E31,Parameters!$A$5:$A$14,0)),""),"") -> 0.67 | X31: =IFERROR(IF(ISNUMBER(INDEX(Parameters!$B$5:$B$14,MATCH(F31,Parameters!$A$5:$A$14,0))),INDEX(Parameters!$B$5:$B$14,MATCH(F31,Parameters!$A$5:$A$14,0)),""),"") -> 1 | Y31: =IF(G31<>"",1,IF(ISNUMBER(Parameters!$B$18),Parameters!$B$18,"")) -> 1 | Z31: =IF(I31<>"",IFERROR(IF(ISNUMBER(INDEX(Parameters!$B$5:$B$14,MATCH(I31,Parameters!$A$5:$A$14,0))),INDEX(Parameters!$B$5:$B$14,MATCH(I31,Parameters!$A$5:$A$14,0)),""),""),IF(ISNUMBER(Parameters!$B$21),Parameters!$B$21,"")) -> 1 | AA31: =IFERROR(IF(ISNUMBER(INDEX(Parameters!$B$5:$B$14,MATCH(J31,Parameters!$A$5:$A$14,0))),INDEX(Parameters!$B$5:$B$14,MATCH(J31,Parameters!$A$5:$A$14,0)),""),"") -> 0.67 | AB31: =IFERROR(IF(ISNUMBER(INDEX(Parameters!$B$5:$B$14,MATCH(K31,Parameters!$A$5:$A$14,0))),INDEX(Parameters!$B$5:$B$14,MATCH(K31,Parameters!$A$5:$A$14,0)),""),"") -> 1 | AC31: =IFERROR(IF(ISNUMBER(INDEX(Parameters!$B$5:$B$14,MATCH(L31,Parameters!$A$5:$A$14,0))),INDEX(Parameters!$B$5:$B$14,MATCH(L31,Parameters!$A$5:$A$14,0)),""),"") -> 1 | AD31: =IFERROR(IF(ISNUMBER(INDEX(Parameters!$B$5:$B$14,MATCH(M31,Parameters!$A$5:$A$14,0))),INDEX(Parameters!$B$5:$B$14,MATCH(M31,Parameters!$A$5:$A$14,0)),""),"") | AE31: =IF(N31<>"",1,IF(ISNUMBER(Parameters!$B$19),Parameters!$B$19,"")) -> 0 | AF31: =IF((Parameters!$I$5*ISNUMBER(V31)+Parameters!$I$6*ISNUMBER(W31)+Parameters!$I$7*ISNUMBER(X31)+Parameters!$I$8*ISNUMBER(Y31))=0,"",(Parameters!$I$5*N(V31)+Parameters!$I$6*N(W31)+Parameters!$I$7*N(X31)+Parameters!$I$8*N(Y31))/(Parameters!$I$5*ISNUMBER(V31)+Parameters!$I$6*ISNUMBER(W31)+Parameters!$I$7*ISNUMBER(X31)+Parameters!$I$8*ISNUMBER(Y31))) -> 0.901 | AG31: =IF((Parameters!$I$9*ISNUMBER(Z31))=0,"",(Parameters!$I$9*N(Z31))/(Parameters!$I$9*ISNUMBER(Z31))) -> 1 | AH31: =IF((Parameters!$I$11*ISNUMBER(AA31)+Parameters!$I$12*ISNUMBER(AB31)+Parameters!$I$13*ISNUMBER(AC31)+Parameters!$I$14*ISNUMBER(AD31)+Parameters!$I$15*ISNUMBER(AE31))=0,"",(Parameters!$I$11*N(AA31)+Parameters!$I$12*N(AB31)+Parameters!$I$13*N(AC31)+Parameters!$I$14*N(AD31)+Parameters!$I$15*N(AE31))/(Parameters!$I$11*ISNUMBER(AA31)+Parameters!$I$12*ISNUMBER(AB31)+Parameters!$I$13*ISNUMBER(AC31)+Parameters!$I$14*ISNUMBER(AD31)+Parameters!$I$15*ISNUMBER(AE31))) -> 0.6675 | AI31: =Parameters!$I$5*ISNUMBER(V31)+Parameters!$I$6*ISNUMBER(W31)+Parameters!$I$7*ISNUMBER(X31)+Parameters!$I$8*ISNUMBER(Y31)+Parameters!$I$9*ISNUMBER(Z31)+Parameters!$I$11*ISNUMBER(AA31)+Parameters!$I$12*ISNUMBER(AB31)+Parameters!$I$13*ISNUMBER(AC31)+Parameters!$I$14*ISNUMBER(AD31)+Parameters!$I$15*ISNUMBER(AE31) -> 88 | AJ31: =IF((Parameters!$I$5+Parameters!$I$6+Parameters!$I$7+Parameters!$I$8+Parameters!$I$9+Parameters!$I$11+Parameters!$I$12+Parameters!$I$13+Parameters!$I$14+Parameters!$I$15)=0,"",AI31/(Parameters!$I$5+Parameters!$I$6+Parameters!$I$7+Parameters!$I$8+Parameters!$I$9+Parameters!$I$11+Parameters!$I$12+Parameters!$I$13+Parameters!$I$14+Parameters!$I$15)) -> 0.92631579 | AK31: =IF(AND(ISNUMBER(AF31),ISNUMBER(AH31),OR(NOT((Parameters!$I$9)>0),ISNUMBER(AG31)),AJ31>=Parameters!$B$20),100*(Parameters!$F$18*N(AF31)+Parameters!$F$19*N(AG31)+Parameters!$F$20*N(AH31))/(Parameters!$F$18*ISNUMBER(AF31)+Parameters!$F$19*ISNUMBER(AG31)+Parameters!$F$20*ISNUMBER(AH31)),"") -> 84.4025 | AL31: =IF(ISNUMBER(AK31),RANK(AK31,$AK$2:$AK$113),"") -> 30 | AM31: =IF(((D31="Implemented/available")+(E31="Implemented/available")+(J31="Implemented/available")+(K31="Implemented/available")+(L31="Implemented/available")+(M31="Implemented/available"))=0,"",(AND(D31="Implemented/available",O31<>"")+AND(E31="Implemented/available",P31<>"")+AND(J31="Implemented/available",Q31<>"")+AND(K31="Implemented/available",R31<>"")+AND(L31="Implemented/available",S31<>"")+AND(M31="Implemented/available",T31<>""))/((D31="Implemented/available")+(E31="Implemented/available")+(J31="Implemented/available")+(K31="Implemented/available")+(L31="Implemented/available")+(M31="Implemented/available"))) -> 1
A32: BitCurator Environment | B32: BitCurator Consortium | C32: Digital preservation tool | D32: Implemented/available | E32: In progress | F32: Implemented/available | G32: Advisory board or steering committee | H32: Both | I32: Formal | J32: Considering | K32: No direct costs | L32: Implemented/available | M32: Implemented/available | O32: https://bitcuratorconsortium.org/about/executive-council/ | S32: https://bitcuratorconsortium.org/inclusivity-statement/ | T32: https://bitcuratorconsortium.org/privacy-policy/ | U32: https://bitcuratorconsortium.org/bitcurator-consortium-charter/ | V32: =IFERROR(IF(ISNUMBER(INDEX(Parameters!$B$5:$B$14,MATCH(D32,Parameters!$A$5:$A$14,0))),INDEX(Parameters!$B$5:$B$14,MATCH(D32,Parameters!$A$5:$A$14,0)),""),"") -> 1 | W32: =IFERROR(IF(ISNUMBER(INDEX(Parameters!$B$5:$B$14,MATCH(E32,Parameters!$A$5:$A$14,0))),INDEX(Parameters!$B$5:$B$14,MATCH(E32,Parameters!$A$5:$A$14,0)),""),"") -> 0.67 | X32: =IFERROR(IF(ISNUMBER(INDEX(Parameters!$B$5:$B$14,MATCH(F32,Parameters!$A$5:$A$14,0))),INDEX(Parameters!$B$5:$B$14,MATCH(F32,Parameters!$A$5:$A$14,0)),""),"") -> 1 | Y32: =IF(G32<>"",1,IF(ISNUMBER(Parameters!$B$18),Parameters!$B$18,"")) -> 1 | Z32: =IF(I32<>"",IFERROR(IF(ISNUMBER(INDEX(Parameters!$B$5:$B$14,MATCH(I32,Parameters!$A$5:$A$14,0))),INDEX(Parameters!$B$5:$B$14,MATCH(I32,Parameters!$A$5:$A$14,0)),""),""),IF(ISNUMBER(Parameters!$B$21),Parameters!$B$21,"")) -> 1 | AA32: =IFERROR(IF(ISNUMBER(INDEX(Parameters!$B$5:$B$14,MATCH(J32,Parameters!$A$5:$A$14,0))),INDEX(Parameters!$B$5:$B$14,MATCH(J32,Parameters!$A$5:$A$14,0)),""),"") -> 0.33 | AB32: =IFERROR(IF(ISNUMBER(INDEX(Parameters!$B$5:$B$14,MATCH(K32,Parameters!$A$5:$A$14,0))),INDEX(Parameters!$B$5:$B$14,MATCH(K32,Parameters!$A$5:$A$14,0)),""),"") -> 1 | AC32: =IFERROR(IF(ISNUMBER(INDEX(Parameters!$B$5:$B$14,MATCH(L32,Parameters!$A$5:$A$14,0))),INDEX(Parameters!$B$5:$B$14,MATCH(L32,Parameters!$A$5:$A$14,0)),""),"") -> 1 | AD32: =IFERROR(IF(ISNUMBER(INDEX(Parameters!$B$5:$B$14,MATCH(M32,Parameters!$A$5:$A$14,0))),INDEX(Parameters!$B$5:$B$14,MATCH(M32,Parameters!$A$5:$A$14,0)),""),"") -> 1 | AE32: =IF(N32<>"",1,IF(ISNUMBER(Parameters!$B$19),Parameters!$B$19,"")) -> 0 | AF32: =IF((Parameters!$I$5*ISNUMBER(V32)+Parameters!$I$6*ISNUMBER(W32)+Parameters!$I$7*ISNUMBER(X32)+Parameters!$I$8*ISNUMBER(Y32))=0,"",(Parameters!$I$5*N(V32)+Parameters!$I$6*N(W32)+Parameters!$I$7*N(X32)+Parameters!$I$8*N(Y32))/(Parameters!$I$5*ISNUMBER(V32)+Parameters!$I$6*ISNUMBER(W32)+Parameters!$I$7*ISNUMBER(X32)+Parameters!$I$8*ISNUMBER(Y32))) -> 0.901 | AG32: =IF((Parameters!$I$9*ISNUMBER(Z32))=0,"",(Parameters!$I$9*N(Z32))/(Parameters!$I$9*ISNUMBER(Z32))) -> 1 | AH32: =IF((Parameters!$I$11*ISNUMBER(AA32)+Parameters!$I$12*ISNUMBER(AB32)+Parameters!$I$13*ISNUMBER(AC32)+Parameters!$I$14*ISNUMBER(AD32)+Parameters!$I$15*ISNUMBER(AE32))=0,"",(Parameters!$I$11*N(AA32)+Parameters!$I$12*N(AB32)+Parameters!$I$13*N(AC32)+Parameters!$I$14*N(AD32)+Parameters!$I$15*N(AE32))/(Parameters!$I$11*ISNUMBER(AA32)+Parameters!$I$12*ISNUMBER(AB32)+Parameters!$I$13*ISNUMBER(AC32)+Parameters!$I$14*ISNUMBER(AD32)+Parameters!$I$15*ISNUMBER(AE32))) -> 0.666 | AI32: =Parameters!$I$5*ISNUMBER(V32)+Parameters!$I$6*ISNUMBER(W32)+Parameters!$I$7*ISNUMBER(X32)+Parameters!$I$8*ISNUMBER(Y32)+Parameters!$I$9*ISNUMBER(Z32)+Parameters!$I$11*ISNUMBER(AA32)+Parameters!$I$12*ISNUMBER(AB32)+Parameters!$I$13*ISNUMBER(AC32)+Parameters!$I$14*ISNUMBER(AD32)+Parameters!$I$15*ISNUMBER(AE32) -> 95 | AJ32: =IF((Parameters!$I$5+Parameters!$I$6+Parameters!$I$7+Parameters!$I$8+Parameters!$I$9+Parameters!$I$11+Parameters!$I$12+Parameters!$I$13+Parameters!$I$14+Parameters!$I$15)=0,"",AI32/(Parameters!$I$5+Parameters!$I$6+Parameters!$I$7+Parameters!$I$8+Parameters!$I$9+Parameters!$I$11+Parameters!$I$12+Parameters!$I$13+Parameters!$I$14+Parameters!$I$15)) -> 1 | AK32: =IF(AND(ISNUMBER(AF32),ISNUMBER(AH32),OR(NOT((Parameters!$I$9)>0),ISNUMBER(AG32)),AJ32>=Parameters!$B$20),100*(Parameters!$F$18*N(AF32)+Parameters!$F$19*N(AG32)+Parameters!$F$20*N(AH32))/(Parameters!$F$18*ISNUMBER(AF32)+Parameters!$F$19*ISNUMBER(AG32)+Parameters!$F$20*ISNUMBER(AH32)),"") -> 84.35 | AL32: =IF(ISNUMBER(AK32),RANK(AK32,$AK$2:$AK$113),"") -> 31 | AM32: =IF(((D32="Implemented/available")+(E32="Implemented/available")+(J32="Implemented/available")+(K32="Implemented/available")+(L32="Implemented/available")+(M32="Implemented/available"))=0,"",(AND(D32="Implemented/available",O32<>"")+AND(E32="Implemented/available",P32<>"")+AND(J32="Implemented/available",Q32<>"")+AND(K32="Implemented/available",R32<>"")+AND(L32="Implemented/available",S32<>"")+AND(M32="Implemented/available",T32<>""))/((D32="Implemented/available")+(E32="Implemented/available")+(J32="Implemented/available")+(K32="Implemented/available")+(L32="Implemented/available")+(M32="Implemented/available"))) -> 1
A33: CORE | B33: The Open University | C33: Discovery system | D33: Implemented/available | E33: In progress | F33: Implemented/available | G33: Multi-board governance | I33: Formal | J33: Implemented/available | K33: Implemented/available | L33: Considering | M33: Implemented/available | O33: https://core.ac.uk/governance | Q33: https://core.ac.uk/accessibility | R33: https://core.ac.uk/membership | T33: https://core.ac.uk/privacy | U33: https://core.ac.uk/governance | V33: =IFERROR(IF(ISNUMBER(INDEX(Parameters!$B$5:$B$14,MATCH(D33,Parameters!$A$5:$A$14,0))),INDEX(Parameters!$B$5:$B$14,MATCH(D33,Parameters!$A$5:$A$14,0)),""),"") -> 1 | W33: =IFERROR(IF(ISNUMBER(INDEX(Parameters!$B$5:$B$14,MATCH(E33,Parameters!$A$5:$A$14,0))),INDEX(Parameters!$B$5:$B$14,MATCH(E33,Parameters!$A$5:$A$14,0)),""),"") -> 0.67 | X33: =IFERROR(IF(ISNUMBER(INDEX(Parameters!$B$5:$B$14,MATCH(F33,Parameters!$A$5:$A$14,0))),INDEX(Parameters!$B$5:$B$14,MATCH(F33,Parameters!$A$5:$A$14,0)),""),"") -> 1 | Y33: =IF(G33<>"",1,IF(ISNUMBER(Parameters!$B$18),Parameters!$B$18,"")) -> 1 | Z33: =IF(I33<>"",IFERROR(IF(ISNUMBER(INDEX(Parameters!$B$5:$B$14,MATCH(I33,Parameters!$A$5:$A$14,0))),INDEX(Parameters!$B$5:$B$14,MATCH(I33,Parameters!$A$5:$A$14,0)),""),""),IF(ISNUMBER(Parameters!$B$21),Parameters!$B$21,"")) -> 1 | AA33: =IFERROR(IF(ISNUMBER(INDEX(Parameters!$B$5:$B$14,MATCH(J33,Parameters!$A$5:$A$14,0))),INDEX(Parameters!$B$5:$B$14,MATCH(J33,Parameters!$A$5:$A$14,0)),""),"") -> 1 | AB33: =IFERROR(IF(ISNUMBER(INDEX(Parameters!$B$5:$B$14,MATCH(K33,Parameters!$A$5:$A$14,0))),INDEX(Parameters!$B$5:$B$14,MATCH(K33,Parameters!$A$5:$A$14,0)),""),"") -> 1 | AC33: =IFERROR(IF(ISNUMBER(INDEX(Parameters!$B$5:$B$14,MATCH(L33,Parameters!$A$5:$A$14,0))),INDEX(Parameters!$B$5:$B$14,MATCH(L33,Parameters!$A$5:$A$14,0)),""),"") -> 0.33 | AD33: =IFERROR(IF(ISNUMBER(INDEX(Parameters!$B$5:$B$14,MATCH(M33,Parameters!$A$5:$A$14,0))),INDEX(Parameters!$B$5:$B$14,MATCH(M33,Parameters!$A$5:$A$14,0)),""),"") -> 1 | AE33: =IF(N33<>"",1,IF(ISNUMBER(Parameters!$B$19),Parameters!$B$19,"")) -> 0 | AF33: =IF((Parameters!$I$5*ISNUMBER(V33)+Parameters!$I$6*ISNUMBER(W33)+Parameters!$I$7*ISNUMBER(X33)+Parameters!$I$8*ISNUMBER(Y33))=0,"",(Parameters!$I$5*N(V33)+Parameters!$I$6*N(W33)+Parameters!$I$7*N(X33)+Parameters!$I$8*N(Y33))/(Parameters!$I$5*ISNUMBER(V33)+Parameters!$I$6*ISNUMBER(W33)+Parameters!$I$7*ISNUMBER(X33)+Parameters!$I$8*ISNUMBER(Y33))) -> 0.901 | AG33: =IF((Parameters!$I$9*ISNUMBER(Z33))=0,"",(Parameters!$I$9*N(Z33))/(Parameters!$I$9*ISNUMBER(Z33))) -> 1 | AH33: =IF((Parameters!$I$11*ISNUMBER(AA33)+Parameters!$I$12*ISNUMBER(AB33)+Parameters!$I$13*ISNUMBER(AC33)+Parameters!$I$14*ISNUMBER(AD33)+Parameters!$I$15*ISNUMBER(AE33))=0,"",(Parameters!$I$11*N(AA33)+Parameters!$I$12*N(AB33)+Parameters!$I$13*N(AC33)+Parameters!$I$14*N(AD33)+Parameters!$I$15*N(AE33))/(Parameters!$I$11*ISNUMBER(AA33)+Parameters!$I$12*ISNUMBER(AB33)+Parameters!$I$13*ISNUMBER(AC33)+Parameters!$I$14*ISNUMBER(AD33)+Parameters!$I$15*ISNUMBER(AE33))) -> 0.666 | AI33: =Parameters!$I$5*ISNUMBER(V33)+Parameters!$I$6*ISNUMBER(W33)+Parameters!$I$7*ISNUMBER(X33)+Parameters!$I$8*ISNUMBER(Y33)+Parameters!$I$9*ISNUMBER(Z33)+Parameters!$I$11*ISNUMBER(AA33)+Parameters!$I$12*ISNUMBER(AB33)+Parameters!$I$13*ISNUMBER(AC33)+Parameters!$I$14*ISNUMBER(AD33)+Parameters!$I$15*ISNUMBER(AE33) -> 95 | AJ33: =IF((Parameters!$I$5+Parameters!$I$6+Parameters!$I$7+Parameters!$I$8+Parameters!$I$9+Parameters!$I$11+Parameters!$I$12+Parameters!$I$13+Parameters!$I$14+Parameters!$I$15)=0,"",AI33/(Parameters!$I$5+Parameters!$I$6+Parameters!$I$7+Parameters!$I$8+Parameters!$I$9+Parameters!$I$11+Parameters!$I$12+Parameters!$I$13+Parameters!$I$14+Parameters!$I$15)) -> 1 | AK33: =IF(AND(ISNUMBER(AF33),ISNUMBER(AH33),OR(NOT((Parameters!$I$9)>0),ISNUMBER(AG33)),AJ33>=Parameters!$B$20),100*(Parameters!$F$18*N(AF33)+Parameters!$F$19*N(AG33)+Parameters!$F$20*N(AH33))/(Parameters!$F$18*ISNUMBER(AF33)+Parameters!$F$19*ISNUMBER(AG33)+Parameters!$F$20*ISNUMBER(AH33)),"") -> 84.35 | AL33: =IF(ISNUMBER(AK33),RANK(AK33,$AK$2:$AK$113),"") -> 31 | AM33: =IF(((D33="Implemented/available")+(E33="Implemented/available")+(J33="Implemented/available")+(K33="Implemented/available")+(L33="Implemented/available")+(M33="Implemented/available"))=0,"",(AND(D33="Implemented/available",O33<>"")+AND(E33="Implemented/available",P33<>"")+AND(J33="Implemented/available",Q33<>"")+AND(K33="Implemented/available",R33<>"")+AND(L33="Implemented/available",S33<>"")+AND(M33="Implemented/available",T33<>""))/((D33="Implemented/available")+(E33="Implemented/available")+(J33="Implemented/available")+(K33="Implemented/available")+(L33="Implemented/available")+(M33="Implemented/available"))) -> 1
A34: Biodiversity Heritage Library | B34: BHL Consortium | C34: Digital library, collection or exhibit platform | Open scholarly dataset | Repository service | D34: Implemented/available | E34: Implemented/available | F34: Implemented/available | G34: Advisory board or steering committee | H34: Both | I34: Formal | J34: Considering | K34: No direct costs | L34: Considering | M34: Implemented/available | O34: https://about.biodiversitylibrary.org/about/bhl-consortium/ | P34: https://about.biodiversitylibrary.org/about/strategic-plan/ | T34: https://www.si.edu/privacy | U34: https://about.biodiversitylibrary.org/about/bylaws/ | V34: =IFERROR(IF(ISNUMBER(INDEX(Parameters!$B$5:$B$14,MATCH(D34,Parameters!$A$5:$A$14,0))),INDEX(Parameters!$B$5:$B$14,MATCH(D34,Parameters!$A$5:$A$14,0)),""),"") -> 1 | W34: =IFERROR(IF(ISNUMBER(INDEX(Parameters!$B$5:$B$14,MATCH(E34,Parameters!$A$5:$A$14,0))),INDEX(Parameters!$B$5:$B$14,MATCH(E34,Parameters!$A$5:$A$14,0)),""),"") -> 1 | X34: =IFERROR(IF(ISNUMBER(INDEX(Parameters!$B$5:$B$14,MATCH(F34,Parameters!$A$5:$A$14,0))),INDEX(Parameters!$B$5:$B$14,MATCH(F34,Parameters!$A$5:$A$14,0)),""),"") -> 1 | Y34: =IF(G34<>"",1,IF(ISNUMBER(Parameters!$B$18),Parameters!$B$18,"")) -> 1 | Z34: =IF(I34<>"",IFERROR(IF(ISNUMBER(INDEX(Parameters!$B$5:$B$14,MATCH(I34,Parameters!$A$5:$A$14,0))),INDEX(Parameters!$B$5:$B$14,MATCH(I34,Parameters!$A$5:$A$14,0)),""),""),IF(ISNUMBER(Parameters!$B$21),Parameters!$B$21,"")) -> 1 | AA34: =IFERROR(IF(ISNUMBER(INDEX(Parameters!$B$5:$B$14,MATCH(J34,Parameters!$A$5:$A$14,0))),INDEX(Parameters!$B$5:$B$14,MATCH(J34,Parameters!$A$5:$A$14,0)),""),"") -> 0.33 | AB34: =IFERROR(IF(ISNUMBER(INDEX(Parameters!$B$5:$B$14,MATCH(K34,Parameters!$A$5:$A$14,0))),INDEX(Parameters!$B$5:$B$14,MATCH(K34,Parameters!$A$5:$A$14,0)),""),"") -> 1 | AC34: =IFERROR(IF(ISNUMBER(INDEX(Parameters!$B$5:$B$14,MATCH(L34,Parameters!$A$5:$A$14,0))),INDEX(Parameters!$B$5:$B$14,MATCH(L34,Parameters!$A$5:$A$14,0)),""),"") -> 0.33 | AD34: =IFERROR(IF(ISNUMBER(INDEX(Parameters!$B$5:$B$14,MATCH(M34,Parameters!$A$5:$A$14,0))),INDEX(Parameters!$B$5:$B$14,MATCH(M34,Parameters!$A$5:$A$14,0)),""),"") -> 1 | AE34: =IF(N34<>"",1,IF(ISNUMBER(Parameters!$B$19),Parameters!$B$19,"")) -> 0 | AF34: =IF((Parameters!$I$5*ISNUMBER(V34)+Parameters!$I$6*ISNUMBER(W34)+Parameters!$I$7*ISNUMBER(X34)+Parameters!$I$8*ISNUMBER(Y34))=0,"",(Parameters!$I$5*N(V34)+Parameters!$I$6*N(W34)+Parameters!$I$7*N(X34)+Parameters!$I$8*N(Y34))/(Parameters!$I$5*ISNUMBER(V34)+Parameters!$I$6*ISNUMBER(W34)+Parameters!$I$7*ISNUMBER(X34)+Parameters!$I$8*ISNUMBER(Y34))) -> 1 | AG34: =IF((Parameters!$I$9*ISNUMBER(Z34))=0,"",(Parameters!$I$9*N(Z34))/(Parameters!$I$9*ISNUMBER(Z34))) -> 1 | AH34: =IF((Parameters!$I$11*ISNUMBER(AA34)+Parameters!$I$12*ISNUMBER(AB34)+Parameters!$I$13*ISNUMBER(AC34)+Parameters!$I$14*ISNUMBER(AD34)+Parameters!$I$15*ISNUMBER(AE34))=0,"",(Parameters!$I$11*N(AA34)+Parameters!$I$12*N(AB34)+Parameters!$I$13*N(AC34)+Parameters!$I$14*N(AD34)+Parameters!$I$15*N(AE34))/(Parameters!$I$11*ISNUMBER(AA34)+Parameters!$I$12*ISNUMBER(AB34)+Parameters!$I$13*ISNUMBER(AC34)+Parameters!$I$14*ISNUMBER(AD34)+Parameters!$I$15*ISNUMBER(AE34))) -> 0.532 | AI34: =Parameters!$I$5*ISNUMBER(V34)+Parameters!$I$6*ISNUMBER(W34)+Parameters!$I$7*ISNUMBER(X34)+Parameters!$I$8*ISNUMBER(Y34)+Parameters!$I$9*ISNUMBER(Z34)+Parameters!$I$11*ISNUMBER(AA34)+Parameters!$I$12*ISNUMBER(AB34)+Parameters!$I$13*ISNUMBER(AC34)+Parameters!$I$14*ISNUMBER(AD34)+Parameters!$I$15*ISNUMBER(AE34) -> 95 | AJ34: =IF((Parameters!$I$5+Parameters!$I$6+Parameters!$I$7+Parameters!$I$8+Parameters!$I$9+Parameters!$I$11+Parameters!$I$12+Parameters!$I$13+Parameters!$I$14+Parameters!$I$15)=0,"",AI34/(Parameters!$I$5+Parameters!$I$6+Parameters!$I$7+Parameters!$I$8+Parameters!$I$9+Parameters!$I$11+Parameters!$I$12+Parameters!$I$13+Parameters!$I$14+Parameters!$I$15)) -> 1 | AK34: =IF(AND(ISNUMBER(AF34),ISNUMBER(AH34),OR(NOT((Parameters!$I$9)>0),ISNUMBER(AG34)),AJ34>=Parameters!$B$20),100*(Parameters!$F$18*N(AF34)+Parameters!$F$19*N(AG34)+Parameters!$F$20*N(AH34))/(Parameters!$F$18*ISNUMBER(AF34)+Parameters!$F$19*ISNUMBER(AG34)+Parameters!$F$20*ISNUMBER(AH34)),"") -> 83.62 | AL34: =IF(ISNUMBER(AK34),RANK(AK34,$AK$2:$AK$113),"") -> 33 | AM34: =IF(((D34="Implemented/available")+(E34="Implemented/available")+(J34="Implemented/available")+(K34="Implemented/available")+(L34="Implemented/available")+(M34="Implemented/available"))=0,"",(AND(D34="Implemented/available",O34<>"")+AND(E34="Implemented/available",P34<>"")+AND(J34="Implemented/available",Q34<>"")+AND(K34="Implemented/available",R34<>"")+AND(L34="Implemented/available",S34<>"")+AND(M34="Implemented/available",T34<>""))/((D34="Implemented/available")+(E34="Implemented/available")+(J34="Implemented/available")+(K34="Implemented/available")+(L34="Implemented/available")+(M34="Implemented/available"))) -> 1
A35: Open Data Editor | B35: Open Knowledge Foundation | C35: Data collection or management tool | D35: Implemented/available | E35: Implemented/available | F35: Implemented/available | G35: Advisory board or steering committee | H35: Provider | I35: Formal | J35: Considering | K35: No direct costs | L35: Considering | M35: Implemented/available | O35: https://okfn.org/en/who-we-are/governance/ | P35: https://okfn.org/en/who-we-are/board/#minutes | T35: https://okfn.org/en/privacy-policy/ | U35: https://okfn.org/en/who-we-are/governance/ | V35: =IFERROR(IF(ISNUMBER(INDEX(Parameters!$B$5:$B$14,MATCH(D35,Parameters!$A$5:$A$14,0))),INDEX(Parameters!$B$5:$B$14,MATCH(D35,Parameters!$A$5:$A$14,0)),""),"") -> 1 | W35: =IFERROR(IF(ISNUMBER(INDEX(Parameters!$B$5:$B$14,MATCH(E35,Parameters!$A$5:$A$14,0))),INDEX(Parameters!$B$5:$B$14,MATCH(E35,Parameters!$A$5:$A$14,0)),""),"") -> 1 | X35: =IFERROR(IF(ISNUMBER(INDEX(Parameters!$B$5:$B$14,MATCH(F35,Parameters!$A$5:$A$14,0))),INDEX(Parameters!$B$5:$B$14,MATCH(F35,Parameters!$A$5:$A$14,0)),""),"") -> 1 | Y35: =IF(G35<>"",1,IF(ISNUMBER(Parameters!$B$18),Parameters!$B$18,"")) -> 1 | Z35: =IF(I35<>"",IFERROR(IF(ISNUMBER(INDEX(Parameters!$B$5:$B$14,MATCH(I35,Parameters!$A$5:$A$14,0))),INDEX(Parameters!$B$5:$B$14,MATCH(I35,Parameters!$A$5:$A$14,0)),""),""),IF(ISNUMBER(Parameters!$B$21),Parameters!$B$21,"")) -> 1 | AA35: =IFERROR(IF(ISNUMBER(INDEX(Parameters!$B$5:$B$14,MATCH(J35,Parameters!$A$5:$A$14,0))),INDEX(Parameters!$B$5:$B$14,MATCH(J35,Parameters!$A$5:$A$14,0)),""),"") -> 0.33 | AB35: =IFERROR(IF(ISNUMBER(INDEX(Parameters!$B$5:$B$14,MATCH(K35,Parameters!$A$5:$A$14,0))),INDEX(Parameters!$B$5:$B$14,MATCH(K35,Parameters!$A$5:$A$14,0)),""),"") -> 1 | AC35: =IFERROR(IF(ISNUMBER(INDEX(Parameters!$B$5:$B$14,MATCH(L35,Parameters!$A$5:$A$14,0))),INDEX(Parameters!$B$5:$B$14,MATCH(L35,Parameters!$A$5:$A$14,0)),""),"") -> 0.33 | AD35: =IFERROR(IF(ISNUMBER(INDEX(Parameters!$B$5:$B$14,MATCH(M35,Parameters!$A$5:$A$14,0))),INDEX(Parameters!$B$5:$B$14,MATCH(M35,Parameters!$A$5:$A$14,0)),""),"") -> 1 | AE35: =IF(N35<>"",1,IF(ISNUMBER(Parameters!$B$19),Parameters!$B$19,"")) -> 0 | AF35: =IF((Parameters!$I$5*ISNUMBER(V35)+Parameters!$I$6*ISNUMBER(W35)+Parameters!$I$7*ISNUMBER(X35)+Parameters!$I$8*ISNUMBER(Y35))=0,"",(Parameters!$I$5*N(V35)+Parameters!$I$6*N(W35)+Parameters!$I$7*N(X35)+Parameters!$I$8*N(Y35))/(Parameters!$I$5*ISNUMBER(V35)+Parameters!$I$6*ISNUMBER(W35)+Parameters!$I$7*ISNUMBER(X35)+Parameters!$I$8*ISNUMBER(Y35))) -> 1 | AG35: =IF((Parameters!$I$9*ISNUMBER(Z35))=0,"",(Parameters!$I$9*N(Z35))/(Parameters!$I$9*ISNUMBER(Z35))) -> 1 | AH35: =IF((Parameters!$I$11*ISNUMBER(AA35)+Parameters!$I$12*ISNUMBER(AB35)+Parameters!$I$13*ISNUMBER(AC35)+Parameters!$I$14*ISNUMBER(AD35)+Parameters!$I$15*ISNUMBER(AE35))=0,"",(Parameters!$I$11*N(AA35)+Parameters!$I$12*N(AB35)+Parameters!$I$13*N(AC35)+Parameters!$I$14*N(AD35)+Parameters!$I$15*N(AE35))/(Parameters!$I$11*ISNUMBER(AA35)+Parameters!$I$12*ISNUMBER(AB35)+Parameters!$I$13*ISNUMBER(AC35)+Parameters!$I$14*ISNUMBER(AD35)+Parameters!$I$15*ISNUMBER(AE35))) -> 0.532 | AI35: =Parameters!$I$5*ISNUMBER(V35)+Parameters!$I$6*ISNUMBER(W35)+Parameters!$I$7*ISNUMBER(X35)+Parameters!$I$8*ISNUMBER(Y35)+Parameters!$I$9*ISNUMBER(Z35)+Parameters!$I$11*ISNUMBER(AA35)+Parameters!$I$12*ISNUMBER(AB35)+Parameters!$I$13*ISNUMBER(AC35)+Parameters!$I$14*ISNUMBER(AD35)+Parameters!$I$15*ISNUMBER(AE35) -> 95 | AJ35: =IF((Parameters!$I$5+Parameters!$I$6+Parameters!$I$7+Parameters!$I$8+Parameters!$I$9+Parameters!$I$11+Parameters!$I$12+Parameters!$I$13+Parameters!$I$14+Parameters!$I$15)=0,"",AI35/(Parameters!$I$5+Parameters!$I$6+Parameters!$I$7+Parameters!$I$8+Parameters!$I$9+Parameters!$I$11+Parameters!$I$12+Parameters!$I$13+Parameters!$I$14+Parameters!$I$15)) -> 1 | AK35: =IF(AND(ISNUMBER(AF35),ISNUMBER(AH35),OR(NOT((Parameters!$I$9)>0),ISNUMBER(AG35)),AJ35>=Parameters!$B$20),100*(Parameters!$F$18*N(AF35)+Parameters!$F$19*N(AG35)+Parameters!$F$20*N(AH35))/(Parameters!$F$18*ISNUMBER(AF35)+Parameters!$F$19*ISNUMBER(AG35)+Parameters!$F$20*ISNUMBER(AH35)),"") -> 83.62 | AL35: =IF(ISNUMBER(AK35),RANK(AK35,$AK$2:$AK$113),"") -> 33 | AM35: =IF(((D35="Implemented/available")+(E35="Implemented/available")+(J35="Implemented/available")+(K35="Implemented/available")+(L35="Implemented/available")+(M35="Implemented/available"))=0,"",(AND(D35="Implemented/available",O35<>"")+AND(E35="Implemented/available",P35<>"")+AND(J35="Implemented/available",Q35<>"")+AND(K35="Implemented/available",R35<>"")+AND(L35="Implemented/available",S35<>"")+AND(M35="Implemented/available",T35<>""))/((D35="Implemented/available")+(E35="Implemented/available")+(J35="Implemented/available")+(K35="Implemented/available")+(L35="Implemented/available")+(M35="Implemented/available"))) -> 1
A36: OA Switchboard | B36: Stichting OA Switchboard | C36: Open access or subscription management tool | D36: Implemented/available | E36: Implemented/available | F36: Implemented/available | I36: Formal | J36: Unknown | K36: Implemented/available | L36: Implemented/available | M36: Implemented/available | O36: https://www.oaswitchboard.org/governance | P36: https://www.oaswitchboard.org/governance | R36: https://www.oaswitchboard.org/faq | S36: https://www.oaswitchboard.org/governance | T36: https://www.oaswitchboard.org/privacy-statement | U36: https://www.oaswitchboard.org/governance | V36: =IFERROR(IF(ISNUMBER(INDEX(Parameters!$B$5:$B$14,MATCH(D36,Parameters!$A$5:$A$14,0))),INDEX(Parameters!$B$5:$B$14,MATCH(D36,Parameters!$A$5:$A$14,0)),""),"") -> 1 | W36: =IFERROR(IF(ISNUMBER(INDEX(Parameters!$B$5:$B$14,MATCH(E36,Parameters!$A$5:$A$14,0))),INDEX(Parameters!$B$5:$B$14,MATCH(E36,Parameters!$A$5:$A$14,0)),""),"") -> 1 | X36: =IFERROR(IF(ISNUMBER(INDEX(Parameters!$B$5:$B$14,MATCH(F36,Parameters!$A$5:$A$14,0))),INDEX(Parameters!$B$5:$B$14,MATCH(F36,Parameters!$A$5:$A$14,0)),""),"") -> 1 | Y36: =IF(G36<>"",1,IF(ISNUMBER(Parameters!$B$18),Parameters!$B$18,"")) -> 0 | Z36: =IF(I36<>"",IFERROR(IF(ISNUMBER(INDEX(Parameters!$B$5:$B$14,MATCH(I36,Parameters!$A$5:$A$14,0))),INDEX(Parameters!$B$5:$B$14,MATCH(I36,Parameters!$A$5:$A$14,0)),""),""),IF(ISNUMBER(Parameters!$B$21),Parameters!$B$21,"")) -> 1 | AA36: =IFERROR(IF(ISNUMBER(INDEX(Parameters!$B$5:$B$14,MATCH(J36,Parameters!$A$5:$A$14,0))),INDEX(Parameters!$B$5:$B$14,MATCH(J36,Parameters!$A$5:$A$14,0)),""),"") | AB36: =IFERROR(IF(ISNUMBER(INDEX(Parameters!$B$5:$B$14,MATCH(K36,Parameters!$A$5:$A$14,0))),INDEX(Parameters!$B$5:$B$14,MATCH(K36,Parameters!$A$5:$A$14,0)),""),"") -> 1 | AC36: =IFERROR(IF(ISNUMBER(INDEX(Parameters!$B$5:$B$14,MATCH(L36,Parameters!$A$5:$A$14,0))),INDEX(Parameters!$B$5:$B$14,MATCH(L36,Parameters!$A$5:$A$14,0)),""),"") -> 1 | AD36: =IFERROR(IF(ISNUMBER(INDEX(Parameters!$B$5:$B$14,MATCH(M36,Parameters!$A$5:$A$14,0))),INDEX(Parameters!$B$5:$B$14,MATCH(M36,Parameters!$A$5:$A$14,0)),""),"") -> 1 | AE36: =IF(N36<>"",1,IF(ISNUMBER(Parameters!$B$19),Parameters!$B$19,"")) -> 0 | AF36: =IF((Parameters!$I$5*ISNUMBER(V36)+Parameters!$I$6*ISNUMBER(W36)+Parameters!$I$7*ISNUMBER(X36)+Parameters!$I$8*ISNUMBER(Y36))=0,"",(Parameters!$I$5*N(V36)+Parameters!$I$6*N(W36)+Parameters!$I$7*N(X36)+Parameters!$I$8*N(Y36))/(Parameters!$I$5*ISNUMBER(V36)+Parameters!$I$6*ISNUMBER(W36)+Parameters!$I$7*ISNUMBER(X36)+Parameters!$I$8*ISNUMBER(Y36))) -> 0.8 | AG36: =IF((Parameters!$I$9*ISNUMBER(Z36))=0,"",(Parameters!$I$9*N(Z36))/(Parameters!$I$9*ISNUMBER(Z36))) -> 1 | AH36: =IF((Parameters!$I$11*ISNUMBER(AA36)+Parameters!$I$12*ISNUMBER(AB36)+Parameters!$I$13*ISNUMBER(AC36)+Parameters!$I$14*ISNUMBER(AD36)+Parameters!$I$15*ISNUMBER(AE36))=0,"",(Parameters!$I$11*N(AA36)+Parameters!$I$12*N(AB36)+Parameters!$I$13*N(AC36)+Parameters!$I$14*N(AD36)+Parameters!$I$15*N(AE36))/(Parameters!$I$11*ISNUMBER(AA36)+Parameters!$I$12*ISNUMBER(AB36)+Parameters!$I$13*ISNUMBER(AC36)+Parameters!$I$14*ISNUMBER(AD36)+Parameters!$I$15*ISNUMBER(AE36))) -> 0.75 | AI36: =Parameters!$I$5*ISNUMBER(V36)+Parameters!$I$6*ISNUMBER(W36)+Parameters!$I$7*ISNUMBER(X36)+Parameters!$I$8*ISNUMBER(Y36)+Parameters!$I$9*ISNUMBER(Z36)+Parameters!$I$11*ISNUMBER(AA36)+Parameters!$I$12*ISNUMBER(AB36)+Parameters!$I$13*ISNUMBER(AC36)+Parameters!$I$14*ISNUMBER(AD36)+Parameters!$I$15*ISNUMBER(AE36) -> 88 | AJ36: =IF((Parameters!$I$5+Parameters!$I$6+Parameters!$I$7+Parameters!$I$8+Parameters!$I$9+Parameters!$I$11+Parameters!$I$12+Parameters!$I$13+Parameters!$I$14+Parameters!$I$15)=0,"",AI36/(Parameters!$I$5+Parameters!$I$6+Parameters!$I$7+Parameters!$I$8+Parameters!$I$9+Parameters!$I$11+Parameters!$I$12+Parameters!$I$13+Parameters!$I$14+Parameters!$I$15)) -> 0.92631579 | AK36: =IF(AND(ISNUMBER(AF36),ISNUMBER(AH36),OR(NOT((Parameters!$I$9)>0),ISNUMBER(AG36)),AJ36>=Parameters!$B$20),100*(Parameters!$F$18*N(AF36)+Parameters!$F$19*N(AG36)+Parameters!$F$20*N(AH36))/(Parameters!$F$18*ISNUMBER(AF36)+Parameters!$F$19*ISNUMBER(AG36)+Parameters!$F$20*ISNUMBER(AH36)),"") -> 83.25 | AL36: =IF(ISNUMBER(AK36),RANK(AK36,$AK$2:$AK$113),"") -> 35 | AM36: =IF(((D36="Implemented/available")+(E36="Implemented/available")+(J36="Implemented/available")+(K36="Implemented/available")+(L36="Implemented/available")+(M36="Implemented/available"))=0,"",(AND(D36="Implemented/available",O36<>"")+AND(E36="Implemented/available",P36<>"")+AND(J36="Implemented/available",Q36<>"")+AND(K36="Implemented/available",R36<>"")+AND(L36="Implemented/available",S36<>"")+AND(M36="Implemented/available",T36<>""))/((D36="Implemented/available")+(E36="Implemented/available")+(J36="Implemented/available")+(K36="Implemented/available")+(L36="Implemented/available")+(M36="Implemented/available"))) -> 1
A37: CLOCKSS | B37: CLOCKSS | C37: Digital preservation service | D37: Implemented/available | E37: Considering | F37: Implemented/available | G37: Advisory board or steering committee | I37: Formal | J37: In progress | K37: Implemented/available | L37: Implemented/available | M37: Implemented/available | O37: https://clockss.org/digital-archive-community/board-of-directors/ | R37: https://clockss.org/join-clockss/ | S37: https://clockss.org/biblio-equity-in-action-advancing-collection-development-for-diversity-equity-and-inclusion/ | T37: https://clockss.org/clockss-privacy-policy/ | U37: https://clockss.org/wp-content/uploads/2024/03/DIGITAL-DISTRIBUTED-COMMUNITY-ARCHIVE-ByLaws.pdf | V37: =IFERROR(IF(ISNUMBER(INDEX(Parameters!$B$5:$B$14,MATCH(D37,Parameters!$A$5:$A$14,0))),INDEX(Parameters!$B$5:$B$14,MATCH(D37,Parameters!$A$5:$A$14,0)),""),"") -> 1 | W37: =IFERROR(IF(ISNUMBER(INDEX(Parameters!$B$5:$B$14,MATCH(E37,Parameters!$A$5:$A$14,0))),INDEX(Parameters!$B$5:$B$14,MATCH(E37,Parameters!$A$5:$A$14,0)),""),"") -> 0.33 | X37: =IFERROR(IF(ISNUMBER(INDEX(Parameters!$B$5:$B$14,MATCH(F37,Parameters!$A$5:$A$14,0))),INDEX(Parameters!$B$5:$B$14,MATCH(F37,Parameters!$A$5:$A$14,0)),""),"") -> 1 | Y37: =IF(G37<>"",1,IF(ISNUMBER(Parameters!$B$18),Parameters!$B$18,"")) -> 1 | Z37: =IF(I37<>"",IFERROR(IF(ISNUMBER(INDEX(Parameters!$B$5:$B$14,MATCH(I37,Parameters!$A$5:$A$14,0))),INDEX(Parameters!$B$5:$B$14,MATCH(I37,Parameters!$A$5:$A$14,0)),""),""),IF(ISNUMBER(Parameters!$B$21),Parameters!$B$21,"")) -> 1 | AA37: =IFERROR(IF(ISNUMBER(INDEX(Parameters!$B$5:$B$14,MATCH(J37,Parameters!$A$5:$A$14,0))),INDEX(Parameters!$B$5:$B$14,MATCH(J37,Parameters!$A$5:$A$14,0)),""),"") -> 0.67 | AB37: =IFERROR(IF(ISNUMBER(INDEX(Parameters!$B$5:$B$14,MATCH(K37,Parameters!$A$5:$A$14,0))),INDEX(Parameters!$B$5:$B$14,MATCH(K37,Parameters!$A$5:$A$14,0)),""),"") -> 1 | AC37: =IFERROR(IF(ISNUMBER(INDEX(Parameters!$B$5:$B$14,MATCH(L37,Parameters!$A$5:$A$14,0))),INDEX(Parameters!$B$5:$B$14,MATCH(L37,Parameters!$A$5:$A$14,0)),""),"") -> 1 | AD37: =IFERROR(IF(ISNUMBER(INDEX(Parameters!$B$5:$B$14,MATCH(M37,Parameters!$A$5:$A$14,0))),INDEX(Parameters!$B$5:$B$14,MATCH(M37,Parameters!$A$5:$A$14,0)),""),"") -> 1 | AE37: =IF(N37<>"",1,IF(ISNUMBER(Parameters!$B$19),Parameters!$B$19,"")) -> 0 | AF37: =IF((Parameters!$I$5*ISNUMBER(V37)+Parameters!$I$6*ISNUMBER(W37)+Parameters!$I$7*ISNUMBER(X37)+Parameters!$I$8*ISNUMBER(Y37))=0,"",(Parameters!$I$5*N(V37)+Parameters!$I$6*N(W37)+Parameters!$I$7*N(X37)+Parameters!$I$8*N(Y37))/(Parameters!$I$5*ISNUMBER(V37)+Parameters!$I$6*ISNUMBER(W37)+Parameters!$I$7*ISNUMBER(X37)+Parameters!$I$8*ISNUMBER(Y37))) -> 0.799 | AG37: =IF((Parameters!$I$9*ISNUMBER(Z37))=0,"",(Parameters!$I$9*N(Z37))/(Parameters!$I$9*ISNUMBER(Z37))) -> 1 | AH37: =IF((Parameters!$I$11*ISNUMBER(AA37)+Parameters!$I$12*ISNUMBER(AB37)+Parameters!$I$13*ISNUMBER(AC37)+Parameters!$I$14*ISNUMBER(AD37)+Parameters!$I$15*ISNUMBER(AE37))=0,"",(Parameters!$I$11*N(AA37)+Parameters!$I$12*N(AB37)+Parameters!$I$13*N(AC37)+Parameters!$I$14*N(AD37)+Parameters!$I$15*N(AE37))/(Parameters!$I$11*ISNUMBER(AA37)+Parameters!$I$12*ISNUMBER(AB37)+Parameters!$I$13*ISNUMBER(AC37)+Parameters!$I$14*ISNUMBER(AD37)+Parameters!$I$15*ISNUMBER(AE37))) -> 0.734 | AI37: =Parameters!$I$5*ISNUMBER(V37)+Parameters!$I$6*ISNUMBER(W37)+Parameters!$I$7*ISNUMBER(X37)+Parameters!$I$8*ISNUMBER(Y37)+Parameters!$I$9*ISNUMBER(Z37)+Parameters!$I$11*ISNUMBER(AA37)+Parameters!$I$12*ISNUMBER(AB37)+Parameters!$I$13*ISNUMBER(AC37)+Parameters!$I$14*ISNUMBER(AD37)+Parameters!$I$15*ISNUMBER(AE37) -> 95 | AJ37: =IF((Parameters!$I$5+Parameters!$I$6+Parameters!$I$7+Parameters!$I$8+Parameters!$I$9+Parameters!$I$11+Parameters!$I$12+Parameters!$I$13+Parameters!$I$14+Parameters!$I$15)=0,"",AI37/(Parameters!$I$5+Parameters!$I$6+Parameters!$I$7+Parameters!$I$8+Parameters!$I$9+Parameters!$I$11+Parameters!$I$12+Parameters!$I$13+Parameters!$I$14+Parameters!$I$15)) -> 1 | AK37: =IF(AND(ISNUMBER(AF37),ISNUMBER(AH37),OR(NOT((Parameters!$I$9)>0),ISNUMBER(AG37)),AJ37>=Parameters!$B$20),100*(Parameters!$F$18*N(AF37)+Parameters!$F$19*N(AG37)+Parameters!$F$20*N(AH37))/(Parameters!$F$18*ISNUMBER(AF37)+Parameters!$F$19*ISNUMBER(AG37)+Parameters!$F$20*ISNUMBER(AH37)),"") -> 82.65 | AL37: =IF(ISNUMBER(AK37),RANK(AK37,$AK$2:$AK$113),"") -> 36 | AM37: =IF(((D37="Implemented/available")+(E37="Implemented/available")+(J37="Implemented/available")+(K37="Implemented/available")+(L37="Implemented/available")+(M37="Implemented/available"))=0,"",(AND(D37="Implemented/available",O37<>"")+AND(E37="Implemented/available",P37<>"")+AND(J37="Implemented/available",Q37<>"")+AND(K37="Implemented/available",R37<>"")+AND(L37="Implemented/available",S37<>"")+AND(M37="Implemented/available",T37<>""))/((D37="Implemented/available")+(E37="Implemented/available")+(J37="Implemented/available")+(K37="Implemented/available")+(L37="Implemented/available")+(M37="Implemented/available"))) -> 1
A38: Peer Community In | B38: PCI, Peer Community In | C38: Peer review system | D38: Implemented/available | E38: Implemented/available | F38: Unknown | G38: Advisory board or steering committee | I38: Formal | J38: Not planning | K38: Implemented/available | L38: Implemented/available | M38: Not applicable | O38: https://peercommunityin.org/pci-structure-history/ | R38: https://peercommunityin.org/pci-finances/ | S38: https://peercommunityin.org/ | V38: =IFERROR(IF(ISNUMBER(INDEX(Parameters!$B$5:$B$14,MATCH(D38,Parameters!$A$5:$A$14,0))),INDEX(Parameters!$B$5:$B$14,MATCH(D38,Parameters!$A$5:$A$14,0)),""),"") -> 1 | W38: =IFERROR(IF(ISNUMBER(INDEX(Parameters!$B$5:$B$14,MATCH(E38,Parameters!$A$5:$A$14,0))),INDEX(Parameters!$B$5:$B$14,MATCH(E38,Parameters!$A$5:$A$14,0)),""),"") -> 1 | X38: =IFERROR(IF(ISNUMBER(INDEX(Parameters!$B$5:$B$14,MATCH(F38,Parameters!$A$5:$A$14,0))),INDEX(Parameters!$B$5:$B$14,MATCH(F38,Parameters!$A$5:$A$14,0)),""),"") | Y38: =IF(G38<>"",1,IF(ISNUMBER(Parameters!$B$18),Parameters!$B$18,"")) -> 1 | Z38: =IF(I38<>"",IFERROR(IF(ISNUMBER(INDEX(Parameters!$B$5:$B$14,MATCH(I38,Parameters!$A$5:$A$14,0))),INDEX(Parameters!$B$5:$B$14,MATCH(I38,Parameters!$A$5:$A$14,0)),""),""),IF(ISNUMBER(Parameters!$B$21),Parameters!$B$21,"")) -> 1 | AA38: =IFERROR(IF(ISNUMBER(INDEX(Parameters!$B$5:$B$14,MATCH(J38,Parameters!$A$5:$A$14,0))),INDEX(Parameters!$B$5:$B$14,MATCH(J38,Parameters!$A$5:$A$14,0)),""),"") -> 0 | AB38: =IFERROR(IF(ISNUMBER(INDEX(Parameters!$B$5:$B$14,MATCH(K38,Parameters!$A$5:$A$14,0))),INDEX(Parameters!$B$5:$B$14,MATCH(K38,Parameters!$A$5:$A$14,0)),""),"") -> 1 | AC38: =IFERROR(IF(ISNUMBER(INDEX(Parameters!$B$5:$B$14,MATCH(L38,Parameters!$A$5:$A$14,0))),INDEX(Parameters!$B$5:$B$14,MATCH(L38,Parameters!$A$5:$A$14,0)),""),"") -> 1 | AD38: =IFERROR(IF(ISNUMBER(INDEX(Parameters!$B$5:$B$14,MATCH(M38,Parameters!$A$5:$A$14,0))),INDEX(Parameters!$B$5:$B$14,MATCH(M38,Parameters!$A$5:$A$14,0)),""),"") | AE38: =IF(N38<>"",1,IF(ISNUMBER(Parameters!$B$19),Parameters!$B$19,"")) -> 0 | AF38: =IF((Parameters!$I$5*ISNUMBER(V38)+Parameters!$I$6*ISNUMBER(W38)+Parameters!$I$7*ISNUMBER(X38)+Parameters!$I$8*ISNUMBER(Y38))=0,"",(Parameters!$I$5*N(V38)+Parameters!$I$6*N(W38)+Parameters!$I$7*N(X38)+Parameters!$I$8*N(Y38))/(Parameters!$I$5*ISNUMBER(V38)+Parameters!$I$6*ISNUMBER(W38)+Parameters!$I$7*ISNUMBER(X38)+Parameters!$I$8*ISNUMBER(Y38))) -> 1 | AG38: =IF((Parameters!$I$9*ISNUMBER(Z38))=0,"",(Parameters!$I$9*N(Z38))/(Parameters!$I$9*ISNUMBER(Z38))) -> 1 | AH38: =IF((Parameters!$I$11*ISNUMBER(AA38)+Parameters!$I$12*ISNUMBER(AB38)+Parameters!$I$13*ISNUMBER(AC38)+Parameters!$I$14*ISNUMBER(AD38)+Parameters!$I$15*ISNUMBER(AE38))=0,"",(Parameters!$I$11*N(AA38)+Parameters!$I$12*N(AB38)+Parameters!$I$13*N(AC38)+Parameters!$I$14*N(AD38)+Parameters!$I$15*N(AE38))/(Parameters!$I$11*ISNUMBER(AA38)+Parameters!$I$12*ISNUMBER(AB38)+Parameters!$I$13*ISNUMBER(AC38)+Parameters!$I$14*ISNUMBER(AD38)+Parameters!$I$15*ISNUMBER(AE38))) -> 0.5 | AI38: =Parameters!$I$5*ISNUMBER(V38)+Parameters!$I$6*ISNUMBER(W38)+Parameters!$I$7*ISNUMBER(X38)+Parameters!$I$8*ISNUMBER(Y38)+Parameters!$I$9*ISNUMBER(Z38)+Parameters!$I$11*ISNUMBER(AA38)+Parameters!$I$12*ISNUMBER(AB38)+Parameters!$I$13*ISNUMBER(AC38)+Parameters!$I$14*ISNUMBER(AD38)+Parameters!$I$15*ISNUMBER(AE38) -> 80 | AJ38: =IF((Parameters!$I$5+Parameters!$I$6+Parameters!$I$7+Parameters!$I$8+Parameters!$I$9+Parameters!$I$11+Parameters!$I$12+Parameters!$I$13+Parameters!$I$14+Parameters!$I$15)=0,"",AI38/(Parameters!$I$5+Parameters!$I$6+Parameters!$I$7+Parameters!$I$8+Parameters!$I$9+Parameters!$I$11+Parameters!$I$12+Parameters!$I$13+Parameters!$I$14+Parameters!$I$15)) -> 0.84210526 | AK38: =IF(AND(ISNUMBER(AF38),ISNUMBER(AH38),OR(NOT((Parameters!$I$9)>0),ISNUMBER(AG38)),AJ38>=Parameters!$B$20),100*(Parameters!$F$18*N(AF38)+Parameters!$F$19*N(AG38)+Parameters!$F$20*N(AH38))/(Parameters!$F$18*ISNUMBER(AF38)+Parameters!$F$19*ISNUMBER(AG38)+Parameters!$F$20*ISNUMBER(AH38)),"") -> 82.5 | AL38: =IF(ISNUMBER(AK38),RANK(AK38,$AK$2:$AK$113),"") -> 37 | AM38: =IF(((D38="Implemented/available")+(E38="Implemented/available")+(J38="Implemented/available")+(K38="Implemented/available")+(L38="Implemented/available")+(M38="Implemented/available"))=0,"",(AND(D38="Implemented/available",O38<>"")+AND(E38="Implemented/available",P38<>"")+AND(J38="Implemented/available",Q38<>"")+AND(K38="Implemented/available",R38<>"")+AND(L38="Implemented/available",S38<>"")+AND(M38="Implemented/available",T38<>""))/((D38="Implemented/available")+(E38="Implemented/available")+(J38="Implemented/available")+(K38="Implemented/available")+(L38="Implemented/available")+(M38="Implemented/available"))) -> 0.75
A39: Vireo ETD | B39: Texas Digital Library | C39: Publishing system | Repository software | Submissions system | D39: Implemented/available | E39: Implemented/available | F39: Implemented/available | G39: Advisory board or steering committee | I39: Formal | J39: Implemented/available | K39: Implemented/available | L39: Not planning | M39: Unknown | O39: https://www.tdl.org/about-tdl/governance/ | P39: https://texasdigitallibrary.atlassian.net/wiki/x/9YBuOw | Q39: https://texasdigitallibrary.atlassian.net/wiki/spaces/VUG/pages/2701131781/Accessibility | R39: https://www.tdl.org/community/members/membership/fees/ | U39: https://texasdigitallibrary.atlassian.net/wiki/x/9YBuOw | V39: =IFERROR(IF(ISNUMBER(INDEX(Parameters!$B$5:$B$14,MATCH(D39,Parameters!$A$5:$A$14,0))),INDEX(Parameters!$B$5:$B$14,MATCH(D39,Parameters!$A$5:$A$14,0)),""),"") -> 1 | W39: =IFERROR(IF(ISNUMBER(INDEX(Parameters!$B$5:$B$14,MATCH(E39,Parameters!$A$5:$A$14,0))),INDEX(Parameters!$B$5:$B$14,MATCH(E39,Parameters!$A$5:$A$14,0)),""),"") -> 1 | X39: =IFERROR(IF(ISNUMBER(INDEX(Parameters!$B$5:$B$14,MATCH(F39,Parameters!$A$5:$A$14,0))),INDEX(Parameters!$B$5:$B$14,MATCH(F39,Parameters!$A$5:$A$14,0)),""),"") -> 1 | Y39: =IF(G39<>"",1,IF(ISNUMBER(Parameters!$B$18),Parameters!$B$18,"")) -> 1 | Z39: =IF(I39<>"",IFERROR(IF(ISNUMBER(INDEX(Parameters!$B$5:$B$14,MATCH(I39,Parameters!$A$5:$A$14,0))),INDEX(Parameters!$B$5:$B$14,MATCH(I39,Parameters!$A$5:$A$14,0)),""),""),IF(ISNUMBER(Parameters!$B$21),Parameters!$B$21,"")) -> 1 | AA39: =IFERROR(IF(ISNUMBER(INDEX(Parameters!$B$5:$B$14,MATCH(J39,Parameters!$A$5:$A$14,0))),INDEX(Parameters!$B$5:$B$14,MATCH(J39,Parameters!$A$5:$A$14,0)),""),"") -> 1 | AB39: =IFERROR(IF(ISNUMBER(INDEX(Parameters!$B$5:$B$14,MATCH(K39,Parameters!$A$5:$A$14,0))),INDEX(Parameters!$B$5:$B$14,MATCH(K39,Parameters!$A$5:$A$14,0)),""),"") -> 1 | AC39: =IFERROR(IF(ISNUMBER(INDEX(Parameters!$B$5:$B$14,MATCH(L39,Parameters!$A$5:$A$14,0))),INDEX(Parameters!$B$5:$B$14,MATCH(L39,Parameters!$A$5:$A$14,0)),""),"") -> 0 | AD39: =IFERROR(IF(ISNUMBER(INDEX(Parameters!$B$5:$B$14,MATCH(M39,Parameters!$A$5:$A$14,0))),INDEX(Parameters!$B$5:$B$14,MATCH(M39,Parameters!$A$5:$A$14,0)),""),"") | AE39: =IF(N39<>"",1,IF(ISNUMBER(Parameters!$B$19),Parameters!$B$19,"")) -> 0 | AF39: =IF((Parameters!$I$5*ISNUMBER(V39)+Parameters!$I$6*ISNUMBER(W39)+Parameters!$I$7*ISNUMBER(X39)+Parameters!$I$8*ISNUMBER(Y39))=0,"",(Parameters!$I$5*N(V39)+Parameters!$I$6*N(W39)+Parameters!$I$7*N(X39)+Parameters!$I$8*N(Y39))/(Parameters!$I$5*ISNUMBER(V39)+Parameters!$I$6*ISNUMBER(W39)+Parameters!$I$7*ISNUMBER(X39)+Parameters!$I$8*ISNUMBER(Y39))) -> 1 | AG39: =IF((Parameters!$I$9*ISNUMBER(Z39))=0,"",(Parameters!$I$9*N(Z39))/(Parameters!$I$9*ISNUMBER(Z39))) -> 1 | AH39: =IF((Parameters!$I$11*ISNUMBER(AA39)+Parameters!$I$12*ISNUMBER(AB39)+Parameters!$I$13*ISNUMBER(AC39)+Parameters!$I$14*ISNUMBER(AD39)+Parameters!$I$15*ISNUMBER(AE39))=0,"",(Parameters!$I$11*N(AA39)+Parameters!$I$12*N(AB39)+Parameters!$I$13*N(AC39)+Parameters!$I$14*N(AD39)+Parameters!$I$15*N(AE39))/(Parameters!$I$11*ISNUMBER(AA39)+Parameters!$I$12*ISNUMBER(AB39)+Parameters!$I$13*ISNUMBER(AC39)+Parameters!$I$14*ISNUMBER(AD39)+Parameters!$I$15*ISNUMBER(AE39))) -> 0.5 | AI39: =Parameters!$I$5*ISNUMBER(V39)+Parameters!$I$6*ISNUMBER(W39)+Parameters!$I$7*ISNUMBER(X39)+Parameters!$I$8*ISNUMBER(Y39)+Parameters!$I$9*ISNUMBER(Z39)+Parameters!$I$11*ISNUMBER(AA39)+Parameters!$I$12*ISNUMBER(AB39)+Parameters!$I$13*ISNUMBER(AC39)+Parameters!$I$14*ISNUMBER(AD39)+Parameters!$I$15*ISNUMBER(AE39) -> 88 | AJ39: =IF((Parameters!$I$5+Parameters!$I$6+Parameters!$I$7+Parameters!$I$8+Parameters!$I$9+Parameters!$I$11+Parameters!$I$12+Parameters!$I$13+Parameters!$I$14+Parameters!$I$15)=0,"",AI39/(Parameters!$I$5+Parameters!$I$6+Parameters!$I$7+Parameters!$I$8+Parameters!$I$9+Parameters!$I$11+Parameters!$I$12+Parameters!$I$13+Parameters!$I$14+Parameters!$I$15)) -> 0.92631579 | AK39: =IF(AND(ISNUMBER(AF39),ISNUMBER(AH39),OR(NOT((Parameters!$I$9)>0),ISNUMBER(AG39)),AJ39>=Parameters!$B$20),100*(Parameters!$F$18*N(AF39)+Parameters!$F$19*N(AG39)+Parameters!$F$20*N(AH39))/(Parameters!$F$18*ISNUMBER(AF39)+Parameters!$F$19*ISNUMBER(AG39)+Parameters!$F$20*ISNUMBER(AH39)),"") -> 82.5 | AL39: =IF(ISNUMBER(AK39),RANK(AK39,$AK$2:$AK$113),"") -> 37 | AM39: =IF(((D39="Implemented/available")+(E39="Implemented/available")+(J39="Implemented/available")+(K39="Implemented/available")+(L39="Implemented/available")+(M39="Implemented/available"))=0,"",(AND(D39="Implemented/available",O39<>"")+AND(E39="Implemented/available",P39<>"")+AND(J39="Implemented/available",Q39<>"")+AND(K39="Implemented/available",R39<>"")+AND(L39="Implemented/available",S39<>"")+AND(M39="Implemented/available",T39<>""))/((D39="Implemented/available")+(E39="Implemented/available")+(J39="Implemented/available")+(K39="Implemented/available")+(L39="Implemented/available")+(M39="Implemented/available"))) -> 1
A40: Arches Heritage Data Management Platform | B40: Getty Conservation Institute (GCI) | C40: Data management planning tool or service | D40: Implemented/available | E40: In progress | F40: Implemented/available | G40: Advisory board or steering committee | I40: Formal | J40: Implemented/available | K40: No direct costs | L40: Not planning | M40: Not planning | N40: FAIR Guiding Principles for Scientific Data Management and Stewardship | O40: https://www.archesproject.org/archesgovernance/ | Q40: https://www.archesproject.org/accessibility/ | U40: https://www.archesproject.org/archesgovernance/ | V40: =IFERROR(IF(ISNUMBER(INDEX(Parameters!$B$5:$B$14,MATCH(D40,Parameters!$A$5:$A$14,0))),INDEX(Parameters!$B$5:$B$14,MATCH(D40,Parameters!$A$5:$A$14,0)),""),"") -> 1 | W40: =IFERROR(IF(ISNUMBER(INDEX(Parameters!$B$5:$B$14,MATCH(E40,Parameters!$A$5:$A$14,0))),INDEX(Parameters!$B$5:$B$14,MATCH(E40,Parameters!$A$5:$A$14,0)),""),"") -> 0.67 | X40: =IFERROR(IF(ISNUMBER(INDEX(Parameters!$B$5:$B$14,MATCH(F40,Parameters!$A$5:$A$14,0))),INDEX(Parameters!$B$5:$B$14,MATCH(F40,Parameters!$A$5:$A$14,0)),""),"") -> 1 | Y40: =IF(G40<>"",1,IF(ISNUMBER(Parameters!$B$18),Parameters!$B$18,"")) -> 1 | Z40: =IF(I40<>"",IFERROR(IF(ISNUMBER(INDEX(Parameters!$B$5:$B$14,MATCH(I40,Parameters!$A$5:$A$14,0))),INDEX(Parameters!$B$5:$B$14,MATCH(I40,Parameters!$A$5:$A$14,0)),""),""),IF(ISNUMBER(Parameters!$B$21),Parameters!$B$21,"")) -> 1 | AA40: =IFERROR(IF(ISNUMBER(INDEX(Parameters!$B$5:$B$14,MATCH(J40,Parameters!$A$5:$A$14,0))),INDEX(Parameters!$B$5:$B$14,MATCH(J40,Parameters!$A$5:$A$14,0)),""),"") -> 1 | AB40: =IFERROR(IF(ISNUMBER(INDEX(Parameters!$B$5:$B$14,MATCH(K40,Parameters!$A$5:$A$14,0))),INDEX(Parameters!$B$5:$B$14,MATCH(K40,Parameters!$A$5:$A$14,0)),""),"") -> 1 | AC40: =IFERROR(IF(ISNUMBER(INDEX(Parameters!$B$5:$B$14,MATCH(L40,Parameters!$A$5:$A$14,0))),INDEX(Parameters!$B$5:$B$14,MATCH(L40,Parameters!$A$5:$A$14,0)),""),"") -> 0 | AD40: =IFERROR(IF(ISNUMBER(INDEX(Parameters!$B$5:$B$14,MATCH(M40,Parameters!$A$5:$A$14,0))),INDEX(Parameters!$B$5:$B$14,MATCH(M40,Parameters!$A$5:$A$14,0)),""),"") -> 0 | AE40: =IF(N40<>"",1,IF(ISNUMBER(Parameters!$B$19),Parameters!$B$19,"")) -> 1 | AF40: =IF((Parameters!$I$5*ISNUMBER(V40)+Parameters!$I$6*ISNUMBER(W40)+Parameters!$I$7*ISNUMBER(X40)+Parameters!$I$8*ISNUMBER(Y40))=0,"",(Parameters!$I$5*N(V40)+Parameters!$I$6*N(W40)+Parameters!$I$7*N(X40)+Parameters!$I$8*N(Y40))/(Parameters!$I$5*ISNUMBER(V40)+Parameters!$I$6*ISNUMBER(W40)+Parameters!$I$7*ISNUMBER(X40)+Parameters!$I$8*ISNUMBER(Y40))) -> 0.901 | AG40: =IF((Parameters!$I$9*ISNUMBER(Z40))=0,"",(Parameters!$I$9*N(Z40))/(Parameters!$I$9*ISNUMBER(Z40))) -> 1 | AH40: =IF((Parameters!$I$11*ISNUMBER(AA40)+Parameters!$I$12*ISNUMBER(AB40)+Parameters!$I$13*ISNUMBER(AC40)+Parameters!$I$14*ISNUMBER(AD40)+Parameters!$I$15*ISNUMBER(AE40))=0,"",(Parameters!$I$11*N(AA40)+Parameters!$I$12*N(AB40)+Parameters!$I$13*N(AC40)+Parameters!$I$14*N(AD40)+Parameters!$I$15*N(AE40))/(Parameters!$I$11*ISNUMBER(AA40)+Parameters!$I$12*ISNUMBER(AB40)+Parameters!$I$13*ISNUMBER(AC40)+Parameters!$I$14*ISNUMBER(AD40)+Parameters!$I$15*ISNUMBER(AE40))) -> 0.6 | AI40: =Parameters!$I$5*ISNUMBER(V40)+Parameters!$I$6*ISNUMBER(W40)+Parameters!$I$7*ISNUMBER(X40)+Parameters!$I$8*ISNUMBER(Y40)+Parameters!$I$9*ISNUMBER(Z40)+Parameters!$I$11*ISNUMBER(AA40)+Parameters!$I$12*ISNUMBER(AB40)+Parameters!$I$13*ISNUMBER(AC40)+Parameters!$I$14*ISNUMBER(AD40)+Parameters!$I$15*ISNUMBER(AE40) -> 95 | AJ40: =IF((Parameters!$I$5+Parameters!$I$6+Parameters!$I$7+Parameters!$I$8+Parameters!$I$9+Parameters!$I$11+Parameters!$I$12+Parameters!$I$13+Parameters!$I$14+Parameters!$I$15)=0,"",AI40/(Parameters!$I$5+Parameters!$I$6+Parameters!$I$7+Parameters!$I$8+Parameters!$I$9+Parameters!$I$11+Parameters!$I$12+Parameters!$I$13+Parameters!$I$14+Parameters!$I$15)) -> 1 | AK40: =IF(AND(ISNUMBER(AF40),ISNUMBER(AH40),OR(NOT((Parameters!$I$9)>0),ISNUMBER(AG40)),AJ40>=Parameters!$B$20),100*(Parameters!$F$18*N(AF40)+Parameters!$F$19*N(AG40)+Parameters!$F$20*N(AH40))/(Parameters!$F$18*ISNUMBER(AF40)+Parameters!$F$19*ISNUMBER(AG40)+Parameters!$F$20*ISNUMBER(AH40)),"") -> 82.04 | AL40: =IF(ISNUMBER(AK40),RANK(AK40,$AK$2:$AK$113),"") -> 39 | AM40: =IF(((D40="Implemented/available")+(E40="Implemented/available")+(J40="Implemented/available")+(K40="Implemented/available")+(L40="Implemented/available")+(M40="Implemented/available"))=0,"",(AND(D40="Implemented/available",O40<>"")+AND(E40="Implemented/available",P40<>"")+AND(J40="Implemented/available",Q40<>"")+AND(K40="Implemented/available",R40<>"")+AND(L40="Implemented/available",S40<>"")+AND(M40="Implemented/available",T40<>""))/((D40="Implemented/available")+(E40="Implemented/available")+(J40="Implemented/available")+(K40="Implemented/available")+(L40="Implemented/available")+(M40="Implemented/available"))) -> 1
