Workbook

Sheet Codebook
A1: OISI Component 1 — Community Engagement: codebook and method
A2: Dataset: Infra Finder data, Invest in Open Infrastructure, v3.0 (Zenodo record 18225266, 13 Jan 2026). 112 infrastructures. Variable values are self-reported and only as current as the snapshot.
A4: 1. Score formula
A5: Community Engagement Score (0–100) = 100 × Σ(wᵢ × sᵢ) / Σ(wᵢ), summed only over metrics i that have a valid score sᵢ (0–1).
A6: Weights wᵢ are on the Parameters sheet (E1=8%, E2=22%, C1=18%, C2=12%, C3=5%, G1=15%, G2=20%). They sum to 100%, so the 30/35/35 sub-component weights are implied, not applied separately.
A7: Missing data rule: Unknown, blank and Not applicable are NA — excluded from both numerator and denominator, never counted as 0.
A8: Completeness rule: a repo is scored only if scored metrics carry ≥ 60% of the weight AND at least one metric is scored in each of the 3 sub-components. Otherwise the score is NA.
A9: Uncertainty rule: every score carries a range. Lower bound = score if all missing metrics were 0; upper bound = score if all missing metrics were 1. Result status: Reportable (≥85% of weight scored) can be ranked and cited; Provisional (60–85%) is cited only with its range.
A10: Overall OISI contribution: this component × 25% (OISI = 100 × [0.25 CE + 0.25 Governance + 0.25 Org. Capacity + 0.25 Dev. Activity]).
A12: 2. Metric definitions
A13: Code | B13: Metric | C13: Sub-component | D13: Weight | E13: Source field type | F13: Scoring rule (automatic) | G13: NA / missing rule | H13: Verification guidance (override on Verification sheet)
A14: E1 | B14: Engagement status (037) | C14: Engagement & Participation | D14: =Parameters!$E$6 -> 0.08 | E14: Status list | F14: Ladder: Implemented 1.00; In progress 0.67; Considering 0.33; Not planning 0. | G14: Unknown / blank → NA | H14: Open 116_community_engagement_url; confirm a real programme exists. About 85% of scored repos are "Implemented", so weight is only 8%.
A15: E2 | B15: Engagement breadth (038 + coded 938) | C15: Engagement & Participation | D15: =Parameters!$E$7 -> 0.22 | E15: Multi-select checklist + coded free text | F15: Score = min(n, 8) / 8, n = distinct categories in the UNION of the 038 checklist and categories coded from 938 text (Dictionary sheet). "Other" counts as 1 only with 938 text. Gate: if E1 ≤ Considering, E2 = 0 and flagged. | G15: No category from either source → NA (never 0) | H15: Coded text is strict (precision over recall) so it can understate breadth. Check the Audit sheet; override on Verification (E2 override) after reading the text. Sensitivity row "E2 checklist only" shows the effect of dropping 938.
A16: C1 | B16: Contribution routes (040 + 940) | C16: Contribution Mechanisms | D16: =Parameters!$E$8 -> 0.18 | E16: Multi-select (8 categories) + free text | F16: Score = min(n, 6) / 6. "Contribute funds" counts (OISI draft). "Other" counts as 1 only with 940 text. | G16: Blank / "Not applicable" → NA | H16: Check the listed routes against the website and repo.
A17: C2 | B17: Contribution guidance (041) | C17: Contribution Mechanisms | D17: =Parameters!$E$9 -> 0.12 | E17: URL (not a status) | F17: Tiers from the URL: dedicated guide 1.00; other get-involved page 0.50. Suspect URL → NA until verified. | G17: Blank → NA | H17: Open each URL. 1.00 = usable how-to; 0.50 = general invitation; 0 = verified absent. Check the repo for CONTRIBUTING.md.
A18: C3 | B18: Open contribution infrastructure (019) | C18: Contribution Mechanisms | D18: =Parameters!$E$10 -> 0.05 | E18: URL host | F18: Public forge (GitHub, GitLab.com, Bitbucket, Codeberg, SourceHut) 1.00; other host 0.50. Replaces 039. | G18: Blank → NA | H18: Low weight (5%): 103 of 108 repos score 1.00, so it separates little until live checks are added (CONTRIBUTING file, issue tracker, recent commits, external contributors).
A19: G1 | B19: Code of Conduct (042) | C19: Community Norms & Governance | D19: =Parameters!$E$11 -> 0.15 | E19: Status list | F19: Same ladder as E1. | G19: Unknown → NA | H19: Open 043 URL. An inherited parent-organisation Code counts only if it explicitly covers this community.
A20: G2 | B20: Community governance (048) | C20: Community Norms & Governance | D20: =Parameters!$E$12 -> 0.2 | E20: Status list | F20: Formal 1.00; Ad hoc 0.50; None 0. | G20: Blank → NA | H20: Open 049 URL: bylaws, charter or governance page = Formal. Enter 0 only when absence is verified.
A21: 039 (contribution pathways) is NOT scored: 68 of 112 values are Unknown. It is kept only as a consistency flag (Calc column R). 078, 107 are descriptive only. Supporting URLs (116, 043, 049) are evidence, not scored.
A23: 3. Decision log
A24: # | B24: Decision | C24: Rationale
A25: D1 | B25: Blank / Unknown / Not applicable = NA, never 0. | C25: Follows the OISI missing-data rule. The Zenodo dataset does not say whether a blank means "none" or "not answered", so assuming 0 would invent evidence and penalise skipped questions.
A26: D2 | B26: A blank becomes 0 only through verification. | C26: Record the evidence on the Verification sheet; verified overrides replace auto scores.
A27: D3 | B27: Flat weighted mean over available metrics, with a completeness threshold. | C27: Avoids inflating repos that were scored on one or two metrics. Threshold 60% of weight + all three sub-components; 50% and 70% shown in Sensitivity.
A28: D4 | B28: Inherited Code of Conduct counts only if explicitly applicable and verified. | C28: Keeps the rule consistent without crediting a generic organisational page.
A29: D5 | B29: "Contribute funds" counts in 040. | C29: The OISI draft lists funding as a contribution opportunity. Sensitivity sheet shows the effect of excluding it.
A30: D6 | B30: 041 is scored in tiers (1 / 0.5 / NA-or-0) from the URL. | C30: The field is a URL, not a status; only ~25 of 81 URLs are dedicated contribution documents and 6 are not guidance at all. Tiers are provisional until each URL is opened.
A31: D7 | B31: "Other" counts as one category only with a free-text description. | C31: Prevents unverifiable credit.
A32: D8 | B32: 039 is removed from the score; replaced by C3 (019). | C32: 68 of 112 are Unknown. Inferring a pathway from 040/041 would double-count the same evidence, so C3 uses a different, almost complete field (019). 039 stays only as a consistency flag.
A33: D9 | B33: Engagement gate (037 ≤ Considering → 038 = 0). | C33: Two repos list activities while reporting no implemented engagement; flagged for verification.
A34: D10 | B34: Every score is published with a lower and upper bound. | C34: Renormalising over available metrics lets a repo with 60% of the weight scored reach 100. The range (missing = 0 vs missing = 1) shows how much of the score rests on assumption; a repo is confidently high only if its lower bound is also high.
A35: D11 | B35: Only Reportable repos (≥85% of weight scored) are ranked in the top/bottom lists and headline claims. | C35: Provisional scores stay visible but are labelled; they should not be named best or worst.
... A38: D14 | B38: D14: 938 free text is coded onto the 12 categories and unioned with 038. | C38: 038 and 938 are complementary (only 11 repos have both, none identical). Coder is a published keyword dictionary, strict by design, audited on 20 repos (Audit sheet) with a checklist-only sensitivity scenario.
A39: 4. Verification workflow
A40: 1) Go to the Verification sheet. Filter "Open flags" > 0 first (flags are explained in the Action column).
A41: 2) Open the evidence URL, decide the verified value, and type it in the yellow override cell for that metric (a number 0–1, or NA). Leave blank to keep the automatic score.
A42: 3) Fill Verified by, Date, Evidence/notes, and set Verification status. Scoring, Summary and Sensitivity update automatically.
A43: Example row (illustrative format only): Service = Hyrax | 039 override = 1.00 | Verified by = initials | Date = 2026-02-01 | Notes = "Getting Started page lists code, docs and group routes" | Status = Verified.
A44: 4) Re-check Sensitivity and the score ranges after verification: as NA cells are resolved, ranges narrow and Provisional repos become Reportable.
A46: 5. Sheet guide and colour legend
A47: Summary | B47: Headline results, coverage, distribution, sensitivity, flags, top/bottom 10, charts.
A48: Scoring | B48: Final metric scores (override else auto), sub-scores, completeness, eligibility, component score, lower/upper bounds, result status (Reportable / Provisional / Not scored), rank.
A49: Verification | B49: Where you enter verified values and evidence. Only sheet (besides Parameters) with inputs.
A50: Calc | B50: Automatic parsing and scoring from Data; flags.
A51: Sensitivity | B51: Alternative thresholds, weights and rules vs base, including shrinkage toward median and the require-038/040 rule.
A52: Descriptive | B52: Membership variables, reported not scored.
A53: Parameters | B53: Weights, ladders, caps, tiers, thresholds.
A54: Data | B54: Source data (20 columns of the 112-row sheet; empty verification_status/notes columns moved to Verification).
A55: Blue text, yellow fill | B55: Editable input.
A56: Black text | B56: Formula — do not overwrite.
A58: 6. Limitations
A59: Self-reported data; scores measure what the infrastructures reported (and what has been verified), not independently observed community health.
A60: Breadth caps (8 and 6), the 0.5 tier for 041, and the keyword dictionary are judgement calls; test them on Parameters and Dictionary. Coder precision is measured only on 11 repos with both fields, so the Audit sheet is needed before publication.
A61: 038 and 037 are related (both describe engagement) and 040 overlaps with 048 ("Contribute to governance"); the weights were not changed for this, but it is worth stating in the paper.
A63: 7. Changes in v2 (new metric set)
A64: New sheets: Dictionary (keywords per category), Coding (per-repo checklist and text flags, union count), Audit (20-repo sample for human review).
A65: Metric slots: Scoring columns D–J are now E1, E2, C1, C2, C3, G1, G2. Verification override columns follow the same order.
A66: Parameters: weights E1 8%, E2 22%, C1 18%, C2 12%, C3 5%, G1 15%, G2 20%; section G holds the C3 host rules.
A67: Sensitivity: the old "039 inferred" scenario is replaced by "E2 checklist only (938 not used)".

Sheet Summary
A1: OISI Component 1 — Community Engagement: results summary
A2: All figures are live formulas. Scores use the strict missing-data rule (Unknown / blank / Not applicable = NA, never 0). Metric set v2: E1, E2 (038 + coded 938), C1, C2, C3 (019), G1, G2. Component = 25% of overall OISI.
A4: 1. Headline
A5: Repositories in dataset | B5: =COUNTA(Scoring!$A$2:$A$113) -> 112
A6: Primary completeness threshold | B6: =Parameters!$C$56 -> 0.6
A7: Repositories with a score | B7: =COUNT(Scoring!$S$2:$S$113) -> 87
A8: Share scored | B8: =B7/B5 -> 0.77678571
A9: Median score | B9: =IFERROR(MEDIAN(Scoring!$S$2:$S$113),"n/a") -> 78.225806
A10: Mean score | B10: =IFERROR(AVERAGE(Scoring!$S$2:$S$113),"n/a") -> 75.90664
A11: 25th percentile | B11: =IFERROR(QUARTILE(Scoring!$S$2:$S$113,1),"n/a") -> 62.683333
A12: 75th percentile | B12: =IFERROR(QUARTILE(Scoring!$S$2:$S$113,3),"n/a") -> 88.75
A13: Minimum | B13: =IFERROR(MIN(Scoring!$S$2:$S$113),"n/a") -> 37.705882
A14: Maximum | B14: =IFERROR(MAX(Scoring!$S$2:$S$113),"n/a") -> 100
A15: Std. deviation | B15: =IFERROR(STDEV(Scoring!$S$2:$S$113),"n/a") -> 16.223826
A16: Contribution to OISI (points) at median score | B16: =IFERROR(B9*Parameters!$C$21,"n/a") -> 19.556452
A17: Reportable repos (≥ 85% of weight scored) | B17: =COUNTIF(Scoring!$V$2:$V$113,"Reportable") -> 51
A19: 2. Metric coverage and level
A20: Metric | B20: Weight | C20: Scored (n) | D20: NA (n) | E20: NA % | F20: Mean (scored) | G20: Share at 1.00
A21: E1 Engagement status (037) | B21: =Parameters!$E$6 -> 0.08 | C21: =COUNT(Scoring!$D$2:$D$113) -> 111 | D21: =$B$5-C21 -> 1 | E21: =D21/$B$5 -> 0.0089285714 | F21: =IFERROR(AVERAGE(Scoring!$D$2:$D$113),"n/a") -> 0.91297297 | G21: =IFERROR(COUNTIF(Scoring!$D$2:$D$113,1)/C21,"n/a") -> 0.84684685
A22: E2 Engagement breadth (038 + coded 938) | B22: =Parameters!$E$7 -> 0.22 | C22: =COUNT(Scoring!$E$2:$E$113) -> 73 | D22: =$B$5-C22 -> 39 | E22: =D22/$B$5 -> 0.34821429 | F22: =IFERROR(AVERAGE(Scoring!$E$2:$E$113),"n/a") -> 0.65582192 | G22: =IFERROR(COUNTIF(Scoring!$E$2:$E$113,1)/C22,"n/a") -> 0.32876712
A23: C1 Contribution routes (040) | B23: =Parameters!$E$8 -> 0.18 | C23: =COUNT(Scoring!$F$2:$F$113) -> 73 | D23: =$B$5-C23 -> 39 | E23: =D23/$B$5 -> 0.34821429 | F23: =IFERROR(AVERAGE(Scoring!$F$2:$F$113),"n/a") -> 0.64611872 | G23: =IFERROR(COUNTIF(Scoring!$F$2:$F$113,1)/C23,"n/a") -> 0.21917808
A24: C2 Contribution guidance (041) | B24: =Parameters!$E$9 -> 0.12 | C24: =COUNT(Scoring!$G$2:$G$113) -> 75 | D24: =$B$5-C24 -> 37 | E24: =D24/$B$5 -> 0.33035714 | F24: =IFERROR(AVERAGE(Scoring!$G$2:$G$113),"n/a") -> 0.66666667 | G24: =IFERROR(COUNTIF(Scoring!$G$2:$G$113,1)/C24,"n/a") -> 0.33333333
A25: C3 Open contribution infrastructure (019) | B25: =Parameters!$E$10 -> 0.05 | C25: =COUNT(Scoring!$H$2:$H$113) -> 108 | D25: =$B$5-C25 -> 4 | E25: =D25/$B$5 -> 0.035714286 | F25: =IFERROR(AVERAGE(Scoring!$H$2:$H$113),"n/a") -> 0.97685185 | G25: =IFERROR(COUNTIF(Scoring!$H$2:$H$113,1)/C25,"n/a") -> 0.9537037
A26: G1 Code of Conduct (042) | B26: =Parameters!$E$11 -> 0.15 | C26: =COUNT(Scoring!$I$2:$I$113) -> 105 | D26: =$B$5-C26 -> 7 | E26: =D26/$B$5 -> 0.0625 | F26: =IFERROR(AVERAGE(Scoring!$I$2:$I$113),"n/a") -> 0.76152381 | G26: =IFERROR(COUNTIF(Scoring!$I$2:$I$113,1)/C26,"n/a") -> 0.64761905
A27: G2 Community governance (048) | B27: =Parameters!$E$12 -> 0.2 | C27: =COUNT(Scoring!$J$2:$J$113) -> 87 | D27: =$B$5-C27 -> 25 | E27: =D27/$B$5 -> 0.22321429 | F27: =IFERROR(AVERAGE(Scoring!$J$2:$J$113),"n/a") -> 0.79885057 | G27: =IFERROR(COUNTIF(Scoring!$J$2:$J$113,1)/C27,"n/a") -> 0.59770115
A30: 3. Sub-component medians (0–100, scored repos only)
A31: Engagement & Participation (30%) | B31: =IFERROR(MEDIAN(Scoring!$K$2:$K$113),"n/a") -> 81.666667
A32: Contribution Mechanisms (35%) | B32: =IFERROR(MEDIAN(Scoring!$L$2:$L$113),"n/a") -> 74.285714
A33: Community Norms & Governance (35%) | B33: =IFERROR(MEDIAN(Scoring!$M$2:$M$113),"n/a") -> 78.642857
A36: 4. Score distribution
A37: Band | B37: Repos
A38: 0 – <25 | B38: =COUNTIFS(Scoring!$S$2:$S$113,">=0",Scoring!$S$2:$S$113,"<25") -> 0
A39: 25 – <50 | B39: =COUNTIFS(Scoring!$S$2:$S$113,">=25",Scoring!$S$2:$S$113,"<50") -> 6
A40: 50 – <75 | B40: =COUNTIFS(Scoring!$S$2:$S$113,">=50",Scoring!$S$2:$S$113,"<75") -> 33
A41: 75 – 100 | B41: =COUNTIFS(Scoring!$S$2:$S$113,">=75",Scoring!$S$2:$S$113,"<100.0001") -> 48
A42: Not scored (below completeness threshold) | B42: =$B$5-$B$7 -> 25
A45: 5. Completeness bands
A46: High | B46: =COUNTIF(Scoring!$X$2:$X$113,"High") -> 51 | C46: High ≥ 85% of weight scored; Medium ≥ primary threshold; Low below it (not scored).
A47: Medium | B47: =COUNTIF(Scoring!$X$2:$X$113,"Medium") -> 36
A48: Low | B48: =COUNTIF(Scoring!$X$2:$X$113,"Low") -> 25
A49: Result status
A50: Reportable | B50: =COUNTIF(Scoring!$V$2:$V$113,"Reportable") -> 51 | C50: Reportable = ≥85% of weight scored: safe to rank and cite. Provisional = scored but incomplete: cite only with its range.
A51: Provisional | B51: =COUNTIF(Scoring!$V$2:$V$113,"Provisional") -> 36
A52: Not scored | B52: =COUNTIF(Scoring!$V$2:$V$113,"Not scored") -> 25
A53: Mean score range width, provisional repos (upper − lower) | B53: =IFERROR(AVERAGEIFS(Scoring!$U$2:$U$113,Scoring!$V$2:$V$113,"Provisional")-AVERAGEIFS(Scoring!$T$2:$T$113,Scoring!$V$2:$V$113,"Provisional"),"n/a") -> 28.388889
A54: Mean score range width, reportable repos | B54: =IFERROR(AVERAGEIFS(Scoring!$U$2:$U$113,Scoring!$V$2:$V$113,"Reportable")-AVERAGEIFS(Scoring!$T$2:$T$113,Scoring!$V$2:$V$113,"Reportable"),"n/a") -> 1.8823529
A57: 6. Sensitivity of results to rules
A58: Scenario | B58: Repos scored | C58: Median | D58: Mean | E58: Mean |Δ| vs base | F58: Max |Δ| vs base
A59: BASE (primary threshold) | B59: =COUNT(Sensitivity!$B$2:$B$113) -> 87 | C59: =IFERROR(MEDIAN(Sensitivity!$B$2:$B$113),"n/a") -> 78.225806 | D59: =IFERROR(AVERAGE(Sensitivity!$B$2:$B$113),"n/a") -> 75.90664 | E59: – | F59: –
A60: Threshold – lower | B60: =COUNT(Sensitivity!$C$2:$C$113) -> 90 | C60: =IFERROR(MEDIAN(Sensitivity!$C$2:$C$113),"n/a") -> 77.461538 | D60: =IFERROR(AVERAGE(Sensitivity!$C$2:$C$113),"n/a") -> 75.404005 | E60: =IFERROR(AVERAGE(Sensitivity!$J$2:$J$113),"n/a") -> 0 | F60: =IFERROR(MAX(Sensitivity!$J$2:$J$113),"n/a") -> 0
A61: Threshold – higher | B61: =COUNT(Sensitivity!$D$2:$D$113) -> 71 | C61: =IFERROR(MEDIAN(Sensitivity!$D$2:$D$113),"n/a") -> 76.923077 | D61: =IFERROR(AVERAGE(Sensitivity!$D$2:$D$113),"n/a") -> 76.199711 | E61: =IFERROR(AVERAGE(Sensitivity!$K$2:$K$113),"n/a") -> 0 | F61: =IFERROR(MAX(Sensitivity!$K$2:$K$113),"n/a") -> 0
A62: E2 checklist only (938 not used) | B62: =COUNT(Sensitivity!$E$2:$E$113) -> 84 | C62: =IFERROR(MEDIAN(Sensitivity!$E$2:$E$113),"n/a") -> 80.769231 | D62: =IFERROR(AVERAGE(Sensitivity!$E$2:$E$113),"n/a") -> 78.536339 | E62: =IFERROR(AVERAGE(Sensitivity!$L$2:$L$113),"n/a") -> 2.0977127 | F62: =IFERROR(MAX(Sensitivity!$L$2:$L$113),"n/a") -> 16.711538
A63: Equal metric weights | B63: =COUNT(Sensitivity!$F$2:$F$113) -> 87 | C63: =IFERROR(MEDIAN(Sensitivity!$F$2:$F$113),"n/a") -> 80.952381 | D63: =IFERROR(AVERAGE(Sensitivity!$F$2:$F$113),"n/a") -> 79.93077 | E63: =IFERROR(AVERAGE(Sensitivity!$M$2:$M$113),"n/a") -> 4.4520714 | F63: =IFERROR(MAX(Sensitivity!$M$2:$M$113),"n/a") -> 15.122549
A64: C1 excl. "Contribute funds" | B64: =COUNT(Sensitivity!$G$2:$G$113) -> 89 | C64: =IFERROR(MEDIAN(Sensitivity!$G$2:$G$113),"n/a") -> 76.923077 | D64: =IFERROR(AVERAGE(Sensitivity!$G$2:$G$113),"n/a") -> 74.515424 | E64: =IFERROR(AVERAGE(Sensitivity!$N$2:$N$113),"n/a") -> 1.1057793 | F64: =IFERROR(MAX(Sensitivity!$N$2:$N$113),"n/a") -> 4.5454545
A65: Shrinkage toward median | B65: =COUNT(Sensitivity!$H$2:$H$113) -> 87 | C65: =IFERROR(MEDIAN(Sensitivity!$H$2:$H$113),"n/a") -> 78.225806 | D65: =IFERROR(AVERAGE(Sensitivity!$H$2:$H$113),"n/a") -> 76.098788 | E65: =IFERROR(AVERAGE(Sensitivity!$O$2:$O$113),"n/a") -> 1.8691512 | F65: =IFERROR(MAX(Sensitivity!$O$2:$O$113),"n/a") -> 12.966376
A66: Require E2 or C1 scored | B66: =COUNT(Sensitivity!$I$2:$I$113) -> 81 | C66: =IFERROR(MEDIAN(Sensitivity!$I$2:$I$113),"n/a") -> 76.25 | D66: =IFERROR(AVERAGE(Sensitivity!$I$2:$I$113),"n/a") -> 74.58779 | E66: =IFERROR(AVERAGE(Sensitivity!$P$2:$P$113),"n/a") -> 0 | F66: =IFERROR(MAX(Sensitivity!$P$2:$P$113),"n/a") -> 0
A69: 7. Data-quality flags requiring verification (repos affected)
A70: 037 vs 038 conflict | B70: =SUM(Calc!$L$2:$L$113) -> 2
A71: Code of Conduct URL but status ≠ Implemented | B71: =SUM(Calc!$M$2:$M$113) -> 5
A72: Governance "Formal" with no URL | B72: =SUM(Calc!$N$2:$N$113) -> 7
A73: Governance blank but URL present | B73: =SUM(Calc!$O$2:$O$113) -> 1
A74: Engagement text/URL given but no category coded | B74: =SUM(Calc!$P$2:$P$113) -> 21
A75: 041 suspect URL (not a guideline) | B75: =SUM(Calc!$Q$2:$Q$113) -> 6
A76: 039 contradicts contribution evidence (consistency check) | B76: =SUM(Calc!$R$2:$R$113) -> 4
A77: No code-repository URL | B77: =SUM(Calc!$S$2:$S$113) -> 4
A80: 8. Top 10 and bottom 10 — reportable repos only (≥85% of weight scored)
A81: Top 10 (reportable) | B81: Score | C81: Range (low–high) | D81: Bottom 10 (reportable) | E81: Score | F81: Range (low–high)
A82: =IFERROR(INDEX(Scoring!$A$2:$A$113,MATCH(1,Scoring!$AA$2:$AA$113,0)),"") -> Thoth Open Metadata | B82: =IFERROR(INDEX(Scoring!$S$2:$S$113,MATCH(1,Scoring!$AA$2:$AA$113,0)),"") -> 100 | C82: =IFERROR(TEXT(INDEX(Scoring!$T$2:$T$113,MATCH(1,Scoring!$AA$2:$AA$113,0)),"0")&" – "&TEXT(INDEX(Scoring!$U$2:$U$113,MATCH(1,Scoring!$AA$2:$AA$113,0)),"0"),"") -> 88 – 100 | D82: =IFERROR(INDEX(Scoring!$A$2:$A$113,MATCH($B$50-0,Scoring!$AA$2:$AA$113,0)),"") -> Tropy | E82: =IFERROR(INDEX(Scoring!$S$2:$S$113,MATCH($B$50-0,Scoring!$AA$2:$AA$113,0)),"") -> 45.2 | F82: =IFERROR(TEXT(INDEX(Scoring!$T$2:$T$113,MATCH($B$50-0,Scoring!$AA$2:$AA$113,0)),"0")&" – "&TEXT(INDEX(Scoring!$U$2:$U$113,MATCH($B$50-0,Scoring!$AA$2:$AA$113,0)),"0"),"") -> 45 – 45
A83: =IFERROR(INDEX(Scoring!$A$2:$A$113,MATCH(2,Scoring!$AA$2:$AA$113,0)),"") -> DSpace | B83: =IFERROR(INDEX(Scoring!$S$2:$S$113,MATCH(2,Scoring!$AA$2:$AA$113,0)),"") -> 97.25 | C83: =IFERROR(TEXT(INDEX(Scoring!$T$2:$T$113,MATCH(2,Scoring!$AA$2:$AA$113,0)),"0")&" – "&TEXT(INDEX(Scoring!$U$2:$U$113,MATCH(2,Scoring!$AA$2:$AA$113,0)),"0"),"") -> 97 – 97 | D83: =IFERROR(INDEX(Scoring!$A$2:$A$113,MATCH($B$50-1,Scoring!$AA$2:$AA$113,0)),"") -> Metadata Encoding and Transmission Standard (METS) | E83: =IFERROR(INDEX(Scoring!$S$2:$S$113,MATCH($B$50-1,Scoring!$AA$2:$AA$113,0)),"") -> 46.5 | F83: =IFERROR(TEXT(INDEX(Scoring!$T$2:$T$113,MATCH($B$50-1,Scoring!$AA$2:$AA$113,0)),"0")&" – "&TEXT(INDEX(Scoring!$U$2:$U$113,MATCH($B$50-1,Scoring!$AA$2:$AA$113,0)),"0"),"") -> 47 – 47
A84: =IFERROR(INDEX(Scoring!$A$2:$A$113,MATCH(3,Scoring!$AA$2:$AA$113,0)),"") -> DOAJ (Directory of Open Access Journals) | B84: =IFERROR(INDEX(Scoring!$S$2:$S$113,MATCH(3,Scoring!$AA$2:$AA$113,0)),"") -> 96.590909 | C84: =IFERROR(TEXT(INDEX(Scoring!$T$2:$T$113,MATCH(3,Scoring!$AA$2:$AA$113,0)),"0")&" – "&TEXT(INDEX(Scoring!$U$2:$U$113,MATCH(3,Scoring!$AA$2:$AA$113,0)),"0"),"") -> 85 – 97 | D84: =IFERROR(INDEX(Scoring!$A$2:$A$113,MATCH($B$50-2,Scoring!$AA$2:$AA$113,0)),"") -> Mukurtu CMS | E84: =IFERROR(INDEX(Scoring!$S$2:$S$113,MATCH($B$50-2,Scoring!$AA$2:$AA$113,0)),"") -> 47.8 | F84: =IFERROR(TEXT(INDEX(Scoring!$T$2:$T$113,MATCH($B$50-2,Scoring!$AA$2:$AA$113,0)),"0")&" – "&TEXT(INDEX(Scoring!$U$2:$U$113,MATCH($B$50-2,Scoring!$AA$2:$AA$113,0)),"0"),"") -> 48 – 48
A85: =IFERROR(INDEX(Scoring!$A$2:$A$113,MATCH(4,Scoring!$AA$2:$AA$113,0)),"") -> VuFind® | B85: =IFERROR(INDEX(Scoring!$S$2:$S$113,MATCH(4,Scoring!$AA$2:$AA$113,0)),"") -> 94.5 | C85: =IFERROR(TEXT(INDEX(Scoring!$T$2:$T$113,MATCH(4,Scoring!$AA$2:$AA$113,0)),"0")&" – "&TEXT(INDEX(Scoring!$U$2:$U$113,MATCH(4,Scoring!$AA$2:$AA$113,0)),"0"),"") -> 95 – 95 | D85: =IFERROR(INDEX(Scoring!$A$2:$A$113,MATCH($B$50-3,Scoring!$AA$2:$AA$113,0)),"") -> Data Citation Corpus | E85: =IFERROR(INDEX(Scoring!$S$2:$S$113,MATCH($B$50-3,Scoring!$AA$2:$AA$113,0)),"") -> 48.5 | F85: =IFERROR(TEXT(INDEX(Scoring!$T$2:$T$113,MATCH($B$50-3,Scoring!$AA$2:$AA$113,0)),"0")&" – "&TEXT(INDEX(Scoring!$U$2:$U$113,MATCH($B$50-3,Scoring!$AA$2:$AA$113,0)),"0"),"") -> 49 – 49
A86: =IFERROR(INDEX(Scoring!$A$2:$A$113,MATCH(5,Scoring!$AA$2:$AA$113,0)),"") -> Academic Preservation Trust (APTrust) | B86: =IFERROR(INDEX(Scoring!$S$2:$S$113,MATCH(5,Scoring!$AA$2:$AA$113,0)),"") -> 94 | C86: =IFERROR(TEXT(INDEX(Scoring!$T$2:$T$113,MATCH(5,Scoring!$AA$2:$AA$113,0)),"0")&" – "&TEXT(INDEX(Scoring!$U$2:$U$113,MATCH(5,Scoring!$AA$2:$AA$113,0)),"0"),"") -> 94 – 94 | D86: =IFERROR(INDEX(Scoring!$A$2:$A$113,MATCH($B$50-4,Scoring!$AA$2:$AA$113,0)),"") -> OpenAlex | E86: =IFERROR(INDEX(Scoring!$S$2:$S$113,MATCH($B$50-4,Scoring!$AA$2:$AA$113,0)),"") -> 50.25 | F86: =IFERROR(TEXT(INDEX(Scoring!$T$2:$T$113,MATCH($B$50-4,Scoring!$AA$2:$AA$113,0)),"0")&" – "&TEXT(INDEX(Scoring!$U$2:$U$113,MATCH($B$50-4,Scoring!$AA$2:$AA$113,0)),"0"),"") -> 50 – 50
A87: =IFERROR(INDEX(Scoring!$A$2:$A$113,MATCH(6,Scoring!$AA$2:$AA$113,0)),"") -> Fedora | B87: =IFERROR(INDEX(Scoring!$S$2:$S$113,MATCH(6,Scoring!$AA$2:$AA$113,0)),"") -> 94 | C87: =IFERROR(TEXT(INDEX(Scoring!$T$2:$T$113,MATCH(6,Scoring!$AA$2:$AA$113,0)),"0")&" – "&TEXT(INDEX(Scoring!$U$2:$U$113,MATCH(6,Scoring!$AA$2:$AA$113,0)),"0"),"") -> 94 – 94 | D87: =IFERROR(INDEX(Scoring!$A$2:$A$113,MATCH($B$50-5,Scoring!$AA$2:$AA$113,0)),"") -> RePEc | E87: =IFERROR(INDEX(Scoring!$S$2:$S$113,MATCH($B$50-5,Scoring!$AA$2:$AA$113,0)),"") -> 52.272727 | F87: =IFERROR(TEXT(INDEX(Scoring!$T$2:$T$113,MATCH($B$50-5,Scoring!$AA$2:$AA$113,0)),"0")&" – "&TEXT(INDEX(Scoring!$U$2:$U$113,MATCH($B$50-5,Scoring!$AA$2:$AA$113,0)),"0"),"") -> 46 – 58
A88: =IFERROR(INDEX(Scoring!$A$2:$A$113,MATCH(7,Scoring!$AA$2:$AA$113,0)),"") -> Hyku | B88: =IFERROR(INDEX(Scoring!$S$2:$S$113,MATCH(7,Scoring!$AA$2:$AA$113,0)),"") -> 94 | C88: =IFERROR(TEXT(INDEX(Scoring!$T$2:$T$113,MATCH(7,Scoring!$AA$2:$AA$113,0)),"0")&" – "&TEXT(INDEX(Scoring!$U$2:$U$113,MATCH(7,Scoring!$AA$2:$AA$113,0)),"0"),"") -> 94 – 94 | D88: =IFERROR(INDEX(Scoring!$A$2:$A$113,MATCH($B$50-6,Scoring!$AA$2:$AA$113,0)),"") -> OpenEdition | E88: =IFERROR(INDEX(Scoring!$S$2:$S$113,MATCH($B$50-6,Scoring!$AA$2:$AA$113,0)),"") -> 52.784091 | F88: =IFERROR(TEXT(INDEX(Scoring!$T$2:$T$113,MATCH($B$50-6,Scoring!$AA$2:$AA$113,0)),"0")&" – "&TEXT(INDEX(Scoring!$U$2:$U$113,MATCH($B$50-6,Scoring!$AA$2:$AA$113,0)),"0"),"") -> 46 – 58
A89: =IFERROR(INDEX(Scoring!$A$2:$A$113,MATCH(8,Scoring!$AA$2:$AA$113,0)),"") -> Hyrax | B89: =IFERROR(INDEX(Scoring!$S$2:$S$113,MATCH(8,Scoring!$AA$2:$AA$113,0)),"") -> 94 | C89: =IFERROR(TEXT(INDEX(Scoring!$T$2:$T$113,MATCH(8,Scoring!$AA$2:$AA$113,0)),"0")&" – "&TEXT(INDEX(Scoring!$U$2:$U$113,MATCH(8,Scoring!$AA$2:$AA$113,0)),"0"),"") -> 94 – 94 | D89: =IFERROR(INDEX(Scoring!$A$2:$A$113,MATCH($B$50-7,Scoring!$AA$2:$AA$113,0)),"") -> COAR International Repository Directory (IRD) | E89: =IFERROR(INDEX(Scoring!$S$2:$S$113,MATCH($B$50-7,Scoring!$AA$2:$AA$113,0)),"") -> 56.05 | F89: =IFERROR(TEXT(INDEX(Scoring!$T$2:$T$113,MATCH($B$50-7,Scoring!$AA$2:$AA$113,0)),"0")&" – "&TEXT(INDEX(Scoring!$U$2:$U$113,MATCH($B$50-7,Scoring!$AA$2:$AA$113,0)),"0"),"") -> 56 – 56
A90: =IFERROR(INDEX(Scoring!$A$2:$A$113,MATCH(9,Scoring!$AA$2:$AA$113,0)),"") -> Research Organization Registry (ROR) | B90: =IFERROR(INDEX(Scoring!$S$2:$S$113,MATCH(9,Scoring!$AA$2:$AA$113,0)),"") -> 91 | C90: =IFERROR(TEXT(INDEX(Scoring!$T$2:$T$113,MATCH(9,Scoring!$AA$2:$AA$113,0)),"0")&" – "&TEXT(INDEX(Scoring!$U$2:$U$113,MATCH(9,Scoring!$AA$2:$AA$113,0)),"0"),"") -> 91 – 91 | D90: =IFERROR(INDEX(Scoring!$A$2:$A$113,MATCH($B$50-8,Scoring!$AA$2:$AA$113,0)),"") -> Fulcrum | E90: =IFERROR(INDEX(Scoring!$S$2:$S$113,MATCH($B$50-8,Scoring!$AA$2:$AA$113,0)),"") -> 56.25 | F90: =IFERROR(TEXT(INDEX(Scoring!$T$2:$T$113,MATCH($B$50-8,Scoring!$AA$2:$AA$113,0)),"0")&" – "&TEXT(INDEX(Scoring!$U$2:$U$113,MATCH($B$50-8,Scoring!$AA$2:$AA$113,0)),"0"),"") -> 50 – 61
A91: =IFERROR(INDEX(Scoring!$A$2:$A$113,MATCH(10,Scoring!$AA$2:$AA$113,0)),"") -> iRODS | B91: =IFERROR(INDEX(Scoring!$S$2:$S$113,MATCH(10,Scoring!$AA$2:$AA$113,0)),"") -> 90 | C91: =IFERROR(TEXT(INDEX(Scoring!$T$2:$T$113,MATCH(10,Scoring!$AA$2:$AA$113,0)),"0")&" – "&TEXT(INDEX(Scoring!$U$2:$U$113,MATCH(10,Scoring!$AA$2:$AA$113,0)),"0"),"") -> 90 – 90 | D91: =IFERROR(INDEX(Scoring!$A$2:$A$113,MATCH($B$50-9,Scoring!$AA$2:$AA$113,0)),"") -> Database Information System | E91: =IFERROR(INDEX(Scoring!$S$2:$S$113,MATCH($B$50-9,Scoring!$AA$2:$AA$113,0)),"") -> 57.045455 | F91: =IFERROR(TEXT(INDEX(Scoring!$T$2:$T$113,MATCH($B$50-9,Scoring!$AA$2:$AA$113,0)),"0")&" – "&TEXT(INDEX(Scoring!$U$2:$U$113,MATCH($B$50-9,Scoring!$AA$2:$AA$113,0)),"0"),"") -> 50 – 62
A93: Provisional repos (scored, <85% of weight) are excluded from these lists. Filter Scoring → Result status to see them with their ranges.
A96: 9. E2 coding quality (938 text coder vs 038 checklist, repos with both filled)
A97: Repos with both 038 and 938 filled | B97: =SUM(Coding!AH2:AH113) -> 11
A98: Coded categories also in checklist | B98: =SUM(Coding!AI2:AI113) -> 14
A99: Coded categories not in checklist | B99: =SUM(Coding!AJ2:AJ113) -> 0
A100: Precision vs checklist | B100: =IFERROR(B98/(B98+B99),"n/a") -> 1
A101: Recall of checklist (share of checklist categories the coder found) | B101: =IFERROR(B98/SUM(Coding!AK2:AK113),"n/a") -> 0.14893617
A102: Repos with ≥1 category from 038 alone | B102: =COUNTIF(Coding!AG2:AG113,">0") -> 52
A103: Repos with ≥1 category from 038 + coded 938 | B103: =COUNTIF(Coding!AF2:AF113,">0") -> 73
A104: Categories added by 938 text only (all repos) | B104: =SUM(Coding!AD2:AD113) -> 61
A106: Precision is measured against the checklist, which can itself be incomplete, so a "not in checklist" hit is not automatically wrong. See the Audit sheet.

Sheet Scoring
A1: Service | B1: Provider | C1: Solution category | D1: E1 Engagement status (037) | E1: E2 Engagement breadth (038 + coded 938) | F1: C1 Contribution routes (040) | G1: C2 Contribution guidance (041) | H1: C3 Open contribution infrastructure (019) | I1: G1 Code of Conduct (042) | J1: G2 Governance (048) | K1: Engagement & Participation (0–100) | L1: Contribution Mechanisms (0–100) | M1: Norms & Governance (0–100) | N1: Weight scored (share) | O1: Weighted sum | P1: Metrics scored (of 7) | Q1: Sub-components covered (of 3) | R1: Eligible for score? | S1: COMMUNITY ENGAGEMENT SCORE (0–100) | T1: Lower bound (missing metrics = 0) | U1: Upper bound (missing metrics = 1) | V1: Result status | W1: Rank (all scored) | X1: Completeness band | Y1: Data-quality flags | Z1: Rank key – reportable only (helper) | AA1: Rank – reportable only (helper)
A2: =Data!$A2 -> 2i2c | B2: =Data!$B2 -> Code for Science and Society | C2: =Data!$E2 -> Authoring tool | D2: =IF(Verification!C2="",Calc!B2,Verification!C2) -> 1 | E2: =IF(Verification!D2="",Calc!D2,Verification!D2) -> NA | F2: =IF(Verification!E2="",Calc!G2,Verification!E2) -> NA | G2: =IF(Verification!F2="",Calc!I2,Verification!F2) -> NA | H2: =IF(Verification!G2="",Calc!E2,Verification!G2) -> 1 | I2: =IF(Verification!H2="",Calc!J2,Verification!H2) -> 1 | J2: =IF(Verification!I2="",Calc!K2,Verification!I2) -> NA | K2: =IF(COUNT(D2:E2)=0,"NA",(IF(ISNUMBER(D2),D2*Parameters!$E$6,0)+IF(ISNUMBER(E2),E2*Parameters!$E$7,0))/(IF(ISNUMBER(D2),Parameters!$E$6,0)+IF(ISNUMBER(E2),Parameters!$E$7,0))*100) -> 100 | L2: =IF(COUNT(F2:H2)=0,"NA",(IF(ISNUMBER(F2),F2*Parameters!$E$8,0)+IF(ISNUMBER(G2),G2*Parameters!$E$9,0)+IF(ISNUMBER(H2),H2*Parameters!$E$10,0))/(IF(ISNUMBER(F2),Parameters!$E$8,0)+IF(ISNUMBER(G2),Parameters!$E$9,0)+IF(ISNUMBER(H2),Parameters!$E$10,0))*100) -> 100 | M2: =IF(COUNT(I2:J2)=0,"NA",(IF(ISNUMBER(I2),I2*Parameters!$E$11,0)+IF(ISNUMBER(J2),J2*Parameters!$E$12,0))/(IF(ISNUMBER(I2),Parameters!$E$11,0)+IF(ISNUMBER(J2),Parameters!$E$12,0))*100) -> 100 | N2: =IF(ISNUMBER(D2),Parameters!$E$6,0)+IF(ISNUMBER(E2),Parameters!$E$7,0)+IF(ISNUMBER(F2),Parameters!$E$8,0)+IF(ISNUMBER(G2),Parameters!$E$9,0)+IF(ISNUMBER(H2),Parameters!$E$10,0)+IF(ISNUMBER(I2),Parameters!$E$11,0)+IF(ISNUMBER(J2),Parameters!$E$12,0) -> 0.28 | O2: =IF(ISNUMBER(D2),D2*Parameters!$E$6,0)+IF(ISNUMBER(E2),E2*Parameters!$E$7,0)+IF(ISNUMBER(F2),F2*Parameters!$E$8,0)+IF(ISNUMBER(G2),G2*Parameters!$E$9,0)+IF(ISNUMBER(H2),H2*Parameters!$E$10,0)+IF(ISNUMBER(I2),I2*Parameters!$E$11,0)+IF(ISNUMBER(J2),J2*Parameters!$E$12,0) -> 0.28 | P2: =COUNT(D2:J2) -> 3 | Q2: =(COUNT(D2:E2)>0)+(COUNT(F2:H2)>0)+(COUNT(I2:J2)>0) -> 3 | R2: =IF(AND(N2>=Parameters!$C$56,Q2>=Parameters!$C$59),"Yes","No") -> No | S2: =IF(R2="Yes",O2/N2*100,"NA") -> NA | T2: =IF(R2="Yes",O2/Parameters!$E$13*100,"NA") -> NA | U2: =IF(R2="Yes",(O2+(Parameters!$E$13-N2))/Parameters!$E$13*100,"NA") -> NA | V2: =IF(R2<>"Yes","Not scored",IF(N2>=Parameters!$C$60,"Reportable","Provisional")) -> Not scored | W2: =IF(ISNUMBER(S2),RANK(S2,$S$2:$S$113,0),"NA") -> NA | X2: =IF(N2>=Parameters!$C$60,"High",IF(N2>=Parameters!$C$56,"Medium","Low")) -> Low | Y2: =Calc!T2 -> 1 | Z2: =IF(V2="Reportable",S2-ROW()*0.000000001,"") | AA2: =IF(ISNUMBER(Z2),RANK(Z2,$Z$2:$Z$113,0),"NA") -> NA
A3: =Data!$A3 -> Academic Preservation Trust (APTrust) | B3: =Data!$B3 -> Academic Preservation Trust (APTrust) | C3: =Data!$E3 -> Digital preservation service | D3: =IF(Verification!C3="",Calc!B3,Verification!C3) -> 1 | E3: =IF(Verification!D3="",Calc!D3,Verification!D3) -> 1 | F3: =IF(Verification!E3="",Calc!G3,Verification!E3) -> 1 | G3: =IF(Verification!F3="",Calc!I3,Verification!F3) -> 0.5 | H3: =IF(Verification!G3="",Calc!E3,Verification!G3) -> 1 | I3: =IF(Verification!H3="",Calc!J3,Verification!H3) -> 1 | J3: =IF(Verification!I3="",Calc!K3,Verification!I3) -> 1 | K3: =IF(COUNT(D3:E3)=0,"NA",(IF(ISNUMBER(D3),D3*Parameters!$E$6,0)+IF(ISNUMBER(E3),E3*Parameters!$E$7,0))/(IF(ISNUMBER(D3),Parameters!$E$6,0)+IF(ISNUMBER(E3),Parameters!$E$7,0))*100) -> 100 | L3: =IF(COUNT(F3:H3)=0,"NA",(IF(ISNUMBER(F3),F3*Parameters!$E$8,0)+IF(ISNUMBER(G3),G3*Parameters!$E$9,0)+IF(ISNUMBER(H3),H3*Parameters!$E$10,0))/(IF(ISNUMBER(F3),Parameters!$E$8,0)+IF(ISNUMBER(G3),Parameters!$E$9,0)+IF(ISNUMBER(H3),Parameters!$E$10,0))*100) -> 82.857143 | M3: =IF(COUNT(I3:J3)=0,"NA",(IF(ISNUMBER(I3),I3*Parameters!$E$11,0)+IF(ISNUMBER(J3),J3*Parameters!$E$12,0))/(IF(ISNUMBER(I3),Parameters!$E$11,0)+IF(ISNUMBER(J3),Parameters!$E$12,0))*100) -> 100 | N3: =IF(ISNUMBER(D3),Parameters!$E$6,0)+IF(ISNUMBER(E3),Parameters!$E$7,0)+IF(ISNUMBER(F3),Parameters!$E$8,0)+IF(ISNUMBER(G3),Parameters!$E$9,0)+IF(ISNUMBER(H3),Parameters!$E$10,0)+IF(ISNUMBER(I3),Parameters!$E$11,0)+IF(ISNUMBER(J3),Parameters!$E$12,0) -> 1 | O3: =IF(ISNUMBER(D3),D3*Parameters!$E$6,0)+IF(ISNUMBER(E3),E3*Parameters!$E$7,0)+IF(ISNUMBER(F3),F3*Parameters!$E$8,0)+IF(ISNUMBER(G3),G3*Parameters!$E$9,0)+IF(ISNUMBER(H3),H3*Parameters!$E$10,0)+IF(ISNUMBER(I3),I3*Parameters!$E$11,0)+IF(ISNUMBER(J3),J3*Parameters!$E$12,0) -> 0.94 | P3: =COUNT(D3:J3) -> 7 | Q3: =(COUNT(D3:E3)>0)+(COUNT(F3:H3)>0)+(COUNT(I3:J3)>0) -> 3 | R3: =IF(AND(N3>=Parameters!$C$56,Q3>=Parameters!$C$59),"Yes","No") -> Yes | S3: =IF(R3="Yes",O3/N3*100,"NA") -> 94 | T3: =IF(R3="Yes",O3/Parameters!$E$13*100,"NA") -> 94 | U3: =IF(R3="Yes",(O3+(Parameters!$E$13-N3))/Parameters!$E$13*100,"NA") -> 94 | V3: =IF(R3<>"Yes","Not scored",IF(N3>=Parameters!$C$60,"Reportable","Provisional")) -> Reportable | W3: =IF(ISNUMBER(S3),RANK(S3,$S$2:$S$113,0),"NA") -> 13 | X3: =IF(N3>=Parameters!$C$60,"High",IF(N3>=Parameters!$C$56,"Medium","Low")) -> High | Y3: =Calc!T3 -> 0 | Z3: =IF(V3="Reportable",S3-ROW()*0.000000001,"") -> 94 | AA3: =IF(ISNUMBER(Z3),RANK(Z3,$Z$2:$Z$113,0),"NA") -> 5
A4: =Data!$A4 -> AfricArXiv | B4: =Data!$B4 -> UbuntuNet Alliance | C4: =Data!$E4 -> Repository service | D4: =IF(Verification!C4="",Calc!B4,Verification!C4) -> 0.33 | E4: =IF(Verification!D4="",Calc!D4,Verification!D4) -> NA | F4: =IF(Verification!E4="",Calc!G4,Verification!E4) -> NA | G4: =IF(Verification!F4="",Calc!I4,Verification!F4) -> NA | H4: =IF(Verification!G4="",Calc!E4,Verification!G4) -> NA | I4: =IF(Verification!H4="",Calc!J4,Verification!H4) -> 1 | J4: =IF(Verification!I4="",Calc!K4,Verification!I4) -> 0.5 | K4: =IF(COUNT(D4:E4)=0,"NA",(IF(ISNUMBER(D4),D4*Parameters!$E$6,0)+IF(ISNUMBER(E4),E4*Parameters!$E$7,0))/(IF(ISNUMBER(D4),Parameters!$E$6,0)+IF(ISNUMBER(E4),Parameters!$E$7,0))*100) -> 33 | L4: =IF(COUNT(F4:H4)=0,"NA",(IF(ISNUMBER(F4),F4*Parameters!$E$8,0)+IF(ISNUMBER(G4),G4*Parameters!$E$9,0)+IF(ISNUMBER(H4),H4*Parameters!$E$10,0))/(IF(ISNUMBER(F4),Parameters!$E$8,0)+IF(ISNUMBER(G4),Parameters!$E$9,0)+IF(ISNUMBER(H4),Parameters!$E$10,0))*100) -> NA | M4: =IF(COUNT(I4:J4)=0,"NA",(IF(ISNUMBER(I4),I4*Parameters!$E$11,0)+IF(ISNUMBER(J4),J4*Parameters!$E$12,0))/(IF(ISNUMBER(I4),Parameters!$E$11,0)+IF(ISNUMBER(J4),Parameters!$E$12,0))*100) -> 71.428571 | N4: =IF(ISNUMBER(D4),Parameters!$E$6,0)+IF(ISNUMBER(E4),Parameters!$E$7,0)+IF(ISNUMBER(F4),Parameters!$E$8,0)+IF(ISNUMBER(G4),Parameters!$E$9,0)+IF(ISNUMBER(H4),Parameters!$E$10,0)+IF(ISNUMBER(I4),Parameters!$E$11,0)+IF(ISNUMBER(J4),Parameters!$E$12,0) -> 0.43 | O4: =IF(ISNUMBER(D4),D4*Parameters!$E$6,0)+IF(ISNUMBER(E4),E4*Parameters!$E$7,0)+IF(ISNUMBER(F4),F4*Parameters!$E$8,0)+IF(ISNUMBER(G4),G4*Parameters!$E$9,0)+IF(ISNUMBER(H4),H4*Parameters!$E$10,0)+IF(ISNUMBER(I4),I4*Parameters!$E$11,0)+IF(ISNUMBER(J4),J4*Parameters!$E$12,0) -> 0.2764 | P4: =COUNT(D4:J4) -> 3 | Q4: =(COUNT(D4:E4)>0)+(COUNT(F4:H4)>0)+(COUNT(I4:J4)>0) -> 2 | R4: =IF(AND(N4>=Parameters!$C$56,Q4>=Parameters!$C$59),"Yes","No") -> No | S4: =IF(R4="Yes",O4/N4*100,"NA") -> NA | T4: =IF(R4="Yes",O4/Parameters!$E$13*100,"NA") -> NA | U4: =IF(R4="Yes",(O4+(Parameters!$E$13-N4))/Parameters!$E$13*100,"NA") -> NA | V4: =IF(R4<>"Yes","Not scored",IF(N4>=Parameters!$C$60,"Reportable","Provisional")) -> Not scored | W4: =IF(ISNUMBER(S4),RANK(S4,$S$2:$S$113,0),"NA") -> NA | X4: =IF(N4>=Parameters!$C$60,"High",IF(N4>=Parameters!$C$56,"Medium","Low")) -> Low | Y4: =Calc!T4 -> 1 | Z4: =IF(V4="Reportable",S4-ROW()*0.000000001,"") | AA4: =IF(ISNUMBER(Z4),RANK(Z4,$Z$2:$Z$113,0),"NA") -> NA
A5: =Data!$A5 -> Arches Heritage Data Management Platform | B5: =Data!$B5 -> Getty Conservation Institute (GCI) | C5: =Data!$E5 -> Data management planning tool or service | D5: =IF(Verification!C5="",Calc!B5,Verification!C5) -> 1 | E5: =IF(Verification!D5="",Calc!D5,Verification!D5) -> NA | F5: =IF(Verification!E5="",Calc!G5,Verification!E5) -> NA | G5: =IF(Verification!F5="",Calc!I5,Verification!F5) -> 1 | H5: =IF(Verification!G5="",Calc!E5,Verification!G5) -> 1 | I5: =IF(Verification!H5="",Calc!J5,Verification!H5) -> 1 | J5: =IF(Verification!I5="",Calc!K5,Verification!I5) -> 1 | K5: =IF(COUNT(D5:E5)=0,"NA",(IF(ISNUMBER(D5),D5*Parameters!$E$6,0)+IF(ISNUMBER(E5),E5*Parameters!$E$7,0))/(IF(ISNUMBER(D5),Parameters!$E$6,0)+IF(ISNUMBER(E5),Parameters!$E$7,0))*100) -> 100 | L5: =IF(COUNT(F5:H5)=0,"NA",(IF(ISNUMBER(F5),F5*Parameters!$E$8,0)+IF(ISNUMBER(G5),G5*Parameters!$E$9,0)+IF(ISNUMBER(H5),H5*Parameters!$E$10,0))/(IF(ISNUMBER(F5),Parameters!$E$8,0)+IF(ISNUMBER(G5),Parameters!$E$9,0)+IF(ISNUMBER(H5),Parameters!$E$10,0))*100) -> 100 | M5: =IF(COUNT(I5:J5)=0,"NA",(IF(ISNUMBER(I5),I5*Parameters!$E$11,0)+IF(ISNUMBER(J5),J5*Parameters!$E$12,0))/(IF(ISNUMBER(I5),Parameters!$E$11,0)+IF(ISNUMBER(J5),Parameters!$E$12,0))*100) -> 100 | N5: =IF(ISNUMBER(D5),Parameters!$E$6,0)+IF(ISNUMBER(E5),Parameters!$E$7,0)+IF(ISNUMBER(F5),Parameters!$E$8,0)+IF(ISNUMBER(G5),Parameters!$E$9,0)+IF(ISNUMBER(H5),Parameters!$E$10,0)+IF(ISNUMBER(I5),Parameters!$E$11,0)+IF(ISNUMBER(J5),Parameters!$E$12,0) -> 0.6 | O5: =IF(ISNUMBER(D5),D5*Parameters!$E$6,0)+IF(ISNUMBER(E5),E5*Parameters!$E$7,0)+IF(ISNUMBER(F5),F5*Parameters!$E$8,0)+IF(ISNUMBER(G5),G5*Parameters!$E$9,0)+IF(ISNUMBER(H5),H5*Parameters!$E$10,0)+IF(ISNUMBER(I5),I5*Parameters!$E$11,0)+IF(ISNUMBER(J5),J5*Parameters!$E$12,0) -> 0.6 | P5: =COUNT(D5:J5) -> 5 | Q5: =(COUNT(D5:E5)>0)+(COUNT(F5:H5)>0)+(COUNT(I5:J5)>0) -> 3 | R5: =IF(AND(N5>=Parameters!$C$56,Q5>=Parameters!$C$59),"Yes","No") -> Yes | S5: =IF(R5="Yes",O5/N5*100,"NA") -> 100 | T5: =IF(R5="Yes",O5/Parameters!$E$13*100,"NA") -> 60 | U5: =IF(R5="Yes",(O5+(Parameters!$E$13-N5))/Parameters!$E$13*100,"NA") -> 100 | V5: =IF(R5<>"Yes","Not scored",IF(N5>=Parameters!$C$60,"Reportable","Provisional")) -> Provisional | W5: =IF(ISNUMBER(S5),RANK(S5,$S$2:$S$113,0),"NA") -> 1 | X5: =IF(N5>=Parameters!$C$60,"High",IF(N5>=Parameters!$C$56,"Medium","Low")) -> Medium | Y5: =Calc!T5 -> 1 | Z5: =IF(V5="Reportable",S5-ROW()*0.000000001,"") | AA5: =IF(ISNUMBER(Z5),RANK(Z5,$Z$2:$Z$113,0),"NA") -> NA
A6: =Data!$A6 -> Archipelago Commons | B6: =Data!$B6 -> Metropolitan New York Library Council | C6: =Data!$E6 -> Digital library, collection or exhibit platform | Repository software | D6: =IF(Verification!C6="",Calc!B6,Verification!C6) -> 1 | E6: =IF(Verification!D6="",Calc!D6,Verification!D6) -> 0.875 | F6: =IF(Verification!E6="",Calc!G6,Verification!E6) -> 0.5 | G6: =IF(Verification!F6="",Calc!I6,Verification!F6) -> 0.5 | H6: =IF(Verification!G6="",Calc!E6,Verification!G6) -> 1 | I6: =IF(Verification!H6="",Calc!J6,Verification!H6) -> 1 | J6: =IF(Verification!I6="",Calc!K6,Verification!I6) -> 1 | K6: =IF(COUNT(D6:E6)=0,"NA",(IF(ISNUMBER(D6),D6*Parameters!$E$6,0)+IF(ISNUMBER(E6),E6*Parameters!$E$7,0))/(IF(ISNUMBER(D6),Parameters!$E$6,0)+IF(ISNUMBER(E6),Parameters!$E$7,0))*100) -> 90.833333 | L6: =IF(COUNT(F6:H6)=0,"NA",(IF(ISNUMBER(F6),F6*Parameters!$E$8,0)+IF(ISNUMBER(G6),G6*Parameters!$E$9,0)+IF(ISNUMBER(H6),H6*Parameters!$E$10,0))/(IF(ISNUMBER(F6),Parameters!$E$8,0)+IF(ISNUMBER(G6),Parameters!$E$9,0)+IF(ISNUMBER(H6),Parameters!$E$10,0))*100) -> 57.142857 | M6: =IF(COUNT(I6:J6)=0,"NA",(IF(ISNUMBER(I6),I6*Parameters!$E$11,0)+IF(ISNUMBER(J6),J6*Parameters!$E$12,0))/(IF(ISNUMBER(I6),Parameters!$E$11,0)+IF(ISNUMBER(J6),Parameters!$E$12,0))*100) -> 100 | N6: =IF(ISNUMBER(D6),Parameters!$E$6,0)+IF(ISNUMBER(E6),Parameters!$E$7,0)+IF(ISNUMBER(F6),Parameters!$E$8,0)+IF(ISNUMBER(G6),Parameters!$E$9,0)+IF(ISNUMBER(H6),Parameters!$E$10,0)+IF(ISNUMBER(I6),Parameters!$E$11,0)+IF(ISNUMBER(J6),Parameters!$E$12,0) -> 1 | O6: =IF(ISNUMBER(D6),D6*Parameters!$E$6,0)+IF(ISNUMBER(E6),E6*Parameters!$E$7,0)+IF(ISNUMBER(F6),F6*Parameters!$E$8,0)+IF(ISNUMBER(G6),G6*Parameters!$E$9,0)+IF(ISNUMBER(H6),H6*Parameters!$E$10,0)+IF(ISNUMBER(I6),I6*Parameters!$E$11,0)+IF(ISNUMBER(J6),J6*Parameters!$E$12,0) -> 0.8225 | P6: =COUNT(D6:J6) -> 7 | Q6: =(COUNT(D6:E6)>0)+(COUNT(F6:H6)>0)+(COUNT(I6:J6)>0) -> 3 | R6: =IF(AND(N6>=Parameters!$C$56,Q6>=Parameters!$C$59),"Yes","No") -> Yes | S6: =IF(R6="Yes",O6/N6*100,"NA") -> 82.25 | T6: =IF(R6="Yes",O6/Parameters!$E$13*100,"NA") -> 82.25 | U6: =IF(R6="Yes",(O6+(Parameters!$E$13-N6))/Parameters!$E$13*100,"NA") -> 82.25 | V6: =IF(R6<>"Yes","Not scored",IF(N6>=Parameters!$C$60,"Reportable","Provisional")) -> Reportable | W6: =IF(ISNUMBER(S6),RANK(S6,$S$2:$S$113,0),"NA") -> 37 | X6: =IF(N6>=Parameters!$C$60,"High",IF(N6>=Parameters!$C$56,"Medium","Low")) -> High | Y6: =Calc!T6 -> 0 | Z6: =IF(V6="Reportable",S6-ROW()*0.000000001,"") -> 82.25 | AA6: =IF(ISNUMBER(Z6),RANK(Z6,$Z$2:$Z$113,0),"NA") -> 25
A7: =Data!$A7 -> Archival Resource Key | B7: =Data!$B7 -> ARK Alliance | C7: =Data!$E7 -> Standard, specification or protocol | D7: =IF(Verification!C7="",Calc!B7,Verification!C7) -> 1 | E7: =IF(Verification!D7="",Calc!D7,Verification!D7) -> NA | F7: =IF(Verification!E7="",Calc!G7,Verification!E7) -> 0.83333333 | G7: =IF(Verification!F7="",Calc!I7,Verification!F7) -> 0.5 | H7: =IF(Verification!G7="",Calc!E7,Verification!G7) -> 1 | I7: =IF(Verification!H7="",Calc!J7,Verification!H7) -> 1 | J7: =IF(Verification!I7="",Calc!K7,Verification!I7) -> 0.5 | K7: =IF(COUNT(D7:E7)=0,"NA",(IF(ISNUMBER(D7),D7*Parameters!$E$6,0)+IF(ISNUMBER(E7),E7*Parameters!$E$7,0))/(IF(ISNUMBER(D7),Parameters!$E$6,0)+IF(ISNUMBER(E7),Parameters!$E$7,0))*100) -> 100 | L7: =IF(COUNT(F7:H7)=0,"NA",(IF(ISNUMBER(F7),F7*Parameters!$E$8,0)+IF(ISNUMBER(G7),G7*Parameters!$E$9,0)+IF(ISNUMBER(H7),H7*Parameters!$E$10,0))/(IF(ISNUMBER(F7),Parameters!$E$8,0)+IF(ISNUMBER(G7),Parameters!$E$9,0)+IF(ISNUMBER(H7),Parameters!$E$10,0))*100) -> 74.285714 | M7: =IF(COUNT(I7:J7)=0,"NA",(IF(ISNUMBER(I7),I7*Parameters!$E$11,0)+IF(ISNUMBER(J7),J7*Parameters!$E$12,0))/(IF(ISNUMBER(I7),Parameters!$E$11,0)+IF(ISNUMBER(J7),Parameters!$E$12,0))*100) -> 71.428571 | N7: =IF(ISNUMBER(D7),Parameters!$E$6,0)+IF(ISNUMBER(E7),Parameters!$E$7,0)+IF(ISNUMBER(F7),Parameters!$E$8,0)+IF(ISNUMBER(G7),Parameters!$E$9,0)+IF(ISNUMBER(H7),Parameters!$E$10,0)+IF(ISNUMBER(I7),Parameters!$E$11,0)+IF(ISNUMBER(J7),Parameters!$E$12,0) -> 0.78 | O7: =IF(ISNUMBER(D7),D7*Parameters!$E$6,0)+IF(ISNUMBER(E7),E7*Parameters!$E$7,0)+IF(ISNUMBER(F7),F7*Parameters!$E$8,0)+IF(ISNUMBER(G7),G7*Parameters!$E$9,0)+IF(ISNUMBER(H7),H7*Parameters!$E$10,0)+IF(ISNUMBER(I7),I7*Parameters!$E$11,0)+IF(ISNUMBER(J7),J7*Parameters!$E$12,0) -> 0.59 | P7: =COUNT(D7:J7) -> 6 | Q7: =(COUNT(D7:E7)>0)+(COUNT(F7:H7)>0)+(COUNT(I7:J7)>0) -> 3 | R7: =IF(AND(N7>=Parameters!$C$56,Q7>=Parameters!$C$59),"Yes","No") -> Yes | S7: =IF(R7="Yes",O7/N7*100,"NA") -> 75.641026 | T7: =IF(R7="Yes",O7/Parameters!$E$13*100,"NA") -> 59 | U7: =IF(R7="Yes",(O7+(Parameters!$E$13-N7))/Parameters!$E$13*100,"NA") -> 81 | V7: =IF(R7<>"Yes","Not scored",IF(N7>=Parameters!$C$60,"Reportable","Provisional")) -> Provisional | W7: =IF(ISNUMBER(S7),RANK(S7,$S$2:$S$113,0),"NA") -> 48 | X7: =IF(N7>=Parameters!$C$60,"High",IF(N7>=Parameters!$C$56,"Medium","Low")) -> Medium | Y7: =Calc!T7 -> 1 | Z7: =IF(V7="Reportable",S7-ROW()*0.000000001,"") | AA7: =IF(ISNUMBER(Z7),RANK(Z7,$Z$2:$Z$113,0),"NA") -> NA
A8: =Data!$A8 -> Archivematica | B8: =Data!$B8 -> Artefactual | C8: =Data!$E8 -> Digital preservation system | D8: =IF(Verification!C8="",Calc!B8,Verification!C8) -> 1 | E8: =IF(Verification!D8="",Calc!D8,Verification!D8) -> NA | F8: =IF(Verification!E8="",Calc!G8,Verification!E8) -> NA | G8: =IF(Verification!F8="",Calc!I8,Verification!F8) -> 1 | H8: =IF(Verification!G8="",Calc!E8,Verification!G8) -> 1 | I8: =IF(Verification!H8="",Calc!J8,Verification!H8) -> NA | J8: =IF(Verification!I8="",Calc!K8,Verification!I8) -> NA | K8: =IF(COUNT(D8:E8)=0,"NA",(IF(ISNUMBER(D8),D8*Parameters!$E$6,0)+IF(ISNUMBER(E8),E8*Parameters!$E$7,0))/(IF(ISNUMBER(D8),Parameters!$E$6,0)+IF(ISNUMBER(E8),Parameters!$E$7,0))*100) -> 100 | L8: =IF(COUNT(F8:H8)=0,"NA",(IF(ISNUMBER(F8),F8*Parameters!$E$8,0)+IF(ISNUMBER(G8),G8*Parameters!$E$9,0)+IF(ISNUMBER(H8),H8*Parameters!$E$10,0))/(IF(ISNUMBER(F8),Parameters!$E$8,0)+IF(ISNUMBER(G8),Parameters!$E$9,0)+IF(ISNUMBER(H8),Parameters!$E$10,0))*100) -> 100 | M8: =IF(COUNT(I8:J8)=0,"NA",(IF(ISNUMBER(I8),I8*Parameters!$E$11,0)+IF(ISNUMBER(J8),J8*Parameters!$E$12,0))/(IF(ISNUMBER(I8),Parameters!$E$11,0)+IF(ISNUMBER(J8),Parameters!$E$12,0))*100) -> NA | N8: =IF(ISNUMBER(D8),Parameters!$E$6,0)+IF(ISNUMBER(E8),Parameters!$E$7,0)+IF(ISNUMBER(F8),Parameters!$E$8,0)+IF(ISNUMBER(G8),Parameters!$E$9,0)+IF(ISNUMBER(H8),Parameters!$E$10,0)+IF(ISNUMBER(I8),Parameters!$E$11,0)+IF(ISNUMBER(J8),Parameters!$E$12,0) -> 0.25 | O8: =IF(ISNUMBER(D8),D8*Parameters!$E$6,0)+IF(ISNUMBER(E8),E8*Parameters!$E$7,0)+IF(ISNUMBER(F8),F8*Parameters!$E$8,0)+IF(ISNUMBER(G8),G8*Parameters!$E$9,0)+IF(ISNUMBER(H8),H8*Parameters!$E$10,0)+IF(ISNUMBER(I8),I8*Parameters!$E$11,0)+IF(ISNUMBER(J8),J8*Parameters!$E$12,0) -> 0.25 | P8: =COUNT(D8:J8) -> 3 | Q8: =(COUNT(D8:E8)>0)+(COUNT(F8:H8)>0)+(COUNT(I8:J8)>0) -> 2 | R8: =IF(AND(N8>=Parameters!$C$56,Q8>=Parameters!$C$59),"Yes","No") -> No | S8: =IF(R8="Yes",O8/N8*100,"NA") -> NA | T8: =IF(R8="Yes",O8/Parameters!$E$13*100,"NA") -> NA | U8: =IF(R8="Yes",(O8+(Parameters!$E$13-N8))/Parameters!$E$13*100,"NA") -> NA | V8: =IF(R8<>"Yes","Not scored",IF(N8>=Parameters!$C$60,"Reportable","Provisional")) -> Not scored | W8: =IF(ISNUMBER(S8),RANK(S8,$S$2:$S$113,0),"NA") -> NA | X8: =IF(N8>=Parameters!$C$60,"High",IF(N8>=Parameters!$C$56,"Medium","Low")) -> Low | Y8: =Calc!T8 -> 2 | Z8: =IF(V8="Reportable",S8-ROW()*0.000000001,"") | AA8: =IF(ISNUMBER(Z8),RANK(Z8,$Z$2:$Z$113,0),"NA") -> NA
A9: =Data!$A9 -> ArchivesSpace | B9: =Data!$B9 -> ArchivesSpace | C9: =Data!$E9 -> Archive information management system | Discovery system | D9: =IF(Verification!C9="",Calc!B9,Verification!C9) -> 1 | E9: =IF(Verification!D9="",Calc!D9,Verification!D9) -> 1 | F9: =IF(Verification!E9="",Calc!G9,Verification!E9) -> NA | G9: =IF(Verification!F9="",Calc!I9,Verification!F9) -> 1 | H9: =IF(Verification!G9="",Calc!E9,Verification!G9) -> 1 | I9: =IF(Verification!H9="",Calc!J9,Verification!H9) -> 1 | J9: =IF(Verification!I9="",Calc!K9,Verification!I9) -> 1 | K9: =IF(COUNT(D9:E9)=0,"NA",(IF(ISNUMBER(D9),D9*Parameters!$E$6,0)+IF(ISNUMBER(E9),E9*Parameters!$E$7,0))/(IF(ISNUMBER(D9),Parameters!$E$6,0)+IF(ISNUMBER(E9),Parameters!$E$7,0))*100) -> 100 | L9: =IF(COUNT(F9:H9)=0,"NA",(IF(ISNUMBER(F9),F9*Parameters!$E$8,0)+IF(ISNUMBER(G9),G9*Parameters!$E$9,0)+IF(ISNUMBER(H9),H9*Parameters!$E$10,0))/(IF(ISNUMBER(F9),Parameters!$E$8,0)+IF(ISNUMBER(G9),Parameters!$E$9,0)+IF(ISNUMBER(H9),Parameters!$E$10,0))*100) -> 100 | M9: =IF(COUNT(I9:J9)=0,"NA",(IF(ISNUMBER(I9),I9*Parameters!$E$11,0)+IF(ISNUMBER(J9),J9*Parameters!$E$12,0))/(IF(ISNUMBER(I9),Parameters!$E$11,0)+IF(ISNUMBER(J9),Parameters!$E$12,0))*100) -> 100 | N9: =IF(ISNUMBER(D9),Parameters!$E$6,0)+IF(ISNUMBER(E9),Parameters!$E$7,0)+IF(ISNUMBER(F9),Parameters!$E$8,0)+IF(ISNUMBER(G9),Parameters!$E$9,0)+IF(ISNUMBER(H9),Parameters!$E$10,0)+IF(ISNUMBER(I9),Parameters!$E$11,0)+IF(ISNUMBER(J9),Parameters!$E$12,0) -> 0.82 | O9: =IF(ISNUMBER(D9),D9*Parameters!$E$6,0)+IF(ISNUMBER(E9),E9*Parameters!$E$7,0)+IF(ISNUMBER(F9),F9*Parameters!$E$8,0)+IF(ISNUMBER(G9),G9*Parameters!$E$9,0)+IF(ISNUMBER(H9),H9*Parameters!$E$10,0)+IF(ISNUMBER(I9),I9*Parameters!$E$11,0)+IF(ISNUMBER(J9),J9*Parameters!$E$12,0) -> 0.82 | P9: =COUNT(D9:J9) -> 6 | Q9: =(COUNT(D9:E9)>0)+(COUNT(F9:H9)>0)+(COUNT(I9:J9)>0) -> 3 | R9: =IF(AND(N9>=Parameters!$C$56,Q9>=Parameters!$C$59),"Yes","No") -> Yes | S9: =IF(R9="Yes",O9/N9*100,"NA") -> 100 | T9: =IF(R9="Yes",O9/Parameters!$E$13*100,"NA") -> 82 | U9: =IF(R9="Yes",(O9+(Parameters!$E$13-N9))/Parameters!$E$13*100,"NA") -> 100 | V9: =IF(R9<>"Yes","Not scored",IF(N9>=Parameters!$C$60,"Reportable","Provisional")) -> Provisional | W9: =IF(ISNUMBER(S9),RANK(S9,$S$2:$S$113,0),"NA") -> 1 | X9: =IF(N9>=Parameters!$C$60,"High",IF(N9>=Parameters!$C$56,"Medium","Low")) -> Medium | Y9: =Calc!T9 -> 0 | Z9: =IF(V9="Reportable",S9-ROW()*0.000000001,"") | AA9: =IF(ISNUMBER(Z9),RANK(Z9,$Z$2:$Z$113,0),"NA") -> NA
A10: =Data!$A10 -> ARGOS | B10: =Data!$B10 -> OpenAIRE | C10: =Data!$E10 -> Data management planning tool or service | D10: =IF(Verification!C10="",Calc!B10,Verification!C10) -> 1 | E10: =IF(Verification!D10="",Calc!D10,Verification!D10) -> 1 | F10: =IF(Verification!E10="",Calc!G10,Verification!E10) -> NA | G10: =IF(Verification!F10="",Calc!I10,Verification!F10) -> NA | H10: =IF(Verification!G10="",Calc!E10,Verification!G10) -> 1 | I10: =IF(Verification!H10="",Calc!J10,Verification!H10) -> 1 | J10: =IF(Verification!I10="",Calc!K10,Verification!I10) -> 1 | K10: =IF(COUNT(D10:E10)=0,"NA",(IF(ISNUMBER(D10),D10*Parameters!$E$6,0)+IF(ISNUMBER(E10),E10*Parameters!$E$7,0))/(IF(ISNUMBER(D10),Parameters!$E$6,0)+IF(ISNUMBER(E10),Parameters!$E$7,0))*100) -> 100 | L10: =IF(COUNT(F10:H10)=0,"NA",(IF(ISNUMBER(F10),F10*Parameters!$E$8,0)+IF(ISNUMBER(G10),G10*Parameters!$E$9,0)+IF(ISNUMBER(H10),H10*Parameters!$E$10,0))/(IF(ISNUMBER(F10),Parameters!$E$8,0)+IF(ISNUMBER(G10),Parameters!$E$9,0)+IF(ISNUMBER(H10),Parameters!$E$10,0))*100) -> 100 | M10: =IF(COUNT(I10:J10)=0,"NA",(IF(ISNUMBER(I10),I10*Parameters!$E$11,0)+IF(ISNUMBER(J10),J10*Parameters!$E$12,0))/(IF(ISNUMBER(I10),Parameters!$E$11,0)+IF(ISNUMBER(J10),Parameters!$E$12,0))*100) -> 100 | N10: =IF(ISNUMBER(D10),Parameters!$E$6,0)+IF(ISNUMBER(E10),Parameters!$E$7,0)+IF(ISNUMBER(F10),Parameters!$E$8,0)+IF(ISNUMBER(G10),Parameters!$E$9,0)+IF(ISNUMBER(H10),Parameters!$E$10,0)+IF(ISNUMBER(I10),Parameters!$E$11,0)+IF(ISNUMBER(J10),Parameters!$E$12,0) -> 0.7 | O10: =IF(ISNUMBER(D10),D10*Parameters!$E$6,0)+IF(ISNUMBER(E10),E10*Parameters!$E$7,0)+IF(ISNUMBER(F10),F10*Parameters!$E$8,0)+IF(ISNUMBER(G10),G10*Parameters!$E$9,0)+IF(ISNUMBER(H10),H10*Parameters!$E$10,0)+IF(ISNUMBER(I10),I10*Parameters!$E$11,0)+IF(ISNUMBER(J10),J10*Parameters!$E$12,0) -> 0.7 | P10: =COUNT(D10:J10) -> 5 | Q10: =(COUNT(D10:E10)>0)+(COUNT(F10:H10)>0)+(COUNT(I10:J10)>0) -> 3 | R10: =IF(AND(N10>=Parameters!$C$56,Q10>=Parameters!$C$59),"Yes","No") -> Yes | S10: =IF(R10="Yes",O10/N10*100,"NA") -> 100 | T10: =IF(R10="Yes",O10/Parameters!$E$13*100,"NA") -> 70 | U10: =IF(R10="Yes",(O10+(Parameters!$E$13-N10))/Parameters!$E$13*100,"NA") -> 100 | V10: =IF(R10<>"Yes","Not scored",IF(N10>=Parameters!$C$60,"Reportable","Provisional")) -> Provisional | W10: =IF(ISNUMBER(S10),RANK(S10,$S$2:$S$113,0),"NA") -> 1 | X10: =IF(N10>=Parameters!$C$60,"High",IF(N10>=Parameters!$C$56,"Medium","Low")) -> Medium | Y10: =Calc!T10 -> 0 | Z10: =IF(V10="Reportable",S10-ROW()*0.000000001,"") | AA10: =IF(ISNUMBER(Z10),RANK(Z10,$Z$2:$Z$113,0),"NA") -> NA
A11: =Data!$A11 -> arXiv | B11: =Data!$B11 -> Cornell University | C11: =Data!$E11 -> Repository service | D11: =IF(Verification!C11="",Calc!B11,Verification!C11) -> 1 | E11: =IF(Verification!D11="",Calc!D11,Verification!D11) -> 0.125 | F11: =IF(Verification!E11="",Calc!G11,Verification!E11) -> 0.5 | G11: =IF(Verification!F11="",Calc!I11,Verification!F11) -> 0.5 | H11: =IF(Verification!G11="",Calc!E11,Verification!G11) -> 1 | I11: =IF(Verification!H11="",Calc!J11,Verification!H11) -> 1 | J11: =IF(Verification!I11="",Calc!K11,Verification!I11) -> 1 | K11: =IF(COUNT(D11:E11)=0,"NA",(IF(ISNUMBER(D11),D11*Parameters!$E$6,0)+IF(ISNUMBER(E11),E11*Parameters!$E$7,0))/(IF(ISNUMBER(D11),Parameters!$E$6,0)+IF(ISNUMBER(E11),Parameters!$E$7,0))*100) -> 35.833333 | L11: =IF(COUNT(F11:H11)=0,"NA",(IF(ISNUMBER(F11),F11*Parameters!$E$8,0)+IF(ISNUMBER(G11),G11*Parameters!$E$9,0)+IF(ISNUMBER(H11),H11*Parameters!$E$10,0))/(IF(ISNUMBER(F11),Parameters!$E$8,0)+IF(ISNUMBER(G11),Parameters!$E$9,0)+IF(ISNUMBER(H11),Parameters!$E$10,0))*100) -> 57.142857 | M11: =IF(COUNT(I11:J11)=0,"NA",(IF(ISNUMBER(I11),I11*Parameters!$E$11,0)+IF(ISNUMBER(J11),J11*Parameters!$E$12,0))/(IF(ISNUMBER(I11),Parameters!$E$11,0)+IF(ISNUMBER(J11),Parameters!$E$12,0))*100) -> 100 | N11: =IF(ISNUMBER(D11),Parameters!$E$6,0)+IF(ISNUMBER(E11),Parameters!$E$7,0)+IF(ISNUMBER(F11),Parameters!$E$8,0)+IF(ISNUMBER(G11),Parameters!$E$9,0)+IF(ISNUMBER(H11),Parameters!$E$10,0)+IF(ISNUMBER(I11),Parameters!$E$11,0)+IF(ISNUMBER(J11),Parameters!$E$12,0) -> 1 | O11: =IF(ISNUMBER(D11),D11*Parameters!$E$6,0)+IF(ISNUMBER(E11),E11*Parameters!$E$7,0)+IF(ISNUMBER(F11),F11*Parameters!$E$8,0)+IF(ISNUMBER(G11),G11*Parameters!$E$9,0)+IF(ISNUMBER(H11),H11*Parameters!$E$10,0)+IF(ISNUMBER(I11),I11*Parameters!$E$11,0)+IF(ISNUMBER(J11),J11*Parameters!$E$12,0) -> 0.6575 | P11: =COUNT(D11:J11) -> 7 | Q11: =(COUNT(D11:E11)>0)+(COUNT(F11:H11)>0)+(COUNT(I11:J11)>0) -> 3 | R11: =IF(AND(N11>=Parameters!$C$56,Q11>=Parameters!$C$59),"Yes","No") -> Yes | S11: =IF(R11="Yes",O11/N11*100,"NA") -> 65.75 | T11: =IF(R11="Yes",O11/Parameters!$E$13*100,"NA") -> 65.75 | U11: =IF(R11="Yes",(O11+(Parameters!$E$13-N11))/Parameters!$E$13*100,"NA") -> 65.75 | V11: =IF(R11<>"Yes","Not scored",IF(N11>=Parameters!$C$60,"Reportable","Provisional")) -> Reportable | W11: =IF(ISNUMBER(S11),RANK(S11,$S$2:$S$113,0),"NA") -> 61 | X11: =IF(N11>=Parameters!$C$60,"High",IF(N11>=Parameters!$C$56,"Medium","Low")) -> High | Y11: =Calc!T11 -> 0 | Z11: =IF(V11="Reportable",S11-ROW()*0.000000001,"") -> 65.75 | AA11: =IF(ISNUMBER(Z11),RANK(Z11,$Z$2:$Z$113,0),"NA") -> 35
A12: =Data!$A12 -> AtoM | B12: =Data!$B12 -> Artefactual | C12: =Data!$E12 -> Archive information management system | D12: =IF(Verification!C12="",Calc!B12,Verification!C12) -> 0.67 | E12: =IF(Verification!D12="",Calc!D12,Verification!D12) -> NA | F12: =IF(Verification!E12="",Calc!G12,Verification!E12) -> NA | G12: =IF(Verification!F12="",Calc!I12,Verification!F12) -> NA | H12: =IF(Verification!G12="",Calc!E12,Verification!G12) -> 1 | I12: =IF(Verification!H12="",Calc!J12,Verification!H12) -> NA | J12: =IF(Verification!I12="",Calc!K12,Verification!I12) -> NA | K12: =IF(COUNT(D12:E12)=0,"NA",(IF(ISNUMBER(D12),D12*Parameters!$E$6,0)+IF(ISNUMBER(E12),E12*Parameters!$E$7,0))/(IF(ISNUMBER(D12),Parameters!$E$6,0)+IF(ISNUMBER(E12),Parameters!$E$7,0))*100) -> 67 | L12: =IF(COUNT(F12:H12)=0,"NA",(IF(ISNUMBER(F12),F12*Parameters!$E$8,0)+IF(ISNUMBER(G12),G12*Parameters!$E$9,0)+IF(ISNUMBER(H12),H12*Parameters!$E$10,0))/(IF(ISNUMBER(F12),Parameters!$E$8,0)+IF(ISNUMBER(G12),Parameters!$E$9,0)+IF(ISNUMBER(H12),Parameters!$E$10,0))*100) -> 100 | M12: =IF(COUNT(I12:J12)=0,"NA",(IF(ISNUMBER(I12),I12*Parameters!$E$11,0)+IF(ISNUMBER(J12),J12*Parameters!$E$12,0))/(IF(ISNUMBER(I12),Parameters!$E$11,0)+IF(ISNUMBER(J12),Parameters!$E$12,0))*100) -> NA | N12: =IF(ISNUMBER(D12),Parameters!$E$6,0)+IF(ISNUMBER(E12),Parameters!$E$7,0)+IF(ISNUMBER(F12),Parameters!$E$8,0)+IF(ISNUMBER(G12),Parameters!$E$9,0)+IF(ISNUMBER(H12),Parameters!$E$10,0)+IF(ISNUMBER(I12),Parameters!$E$11,0)+IF(ISNUMBER(J12),Parameters!$E$12,0) -> 0.13 | O12: =IF(ISNUMBER(D12),D12*Parameters!$E$6,0)+IF(ISNUMBER(E12),E12*Parameters!$E$7,0)+IF(ISNUMBER(F12),F12*Parameters!$E$8,0)+IF(ISNUMBER(G12),G12*Parameters!$E$9,0)+IF(ISNUMBER(H12),H12*Parameters!$E$10,0)+IF(ISNUMBER(I12),I12*Parameters!$E$11,0)+IF(ISNUMBER(J12),J12*Parameters!$E$12,0) -> 0.1036 | P12: =COUNT(D12:J12) -> 2 | Q12: =(COUNT(D12:E12)>0)+(COUNT(F12:H12)>0)+(COUNT(I12:J12)>0) -> 2 | R12: =IF(AND(N12>=Parameters!$C$56,Q12>=Parameters!$C$59),"Yes","No") -> No | S12: =IF(R12="Yes",O12/N12*100,"NA") -> NA | T12: =IF(R12="Yes",O12/Parameters!$E$13*100,"NA") -> NA | U12: =IF(R12="Yes",(O12+(Parameters!$E$13-N12))/Parameters!$E$13*100,"NA") -> NA | V12: =IF(R12<>"Yes","Not scored",IF(N12>=Parameters!$C$60,"Reportable","Provisional")) -> Not scored | W12: =IF(ISNUMBER(S12),RANK(S12,$S$2:$S$113,0),"NA") -> NA | X12: =IF(N12>=Parameters!$C$60,"High",IF(N12>=Parameters!$C$56,"Medium","Low")) -> Low | Y12: =Calc!T12 -> 2 | Z12: =IF(V12="Reportable",S12-ROW()*0.000000001,"") | AA12: =IF(ISNUMBER(Z12),RANK(Z12,$Z$2:$Z$113,0),"NA") -> NA
A13: =Data!$A13 -> Avalon Media System | B13: =Data!$B13 -> Indiana University Libraries | C13: =Data!$E13 -> Digital library, collection or exhibit platform | Repository software | D13: =IF(Verification!C13="",Calc!B13,Verification!C13) -> 1 | E13: =IF(Verification!D13="",Calc!D13,Verification!D13) -> 0.625 | F13: =IF(Verification!E13="",Calc!G13,Verification!E13) -> 1 | G13: =IF(Verification!F13="",Calc!I13,Verification!F13) -> 0.5 | H13: =IF(Verification!G13="",Calc!E13,Verification!G13) -> 1 | I13: =IF(Verification!H13="",Calc!J13,Verification!H13) -> 1 | J13: =IF(Verification!I13="",Calc!K13,Verification!I13) -> 1 | K13: =IF(COUNT(D13:E13)=0,"NA",(IF(ISNUMBER(D13),D13*Parameters!$E$6,0)+IF(ISNUMBER(E13),E13*Parameters!$E$7,0))/(IF(ISNUMBER(D13),Parameters!$E$6,0)+IF(ISNUMBER(E13),Parameters!$E$7,0))*100) -> 72.5 | L13: =IF(COUNT(F13:H13)=0,"NA",(IF(ISNUMBER(F13),F13*Parameters!$E$8,0)+IF(ISNUMBER(G13),G13*Parameters!$E$9,0)+IF(ISNUMBER(H13),H13*Parameters!$E$10,0))/(IF(ISNUMBER(F13),Parameters!$E$8,0)+IF(ISNUMBER(G13),Parameters!$E$9,0)+IF(ISNUMBER(H13),Parameters!$E$10,0))*100) -> 82.857143 | M13: =IF(COUNT(I13:J13)=0,"NA",(IF(ISNUMBER(I13),I13*Parameters!$E$11,0)+IF(ISNUMBER(J13),J13*Parameters!$E$12,0))/(IF(ISNUMBER(I13),Parameters!$E$11,0)+IF(ISNUMBER(J13),Parameters!$E$12,0))*100) -> 100 | N13: =IF(ISNUMBER(D13),Parameters!$E$6,0)+IF(ISNUMBER(E13),Parameters!$E$7,0)+IF(ISNUMBER(F13),Parameters!$E$8,0)+IF(ISNUMBER(G13),Parameters!$E$9,0)+IF(ISNUMBER(H13),Parameters!$E$10,0)+IF(ISNUMBER(I13),Parameters!$E$11,0)+IF(ISNUMBER(J13),Parameters!$E$12,0) -> 1 | O13: =IF(ISNUMBER(D13),D13*Parameters!$E$6,0)+IF(ISNUMBER(E13),E13*Parameters!$E$7,0)+IF(ISNUMBER(F13),F13*Parameters!$E$8,0)+IF(ISNUMBER(G13),G13*Parameters!$E$9,0)+IF(ISNUMBER(H13),H13*Parameters!$E$10,0)+IF(ISNUMBER(I13),I13*Parameters!$E$11,0)+IF(ISNUMBER(J13),J13*Parameters!$E$12,0) -> 0.8575 | P13: =COUNT(D13:J13) -> 7 | Q13: =(COUNT(D13:E13)>0)+(COUNT(F13:H13)>0)+(COUNT(I13:J13)>0) -> 3 | R13: =IF(AND(N13>=Parameters!$C$56,Q13>=Parameters!$C$59),"Yes","No") -> Yes | S13: =IF(R13="Yes",O13/N13*100,"NA") -> 85.75 | T13: =IF(R13="Yes",O13/Parameters!$E$13*100,"NA") -> 85.75 | U13: =IF(R13="Yes",(O13+(Parameters!$E$13-N13))/Parameters!$E$13*100,"NA") -> 85.75 | V13: =IF(R13<>"Yes","Not scored",IF(N13>=Parameters!$C$60,"Reportable","Provisional")) -> Reportable | W13: =IF(ISNUMBER(S13),RANK(S13,$S$2:$S$113,0),"NA") -> 28 | X13: =IF(N13>=Parameters!$C$60,"High",IF(N13>=Parameters!$C$56,"Medium","Low")) -> High | Y13: =Calc!T13 -> 0 | Z13: =IF(V13="Reportable",S13-ROW()*0.000000001,"") -> 85.75 | AA13: =IF(ISNUMBER(Z13),RANK(Z13,$Z$2:$Z$113,0),"NA") -> 17
... A113: =Data!$A113 -> Zotero | B113: =Data!$B113 -> Digital Scholar | C113: =Data!$E113 -> Annotations system | D113: =IF(Verification!C113="",Calc!B113,Verification!C113) -> 1 | E113: =IF(Verification!D113="",Calc!D113,Verification!D113) -> 0.5 | F113: =IF(Verification!E113="",Calc!G113,Verification!E113) -> 0.5 | G113: =IF(Verification!F113="",Calc!I113,Verification!F113) -> 0.5 | H113: =IF(Verification!G113="",Calc!E113,Verification!G113) -> 1 | I113: =IF(Verification!H113="",Calc!J113,Verification!H113) -> 1 | J113: =IF(Verification!I113="",Calc!K113,Verification!I113) -> 0.5 | K113: =IF(COUNT(D113:E113)=0,"NA",(IF(ISNUMBER(D113),D113*Parameters!$E$6,0)+IF(ISNUMBER(E113),E113*Parameters!$E$7,0))/(IF(ISNUMBER(D113),Parameters!$E$6,0)+IF(ISNUMBER(E113),Parameters!$E$7,0))*100) -> 63.333333 | L113: =IF(COUNT(F113:H113)=0,"NA",(IF(ISNUMBER(F113),F113*Parameters!$E$8,0)+IF(ISNUMBER(G113),G113*Parameters!$E$9,0)+IF(ISNUMBER(H113),H113*Parameters!$E$10,0))/(IF(ISNUMBER(F113),Parameters!$E$8,0)+IF(ISNUMBER(G113),Parameters!$E$9,0)+IF(ISNUMBER(H113),Parameters!$E$10,0))*100) -> 57.142857 | M113: =IF(COUNT(I113:J113)=0,"NA",(IF(ISNUMBER(I113),I113*Parameters!$E$11,0)+IF(ISNUMBER(J113),J113*Parameters!$E$12,0))/(IF(ISNUMBER(I113),Parameters!$E$11,0)+IF(ISNUMBER(J113),Parameters!$E$12,0))*100) -> 71.428571 | N113: =IF(ISNUMBER(D113),Parameters!$E$6,0)+IF(ISNUMBER(E113),Parameters!$E$7,0)+IF(ISNUMBER(F113),Parameters!$E$8,0)+IF(ISNUMBER(G113),Parameters!$E$9,0)+IF(ISNUMBER(H113),Parameters!$E$10,0)+IF(ISNUMBER(I113),Parameters!$E$11,0)+IF(ISNUMBER(J113),Parameters!$E$12,0) -> 1 | O113: =IF(ISNUMBER(D113),D113*Parameters!$E$6,0)+IF(ISNUMBER(E113),E113*Parameters!$E$7,0)+IF(ISNUMBER(F113),F113*Parameters!$E$8,0)+IF(ISNUMBER(G113),G113*Parameters!$E$9,0)+IF(ISNUMBER(H113),H113*Parameters!$E$10,0)+IF(ISNUMBER(I113),I113*Parameters!$E$11,0)+IF(ISNUMBER(J113),J113*Parameters!$E$12,0) -> 0.64 | P113: =COUNT(D113:J113) -> 7 | Q113: =(COUNT(D113:E113)>0)+(COUNT(F113:H113)>0)+(COUNT(I113:J113)>0) -> 3 | R113: =IF(AND(N113>=Parameters!$C$56,Q113>=Parameters!$C$59),"Yes","No") -> Yes | S113: =IF(R113="Yes",O113/N113*100,"NA") -> 64 | T113: =IF(R113="Yes",O113/Parameters!$E$13*100,"NA") -> 64 | U113: =IF(R113="Yes",(O113+(Parameters!$E$13-N113))/Parameters!$E$13*100,"NA") -> 64 | V113: =IF(R113<>"Yes","Not scored",IF(N113>=Parameters!$C$60,"Reportable","Provisional")) -> Reportable | W113: =IF(ISNUMBER(S113),RANK(S113,$S$2:$S$113,0),"NA") -> 63 | X113: =IF(N113>=Parameters!$C$60,"High",IF(N113>=Parameters!$C$56,"Medium","Low")) -> High | Y113: =Calc!T113 -> 0 | Z113: =IF(V113="Reportable",S113-ROW()*0.000000001,"") -> 64 | AA113: =IF(ISNUMBER(Z113),RANK(Z113,$Z$2:$Z$113,0),"NA") -> 37

Sheet Verification
A1: Service | B1: Verification status | C1: E1 override (037) | D1: E2 override (breadth) | E1: C1 override (040) | F1: C2 override (041) | G1: C3 override (019) | H1: G1 override (042) | I1: G2 override (048) | J1: Verified by | K1: Date verified | L1: Evidence / notes | M1: Open flags (count) | N1: Action required (auto)
A2: =Data!$A2 -> 2i2c | B2: Not started | M2: =Calc!T2 -> 1 | N2: =TRIM(IF(Calc!L2=1,"Engagement listed but 037 says Considering or lower; ","")&IF(Calc!M2=1,"CoC URL but status not Implemented; ","")&IF(Calc!N2=1,"Formal governance has no URL; ","")&IF(Calc!O2=1,"Governance blank but URL given; ","")&IF(Calc!P2=1,"Text/URL given but no engagement category coded (read manually); ","")&IF(Calc!Q2=1,"Check 041 URL; ","")&IF(Calc!R2=1,"039 says Considering/Not planning but contribution evidence exists; ","")&IF(Calc!S2=1,"No repo URL (manual check); ","")) -> Text/URL given but no engagement category coded (read manually);
A3: =Data!$A3 -> Academic Preservation Trust (APTrust) | B3: Not started | M3: =Calc!T3 -> 0 | N3: =TRIM(IF(Calc!L3=1,"Engagement listed but 037 says Considering or lower; ","")&IF(Calc!M3=1,"CoC URL but status not Implemented; ","")&IF(Calc!N3=1,"Formal governance has no URL; ","")&IF(Calc!O3=1,"Governance blank but URL given; ","")&IF(Calc!P3=1,"Text/URL given but no engagement category coded (read manually); ","")&IF(Calc!Q3=1,"Check 041 URL; ","")&IF(Calc!R3=1,"039 says Considering/Not planning but contribution evidence exists; ","")&IF(Calc!S3=1,"No repo URL (manual check); ",""))
A4: =Data!$A4 -> AfricArXiv | B4: Not started | M4: =Calc!T4 -> 1 | N4: =TRIM(IF(Calc!L4=1,"Engagement listed but 037 says Considering or lower; ","")&IF(Calc!M4=1,"CoC URL but status not Implemented; ","")&IF(Calc!N4=1,"Formal governance has no URL; ","")&IF(Calc!O4=1,"Governance blank but URL given; ","")&IF(Calc!P4=1,"Text/URL given but no engagement category coded (read manually); ","")&IF(Calc!Q4=1,"Check 041 URL; ","")&IF(Calc!R4=1,"039 says Considering/Not planning but contribution evidence exists; ","")&IF(Calc!S4=1,"No repo URL (manual check); ","")) -> No repo URL (manual check);
A5: =Data!$A5 -> Arches Heritage Data Management Platform | B5: Not started | M5: =Calc!T5 -> 1 | N5: =TRIM(IF(Calc!L5=1,"Engagement listed but 037 says Considering or lower; ","")&IF(Calc!M5=1,"CoC URL but status not Implemented; ","")&IF(Calc!N5=1,"Formal governance has no URL; ","")&IF(Calc!O5=1,"Governance blank but URL given; ","")&IF(Calc!P5=1,"Text/URL given but no engagement category coded (read manually); ","")&IF(Calc!Q5=1,"Check 041 URL; ","")&IF(Calc!R5=1,"039 says Considering/Not planning but contribution evidence exists; ","")&IF(Calc!S5=1,"No repo URL (manual check); ","")) -> Text/URL given but no engagement category coded (read manually);
A6: =Data!$A6 -> Archipelago Commons | B6: Not started | M6: =Calc!T6 -> 0 | N6: =TRIM(IF(Calc!L6=1,"Engagement listed but 037 says Considering or lower; ","")&IF(Calc!M6=1,"CoC URL but status not Implemented; ","")&IF(Calc!N6=1,"Formal governance has no URL; ","")&IF(Calc!O6=1,"Governance blank but URL given; ","")&IF(Calc!P6=1,"Text/URL given but no engagement category coded (read manually); ","")&IF(Calc!Q6=1,"Check 041 URL; ","")&IF(Calc!R6=1,"039 says Considering/Not planning but contribution evidence exists; ","")&IF(Calc!S6=1,"No repo URL (manual check); ",""))
A7: =Data!$A7 -> Archival Resource Key | B7: Not started | M7: =Calc!T7 -> 1 | N7: =TRIM(IF(Calc!L7=1,"Engagement listed but 037 says Considering or lower; ","")&IF(Calc!M7=1,"CoC URL but status not Implemented; ","")&IF(Calc!N7=1,"Formal governance has no URL; ","")&IF(Calc!O7=1,"Governance blank but URL given; ","")&IF(Calc!P7=1,"Text/URL given but no engagement category coded (read manually); ","")&IF(Calc!Q7=1,"Check 041 URL; ","")&IF(Calc!R7=1,"039 says Considering/Not planning but contribution evidence exists; ","")&IF(Calc!S7=1,"No repo URL (manual check); ","")) -> Text/URL given but no engagement category coded (read manually);
A8: =Data!$A8 -> Archivematica | B8: Not started | M8: =Calc!T8 -> 2 | N8: =TRIM(IF(Calc!L8=1,"Engagement listed but 037 says Considering or lower; ","")&IF(Calc!M8=1,"CoC URL but status not Implemented; ","")&IF(Calc!N8=1,"Formal governance has no URL; ","")&IF(Calc!O8=1,"Governance blank but URL given; ","")&IF(Calc!P8=1,"Text/URL given but no engagement category coded (read manually); ","")&IF(Calc!Q8=1,"Check 041 URL; ","")&IF(Calc!R8=1,"039 says Considering/Not planning but contribution evidence exists; ","")&IF(Calc!S8=1,"No repo URL (manual check); ","")) -> CoC URL but status not Implemented; Text/URL given but no engagement category coded (read manually);
A9: =Data!$A9 -> ArchivesSpace | B9: Not started | M9: =Calc!T9 -> 0 | N9: =TRIM(IF(Calc!L9=1,"Engagement listed but 037 says Considering or lower; ","")&IF(Calc!M9=1,"CoC URL but status not Implemented; ","")&IF(Calc!N9=1,"Formal governance has no URL; ","")&IF(Calc!O9=1,"Governance blank but URL given; ","")&IF(Calc!P9=1,"Text/URL given but no engagement category coded (read manually); ","")&IF(Calc!Q9=1,"Check 041 URL; ","")&IF(Calc!R9=1,"039 says Considering/Not planning but contribution evidence exists; ","")&IF(Calc!S9=1,"No repo URL (manual check); ",""))
A10: =Data!$A10 -> ARGOS | B10: Not started | M10: =Calc!T10 -> 0 | N10: =TRIM(IF(Calc!L10=1,"Engagement listed but 037 says Considering or lower; ","")&IF(Calc!M10=1,"CoC URL but status not Implemented; ","")&IF(Calc!N10=1,"Formal governance has no URL; ","")&IF(Calc!O10=1,"Governance blank but URL given; ","")&IF(Calc!P10=1,"Text/URL given but no engagement category coded (read manually); ","")&IF(Calc!Q10=1,"Check 041 URL; ","")&IF(Calc!R10=1,"039 says Considering/Not planning but contribution evidence exists; ","")&IF(Calc!S10=1,"No repo URL (manual check); ",""))
A11: =Data!$A11 -> arXiv | B11: Not started | M11: =Calc!T11 -> 0 | N11: =TRIM(IF(Calc!L11=1,"Engagement listed but 037 says Considering or lower; ","")&IF(Calc!M11=1,"CoC URL but status not Implemented; ","")&IF(Calc!N11=1,"Formal governance has no URL; ","")&IF(Calc!O11=1,"Governance blank but URL given; ","")&IF(Calc!P11=1,"Text/URL given but no engagement category coded (read manually); ","")&IF(Calc!Q11=1,"Check 041 URL; ","")&IF(Calc!R11=1,"039 says Considering/Not planning but contribution evidence exists; ","")&IF(Calc!S11=1,"No repo URL (manual check); ",""))
A12: =Data!$A12 -> AtoM | B12: Not started | M12: =Calc!T12 -> 2 | N12: =TRIM(IF(Calc!L12=1,"Engagement listed but 037 says Considering or lower; ","")&IF(Calc!M12=1,"CoC URL but status not Implemented; ","")&IF(Calc!N12=1,"Formal governance has no URL; ","")&IF(Calc!O12=1,"Governance blank but URL given; ","")&IF(Calc!P12=1,"Text/URL given but no engagement category coded (read manually); ","")&IF(Calc!Q12=1,"Check 041 URL; ","")&IF(Calc!R12=1,"039 says Considering/Not planning but contribution evidence exists; ","")&IF(Calc!S12=1,"No repo URL (manual check); ","")) -> CoC URL but status not Implemented; Check 041 URL;
A13: =Data!$A13 -> Avalon Media System | B13: Not started | M13: =Calc!T13 -> 0 | N13: =TRIM(IF(Calc!L13=1,"Engagement listed but 037 says Considering or lower; ","")&IF(Calc!M13=1,"CoC URL but status not Implemented; ","")&IF(Calc!N13=1,"Formal governance has no URL; ","")&IF(Calc!O13=1,"Governance blank but URL given; ","")&IF(Calc!P13=1,"Text/URL given but no engagement category coded (read manually); ","")&IF(Calc!Q13=1,"Check 041 URL; ","")&IF(Calc!R13=1,"039 says Considering/Not planning but contribution evidence exists; ","")&IF(Calc!S13=1,"No repo URL (manual check); ",""))
... A113: =Data!$A113 -> Zotero | B113: Not started | M113: =Calc!T113 -> 0 | N113: =TRIM(IF(Calc!L113=1,"Engagement listed but 037 says Considering or lower; ","")&IF(Calc!M113=1,"CoC URL but status not Implemented; ","")&IF(Calc!N113=1,"Formal governance has no URL; ","")&IF(Calc!O113=1,"Governance blank but URL given; ","")&IF(Calc!P113=1,"Text/URL given but no engagement category coded (read manually); ","")&IF(Calc!Q113=1,"Check 041 URL; ","")&IF(Calc!R113=1,"039 says Considering/Not planning but contribution evidence exists; ","")&IF(Calc!S113=1,"No repo URL (manual check); ",""))

Sheet Coding
A1: Service | B1: 038: Annual meetings | C1: 038: Blogs | D1: 038: Community calls | E1: 038: Conference participation | F1: 038: Development sprints | G1: 038: Interest, working, user, or advisory groups | H1: 038: Mailing lists and discussion forums (including Slack) | I1: 038: Social media | J1: 038: Staff roles with responsibility for community engagement | K1: 038: User research | L1: 038: Volunteer or ambassador network | M1: 038: Webinars and training | N1: 938: Annual meetings | O1: 938: Blogs | P1: 938: Community calls | Q1: 938: Conference participation | R1: 938: Development sprints | S1: 938: Interest, working, user, or advisory groups | T1: 938: Mailing lists and discussion forums (including Slack) | U1: 938: Social media | V1: 938: Staff roles with responsibility for community engagement | W1: 938: User research | X1: 938: Volunteer or ambassador network | Y1: 938: Webinars and training | Z1: 038 has "Other" | AA1: 938 text given | AB1: Checklist categories (n) | AC1: Union categories (n) | AD1: Added by 938 text only | AE1: "Other" credit (needs 938 text) | AF1: E2 category count (union) | AG1: E2 count, checklist only (sensitivity) | AH1: Both 038 and 938 filled | AI1: Coded cats also in checklist | AJ1: Coded cats NOT in checklist | AK1: Checklist cats (both-filled repos)
A2: =Data!$A2 -> 2i2c | B2: =IF(ISNUMBER(SEARCH(Dictionary!$A$5,Data!$H2)),1,0) -> 0 | C2: =IF(ISNUMBER(SEARCH(Dictionary!$A$6,Data!$H2)),1,0) -> 0 | D2: =IF(ISNUMBER(SEARCH(Dictionary!$A$7,Data!$H2)),1,0) -> 0 | E2: =IF(ISNUMBER(SEARCH(Dictionary!$A$8,Data!$H2)),1,0) -> 0 | F2: =IF(ISNUMBER(SEARCH(Dictionary!$A$9,Data!$H2)),1,0) -> 0 | G2: =IF(ISNUMBER(SEARCH(Dictionary!$A$10,Data!$H2)),1,0) -> 0 | H2: =IF(ISNUMBER(SEARCH(Dictionary!$A$11,Data!$H2)),1,0) -> 0 | I2: =IF(ISNUMBER(SEARCH(Dictionary!$A$12,Data!$H2)),1,0) -> 0 | J2: =IF(ISNUMBER(SEARCH(Dictionary!$A$13,Data!$H2)),1,0) -> 0 | K2: =IF(ISNUMBER(SEARCH(Dictionary!$A$14,Data!$H2)),1,0) -> 0 | L2: =IF(ISNUMBER(SEARCH(Dictionary!$A$15,Data!$H2)),1,0) -> 0 | M2: =IF(ISNUMBER(SEARCH(Dictionary!$A$16,Data!$H2)),1,0) -> 0 | N2: =IF(SUMPRODUCT((Dictionary!$C$5:$C$96=Dictionary!$A$5)*(Dictionary!$D$5:$D$96<>"")*ISNUMBER(SEARCH(Dictionary!$D$5:$D$96,Data!$I2)))>0,1,0) -> 0 | O2: =IF(SUMPRODUCT((Dictionary!$C$5:$C$96=Dictionary!$A$6)*(Dictionary!$D$5:$D$96<>"")*ISNUMBER(SEARCH(Dictionary!$D$5:$D$96,Data!$I2)))>0,1,0) -> 0 | P2: =IF(SUMPRODUCT((Dictionary!$C$5:$C$96=Dictionary!$A$7)*(Dictionary!$D$5:$D$96<>"")*ISNUMBER(SEARCH(Dictionary!$D$5:$D$96,Data!$I2)))>0,1,0) -> 0 | Q2: =IF(SUMPRODUCT((Dictionary!$C$5:$C$96=Dictionary!$A$8)*(Dictionary!$D$5:$D$96<>"")*ISNUMBER(SEARCH(Dictionary!$D$5:$D$96,Data!$I2)))>0,1,0) -> 0 | R2: =IF(SUMPRODUCT((Dictionary!$C$5:$C$96=Dictionary!$A$9)*(Dictionary!$D$5:$D$96<>"")*ISNUMBER(SEARCH(Dictionary!$D$5:$D$96,Data!$I2)))>0,1,0) -> 0 | S2: =IF(SUMPRODUCT((Dictionary!$C$5:$C$96=Dictionary!$A$10)*(Dictionary!$D$5:$D$96<>"")*ISNUMBER(SEARCH(Dictionary!$D$5:$D$96,Data!$I2)))>0,1,0) -> 0 | T2: =IF(SUMPRODUCT((Dictionary!$C$5:$C$96=Dictionary!$A$11)*(Dictionary!$D$5:$D$96<>"")*ISNUMBER(SEARCH(Dictionary!$D$5:$D$96,Data!$I2)))>0,1,0) -> 0 | U2: =IF(SUMPRODUCT((Dictionary!$C$5:$C$96=Dictionary!$A$12)*(Dictionary!$D$5:$D$96<>"")*ISNUMBER(SEARCH(Dictionary!$D$5:$D$96,Data!$I2)))>0,1,0) -> 0 | V2: =IF(SUMPRODUCT((Dictionary!$C$5:$C$96=Dictionary!$A$13)*(Dictionary!$D$5:$D$96<>"")*ISNUMBER(SEARCH(Dictionary!$D$5:$D$96,Data!$I2)))>0,1,0) -> 0 | W2: =IF(SUMPRODUCT((Dictionary!$C$5:$C$96=Dictionary!$A$14)*(Dictionary!$D$5:$D$96<>"")*ISNUMBER(SEARCH(Dictionary!$D$5:$D$96,Data!$I2)))>0,1,0) -> 0 | X2: =IF(SUMPRODUCT((Dictionary!$C$5:$C$96=Dictionary!$A$15)*(Dictionary!$D$5:$D$96<>"")*ISNUMBER(SEARCH(Dictionary!$D$5:$D$96,Data!$I2)))>0,1,0) -> 0 | Y2: =IF(SUMPRODUCT((Dictionary!$C$5:$C$96=Dictionary!$A$16)*(Dictionary!$D$5:$D$96<>"")*ISNUMBER(SEARCH(Dictionary!$D$5:$D$96,Data!$I2)))>0,1,0) -> 0 | Z2: =IF(ISNUMBER(SEARCH("Other",Data!$H2)),1,0) -> 0 | AA2: =IF(Data!$I2<>"",1,0) -> 1 | AB2: =SUM(B2:M2) -> 0 | AC2: =SUMPRODUCT(--((B2:M2+N2:Y2)>0)) -> 0 | AD2: =AC2-AB2 -> 0 | AE2: =IF(AND(Z2=1,AA2=1),1,0) -> 0 | AF2: =AC2+AE2 -> 0 | AG2: =AB2+AE2 -> 0 | AH2: =IF(AND(Data!$H2<>"",Data!$I2<>""),1,0) -> 0 | AI2: =IF(AH2=1,SUMPRODUCT(N2:Y2*B2:M2),"") | AJ2: =IF(AH2=1,SUMPRODUCT(--(N2:Y2>B2:M2)),"") | AK2: =IF(AH2=1,AB2,"")
A3: =Data!$A3 -> Academic Preservation Trust (APTrust) | B3: =IF(ISNUMBER(SEARCH(Dictionary!$A$5,Data!$H3)),1,0) -> 1 | C3: =IF(ISNUMBER(SEARCH(Dictionary!$A$6,Data!$H3)),1,0) -> 1 | D3: =IF(ISNUMBER(SEARCH(Dictionary!$A$7,Data!$H3)),1,0) -> 1 | E3: =IF(ISNUMBER(SEARCH(Dictionary!$A$8,Data!$H3)),1,0) -> 1 | F3: =IF(ISNUMBER(SEARCH(Dictionary!$A$9,Data!$H3)),1,0) -> 1 | G3: =IF(ISNUMBER(SEARCH(Dictionary!$A$10,Data!$H3)),1,0) -> 1 | H3: =IF(ISNUMBER(SEARCH(Dictionary!$A$11,Data!$H3)),1,0) -> 1 | I3: =IF(ISNUMBER(SEARCH(Dictionary!$A$12,Data!$H3)),1,0) -> 0 | J3: =IF(ISNUMBER(SEARCH(Dictionary!$A$13,Data!$H3)),1,0) -> 1 | K3: =IF(ISNUMBER(SEARCH(Dictionary!$A$14,Data!$H3)),1,0) -> 1 | L3: =IF(ISNUMBER(SEARCH(Dictionary!$A$15,Data!$H3)),1,0) -> 0 | M3: =IF(ISNUMBER(SEARCH(Dictionary!$A$16,Data!$H3)),1,0) -> 1 | N3: =IF(SUMPRODUCT((Dictionary!$C$5:$C$96=Dictionary!$A$5)*(Dictionary!$D$5:$D$96<>"")*ISNUMBER(SEARCH(Dictionary!$D$5:$D$96,Data!$I3)))>0,1,0) -> 0 | O3: =IF(SUMPRODUCT((Dictionary!$C$5:$C$96=Dictionary!$A$6)*(Dictionary!$D$5:$D$96<>"")*ISNUMBER(SEARCH(Dictionary!$D$5:$D$96,Data!$I3)))>0,1,0) -> 0 | P3: =IF(SUMPRODUCT((Dictionary!$C$5:$C$96=Dictionary!$A$7)*(Dictionary!$D$5:$D$96<>"")*ISNUMBER(SEARCH(Dictionary!$D$5:$D$96,Data!$I3)))>0,1,0) -> 0 | Q3: =IF(SUMPRODUCT((Dictionary!$C$5:$C$96=Dictionary!$A$8)*(Dictionary!$D$5:$D$96<>"")*ISNUMBER(SEARCH(Dictionary!$D$5:$D$96,Data!$I3)))>0,1,0) -> 0 | R3: =IF(SUMPRODUCT((Dictionary!$C$5:$C$96=Dictionary!$A$9)*(Dictionary!$D$5:$D$96<>"")*ISNUMBER(SEARCH(Dictionary!$D$5:$D$96,Data!$I3)))>0,1,0) -> 0 | S3: =IF(SUMPRODUCT((Dictionary!$C$5:$C$96=Dictionary!$A$10)*(Dictionary!$D$5:$D$96<>"")*ISNUMBER(SEARCH(Dictionary!$D$5:$D$96,Data!$I3)))>0,1,0) -> 0 | T3: =IF(SUMPRODUCT((Dictionary!$C$5:$C$96=Dictionary!$A$11)*(Dictionary!$D$5:$D$96<>"")*ISNUMBER(SEARCH(Dictionary!$D$5:$D$96,Data!$I3)))>0,1,0) -> 0 | U3: =IF(SUMPRODUCT((Dictionary!$C$5:$C$96=Dictionary!$A$12)*(Dictionary!$D$5:$D$96<>"")*ISNUMBER(SEARCH(Dictionary!$D$5:$D$96,Data!$I3)))>0,1,0) -> 0 | V3: =IF(SUMPRODUCT((Dictionary!$C$5:$C$96=Dictionary!$A$13)*(Dictionary!$D$5:$D$96<>"")*ISNUMBER(SEARCH(Dictionary!$D$5:$D$96,Data!$I3)))>0,1,0) -> 0 | W3: =IF(SUMPRODUCT((Dictionary!$C$5:$C$96=Dictionary!$A$14)*(Dictionary!$D$5:$D$96<>"")*ISNUMBER(SEARCH(Dictionary!$D$5:$D$96,Data!$I3)))>0,1,0) -> 0 | X3: =IF(SUMPRODUCT((Dictionary!$C$5:$C$96=Dictionary!$A$15)*(Dictionary!$D$5:$D$96<>"")*ISNUMBER(SEARCH(Dictionary!$D$5:$D$96,Data!$I3)))>0,1,0) -> 0 | Y3: =IF(SUMPRODUCT((Dictionary!$C$5:$C$96=Dictionary!$A$16)*(Dictionary!$D$5:$D$96<>"")*ISNUMBER(SEARCH(Dictionary!$D$5:$D$96,Data!$I3)))>0,1,0) -> 0 | Z3: =IF(ISNUMBER(SEARCH("Other",Data!$H3)),1,0) -> 0 | AA3: =IF(Data!$I3<>"",1,0) -> 0 | AB3: =SUM(B3:M3) -> 10 | AC3: =SUMPRODUCT(--((B3:M3+N3:Y3)>0)) -> 10 | AD3: =AC3-AB3 -> 0 | AE3: =IF(AND(Z3=1,AA3=1),1,0) -> 0 | AF3: =AC3+AE3 -> 10 | AG3: =AB3+AE3 -> 10 | AH3: =IF(AND(Data!$H3<>"",Data!$I3<>""),1,0) -> 0 | AI3: =IF(AH3=1,SUMPRODUCT(N3:Y3*B3:M3),"") | AJ3: =IF(AH3=1,SUMPRODUCT(--(N3:Y3>B3:M3)),"") | AK3: =IF(AH3=1,AB3,"")
A4: =Data!$A4 -> AfricArXiv | B4: =IF(ISNUMBER(SEARCH(Dictionary!$A$5,Data!$H4)),1,0) -> 0 | C4: =IF(ISNUMBER(SEARCH(Dictionary!$A$6,Data!$H4)),1,0) -> 0 | D4: =IF(ISNUMBER(SEARCH(Dictionary!$A$7,Data!$H4)),1,0) -> 0 | E4: =IF(ISNUMBER(SEARCH(Dictionary!$A$8,Data!$H4)),1,0) -> 0 | F4: =IF(ISNUMBER(SEARCH(Dictionary!$A$9,Data!$H4)),1,0) -> 0 | G4: =IF(ISNUMBER(SEARCH(Dictionary!$A$10,Data!$H4)),1,0) -> 0 | H4: =IF(ISNUMBER(SEARCH(Dictionary!$A$11,Data!$H4)),1,0) -> 0 | I4: =IF(ISNUMBER(SEARCH(Dictionary!$A$12,Data!$H4)),1,0) -> 0 | J4: =IF(ISNUMBER(SEARCH(Dictionary!$A$13,Data!$H4)),1,0) -> 0 | K4: =IF(ISNUMBER(SEARCH(Dictionary!$A$14,Data!$H4)),1,0) -> 0 | L4: =IF(ISNUMBER(SEARCH(Dictionary!$A$15,Data!$H4)),1,0) -> 0 | M4: =IF(ISNUMBER(SEARCH(Dictionary!$A$16,Data!$H4)),1,0) -> 0 | N4: =IF(SUMPRODUCT((Dictionary!$C$5:$C$96=Dictionary!$A$5)*(Dictionary!$D$5:$D$96<>"")*ISNUMBER(SEARCH(Dictionary!$D$5:$D$96,Data!$I4)))>0,1,0) -> 0 | O4: =IF(SUMPRODUCT((Dictionary!$C$5:$C$96=Dictionary!$A$6)*(Dictionary!$D$5:$D$96<>"")*ISNUMBER(SEARCH(Dictionary!$D$5:$D$96,Data!$I4)))>0,1,0) -> 0 | P4: =IF(SUMPRODUCT((Dictionary!$C$5:$C$96=Dictionary!$A$7)*(Dictionary!$D$5:$D$96<>"")*ISNUMBER(SEARCH(Dictionary!$D$5:$D$96,Data!$I4)))>0,1,0) -> 0 | Q4: =IF(SUMPRODUCT((Dictionary!$C$5:$C$96=Dictionary!$A$8)*(Dictionary!$D$5:$D$96<>"")*ISNUMBER(SEARCH(Dictionary!$D$5:$D$96,Data!$I4)))>0,1,0) -> 0 | R4: =IF(SUMPRODUCT((Dictionary!$C$5:$C$96=Dictionary!$A$9)*(Dictionary!$D$5:$D$96<>"")*ISNUMBER(SEARCH(Dictionary!$D$5:$D$96,Data!$I4)))>0,1,0) -> 0 | S4: =IF(SUMPRODUCT((Dictionary!$C$5:$C$96=Dictionary!$A$10)*(Dictionary!$D$5:$D$96<>"")*ISNUMBER(SEARCH(Dictionary!$D$5:$D$96,Data!$I4)))>0,1,0) -> 0 | T4: =IF(SUMPRODUCT((Dictionary!$C$5:$C$96=Dictionary!$A$11)*(Dictionary!$D$5:$D$96<>"")*ISNUMBER(SEARCH(Dictionary!$D$5:$D$96,Data!$I4)))>0,1,0) -> 0 | U4: =IF(SUMPRODUCT((Dictionary!$C$5:$C$96=Dictionary!$A$12)*(Dictionary!$D$5:$D$96<>"")*ISNUMBER(SEARCH(Dictionary!$D$5:$D$96,Data!$I4)))>0,1,0) -> 0 | V4: =IF(SUMPRODUCT((Dictionary!$C$5:$C$96=Dictionary!$A$13)*(Dictionary!$D$5:$D$96<>"")*ISNUMBER(SEARCH(Dictionary!$D$5:$D$96,Data!$I4)))>0,1,0) -> 0 | W4: =IF(SUMPRODUCT((Dictionary!$C$5:$C$96=Dictionary!$A$14)*(Dictionary!$D$5:$D$96<>"")*ISNUMBER(SEARCH(Dictionary!$D$5:$D$96,Data!$I4)))>0,1,0) -> 0 | X4: =IF(SUMPRODUCT((Dictionary!$C$5:$C$96=Dictionary!$A$15)*(Dictionary!$D$5:$D$96<>"")*ISNUMBER(SEARCH(Dictionary!$D$5:$D$96,Data!$I4)))>0,1,0) -> 0 | Y4: =IF(SUMPRODUCT((Dictionary!$C$5:$C$96=Dictionary!$A$16)*(Dictionary!$D$5:$D$96<>"")*ISNUMBER(SEARCH(Dictionary!$D$5:$D$96,Data!$I4)))>0,1,0) -> 0 | Z4: =IF(ISNUMBER(SEARCH("Other",Data!$H4)),1,0) -> 0 | AA4: =IF(Data!$I4<>"",1,0) -> 0 | AB4: =SUM(B4:M4) -> 0 | AC4: =SUMPRODUCT(--((B4:M4+N4:Y4)>0)) -> 0 | AD4: =AC4-AB4 -> 0 | AE4: =IF(AND(Z4=1,AA4=1),1,0) -> 0 | AF4: =AC4+AE4 -> 0 | AG4: =AB4+AE4 -> 0 | AH4: =IF(AND(Data!$H4<>"",Data!$I4<>""),1,0) -> 0 | AI4: =IF(AH4=1,SUMPRODUCT(N4:Y4*B4:M4),"") | AJ4: =IF(AH4=1,SUMPRODUCT(--(N4:Y4>B4:M4)),"") | AK4: =IF(AH4=1,AB4,"")
A5: =Data!$A5 -> Arches Heritage Data Management Platform | B5: =IF(ISNUMBER(SEARCH(Dictionary!$A$5,Data!$H5)),1,0) -> 0 | C5: =IF(ISNUMBER(SEARCH(Dictionary!$A$6,Data!$H5)),1,0) -> 0 | D5: =IF(ISNUMBER(SEARCH(Dictionary!$A$7,Data!$H5)),1,0) -> 0 | E5: =IF(ISNUMBER(SEARCH(Dictionary!$A$8,Data!$H5)),1,0) -> 0 | F5: =IF(ISNUMBER(SEARCH(Dictionary!$A$9,Data!$H5)),1,0) -> 0 | G5: =IF(ISNUMBER(SEARCH(Dictionary!$A$10,Data!$H5)),1,0) -> 0 | H5: =IF(ISNUMBER(SEARCH(Dictionary!$A$11,Data!$H5)),1,0) -> 0 | I5: =IF(ISNUMBER(SEARCH(Dictionary!$A$12,Data!$H5)),1,0) -> 0 | J5: =IF(ISNUMBER(SEARCH(Dictionary!$A$13,Data!$H5)),1,0) -> 0 | K5: =IF(ISNUMBER(SEARCH(Dictionary!$A$14,Data!$H5)),1,0) -> 0 | L5: =IF(ISNUMBER(SEARCH(Dictionary!$A$15,Data!$H5)),1,0) -> 0 | M5: =IF(ISNUMBER(SEARCH(Dictionary!$A$16,Data!$H5)),1,0) -> 0 | N5: =IF(SUMPRODUCT((Dictionary!$C$5:$C$96=Dictionary!$A$5)*(Dictionary!$D$5:$D$96<>"")*ISNUMBER(SEARCH(Dictionary!$D$5:$D$96,Data!$I5)))>0,1,0) -> 0 | O5: =IF(SUMPRODUCT((Dictionary!$C$5:$C$96=Dictionary!$A$6)*(Dictionary!$D$5:$D$96<>"")*ISNUMBER(SEARCH(Dictionary!$D$5:$D$96,Data!$I5)))>0,1,0) -> 0 | P5: =IF(SUMPRODUCT((Dictionary!$C$5:$C$96=Dictionary!$A$7)*(Dictionary!$D$5:$D$96<>"")*ISNUMBER(SEARCH(Dictionary!$D$5:$D$96,Data!$I5)))>0,1,0) -> 0 | Q5: =IF(SUMPRODUCT((Dictionary!$C$5:$C$96=Dictionary!$A$8)*(Dictionary!$D$5:$D$96<>"")*ISNUMBER(SEARCH(Dictionary!$D$5:$D$96,Data!$I5)))>0,1,0) -> 0 | R5: =IF(SUMPRODUCT((Dictionary!$C$5:$C$96=Dictionary!$A$9)*(Dictionary!$D$5:$D$96<>"")*ISNUMBER(SEARCH(Dictionary!$D$5:$D$96,Data!$I5)))>0,1,0) -> 0 | S5: =IF(SUMPRODUCT((Dictionary!$C$5:$C$96=Dictionary!$A$10)*(Dictionary!$D$5:$D$96<>"")*ISNUMBER(SEARCH(Dictionary!$D$5:$D$96,Data!$I5)))>0,1,0) -> 0 | T5: =IF(SUMPRODUCT((Dictionary!$C$5:$C$96=Dictionary!$A$11)*(Dictionary!$D$5:$D$96<>"")*ISNUMBER(SEARCH(Dictionary!$D$5:$D$96,Data!$I5)))>0,1,0) -> 0 | U5: =IF(SUMPRODUCT((Dictionary!$C$5:$C$96=Dictionary!$A$12)*(Dictionary!$D$5:$D$96<>"")*ISNUMBER(SEARCH(Dictionary!$D$5:$D$96,Data!$I5)))>0,1,0) -> 0 | V5: =IF(SUMPRODUCT((Dictionary!$C$5:$C$96=Dictionary!$A$13)*(Dictionary!$D$5:$D$96<>"")*ISNUMBER(SEARCH(Dictionary!$D$5:$D$96,Data!$I5)))>0,1,0) -> 0 | W5: =IF(SUMPRODUCT((Dictionary!$C$5:$C$96=Dictionary!$A$14)*(Dictionary!$D$5:$D$96<>"")*ISNUMBER(SEARCH(Dictionary!$D$5:$D$96,Data!$I5)))>0,1,0) -> 0 | X5: =IF(SUMPRODUCT((Dictionary!$C$5:$C$96=Dictionary!$A$15)*(Dictionary!$D$5:$D$96<>"")*ISNUMBER(SEARCH(Dictionary!$D$5:$D$96,Data!$I5)))>0,1,0) -> 0 | Y5: =IF(SUMPRODUCT((Dictionary!$C$5:$C$96=Dictionary!$A$16)*(Dictionary!$D$5:$D$96<>"")*ISNUMBER(SEARCH(Dictionary!$D$5:$D$96,Data!$I5)))>0,1,0) -> 0 | Z5: =IF(ISNUMBER(SEARCH("Other",Data!$H5)),1,0) -> 0 | AA5: =IF(Data!$I5<>"",1,0) -> 0 | AB5: =SUM(B5:M5) -> 0 | AC5: =SUMPRODUCT(--((B5:M5+N5:Y5)>0)) -> 0 | AD5: =AC5-AB5 -> 0 | AE5: =IF(AND(Z5=1,AA5=1),1,0) -> 0 | AF5: =AC5+AE5 -> 0 | AG5: =AB5+AE5 -> 0 | AH5: =IF(AND(Data!$H5<>"",Data!$I5<>""),1,0) -> 0 | AI5: =IF(AH5=1,SUMPRODUCT(N5:Y5*B5:M5),"") | AJ5: =IF(AH5=1,SUMPRODUCT(--(N5:Y5>B5:M5)),"") | AK5: =IF(AH5=1,AB5,"")
A6: =Data!$A6 -> Archipelago Commons | B6: =IF(ISNUMBER(SEARCH(Dictionary!$A$5,Data!$H6)),1,0) -> 0 | C6: =IF(ISNUMBER(SEARCH(Dictionary!$A$6,Data!$H6)),1,0) -> 0 | D6: =IF(ISNUMBER(SEARCH(Dictionary!$A$7,Data!$H6)),1,0) -> 1 | E6: =IF(ISNUMBER(SEARCH(Dictionary!$A$8,Data!$H6)),1,0) -> 1 | F6: =IF(ISNUMBER(SEARCH(Dictionary!$A$9,Data!$H6)),1,0) -> 0 | G6: =IF(ISNUMBER(SEARCH(Dictionary!$A$10,Data!$H6)),1,0) -> 1 | H6: =IF(ISNUMBER(SEARCH(Dictionary!$A$11,Data!$H6)),1,0) -> 1 | I6: =IF(ISNUMBER(SEARCH(Dictionary!$A$12,Data!$H6)),1,0) -> 0 | J6: =IF(ISNUMBER(SEARCH(Dictionary!$A$13,Data!$H6)),1,0) -> 1 | K6: =IF(ISNUMBER(SEARCH(Dictionary!$A$14,Data!$H6)),1,0) -> 0 | L6: =IF(ISNUMBER(SEARCH(Dictionary!$A$15,Data!$H6)),1,0) -> 1 | M6: =IF(ISNUMBER(SEARCH(Dictionary!$A$16,Data!$H6)),1,0) -> 1 | N6: =IF(SUMPRODUCT((Dictionary!$C$5:$C$96=Dictionary!$A$5)*(Dictionary!$D$5:$D$96<>"")*ISNUMBER(SEARCH(Dictionary!$D$5:$D$96,Data!$I6)))>0,1,0) -> 0 | O6: =IF(SUMPRODUCT((Dictionary!$C$5:$C$96=Dictionary!$A$6)*(Dictionary!$D$5:$D$96<>"")*ISNUMBER(SEARCH(Dictionary!$D$5:$D$96,Data!$I6)))>0,1,0) -> 0 | P6: =IF(SUMPRODUCT((Dictionary!$C$5:$C$96=Dictionary!$A$7)*(Dictionary!$D$5:$D$96<>"")*ISNUMBER(SEARCH(Dictionary!$D$5:$D$96,Data!$I6)))>0,1,0) -> 0 | Q6: =IF(SUMPRODUCT((Dictionary!$C$5:$C$96=Dictionary!$A$8)*(Dictionary!$D$5:$D$96<>"")*ISNUMBER(SEARCH(Dictionary!$D$5:$D$96,Data!$I6)))>0,1,0) -> 0 | R6: =IF(SUMPRODUCT((Dictionary!$C$5:$C$96=Dictionary!$A$9)*(Dictionary!$D$5:$D$96<>"")*ISNUMBER(SEARCH(Dictionary!$D$5:$D$96,Data!$I6)))>0,1,0) -> 0 | S6: =IF(SUMPRODUCT((Dictionary!$C$5:$C$96=Dictionary!$A$10)*(Dictionary!$D$5:$D$96<>"")*ISNUMBER(SEARCH(Dictionary!$D$5:$D$96,Data!$I6)))>0,1,0) -> 0 | T6: =IF(SUMPRODUCT((Dictionary!$C$5:$C$96=Dictionary!$A$11)*(Dictionary!$D$5:$D$96<>"")*ISNUMBER(SEARCH(Dictionary!$D$5:$D$96,Data!$I6)))>0,1,0) -> 1 | U6: =IF(SUMPRODUCT((Dictionary!$C$5:$C$96=Dictionary!$A$12)*(Dictionary!$D$5:$D$96<>"")*ISNUMBER(SEARCH(Dictionary!$D$5:$D$96,Data!$I6)))>0,1,0) -> 0 | V6: =IF(SUMPRODUCT((Dictionary!$C$5:$C$96=Dictionary!$A$13)*(Dictionary!$D$5:$D$96<>"")*ISNUMBER(SEARCH(Dictionary!$D$5:$D$96,Data!$I6)))>0,1,0) -> 0 | W6: =IF(SUMPRODUCT((Dictionary!$C$5:$C$96=Dictionary!$A$14)*(Dictionary!$D$5:$D$96<>"")*ISNUMBER(SEARCH(Dictionary!$D$5:$D$96,Data!$I6)))>0,1,0) -> 0 | X6: =IF(SUMPRODUCT((Dictionary!$C$5:$C$96=Dictionary!$A$15)*(Dictionary!$D$5:$D$96<>"")*ISNUMBER(SEARCH(Dictionary!$D$5:$D$96,Data!$I6)))>0,1,0) -> 0 | Y6: =IF(SUMPRODUCT((Dictionary!$C$5:$C$96=Dictionary!$A$16)*(Dictionary!$D$5:$D$96<>"")*ISNUMBER(SEARCH(Dictionary!$D$5:$D$96,Data!$I6)))>0,1,0) -> 0 | Z6: =IF(ISNUMBER(SEARCH("Other",Data!$H6)),1,0) -> 0 | AA6: =IF(Data!$I6<>"",1,0) -> 1 | AB6: =SUM(B6:M6) -> 7 | AC6: =SUMPRODUCT(--((B6:M6+N6:Y6)>0)) -> 7 | AD6: =AC6-AB6 -> 0 | AE6: =IF(AND(Z6=1,AA6=1),1,0) -> 0 | AF6: =AC6+AE6 -> 7 | AG6: =AB6+AE6 -> 7 | AH6: =IF(AND(Data!$H6<>"",Data!$I6<>""),1,0) -> 1 | AI6: =IF(AH6=1,SUMPRODUCT(N6:Y6*B6:M6),"") -> 1 | AJ6: =IF(AH6=1,SUMPRODUCT(--(N6:Y6>B6:M6)),"") -> 0 | AK6: =IF(AH6=1,AB6,"") -> 7
A7: =Data!$A7 -> Archival Resource Key | B7: =IF(ISNUMBER(SEARCH(Dictionary!$A$5,Data!$H7)),1,0) -> 0 | C7: =IF(ISNUMBER(SEARCH(Dictionary!$A$6,Data!$H7)),1,0) -> 0 | D7: =IF(ISNUMBER(SEARCH(Dictionary!$A$7,Data!$H7)),1,0) -> 0 | E7: =IF(ISNUMBER(SEARCH(Dictionary!$A$8,Data!$H7)),1,0) -> 0 | F7: =IF(ISNUMBER(SEARCH(Dictionary!$A$9,Data!$H7)),1,0) -> 0 | G7: =IF(ISNUMBER(SEARCH(Dictionary!$A$10,Data!$H7)),1,0) -> 0 | H7: =IF(ISNUMBER(SEARCH(Dictionary!$A$11,Data!$H7)),1,0) -> 0 | I7: =IF(ISNUMBER(SEARCH(Dictionary!$A$12,Data!$H7)),1,0) -> 0 | J7: =IF(ISNUMBER(SEARCH(Dictionary!$A$13,Data!$H7)),1,0) -> 0 | K7: =IF(ISNUMBER(SEARCH(Dictionary!$A$14,Data!$H7)),1,0) -> 0 | L7: =IF(ISNUMBER(SEARCH(Dictionary!$A$15,Data!$H7)),1,0) -> 0 | M7: =IF(ISNUMBER(SEARCH(Dictionary!$A$16,Data!$H7)),1,0) -> 0 | N7: =IF(SUMPRODUCT((Dictionary!$C$5:$C$96=Dictionary!$A$5)*(Dictionary!$D$5:$D$96<>"")*ISNUMBER(SEARCH(Dictionary!$D$5:$D$96,Data!$I7)))>0,1,0) -> 0 | O7: =IF(SUMPRODUCT((Dictionary!$C$5:$C$96=Dictionary!$A$6)*(Dictionary!$D$5:$D$96<>"")*ISNUMBER(SEARCH(Dictionary!$D$5:$D$96,Data!$I7)))>0,1,0) -> 0 | P7: =IF(SUMPRODUCT((Dictionary!$C$5:$C$96=Dictionary!$A$7)*(Dictionary!$D$5:$D$96<>"")*ISNUMBER(SEARCH(Dictionary!$D$5:$D$96,Data!$I7)))>0,1,0) -> 0 | Q7: =IF(SUMPRODUCT((Dictionary!$C$5:$C$96=Dictionary!$A$8)*(Dictionary!$D$5:$D$96<>"")*ISNUMBER(SEARCH(Dictionary!$D$5:$D$96,Data!$I7)))>0,1,0) -> 0 | R7: =IF(SUMPRODUCT((Dictionary!$C$5:$C$96=Dictionary!$A$9)*(Dictionary!$D$5:$D$96<>"")*ISNUMBER(SEARCH(Dictionary!$D$5:$D$96,Data!$I7)))>0,1,0) -> 0 | S7: =IF(SUMPRODUCT((Dictionary!$C$5:$C$96=Dictionary!$A$10)*(Dictionary!$D$5:$D$96<>"")*ISNUMBER(SEARCH(Dictionary!$D$5:$D$96,Data!$I7)))>0,1,0) -> 0 | T7: =IF(SUMPRODUCT((Dictionary!$C$5:$C$96=Dictionary!$A$11)*(Dictionary!$D$5:$D$96<>"")*ISNUMBER(SEARCH(Dictionary!$D$5:$D$96,Data!$I7)))>0,1,0) -> 0 | U7: =IF(SUMPRODUCT((Dictionary!$C$5:$C$96=Dictionary!$A$12)*(Dictionary!$D$5:$D$96<>"")*ISNUMBER(SEARCH(Dictionary!$D$5:$D$96,Data!$I7)))>0,1,0) -> 0 | V7: =IF(SUMPRODUCT((Dictionary!$C$5:$C$96=Dictionary!$A$13)*(Dictionary!$D$5:$D$96<>"")*ISNUMBER(SEARCH(Dictionary!$D$5:$D$96,Data!$I7)))>0,1,0) -> 0 | W7: =IF(SUMPRODUCT((Dictionary!$C$5:$C$96=Dictionary!$A$14)*(Dictionary!$D$5:$D$96<>"")*ISNUMBER(SEARCH(Dictionary!$D$5:$D$96,Data!$I7)))>0,1,0) -> 0 | X7: =IF(SUMPRODUCT((Dictionary!$C$5:$C$96=Dictionary!$A$15)*(Dictionary!$D$5:$D$96<>"")*ISNUMBER(SEARCH(Dictionary!$D$5:$D$96,Data!$I7)))>0,1,0) -> 0 | Y7: =IF(SUMPRODUCT((Dictionary!$C$5:$C$96=Dictionary!$A$16)*(Dictionary!$D$5:$D$96<>"")*ISNUMBER(SEARCH(Dictionary!$D$5:$D$96,Data!$I7)))>0,1,0) -> 0 | Z7: =IF(ISNUMBER(SEARCH("Other",Data!$H7)),1,0) -> 0 | AA7: =IF(Data!$I7<>"",1,0) -> 0 | AB7: =SUM(B7:M7) -> 0 | AC7: =SUMPRODUCT(--((B7:M7+N7:Y7)>0)) -> 0 | AD7: =AC7-AB7 -> 0 | AE7: =IF(AND(Z7=1,AA7=1),1,0) -> 0 | AF7: =AC7+AE7 -> 0 | AG7: =AB7+AE7 -> 0 | AH7: =IF(AND(Data!$H7<>"",Data!$I7<>""),1,0) -> 0 | AI7: =IF(AH7=1,SUMPRODUCT(N7:Y7*B7:M7),"") | AJ7: =IF(AH7=1,SUMPRODUCT(--(N7:Y7>B7:M7)),"") | AK7: =IF(AH7=1,AB7,"")
A8: =Data!$A8 -> Archivematica | B8: =IF(ISNUMBER(SEARCH(Dictionary!$A$5,Data!$H8)),1,0) -> 0 | C8: =IF(ISNUMBER(SEARCH(Dictionary!$A$6,Data!$H8)),1,0) -> 0 | D8: =IF(ISNUMBER(SEARCH(Dictionary!$A$7,Data!$H8)),1,0) -> 0 | E8: =IF(ISNUMBER(SEARCH(Dictionary!$A$8,Data!$H8)),1,0) -> 0 | F8: =IF(ISNUMBER(SEARCH(Dictionary!$A$9,Data!$H8)),1,0) -> 0 | G8: =IF(ISNUMBER(SEARCH(Dictionary!$A$10,Data!$H8)),1,0) -> 0 | H8: =IF(ISNUMBER(SEARCH(Dictionary!$A$11,Data!$H8)),1,0) -> 0 | I8: =IF(ISNUMBER(SEARCH(Dictionary!$A$12,Data!$H8)),1,0) -> 0 | J8: =IF(ISNUMBER(SEARCH(Dictionary!$A$13,Data!$H8)),1,0) -> 0 | K8: =IF(ISNUMBER(SEARCH(Dictionary!$A$14,Data!$H8)),1,0) -> 0 | L8: =IF(ISNUMBER(SEARCH(Dictionary!$A$15,Data!$H8)),1,0) -> 0 | M8: =IF(ISNUMBER(SEARCH(Dictionary!$A$16,Data!$H8)),1,0) -> 0 | N8: =IF(SUMPRODUCT((Dictionary!$C$5:$C$96=Dictionary!$A$5)*(Dictionary!$D$5:$D$96<>"")*ISNUMBER(SEARCH(Dictionary!$D$5:$D$96,Data!$I8)))>0,1,0) -> 0 | O8: =IF(SUMPRODUCT((Dictionary!$C$5:$C$96=Dictionary!$A$6)*(Dictionary!$D$5:$D$96<>"")*ISNUMBER(SEARCH(Dictionary!$D$5:$D$96,Data!$I8)))>0,1,0) -> 0 | P8: =IF(SUMPRODUCT((Dictionary!$C$5:$C$96=Dictionary!$A$7)*(Dictionary!$D$5:$D$96<>"")*ISNUMBER(SEARCH(Dictionary!$D$5:$D$96,Data!$I8)))>0,1,0) -> 0 | Q8: =IF(SUMPRODUCT((Dictionary!$C$5:$C$96=Dictionary!$A$8)*(Dictionary!$D$5:$D$96<>"")*ISNUMBER(SEARCH(Dictionary!$D$5:$D$96,Data!$I8)))>0,1,0) -> 0 | R8: =IF(SUMPRODUCT((Dictionary!$C$5:$C$96=Dictionary!$A$9)*(Dictionary!$D$5:$D$96<>"")*ISNUMBER(SEARCH(Dictionary!$D$5:$D$96,Data!$I8)))>0,1,0) -> 0 | S8: =IF(SUMPRODUCT((Dictionary!$C$5:$C$96=Dictionary!$A$10)*(Dictionary!$D$5:$D$96<>"")*ISNUMBER(SEARCH(Dictionary!$D$5:$D$96,Data!$I8)))>0,1,0) -> 0 | T8: =IF(SUMPRODUCT((Dictionary!$C$5:$C$96=Dictionary!$A$11)*(Dictionary!$D$5:$D$96<>"")*ISNUMBER(SEARCH(Dictionary!$D$5:$D$96,Data!$I8)))>0,1,0) -> 0 | U8: =IF(SUMPRODUCT((Dictionary!$C$5:$C$96=Dictionary!$A$12)*(Dictionary!$D$5:$D$96<>"")*ISNUMBER(SEARCH(Dictionary!$D$5:$D$96,Data!$I8)))>0,1,0) -> 0 | V8: =IF(SUMPRODUCT((Dictionary!$C$5:$C$96=Dictionary!$A$13)*(Dictionary!$D$5:$D$96<>"")*ISNUMBER(SEARCH(Dictionary!$D$5:$D$96,Data!$I8)))>0,1,0) -> 0 | W8: =IF(SUMPRODUCT((Dictionary!$C$5:$C$96=Dictionary!$A$14)*(Dictionary!$D$5:$D$96<>"")*ISNUMBER(SEARCH(Dictionary!$D$5:$D$96,Data!$I8)))>0,1,0) -> 0 | X8: =IF(SUMPRODUCT((Dictionary!$C$5:$C$96=Dictionary!$A$15)*(Dictionary!$D$5:$D$96<>"")*ISNUMBER(SEARCH(Dictionary!$D$5:$D$96,Data!$I8)))>0,1,0) -> 0 | Y8: =IF(SUMPRODUCT((Dictionary!$C$5:$C$96=Dictionary!$A$16)*(Dictionary!$D$5:$D$96<>"")*ISNUMBER(SEARCH(Dictionary!$D$5:$D$96,Data!$I8)))>0,1,0) -> 0 | Z8: =IF(ISNUMBER(SEARCH("Other",Data!$H8)),1,0) -> 0 | AA8: =IF(Data!$I8<>"",1,0) -> 0 | AB8: =SUM(B8:M8) -> 0 | AC8: =SUMPRODUCT(--((B8:M8+N8:Y8)>0)) -> 0 | AD8: =AC8-AB8 -> 0 | AE8: =IF(AND(Z8=1,AA8=1),1,0) -> 0 | AF8: =AC8+AE8 -> 0 | AG8: =AB8+AE8 -> 0 | AH8: =IF(AND(Data!$H8<>"",Data!$I8<>""),1,0) -> 0 | AI8: =IF(AH8=1,SUMPRODUCT(N8:Y8*B8:M8),"") | AJ8: =IF(AH8=1,SUMPRODUCT(--(N8:Y8>B8:M8)),"") | AK8: =IF(AH8=1,AB8,"")
A9: =Data!$A9 -> ArchivesSpace | B9: =IF(ISNUMBER(SEARCH(Dictionary!$A$5,Data!$H9)),1,0) -> 1 | C9: =IF(ISNUMBER(SEARCH(Dictionary!$A$6,Data!$H9)),1,0) -> 1 | D9: =IF(ISNUMBER(SEARCH(Dictionary!$A$7,Data!$H9)),1,0) -> 1 | E9: =IF(ISNUMBER(SEARCH(Dictionary!$A$8,Data!$H9)),1,0) -> 1 | F9: =IF(ISNUMBER(SEARCH(Dictionary!$A$9,Data!$H9)),1,0) -> 0 | G9: =IF(ISNUMBER(SEARCH(Dictionary!$A$10,Data!$H9)),1,0) -> 1 | H9: =IF(ISNUMBER(SEARCH(Dictionary!$A$11,Data!$H9)),1,0) -> 1 | I9: =IF(ISNUMBER(SEARCH(Dictionary!$A$12,Data!$H9)),1,0) -> 1 | J9: =IF(ISNUMBER(SEARCH(Dictionary!$A$13,Data!$H9)),1,0) -> 1 | K9: =IF(ISNUMBER(SEARCH(Dictionary!$A$14,Data!$H9)),1,0) -> 0 | L9: =IF(ISNUMBER(SEARCH(Dictionary!$A$15,Data!$H9)),1,0) -> 0 | M9: =IF(ISNUMBER(SEARCH(Dictionary!$A$16,Data!$H9)),1,0) -> 1 | N9: =IF(SUMPRODUCT((Dictionary!$C$5:$C$96=Dictionary!$A$5)*(Dictionary!$D$5:$D$96<>"")*ISNUMBER(SEARCH(Dictionary!$D$5:$D$96,Data!$I9)))>0,1,0) -> 0 | O9: =IF(SUMPRODUCT((Dictionary!$C$5:$C$96=Dictionary!$A$6)*(Dictionary!$D$5:$D$96<>"")*ISNUMBER(SEARCH(Dictionary!$D$5:$D$96,Data!$I9)))>0,1,0) -> 0 | P9: =IF(SUMPRODUCT((Dictionary!$C$5:$C$96=Dictionary!$A$7)*(Dictionary!$D$5:$D$96<>"")*ISNUMBER(SEARCH(Dictionary!$D$5:$D$96,Data!$I9)))>0,1,0) -> 0 | Q9: =IF(SUMPRODUCT((Dictionary!$C$5:$C$96=Dictionary!$A$8)*(Dictionary!$D$5:$D$96<>"")*ISNUMBER(SEARCH(Dictionary!$D$5:$D$96,Data!$I9)))>0,1,0) -> 0 | R9: =IF(SUMPRODUCT((Dictionary!$C$5:$C$96=Dictionary!$A$9)*(Dictionary!$D$5:$D$96<>"")*ISNUMBER(SEARCH(Dictionary!$D$5:$D$96,Data!$I9)))>0,1,0) -> 0 | S9: =IF(SUMPRODUCT((Dictionary!$C$5:$C$96=Dictionary!$A$10)*(Dictionary!$D$5:$D$96<>"")*ISNUMBER(SEARCH(Dictionary!$D$5:$D$96,Data!$I9)))>0,1,0) -> 0 | T9: =IF(SUMPRODUCT((Dictionary!$C$5:$C$96=Dictionary!$A$11)*(Dictionary!$D$5:$D$96<>"")*ISNUMBER(SEARCH(Dictionary!$D$5:$D$96,Data!$I9)))>0,1,0) -> 0 | U9: =IF(SUMPRODUCT((Dictionary!$C$5:$C$96=Dictionary!$A$12)*(Dictionary!$D$5:$D$96<>"")*ISNUMBER(SEARCH(Dictionary!$D$5:$D$96,Data!$I9)))>0,1,0) -> 0 | V9: =IF(SUMPRODUCT((Dictionary!$C$5:$C$96=Dictionary!$A$13)*(Dictionary!$D$5:$D$96<>"")*ISNUMBER(SEARCH(Dictionary!$D$5:$D$96,Data!$I9)))>0,1,0) -> 0 | W9: =IF(SUMPRODUCT((Dictionary!$C$5:$C$96=Dictionary!$A$14)*(Dictionary!$D$5:$D$96<>"")*ISNUMBER(SEARCH(Dictionary!$D$5:$D$96,Data!$I9)))>0,1,0) -> 0 | X9: =IF(SUMPRODUCT((Dictionary!$C$5:$C$96=Dictionary!$A$15)*(Dictionary!$D$5:$D$96<>"")*ISNUMBER(SEARCH(Dictionary!$D$5:$D$96,Data!$I9)))>0,1,0) -> 0 | Y9: =IF(SUMPRODUCT((Dictionary!$C$5:$C$96=Dictionary!$A$16)*(Dictionary!$D$5:$D$96<>"")*ISNUMBER(SEARCH(Dictionary!$D$5:$D$96,Data!$I9)))>0,1,0) -> 0 | Z9: =IF(ISNUMBER(SEARCH("Other",Data!$H9)),1,0) -> 0 | AA9: =IF(Data!$I9<>"",1,0) -> 0 | AB9: =SUM(B9:M9) -> 9 | AC9: =SUMPRODUCT(--((B9:M9+N9:Y9)>0)) -> 9 | AD9: =AC9-AB9 -> 0 | AE9: =IF(AND(Z9=1,AA9=1),1,0) -> 0 | AF9: =AC9+AE9 -> 9 | AG9: =AB9+AE9 -> 9 | AH9: =IF(AND(Data!$H9<>"",Data!$I9<>""),1,0) -> 0 | AI9: =IF(AH9=1,SUMPRODUCT(N9:Y9*B9:M9),"") | AJ9: =IF(AH9=1,SUMPRODUCT(--(N9:Y9>B9:M9)),"") | AK9: =IF(AH9=1,AB9,"")
A10: =Data!$A10 -> ARGOS | B10: =IF(ISNUMBER(SEARCH(Dictionary!$A$5,Data!$H10)),1,0) -> 0 | C10: =IF(ISNUMBER(SEARCH(Dictionary!$A$6,Data!$H10)),1,0) -> 1 | D10: =IF(ISNUMBER(SEARCH(Dictionary!$A$7,Data!$H10)),1,0) -> 1 | E10: =IF(ISNUMBER(SEARCH(Dictionary!$A$8,Data!$H10)),1,0) -> 1 | F10: =IF(ISNUMBER(SEARCH(Dictionary!$A$9,Data!$H10)),1,0) -> 1 | G10: =IF(ISNUMBER(SEARCH(Dictionary!$A$10,Data!$H10)),1,0) -> 1 | H10: =IF(ISNUMBER(SEARCH(Dictionary!$A$11,Data!$H10)),1,0) -> 0 | I10: =IF(ISNUMBER(SEARCH(Dictionary!$A$12,Data!$H10)),1,0) -> 1 | J10: =IF(ISNUMBER(SEARCH(Dictionary!$A$13,Data!$H10)),1,0) -> 1 | K10: =IF(ISNUMBER(SEARCH(Dictionary!$A$14,Data!$H10)),1,0) -> 0 | L10: =IF(ISNUMBER(SEARCH(Dictionary!$A$15,Data!$H10)),1,0) -> 0 | M10: =IF(ISNUMBER(SEARCH(Dictionary!$A$16,Data!$H10)),1,0) -> 1 | N10: =IF(SUMPRODUCT((Dictionary!$C$5:$C$96=Dictionary!$A$5)*(Dictionary!$D$5:$D$96<>"")*ISNUMBER(SEARCH(Dictionary!$D$5:$D$96,Data!$I10)))>0,1,0) -> 0 | O10: =IF(SUMPRODUCT((Dictionary!$C$5:$C$96=Dictionary!$A$6)*(Dictionary!$D$5:$D$96<>"")*ISNUMBER(SEARCH(Dictionary!$D$5:$D$96,Data!$I10)))>0,1,0) -> 0 | P10: =IF(SUMPRODUCT((Dictionary!$C$5:$C$96=Dictionary!$A$7)*(Dictionary!$D$5:$D$96<>"")*ISNUMBER(SEARCH(Dictionary!$D$5:$D$96,Data!$I10)))>0,1,0) -> 0 | Q10: =IF(SUMPRODUCT((Dictionary!$C$5:$C$96=Dictionary!$A$8)*(Dictionary!$D$5:$D$96<>"")*ISNUMBER(SEARCH(Dictionary!$D$5:$D$96,Data!$I10)))>0,1,0) -> 0 | R10: =IF(SUMPRODUCT((Dictionary!$C$5:$C$96=Dictionary!$A$9)*(Dictionary!$D$5:$D$96<>"")*ISNUMBER(SEARCH(Dictionary!$D$5:$D$96,Data!$I10)))>0,1,0) -> 0 | S10: =IF(SUMPRODUCT((Dictionary!$C$5:$C$96=Dictionary!$A$10)*(Dictionary!$D$5:$D$96<>"")*ISNUMBER(SEARCH(Dictionary!$D$5:$D$96,Data!$I10)))>0,1,0) -> 0 | T10: =IF(SUMPRODUCT((Dictionary!$C$5:$C$96=Dictionary!$A$11)*(Dictionary!$D$5:$D$96<>"")*ISNUMBER(SEARCH(Dictionary!$D$5:$D$96,Data!$I10)))>0,1,0) -> 0 | U10: =IF(SUMPRODUCT((Dictionary!$C$5:$C$96=Dictionary!$A$12)*(Dictionary!$D$5:$D$96<>"")*ISNUMBER(SEARCH(Dictionary!$D$5:$D$96,Data!$I10)))>0,1,0) -> 0 | V10: =IF(SUMPRODUCT((Dictionary!$C$5:$C$96=Dictionary!$A$13)*(Dictionary!$D$5:$D$96<>"")*ISNUMBER(SEARCH(Dictionary!$D$5:$D$96,Data!$I10)))>0,1,0) -> 0 | W10: =IF(SUMPRODUCT((Dictionary!$C$5:$C$96=Dictionary!$A$14)*(Dictionary!$D$5:$D$96<>"")*ISNUMBER(SEARCH(Dictionary!$D$5:$D$96,Data!$I10)))>0,1,0) -> 0 | X10: =IF(SUMPRODUCT((Dictionary!$C$5:$C$96=Dictionary!$A$15)*(Dictionary!$D$5:$D$96<>"")*ISNUMBER(SEARCH(Dictionary!$D$5:$D$96,Data!$I10)))>0,1,0) -> 0 | Y10: =IF(SUMPRODUCT((Dictionary!$C$5:$C$96=Dictionary!$A$16)*(Dictionary!$D$5:$D$96<>"")*ISNUMBER(SEARCH(Dictionary!$D$5:$D$96,Data!$I10)))>0,1,0) -> 0 | Z10: =IF(ISNUMBER(SEARCH("Other",Data!$H10)),1,0) -> 0 | AA10: =IF(Data!$I10<>"",1,0) -> 0 | AB10: =SUM(B10:M10) -> 8 | AC10: =SUMPRODUCT(--((B10:M10+N10:Y10)>0)) -> 8 | AD10: =AC10-AB10 -> 0 | AE10: =IF(AND(Z10=1,AA10=1),1,0) -> 0 | AF10: =AC10+AE10 -> 8 | AG10: =AB10+AE10 -> 8 | AH10: =IF(AND(Data!$H10<>"",Data!$I10<>""),1,0) -> 0 | AI10: =IF(AH10=1,SUMPRODUCT(N10:Y10*B10:M10),"") | AJ10: =IF(AH10=1,SUMPRODUCT(--(N10:Y10>B10:M10)),"") | AK10: =IF(AH10=1,AB10,"")
A11: =Data!$A11 -> arXiv | B11: =IF(ISNUMBER(SEARCH(Dictionary!$A$5,Data!$H11)),1,0) -> 0 | C11: =IF(ISNUMBER(SEARCH(Dictionary!$A$6,Data!$H11)),1,0) -> 0 | D11: =IF(ISNUMBER(SEARCH(Dictionary!$A$7,Data!$H11)),1,0) -> 0 | E11: =IF(ISNUMBER(SEARCH(Dictionary!$A$8,Data!$H11)),1,0) -> 0 | F11: =IF(ISNUMBER(SEARCH(Dictionary!$A$9,Data!$H11)),1,0) -> 0 | G11: =IF(ISNUMBER(SEARCH(Dictionary!$A$10,Data!$H11)),1,0) -> 0 | H11: =IF(ISNUMBER(SEARCH(Dictionary!$A$11,Data!$H11)),1,0) -> 0 | I11: =IF(ISNUMBER(SEARCH(Dictionary!$A$12,Data!$H11)),1,0) -> 0 | J11: =IF(ISNUMBER(SEARCH(Dictionary!$A$13,Data!$H11)),1,0) -> 0 | K11: =IF(ISNUMBER(SEARCH(Dictionary!$A$14,Data!$H11)),1,0) -> 0 | L11: =IF(ISNUMBER(SEARCH(Dictionary!$A$15,Data!$H11)),1,0) -> 0 | M11: =IF(ISNUMBER(SEARCH(Dictionary!$A$16,Data!$H11)),1,0) -> 0 | N11: =IF(SUMPRODUCT((Dictionary!$C$5:$C$96=Dictionary!$A$5)*(Dictionary!$D$5:$D$96<>"")*ISNUMBER(SEARCH(Dictionary!$D$5:$D$96,Data!$I11)))>0,1,0) -> 0 | O11: =IF(SUMPRODUCT((Dictionary!$C$5:$C$96=Dictionary!$A$6)*(Dictionary!$D$5:$D$96<>"")*ISNUMBER(SEARCH(Dictionary!$D$5:$D$96,Data!$I11)))>0,1,0) -> 0 | P11: =IF(SUMPRODUCT((Dictionary!$C$5:$C$96=Dictionary!$A$7)*(Dictionary!$D$5:$D$96<>"")*ISNUMBER(SEARCH(Dictionary!$D$5:$D$96,Data!$I11)))>0,1,0) -> 0 | Q11: =IF(SUMPRODUCT((Dictionary!$C$5:$C$96=Dictionary!$A$8)*(Dictionary!$D$5:$D$96<>"")*ISNUMBER(SEARCH(Dictionary!$D$5:$D$96,Data!$I11)))>0,1,0) -> 0 | R11: =IF(SUMPRODUCT((Dictionary!$C$5:$C$96=Dictionary!$A$9)*(Dictionary!$D$5:$D$96<>"")*ISNUMBER(SEARCH(Dictionary!$D$5:$D$96,Data!$I11)))>0,1,0) -> 0 | S11: =IF(SUMPRODUCT((Dictionary!$C$5:$C$96=Dictionary!$A$10)*(Dictionary!$D$5:$D$96<>"")*ISNUMBER(SEARCH(Dictionary!$D$5:$D$96,Data!$I11)))>0,1,0) -> 1 | T11: =IF(SUMPRODUCT((Dictionary!$C$5:$C$96=Dictionary!$A$11)*(Dictionary!$D$5:$D$96<>"")*ISNUMBER(SEARCH(Dictionary!$D$5:$D$96,Data!$I11)))>0,1,0) -> 0 | U11: =IF(SUMPRODUCT((Dictionary!$C$5:$C$96=Dictionary!$A$12)*(Dictionary!$D$5:$D$96<>"")*ISNUMBER(SEARCH(Dictionary!$D$5:$D$96,Data!$I11)))>0,1,0) -> 0 | V11: =IF(SUMPRODUCT((Dictionary!$C$5:$C$96=Dictionary!$A$13)*(Dictionary!$D$5:$D$96<>"")*ISNUMBER(SEARCH(Dictionary!$D$5:$D$96,Data!$I11)))>0,1,0) -> 0 | W11: =IF(SUMPRODUCT((Dictionary!$C$5:$C$96=Dictionary!$A$14)*(Dictionary!$D$5:$D$96<>"")*ISNUMBER(SEARCH(Dictionary!$D$5:$D$96,Data!$I11)))>0,1,0) -> 0 | X11: =IF(SUMPRODUCT((Dictionary!$C$5:$C$96=Dictionary!$A$15)*(Dictionary!$D$5:$D$96<>"")*ISNUMBER(SEARCH(Dictionary!$D$5:$D$96,Data!$I11)))>0,1,0) -> 0 | Y11: =IF(SUMPRODUCT((Dictionary!$C$5:$C$96=Dictionary!$A$16)*(Dictionary!$D$5:$D$96<>"")*ISNUMBER(SEARCH(Dictionary!$D$5:$D$96,Data!$I11)))>0,1,0) -> 0 | Z11: =IF(ISNUMBER(SEARCH("Other",Data!$H11)),1,0) -> 0 | AA11: =IF(Data!$I11<>"",1,0) -> 1 | AB11: =SUM(B11:M11) -> 0 | AC11: =SUMPRODUCT(--((B11:M11+N11:Y11)>0)) -> 1 | AD11: =AC11-AB11 -> 1 | AE11: =IF(AND(Z11=1,AA11=1),1,0) -> 0 | AF11: =AC11+AE11 -> 1 | AG11: =AB11+AE11 -> 0 | AH11: =IF(AND(Data!$H11<>"",Data!$I11<>""),1,0) -> 0 | AI11: =IF(AH11=1,SUMPRODUCT(N11:Y11*B11:M11),"") | AJ11: =IF(AH11=1,SUMPRODUCT(--(N11:Y11>B11:M11)),"") | AK11: =IF(AH11=1,AB11,"")
A12: =Data!$A12 -> AtoM | B12: =IF(ISNUMBER(SEARCH(Dictionary!$A$5,Data!$H12)),1,0) -> 0 | C12: =IF(ISNUMBER(SEARCH(Dictionary!$A$6,Data!$H12)),1,0) -> 0 | D12: =IF(ISNUMBER(SEARCH(Dictionary!$A$7,Data!$H12)),1,0) -> 0 | E12: =IF(ISNUMBER(SEARCH(Dictionary!$A$8,Data!$H12)),1,0) -> 0 | F12: =IF(ISNUMBER(SEARCH(Dictionary!$A$9,Data!$H12)),1,0) -> 0 | G12: =IF(ISNUMBER(SEARCH(Dictionary!$A$10,Data!$H12)),1,0) -> 0 | H12: =IF(ISNUMBER(SEARCH(Dictionary!$A$11,Data!$H12)),1,0) -> 0 | I12: =IF(ISNUMBER(SEARCH(Dictionary!$A$12,Data!$H12)),1,0) -> 0 | J12: =IF(ISNUMBER(SEARCH(Dictionary!$A$13,Data!$H12)),1,0) -> 0 | K12: =IF(ISNUMBER(SEARCH(Dictionary!$A$14,Data!$H12)),1,0) -> 0 | L12: =IF(ISNUMBER(SEARCH(Dictionary!$A$15,Data!$H12)),1,0) -> 0 | M12: =IF(ISNUMBER(SEARCH(Dictionary!$A$16,Data!$H12)),1,0) -> 0 | N12: =IF(SUMPRODUCT((Dictionary!$C$5:$C$96=Dictionary!$A$5)*(Dictionary!$D$5:$D$96<>"")*ISNUMBER(SEARCH(Dictionary!$D$5:$D$96,Data!$I12)))>0,1,0) -> 0 | O12: =IF(SUMPRODUCT((Dictionary!$C$5:$C$96=Dictionary!$A$6)*(Dictionary!$D$5:$D$96<>"")*ISNUMBER(SEARCH(Dictionary!$D$5:$D$96,Data!$I12)))>0,1,0) -> 0 | P12: =IF(SUMPRODUCT((Dictionary!$C$5:$C$96=Dictionary!$A$7)*(Dictionary!$D$5:$D$96<>"")*ISNUMBER(SEARCH(Dictionary!$D$5:$D$96,Data!$I12)))>0,1,0) -> 0 | Q12: =IF(SUMPRODUCT((Dictionary!$C$5:$C$96=Dictionary!$A$8)*(Dictionary!$D$5:$D$96<>"")*ISNUMBER(SEARCH(Dictionary!$D$5:$D$96,Data!$I12)))>0,1,0) -> 0 | R12: =IF(SUMPRODUCT((Dictionary!$C$5:$C$96=Dictionary!$A$9)*(Dictionary!$D$5:$D$96<>"")*ISNUMBER(SEARCH(Dictionary!$D$5:$D$96,Data!$I12)))>0,1,0) -> 0 | S12: =IF(SUMPRODUCT((Dictionary!$C$5:$C$96=Dictionary!$A$10)*(Dictionary!$D$5:$D$96<>"")*ISNUMBER(SEARCH(Dictionary!$D$5:$D$96,Data!$I12)))>0,1,0) -> 0 | T12: =IF(SUMPRODUCT((Dictionary!$C$5:$C$96=Dictionary!$A$11)*(Dictionary!$D$5:$D$96<>"")*ISNUMBER(SEARCH(Dictionary!$D$5:$D$96,Data!$I12)))>0,1,0) -> 0 | U12: =IF(SUMPRODUCT((Dictionary!$C$5:$C$96=Dictionary!$A$12)*(Dictionary!$D$5:$D$96<>"")*ISNUMBER(SEARCH(Dictionary!$D$5:$D$96,Data!$I12)))>0,1,0) -> 0 | V12: =IF(SUMPRODUCT((Dictionary!$C$5:$C$96=Dictionary!$A$13)*(Dictionary!$D$5:$D$96<>"")*ISNUMBER(SEARCH(Dictionary!$D$5:$D$96,Data!$I12)))>0,1,0) -> 0 | W12: =IF(SUMPRODUCT((Dictionary!$C$5:$C$96=Dictionary!$A$14)*(Dictionary!$D$5:$D$96<>"")*ISNUMBER(SEARCH(Dictionary!$D$5:$D$96,Data!$I12)))>0,1,0) -> 0 | X12: =IF(SUMPRODUCT((Dictionary!$C$5:$C$96=Dictionary!$A$15)*(Dictionary!$D$5:$D$96<>"")*ISNUMBER(SEARCH(Dictionary!$D$5:$D$96,Data!$I12)))>0,1,0) -> 0 | Y12: =IF(SUMPRODUCT((Dictionary!$C$5:$C$96=Dictionary!$A$16)*(Dictionary!$D$5:$D$96<>"")*ISNUMBER(SEARCH(Dictionary!$D$5:$D$96,Data!$I12)))>0,1,0) -> 0 | Z12: =IF(ISNUMBER(SEARCH("Other",Data!$H12)),1,0) -> 0 | AA12: =IF(Data!$I12<>"",1,0) -> 0 | AB12: =SUM(B12:M12) -> 0 | AC12: =SUMPRODUCT(--((B12:M12+N12:Y12)>0)) -> 0 | AD12: =AC12-AB12 -> 0 | AE12: =IF(AND(Z12=1,AA12=1),1,0) -> 0 | AF12: =AC12+AE12 -> 0 | AG12: =AB12+AE12 -> 0 | AH12: =IF(AND(Data!$H12<>"",Data!$I12<>""),1,0) -> 0 | AI12: =IF(AH12=1,SUMPRODUCT(N12:Y12*B12:M12),"") | AJ12: =IF(AH12=1,SUMPRODUCT(--(N12:Y12>B12:M12)),"") | AK12: =IF(AH12=1,AB12,"")
A13: =Data!$A13 -> Avalon Media System | B13: =IF(ISNUMBER(SEARCH(Dictionary!$A$5,Data!$H13)),1,0) -> 1 | C13: =IF(ISNUMBER(SEARCH(Dictionary!$A$6,Data!$H13)),1,0) -> 0 | D13: =IF(ISNUMBER(SEARCH(Dictionary!$A$7,Data!$H13)),1,0) -> 1 | E13: =IF(ISNUMBER(SEARCH(Dictionary!$A$8,Data!$H13)),1,0) -> 1 | F13: =IF(ISNUMBER(SEARCH(Dictionary!$A$9,Data!$H13)),1,0) -> 0 | G13: =IF(ISNUMBER(SEARCH(Dictionary!$A$10,Data!$H13)),1,0) -> 1 | H13: =IF(ISNUMBER(SEARCH(Dictionary!$A$11,Data!$H13)),1,0) -> 1 | I13: =IF(ISNUMBER(SEARCH(Dictionary!$A$12,Data!$H13)),1,0) -> 0 | J13: =IF(ISNUMBER(SEARCH(Dictionary!$A$13,Data!$H13)),1,0) -> 0 | K13: =IF(ISNUMBER(SEARCH(Dictionary!$A$14,Data!$H13)),1,0) -> 0 | L13: =IF(ISNUMBER(SEARCH(Dictionary!$A$15,Data!$H13)),1,0) -> 0 | M13: =IF(ISNUMBER(SEARCH(Dictionary!$A$16,Data!$H13)),1,0) -> 0 | N13: =IF(SUMPRODUCT((Dictionary!$C$5:$C$96=Dictionary!$A$5)*(Dictionary!$D$5:$D$96<>"")*ISNUMBER(SEARCH(Dictionary!$D$5:$D$96,Data!$I13)))>0,1,0) -> 0 | O13: =IF(SUMPRODUCT((Dictionary!$C$5:$C$96=Dictionary!$A$6)*(Dictionary!$D$5:$D$96<>"")*ISNUMBER(SEARCH(Dictionary!$D$5:$D$96,Data!$I13)))>0,1,0) -> 0 | P13: =IF(SUMPRODUCT((Dictionary!$C$5:$C$96=Dictionary!$A$7)*(Dictionary!$D$5:$D$96<>"")*ISNUMBER(SEARCH(Dictionary!$D$5:$D$96,Data!$I13)))>0,1,0) -> 0 | Q13: =IF(SUMPRODUCT((Dictionary!$C$5:$C$96=Dictionary!$A$8)*(Dictionary!$D$5:$D$96<>"")*ISNUMBER(SEARCH(Dictionary!$D$5:$D$96,Data!$I13)))>0,1,0) -> 0 | R13: =IF(SUMPRODUCT((Dictionary!$C$5:$C$96=Dictionary!$A$9)*(Dictionary!$D$5:$D$96<>"")*ISNUMBER(SEARCH(Dictionary!$D$5:$D$96,Data!$I13)))>0,1,0) -> 0 | S13: =IF(SUMPRODUCT((Dictionary!$C$5:$C$96=Dictionary!$A$10)*(Dictionary!$D$5:$D$96<>"")*ISNUMBER(SEARCH(Dictionary!$D$5:$D$96,Data!$I13)))>0,1,0) -> 0 | T13: =IF(SUMPRODUCT((Dictionary!$C$5:$C$96=Dictionary!$A$11)*(Dictionary!$D$5:$D$96<>"")*ISNUMBER(SEARCH(Dictionary!$D$5:$D$96,Data!$I13)))>0,1,0) -> 0 | U13: =IF(SUMPRODUCT((Dictionary!$C$5:$C$96=Dictionary!$A$12)*(Dictionary!$D$5:$D$96<>"")*ISNUMBER(SEARCH(Dictionary!$D$5:$D$96,Data!$I13)))>0,1,0) -> 0 | V13: =IF(SUMPRODUCT((Dictionary!$C$5:$C$96=Dictionary!$A$13)*(Dictionary!$D$5:$D$96<>"")*ISNUMBER(SEARCH(Dictionary!$D$5:$D$96,Data!$I13)))>0,1,0) -> 0 | W13: =IF(SUMPRODUCT((Dictionary!$C$5:$C$96=Dictionary!$A$14)*(Dictionary!$D$5:$D$96<>"")*ISNUMBER(SEARCH(Dictionary!$D$5:$D$96,Data!$I13)))>0,1,0) -> 0 | X13: =IF(SUMPRODUCT((Dictionary!$C$5:$C$96=Dictionary!$A$15)*(Dictionary!$D$5:$D$96<>"")*ISNUMBER(SEARCH(Dictionary!$D$5:$D$96,Data!$I13)))>0,1,0) -> 0 | Y13: =IF(SUMPRODUCT((Dictionary!$C$5:$C$96=Dictionary!$A$16)*(Dictionary!$D$5:$D$96<>"")*ISNUMBER(SEARCH(Dictionary!$D$5:$D$96,Data!$I13)))>0,1,0) -> 0 | Z13: =IF(ISNUMBER(SEARCH("Other",Data!$H13)),1,0) -> 0 | AA13: =IF(Data!$I13<>"",1,0) -> 0 | AB13: =SUM(B13:M13) -> 5 | AC13: =SUMPRODUCT(--((B13:M13+N13:Y13)>0)) -> 5 | AD13: =AC13-AB13 -> 0 | AE13: =IF(AND(Z13=1,AA13=1),1,0) -> 0 | AF13: =AC13+AE13 -> 5 | AG13: =AB13+AE13 -> 5 | AH13: =IF(AND(Data!$H13<>"",Data!$I13<>""),1,0) -> 0 | AI13: =IF(AH13=1,SUMPRODUCT(N13:Y13*B13:M13),"") | AJ13: =IF(AH13=1,SUMPRODUCT(--(N13:Y13>B13:M13)),"") | AK13: =IF(AH13=1,AB13,"")
... A113: =Data!$A113 -> Zotero | B113: =IF(ISNUMBER(SEARCH(Dictionary!$A$5,Data!$H113)),1,0) -> 0 | C113: =IF(ISNUMBER(SEARCH(Dictionary!$A$6,Data!$H113)),1,0) -> 1 | D113: =IF(ISNUMBER(SEARCH(Dictionary!$A$7,Data!$H113)),1,0) -> 0 | E113: =IF(ISNUMBER(SEARCH(Dictionary!$A$8,Data!$H113)),1,0) -> 0 | F113: =IF(ISNUMBER(SEARCH(Dictionary!$A$9,Data!$H113)),1,0) -> 0 | G113: =IF(ISNUMBER(SEARCH(Dictionary!$A$10,Data!$H113)),1,0) -> 0 | H113: =IF(ISNUMBER(SEARCH(Dictionary!$A$11,Data!$H113)),1,0) -> 1 | I113: =IF(ISNUMBER(SEARCH(Dictionary!$A$12,Data!$H113)),1,0) -> 1 | J113: =IF(ISNUMBER(SEARCH(Dictionary!$A$13,Data!$H113)),1,0) -> 1 | K113: =IF(ISNUMBER(SEARCH(Dictionary!$A$14,Data!$H113)),1,0) -> 0 | L113: =IF(ISNUMBER(SEARCH(Dictionary!$A$15,Data!$H113)),1,0) -> 0 | M113: =IF(ISNUMBER(SEARCH(Dictionary!$A$16,Data!$H113)),1,0) -> 0 | N113: =IF(SUMPRODUCT((Dictionary!$C$5:$C$96=Dictionary!$A$5)*(Dictionary!$D$5:$D$96<>"")*ISNUMBER(SEARCH(Dictionary!$D$5:$D$96,Data!$I113)))>0,1,0) -> 0 | O113: =IF(SUMPRODUCT((Dictionary!$C$5:$C$96=Dictionary!$A$6)*(Dictionary!$D$5:$D$96<>"")*ISNUMBER(SEARCH(Dictionary!$D$5:$D$96,Data!$I113)))>0,1,0) -> 0 | P113: =IF(SUMPRODUCT((Dictionary!$C$5:$C$96=Dictionary!$A$7)*(Dictionary!$D$5:$D$96<>"")*ISNUMBER(SEARCH(Dictionary!$D$5:$D$96,Data!$I113)))>0,1,0) -> 0 | Q113: =IF(SUMPRODUCT((Dictionary!$C$5:$C$96=Dictionary!$A$8)*(Dictionary!$D$5:$D$96<>"")*ISNUMBER(SEARCH(Dictionary!$D$5:$D$96,Data!$I113)))>0,1,0) -> 0 | R113: =IF(SUMPRODUCT((Dictionary!$C$5:$C$96=Dictionary!$A$9)*(Dictionary!$D$5:$D$96<>"")*ISNUMBER(SEARCH(Dictionary!$D$5:$D$96,Data!$I113)))>0,1,0) -> 0 | S113: =IF(SUMPRODUCT((Dictionary!$C$5:$C$96=Dictionary!$A$10)*(Dictionary!$D$5:$D$96<>"")*ISNUMBER(SEARCH(Dictionary!$D$5:$D$96,Data!$I113)))>0,1,0) -> 0 | T113: =IF(SUMPRODUCT((Dictionary!$C$5:$C$96=Dictionary!$A$11)*(Dictionary!$D$5:$D$96<>"")*ISNUMBER(SEARCH(Dictionary!$D$5:$D$96,Data!$I113)))>0,1,0) -> 0 | U113: =IF(SUMPRODUCT((Dictionary!$C$5:$C$96=Dictionary!$A$12)*(Dictionary!$D$5:$D$96<>"")*ISNUMBER(SEARCH(Dictionary!$D$5:$D$96,Data!$I113)))>0,1,0) -> 0 | V113: =IF(SUMPRODUCT((Dictionary!$C$5:$C$96=Dictionary!$A$13)*(Dictionary!$D$5:$D$96<>"")*ISNUMBER(SEARCH(Dictionary!$D$5:$D$96,Data!$I113)))>0,1,0) -> 0 | W113: =IF(SUMPRODUCT((Dictionary!$C$5:$C$96=Dictionary!$A$14)*(Dictionary!$D$5:$D$96<>"")*ISNUMBER(SEARCH(Dictionary!$D$5:$D$96,Data!$I113)))>0,1,0) -> 0 | X113: =IF(SUMPRODUCT((Dictionary!$C$5:$C$96=Dictionary!$A$15)*(Dictionary!$D$5:$D$96<>"")*ISNUMBER(SEARCH(Dictionary!$D$5:$D$96,Data!$I113)))>0,1,0) -> 0 | Y113: =IF(SUMPRODUCT((Dictionary!$C$5:$C$96=Dictionary!$A$16)*(Dictionary!$D$5:$D$96<>"")*ISNUMBER(SEARCH(Dictionary!$D$5:$D$96,Data!$I113)))>0,1,0) -> 0 | Z113: =IF(ISNUMBER(SEARCH("Other",Data!$H113)),1,0) -> 0 | AA113: =IF(Data!$I113<>"",1,0) -> 0 | AB113: =SUM(B113:M113) -> 4 | AC113: =SUMPRODUCT(--((B113:M113+N113:Y113)>0)) -> 4 | AD113: =AC113-AB113 -> 0 | AE113: =IF(AND(Z113=1,AA113=1),1,0) -> 0 | AF113: =AC113+AE113 -> 4 | AG113: =AB113+AE113 -> 4 | AH113: =IF(AND(Data!$H113<>"",Data!$I113<>""),1,0) -> 0 | AI113: =IF(AH113=1,SUMPRODUCT(N113:Y113*B113:M113),"") | AJ113: =IF(AH113=1,SUMPRODUCT(--(N113:Y113>B113:M113)),"") | AK113: =IF(AH113=1,AB113,"")

Sheet Calc
A1: Service | B1: 037 score (auto) | C1: E2 category count (union 038 + coded 938) | D1: E2 score (auto, gated) | E1: C3 score (auto, from 019) | F1: 040 category count | G1: C1 score (040, auto) | H1: 041 URL class | I1: C2 score (041, auto) | J1: G1 score (042, auto) | K1: G2 score (048, auto) | L1: FLAG 037 vs 038 conflict | M1: FLAG CoC URL but status ≠ Implemented | N1: FLAG Governance Formal, no URL | O1: FLAG Governance blank but URL present | P1: FLAG engagement text/URL given but no category coded | Q1: FLAG 041 suspect URL | R1: FLAG 039 contradicts contribution evidence | S1: FLAG no code-repo URL | T1: Flags (count) | U1: 040 count excl. funds | V1: 040 score excl. funds (sensitivity) | X1: Auto scores computed from Data + Parameters. Do not type here — enter verified values on the Verification sheet; Scoring uses them in preference to these auto values.
A2: =Data!$A2 -> 2i2c | B2: =IFERROR(INDEX(Parameters!$C$25:$C$28,MATCH(Data!$G2,Parameters!$B$25:$B$28,0)),"NA") -> 1 | C2: =IF(Coding!AF2=0,"",Coding!AF2) | D2: =IF(OR(C2="",C2=0),"NA",IF(AND(Parameters!$C$39=1,ISNUMBER(B2),B2<=Parameters!$C$40),0,MIN(C2,Parameters!$C$37)/Parameters!$C$37)) -> NA | E2: =IF(Data!$F2="","NA",IF(SUMPRODUCT((Parameters!$B$66:$B$70<>"")*ISNUMBER(SEARCH(Parameters!$B$66:$B$70,Data!$F2)))>0,Parameters!$C$63,Parameters!$C$64)) -> 1 | F2: =IF(OR(Data!$L2="",Data!$L2="Not applicable"),"",LEN(Data!$L2)-LEN(SUBSTITUTE(Data!$L2,"|",""))+1-IF(ISNUMBER(SEARCH("Other",Data!$L2)),1,0)-IF(ISNUMBER(SEARCH("Not applicable",Data!$L2)),1,0)+IF(AND(ISNUMBER(SEARCH("Other",Data!$L2)),Data!$M2<>""),1,0)) | G2: =IF(OR(F2="",F2=0),"NA",MIN(F2,Parameters!$C$38)/Parameters!$C$38) -> NA | H2: =IF(Data!$N2="","Blank",IF(SUMPRODUCT((Parameters!$B$49:$B$53<>"")*ISNUMBER(SEARCH(Parameters!$B$49:$B$53,Data!$N2)))>0,"CHECK: suspect URL",IF(ISNUMBER(SEARCH(Parameters!$C$46,Data!$N2)),"Contribution guide","Other page"))) -> Blank | I2: =IF(H2="Contribution guide",Parameters!$C$44,IF(H2="Other page",Parameters!$C$45,"NA")) -> NA | J2: =IFERROR(INDEX(Parameters!$C$25:$C$28,MATCH(Data!$O2,Parameters!$B$25:$B$28,0)),"NA") -> 1 | K2: =IFERROR(INDEX(Parameters!$C$32:$C$34,MATCH(Data!$Q2,Parameters!$B$32:$B$34,0)),"NA") -> NA | L2: =IF(AND(Coding!AF2>0,ISNUMBER(B2),B2<=Parameters!$C$40),1,0) -> 0 | M2: =IF(AND(Data!$P2<>"",NOT(AND(ISNUMBER(J2),J2=1))),1,0) -> 0 | N2: =IF(AND(Data!$Q2="Formal",Data!$R2=""),1,0) -> 0 | O2: =IF(AND(Data!$Q2="",Data!$R2<>""),1,0) -> 0 | P2: =IF(AND(ISNUMBER(B2),B2=1,Coding!AF2=0,OR(Data!$I2<>"",Data!$J2<>"")),1,0) -> 1 | Q2: =IF(H2="CHECK: suspect URL",1,0) -> 0 | R2: =IF(AND(OR(Data!$K2="Considering",Data!$K2="Not planning"),OR(AND(ISNUMBER(F2),F2>0),Data!$N2<>"")),1,0) -> 0 | S2: =IF(Data!$F2="",1,0) -> 0 | T2: =SUM(L2:S2) -> 1 | U2: =IF(ISNUMBER(F2),F2-IF(ISNUMBER(SEARCH("Contribute funds",Data!$L2)),1,0),"") | V2: =IF(ISNUMBER(U2),MIN(U2,Parameters!$C$38)/Parameters!$C$38,"NA") -> NA
A3: =Data!$A3 -> Academic Preservation Trust (APTrust) | B3: =IFERROR(INDEX(Parameters!$C$25:$C$28,MATCH(Data!$G3,Parameters!$B$25:$B$28,0)),"NA") -> 1 | C3: =IF(Coding!AF3=0,"",Coding!AF3) -> 10 | D3: =IF(OR(C3="",C3=0),"NA",IF(AND(Parameters!$C$39=1,ISNUMBER(B3),B3<=Parameters!$C$40),0,MIN(C3,Parameters!$C$37)/Parameters!$C$37)) -> 1 | E3: =IF(Data!$F3="","NA",IF(SUMPRODUCT((Parameters!$B$66:$B$70<>"")*ISNUMBER(SEARCH(Parameters!$B$66:$B$70,Data!$F3)))>0,Parameters!$C$63,Parameters!$C$64)) -> 1 | F3: =IF(OR(Data!$L3="",Data!$L3="Not applicable"),"",LEN(Data!$L3)-LEN(SUBSTITUTE(Data!$L3,"|",""))+1-IF(ISNUMBER(SEARCH("Other",Data!$L3)),1,0)-IF(ISNUMBER(SEARCH("Not applicable",Data!$L3)),1,0)+IF(AND(ISNUMBER(SEARCH("Other",Data!$L3)),Data!$M3<>""),1,0)) -> 7 | G3: =IF(OR(F3="",F3=0),"NA",MIN(F3,Parameters!$C$38)/Parameters!$C$38) -> 1 | H3: =IF(Data!$N3="","Blank",IF(SUMPRODUCT((Parameters!$B$49:$B$53<>"")*ISNUMBER(SEARCH(Parameters!$B$49:$B$53,Data!$N3)))>0,"CHECK: suspect URL",IF(ISNUMBER(SEARCH(Parameters!$C$46,Data!$N3)),"Contribution guide","Other page"))) -> Other page | I3: =IF(H3="Contribution guide",Parameters!$C$44,IF(H3="Other page",Parameters!$C$45,"NA")) -> 0.5 | J3: =IFERROR(INDEX(Parameters!$C$25:$C$28,MATCH(Data!$O3,Parameters!$B$25:$B$28,0)),"NA") -> 1 | K3: =IFERROR(INDEX(Parameters!$C$32:$C$34,MATCH(Data!$Q3,Parameters!$B$32:$B$34,0)),"NA") -> 1 | L3: =IF(AND(Coding!AF3>0,ISNUMBER(B3),B3<=Parameters!$C$40),1,0) -> 0 | M3: =IF(AND(Data!$P3<>"",NOT(AND(ISNUMBER(J3),J3=1))),1,0) -> 0 | N3: =IF(AND(Data!$Q3="Formal",Data!$R3=""),1,0) -> 0 | O3: =IF(AND(Data!$Q3="",Data!$R3<>""),1,0) -> 0 | P3: =IF(AND(ISNUMBER(B3),B3=1,Coding!AF3=0,OR(Data!$I3<>"",Data!$J3<>"")),1,0) -> 0 | Q3: =IF(H3="CHECK: suspect URL",1,0) -> 0 | R3: =IF(AND(OR(Data!$K3="Considering",Data!$K3="Not planning"),OR(AND(ISNUMBER(F3),F3>0),Data!$N3<>"")),1,0) -> 0 | S3: =IF(Data!$F3="",1,0) -> 0 | T3: =SUM(L3:S3) -> 0 | U3: =IF(ISNUMBER(F3),F3-IF(ISNUMBER(SEARCH("Contribute funds",Data!$L3)),1,0),"") -> 6 | V3: =IF(ISNUMBER(U3),MIN(U3,Parameters!$C$38)/Parameters!$C$38,"NA") -> 1
A4: =Data!$A4 -> AfricArXiv | B4: =IFERROR(INDEX(Parameters!$C$25:$C$28,MATCH(Data!$G4,Parameters!$B$25:$B$28,0)),"NA") -> 0.33 | C4: =IF(Coding!AF4=0,"",Coding!AF4) | D4: =IF(OR(C4="",C4=0),"NA",IF(AND(Parameters!$C$39=1,ISNUMBER(B4),B4<=Parameters!$C$40),0,MIN(C4,Parameters!$C$37)/Parameters!$C$37)) -> NA | E4: =IF(Data!$F4="","NA",IF(SUMPRODUCT((Parameters!$B$66:$B$70<>"")*ISNUMBER(SEARCH(Parameters!$B$66:$B$70,Data!$F4)))>0,Parameters!$C$63,Parameters!$C$64)) -> NA | F4: =IF(OR(Data!$L4="",Data!$L4="Not applicable"),"",LEN(Data!$L4)-LEN(SUBSTITUTE(Data!$L4,"|",""))+1-IF(ISNUMBER(SEARCH("Other",Data!$L4)),1,0)-IF(ISNUMBER(SEARCH("Not applicable",Data!$L4)),1,0)+IF(AND(ISNUMBER(SEARCH("Other",Data!$L4)),Data!$M4<>""),1,0)) | G4: =IF(OR(F4="",F4=0),"NA",MIN(F4,Parameters!$C$38)/Parameters!$C$38) -> NA | H4: =IF(Data!$N4="","Blank",IF(SUMPRODUCT((Parameters!$B$49:$B$53<>"")*ISNUMBER(SEARCH(Parameters!$B$49:$B$53,Data!$N4)))>0,"CHECK: suspect URL",IF(ISNUMBER(SEARCH(Parameters!$C$46,Data!$N4)),"Contribution guide","Other page"))) -> Blank | I4: =IF(H4="Contribution guide",Parameters!$C$44,IF(H4="Other page",Parameters!$C$45,"NA")) -> NA | J4: =IFERROR(INDEX(Parameters!$C$25:$C$28,MATCH(Data!$O4,Parameters!$B$25:$B$28,0)),"NA") -> 1 | K4: =IFERROR(INDEX(Parameters!$C$32:$C$34,MATCH(Data!$Q4,Parameters!$B$32:$B$34,0)),"NA") -> 0.5 | L4: =IF(AND(Coding!AF4>0,ISNUMBER(B4),B4<=Parameters!$C$40),1,0) -> 0 | M4: =IF(AND(Data!$P4<>"",NOT(AND(ISNUMBER(J4),J4=1))),1,0) -> 0 | N4: =IF(AND(Data!$Q4="Formal",Data!$R4=""),1,0) -> 0 | O4: =IF(AND(Data!$Q4="",Data!$R4<>""),1,0) -> 0 | P4: =IF(AND(ISNUMBER(B4),B4=1,Coding!AF4=0,OR(Data!$I4<>"",Data!$J4<>"")),1,0) -> 0 | Q4: =IF(H4="CHECK: suspect URL",1,0) -> 0 | R4: =IF(AND(OR(Data!$K4="Considering",Data!$K4="Not planning"),OR(AND(ISNUMBER(F4),F4>0),Data!$N4<>"")),1,0) -> 0 | S4: =IF(Data!$F4="",1,0) -> 1 | T4: =SUM(L4:S4) -> 1 | U4: =IF(ISNUMBER(F4),F4-IF(ISNUMBER(SEARCH("Contribute funds",Data!$L4)),1,0),"") | V4: =IF(ISNUMBER(U4),MIN(U4,Parameters!$C$38)/Parameters!$C$38,"NA") -> NA
A5: =Data!$A5 -> Arches Heritage Data Management Platform | B5: =IFERROR(INDEX(Parameters!$C$25:$C$28,MATCH(Data!$G5,Parameters!$B$25:$B$28,0)),"NA") -> 1 | C5: =IF(Coding!AF5=0,"",Coding!AF5) | D5: =IF(OR(C5="",C5=0),"NA",IF(AND(Parameters!$C$39=1,ISNUMBER(B5),B5<=Parameters!$C$40),0,MIN(C5,Parameters!$C$37)/Parameters!$C$37)) -> NA | E5: =IF(Data!$F5="","NA",IF(SUMPRODUCT((Parameters!$B$66:$B$70<>"")*ISNUMBER(SEARCH(Parameters!$B$66:$B$70,Data!$F5)))>0,Parameters!$C$63,Parameters!$C$64)) -> 1 | F5: =IF(OR(Data!$L5="",Data!$L5="Not applicable"),"",LEN(Data!$L5)-LEN(SUBSTITUTE(Data!$L5,"|",""))+1-IF(ISNUMBER(SEARCH("Other",Data!$L5)),1,0)-IF(ISNUMBER(SEARCH("Not applicable",Data!$L5)),1,0)+IF(AND(ISNUMBER(SEARCH("Other",Data!$L5)),Data!$M5<>""),1,0)) | G5: =IF(OR(F5="",F5=0),"NA",MIN(F5,Parameters!$C$38)/Parameters!$C$38) -> NA | H5: =IF(Data!$N5="","Blank",IF(SUMPRODUCT((Parameters!$B$49:$B$53<>"")*ISNUMBER(SEARCH(Parameters!$B$49:$B$53,Data!$N5)))>0,"CHECK: suspect URL",IF(ISNUMBER(SEARCH(Parameters!$C$46,Data!$N5)),"Contribution guide","Other page"))) -> Contribution guide | I5: =IF(H5="Contribution guide",Parameters!$C$44,IF(H5="Other page",Parameters!$C$45,"NA")) -> 1 | J5: =IFERROR(INDEX(Parameters!$C$25:$C$28,MATCH(Data!$O5,Parameters!$B$25:$B$28,0)),"NA") -> 1 | K5: =IFERROR(INDEX(Parameters!$C$32:$C$34,MATCH(Data!$Q5,Parameters!$B$32:$B$34,0)),"NA") -> 1 | L5: =IF(AND(Coding!AF5>0,ISNUMBER(B5),B5<=Parameters!$C$40),1,0) -> 0 | M5: =IF(AND(Data!$P5<>"",NOT(AND(ISNUMBER(J5),J5=1))),1,0) -> 0 | N5: =IF(AND(Data!$Q5="Formal",Data!$R5=""),1,0) -> 0 | O5: =IF(AND(Data!$Q5="",Data!$R5<>""),1,0) -> 0 | P5: =IF(AND(ISNUMBER(B5),B5=1,Coding!AF5=0,OR(Data!$I5<>"",Data!$J5<>"")),1,0) -> 1 | Q5: =IF(H5="CHECK: suspect URL",1,0) -> 0 | R5: =IF(AND(OR(Data!$K5="Considering",Data!$K5="Not planning"),OR(AND(ISNUMBER(F5),F5>0),Data!$N5<>"")),1,0) -> 0 | S5: =IF(Data!$F5="",1,0) -> 0 | T5: =SUM(L5:S5) -> 1 | U5: =IF(ISNUMBER(F5),F5-IF(ISNUMBER(SEARCH("Contribute funds",Data!$L5)),1,0),"") | V5: =IF(ISNUMBER(U5),MIN(U5,Parameters!$C$38)/Parameters!$C$38,"NA") -> NA
A6: =Data!$A6 -> Archipelago Commons | B6: =IFERROR(INDEX(Parameters!$C$25:$C$28,MATCH(Data!$G6,Parameters!$B$25:$B$28,0)),"NA") -> 1 | C6: =IF(Coding!AF6=0,"",Coding!AF6) -> 7 | D6: =IF(OR(C6="",C6=0),"NA",IF(AND(Parameters!$C$39=1,ISNUMBER(B6),B6<=Parameters!$C$40),0,MIN(C6,Parameters!$C$37)/Parameters!$C$37)) -> 0.875 | E6: =IF(Data!$F6="","NA",IF(SUMPRODUCT((Parameters!$B$66:$B$70<>"")*ISNUMBER(SEARCH(Parameters!$B$66:$B$70,Data!$F6)))>0,Parameters!$C$63,Parameters!$C$64)) -> 1 | F6: =IF(OR(Data!$L6="",Data!$L6="Not applicable"),"",LEN(Data!$L6)-LEN(SUBSTITUTE(Data!$L6,"|",""))+1-IF(ISNUMBER(SEARCH("Other",Data!$L6)),1,0)-IF(ISNUMBER(SEARCH("Not applicable",Data!$L6)),1,0)+IF(AND(ISNUMBER(SEARCH("Other",Data!$L6)),Data!$M6<>""),1,0)) -> 3 | G6: =IF(OR(F6="",F6=0),"NA",MIN(F6,Parameters!$C$38)/Parameters!$C$38) -> 0.5 | H6: =IF(Data!$N6="","Blank",IF(SUMPRODUCT((Parameters!$B$49:$B$53<>"")*ISNUMBER(SEARCH(Parameters!$B$49:$B$53,Data!$N6)))>0,"CHECK: suspect URL",IF(ISNUMBER(SEARCH(Parameters!$C$46,Data!$N6)),"Contribution guide","Other page"))) -> Other page | I6: =IF(H6="Contribution guide",Parameters!$C$44,IF(H6="Other page",Parameters!$C$45,"NA")) -> 0.5 | J6: =IFERROR(INDEX(Parameters!$C$25:$C$28,MATCH(Data!$O6,Parameters!$B$25:$B$28,0)),"NA") -> 1 | K6: =IFERROR(INDEX(Parameters!$C$32:$C$34,MATCH(Data!$Q6,Parameters!$B$32:$B$34,0)),"NA") -> 1 | L6: =IF(AND(Coding!AF6>0,ISNUMBER(B6),B6<=Parameters!$C$40),1,0) -> 0 | M6: =IF(AND(Data!$P6<>"",NOT(AND(ISNUMBER(J6),J6=1))),1,0) -> 0 | N6: =IF(AND(Data!$Q6="Formal",Data!$R6=""),1,0) -> 0 | O6: =IF(AND(Data!$Q6="",Data!$R6<>""),1,0) -> 0 | P6: =IF(AND(ISNUMBER(B6),B6=1,Coding!AF6=0,OR(Data!$I6<>"",Data!$J6<>"")),1,0) -> 0 | Q6: =IF(H6="CHECK: suspect URL",1,0) -> 0 | R6: =IF(AND(OR(Data!$K6="Considering",Data!$K6="Not planning"),OR(AND(ISNUMBER(F6),F6>0),Data!$N6<>"")),1,0) -> 0 | S6: =IF(Data!$F6="",1,0) -> 0 | T6: =SUM(L6:S6) -> 0 | U6: =IF(ISNUMBER(F6),F6-IF(ISNUMBER(SEARCH("Contribute funds",Data!$L6)),1,0),"") -> 3 | V6: =IF(ISNUMBER(U6),MIN(U6,Parameters!$C$38)/Parameters!$C$38,"NA") -> 0.5
A7: =Data!$A7 -> Archival Resource Key | B7: =IFERROR(INDEX(Parameters!$C$25:$C$28,MATCH(Data!$G7,Parameters!$B$25:$B$28,0)),"NA") -> 1 | C7: =IF(Coding!AF7=0,"",Coding!AF7) | D7: =IF(OR(C7="",C7=0),"NA",IF(AND(Parameters!$C$39=1,ISNUMBER(B7),B7<=Parameters!$C$40),0,MIN(C7,Parameters!$C$37)/Parameters!$C$37)) -> NA | E7: =IF(Data!$F7="","NA",IF(SUMPRODUCT((Parameters!$B$66:$B$70<>"")*ISNUMBER(SEARCH(Parameters!$B$66:$B$70,Data!$F7)))>0,Parameters!$C$63,Parameters!$C$64)) -> 1 | F7: =IF(OR(Data!$L7="",Data!$L7="Not applicable"),"",LEN(Data!$L7)-LEN(SUBSTITUTE(Data!$L7,"|",""))+1-IF(ISNUMBER(SEARCH("Other",Data!$L7)),1,0)-IF(ISNUMBER(SEARCH("Not applicable",Data!$L7)),1,0)+IF(AND(ISNUMBER(SEARCH("Other",Data!$L7)),Data!$M7<>""),1,0)) -> 5 | G7: =IF(OR(F7="",F7=0),"NA",MIN(F7,Parameters!$C$38)/Parameters!$C$38) -> 0.83333333 | H7: =IF(Data!$N7="","Blank",IF(SUMPRODUCT((Parameters!$B$49:$B$53<>"")*ISNUMBER(SEARCH(Parameters!$B$49:$B$53,Data!$N7)))>0,"CHECK: suspect URL",IF(ISNUMBER(SEARCH(Parameters!$C$46,Data!$N7)),"Contribution guide","Other page"))) -> Other page | I7: =IF(H7="Contribution guide",Parameters!$C$44,IF(H7="Other page",Parameters!$C$45,"NA")) -> 0.5 | J7: =IFERROR(INDEX(Parameters!$C$25:$C$28,MATCH(Data!$O7,Parameters!$B$25:$B$28,0)),"NA") -> 1 | K7: =IFERROR(INDEX(Parameters!$C$32:$C$34,MATCH(Data!$Q7,Parameters!$B$32:$B$34,0)),"NA") -> 0.5 | L7: =IF(AND(Coding!AF7>0,ISNUMBER(B7),B7<=Parameters!$C$40),1,0) -> 0 | M7: =IF(AND(Data!$P7<>"",NOT(AND(ISNUMBER(J7),J7=1))),1,0) -> 0 | N7: =IF(AND(Data!$Q7="Formal",Data!$R7=""),1,0) -> 0 | O7: =IF(AND(Data!$Q7="",Data!$R7<>""),1,0) -> 0 | P7: =IF(AND(ISNUMBER(B7),B7=1,Coding!AF7=0,OR(Data!$I7<>"",Data!$J7<>"")),1,0) -> 1 | Q7: =IF(H7="CHECK: suspect URL",1,0) -> 0 | R7: =IF(AND(OR(Data!$K7="Considering",Data!$K7="Not planning"),OR(AND(ISNUMBER(F7),F7>0),Data!$N7<>"")),1,0) -> 0 | S7: =IF(Data!$F7="",1,0) -> 0 | T7: =SUM(L7:S7) -> 1 | U7: =IF(ISNUMBER(F7),F7-IF(ISNUMBER(SEARCH("Contribute funds",Data!$L7)),1,0),"") -> 4 | V7: =IF(ISNUMBER(U7),MIN(U7,Parameters!$C$38)/Parameters!$C$38,"NA") -> 0.66666667
A8: =Data!$A8 -> Archivematica | B8: =IFERROR(INDEX(Parameters!$C$25:$C$28,MATCH(Data!$G8,Parameters!$B$25:$B$28,0)),"NA") -> 1 | C8: =IF(Coding!AF8=0,"",Coding!AF8) | D8: =IF(OR(C8="",C8=0),"NA",IF(AND(Parameters!$C$39=1,ISNUMBER(B8),B8<=Parameters!$C$40),0,MIN(C8,Parameters!$C$37)/Parameters!$C$37)) -> NA | E8: =IF(Data!$F8="","NA",IF(SUMPRODUCT((Parameters!$B$66:$B$70<>"")*ISNUMBER(SEARCH(Parameters!$B$66:$B$70,Data!$F8)))>0,Parameters!$C$63,Parameters!$C$64)) -> 1 | F8: =IF(OR(Data!$L8="",Data!$L8="Not applicable"),"",LEN(Data!$L8)-LEN(SUBSTITUTE(Data!$L8,"|",""))+1-IF(ISNUMBER(SEARCH("Other",Data!$L8)),1,0)-IF(ISNUMBER(SEARCH("Not applicable",Data!$L8)),1,0)+IF(AND(ISNUMBER(SEARCH("Other",Data!$L8)),Data!$M8<>""),1,0)) | G8: =IF(OR(F8="",F8=0),"NA",MIN(F8,Parameters!$C$38)/Parameters!$C$38) -> NA | H8: =IF(Data!$N8="","Blank",IF(SUMPRODUCT((Parameters!$B$49:$B$53<>"")*ISNUMBER(SEARCH(Parameters!$B$49:$B$53,Data!$N8)))>0,"CHECK: suspect URL",IF(ISNUMBER(SEARCH(Parameters!$C$46,Data!$N8)),"Contribution guide","Other page"))) -> Contribution guide | I8: =IF(H8="Contribution guide",Parameters!$C$44,IF(H8="Other page",Parameters!$C$45,"NA")) -> 1 | J8: =IFERROR(INDEX(Parameters!$C$25:$C$28,MATCH(Data!$O8,Parameters!$B$25:$B$28,0)),"NA") -> NA | K8: =IFERROR(INDEX(Parameters!$C$32:$C$34,MATCH(Data!$Q8,Parameters!$B$32:$B$34,0)),"NA") -> NA | L8: =IF(AND(Coding!AF8>0,ISNUMBER(B8),B8<=Parameters!$C$40),1,0) -> 0 | M8: =IF(AND(Data!$P8<>"",NOT(AND(ISNUMBER(J8),J8=1))),1,0) -> 1 | N8: =IF(AND(Data!$Q8="Formal",Data!$R8=""),1,0) -> 0 | O8: =IF(AND(Data!$Q8="",Data!$R8<>""),1,0) -> 0 | P8: =IF(AND(ISNUMBER(B8),B8=1,Coding!AF8=0,OR(Data!$I8<>"",Data!$J8<>"")),1,0) -> 1 | Q8: =IF(H8="CHECK: suspect URL",1,0) -> 0 | R8: =IF(AND(OR(Data!$K8="Considering",Data!$K8="Not planning"),OR(AND(ISNUMBER(F8),F8>0),Data!$N8<>"")),1,0) -> 0 | S8: =IF(Data!$F8="",1,0) -> 0 | T8: =SUM(L8:S8) -> 2 | U8: =IF(ISNUMBER(F8),F8-IF(ISNUMBER(SEARCH("Contribute funds",Data!$L8)),1,0),"") | V8: =IF(ISNUMBER(U8),MIN(U8,Parameters!$C$38)/Parameters!$C$38,"NA") -> NA
A9: =Data!$A9 -> ArchivesSpace | B9: =IFERROR(INDEX(Parameters!$C$25:$C$28,MATCH(Data!$G9,Parameters!$B$25:$B$28,0)),"NA") -> 1 | C9: =IF(Coding!AF9=0,"",Coding!AF9) -> 9 | D9: =IF(OR(C9="",C9=0),"NA",IF(AND(Parameters!$C$39=1,ISNUMBER(B9),B9<=Parameters!$C$40),0,MIN(C9,Parameters!$C$37)/Parameters!$C$37)) -> 1 | E9: =IF(Data!$F9="","NA",IF(SUMPRODUCT((Parameters!$B$66:$B$70<>"")*ISNUMBER(SEARCH(Parameters!$B$66:$B$70,Data!$F9)))>0,Parameters!$C$63,Parameters!$C$64)) -> 1 | F9: =IF(OR(Data!$L9="",Data!$L9="Not applicable"),"",LEN(Data!$L9)-LEN(SUBSTITUTE(Data!$L9,"|",""))+1-IF(ISNUMBER(SEARCH("Other",Data!$L9)),1,0)-IF(ISNUMBER(SEARCH("Not applicable",Data!$L9)),1,0)+IF(AND(ISNUMBER(SEARCH("Other",Data!$L9)),Data!$M9<>""),1,0)) | G9: =IF(OR(F9="",F9=0),"NA",MIN(F9,Parameters!$C$38)/Parameters!$C$38) -> NA | H9: =IF(Data!$N9="","Blank",IF(SUMPRODUCT((Parameters!$B$49:$B$53<>"")*ISNUMBER(SEARCH(Parameters!$B$49:$B$53,Data!$N9)))>0,"CHECK: suspect URL",IF(ISNUMBER(SEARCH(Parameters!$C$46,Data!$N9)),"Contribution guide","Other page"))) -> Contribution guide | I9: =IF(H9="Contribution guide",Parameters!$C$44,IF(H9="Other page",Parameters!$C$45,"NA")) -> 1 | J9: =IFERROR(INDEX(Parameters!$C$25:$C$28,MATCH(Data!$O9,Parameters!$B$25:$B$28,0)),"NA") -> 1 | K9: =IFERROR(INDEX(Parameters!$C$32:$C$34,MATCH(Data!$Q9,Parameters!$B$32:$B$34,0)),"NA") -> 1 | L9: =IF(AND(Coding!AF9>0,ISNUMBER(B9),B9<=Parameters!$C$40),1,0) -> 0 | M9: =IF(AND(Data!$P9<>"",NOT(AND(ISNUMBER(J9),J9=1))),1,0) -> 0 | N9: =IF(AND(Data!$Q9="Formal",Data!$R9=""),1,0) -> 0 | O9: =IF(AND(Data!$Q9="",Data!$R9<>""),1,0) -> 0 | P9: =IF(AND(ISNUMBER(B9),B9=1,Coding!AF9=0,OR(Data!$I9<>"",Data!$J9<>"")),1,0) -> 0 | Q9: =IF(H9="CHECK: suspect URL",1,0) -> 0 | R9: =IF(AND(OR(Data!$K9="Considering",Data!$K9="Not planning"),OR(AND(ISNUMBER(F9),F9>0),Data!$N9<>"")),1,0) -> 0 | S9: =IF(Data!$F9="",1,0) -> 0 | T9: =SUM(L9:S9) -> 0 | U9: =IF(ISNUMBER(F9),F9-IF(ISNUMBER(SEARCH("Contribute funds",Data!$L9)),1,0),"") | V9: =IF(ISNUMBER(U9),MIN(U9,Parameters!$C$38)/Parameters!$C$38,"NA") -> NA
A10: =Data!$A10 -> ARGOS | B10: =IFERROR(INDEX(Parameters!$C$25:$C$28,MATCH(Data!$G10,Parameters!$B$25:$B$28,0)),"NA") -> 1 | C10: =IF(Coding!AF10=0,"",Coding!AF10) -> 8 | D10: =IF(OR(C10="",C10=0),"NA",IF(AND(Parameters!$C$39=1,ISNUMBER(B10),B10<=Parameters!$C$40),0,MIN(C10,Parameters!$C$37)/Parameters!$C$37)) -> 1 | E10: =IF(Data!$F10="","NA",IF(SUMPRODUCT((Parameters!$B$66:$B$70<>"")*ISNUMBER(SEARCH(Parameters!$B$66:$B$70,Data!$F10)))>0,Parameters!$C$63,Parameters!$C$64)) -> 1 | F10: =IF(OR(Data!$L10="",Data!$L10="Not applicable"),"",LEN(Data!$L10)-LEN(SUBSTITUTE(Data!$L10,"|",""))+1-IF(ISNUMBER(SEARCH("Other",Data!$L10)),1,0)-IF(ISNUMBER(SEARCH("Not applicable",Data!$L10)),1,0)+IF(AND(ISNUMBER(SEARCH("Other",Data!$L10)),Data!$M10<>""),1,0)) | G10: =IF(OR(F10="",F10=0),"NA",MIN(F10,Parameters!$C$38)/Parameters!$C$38) -> NA | H10: =IF(Data!$N10="","Blank",IF(SUMPRODUCT((Parameters!$B$49:$B$53<>"")*ISNUMBER(SEARCH(Parameters!$B$49:$B$53,Data!$N10)))>0,"CHECK: suspect URL",IF(ISNUMBER(SEARCH(Parameters!$C$46,Data!$N10)),"Contribution guide","Other page"))) -> Blank | I10: =IF(H10="Contribution guide",Parameters!$C$44,IF(H10="Other page",Parameters!$C$45,"NA")) -> NA | J10: =IFERROR(INDEX(Parameters!$C$25:$C$28,MATCH(Data!$O10,Parameters!$B$25:$B$28,0)),"NA") -> 1 | K10: =IFERROR(INDEX(Parameters!$C$32:$C$34,MATCH(Data!$Q10,Parameters!$B$32:$B$34,0)),"NA") -> 1 | L10: =IF(AND(Coding!AF10>0,ISNUMBER(B10),B10<=Parameters!$C$40),1,0) -> 0 | M10: =IF(AND(Data!$P10<>"",NOT(AND(ISNUMBER(J10),J10=1))),1,0) -> 0 | N10: =IF(AND(Data!$Q10="Formal",Data!$R10=""),1,0) -> 0 | O10: =IF(AND(Data!$Q10="",Data!$R10<>""),1,0) -> 0 | P10: =IF(AND(ISNUMBER(B10),B10=1,Coding!AF10=0,OR(Data!$I10<>"",Data!$J10<>"")),1,0) -> 0 | Q10: =IF(H10="CHECK: suspect URL",1,0) -> 0 | R10: =IF(AND(OR(Data!$K10="Considering",Data!$K10="Not planning"),OR(AND(ISNUMBER(F10),F10>0),Data!$N10<>"")),1,0) -> 0 | S10: =IF(Data!$F10="",1,0) -> 0 | T10: =SUM(L10:S10) -> 0 | U10: =IF(ISNUMBER(F10),F10-IF(ISNUMBER(SEARCH("Contribute funds",Data!$L10)),1,0),"") | V10: =IF(ISNUMBER(U10),MIN(U10,Parameters!$C$38)/Parameters!$C$38,"NA") -> NA
A11: =Data!$A11 -> arXiv | B11: =IFERROR(INDEX(Parameters!$C$25:$C$28,MATCH(Data!$G11,Parameters!$B$25:$B$28,0)),"NA") -> 1 | C11: =IF(Coding!AF11=0,"",Coding!AF11) -> 1 | D11: =IF(OR(C11="",C11=0),"NA",IF(AND(Parameters!$C$39=1,ISNUMBER(B11),B11<=Parameters!$C$40),0,MIN(C11,Parameters!$C$37)/Parameters!$C$37)) -> 0.125 | E11: =IF(Data!$F11="","NA",IF(SUMPRODUCT((Parameters!$B$66:$B$70<>"")*ISNUMBER(SEARCH(Parameters!$B$66:$B$70,Data!$F11)))>0,Parameters!$C$63,Parameters!$C$64)) -> 1 | F11: =IF(OR(Data!$L11="",Data!$L11="Not applicable"),"",LEN(Data!$L11)-LEN(SUBSTITUTE(Data!$L11,"|",""))+1-IF(ISNUMBER(SEARCH("Other",Data!$L11)),1,0)-IF(ISNUMBER(SEARCH("Not applicable",Data!$L11)),1,0)+IF(AND(ISNUMBER(SEARCH("Other",Data!$L11)),Data!$M11<>""),1,0)) -> 3 | G11: =IF(OR(F11="",F11=0),"NA",MIN(F11,Parameters!$C$38)/Parameters!$C$38) -> 0.5 | H11: =IF(Data!$N11="","Blank",IF(SUMPRODUCT((Parameters!$B$49:$B$53<>"")*ISNUMBER(SEARCH(Parameters!$B$49:$B$53,Data!$N11)))>0,"CHECK: suspect URL",IF(ISNUMBER(SEARCH(Parameters!$C$46,Data!$N11)),"Contribution guide","Other page"))) -> Other page | I11: =IF(H11="Contribution guide",Parameters!$C$44,IF(H11="Other page",Parameters!$C$45,"NA")) -> 0.5 | J11: =IFERROR(INDEX(Parameters!$C$25:$C$28,MATCH(Data!$O11,Parameters!$B$25:$B$28,0)),"NA") -> 1 | K11: =IFERROR(INDEX(Parameters!$C$32:$C$34,MATCH(Data!$Q11,Parameters!$B$32:$B$34,0)),"NA") -> 1 | L11: =IF(AND(Coding!AF11>0,ISNUMBER(B11),B11<=Parameters!$C$40),1,0) -> 0 | M11: =IF(AND(Data!$P11<>"",NOT(AND(ISNUMBER(J11),J11=1))),1,0) -> 0 | N11: =IF(AND(Data!$Q11="Formal",Data!$R11=""),1,0) -> 0 | O11: =IF(AND(Data!$Q11="",Data!$R11<>""),1,0) -> 0 | P11: =IF(AND(ISNUMBER(B11),B11=1,Coding!AF11=0,OR(Data!$I11<>"",Data!$J11<>"")),1,0) -> 0 | Q11: =IF(H11="CHECK: suspect URL",1,0) -> 0 | R11: =IF(AND(OR(Data!$K11="Considering",Data!$K11="Not planning"),OR(AND(ISNUMBER(F11),F11>0),Data!$N11<>"")),1,0) -> 0 | S11: =IF(Data!$F11="",1,0) -> 0 | T11: =SUM(L11:S11) -> 0 | U11: =IF(ISNUMBER(F11),F11-IF(ISNUMBER(SEARCH("Contribute funds",Data!$L11)),1,0),"") -> 2 | V11: =IF(ISNUMBER(U11),MIN(U11,Parameters!$C$38)/Parameters!$C$38,"NA") -> 0.33333333
A12: =Data!$A12 -> AtoM | B12: =IFERROR(INDEX(Parameters!$C$25:$C$28,MATCH(Data!$G12,Parameters!$B$25:$B$28,0)),"NA") -> 0.67 | C12: =IF(Coding!AF12=0,"",Coding!AF12) | D12: =IF(OR(C12="",C12=0),"NA",IF(AND(Parameters!$C$39=1,ISNUMBER(B12),B12<=Parameters!$C$40),0,MIN(C12,Parameters!$C$37)/Parameters!$C$37)) -> NA | E12: =IF(Data!$F12="","NA",IF(SUMPRODUCT((Parameters!$B$66:$B$70<>"")*ISNUMBER(SEARCH(Parameters!$B$66:$B$70,Data!$F12)))>0,Parameters!$C$63,Parameters!$C$64)) -> 1 | F12: =IF(OR(Data!$L12="",Data!$L12="Not applicable"),"",LEN(Data!$L12)-LEN(SUBSTITUTE(Data!$L12,"|",""))+1-IF(ISNUMBER(SEARCH("Other",Data!$L12)),1,0)-IF(ISNUMBER(SEARCH("Not applicable",Data!$L12)),1,0)+IF(AND(ISNUMBER(SEARCH("Other",Data!$L12)),Data!$M12<>""),1,0)) | G12: =IF(OR(F12="",F12=0),"NA",MIN(F12,Parameters!$C$38)/Parameters!$C$38) -> NA | H12: =IF(Data!$N12="","Blank",IF(SUMPRODUCT((Parameters!$B$49:$B$53<>"")*ISNUMBER(SEARCH(Parameters!$B$49:$B$53,Data!$N12)))>0,"CHECK: suspect URL",IF(ISNUMBER(SEARCH(Parameters!$C$46,Data!$N12)),"Contribution guide","Other page"))) -> CHECK: suspect URL | I12: =IF(H12="Contribution guide",Parameters!$C$44,IF(H12="Other page",Parameters!$C$45,"NA")) -> NA | J12: =IFERROR(INDEX(Parameters!$C$25:$C$28,MATCH(Data!$O12,Parameters!$B$25:$B$28,0)),"NA") -> NA | K12: =IFERROR(INDEX(Parameters!$C$32:$C$34,MATCH(Data!$Q12,Parameters!$B$32:$B$34,0)),"NA") -> NA | L12: =IF(AND(Coding!AF12>0,ISNUMBER(B12),B12<=Parameters!$C$40),1,0) -> 0 | M12: =IF(AND(Data!$P12<>"",NOT(AND(ISNUMBER(J12),J12=1))),1,0) -> 1 | N12: =IF(AND(Data!$Q12="Formal",Data!$R12=""),1,0) -> 0 | O12: =IF(AND(Data!$Q12="",Data!$R12<>""),1,0) -> 0 | P12: =IF(AND(ISNUMBER(B12),B12=1,Coding!AF12=0,OR(Data!$I12<>"",Data!$J12<>"")),1,0) -> 0 | Q12: =IF(H12="CHECK: suspect URL",1,0) -> 1 | R12: =IF(AND(OR(Data!$K12="Considering",Data!$K12="Not planning"),OR(AND(ISNUMBER(F12),F12>0),Data!$N12<>"")),1,0) -> 0 | S12: =IF(Data!$F12="",1,0) -> 0 | T12: =SUM(L12:S12) -> 2 | U12: =IF(ISNUMBER(F12),F12-IF(ISNUMBER(SEARCH("Contribute funds",Data!$L12)),1,0),"") | V12: =IF(ISNUMBER(U12),MIN(U12,Parameters!$C$38)/Parameters!$C$38,"NA") -> NA
A13: =Data!$A13 -> Avalon Media System | B13: =IFERROR(INDEX(Parameters!$C$25:$C$28,MATCH(Data!$G13,Parameters!$B$25:$B$28,0)),"NA") -> 1 | C13: =IF(Coding!AF13=0,"",Coding!AF13) -> 5 | D13: =IF(OR(C13="",C13=0),"NA",IF(AND(Parameters!$C$39=1,ISNUMBER(B13),B13<=Parameters!$C$40),0,MIN(C13,Parameters!$C$37)/Parameters!$C$37)) -> 0.625 | E13: =IF(Data!$F13="","NA",IF(SUMPRODUCT((Parameters!$B$66:$B$70<>"")*ISNUMBER(SEARCH(Parameters!$B$66:$B$70,Data!$F13)))>0,Parameters!$C$63,Parameters!$C$64)) -> 1 | F13: =IF(OR(Data!$L13="",Data!$L13="Not applicable"),"",LEN(Data!$L13)-LEN(SUBSTITUTE(Data!$L13,"|",""))+1-IF(ISNUMBER(SEARCH("Other",Data!$L13)),1,0)-IF(ISNUMBER(SEARCH("Not applicable",Data!$L13)),1,0)+IF(AND(ISNUMBER(SEARCH("Other",Data!$L13)),Data!$M13<>""),1,0)) -> 6 | G13: =IF(OR(F13="",F13=0),"NA",MIN(F13,Parameters!$C$38)/Parameters!$C$38) -> 1 | H13: =IF(Data!$N13="","Blank",IF(SUMPRODUCT((Parameters!$B$49:$B$53<>"")*ISNUMBER(SEARCH(Parameters!$B$49:$B$53,Data!$N13)))>0,"CHECK: suspect URL",IF(ISNUMBER(SEARCH(Parameters!$C$46,Data!$N13)),"Contribution guide","Other page"))) -> Other page | I13: =IF(H13="Contribution guide",Parameters!$C$44,IF(H13="Other page",Parameters!$C$45,"NA")) -> 0.5 | J13: =IFERROR(INDEX(Parameters!$C$25:$C$28,MATCH(Data!$O13,Parameters!$B$25:$B$28,0)),"NA") -> 1 | K13: =IFERROR(INDEX(Parameters!$C$32:$C$34,MATCH(Data!$Q13,Parameters!$B$32:$B$34,0)),"NA") -> 1 | L13: =IF(AND(Coding!AF13>0,ISNUMBER(B13),B13<=Parameters!$C$40),1,0) -> 0 | M13: =IF(AND(Data!$P13<>"",NOT(AND(ISNUMBER(J13),J13=1))),1,0) -> 0 | N13: =IF(AND(Data!$Q13="Formal",Data!$R13=""),1,0) -> 0 | O13: =IF(AND(Data!$Q13="",Data!$R13<>""),1,0) -> 0 | P13: =IF(AND(ISNUMBER(B13),B13=1,Coding!AF13=0,OR(Data!$I13<>"",Data!$J13<>"")),1,0) -> 0 | Q13: =IF(H13="CHECK: suspect URL",1,0) -> 0 | R13: =IF(AND(OR(Data!$K13="Considering",Data!$K13="Not planning"),OR(AND(ISNUMBER(F13),F13>0),Data!$N13<>"")),1,0) -> 0 | S13: =IF(Data!$F13="",1,0) -> 0 | T13: =SUM(L13:S13) -> 0 | U13: =IF(ISNUMBER(F13),F13-IF(ISNUMBER(SEARCH("Contribute funds",Data!$L13)),1,0),"") -> 5 | V13: =IF(ISNUMBER(U13),MIN(U13,Parameters!$C$38)/Parameters!$C$38,"NA") -> 0.83333333
... A113: =Data!$A113 -> Zotero | B113: =IFERROR(INDEX(Parameters!$C$25:$C$28,MATCH(Data!$G113,Parameters!$B$25:$B$28,0)),"NA") -> 1 | C113: =IF(Coding!AF113=0,"",Coding!AF113) -> 4 | D113: =IF(OR(C113="",C113=0),"NA",IF(AND(Parameters!$C$39=1,ISNUMBER(B113),B113<=Parameters!$C$40),0,MIN(C113,Parameters!$C$37)/Parameters!$C$37)) -> 0.5 | E113: =IF(Data!$F113="","NA",IF(SUMPRODUCT((Parameters!$B$66:$B$70<>"")*ISNUMBER(SEARCH(Parameters!$B$66:$B$70,Data!$F113)))>0,Parameters!$C$63,Parameters!$C$64)) -> 1 | F113: =IF(OR(Data!$L113="",Data!$L113="Not applicable"),"",LEN(Data!$L113)-LEN(SUBSTITUTE(Data!$L113,"|",""))+1-IF(ISNUMBER(SEARCH("Other",Data!$L113)),1,0)-IF(ISNUMBER(SEARCH("Not applicable",Data!$L113)),1,0)+IF(AND(ISNUMBER(SEARCH("Other",Data!$L113)),Data!$M113<>""),1,0)) -> 3 | G113: =IF(OR(F113="",F113=0),"NA",MIN(F113,Parameters!$C$38)/Parameters!$C$38) -> 0.5 | H113: =IF(Data!$N113="","Blank",IF(SUMPRODUCT((Parameters!$B$49:$B$53<>"")*ISNUMBER(SEARCH(Parameters!$B$49:$B$53,Data!$N113)))>0,"CHECK: suspect URL",IF(ISNUMBER(SEARCH(Parameters!$C$46,Data!$N113)),"Contribution guide","Other page"))) -> Other page | I113: =IF(H113="Contribution guide",Parameters!$C$44,IF(H113="Other page",Parameters!$C$45,"NA")) -> 0.5 | J113: =IFERROR(INDEX(Parameters!$C$25:$C$28,MATCH(Data!$O113,Parameters!$B$25:$B$28,0)),"NA") -> 1 | K113: =IFERROR(INDEX(Parameters!$C$32:$C$34,MATCH(Data!$Q113,Parameters!$B$32:$B$34,0)),"NA") -> 0.5 | L113: =IF(AND(Coding!AF113>0,ISNUMBER(B113),B113<=Parameters!$C$40),1,0) -> 0 | M113: =IF(AND(Data!$P113<>"",NOT(AND(ISNUMBER(J113),J113=1))),1,0) -> 0 | N113: =IF(AND(Data!$Q113="Formal",Data!$R113=""),1,0) -> 0 | O113: =IF(AND(Data!$Q113="",Data!$R113<>""),1,0) -> 0 | P113: =IF(AND(ISNUMBER(B113),B113=1,Coding!AF113=0,OR(Data!$I113<>"",Data!$J113<>"")),1,0) -> 0 | Q113: =IF(H113="CHECK: suspect URL",1,0) -> 0 | R113: =IF(AND(OR(Data!$K113="Considering",Data!$K113="Not planning"),OR(AND(ISNUMBER(F113),F113>0),Data!$N113<>"")),1,0) -> 0 | S113: =IF(Data!$F113="",1,0) -> 0 | T113: =SUM(L113:S113) -> 0 | U113: =IF(ISNUMBER(F113),F113-IF(ISNUMBER(SEARCH("Contribute funds",Data!$L113)),1,0),"") -> 2 | V113: =IF(ISNUMBER(U113),MIN(U113,Parameters!$C$38)/Parameters!$C$38,"NA") -> 0.33333333

Sheet Sensitivity
A1: Service | B1: BASE score (primary threshold) | C1: Threshold – lower | D1: Threshold – higher | E1: E2 checklist only (938 not used) | F1: Equal metric weights | G1: C1 excluding "Contribute funds" | H1: Shrinkage toward median (completeness-weighted) | I1: Require 038 or 040 to be scored | J1: |Δ| lower thr | K1: |Δ| higher thr | L1: |Δ| checklist only | M1: |Δ| equal weights | N1: |Δ| excl. funds | O1: |Δ| shrinkage | P1: |Δ| require 038/040
A2: =Data!$A2 -> 2i2c | B2: =Scoring!S2 -> NA | C2: =IF(AND(Scoring!N2>=Parameters!$C$57,Scoring!Q2>=Parameters!$C$59),Scoring!O2/Scoring!N2*100,"NA") -> NA | D2: =IF(AND(Scoring!N2>=Parameters!$C$58,Scoring!Q2>=Parameters!$C$59),Scoring!O2/Scoring!N2*100,"NA") -> NA | E2: =IF(AND((Scoring!N2-IF(ISNUMBER(Scoring!E2),Parameters!$E$7,0)+IF(ISNUMBER(IF(Verification!D2<>"",Verification!D2,IF(Coding!AG2=0,"NA",IF(AND(Parameters!$C$39=1,ISNUMBER(Calc!B2),Calc!B2<=Parameters!$C$40),0,MIN(Coding!AG2,Parameters!$C$37)/Parameters!$C$37)))),Parameters!$E$7,0))>=Parameters!$C$56,Scoring!Q2>=Parameters!$C$59),(Scoring!O2-IF(ISNUMBER(Scoring!E2),Parameters!$E$7*Scoring!E2,0)+IF(ISNUMBER(IF(Verification!D2<>"",Verification!D2,IF(Coding!AG2=0,"NA",IF(AND(Parameters!$C$39=1,ISNUMBER(Calc!B2),Calc!B2<=Parameters!$C$40),0,MIN(Coding!AG2,Parameters!$C$37)/Parameters!$C$37)))),Parameters!$E$7*IF(Verification!D2<>"",Verification!D2,IF(Coding!AG2=0,"NA",IF(AND(Parameters!$C$39=1,ISNUMBER(Calc!B2),Calc!B2<=Parameters!$C$40),0,MIN(Coding!AG2,Parameters!$C$37)/Parameters!$C$37))),0))/(Scoring!N2-IF(ISNUMBER(Scoring!E2),Parameters!$E$7,0)+IF(ISNUMBER(IF(Verification!D2<>"",Verification!D2,IF(Coding!AG2=0,"NA",IF(AND(Parameters!$C$39=1,ISNUMBER(Calc!B2),Calc!B2<=Parameters!$C$40),0,MIN(Coding!AG2,Parameters!$C$37)/Parameters!$C$37)))),Parameters!$E$7,0))*100,"NA") -> NA | F2: =IF(Scoring!R2="Yes",AVERAGE(Scoring!D2:J2)*100,"NA") -> NA | G2: =IF(AND((Scoring!N2-IF(ISNUMBER(Scoring!F2),Parameters!$E$8,0)+IF(ISNUMBER(IF(Verification!E2<>"",Scoring!F2,Calc!V2)),Parameters!$E$8,0))>=Parameters!$C$56,Scoring!Q2>=Parameters!$C$59),(Scoring!O2-IF(ISNUMBER(Scoring!F2),Parameters!$E$8*Scoring!F2,0)+IF(ISNUMBER(IF(Verification!E2<>"",Scoring!F2,Calc!V2)),Parameters!$E$8*IF(Verification!E2<>"",Scoring!F2,Calc!V2),0))/(Scoring!N2-IF(ISNUMBER(Scoring!F2),Parameters!$E$8,0)+IF(ISNUMBER(IF(Verification!E2<>"",Scoring!F2,Calc!V2)),Parameters!$E$8,0))*100,"NA") -> NA | H2: =IF(ISNUMBER(Scoring!S2),(Scoring!N2/Parameters!$E$13)*Scoring!S2+(1-Scoring!N2/Parameters!$E$13)*Summary!$B$9,"NA") -> NA | I2: =IF(AND(ISNUMBER(Scoring!S2),COUNT(Scoring!E2,Scoring!F2)>0),Scoring!S2,"NA") -> NA | J2: =IF(AND(ISNUMBER($B2),ISNUMBER(C2)),ABS(C2-$B2),"") | K2: =IF(AND(ISNUMBER($B2),ISNUMBER(D2)),ABS(D2-$B2),"") | L2: =IF(AND(ISNUMBER($B2),ISNUMBER(E2)),ABS(E2-$B2),"") | M2: =IF(AND(ISNUMBER($B2),ISNUMBER(F2)),ABS(F2-$B2),"") | N2: =IF(AND(ISNUMBER($B2),ISNUMBER(G2)),ABS(G2-$B2),"") | O2: =IF(AND(ISNUMBER($B2),ISNUMBER(H2)),ABS(H2-$B2),"") | P2: =IF(AND(ISNUMBER($B2),ISNUMBER(I2)),ABS(I2-$B2),"")
A3: =Data!$A3 -> Academic Preservation Trust (APTrust) | B3: =Scoring!S3 -> 94 | C3: =IF(AND(Scoring!N3>=Parameters!$C$57,Scoring!Q3>=Parameters!$C$59),Scoring!O3/Scoring!N3*100,"NA") -> 94 | D3: =IF(AND(Scoring!N3>=Parameters!$C$58,Scoring!Q3>=Parameters!$C$59),Scoring!O3/Scoring!N3*100,"NA") -> 94 | E3: =IF(AND((Scoring!N3-IF(ISNUMBER(Scoring!E3),Parameters!$E$7,0)+IF(ISNUMBER(IF(Verification!D3<>"",Verification!D3,IF(Coding!AG3=0,"NA",IF(AND(Parameters!$C$39=1,ISNUMBER(Calc!B3),Calc!B3<=Parameters!$C$40),0,MIN(Coding!AG3,Parameters!$C$37)/Parameters!$C$37)))),Parameters!$E$7,0))>=Parameters!$C$56,Scoring!Q3>=Parameters!$C$59),(Scoring!O3-IF(ISNUMBER(Scoring!E3),Parameters!$E$7*Scoring!E3,0)+IF(ISNUMBER(IF(Verification!D3<>"",Verification!D3,IF(Coding!AG3=0,"NA",IF(AND(Parameters!$C$39=1,ISNUMBER(Calc!B3),Calc!B3<=Parameters!$C$40),0,MIN(Coding!AG3,Parameters!$C$37)/Parameters!$C$37)))),Parameters!$E$7*IF(Verification!D3<>"",Verification!D3,IF(Coding!AG3=0,"NA",IF(AND(Parameters!$C$39=1,ISNUMBER(Calc!B3),Calc!B3<=Parameters!$C$40),0,MIN(Coding!AG3,Parameters!$C$37)/Parameters!$C$37))),0))/(Scoring!N3-IF(ISNUMBER(Scoring!E3),Parameters!$E$7,0)+IF(ISNUMBER(IF(Verification!D3<>"",Verification!D3,IF(Coding!AG3=0,"NA",IF(AND(Parameters!$C$39=1,ISNUMBER(Calc!B3),Calc!B3<=Parameters!$C$40),0,MIN(Coding!AG3,Parameters!$C$37)/Parameters!$C$37)))),Parameters!$E$7,0))*100,"NA") -> 94 | F3: =IF(Scoring!R3="Yes",AVERAGE(Scoring!D3:J3)*100,"NA") -> 92.857143 | G3: =IF(AND((Scoring!N3-IF(ISNUMBER(Scoring!F3),Parameters!$E$8,0)+IF(ISNUMBER(IF(Verification!E3<>"",Scoring!F3,Calc!V3)),Parameters!$E$8,0))>=Parameters!$C$56,Scoring!Q3>=Parameters!$C$59),(Scoring!O3-IF(ISNUMBER(Scoring!F3),Parameters!$E$8*Scoring!F3,0)+IF(ISNUMBER(IF(Verification!E3<>"",Scoring!F3,Calc!V3)),Parameters!$E$8*IF(Verification!E3<>"",Scoring!F3,Calc!V3),0))/(Scoring!N3-IF(ISNUMBER(Scoring!F3),Parameters!$E$8,0)+IF(ISNUMBER(IF(Verification!E3<>"",Scoring!F3,Calc!V3)),Parameters!$E$8,0))*100,"NA") -> 94 | H3: =IF(ISNUMBER(Scoring!S3),(Scoring!N3/Parameters!$E$13)*Scoring!S3+(1-Scoring!N3/Parameters!$E$13)*Summary!$B$9,"NA") -> 94 | I3: =IF(AND(ISNUMBER(Scoring!S3),COUNT(Scoring!E3,Scoring!F3)>0),Scoring!S3,"NA") -> 94 | J3: =IF(AND(ISNUMBER($B3),ISNUMBER(C3)),ABS(C3-$B3),"") -> 0 | K3: =IF(AND(ISNUMBER($B3),ISNUMBER(D3)),ABS(D3-$B3),"") -> 0 | L3: =IF(AND(ISNUMBER($B3),ISNUMBER(E3)),ABS(E3-$B3),"") -> 0 | M3: =IF(AND(ISNUMBER($B3),ISNUMBER(F3)),ABS(F3-$B3),"") -> 1.1428571 | N3: =IF(AND(ISNUMBER($B3),ISNUMBER(G3)),ABS(G3-$B3),"") -> 0 | O3: =IF(AND(ISNUMBER($B3),ISNUMBER(H3)),ABS(H3-$B3),"") -> 0 | P3: =IF(AND(ISNUMBER($B3),ISNUMBER(I3)),ABS(I3-$B3),"") -> 0
A4: =Data!$A4 -> AfricArXiv | B4: =Scoring!S4 -> NA | C4: =IF(AND(Scoring!N4>=Parameters!$C$57,Scoring!Q4>=Parameters!$C$59),Scoring!O4/Scoring!N4*100,"NA") -> NA | D4: =IF(AND(Scoring!N4>=Parameters!$C$58,Scoring!Q4>=Parameters!$C$59),Scoring!O4/Scoring!N4*100,"NA") -> NA | E4: =IF(AND((Scoring!N4-IF(ISNUMBER(Scoring!E4),Parameters!$E$7,0)+IF(ISNUMBER(IF(Verification!D4<>"",Verification!D4,IF(Coding!AG4=0,"NA",IF(AND(Parameters!$C$39=1,ISNUMBER(Calc!B4),Calc!B4<=Parameters!$C$40),0,MIN(Coding!AG4,Parameters!$C$37)/Parameters!$C$37)))),Parameters!$E$7,0))>=Parameters!$C$56,Scoring!Q4>=Parameters!$C$59),(Scoring!O4-IF(ISNUMBER(Scoring!E4),Parameters!$E$7*Scoring!E4,0)+IF(ISNUMBER(IF(Verification!D4<>"",Verification!D4,IF(Coding!AG4=0,"NA",IF(AND(Parameters!$C$39=1,ISNUMBER(Calc!B4),Calc!B4<=Parameters!$C$40),0,MIN(Coding!AG4,Parameters!$C$37)/Parameters!$C$37)))),Parameters!$E$7*IF(Verification!D4<>"",Verification!D4,IF(Coding!AG4=0,"NA",IF(AND(Parameters!$C$39=1,ISNUMBER(Calc!B4),Calc!B4<=Parameters!$C$40),0,MIN(Coding!AG4,Parameters!$C$37)/Parameters!$C$37))),0))/(Scoring!N4-IF(ISNUMBER(Scoring!E4),Parameters!$E$7,0)+IF(ISNUMBER(IF(Verification!D4<>"",Verification!D4,IF(Coding!AG4=0,"NA",IF(AND(Parameters!$C$39=1,ISNUMBER(Calc!B4),Calc!B4<=Parameters!$C$40),0,MIN(Coding!AG4,Parameters!$C$37)/Parameters!$C$37)))),Parameters!$E$7,0))*100,"NA") -> NA | F4: =IF(Scoring!R4="Yes",AVERAGE(Scoring!D4:J4)*100,"NA") -> NA | G4: =IF(AND((Scoring!N4-IF(ISNUMBER(Scoring!F4),Parameters!$E$8,0)+IF(ISNUMBER(IF(Verification!E4<>"",Scoring!F4,Calc!V4)),Parameters!$E$8,0))>=Parameters!$C$56,Scoring!Q4>=Parameters!$C$59),(Scoring!O4-IF(ISNUMBER(Scoring!F4),Parameters!$E$8*Scoring!F4,0)+IF(ISNUMBER(IF(Verification!E4<>"",Scoring!F4,Calc!V4)),Parameters!$E$8*IF(Verification!E4<>"",Scoring!F4,Calc!V4),0))/(Scoring!N4-IF(ISNUMBER(Scoring!F4),Parameters!$E$8,0)+IF(ISNUMBER(IF(Verification!E4<>"",Scoring!F4,Calc!V4)),Parameters!$E$8,0))*100,"NA") -> NA | H4: =IF(ISNUMBER(Scoring!S4),(Scoring!N4/Parameters!$E$13)*Scoring!S4+(1-Scoring!N4/Parameters!$E$13)*Summary!$B$9,"NA") -> NA | I4: =IF(AND(ISNUMBER(Scoring!S4),COUNT(Scoring!E4,Scoring!F4)>0),Scoring!S4,"NA") -> NA | J4: =IF(AND(ISNUMBER($B4),ISNUMBER(C4)),ABS(C4-$B4),"") | K4: =IF(AND(ISNUMBER($B4),ISNUMBER(D4)),ABS(D4-$B4),"") | L4: =IF(AND(ISNUMBER($B4),ISNUMBER(E4)),ABS(E4-$B4),"") | M4: =IF(AND(ISNUMBER($B4),ISNUMBER(F4)),ABS(F4-$B4),"") | N4: =IF(AND(ISNUMBER($B4),ISNUMBER(G4)),ABS(G4-$B4),"") | O4: =IF(AND(ISNUMBER($B4),ISNUMBER(H4)),ABS(H4-$B4),"") | P4: =IF(AND(ISNUMBER($B4),ISNUMBER(I4)),ABS(I4-$B4),"")
A5: =Data!$A5 -> Arches Heritage Data Management Platform | B5: =Scoring!S5 -> 100 | C5: =IF(AND(Scoring!N5>=Parameters!$C$57,Scoring!Q5>=Parameters!$C$59),Scoring!O5/Scoring!N5*100,"NA") -> 100 | D5: =IF(AND(Scoring!N5>=Parameters!$C$58,Scoring!Q5>=Parameters!$C$59),Scoring!O5/Scoring!N5*100,"NA") -> NA | E5: =IF(AND((Scoring!N5-IF(ISNUMBER(Scoring!E5),Parameters!$E$7,0)+IF(ISNUMBER(IF(Verification!D5<>"",Verification!D5,IF(Coding!AG5=0,"NA",IF(AND(Parameters!$C$39=1,ISNUMBER(Calc!B5),Calc!B5<=Parameters!$C$40),0,MIN(Coding!AG5,Parameters!$C$37)/Parameters!$C$37)))),Parameters!$E$7,0))>=Parameters!$C$56,Scoring!Q5>=Parameters!$C$59),(Scoring!O5-IF(ISNUMBER(Scoring!E5),Parameters!$E$7*Scoring!E5,0)+IF(ISNUMBER(IF(Verification!D5<>"",Verification!D5,IF(Coding!AG5=0,"NA",IF(AND(Parameters!$C$39=1,ISNUMBER(Calc!B5),Calc!B5<=Parameters!$C$40),0,MIN(Coding!AG5,Parameters!$C$37)/Parameters!$C$37)))),Parameters!$E$7*IF(Verification!D5<>"",Verification!D5,IF(Coding!AG5=0,"NA",IF(AND(Parameters!$C$39=1,ISNUMBER(Calc!B5),Calc!B5<=Parameters!$C$40),0,MIN(Coding!AG5,Parameters!$C$37)/Parameters!$C$37))),0))/(Scoring!N5-IF(ISNUMBER(Scoring!E5),Parameters!$E$7,0)+IF(ISNUMBER(IF(Verification!D5<>"",Verification!D5,IF(Coding!AG5=0,"NA",IF(AND(Parameters!$C$39=1,ISNUMBER(Calc!B5),Calc!B5<=Parameters!$C$40),0,MIN(Coding!AG5,Parameters!$C$37)/Parameters!$C$37)))),Parameters!$E$7,0))*100,"NA") -> 100 | F5: =IF(Scoring!R5="Yes",AVERAGE(Scoring!D5:J5)*100,"NA") -> 100 | G5: =IF(AND((Scoring!N5-IF(ISNUMBER(Scoring!F5),Parameters!$E$8,0)+IF(ISNUMBER(IF(Verification!E5<>"",Scoring!F5,Calc!V5)),Parameters!$E$8,0))>=Parameters!$C$56,Scoring!Q5>=Parameters!$C$59),(Scoring!O5-IF(ISNUMBER(Scoring!F5),Parameters!$E$8*Scoring!F5,0)+IF(ISNUMBER(IF(Verification!E5<>"",Scoring!F5,Calc!V5)),Parameters!$E$8*IF(Verification!E5<>"",Scoring!F5,Calc!V5),0))/(Scoring!N5-IF(ISNUMBER(Scoring!F5),Parameters!$E$8,0)+IF(ISNUMBER(IF(Verification!E5<>"",Scoring!F5,Calc!V5)),Parameters!$E$8,0))*100,"NA") -> 100 | H5: =IF(ISNUMBER(Scoring!S5),(Scoring!N5/Parameters!$E$13)*Scoring!S5+(1-Scoring!N5/Parameters!$E$13)*Summary!$B$9,"NA") -> 91.290323 | I5: =IF(AND(ISNUMBER(Scoring!S5),COUNT(Scoring!E5,Scoring!F5)>0),Scoring!S5,"NA") -> NA | J5: =IF(AND(ISNUMBER($B5),ISNUMBER(C5)),ABS(C5-$B5),"") -> 0 | K5: =IF(AND(ISNUMBER($B5),ISNUMBER(D5)),ABS(D5-$B5),"") | L5: =IF(AND(ISNUMBER($B5),ISNUMBER(E5)),ABS(E5-$B5),"") -> 0 | M5: =IF(AND(ISNUMBER($B5),ISNUMBER(F5)),ABS(F5-$B5),"") -> 0 | N5: =IF(AND(ISNUMBER($B5),ISNUMBER(G5)),ABS(G5-$B5),"") -> 0 | O5: =IF(AND(ISNUMBER($B5),ISNUMBER(H5)),ABS(H5-$B5),"") -> 8.7096774 | P5: =IF(AND(ISNUMBER($B5),ISNUMBER(I5)),ABS(I5-$B5),"")
A6: =Data!$A6 -> Archipelago Commons | B6: =Scoring!S6 -> 82.25 | C6: =IF(AND(Scoring!N6>=Parameters!$C$57,Scoring!Q6>=Parameters!$C$59),Scoring!O6/Scoring!N6*100,"NA") -> 82.25 | D6: =IF(AND(Scoring!N6>=Parameters!$C$58,Scoring!Q6>=Parameters!$C$59),Scoring!O6/Scoring!N6*100,"NA") -> 82.25 | E6: =IF(AND((Scoring!N6-IF(ISNUMBER(Scoring!E6),Parameters!$E$7,0)+IF(ISNUMBER(IF(Verification!D6<>"",Verification!D6,IF(Coding!AG6=0,"NA",IF(AND(Parameters!$C$39=1,ISNUMBER(Calc!B6),Calc!B6<=Parameters!$C$40),0,MIN(Coding!AG6,Parameters!$C$37)/Parameters!$C$37)))),Parameters!$E$7,0))>=Parameters!$C$56,Scoring!Q6>=Parameters!$C$59),(Scoring!O6-IF(ISNUMBER(Scoring!E6),Parameters!$E$7*Scoring!E6,0)+IF(ISNUMBER(IF(Verification!D6<>"",Verification!D6,IF(Coding!AG6=0,"NA",IF(AND(Parameters!$C$39=1,ISNUMBER(Calc!B6),Calc!B6<=Parameters!$C$40),0,MIN(Coding!AG6,Parameters!$C$37)/Parameters!$C$37)))),Parameters!$E$7*IF(Verification!D6<>"",Verification!D6,IF(Coding!AG6=0,"NA",IF(AND(Parameters!$C$39=1,ISNUMBER(Calc!B6),Calc!B6<=Parameters!$C$40),0,MIN(Coding!AG6,Parameters!$C$37)/Parameters!$C$37))),0))/(Scoring!N6-IF(ISNUMBER(Scoring!E6),Parameters!$E$7,0)+IF(ISNUMBER(IF(Verification!D6<>"",Verification!D6,IF(Coding!AG6=0,"NA",IF(AND(Parameters!$C$39=1,ISNUMBER(Calc!B6),Calc!B6<=Parameters!$C$40),0,MIN(Coding!AG6,Parameters!$C$37)/Parameters!$C$37)))),Parameters!$E$7,0))*100,"NA") -> 82.25 | F6: =IF(Scoring!R6="Yes",AVERAGE(Scoring!D6:J6)*100,"NA") -> 83.928571 | G6: =IF(AND((Scoring!N6-IF(ISNUMBER(Scoring!F6),Parameters!$E$8,0)+IF(ISNUMBER(IF(Verification!E6<>"",Scoring!F6,Calc!V6)),Parameters!$E$8,0))>=Parameters!$C$56,Scoring!Q6>=Parameters!$C$59),(Scoring!O6-IF(ISNUMBER(Scoring!F6),Parameters!$E$8*Scoring!F6,0)+IF(ISNUMBER(IF(Verification!E6<>"",Scoring!F6,Calc!V6)),Parameters!$E$8*IF(Verification!E6<>"",Scoring!F6,Calc!V6),0))/(Scoring!N6-IF(ISNUMBER(Scoring!F6),Parameters!$E$8,0)+IF(ISNUMBER(IF(Verification!E6<>"",Scoring!F6,Calc!V6)),Parameters!$E$8,0))*100,"NA") -> 82.25 | H6: =IF(ISNUMBER(Scoring!S6),(Scoring!N6/Parameters!$E$13)*Scoring!S6+(1-Scoring!N6/Parameters!$E$13)*Summary!$B$9,"NA") -> 82.25 | I6: =IF(AND(ISNUMBER(Scoring!S6),COUNT(Scoring!E6,Scoring!F6)>0),Scoring!S6,"NA") -> 82.25 | J6: =IF(AND(ISNUMBER($B6),ISNUMBER(C6)),ABS(C6-$B6),"") -> 0 | K6: =IF(AND(ISNUMBER($B6),ISNUMBER(D6)),ABS(D6-$B6),"") -> 0 | L6: =IF(AND(ISNUMBER($B6),ISNUMBER(E6)),ABS(E6-$B6),"") -> 0 | M6: =IF(AND(ISNUMBER($B6),ISNUMBER(F6)),ABS(F6-$B6),"") -> 1.6785714 | N6: =IF(AND(ISNUMBER($B6),ISNUMBER(G6)),ABS(G6-$B6),"") -> 0 | O6: =IF(AND(ISNUMBER($B6),ISNUMBER(H6)),ABS(H6-$B6),"") -> 0 | P6: =IF(AND(ISNUMBER($B6),ISNUMBER(I6)),ABS(I6-$B6),"") -> 0
A7: =Data!$A7 -> Archival Resource Key | B7: =Scoring!S7 -> 75.641026 | C7: =IF(AND(Scoring!N7>=Parameters!$C$57,Scoring!Q7>=Parameters!$C$59),Scoring!O7/Scoring!N7*100,"NA") -> 75.641026 | D7: =IF(AND(Scoring!N7>=Parameters!$C$58,Scoring!Q7>=Parameters!$C$59),Scoring!O7/Scoring!N7*100,"NA") -> 75.641026 | E7: =IF(AND((Scoring!N7-IF(ISNUMBER(Scoring!E7),Parameters!$E$7,0)+IF(ISNUMBER(IF(Verification!D7<>"",Verification!D7,IF(Coding!AG7=0,"NA",IF(AND(Parameters!$C$39=1,ISNUMBER(Calc!B7),Calc!B7<=Parameters!$C$40),0,MIN(Coding!AG7,Parameters!$C$37)/Parameters!$C$37)))),Parameters!$E$7,0))>=Parameters!$C$56,Scoring!Q7>=Parameters!$C$59),(Scoring!O7-IF(ISNUMBER(Scoring!E7),Parameters!$E$7*Scoring!E7,0)+IF(ISNUMBER(IF(Verification!D7<>"",Verification!D7,IF(Coding!AG7=0,"NA",IF(AND(Parameters!$C$39=1,ISNUMBER(Calc!B7),Calc!B7<=Parameters!$C$40),0,MIN(Coding!AG7,Parameters!$C$37)/Parameters!$C$37)))),Parameters!$E$7*IF(Verification!D7<>"",Verification!D7,IF(Coding!AG7=0,"NA",IF(AND(Parameters!$C$39=1,ISNUMBER(Calc!B7),Calc!B7<=Parameters!$C$40),0,MIN(Coding!AG7,Parameters!$C$37)/Parameters!$C$37))),0))/(Scoring!N7-IF(ISNUMBER(Scoring!E7),Parameters!$E$7,0)+IF(ISNUMBER(IF(Verification!D7<>"",Verification!D7,IF(Coding!AG7=0,"NA",IF(AND(Parameters!$C$39=1,ISNUMBER(Calc!B7),Calc!B7<=Parameters!$C$40),0,MIN(Coding!AG7,Parameters!$C$37)/Parameters!$C$37)))),Parameters!$E$7,0))*100,"NA") -> 75.641026 | F7: =IF(Scoring!R7="Yes",AVERAGE(Scoring!D7:J7)*100,"NA") -> 80.555556 | G7: =IF(AND((Scoring!N7-IF(ISNUMBER(Scoring!F7),Parameters!$E$8,0)+IF(ISNUMBER(IF(Verification!E7<>"",Scoring!F7,Calc!V7)),Parameters!$E$8,0))>=Parameters!$C$56,Scoring!Q7>=Parameters!$C$59),(Scoring!O7-IF(ISNUMBER(Scoring!F7),Parameters!$E$8*Scoring!F7,0)+IF(ISNUMBER(IF(Verification!E7<>"",Scoring!F7,Calc!V7)),Parameters!$E$8*IF(Verification!E7<>"",Scoring!F7,Calc!V7),0))/(Scoring!N7-IF(ISNUMBER(Scoring!F7),Parameters!$E$8,0)+IF(ISNUMBER(IF(Verification!E7<>"",Scoring!F7,Calc!V7)),Parameters!$E$8,0))*100,"NA") -> 71.794872 | H7: =IF(ISNUMBER(Scoring!S7),(Scoring!N7/Parameters!$E$13)*Scoring!S7+(1-Scoring!N7/Parameters!$E$13)*Summary!$B$9,"NA") -> 76.209677 | I7: =IF(AND(ISNUMBER(Scoring!S7),COUNT(Scoring!E7,Scoring!F7)>0),Scoring!S7,"NA") -> 75.641026 | J7: =IF(AND(ISNUMBER($B7),ISNUMBER(C7)),ABS(C7-$B7),"") -> 0 | K7: =IF(AND(ISNUMBER($B7),ISNUMBER(D7)),ABS(D7-$B7),"") -> 0 | L7: =IF(AND(ISNUMBER($B7),ISNUMBER(E7)),ABS(E7-$B7),"") -> 0 | M7: =IF(AND(ISNUMBER($B7),ISNUMBER(F7)),ABS(F7-$B7),"") -> 4.9145299 | N7: =IF(AND(ISNUMBER($B7),ISNUMBER(G7)),ABS(G7-$B7),"") -> 3.8461538 | O7: =IF(AND(ISNUMBER($B7),ISNUMBER(H7)),ABS(H7-$B7),"") -> 0.56865178 | P7: =IF(AND(ISNUMBER($B7),ISNUMBER(I7)),ABS(I7-$B7),"") -> 0
A8: =Data!$A8 -> Archivematica | B8: =Scoring!S8 -> NA | C8: =IF(AND(Scoring!N8>=Parameters!$C$57,Scoring!Q8>=Parameters!$C$59),Scoring!O8/Scoring!N8*100,"NA") -> NA | D8: =IF(AND(Scoring!N8>=Parameters!$C$58,Scoring!Q8>=Parameters!$C$59),Scoring!O8/Scoring!N8*100,"NA") -> NA | E8: =IF(AND((Scoring!N8-IF(ISNUMBER(Scoring!E8),Parameters!$E$7,0)+IF(ISNUMBER(IF(Verification!D8<>"",Verification!D8,IF(Coding!AG8=0,"NA",IF(AND(Parameters!$C$39=1,ISNUMBER(Calc!B8),Calc!B8<=Parameters!$C$40),0,MIN(Coding!AG8,Parameters!$C$37)/Parameters!$C$37)))),Parameters!$E$7,0))>=Parameters!$C$56,Scoring!Q8>=Parameters!$C$59),(Scoring!O8-IF(ISNUMBER(Scoring!E8),Parameters!$E$7*Scoring!E8,0)+IF(ISNUMBER(IF(Verification!D8<>"",Verification!D8,IF(Coding!AG8=0,"NA",IF(AND(Parameters!$C$39=1,ISNUMBER(Calc!B8),Calc!B8<=Parameters!$C$40),0,MIN(Coding!AG8,Parameters!$C$37)/Parameters!$C$37)))),Parameters!$E$7*IF(Verification!D8<>"",Verification!D8,IF(Coding!AG8=0,"NA",IF(AND(Parameters!$C$39=1,ISNUMBER(Calc!B8),Calc!B8<=Parameters!$C$40),0,MIN(Coding!AG8,Parameters!$C$37)/Parameters!$C$37))),0))/(Scoring!N8-IF(ISNUMBER(Scoring!E8),Parameters!$E$7,0)+IF(ISNUMBER(IF(Verification!D8<>"",Verification!D8,IF(Coding!AG8=0,"NA",IF(AND(Parameters!$C$39=1,ISNUMBER(Calc!B8),Calc!B8<=Parameters!$C$40),0,MIN(Coding!AG8,Parameters!$C$37)/Parameters!$C$37)))),Parameters!$E$7,0))*100,"NA") -> NA | F8: =IF(Scoring!R8="Yes",AVERAGE(Scoring!D8:J8)*100,"NA") -> NA | G8: =IF(AND((Scoring!N8-IF(ISNUMBER(Scoring!F8),Parameters!$E$8,0)+IF(ISNUMBER(IF(Verification!E8<>"",Scoring!F8,Calc!V8)),Parameters!$E$8,0))>=Parameters!$C$56,Scoring!Q8>=Parameters!$C$59),(Scoring!O8-IF(ISNUMBER(Scoring!F8),Parameters!$E$8*Scoring!F8,0)+IF(ISNUMBER(IF(Verification!E8<>"",Scoring!F8,Calc!V8)),Parameters!$E$8*IF(Verification!E8<>"",Scoring!F8,Calc!V8),0))/(Scoring!N8-IF(ISNUMBER(Scoring!F8),Parameters!$E$8,0)+IF(ISNUMBER(IF(Verification!E8<>"",Scoring!F8,Calc!V8)),Parameters!$E$8,0))*100,"NA") -> NA | H8: =IF(ISNUMBER(Scoring!S8),(Scoring!N8/Parameters!$E$13)*Scoring!S8+(1-Scoring!N8/Parameters!$E$13)*Summary!$B$9,"NA") -> NA | I8: =IF(AND(ISNUMBER(Scoring!S8),COUNT(Scoring!E8,Scoring!F8)>0),Scoring!S8,"NA") -> NA | J8: =IF(AND(ISNUMBER($B8),ISNUMBER(C8)),ABS(C8-$B8),"") | K8: =IF(AND(ISNUMBER($B8),ISNUMBER(D8)),ABS(D8-$B8),"") | L8: =IF(AND(ISNUMBER($B8),ISNUMBER(E8)),ABS(E8-$B8),"") | M8: =IF(AND(ISNUMBER($B8),ISNUMBER(F8)),ABS(F8-$B8),"") | N8: =IF(AND(ISNUMBER($B8),ISNUMBER(G8)),ABS(G8-$B8),"") | O8: =IF(AND(ISNUMBER($B8),ISNUMBER(H8)),ABS(H8-$B8),"") | P8: =IF(AND(ISNUMBER($B8),ISNUMBER(I8)),ABS(I8-$B8),"")
A9: =Data!$A9 -> ArchivesSpace | B9: =Scoring!S9 -> 100 | C9: =IF(AND(Scoring!N9>=Parameters!$C$57,Scoring!Q9>=Parameters!$C$59),Scoring!O9/Scoring!N9*100,"NA") -> 100 | D9: =IF(AND(Scoring!N9>=Parameters!$C$58,Scoring!Q9>=Parameters!$C$59),Scoring!O9/Scoring!N9*100,"NA") -> 100 | E9: =IF(AND((Scoring!N9-IF(ISNUMBER(Scoring!E9),Parameters!$E$7,0)+IF(ISNUMBER(IF(Verification!D9<>"",Verification!D9,IF(Coding!AG9=0,"NA",IF(AND(Parameters!$C$39=1,ISNUMBER(Calc!B9),Calc!B9<=Parameters!$C$40),0,MIN(Coding!AG9,Parameters!$C$37)/Parameters!$C$37)))),Parameters!$E$7,0))>=Parameters!$C$56,Scoring!Q9>=Parameters!$C$59),(Scoring!O9-IF(ISNUMBER(Scoring!E9),Parameters!$E$7*Scoring!E9,0)+IF(ISNUMBER(IF(Verification!D9<>"",Verification!D9,IF(Coding!AG9=0,"NA",IF(AND(Parameters!$C$39=1,ISNUMBER(Calc!B9),Calc!B9<=Parameters!$C$40),0,MIN(Coding!AG9,Parameters!$C$37)/Parameters!$C$37)))),Parameters!$E$7*IF(Verification!D9<>"",Verification!D9,IF(Coding!AG9=0,"NA",IF(AND(Parameters!$C$39=1,ISNUMBER(Calc!B9),Calc!B9<=Parameters!$C$40),0,MIN(Coding!AG9,Parameters!$C$37)/Parameters!$C$37))),0))/(Scoring!N9-IF(ISNUMBER(Scoring!E9),Parameters!$E$7,0)+IF(ISNUMBER(IF(Verification!D9<>"",Verification!D9,IF(Coding!AG9=0,"NA",IF(AND(Parameters!$C$39=1,ISNUMBER(Calc!B9),Calc!B9<=Parameters!$C$40),0,MIN(Coding!AG9,Parameters!$C$37)/Parameters!$C$37)))),Parameters!$E$7,0))*100,"NA") -> 100 | F9: =IF(Scoring!R9="Yes",AVERAGE(Scoring!D9:J9)*100,"NA") -> 100 | G9: =IF(AND((Scoring!N9-IF(ISNUMBER(Scoring!F9),Parameters!$E$8,0)+IF(ISNUMBER(IF(Verification!E9<>"",Scoring!F9,Calc!V9)),Parameters!$E$8,0))>=Parameters!$C$56,Scoring!Q9>=Parameters!$C$59),(Scoring!O9-IF(ISNUMBER(Scoring!F9),Parameters!$E$8*Scoring!F9,0)+IF(ISNUMBER(IF(Verification!E9<>"",Scoring!F9,Calc!V9)),Parameters!$E$8*IF(Verification!E9<>"",Scoring!F9,Calc!V9),0))/(Scoring!N9-IF(ISNUMBER(Scoring!F9),Parameters!$E$8,0)+IF(ISNUMBER(IF(Verification!E9<>"",Scoring!F9,Calc!V9)),Parameters!$E$8,0))*100,"NA") -> 100 | H9: =IF(ISNUMBER(Scoring!S9),(Scoring!N9/Parameters!$E$13)*Scoring!S9+(1-Scoring!N9/Parameters!$E$13)*Summary!$B$9,"NA") -> 96.080645 | I9: =IF(AND(ISNUMBER(Scoring!S9),COUNT(Scoring!E9,Scoring!F9)>0),Scoring!S9,"NA") -> 100 | J9: =IF(AND(ISNUMBER($B9),ISNUMBER(C9)),ABS(C9-$B9),"") -> 0 | K9: =IF(AND(ISNUMBER($B9),ISNUMBER(D9)),ABS(D9-$B9),"") -> 0 | L9: =IF(AND(ISNUMBER($B9),ISNUMBER(E9)),ABS(E9-$B9),"") -> 0 | M9: =IF(AND(ISNUMBER($B9),ISNUMBER(F9)),ABS(F9-$B9),"") -> 0 | N9: =IF(AND(ISNUMBER($B9),ISNUMBER(G9)),ABS(G9-$B9),"") -> 0 | O9: =IF(AND(ISNUMBER($B9),ISNUMBER(H9)),ABS(H9-$B9),"") -> 3.9193548 | P9: =IF(AND(ISNUMBER($B9),ISNUMBER(I9)),ABS(I9-$B9),"") -> 0
A10: =Data!$A10 -> ARGOS | B10: =Scoring!S10 -> 100 | C10: =IF(AND(Scoring!N10>=Parameters!$C$57,Scoring!Q10>=Parameters!$C$59),Scoring!O10/Scoring!N10*100,"NA") -> 100 | D10: =IF(AND(Scoring!N10>=Parameters!$C$58,Scoring!Q10>=Parameters!$C$59),Scoring!O10/Scoring!N10*100,"NA") -> 100 | E10: =IF(AND((Scoring!N10-IF(ISNUMBER(Scoring!E10),Parameters!$E$7,0)+IF(ISNUMBER(IF(Verification!D10<>"",Verification!D10,IF(Coding!AG10=0,"NA",IF(AND(Parameters!$C$39=1,ISNUMBER(Calc!B10),Calc!B10<=Parameters!$C$40),0,MIN(Coding!AG10,Parameters!$C$37)/Parameters!$C$37)))),Parameters!$E$7,0))>=Parameters!$C$56,Scoring!Q10>=Parameters!$C$59),(Scoring!O10-IF(ISNUMBER(Scoring!E10),Parameters!$E$7*Scoring!E10,0)+IF(ISNUMBER(IF(Verification!D10<>"",Verification!D10,IF(Coding!AG10=0,"NA",IF(AND(Parameters!$C$39=1,ISNUMBER(Calc!B10),Calc!B10<=Parameters!$C$40),0,MIN(Coding!AG10,Parameters!$C$37)/Parameters!$C$37)))),Parameters!$E$7*IF(Verification!D10<>"",Verification!D10,IF(Coding!AG10=0,"NA",IF(AND(Parameters!$C$39=1,ISNUMBER(Calc!B10),Calc!B10<=Parameters!$C$40),0,MIN(Coding!AG10,Parameters!$C$37)/Parameters!$C$37))),0))/(Scoring!N10-IF(ISNUMBER(Scoring!E10),Parameters!$E$7,0)+IF(ISNUMBER(IF(Verification!D10<>"",Verification!D10,IF(Coding!AG10=0,"NA",IF(AND(Parameters!$C$39=1,ISNUMBER(Calc!B10),Calc!B10<=Parameters!$C$40),0,MIN(Coding!AG10,Parameters!$C$37)/Parameters!$C$37)))),Parameters!$E$7,0))*100,"NA") -> 100 | F10: =IF(Scoring!R10="Yes",AVERAGE(Scoring!D10:J10)*100,"NA") -> 100 | G10: =IF(AND((Scoring!N10-IF(ISNUMBER(Scoring!F10),Parameters!$E$8,0)+IF(ISNUMBER(IF(Verification!E10<>"",Scoring!F10,Calc!V10)),Parameters!$E$8,0))>=Parameters!$C$56,Scoring!Q10>=Parameters!$C$59),(Scoring!O10-IF(ISNUMBER(Scoring!F10),Parameters!$E$8*Scoring!F10,0)+IF(ISNUMBER(IF(Verification!E10<>"",Scoring!F10,Calc!V10)),Parameters!$E$8*IF(Verification!E10<>"",Scoring!F10,Calc!V10),0))/(Scoring!N10-IF(ISNUMBER(Scoring!F10),Parameters!$E$8,0)+IF(ISNUMBER(IF(Verification!E10<>"",Scoring!F10,Calc!V10)),Parameters!$E$8,0))*100,"NA") -> 100 | H10: =IF(ISNUMBER(Scoring!S10),(Scoring!N10/Parameters!$E$13)*Scoring!S10+(1-Scoring!N10/Parameters!$E$13)*Summary!$B$9,"NA") -> 93.467742 | I10: =IF(AND(ISNUMBER(Scoring!S10),COUNT(Scoring!E10,Scoring!F10)>0),Scoring!S10,"NA") -> 100 | J10: =IF(AND(ISNUMBER($B10),ISNUMBER(C10)),ABS(C10-$B10),"") -> 0 | K10: =IF(AND(ISNUMBER($B10),ISNUMBER(D10)),ABS(D10-$B10),"") -> 0 | L10: =IF(AND(ISNUMBER($B10),ISNUMBER(E10)),ABS(E10-$B10),"") -> 0 | M10: =IF(AND(ISNUMBER($B10),ISNUMBER(F10)),ABS(F10-$B10),"") -> 0 | N10: =IF(AND(ISNUMBER($B10),ISNUMBER(G10)),ABS(G10-$B10),"") -> 0 | O10: =IF(AND(ISNUMBER($B10),ISNUMBER(H10)),ABS(H10-$B10),"") -> 6.5322581 | P10: =IF(AND(ISNUMBER($B10),ISNUMBER(I10)),ABS(I10-$B10),"") -> 0
A11: =Data!$A11 -> arXiv | B11: =Scoring!S11 -> 65.75 | C11: =IF(AND(Scoring!N11>=Parameters!$C$57,Scoring!Q11>=Parameters!$C$59),Scoring!O11/Scoring!N11*100,"NA") -> 65.75 | D11: =IF(AND(Scoring!N11>=Parameters!$C$58,Scoring!Q11>=Parameters!$C$59),Scoring!O11/Scoring!N11*100,"NA") -> 65.75 | E11: =IF(AND((Scoring!N11-IF(ISNUMBER(Scoring!E11),Parameters!$E$7,0)+IF(ISNUMBER(IF(Verification!D11<>"",Verification!D11,IF(Coding!AG11=0,"NA",IF(AND(Parameters!$C$39=1,ISNUMBER(Calc!B11),Calc!B11<=Parameters!$C$40),0,MIN(Coding!AG11,Parameters!$C$37)/Parameters!$C$37)))),Parameters!$E$7,0))>=Parameters!$C$56,Scoring!Q11>=Parameters!$C$59),(Scoring!O11-IF(ISNUMBER(Scoring!E11),Parameters!$E$7*Scoring!E11,0)+IF(ISNUMBER(IF(Verification!D11<>"",Verification!D11,IF(Coding!AG11=0,"NA",IF(AND(Parameters!$C$39=1,ISNUMBER(Calc!B11),Calc!B11<=Parameters!$C$40),0,MIN(Coding!AG11,Parameters!$C$37)/Parameters!$C$37)))),Parameters!$E$7*IF(Verification!D11<>"",Verification!D11,IF(Coding!AG11=0,"NA",IF(AND(Parameters!$C$39=1,ISNUMBER(Calc!B11),Calc!B11<=Parameters!$C$40),0,MIN(Coding!AG11,Parameters!$C$37)/Parameters!$C$37))),0))/(Scoring!N11-IF(ISNUMBER(Scoring!E11),Parameters!$E$7,0)+IF(ISNUMBER(IF(Verification!D11<>"",Verification!D11,IF(Coding!AG11=0,"NA",IF(AND(Parameters!$C$39=1,ISNUMBER(Calc!B11),Calc!B11<=Parameters!$C$40),0,MIN(Coding!AG11,Parameters!$C$37)/Parameters!$C$37)))),Parameters!$E$7,0))*100,"NA") -> 80.769231 | F11: =IF(Scoring!R11="Yes",AVERAGE(Scoring!D11:J11)*100,"NA") -> 73.214286 | G11: =IF(AND((Scoring!N11-IF(ISNUMBER(Scoring!F11),Parameters!$E$8,0)+IF(ISNUMBER(IF(Verification!E11<>"",Scoring!F11,Calc!V11)),Parameters!$E$8,0))>=Parameters!$C$56,Scoring!Q11>=Parameters!$C$59),(Scoring!O11-IF(ISNUMBER(Scoring!F11),Parameters!$E$8*Scoring!F11,0)+IF(ISNUMBER(IF(Verification!E11<>"",Scoring!F11,Calc!V11)),Parameters!$E$8*IF(Verification!E11<>"",Scoring!F11,Calc!V11),0))/(Scoring!N11-IF(ISNUMBER(Scoring!F11),Parameters!$E$8,0)+IF(ISNUMBER(IF(Verification!E11<>"",Scoring!F11,Calc!V11)),Parameters!$E$8,0))*100,"NA") -> 62.75 | H11: =IF(ISNUMBER(Scoring!S11),(Scoring!N11/Parameters!$E$13)*Scoring!S11+(1-Scoring!N11/Parameters!$E$13)*Summary!$B$9,"NA") -> 65.75 | I11: =IF(AND(ISNUMBER(Scoring!S11),COUNT(Scoring!E11,Scoring!F11)>0),Scoring!S11,"NA") -> 65.75 | J11: =IF(AND(ISNUMBER($B11),ISNUMBER(C11)),ABS(C11-$B11),"") -> 0 | K11: =IF(AND(ISNUMBER($B11),ISNUMBER(D11)),ABS(D11-$B11),"") -> 0 | L11: =IF(AND(ISNUMBER($B11),ISNUMBER(E11)),ABS(E11-$B11),"") -> 15.019231 | M11: =IF(AND(ISNUMBER($B11),ISNUMBER(F11)),ABS(F11-$B11),"") -> 7.4642857 | N11: =IF(AND(ISNUMBER($B11),ISNUMBER(G11)),ABS(G11-$B11),"") -> 3 | O11: =IF(AND(ISNUMBER($B11),ISNUMBER(H11)),ABS(H11-$B11),"") -> 0 | P11: =IF(AND(ISNUMBER($B11),ISNUMBER(I11)),ABS(I11-$B11),"") -> 0
A12: =Data!$A12 -> AtoM | B12: =Scoring!S12 -> NA | C12: =IF(AND(Scoring!N12>=Parameters!$C$57,Scoring!Q12>=Parameters!$C$59),Scoring!O12/Scoring!N12*100,"NA") -> NA | D12: =IF(AND(Scoring!N12>=Parameters!$C$58,Scoring!Q12>=Parameters!$C$59),Scoring!O12/Scoring!N12*100,"NA") -> NA | E12: =IF(AND((Scoring!N12-IF(ISNUMBER(Scoring!E12),Parameters!$E$7,0)+IF(ISNUMBER(IF(Verification!D12<>"",Verification!D12,IF(Coding!AG12=0,"NA",IF(AND(Parameters!$C$39=1,ISNUMBER(Calc!B12),Calc!B12<=Parameters!$C$40),0,MIN(Coding!AG12,Parameters!$C$37)/Parameters!$C$37)))),Parameters!$E$7,0))>=Parameters!$C$56,Scoring!Q12>=Parameters!$C$59),(Scoring!O12-IF(ISNUMBER(Scoring!E12),Parameters!$E$7*Scoring!E12,0)+IF(ISNUMBER(IF(Verification!D12<>"",Verification!D12,IF(Coding!AG12=0,"NA",IF(AND(Parameters!$C$39=1,ISNUMBER(Calc!B12),Calc!B12<=Parameters!$C$40),0,MIN(Coding!AG12,Parameters!$C$37)/Parameters!$C$37)))),Parameters!$E$7*IF(Verification!D12<>"",Verification!D12,IF(Coding!AG12=0,"NA",IF(AND(Parameters!$C$39=1,ISNUMBER(Calc!B12),Calc!B12<=Parameters!$C$40),0,MIN(Coding!AG12,Parameters!$C$37)/Parameters!$C$37))),0))/(Scoring!N12-IF(ISNUMBER(Scoring!E12),Parameters!$E$7,0)+IF(ISNUMBER(IF(Verification!D12<>"",Verification!D12,IF(Coding!AG12=0,"NA",IF(AND(Parameters!$C$39=1,ISNUMBER(Calc!B12),Calc!B12<=Parameters!$C$40),0,MIN(Coding!AG12,Parameters!$C$37)/Parameters!$C$37)))),Parameters!$E$7,0))*100,"NA") -> NA | F12: =IF(Scoring!R12="Yes",AVERAGE(Scoring!D12:J12)*100,"NA") -> NA | G12: =IF(AND((Scoring!N12-IF(ISNUMBER(Scoring!F12),Parameters!$E$8,0)+IF(ISNUMBER(IF(Verification!E12<>"",Scoring!F12,Calc!V12)),Parameters!$E$8,0))>=Parameters!$C$56,Scoring!Q12>=Parameters!$C$59),(Scoring!O12-IF(ISNUMBER(Scoring!F12),Parameters!$E$8*Scoring!F12,0)+IF(ISNUMBER(IF(Verification!E12<>"",Scoring!F12,Calc!V12)),Parameters!$E$8*IF(Verification!E12<>"",Scoring!F12,Calc!V12),0))/(Scoring!N12-IF(ISNUMBER(Scoring!F12),Parameters!$E$8,0)+IF(ISNUMBER(IF(Verification!E12<>"",Scoring!F12,Calc!V12)),Parameters!$E$8,0))*100,"NA") -> NA | H12: =IF(ISNUMBER(Scoring!S12),(Scoring!N12/Parameters!$E$13)*Scoring!S12+(1-Scoring!N12/Parameters!$E$13)*Summary!$B$9,"NA") -> NA | I12: =IF(AND(ISNUMBER(Scoring!S12),COUNT(Scoring!E12,Scoring!F12)>0),Scoring!S12,"NA") -> NA | J12: =IF(AND(ISNUMBER($B12),ISNUMBER(C12)),ABS(C12-$B12),"") | K12: =IF(AND(ISNUMBER($B12),ISNUMBER(D12)),ABS(D12-$B12),"") | L12: =IF(AND(ISNUMBER($B12),ISNUMBER(E12)),ABS(E12-$B12),"") | M12: =IF(AND(ISNUMBER($B12),ISNUMBER(F12)),ABS(F12-$B12),"") | N12: =IF(AND(ISNUMBER($B12),ISNUMBER(G12)),ABS(G12-$B12),"") | O12: =IF(AND(ISNUMBER($B12),ISNUMBER(H12)),ABS(H12-$B12),"") | P12: =IF(AND(ISNUMBER($B12),ISNUMBER(I12)),ABS(I12-$B12),"")
A13: =Data!$A13 -> Avalon Media System | B13: =Scoring!S13 -> 85.75 | C13: =IF(AND(Scoring!N13>=Parameters!$C$57,Scoring!Q13>=Parameters!$C$59),Scoring!O13/Scoring!N13*100,"NA") -> 85.75 | D13: =IF(AND(Scoring!N13>=Parameters!$C$58,Scoring!Q13>=Parameters!$C$59),Scoring!O13/Scoring!N13*100,"NA") -> 85.75 | E13: =IF(AND((Scoring!N13-IF(ISNUMBER(Scoring!E13),Parameters!$E$7,0)+IF(ISNUMBER(IF(Verification!D13<>"",Verification!D13,IF(Coding!AG13=0,"NA",IF(AND(Parameters!$C$39=1,ISNUMBER(Calc!B13),Calc!B13<=Parameters!$C$40),0,MIN(Coding!AG13,Parameters!$C$37)/Parameters!$C$37)))),Parameters!$E$7,0))>=Parameters!$C$56,Scoring!Q13>=Parameters!$C$59),(Scoring!O13-IF(ISNUMBER(Scoring!E13),Parameters!$E$7*Scoring!E13,0)+IF(ISNUMBER(IF(Verification!D13<>"",Verification!D13,IF(Coding!AG13=0,"NA",IF(AND(Parameters!$C$39=1,ISNUMBER(Calc!B13),Calc!B13<=Parameters!$C$40),0,MIN(Coding!AG13,Parameters!$C$37)/Parameters!$C$37)))),Parameters!$E$7*IF(Verification!D13<>"",Verification!D13,IF(Coding!AG13=0,"NA",IF(AND(Parameters!$C$39=1,ISNUMBER(Calc!B13),Calc!B13<=Parameters!$C$40),0,MIN(Coding!AG13,Parameters!$C$37)/Parameters!$C$37))),0))/(Scoring!N13-IF(ISNUMBER(Scoring!E13),Parameters!$E$7,0)+IF(ISNUMBER(IF(Verification!D13<>"",Verification!D13,IF(Coding!AG13=0,"NA",IF(AND(Parameters!$C$39=1,ISNUMBER(Calc!B13),Calc!B13<=Parameters!$C$40),0,MIN(Coding!AG13,Parameters!$C$37)/Parameters!$C$37)))),Parameters!$E$7,0))*100,"NA") -> 85.75 | F13: =IF(Scoring!R13="Yes",AVERAGE(Scoring!D13:J13)*100,"NA") -> 87.5 | G13: =IF(AND((Scoring!N13-IF(ISNUMBER(Scoring!F13),Parameters!$E$8,0)+IF(ISNUMBER(IF(Verification!E13<>"",Scoring!F13,Calc!V13)),Parameters!$E$8,0))>=Parameters!$C$56,Scoring!Q13>=Parameters!$C$59),(Scoring!O13-IF(ISNUMBER(Scoring!F13),Parameters!$E$8*Scoring!F13,0)+IF(ISNUMBER(IF(Verification!E13<>"",Scoring!F13,Calc!V13)),Parameters!$E$8*IF(Verification!E13<>"",Scoring!F13,Calc!V13),0))/(Scoring!N13-IF(ISNUMBER(Scoring!F13),Parameters!$E$8,0)+IF(ISNUMBER(IF(Verification!E13<>"",Scoring!F13,Calc!V13)),Parameters!$E$8,0))*100,"NA") -> 82.75 | H13: =IF(ISNUMBER(Scoring!S13),(Scoring!N13/Parameters!$E$13)*Scoring!S13+(1-Scoring!N13/Parameters!$E$13)*Summary!$B$9,"NA") -> 85.75 | I13: =IF(AND(ISNUMBER(Scoring!S13),COUNT(Scoring!E13,Scoring!F13)>0),Scoring!S13,"NA") -> 85.75 | J13: =IF(AND(ISNUMBER($B13),ISNUMBER(C13)),ABS(C13-$B13),"") -> 0 | K13: =IF(AND(ISNUMBER($B13),ISNUMBER(D13)),ABS(D13-$B13),"") -> 0 | L13: =IF(AND(ISNUMBER($B13),ISNUMBER(E13)),ABS(E13-$B13),"") -> 0 | M13: =IF(AND(ISNUMBER($B13),ISNUMBER(F13)),ABS(F13-$B13),"") -> 1.75 | N13: =IF(AND(ISNUMBER($B13),ISNUMBER(G13)),ABS(G13-$B13),"") -> 3 | O13: =IF(AND(ISNUMBER($B13),ISNUMBER(H13)),ABS(H13-$B13),"") -> 0 | P13: =IF(AND(ISNUMBER($B13),ISNUMBER(I13)),ABS(I13-$B13),"") -> 0
... A113: =Data!$A113 -> Zotero | B113: =Scoring!S113 -> 64 | C113: =IF(AND(Scoring!N113>=Parameters!$C$57,Scoring!Q113>=Parameters!$C$59),Scoring!O113/Scoring!N113*100,"NA") -> 64 | D113: =IF(AND(Scoring!N113>=Parameters!$C$58,Scoring!Q113>=Parameters!$C$59),Scoring!O113/Scoring!N113*100,"NA") -> 64 | E113: =IF(AND((Scoring!N113-IF(ISNUMBER(Scoring!E113),Parameters!$E$7,0)+IF(ISNUMBER(IF(Verification!D113<>"",Verification!D113,IF(Coding!AG113=0,"NA",IF(AND(Parameters!$C$39=1,ISNUMBER(Calc!B113),Calc!B113<=Parameters!$C$40),0,MIN(Coding!AG113,Parameters!$C$37)/Parameters!$C$37)))),Parameters!$E$7,0))>=Parameters!$C$56,Scoring!Q113>=Parameters!$C$59),(Scoring!O113-IF(ISNUMBER(Scoring!E113),Parameters!$E$7*Scoring!E113,0)+IF(ISNUMBER(IF(Verification!D113<>"",Verification!D113,IF(Coding!AG113=0,"NA",IF(AND(Parameters!$C$39=1,ISNUMBER(Calc!B113),Calc!B113<=Parameters!$C$40),0,MIN(Coding!AG113,Parameters!$C$37)/Parameters!$C$37)))),Parameters!$E$7*IF(Verification!D113<>"",Verification!D113,IF(Coding!AG113=0,"NA",IF(AND(Parameters!$C$39=1,ISNUMBER(Calc!B113),Calc!B113<=Parameters!$C$40),0,MIN(Coding!AG113,Parameters!$C$37)/Parameters!$C$37))),0))/(Scoring!N113-IF(ISNUMBER(Scoring!E113),Parameters!$E$7,0)+IF(ISNUMBER(IF(Verification!D113<>"",Verification!D113,IF(Coding!AG113=0,"NA",IF(AND(Parameters!$C$39=1,ISNUMBER(Calc!B113),Calc!B113<=Parameters!$C$40),0,MIN(Coding!AG113,Parameters!$C$37)/Parameters!$C$37)))),Parameters!$E$7,0))*100,"NA") -> 64 | F113: =IF(Scoring!R113="Yes",AVERAGE(Scoring!D113:J113)*100,"NA") -> 71.428571 | G113: =IF(AND((Scoring!N113-IF(ISNUMBER(Scoring!F113),Parameters!$E$8,0)+IF(ISNUMBER(IF(Verification!E113<>"",Scoring!F113,Calc!V113)),Parameters!$E$8,0))>=Parameters!$C$56,Scoring!Q113>=Parameters!$C$59),(Scoring!O113-IF(ISNUMBER(Scoring!F113),Parameters!$E$8*Scoring!F113,0)+IF(ISNUMBER(IF(Verification!E113<>"",Scoring!F113,Calc!V113)),Parameters!$E$8*IF(Verification!E113<>"",Scoring!F113,Calc!V113),0))/(Scoring!N113-IF(ISNUMBER(Scoring!F113),Parameters!$E$8,0)+IF(ISNUMBER(IF(Verification!E113<>"",Scoring!F113,Calc!V113)),Parameters!$E$8,0))*100,"NA") -> 61 | H113: =IF(ISNUMBER(Scoring!S113),(Scoring!N113/Parameters!$E$13)*Scoring!S113+(1-Scoring!N113/Parameters!$E$13)*Summary!$B$9,"NA") -> 64 | I113: =IF(AND(ISNUMBER(Scoring!S113),COUNT(Scoring!E113,Scoring!F113)>0),Scoring!S113,"NA") -> 64 | J113: =IF(AND(ISNUMBER($B113),ISNUMBER(C113)),ABS(C113-$B113),"") -> 0 | K113: =IF(AND(ISNUMBER($B113),ISNUMBER(D113)),ABS(D113-$B113),"") -> 0 | L113: =IF(AND(ISNUMBER($B113),ISNUMBER(E113)),ABS(E113-$B113),"") -> 0 | M113: =IF(AND(ISNUMBER($B113),ISNUMBER(F113)),ABS(F113-$B113),"") -> 7.4285714 | N113: =IF(AND(ISNUMBER($B113),ISNUMBER(G113)),ABS(G113-$B113),"") -> 3 | O113: =IF(AND(ISNUMBER($B113),ISNUMBER(H113)),ABS(H113-$B113),"") -> 0 | P113: =IF(AND(ISNUMBER($B113),ISNUMBER(I113)),ABS(I113-$B113),"") -> 0

Sheet Descriptive
A1: Descriptive / contextual variables — reported, NOT scored (078 membership numbers, 107 membership programme URL)
A3: Service | B3: Provider | C3: 078 Membership numbers | D3: log10(membership) | E3: 107 Membership programme URL given? | F3: Membership model evidence? | G3: Community Engagement score | I3: Summary
A4: =Data!$A2 -> 2i2c | B4: =Data!$B2 -> Code for Science and Society | C4: =IF(Data!$S2="","",Data!$S2) | D4: =IF(AND(ISNUMBER(C4),C4>0),LOG10(C4),"") | E4: =IF(Data!$T2<>"","Yes","No") -> No | F4: =IF(OR(AND(ISNUMBER(C4),C4>0),E4="Yes"),"Yes","No") -> No | G4: =Scoring!S2 -> NA | I4: Repos with a membership number reported | J4: =COUNT(C4:C115) -> 54
A5: =Data!$A3 -> Academic Preservation Trust (APTrust) | B5: =Data!$B3 -> Academic Preservation Trust (APTrust) | C5: =IF(Data!$S3="","",Data!$S3) -> 21 | D5: =IF(AND(ISNUMBER(C5),C5>0),LOG10(C5),"") -> 1.3222193 | E5: =IF(Data!$T3<>"","Yes","No") -> Yes | F5: =IF(OR(AND(ISNUMBER(C5),C5>0),E5="Yes"),"Yes","No") -> Yes | G5: =Scoring!S3 -> 94 | I5: …of which equal to 0 | J5: =COUNTIF(C4:C115,0) -> 8
A6: =Data!$A4 -> AfricArXiv | B6: =Data!$B4 -> UbuntuNet Alliance | C6: =IF(Data!$S4="","",Data!$S4) | D6: =IF(AND(ISNUMBER(C6),C6>0),LOG10(C6),"") | E6: =IF(Data!$T4<>"","Yes","No") -> No | F6: =IF(OR(AND(ISNUMBER(C6),C6>0),E6="Yes"),"Yes","No") -> No | G6: =Scoring!S4 -> NA | I6: Median membership (all reported, incl. 0) | J6: =IFERROR(MEDIAN(C4:C115),"n/a") -> 32
A7: =Data!$A5 -> Arches Heritage Data Management Platform | B7: =Data!$B5 -> Getty Conservation Institute (GCI) | C7: =IF(Data!$S5="","",Data!$S5) | D7: =IF(AND(ISNUMBER(C7),C7>0),LOG10(C7),"") | E7: =IF(Data!$T5<>"","Yes","No") -> No | F7: =IF(OR(AND(ISNUMBER(C7),C7>0),E7="Yes"),"Yes","No") -> No | G7: =Scoring!S5 -> 100 | I7: Maximum membership | J7: =MAX(C4:C115) -> 20000
A8: =Data!$A6 -> Archipelago Commons | B8: =Data!$B6 -> Metropolitan New York Library Council | C8: =IF(Data!$S6="","",Data!$S6) | D8: =IF(AND(ISNUMBER(C8),C8>0),LOG10(C8),"") | E8: =IF(Data!$T6<>"","Yes","No") -> No | F8: =IF(OR(AND(ISNUMBER(C8),C8>0),E8="Yes"),"Yes","No") -> No | G8: =Scoring!S6 -> 82.25 | I8: Repos with membership programme URL | J8: =COUNTIF(E4:E115,"Yes") -> 30
A9: =Data!$A7 -> Archival Resource Key | B9: =Data!$B7 -> ARK Alliance | C9: =IF(Data!$S7="","",Data!$S7) | D9: =IF(AND(ISNUMBER(C9),C9>0),LOG10(C9),"") | E9: =IF(Data!$T7<>"","Yes","No") -> No | F9: =IF(OR(AND(ISNUMBER(C9),C9>0),E9="Yes"),"Yes","No") -> No | G9: =Scoring!S7 -> 75.641026 | I9: Mean score – with membership evidence | J9: =IFERROR(AVERAGEIFS(G4:G115,F4:F115,"Yes"),"n/a") -> 82.422317
A10: =Data!$A8 -> Archivematica | B10: =Data!$B8 -> Artefactual | C10: =IF(Data!$S8="","",Data!$S8) | D10: =IF(AND(ISNUMBER(C10),C10>0),LOG10(C10),"") | E10: =IF(Data!$T8<>"","Yes","No") -> No | F10: =IF(OR(AND(ISNUMBER(C10),C10>0),E10="Yes"),"Yes","No") -> No | G10: =Scoring!S8 -> NA | I10: Mean score – without membership evidence | J10: =IFERROR(AVERAGEIFS(G4:G115,F4:F115,"No"),"n/a") -> 69.539046
A11: =Data!$A9 -> ArchivesSpace | B11: =Data!$B9 -> ArchivesSpace | C11: =IF(Data!$S9="","",Data!$S9) -> 500 | D11: =IF(AND(ISNUMBER(C11),C11>0),LOG10(C11),"") -> 2.69897 | E11: =IF(Data!$T9<>"","Yes","No") -> Yes | F11: =IF(OR(AND(ISNUMBER(C11),C11>0),E11="Yes"),"Yes","No") -> Yes | G11: =Scoring!S9 -> 100 | I11: n scored – with membership evidence | J11: =COUNTIFS(F4:F115,"Yes",G4:G115,">=0") -> 43
A12: =Data!$A10 -> ARGOS | B12: =Data!$B10 -> OpenAIRE | C12: =IF(Data!$S10="","",Data!$S10) -> 52 | D12: =IF(AND(ISNUMBER(C12),C12>0),LOG10(C12),"") -> 1.7160033 | E12: =IF(Data!$T10<>"","Yes","No") -> Yes | F12: =IF(OR(AND(ISNUMBER(C12),C12>0),E12="Yes"),"Yes","No") -> Yes | G12: =Scoring!S10 -> 100 | I12: n scored – without membership evidence | J12: =COUNTIFS(F4:F115,"No",G4:G115,">=0") -> 44
A13: =Data!$A11 -> arXiv | B13: =Data!$B11 -> Cornell University | C13: =IF(Data!$S11="","",Data!$S11) -> 290 | D13: =IF(AND(ISNUMBER(C13),C13>0),LOG10(C13),"") -> 2.462398 | E13: =IF(Data!$T11<>"","Yes","No") -> No | F13: =IF(OR(AND(ISNUMBER(C13),C13>0),E13="Yes"),"Yes","No") -> Yes | G13: =Scoring!S11 -> 65.75
A14: =Data!$A12 -> AtoM | B14: =Data!$B12 -> Artefactual | C14: =IF(Data!$S12="","",Data!$S12) | D14: =IF(AND(ISNUMBER(C14),C14>0),LOG10(C14),"") | E14: =IF(Data!$T12<>"","Yes","No") -> No | F14: =IF(OR(AND(ISNUMBER(C14),C14>0),E14="Yes"),"Yes","No") -> No | G14: =Scoring!S12 -> NA | I14: Interpretation note: a membership "0" most plausibly means no membership model, not a small one. These variables describe community size/structure and are kept out of the score, as specified in the OISI draft.
A15: =Data!$A13 -> Avalon Media System | B15: =Data!$B13 -> Indiana University Libraries | C15: =IF(Data!$S13="","",Data!$S13) | D15: =IF(AND(ISNUMBER(C15),C15>0),LOG10(C15),"") | E15: =IF(Data!$T13<>"","Yes","No") -> No | F15: =IF(OR(AND(ISNUMBER(C15),C15>0),E15="Yes"),"Yes","No") -> No | G15: =Scoring!S13 -> 85.75
A16: =Data!$A14 -> Biodiversity Heritage Library | B16: =Data!$B14 -> BHL Consortium | C16: =IF(Data!$S14="","",Data!$S14) -> 38 | D16: =IF(AND(ISNUMBER(C16),C16>0),LOG10(C16),"") -> 1.5797836 | E16: =IF(Data!$T14<>"","Yes","No") -> Yes | F16: =IF(OR(AND(ISNUMBER(C16),C16>0),E16="Yes"),"Yes","No") -> Yes | G16: =Scoring!S14 -> 76.25
A17: =Data!$A15 -> bioRxiv | B17: =Data!$B15 -> Cold Spring Harbor Laboratory | C17: =IF(Data!$S15="","",Data!$S15) | D17: =IF(AND(ISNUMBER(C17),C17>0),LOG10(C17),"") | E17: =IF(Data!$T15<>"","Yes","No") -> No | F17: =IF(OR(AND(ISNUMBER(C17),C17>0),E17="Yes"),"Yes","No") -> No | G17: =Scoring!S15 -> NA
A18: =Data!$A16 -> BitCurator Environment | B18: =Data!$B16 -> BitCurator Consortium | C18: =IF(Data!$S16="","",Data!$S16) -> 30 | D18: =IF(AND(ISNUMBER(C18),C18>0),LOG10(C18),"") -> 1.4771213 | E18: =IF(Data!$T16<>"","Yes","No") -> Yes | F18: =IF(OR(AND(ISNUMBER(C18),C18>0),E18="Yes"),"Yes","No") -> Yes | G18: =Scoring!S16 -> 88.25
A19: =Data!$A17 -> Blacklight | B19: =Data!$B17 -> Blacklight | C19: =IF(Data!$S17="","",Data!$S17) | D19: =IF(AND(ISNUMBER(C19),C19>0),LOG10(C19),"") | E19: =IF(Data!$T17<>"","Yes","No") -> No | F19: =IF(OR(AND(ISNUMBER(C19),C19>0),E19="Yes"),"Yes","No") -> No | G19: =Scoring!S17 -> 85.05
A20: =Data!$A18 -> BrCRIS | B20: =Data!$B18 -> IBICT | C20: =IF(Data!$S18="","",Data!$S18) | D20: =IF(AND(ISNUMBER(C20),C20>0),LOG10(C20),"") | E20: =IF(Data!$T18<>"","Yes","No") -> No | F20: =IF(OR(AND(ISNUMBER(C20),C20>0),E20="Yes"),"Yes","No") -> No | G20: =Scoring!S18 -> NA
A21: =Data!$A19 -> Browsertrix | B21: =Data!$B19 -> Webrecorder | C21: =IF(Data!$S19="","",Data!$S19) | D21: =IF(AND(ISNUMBER(C21),C21>0),LOG10(C21),"") | E21: =IF(Data!$T19<>"","Yes","No") -> No | F21: =IF(OR(AND(ISNUMBER(C21),C21>0),E21="Yes"),"Yes","No") -> No | G21: =Scoring!S19 -> 54.044118
A22: =Data!$A20 -> CLOCKSS | B22: =Data!$B20 -> CLOCKSS | C22: =IF(Data!$S20="","",Data!$S20) -> 968 | D22: =IF(AND(ISNUMBER(C22),C22>0),LOG10(C22),"") -> 2.9858754 | E22: =IF(Data!$T20<>"","Yes","No") -> Yes | F22: =IF(OR(AND(ISNUMBER(C22),C22>0),E22="Yes"),"Yes","No") -> Yes | G22: =Scoring!S20 -> NA
A23: =Data!$A21 -> COAR International Repository Directory (IRD) | B23: =Data!$B21 -> COAR | C23: =IF(Data!$S21="","",Data!$S21) | D23: =IF(AND(ISNUMBER(C23),C23>0),LOG10(C23),"") | E23: =IF(Data!$T21<>"","Yes","No") -> No | F23: =IF(OR(AND(ISNUMBER(C23),C23>0),E23="Yes"),"Yes","No") -> No | G23: =Scoring!S21 -> 56.05
A24: =Data!$A22 -> COAR Notify | B24: =Data!$B22 -> COAR | C24: =IF(Data!$S22="","",Data!$S22) | D24: =IF(AND(ISNUMBER(C24),C24>0),LOG10(C24),"") | E24: =IF(Data!$T22<>"","Yes","No") -> No | F24: =IF(OR(AND(ISNUMBER(C24),C24>0),E24="Yes"),"Yes","No") -> No | G24: =Scoring!S22 -> 62.7
A25: =Data!$A23 -> CollectiveAccess | B25: =Data!$B23 -> Whirl-i-Gig | C25: =IF(Data!$S23="","",Data!$S23) | D25: =IF(AND(ISNUMBER(C25),C25>0),LOG10(C25),"") | E25: =IF(Data!$T23<>"","Yes","No") -> No | F25: =IF(OR(AND(ISNUMBER(C25),C25>0),E25="Yes"),"Yes","No") -> No | G25: =Scoring!S23 -> NA
A26: =Data!$A24 -> CORE | B26: =Data!$B24 -> The Open University | C26: =IF(Data!$S24="","",Data!$S24) | D26: =IF(AND(ISNUMBER(C26),C26>0),LOG10(C26),"") | E26: =IF(Data!$T24<>"","Yes","No") -> No | F26: =IF(OR(AND(ISNUMBER(C26),C26>0),E26="Yes"),"Yes","No") -> No | G26: =Scoring!S24 -> 80.769231
... A115: =Data!$A113 -> Zotero | B115: =Data!$B113 -> Digital Scholar | C115: =IF(Data!$S113="","",Data!$S113) | D115: =IF(AND(ISNUMBER(C115),C115>0),LOG10(C115),"") | E115: =IF(Data!$T113<>"","Yes","No") -> No | F115: =IF(OR(AND(ISNUMBER(C115),C115>0),E115="Yes"),"Yes","No") -> No | G115: =Scoring!S113 -> 64

Sheet Audit
A1: Audit of 938 text coding: random sample of 20 repos where the coder found at least one category (seed 42, drawn from 29 coded repos)
A2: Read the 938 text, check each coded category is supported, and record your verdict. Claude's first-pass check is a draft only; the human verdict column is yours to fill. Text is shown with HTML tags removed (extract only; Data holds the source).
A4: Data row | B4: Service | C4: 938 text (HTML stripped, first 900 chars) | D4: Categories coded by the dictionary (live) | E4: In 038 checklist too? | F4: Claude first-pass check | G4: Human reviewer verdict | H4: Reviewer notes
A5: 6 | B5: =Data!$A6 -> Archipelago Commons | C5: Questions, use cases, and ideas can be shared with the Archipelago Google Groups forum and on the Archipelago Commons Slack Channel. Stakeholders are also invited to visit, subscribe to, and participate in various active GitHub repositories. | D5: =IF(Coding!N6=1,Dictionary!$A$5&"; ","")&IF(Coding!O6=1,Dictionary!$A$6&"; ","")&IF(Coding!P6=1,Dictionary!$A$7&"; ","")&IF(Coding!Q6=1,Dictionary!$A$8&"; ","")&IF(Coding!R6=1,Dictionary!$A$9&"; ","")&IF(Coding!S6=1,Dictionary!$A$10&"; ","")&IF(Coding!T6=1,Dictionary!$A$11&"; ","")&IF(Coding!U6=1,Dictionary!$A$12&"; ","")&IF(Coding!V6=1,Dictionary!$A$13&"; ","")&IF(Coding!W6=1,Dictionary!$A$14&"; ","")&IF(Coding!X6=1,Dictionary!$A$15&"; ","")&IF(Coding!Y6=1,Dictionary!$A$16&"; ","") -> Mailing lists and discussion forums (including Slack); | E5: =IF(Coding!AH6=1,"Both filled; coded not in checklist: "&Coding!AJ6,"Only 938 filled") -> Both filled; coded not in checklist: 0 | F5: Correct: every coded category is supported by the text.
A6: 11 | B6: =Data!$A11 -> arXiv | C6: arXiv governance consists of three advisory councils with volunteer representatives from across our stakeholder groups. The Science Advisory Council represents the scientific and research community of arXiv (those who create valuable content and who systematically read this content); the Institutions Advisory Council represents the scholarly communications community, including librarians and information science and publishing professionals; the Editorial Advisory Council functions as arXiv's Editorial Board and is both advisory and operational (members are the chairs of the Section Editorial Committees). Section Editorial Committees recruit and onboard arXiv's moderators. arXiv's moderators are volunteer subject matter experts with terminal degrees in their field. They evaluate each submission’s content and category, following arXiv policies. Currently there are 200+ arXiv moderators inv | D6: =IF(Coding!N11=1,Dictionary!$A$5&"; ","")&IF(Coding!O11=1,Dictionary!$A$6&"; ","")&IF(Coding!P11=1,Dictionary!$A$7&"; ","")&IF(Coding!Q11=1,Dictionary!$A$8&"; ","")&IF(Coding!R11=1,Dictionary!$A$9&"; ","")&IF(Coding!S11=1,Dictionary!$A$10&"; ","")&IF(Coding!T11=1,Dictionary!$A$11&"; ","")&IF(Coding!U11=1,Dictionary!$A$12&"; ","")&IF(Coding!V11=1,Dictionary!$A$13&"; ","")&IF(Coding!W11=1,Dictionary!$A$14&"; ","")&IF(Coding!X11=1,Dictionary!$A$15&"; ","")&IF(Coding!Y11=1,Dictionary!$A$16&"; ","") -> Interest, working, user, or advisory groups; | E6: =IF(Coding!AH11=1,"Both filled; coded not in checklist: "&Coding!AJ11,"Only 938 filled") -> Only 938 filled | F6: Correct: every coded category is supported by the text.
A7: 25 | B7: =Data!$A25 -> COUNTER Code of Practice | C7: COUNTER Members have voting rights at our annual general meeting, are eligible to join our committees and working groups as vacancies arise, and receive our consultations and quarterly newsletters and updates. We also work with our members on projects including the development of tools, training events, and resources. https://www.countermetrics.org/members/ | D7: =IF(Coding!N25=1,Dictionary!$A$5&"; ","")&IF(Coding!O25=1,Dictionary!$A$6&"; ","")&IF(Coding!P25=1,Dictionary!$A$7&"; ","")&IF(Coding!Q25=1,Dictionary!$A$8&"; ","")&IF(Coding!R25=1,Dictionary!$A$9&"; ","")&IF(Coding!S25=1,Dictionary!$A$10&"; ","")&IF(Coding!T25=1,Dictionary!$A$11&"; ","")&IF(Coding!U25=1,Dictionary!$A$12&"; ","")&IF(Coding!V25=1,Dictionary!$A$13&"; ","")&IF(Coding!W25=1,Dictionary!$A$14&"; ","")&IF(Coding!X25=1,Dictionary!$A$15&"; ","")&IF(Coding!Y25=1,Dictionary!$A$16&"; ","") -> Annual meetings; Interest, working, user, or advisory groups; Webinars and training; | E7: =IF(Coding!AH25=1,"Both filled; coded not in checklist: "&Coding!AJ25,"Only 938 filled") -> Both filled; coded not in checklist: 0 | F7: Correct: every coded category is supported by the text.
A8: 26 | B8: =Data!$A26 -> Creative Commons Licenses | C8: Dedicated Community Engagement Manager role, annual Global Summit for community members, periodic Community Conversations on emerging topics such as AI and Creative Commons, Community Spotlights on blog | D8: =IF(Coding!N26=1,Dictionary!$A$5&"; ","")&IF(Coding!O26=1,Dictionary!$A$6&"; ","")&IF(Coding!P26=1,Dictionary!$A$7&"; ","")&IF(Coding!Q26=1,Dictionary!$A$8&"; ","")&IF(Coding!R26=1,Dictionary!$A$9&"; ","")&IF(Coding!S26=1,Dictionary!$A$10&"; ","")&IF(Coding!T26=1,Dictionary!$A$11&"; ","")&IF(Coding!U26=1,Dictionary!$A$12&"; ","")&IF(Coding!V26=1,Dictionary!$A$13&"; ","")&IF(Coding!W26=1,Dictionary!$A$14&"; ","")&IF(Coding!X26=1,Dictionary!$A$15&"; ","")&IF(Coding!Y26=1,Dictionary!$A$16&"; ","") -> Annual meetings; Blogs; Community calls; Staff roles with responsibility for community engagement; | E8: =IF(Coding!AH26=1,"Both filled; coded not in checklist: "&Coding!AJ26,"Only 938 filled") -> Only 938 filled | F8: Correct: every coded category is supported by the text.
A9: 27 | B9: =Data!$A27 -> Crossref Metadata Retrieval | C9: Crossref has a large community engagement program, with around 10 staff who have all taken the CSCCE Foundations course. Activities comprise: onboarding and education: https://www.crossref.org/members-area/ multilingual webinars and in-person events: https://www.crossref.org/events/ working and advisory groups: https://www.crossref.org/working-groups/ speaking at and participating in meetings and other infrastructures' working groups ambassador program (51 people in 37 countries): https://www.crossref.org/community/ambassadors/ sponsoring organisations (around 120, helping smaller organizations join for free and enrich metadata - a somewhat train-the-trainer activity): https://www.crossref.org/membership/about-sponsors/ Global Equitable Membership (GEM) program: https://www.crossref.org/gem/ The PLACE collaboration with COPE, OASPA, and DOAJ: https://theplace.discourse.group/ Community f | D9: =IF(Coding!N27=1,Dictionary!$A$5&"; ","")&IF(Coding!O27=1,Dictionary!$A$6&"; ","")&IF(Coding!P27=1,Dictionary!$A$7&"; ","")&IF(Coding!Q27=1,Dictionary!$A$8&"; ","")&IF(Coding!R27=1,Dictionary!$A$9&"; ","")&IF(Coding!S27=1,Dictionary!$A$10&"; ","")&IF(Coding!T27=1,Dictionary!$A$11&"; ","")&IF(Coding!U27=1,Dictionary!$A$12&"; ","")&IF(Coding!V27=1,Dictionary!$A$13&"; ","")&IF(Coding!W27=1,Dictionary!$A$14&"; ","")&IF(Coding!X27=1,Dictionary!$A$15&"; ","")&IF(Coding!Y27=1,Dictionary!$A$16&"; ","") -> Conference participation; Interest, working, user, or advisory groups; Mailing lists and discussion forums (including Slack); Volunteer or ambassador network; Webinars and training; | E9: =IF(Coding!AH27=1,"Both filled; coded not in checklist: "&Coding!AJ27,"Only 938 filled") -> Only 938 filled | F9: Correct: every coded category is supported by the text.
A10: 38 | B10: =Data!$A38 -> DOAJ (Directory of Open Access Journals) | C10: DOAJ recomitted to the Principles of Open Scholarly Infrastructure in 2025: https://blog.doaj.org/2025/10/20/doaj-recommits-to-the-principles-of-open-scholarly-infrastructure/ and is an active member of the POSI Working Group. Members of the communnity contribute to the quality and accuracy of DOAJ metadata. DOAJ is a signatory and active proponent of the Helsinki Initiative on Multilingualism. | D10: =IF(Coding!N38=1,Dictionary!$A$5&"; ","")&IF(Coding!O38=1,Dictionary!$A$6&"; ","")&IF(Coding!P38=1,Dictionary!$A$7&"; ","")&IF(Coding!Q38=1,Dictionary!$A$8&"; ","")&IF(Coding!R38=1,Dictionary!$A$9&"; ","")&IF(Coding!S38=1,Dictionary!$A$10&"; ","")&IF(Coding!T38=1,Dictionary!$A$11&"; ","")&IF(Coding!U38=1,Dictionary!$A$12&"; ","")&IF(Coding!V38=1,Dictionary!$A$13&"; ","")&IF(Coding!W38=1,Dictionary!$A$14&"; ","")&IF(Coding!X38=1,Dictionary!$A$15&"; ","")&IF(Coding!Y38=1,Dictionary!$A$16&"; ","") -> Interest, working, user, or advisory groups; | E10: =IF(Coding!AH38=1,"Both filled; coded not in checklist: "&Coding!AJ38,"Only 938 filled") -> Both filled; coded not in checklist: 0 | F10: Partly: "POSI Working Group" is an external group DOAJ joins, not its own engagement group.
A11: 39 | B11: =Data!$A39 -> dokieli | C11: Workshops and presentations at conferences. There is a community chat answering users and developers questions since 2015. W3C TAG Ethical Web Principles: https://www.w3.org/TR/ethical-web-principles/ | D11: =IF(Coding!N39=1,Dictionary!$A$5&"; ","")&IF(Coding!O39=1,Dictionary!$A$6&"; ","")&IF(Coding!P39=1,Dictionary!$A$7&"; ","")&IF(Coding!Q39=1,Dictionary!$A$8&"; ","")&IF(Coding!R39=1,Dictionary!$A$9&"; ","")&IF(Coding!S39=1,Dictionary!$A$10&"; ","")&IF(Coding!T39=1,Dictionary!$A$11&"; ","")&IF(Coding!U39=1,Dictionary!$A$12&"; ","")&IF(Coding!V39=1,Dictionary!$A$13&"; ","")&IF(Coding!W39=1,Dictionary!$A$14&"; ","")&IF(Coding!X39=1,Dictionary!$A$15&"; ","")&IF(Coding!Y39=1,Dictionary!$A$16&"; ","") -> Conference participation; Mailing lists and discussion forums (including Slack); Webinars and training; | E11: =IF(Coding!AH39=1,"Both filled; coded not in checklist: "&Coding!AJ39,"Only 938 filled") -> Only 938 filled | F11: Correct: every coded category is supported by the text.
A12: 40 | B12: =Data!$A40 -> Dryad | C12: There are many ways for the community to engage including becoming a member, contributing code, serving on governance, donating towards fundraising campaigns, working on documentation, participating in listservs and events and working groups. Dryad adopted the POSI Principles in 2020 and is a member of the POSI Adopters Group. Read our full self-audit at https://blog.datadryad.org/2020/12/08/dryads-commitment-to-the-principles-of-open-scholarly-infrastructure/ . | D12: =IF(Coding!N40=1,Dictionary!$A$5&"; ","")&IF(Coding!O40=1,Dictionary!$A$6&"; ","")&IF(Coding!P40=1,Dictionary!$A$7&"; ","")&IF(Coding!Q40=1,Dictionary!$A$8&"; ","")&IF(Coding!R40=1,Dictionary!$A$9&"; ","")&IF(Coding!S40=1,Dictionary!$A$10&"; ","")&IF(Coding!T40=1,Dictionary!$A$11&"; ","")&IF(Coding!U40=1,Dictionary!$A$12&"; ","")&IF(Coding!V40=1,Dictionary!$A$13&"; ","")&IF(Coding!W40=1,Dictionary!$A$14&"; ","")&IF(Coding!X40=1,Dictionary!$A$15&"; ","")&IF(Coding!Y40=1,Dictionary!$A$16&"; ","") -> Interest, working, user, or advisory groups; Mailing lists and discussion forums (including Slack); | E12: =IF(Coding!AH40=1,"Both filled; coded not in checklist: "&Coding!AJ40,"Only 938 filled") -> Only 938 filled | F12: Correct: every coded category is supported by the text.
A13: 53 | B13: =Data!$A53 -> Hyku | C13: Much of Samvera's development is driven by its Interest and Working Groups. These groups come together to discuss and work on matters of particular importance to the Samvera Community at any given time. Samvera's Interest and Working Groups operate in a transparent and inclusive manner. Each proposed new Group sets out a charter and posts an open invitation for participants from across the Community. Generally the meetings are held online and the minutes are posted on Samvera's wiki . | D13: =IF(Coding!N53=1,Dictionary!$A$5&"; ","")&IF(Coding!O53=1,Dictionary!$A$6&"; ","")&IF(Coding!P53=1,Dictionary!$A$7&"; ","")&IF(Coding!Q53=1,Dictionary!$A$8&"; ","")&IF(Coding!R53=1,Dictionary!$A$9&"; ","")&IF(Coding!S53=1,Dictionary!$A$10&"; ","")&IF(Coding!T53=1,Dictionary!$A$11&"; ","")&IF(Coding!U53=1,Dictionary!$A$12&"; ","")&IF(Coding!V53=1,Dictionary!$A$13&"; ","")&IF(Coding!W53=1,Dictionary!$A$14&"; ","")&IF(Coding!X53=1,Dictionary!$A$15&"; ","")&IF(Coding!Y53=1,Dictionary!$A$16&"; ","") -> Interest, working, user, or advisory groups; | E13: =IF(Coding!AH53=1,"Both filled; coded not in checklist: "&Coding!AJ53,"Only 938 filled") -> Both filled; coded not in checklist: 0 | F13: Correct: every coded category is supported by the text.
A14: 58 | B14: =Data!$A58 -> InvenioRDM | C14: We have a community manager role, which is currently held by Sara Gonzalez at Northwestern University. The community manager for community-based aspects of Invenio, including outreach, engagement, requirements gathering, demonstrations for new users, communication of project news and the development and dissemination of written content about the project. | D14: =IF(Coding!N58=1,Dictionary!$A$5&"; ","")&IF(Coding!O58=1,Dictionary!$A$6&"; ","")&IF(Coding!P58=1,Dictionary!$A$7&"; ","")&IF(Coding!Q58=1,Dictionary!$A$8&"; ","")&IF(Coding!R58=1,Dictionary!$A$9&"; ","")&IF(Coding!S58=1,Dictionary!$A$10&"; ","")&IF(Coding!T58=1,Dictionary!$A$11&"; ","")&IF(Coding!U58=1,Dictionary!$A$12&"; ","")&IF(Coding!V58=1,Dictionary!$A$13&"; ","")&IF(Coding!W58=1,Dictionary!$A$14&"; ","")&IF(Coding!X58=1,Dictionary!$A$15&"; ","")&IF(Coding!Y58=1,Dictionary!$A$16&"; ","") -> Staff roles with responsibility for community engagement; | E14: =IF(Coding!AH58=1,"Both filled; coded not in checklist: "&Coding!AJ58,"Only 938 filled") -> Only 938 filled | F14: Correct: every coded category is supported by the text.
A15: 60 | B15: =Data!$A60 -> Islandora | C15: Islandora seeks to foster open, warm communication and consensus-based decision-making. Islandora’s governance groups collaborate to maintain the code and community and set their direction, as well as manage events and meetings in the Islandora community. Membership in the governance groups emerges from a demonstrated commitment to Islandora through substantial volunteer work and/or Islandora Membership. Interest groups form on any topic of interest, and are given the first right of refusal on consultation and work related to their area of interest in the Islandora community. We take a lot of inspiration from the Principles of Open Scholarly Infrastructure, though we have not formally audited ourselves in comparison to those criteria. This is something we'd love to do, just haven't had time yet (and feel like an external org should do the auditing, not us). | D15: =IF(Coding!N60=1,Dictionary!$A$5&"; ","")&IF(Coding!O60=1,Dictionary!$A$6&"; ","")&IF(Coding!P60=1,Dictionary!$A$7&"; ","")&IF(Coding!Q60=1,Dictionary!$A$8&"; ","")&IF(Coding!R60=1,Dictionary!$A$9&"; ","")&IF(Coding!S60=1,Dictionary!$A$10&"; ","")&IF(Coding!T60=1,Dictionary!$A$11&"; ","")&IF(Coding!U60=1,Dictionary!$A$12&"; ","")&IF(Coding!V60=1,Dictionary!$A$13&"; ","")&IF(Coding!W60=1,Dictionary!$A$14&"; ","")&IF(Coding!X60=1,Dictionary!$A$15&"; ","")&IF(Coding!Y60=1,Dictionary!$A$16&"; ","") -> Interest, working, user, or advisory groups; | E15: =IF(Coding!AH60=1,"Both filled; coded not in checklist: "&Coding!AJ60,"Only 938 filled") -> Both filled; coded not in checklist: 0 | F15: Correct: every coded category is supported by the text.
