Workbook

Sheet Summary
A1: Community Analysis equal-metric scoring summary
A2: Services in source snapshot | B2: 112
A3: Metric set | B3: E1, E2, C1, C2, C3, N1; six equally weighted metrics
A4: Weight per metric | B4: 1/6 = 16.6667% (displayed 16.67%)
A5: Scored services | B5: =COUNT(Scoring!K2:K113)
A6: Mean score | B6: =IFERROR(AVERAGE(Scoring!K2:K113),"")
A7: Scoring rule | B7: Equal arithmetic mean of all six metrics; every unavailable metric is scored as 0. No coverage eligibility gate.
A8: Interpretation | B8: Zero-filled scores are conservative evidence-adjusted results; zero due to unavailable data does not establish zero underlying performance.

Sheet Scoring
A1: Service | B1: Provider | C1: Solution category | D1: E1 | E1: E2 | F1: C1 | G1: C2 | H1: C3 | I1: N1 | J1: Metrics with source data (of 6) | K1: Community Analysis score (0-100; missing=0) | L1: Missing metrics scored as 0 | M1: Review status | N1: Data-quality flags
A2: 2i2c | B2: Code for Science and Society | C2: Authoring tool | D2: =IF(ISNUMBER(Verification!B2),Verification!B2,IF(Calc!B2="",0,Calc!B2)) | E2: =IF(ISNUMBER(Verification!C2),Verification!C2,IF(Calc!C2="",0,Calc!C2)) | F2: =IF(ISNUMBER(Verification!D2),Verification!D2,IF(Calc!D2="",0,Calc!D2)) | G2: =IF(ISNUMBER(Verification!E2),Verification!E2,IF(Calc!E2="",0,Calc!E2)) | H2: =IF(ISNUMBER(Verification!F2),Verification!F2,IF(Calc!F2="",0,Calc!F2)) | I2: =IF(ISNUMBER(Verification!G2),Verification!G2,IF(Calc!G2="",0,Calc!G2)) | J2: =COUNT(Calc!B2:G2) | K2: =AVERAGE(D2:I2) | L2: =6-J2 | M2: =IF(COUNTIF(Verification!H2:L2,"Review*")>0,"Scored - coding review","Scored") | N2: 938 coding requires reviewer confirmation; 019 scored from populated repository field; 043 evidence URL should be checked; not scored separately; 116 retained as source evidence only; not scored; 2 unavailable metric(s) scored as 0
A3: Academic Preservation Trust (APTrust) | B3: Academic Preservation Trust (APTrust) | C3: Digital preservation service | D3: =IF(ISNUMBER(Verification!B3),Verification!B3,IF(Calc!B3="",0,Calc!B3)) | E3: =IF(ISNUMBER(Verification!C3),Verification!C3,IF(Calc!C3="",0,Calc!C3)) | F3: =IF(ISNUMBER(Verification!D3),Verification!D3,IF(Calc!D3="",0,Calc!D3)) | G3: =IF(ISNUMBER(Verification!E3),Verification!E3,IF(Calc!E3="",0,Calc!E3)) | H3: =IF(ISNUMBER(Verification!F3),Verification!F3,IF(Calc!F3="",0,Calc!F3)) | I3: =IF(ISNUMBER(Verification!G3),Verification!G3,IF(Calc!G3="",0,Calc!G3)) | J3: =COUNT(Calc!B3:G3) | K3: =AVERAGE(D3:I3) | L3: =6-J3 | M3: =IF(COUNTIF(Verification!H3:L3,"Review*")>0,"Scored - coding review","Scored") | N3: 041 scored from available URL tier; 019 scored from populated repository field; 043 evidence URL should be checked; not scored separately; 116 retained as source evidence only; not scored
A4: AfricArXiv | B4: UbuntuNet Alliance | C4: Repository service | D4: =IF(ISNUMBER(Verification!B4),Verification!B4,IF(Calc!B4="",0,Calc!B4)) | E4: =IF(ISNUMBER(Verification!C4),Verification!C4,IF(Calc!C4="",0,Calc!C4)) | F4: =IF(ISNUMBER(Verification!D4),Verification!D4,IF(Calc!D4="",0,Calc!D4)) | G4: =IF(ISNUMBER(Verification!E4),Verification!E4,IF(Calc!E4="",0,Calc!E4)) | H4: =IF(ISNUMBER(Verification!F4),Verification!F4,IF(Calc!F4="",0,Calc!F4)) | I4: =IF(ISNUMBER(Verification!G4),Verification!G4,IF(Calc!G4="",0,Calc!G4)) | J4: =COUNT(Calc!B4:G4) | K4: =AVERAGE(D4:I4) | L4: =6-J4 | M4: =IF(COUNTIF(Verification!H4:L4,"Review*")>0,"Scored - coding review","Scored") | N4: 043 evidence URL should be checked; not scored separately; 4 unavailable metric(s) scored as 0
A5: Arches Heritage Data Management Platform | B5: Getty Conservation Institute (GCI) | C5: Data management planning tool or service | D5: =IF(ISNUMBER(Verification!B5),Verification!B5,IF(Calc!B5="",0,Calc!B5)) | E5: =IF(ISNUMBER(Verification!C5),Verification!C5,IF(Calc!C5="",0,Calc!C5)) | F5: =IF(ISNUMBER(Verification!D5),Verification!D5,IF(Calc!D5="",0,Calc!D5)) | G5: =IF(ISNUMBER(Verification!E5),Verification!E5,IF(Calc!E5="",0,Calc!E5)) | H5: =IF(ISNUMBER(Verification!F5),Verification!F5,IF(Calc!F5="",0,Calc!F5)) | I5: =IF(ISNUMBER(Verification!G5),Verification!G5,IF(Calc!G5="",0,Calc!G5)) | J5: =COUNT(Calc!B5:G5) | K5: =AVERAGE(D5:I5) | L5: =6-J5 | M5: =IF(COUNTIF(Verification!H5:L5,"Review*")>0,"Scored - coding review","Scored") | N5: 041 scored from available URL tier; 019 scored from populated repository field; 043 evidence URL should be checked; not scored separately; 116 retained as source evidence only; not scored; 2 unavailable metric(s) scored as 0
A6: Archipelago Commons | B6: Metropolitan New York Library Council | C6: Digital library, collection or exhibit platform | Repository software | D6: =IF(ISNUMBER(Verification!B6),Verification!B6,IF(Calc!B6="",0,Calc!B6)) | E6: =IF(ISNUMBER(Verification!C6),Verification!C6,IF(Calc!C6="",0,Calc!C6)) | F6: =IF(ISNUMBER(Verification!D6),Verification!D6,IF(Calc!D6="",0,Calc!D6)) | G6: =IF(ISNUMBER(Verification!E6),Verification!E6,IF(Calc!E6="",0,Calc!E6)) | H6: =IF(ISNUMBER(Verification!F6),Verification!F6,IF(Calc!F6="",0,Calc!F6)) | I6: =IF(ISNUMBER(Verification!G6),Verification!G6,IF(Calc!G6="",0,Calc!G6)) | J6: =COUNT(Calc!B6:G6) | K6: =AVERAGE(D6:I6) | L6: =6-J6 | M6: =IF(COUNTIF(Verification!H6:L6,"Review*")>0,"Scored - coding review","Scored") | N6: 938 coding requires reviewer confirmation; 041 scored from available URL tier; 019 scored from populated repository field; 043 evidence URL should be checked; not scored separately; 116 retained as source evidence only; not scored
A7: Archival Resource Key | B7: ARK Alliance | C7: Standard, specification or protocol | D7: =IF(ISNUMBER(Verification!B7),Verification!B7,IF(Calc!B7="",0,Calc!B7)) | E7: =IF(ISNUMBER(Verification!C7),Verification!C7,IF(Calc!C7="",0,Calc!C7)) | F7: =IF(ISNUMBER(Verification!D7),Verification!D7,IF(Calc!D7="",0,Calc!D7)) | G7: =IF(ISNUMBER(Verification!E7),Verification!E7,IF(Calc!E7="",0,Calc!E7)) | H7: =IF(ISNUMBER(Verification!F7),Verification!F7,IF(Calc!F7="",0,Calc!F7)) | I7: =IF(ISNUMBER(Verification!G7),Verification!G7,IF(Calc!G7="",0,Calc!G7)) | J7: =COUNT(Calc!B7:G7) | K7: =AVERAGE(D7:I7) | L7: =6-J7 | M7: =IF(COUNTIF(Verification!H7:L7,"Review*")>0,"Scored - coding review","Scored") | N7: 041 scored from available URL tier; 019 scored from populated repository field; 043 evidence URL should be checked; not scored separately; 116 retained as source evidence only; not scored; 1 unavailable metric(s) scored as 0
A8: Archivematica | B8: Artefactual | C8: Digital preservation system | D8: =IF(ISNUMBER(Verification!B8),Verification!B8,IF(Calc!B8="",0,Calc!B8)) | E8: =IF(ISNUMBER(Verification!C8),Verification!C8,IF(Calc!C8="",0,Calc!C8)) | F8: =IF(ISNUMBER(Verification!D8),Verification!D8,IF(Calc!D8="",0,Calc!D8)) | G8: =IF(ISNUMBER(Verification!E8),Verification!E8,IF(Calc!E8="",0,Calc!E8)) | H8: =IF(ISNUMBER(Verification!F8),Verification!F8,IF(Calc!F8="",0,Calc!F8)) | I8: =IF(ISNUMBER(Verification!G8),Verification!G8,IF(Calc!G8="",0,Calc!G8)) | J8: =COUNT(Calc!B8:G8) | K8: =AVERAGE(D8:I8) | L8: =6-J8 | M8: =IF(COUNTIF(Verification!H8:L8,"Review*")>0,"Scored - coding review","Scored") | N8: 041 scored from available URL tier; 019 scored from populated repository field; 043 evidence URL should be checked; not scored separately; 116 retained as source evidence only; not scored; 3 unavailable metric(s) scored as 0
A9: ArchivesSpace | B9: ArchivesSpace | C9: Archive information management system | Discovery system | D9: =IF(ISNUMBER(Verification!B9),Verification!B9,IF(Calc!B9="",0,Calc!B9)) | E9: =IF(ISNUMBER(Verification!C9),Verification!C9,IF(Calc!C9="",0,Calc!C9)) | F9: =IF(ISNUMBER(Verification!D9),Verification!D9,IF(Calc!D9="",0,Calc!D9)) | G9: =IF(ISNUMBER(Verification!E9),Verification!E9,IF(Calc!E9="",0,Calc!E9)) | H9: =IF(ISNUMBER(Verification!F9),Verification!F9,IF(Calc!F9="",0,Calc!F9)) | I9: =IF(ISNUMBER(Verification!G9),Verification!G9,IF(Calc!G9="",0,Calc!G9)) | J9: =COUNT(Calc!B9:G9) | K9: =AVERAGE(D9:I9) | L9: =6-J9 | M9: =IF(COUNTIF(Verification!H9:L9,"Review*")>0,"Scored - coding review","Scored") | N9: 041 scored from available URL tier; 019 scored from populated repository field; 043 evidence URL should be checked; not scored separately; 116 retained as source evidence only; not scored; 1 unavailable metric(s) scored as 0
A10: ARGOS | B10: OpenAIRE | C10: Data management planning tool or service | D10: =IF(ISNUMBER(Verification!B10),Verification!B10,IF(Calc!B10="",0,Calc!B10)) | E10: =IF(ISNUMBER(Verification!C10),Verification!C10,IF(Calc!C10="",0,Calc!C10)) | F10: =IF(ISNUMBER(Verification!D10),Verification!D10,IF(Calc!D10="",0,Calc!D10)) | G10: =IF(ISNUMBER(Verification!E10),Verification!E10,IF(Calc!E10="",0,Calc!E10)) | H10: =IF(ISNUMBER(Verification!F10),Verification!F10,IF(Calc!F10="",0,Calc!F10)) | I10: =IF(ISNUMBER(Verification!G10),Verification!G10,IF(Calc!G10="",0,Calc!G10)) | J10: =COUNT(Calc!B10:G10) | K10: =AVERAGE(D10:I10) | L10: =6-J10 | M10: =IF(COUNTIF(Verification!H10:L10,"Review*")>0,"Scored - coding review","Scored") | N10: 019 scored from populated repository field; 043 evidence URL should be checked; not scored separately; 116 retained as source evidence only; not scored; 2 unavailable metric(s) scored as 0
A11: arXiv | B11: Cornell University | C11: Repository service | D11: =IF(ISNUMBER(Verification!B11),Verification!B11,IF(Calc!B11="",0,Calc!B11)) | E11: =IF(ISNUMBER(Verification!C11),Verification!C11,IF(Calc!C11="",0,Calc!C11)) | F11: =IF(ISNUMBER(Verification!D11),Verification!D11,IF(Calc!D11="",0,Calc!D11)) | G11: =IF(ISNUMBER(Verification!E11),Verification!E11,IF(Calc!E11="",0,Calc!E11)) | H11: =IF(ISNUMBER(Verification!F11),Verification!F11,IF(Calc!F11="",0,Calc!F11)) | I11: =IF(ISNUMBER(Verification!G11),Verification!G11,IF(Calc!G11="",0,Calc!G11)) | J11: =COUNT(Calc!B11:G11) | K11: =AVERAGE(D11:I11) | L11: =6-J11 | M11: =IF(COUNTIF(Verification!H11:L11,"Review*")>0,"Scored - coding review","Scored") | N11: 938 coding requires reviewer confirmation; 041 scored from available URL tier; 019 scored from populated repository field; 043 evidence URL should be checked; not scored separately
A12: AtoM | B12: Artefactual | C12: Archive information management system | D12: =IF(ISNUMBER(Verification!B12),Verification!B12,IF(Calc!B12="",0,Calc!B12)) | E12: =IF(ISNUMBER(Verification!C12),Verification!C12,IF(Calc!C12="",0,Calc!C12)) | F12: =IF(ISNUMBER(Verification!D12),Verification!D12,IF(Calc!D12="",0,Calc!D12)) | G12: =IF(ISNUMBER(Verification!E12),Verification!E12,IF(Calc!E12="",0,Calc!E12)) | H12: =IF(ISNUMBER(Verification!F12),Verification!F12,IF(Calc!F12="",0,Calc!F12)) | I12: =IF(ISNUMBER(Verification!G12),Verification!G12,IF(Calc!G12="",0,Calc!G12)) | J12: =COUNT(Calc!B12:G12) | K12: =AVERAGE(D12:I12) | L12: =6-J12 | M12: =IF(COUNTIF(Verification!H12:L12,"Review*")>0,"Scored - coding review","Scored") | N12: 041 scored from available URL tier; 019 scored from populated repository field; 043 evidence URL should be checked; not scored separately; 4 unavailable metric(s) scored as 0
A13: Avalon Media System | B13: Indiana University Libraries | C13: Digital library, collection or exhibit platform | Repository software | D13: =IF(ISNUMBER(Verification!B13),Verification!B13,IF(Calc!B13="",0,Calc!B13)) | E13: =IF(ISNUMBER(Verification!C13),Verification!C13,IF(Calc!C13="",0,Calc!C13)) | F13: =IF(ISNUMBER(Verification!D13),Verification!D13,IF(Calc!D13="",0,Calc!D13)) | G13: =IF(ISNUMBER(Verification!E13),Verification!E13,IF(Calc!E13="",0,Calc!E13)) | H13: =IF(ISNUMBER(Verification!F13),Verification!F13,IF(Calc!F13="",0,Calc!F13)) | I13: =IF(ISNUMBER(Verification!G13),Verification!G13,IF(Calc!G13="",0,Calc!G13)) | J13: =COUNT(Calc!B13:G13) | K13: =AVERAGE(D13:I13) | L13: =6-J13 | M13: =IF(COUNTIF(Verification!H13:L13,"Review*")>0,"Scored - coding review","Scored") | N13: 041 scored from available URL tier; 019 scored from populated repository field; 043 evidence URL should be checked; not scored separately; 116 retained as source evidence only; not scored
... A113: Zotero | B113: Digital Scholar | C113: Annotations system | D113: =IF(ISNUMBER(Verification!B113),Verification!B113,IF(Calc!B113="",0,Calc!B113)) | E113: =IF(ISNUMBER(Verification!C113),Verification!C113,IF(Calc!C113="",0,Calc!C113)) | F113: =IF(ISNUMBER(Verification!D113),Verification!D113,IF(Calc!D113="",0,Calc!D113)) | G113: =IF(ISNUMBER(Verification!E113),Verification!E113,IF(Calc!E113="",0,Calc!E113)) | H113: =IF(ISNUMBER(Verification!F113),Verification!F113,IF(Calc!F113="",0,Calc!F113)) | I113: =IF(ISNUMBER(Verification!G113),Verification!G113,IF(Calc!G113="",0,Calc!G113)) | J113: =COUNT(Calc!B113:G113) | K113: =AVERAGE(D113:I113) | L113: =6-J113 | M113: =IF(COUNTIF(Verification!H113:L113,"Review*")>0,"Scored - coding review","Scored") | N113: 041 scored from available URL tier; 019 scored from populated repository field; 043 evidence URL should be checked; not scored separately; 116 retained as source evidence only; not scored

Sheet Metric Rules
A1: OISI Community Analysis / Community Engagement: Equal-Weight Scoring Rules
A2: Scoring set | B2: Six metrics E1, E2, C1, C2, C3, N1. Each is equally weighted.
A3: Weights | B3: Each metric = 1/6 = 16.6667%; displayed as 16.67%. Calculations use the exact 1/6 fraction.
A4: Final score | B4: Arithmetic mean of all six metric scores on a 0-100 scale.
A5: Coverage rule | B5: No coverage eligibility gate. Every infrastructure receives a score.
A6: Missing values | B6: Unavailable, blank, Unknown, or ambiguous metric values are scored as 0. This zero-filled score is not proof of zero underlying performance.
A7: Performance bands | B7: None are used.
A8: 038 and 938 | B8: Twelve named 038 activity types plus a thirteenth Other category, only when Other is selected and 938 supports a distinct unlisted activity. Duplicate categories are counted once.
A9: 040 and 940 | B9: Eight named 040 contribution routes plus a ninth Other category, only when Other is selected and 940 supports a distinct unlisted route.
A10: 116 | B10: Evidence only; not a scored metric. It is not included in E2 counts.
A11: 042 and 043 | B11: 042 is one status metric. 043 is supporting evidence for reviewer verification and is not scored separately.
A12: Review status | B12: C2 and C3 are scored automatically when their source fields are populated. URL review notes are audit context, not a scoring prerequisite. Free-text coding and Other categories remain reviewable.
A14: Code | B14: Metric | C14: Source fields | D14: Equal weight | E14: Scoring rule | F14: Missing / verification treatment
A15: E1 | B15: Engagement status | C15: 037 | D15: 0.16666667 | E15: Implemented/available=100; In progress=67; Considering=33; Not planning=0. | F15: Unknown/blank=0.
A16: E2 | B16: Engagement activity breadth | C16: 038 + reviewed/coded 938 | D16: 0.16666667 | E16: 100 x distinct supported activity types / 13. Twelve named types plus valid Other; categories deduplicated. | F16: No supported type=0. Review 938 coding and Other where needed.
A17: C1 | B17: Contribution opportunity breadth | C17: 040 + reviewed 940 | D17: 0.16666667 | E17: 100 x distinct supported routes / 9. Eight named routes plus valid Other; categories deduplicated. | F17: No supported route=0. Review 940 Other where needed.
A18: C2 | B18: Contribution guidance | C18: 041 | D18: 0.16666667 | E18: Available dedicated contribution-guide URL=100; available relevant general participation URL=50. | F18: Blank or suspect URL=0.
A19: C3 | B19: Public contribution repository | C19: 019 | D19: 0.16666667 | E19: Available public-forge URL=100; populated URL on another/unspecified host=50. | F19: Blank field=0.
A20: N1 | B20: Code of Conduct status | C20: 042; 043 evidence only | D20: 0.16666667 | E20: Implemented/available=100; In progress=67; Considering=33; Not planning=0. | F20: Unknown/blank=0. Use 043 as evidence only; no separate URL bonus/penalty.

Sheet Parameters
A1: Code | B1: Metric | C1: Source fields | D1: Weight (exact) | E1: Weight (display) | F1: Dimension
A2: E1 | B2: Engagement status | C2: 037 | D2: 0.16666667 | E2: 16.67% | F2: Engagement & Participation
A3: E2 | B3: Engagement activity breadth | C3: 038 + reviewed/coded 938 | D3: 0.16666667 | E3: 16.67% | F3: Engagement & Participation
A4: C1 | B4: Contribution opportunity breadth | C4: 040 + reviewed 940 | D4: 0.16666667 | E4: 16.67% | F4: Contribution Mechanisms
A5: C2 | B5: Contribution guidance | C5: 041 | D5: 0.16666667 | E5: 16.67% | F5: Contribution Mechanisms
A6: C3 | B6: Public contribution repository | C6: 019 | D6: 0.16666667 | E6: 16.67% | F6: Contribution Mechanisms
A7: N1 | B7: Code of Conduct status | C7: 042; 043 evidence only | D7: 0.16666667 | E7: 16.67% | F7: Community Norms
A8: Total | D8: 1 | E8: 100.00%
A10: Breadth denominator | B10: Available indicators | C10: Count rule
A11: 038 | B11: 13 | C11: 12 named types + valid Other; no duplicate category count
A12: 040 | B12: 9 | C12: 8 named routes + valid Other; no duplicate route count
A13: Coverage eligibility gate | B13: None | C13: All infrastructures receive an equal-weight score; unavailable metrics contribute 0

Sheet Verification
A1: Service | B1: E1 override (0-100) | C1: E2 override (0-100) | D1: C1 override (0-100) | E1: C2 override (0-100) | F1: C3 override (0-100) | G1: N1 override (0-100) | H1: 938 reviewed? | I1: 940 reviewed? | J1: 041 verified? | K1: 019 verified public repo? | L1: 043 checked? | M1: Reviewer notes
A2: 2i2c | H2: Review coding | I2: N/A | J2: No score | K2: Scored from available field | L2: Evidence only
A3: Academic Preservation Trust (APTrust) | H3: N/A | I3: N/A | J3: Scored from available URL | K3: Scored from available field | L3: Evidence only
A4: AfricArXiv | H4: N/A | I4: N/A | J4: No score | K4: No score | L4: Evidence only
A5: Arches Heritage Data Management Platform | H5: N/A | I5: N/A | J5: Scored from available URL | K5: Scored from available field | L5: Evidence only
A6: Archipelago Commons | H6: Review coding | I6: N/A | J6: Scored from available URL | K6: Scored from available field | L6: Evidence only
A7: Archival Resource Key | H7: N/A | I7: N/A | J7: Scored from available URL | K7: Scored from available field | L7: Evidence only
A8: Archivematica | H8: N/A | I8: N/A | J8: Scored from available URL | K8: Scored from available field | L8: Evidence only
A9: ArchivesSpace | H9: N/A | I9: N/A | J9: Scored from available URL | K9: Scored from available field | L9: Evidence only
A10: ARGOS | H10: N/A | I10: N/A | J10: No score | K10: Scored from available field | L10: Evidence only
A11: arXiv | H11: Review coding | I11: N/A | J11: Scored from available URL | K11: Scored from available field | L11: Evidence only
A12: AtoM | H12: N/A | I12: N/A | J12: No score | K12: Scored from available field | L12: Evidence only
A13: Avalon Media System | H13: N/A | I13: N/A | J13: Scored from available URL | K13: Scored from available field | L13: Evidence only
... A113: Zotero | H113: N/A | I113: N/A | J113: Scored from available URL | K113: Scored from available field | L113: Evidence only

Sheet Activity Coding
A1: Service | B1: 038: Annual meetings | C1: 038: Blogs | D1: 038: Community calls | E1: 038: Conference participation | F1: 038: Development sprints | G1: 038: Interest, working, user, or advisory groups | H1: 038: Mailing lists and discussion forums (including Slack) | I1: 038: Social media | J1: 038: Staff roles with responsibility for community engagement | K1: 038: User research | L1: 038: Volunteer or ambassador network | M1: 038: Webinars and training | N1: 938 coded: Annual meetings | O1: 938 coded: Blogs | P1: 938 coded: Community calls | Q1: 938 coded: Conference participation | R1: 938 coded: Development sprints | S1: 938 coded: Interest, working, user, or advisory groups | T1: 938 coded: Mailing lists and discussion forums (including Slack) | U1: 938 coded: Social media | V1: 938 coded: Staff roles with responsibility for community engagement | W1: 938 coded: User research | X1: 938 coded: Volunteer or ambassador network | Y1: 938 coded: Webinars and training | Z1: 038 count | AA1: 938 coded count | AB1: Other supported | AC1: Union count / 13 | AD1: Coded union
A2: 2i2c | B2: 0 | C2: 0 | D2: 0 | E2: 0 | F2: 0 | G2: 0 | H2: 0 | I2: 0 | J2: 0 | K2: 0 | L2: 0 | M2: 0 | N2: 0 | O2: 0 | P2: 1 | Q2: 0 | R2: 0 | S2: 1 | T2: 0 | U2: 0 | V2: 0 | W2: 0 | X2: 0 | Y2: 0 | Z2: 0 | AA2: 2 | AB2: 0 | AC2: 2 | AD2: Community calls; Interest, working, user, or advisory groups
A3: Academic Preservation Trust (APTrust) | B3: 1 | C3: 1 | D3: 1 | E3: 1 | F3: 1 | G3: 1 | H3: 1 | I3: 0 | J3: 1 | K3: 1 | L3: 0 | M3: 1 | N3: 0 | O3: 0 | P3: 0 | Q3: 0 | R3: 0 | S3: 0 | T3: 0 | U3: 0 | V3: 0 | W3: 0 | X3: 0 | Y3: 0 | Z3: 10 | AA3: 0 | AB3: 0 | AC3: 10 | AD3: Annual meetings; Blogs; Community calls; Conference participation; Development sprints; Interest, working, user, or advisory groups; Mailing lists and discussion forums (including Slack); Staff roles with responsibility for community engagement; User research; Webinars and training
A4: AfricArXiv | B4: 0 | C4: 0 | D4: 0 | E4: 0 | F4: 0 | G4: 0 | H4: 0 | I4: 0 | J4: 0 | K4: 0 | L4: 0 | M4: 0 | N4: 0 | O4: 0 | P4: 0 | Q4: 0 | R4: 0 | S4: 0 | T4: 0 | U4: 0 | V4: 0 | W4: 0 | X4: 0 | Y4: 0 | Z4: 0 | AA4: 0 | AB4: 0 | AC4: 0
A5: Arches Heritage Data Management Platform | B5: 0 | C5: 0 | D5: 0 | E5: 0 | F5: 0 | G5: 0 | H5: 0 | I5: 0 | J5: 0 | K5: 0 | L5: 0 | M5: 0 | N5: 0 | O5: 0 | P5: 0 | Q5: 0 | R5: 0 | S5: 0 | T5: 0 | U5: 0 | V5: 0 | W5: 0 | X5: 0 | Y5: 0 | Z5: 0 | AA5: 0 | AB5: 0 | AC5: 0
A6: Archipelago Commons | B6: 0 | C6: 0 | D6: 1 | E6: 1 | F6: 0 | G6: 1 | H6: 1 | I6: 0 | J6: 1 | K6: 0 | L6: 1 | M6: 1 | N6: 0 | O6: 0 | P6: 0 | Q6: 0 | R6: 0 | S6: 1 | T6: 1 | U6: 0 | V6: 0 | W6: 0 | X6: 0 | Y6: 0 | Z6: 7 | AA6: 2 | AB6: 0 | AC6: 7 | AD6: Community calls; Conference participation; Interest, working, user, or advisory groups; Mailing lists and discussion forums (including Slack); Staff roles with responsibility for community engagement; Volunteer or ambassador network; Webinars and training
A7: Archival Resource Key | B7: 0 | C7: 0 | D7: 0 | E7: 0 | F7: 0 | G7: 0 | H7: 0 | I7: 0 | J7: 0 | K7: 0 | L7: 0 | M7: 0 | N7: 0 | O7: 0 | P7: 0 | Q7: 0 | R7: 0 | S7: 0 | T7: 0 | U7: 0 | V7: 0 | W7: 0 | X7: 0 | Y7: 0 | Z7: 0 | AA7: 0 | AB7: 0 | AC7: 0
A8: Archivematica | B8: 0 | C8: 0 | D8: 0 | E8: 0 | F8: 0 | G8: 0 | H8: 0 | I8: 0 | J8: 0 | K8: 0 | L8: 0 | M8: 0 | N8: 0 | O8: 0 | P8: 0 | Q8: 0 | R8: 0 | S8: 0 | T8: 0 | U8: 0 | V8: 0 | W8: 0 | X8: 0 | Y8: 0 | Z8: 0 | AA8: 0 | AB8: 0 | AC8: 0
A9: ArchivesSpace | B9: 1 | C9: 1 | D9: 1 | E9: 1 | F9: 0 | G9: 1 | H9: 1 | I9: 1 | J9: 1 | K9: 0 | L9: 0 | M9: 1 | N9: 0 | O9: 0 | P9: 0 | Q9: 0 | R9: 0 | S9: 0 | T9: 0 | U9: 0 | V9: 0 | W9: 0 | X9: 0 | Y9: 0 | Z9: 9 | AA9: 0 | AB9: 0 | AC9: 9 | AD9: Annual meetings; Blogs; Community calls; Conference participation; Interest, working, user, or advisory groups; Mailing lists and discussion forums (including Slack); Social media; Staff roles with responsibility for community engagement; Webinars and training
A10: ARGOS | B10: 0 | C10: 1 | D10: 1 | E10: 1 | F10: 1 | G10: 1 | H10: 0 | I10: 1 | J10: 1 | K10: 0 | L10: 0 | M10: 1 | N10: 0 | O10: 0 | P10: 0 | Q10: 0 | R10: 0 | S10: 0 | T10: 0 | U10: 0 | V10: 0 | W10: 0 | X10: 0 | Y10: 0 | Z10: 8 | AA10: 0 | AB10: 0 | AC10: 8 | AD10: Blogs; Community calls; Conference participation; Development sprints; Interest, working, user, or advisory groups; Social media; Staff roles with responsibility for community engagement; Webinars and training
A11: arXiv | B11: 0 | C11: 0 | D11: 0 | E11: 0 | F11: 0 | G11: 0 | H11: 0 | I11: 0 | J11: 0 | K11: 0 | L11: 0 | M11: 0 | N11: 0 | O11: 0 | P11: 0 | Q11: 0 | R11: 0 | S11: 1 | T11: 1 | U11: 0 | V11: 0 | W11: 1 | X11: 1 | Y11: 0 | Z11: 0 | AA11: 4 | AB11: 0 | AC11: 4 | AD11: Interest, working, user, or advisory groups; Mailing lists and discussion forums (including Slack); User research; Volunteer or ambassador network
A12: AtoM | B12: 0 | C12: 0 | D12: 0 | E12: 0 | F12: 0 | G12: 0 | H12: 0 | I12: 0 | J12: 0 | K12: 0 | L12: 0 | M12: 0 | N12: 0 | O12: 0 | P12: 0 | Q12: 0 | R12: 0 | S12: 0 | T12: 0 | U12: 0 | V12: 0 | W12: 0 | X12: 0 | Y12: 0 | Z12: 0 | AA12: 0 | AB12: 0 | AC12: 0
A13: Avalon Media System | B13: 1 | C13: 0 | D13: 1 | E13: 1 | F13: 0 | G13: 1 | H13: 1 | I13: 0 | J13: 0 | K13: 0 | L13: 0 | M13: 0 | N13: 0 | O13: 0 | P13: 0 | Q13: 0 | R13: 0 | S13: 0 | T13: 0 | U13: 0 | V13: 0 | W13: 0 | X13: 0 | Y13: 0 | Z13: 5 | AA13: 0 | AB13: 0 | AC13: 5 | AD13: Annual meetings; Community calls; Conference participation; Interest, working, user, or advisory groups; Mailing lists and discussion forums (including Slack)
A14: Biodiversity Heritage Library | B14: 1 | C14: 1 | D14: 0 | E14: 1 | F14: 0 | G14: 0 | H14: 1 | I14: 1 | J14: 0 | K14: 0 | L14: 1 | M14: 1 | N14: 0 | O14: 0 | P14: 0 | Q14: 0 | R14: 0 | S14: 0 | T14: 0 | U14: 0 | V14: 0 | W14: 0 | X14: 0 | Y14: 0 | Z14: 7 | AA14: 0 | AB14: 0 | AC14: 7 | AD14: Annual meetings; Blogs; Conference participation; Mailing lists and discussion forums (including Slack); Social media; Volunteer or ambassador network; Webinars and training
A15: bioRxiv | B15: 0 | C15: 0 | D15: 0 | E15: 0 | F15: 0 | G15: 0 | H15: 0 | I15: 0 | J15: 0 | K15: 0 | L15: 0 | M15: 0 | N15: 0 | O15: 0 | P15: 0 | Q15: 0 | R15: 0 | S15: 0 | T15: 0 | U15: 0 | V15: 0 | W15: 1 | X15: 1 | Y15: 0 | Z15: 0 | AA15: 2 | AB15: 0 | AC15: 2 | AD15: User research; Volunteer or ambassador network
A16: BitCurator Environment | B16: 1 | C16: 1 | D16: 1 | E16: 0 | F16: 0 | G16: 1 | H16: 1 | I16: 0 | J16: 1 | K16: 0 | L16: 0 | M16: 1 | N16: 0 | O16: 0 | P16: 0 | Q16: 0 | R16: 0 | S16: 0 | T16: 0 | U16: 0 | V16: 0 | W16: 0 | X16: 0 | Y16: 0 | Z16: 7 | AA16: 0 | AB16: 0 | AC16: 7 | AD16: Annual meetings; Blogs; Community calls; Interest, working, user, or advisory groups; Mailing lists and discussion forums (including Slack); Staff roles with responsibility for community engagement; Webinars and training
A17: Blacklight | B17: 0 | C17: 1 | D17: 1 | E17: 1 | F17: 1 | G17: 0 | H17: 1 | I17: 1 | J17: 0 | K17: 1 | L17: 1 | M17: 1 | N17: 0 | O17: 0 | P17: 0 | Q17: 0 | R17: 0 | S17: 0 | T17: 0 | U17: 0 | V17: 0 | W17: 0 | X17: 0 | Y17: 0 | Z17: 9 | AA17: 0 | AB17: 0 | AC17: 9 | AD17: Blogs; Community calls; Conference participation; Development sprints; Mailing lists and discussion forums (including Slack); Social media; User research; Volunteer or ambassador network; Webinars and training
A18: BrCRIS | B18: 0 | C18: 0 | D18: 0 | E18: 0 | F18: 0 | G18: 0 | H18: 0 | I18: 0 | J18: 0 | K18: 0 | L18: 0 | M18: 0 | N18: 0 | O18: 0 | P18: 0 | Q18: 0 | R18: 0 | S18: 0 | T18: 0 | U18: 0 | V18: 0 | W18: 0 | X18: 0 | Y18: 0 | Z18: 0 | AA18: 0 | AB18: 0 | AC18: 0
A19: Browsertrix | B19: 0 | C19: 0 | D19: 0 | E19: 0 | F19: 0 | G19: 0 | H19: 0 | I19: 1 | J19: 0 | K19: 0 | L19: 0 | M19: 0 | N19: 0 | O19: 0 | P19: 0 | Q19: 0 | R19: 0 | S19: 0 | T19: 0 | U19: 0 | V19: 0 | W19: 0 | X19: 0 | Y19: 0 | Z19: 1 | AA19: 0 | AB19: 0 | AC19: 1 | AD19: Social media
A20: CLOCKSS | B20: 0 | C20: 0 | D20: 0 | E20: 0 | F20: 0 | G20: 0 | H20: 0 | I20: 0 | J20: 0 | K20: 0 | L20: 0 | M20: 0 | N20: 0 | O20: 0 | P20: 0 | Q20: 0 | R20: 0 | S20: 0 | T20: 0 | U20: 0 | V20: 0 | W20: 0 | X20: 0 | Y20: 0 | Z20: 0 | AA20: 0 | AB20: 0 | AC20: 0
A21: COAR International Repository Directory (IRD) | B21: 0 | C21: 1 | D21: 1 | E21: 0 | F21: 1 | G21: 0 | H21: 0 | I21: 0 | J21: 0 | K21: 0 | L21: 1 | M21: 0 | N21: 0 | O21: 0 | P21: 0 | Q21: 0 | R21: 0 | S21: 0 | T21: 0 | U21: 0 | V21: 0 | W21: 0 | X21: 0 | Y21: 0 | Z21: 4 | AA21: 0 | AB21: 0 | AC21: 4 | AD21: Blogs; Community calls; Development sprints; Volunteer or ambassador network
A22: COAR Notify | B22: 0 | C22: 1 | D22: 0 | E22: 1 | F22: 0 | G22: 1 | H22: 1 | I22: 0 | J22: 0 | K22: 0 | L22: 0 | M22: 1 | N22: 0 | O22: 0 | P22: 0 | Q22: 0 | R22: 0 | S22: 0 | T22: 0 | U22: 0 | V22: 0 | W22: 0 | X22: 0 | Y22: 0 | Z22: 5 | AA22: 0 | AB22: 0 | AC22: 5 | AD22: Blogs; Conference participation; Interest, working, user, or advisory groups; Mailing lists and discussion forums (including Slack); Webinars and training
A23: CollectiveAccess | B23: 0 | C23: 0 | D23: 0 | E23: 0 | F23: 0 | G23: 0 | H23: 0 | I23: 0 | J23: 0 | K23: 0 | L23: 0 | M23: 0 | N23: 0 | O23: 0 | P23: 0 | Q23: 0 | R23: 0 | S23: 0 | T23: 0 | U23: 0 | V23: 0 | W23: 0 | X23: 0 | Y23: 0 | Z23: 0 | AA23: 0 | AB23: 0 | AC23: 0
A24: CORE | B24: 0 | C24: 0 | D24: 0 | E24: 0 | F24: 0 | G24: 0 | H24: 0 | I24: 0 | J24: 0 | K24: 0 | L24: 0 | M24: 0 | N24: 0 | O24: 1 | P24: 0 | Q24: 0 | R24: 0 | S24: 0 | T24: 0 | U24: 0 | V24: 0 | W24: 0 | X24: 0 | Y24: 0 | Z24: 0 | AA24: 1 | AB24: 0 | AC24: 1 | AD24: Blogs
A25: COUNTER Code of Practice | B25: 1 | C25: 1 | D25: 1 | E25: 1 | F25: 0 | G25: 1 | H25: 1 | I25: 1 | J25: 0 | K25: 0 | L25: 0 | M25: 1 | N25: 1 | O25: 1 | P25: 1 | Q25: 1 | R25: 0 | S25: 1 | T25: 0 | U25: 0 | V25: 0 | W25: 1 | X25: 0 | Y25: 1 | Z25: 8 | AA25: 7 | AB25: 0 | AC25: 9 | AD25: Annual meetings; Blogs; Community calls; Conference participation; Interest, working, user, or advisory groups; Mailing lists and discussion forums (including Slack); Social media; User research; Webinars and training
A26: Creative Commons Licenses | B26: 0 | C26: 0 | D26: 0 | E26: 0 | F26: 0 | G26: 0 | H26: 0 | I26: 0 | J26: 0 | K26: 0 | L26: 0 | M26: 0 | N26: 1 | O26: 1 | P26: 1 | Q26: 0 | R26: 0 | S26: 0 | T26: 0 | U26: 0 | V26: 1 | W26: 0 | X26: 0 | Y26: 0 | Z26: 0 | AA26: 4 | AB26: 0 | AC26: 4 | AD26: Annual meetings; Blogs; Community calls; Staff roles with responsibility for community engagement
A27: Crossref Metadata Retrieval | B27: 0 | C27: 0 | D27: 0 | E27: 0 | F27: 0 | G27: 0 | H27: 0 | I27: 0 | J27: 0 | K27: 0 | L27: 0 | M27: 0 | N27: 0 | O27: 1 | P27: 1 | Q27: 1 | R27: 0 | S27: 1 | T27: 1 | U27: 0 | V27: 1 | W27: 0 | X27: 1 | Y27: 1 | Z27: 0 | AA27: 8 | AB27: 0 | AC27: 8 | AD27: Blogs; Community calls; Conference participation; Interest, working, user, or advisory groups; Mailing lists and discussion forums (including Slack); Staff roles with responsibility for community engagement; Volunteer or ambassador network; Webinars and training
A28: D4Science Infrastructure | B28: 0 | C28: 0 | D28: 0 | E28: 0 | F28: 0 | G28: 0 | H28: 0 | I28: 0 | J28: 0 | K28: 0 | L28: 0 | M28: 0 | N28: 0 | O28: 0 | P28: 0 | Q28: 0 | R28: 0 | S28: 0 | T28: 0 | U28: 0 | V28: 0 | W28: 0 | X28: 0 | Y28: 0 | Z28: 0 | AA28: 0 | AB28: 0 | AC28: 0
A29: DART (Digital Archivist's Resource Tool) | B29: 0 | C29: 0 | D29: 0 | E29: 0 | F29: 0 | G29: 0 | H29: 0 | I29: 0 | J29: 0 | K29: 0 | L29: 0 | M29: 0 | N29: 0 | O29: 0 | P29: 0 | Q29: 0 | R29: 0 | S29: 0 | T29: 0 | U29: 0 | V29: 0 | W29: 0 | X29: 0 | Y29: 0 | Z29: 0 | AA29: 0 | AB29: 0 | AC29: 0
A30: Database Information System | B30: 1 | C30: 1 | D30: 0 | E30: 1 | F30: 0 | G30: 0 | H30: 1 | I30: 0 | J30: 1 | K30: 1 | L30: 0 | M30: 1 | N30: 0 | O30: 0 | P30: 0 | Q30: 0 | R30: 0 | S30: 0 | T30: 0 | U30: 0 | V30: 0 | W30: 0 | X30: 0 | Y30: 0 | Z30: 7 | AA30: 0 | AB30: 0 | AC30: 7 | AD30: Annual meetings; Blogs; Conference participation; Mailing lists and discussion forums (including Slack); Staff roles with responsibility for community engagement; User research; Webinars and training
A31: Data Citation Corpus | B31: 0 | C31: 1 | D31: 0 | E31: 1 | F31: 0 | G31: 1 | H31: 1 | I31: 1 | J31: 0 | K31: 0 | L31: 0 | M31: 1 | N31: 0 | O31: 0 | P31: 0 | Q31: 0 | R31: 0 | S31: 0 | T31: 0 | U31: 0 | V31: 0 | W31: 0 | X31: 0 | Y31: 0 | Z31: 6 | AA31: 0 | AB31: 0 | AC31: 6 | AD31: Blogs; Conference participation; Interest, working, user, or advisory groups; Mailing lists and discussion forums (including Slack); Social media; Webinars and training
A32: DataCite | B32: 0 | C32: 0 | D32: 0 | E32: 0 | F32: 0 | G32: 0 | H32: 0 | I32: 0 | J32: 0 | K32: 0 | L32: 0 | M32: 0 | N32: 0 | O32: 1 | P32: 0 | Q32: 0 | R32: 0 | S32: 0 | T32: 0 | U32: 0 | V32: 0 | W32: 0 | X32: 0 | Y32: 0 | Z32: 0 | AA32: 1 | AB32: 0 | AC32: 1 | AD32: Blogs
A33: Data Stewardship Wizard | B33: 1 | C33: 1 | D33: 1 | E33: 1 | F33: 0 | G33: 1 | H33: 1 | I33: 1 | J33: 0 | K33: 1 | L33: 1 | M33: 1 | N33: 0 | O33: 0 | P33: 0 | Q33: 0 | R33: 0 | S33: 0 | T33: 0 | U33: 0 | V33: 0 | W33: 0 | X33: 0 | Y33: 0 | Z33: 10 | AA33: 0 | AB33: 0 | AC33: 10 | AD33: Annual meetings; Blogs; Community calls; Conference participation; Interest, working, user, or advisory groups; Mailing lists and discussion forums (including Slack); Social media; User research; Volunteer or ambassador network; Webinars and training
A34: Dataverse | B34: 0 | C34: 0 | D34: 0 | E34: 0 | F34: 0 | G34: 0 | H34: 0 | I34: 0 | J34: 0 | K34: 0 | L34: 0 | M34: 0 | N34: 0 | O34: 0 | P34: 1 | Q34: 1 | R34: 0 | S34: 0 | T34: 1 | U34: 0 | V34: 0 | W34: 0 | X34: 0 | Y34: 0 | Z34: 0 | AA34: 3 | AB34: 0 | AC34: 3 | AD34: Community calls; Conference participation; Mailing lists and discussion forums (including Slack)
A35: DLCM Backend | B35: 0 | C35: 0 | D35: 1 | E35: 1 | F35: 0 | G35: 1 | H35: 0 | I35: 0 | J35: 0 | K35: 0 | L35: 0 | M35: 1 | N35: 0 | O35: 0 | P35: 0 | Q35: 0 | R35: 0 | S35: 0 | T35: 0 | U35: 0 | V35: 0 | W35: 0 | X35: 0 | Y35: 0 | Z35: 4 | AA35: 0 | AB35: 0 | AC35: 4 | AD35: Community calls; Conference participation; Interest, working, user, or advisory groups; Webinars and training
A36: DLCM Portal | B36: 0 | C36: 0 | D36: 1 | E36: 1 | F36: 0 | G36: 1 | H36: 0 | I36: 0 | J36: 0 | K36: 0 | L36: 0 | M36: 1 | N36: 0 | O36: 0 | P36: 0 | Q36: 0 | R36: 0 | S36: 0 | T36: 0 | U36: 0 | V36: 0 | W36: 0 | X36: 0 | Y36: 0 | Z36: 4 | AA36: 0 | AB36: 0 | AC36: 4 | AD36: Community calls; Conference participation; Interest, working, user, or advisory groups; Webinars and training
A37: DMP Tool | B37: 0 | C37: 1 | D37: 1 | E37: 1 | F37: 0 | G37: 0 | H37: 1 | I37: 1 | J37: 1 | K37: 1 | L37: 0 | M37: 1 | N37: 0 | O37: 0 | P37: 0 | Q37: 0 | R37: 0 | S37: 0 | T37: 0 | U37: 0 | V37: 0 | W37: 0 | X37: 0 | Y37: 0 | Z37: 8 | AA37: 0 | AB37: 0 | AC37: 8 | AD37: Blogs; Community calls; Conference participation; Mailing lists and discussion forums (including Slack); Social media; Staff roles with responsibility for community engagement; User research; Webinars and training
A38: DOAJ (Directory of Open Access Journals) | B38: 0 | C38: 1 | D38: 1 | E38: 1 | F38: 0 | G38: 1 | H38: 0 | I38: 1 | J38: 0 | K38: 1 | L38: 1 | M38: 1 | N38: 0 | O38: 1 | P38: 0 | Q38: 0 | R38: 0 | S38: 1 | T38: 0 | U38: 0 | V38: 0 | W38: 0 | X38: 0 | Y38: 0 | Z38: 8 | AA38: 2 | AB38: 0 | AC38: 9 | AD38: Blogs; Community calls; Conference participation; Interest, working, user, or advisory groups; Other; Social media; User research; Volunteer or ambassador network; Webinars and training
A39: dokieli | B39: 0 | C39: 0 | D39: 0 | E39: 0 | F39: 0 | G39: 0 | H39: 0 | I39: 0 | J39: 0 | K39: 0 | L39: 0 | M39: 0 | N39: 0 | O39: 0 | P39: 0 | Q39: 1 | R39: 0 | S39: 0 | T39: 1 | U39: 0 | V39: 0 | W39: 0 | X39: 0 | Y39: 0 | Z39: 0 | AA39: 2 | AB39: 0 | AC39: 2 | AD39: Conference participation; Mailing lists and discussion forums (including Slack)
A40: Dryad | B40: 0 | C40: 0 | D40: 0 | E40: 0 | F40: 0 | G40: 0 | H40: 0 | I40: 0 | J40: 0 | K40: 0 | L40: 0 | M40: 0 | N40: 0 | O40: 1 | P40: 0 | Q40: 1 | R40: 0 | S40: 1 | T40: 1 | U40: 0 | V40: 0 | W40: 0 | X40: 0 | Y40: 0 | Z40: 0 | AA40: 4 | AB40: 0 | AC40: 4 | AD40: Blogs; Conference participation; Interest, working, user, or advisory groups; Mailing lists and discussion forums (including Slack)
A41: DSpace | B41: 1 | C41: 0 | D41: 0 | E41: 1 | F41: 1 | G41: 1 | H41: 1 | I41: 0 | J41: 1 | K41: 0 | L41: 0 | M41: 1 | N41: 0 | O41: 0 | P41: 0 | Q41: 0 | R41: 0 | S41: 0 | T41: 0 | U41: 0 | V41: 0 | W41: 0 | X41: 0 | Y41: 0 | Z41: 7 | AA41: 0 | AB41: 0 | AC41: 7 | AD41: Annual meetings; Conference participation; Development sprints; Interest, working, user, or advisory groups; Mailing lists and discussion forums (including Slack); Staff roles with responsibility for community engagement; Webinars and training
A42: DuraCloud | B42: 0 | C42: 0 | D42: 0 | E42: 0 | F42: 0 | G42: 0 | H42: 0 | I42: 0 | J42: 0 | K42: 0 | L42: 0 | M42: 0 | N42: 0 | O42: 0 | P42: 0 | Q42: 0 | R42: 0 | S42: 0 | T42: 0 | U42: 0 | V42: 0 | W42: 0 | X42: 0 | Y42: 0 | Z42: 0 | AA42: 0 | AB42: 0 | AC42: 0
A43: Episciences | B43: 0 | C43: 0 | D43: 0 | E43: 0 | F43: 0 | G43: 0 | H43: 0 | I43: 0 | J43: 0 | K43: 0 | L43: 0 | M43: 0 | N43: 0 | O43: 0 | P43: 0 | Q43: 0 | R43: 0 | S43: 0 | T43: 0 | U43: 0 | V43: 0 | W43: 0 | X43: 0 | Y43: 0 | Z43: 0 | AA43: 0 | AB43: 0 | AC43: 0
A44: EPrints | B44: 0 | C44: 0 | D44: 0 | E44: 0 | F44: 0 | G44: 0 | H44: 0 | I44: 0 | J44: 0 | K44: 0 | L44: 0 | M44: 0 | N44: 0 | O44: 0 | P44: 0 | Q44: 0 | R44: 0 | S44: 0 | T44: 0 | U44: 0 | V44: 0 | W44: 0 | X44: 0 | Y44: 0 | Z44: 0 | AA44: 0 | AB44: 0 | AC44: 0
A45: Érudit | B45: 0 | C45: 0 | D45: 0 | E45: 0 | F45: 0 | G45: 0 | H45: 0 | I45: 0 | J45: 0 | K45: 0 | L45: 0 | M45: 0 | N45: 0 | O45: 0 | P45: 0 | Q45: 0 | R45: 0 | S45: 0 | T45: 0 | U45: 0 | V45: 0 | W45: 0 | X45: 0 | Y45: 0 | Z45: 0 | AA45: 0 | AB45: 0 | AC45: 0
A46: Europe PMC | B46: 0 | C46: 0 | D46: 0 | E46: 0 | F46: 0 | G46: 0 | H46: 0 | I46: 0 | J46: 0 | K46: 0 | L46: 0 | M46: 0 | N46: 0 | O46: 1 | P46: 0 | Q46: 1 | R46: 0 | S46: 1 | T46: 1 | U46: 0 | V46: 1 | W46: 1 | X46: 0 | Y46: 1 | Z46: 0 | AA46: 7 | AB46: 0 | AC46: 7 | AD46: Blogs; Conference participation; Interest, working, user, or advisory groups; Mailing lists and discussion forums (including Slack); Staff roles with responsibility for community engagement; User research; Webinars and training
A47: FAIR Wizard | B47: 1 | C47: 1 | D47: 0 | E47: 1 | F47: 0 | G47: 0 | H47: 0 | I47: 1 | J47: 0 | K47: 1 | L47: 0 | M47: 1 | N47: 0 | O47: 0 | P47: 0 | Q47: 0 | R47: 0 | S47: 0 | T47: 0 | U47: 0 | V47: 0 | W47: 0 | X47: 0 | Y47: 0 | Z47: 6 | AA47: 0 | AB47: 0 | AC47: 6 | AD47: Annual meetings; Blogs; Conference participation; Social media; User research; Webinars and training
A48: Fedora | B48: 1 | C48: 1 | D48: 1 | E48: 1 | F48: 1 | G48: 1 | H48: 1 | I48: 1 | J48: 1 | K48: 0 | L48: 0 | M48: 1 | N48: 0 | O48: 0 | P48: 1 | Q48: 1 | R48: 0 | S48: 0 | T48: 1 | U48: 0 | V48: 0 | W48: 0 | X48: 0 | Y48: 0 | Z48: 10 | AA48: 3 | AB48: 0 | AC48: 10 | AD48: Annual meetings; Blogs; Community calls; Conference participation; Development sprints; Interest, working, user, or advisory groups; Mailing lists and discussion forums (including Slack); Social media; Staff roles with responsibility for community engagement; Webinars and training
A49: fido | B49: 1 | C49: 0 | D49: 0 | E49: 1 | F49: 0 | G49: 1 | H49: 1 | I49: 1 | J49: 1 | K49: 1 | L49: 0 | M49: 1 | N49: 0 | O49: 0 | P49: 0 | Q49: 0 | R49: 0 | S49: 0 | T49: 0 | U49: 0 | V49: 0 | W49: 0 | X49: 0 | Y49: 0 | Z49: 8 | AA49: 0 | AB49: 0 | AC49: 8 | AD49: Annual meetings; Conference participation; Interest, working, user, or advisory groups; Mailing lists and discussion forums (including Slack); Social media; Staff roles with responsibility for community engagement; User research; Webinars and training
A50: Fulcrum | B50: 0 | C50: 0 | D50: 0 | E50: 0 | F50: 0 | G50: 0 | H50: 0 | I50: 0 | J50: 0 | K50: 0 | L50: 0 | M50: 0 | N50: 0 | O50: 1 | P50: 0 | Q50: 1 | R50: 0 | S50: 1 | T50: 0 | U50: 0 | V50: 1 | W50: 0 | X50: 0 | Y50: 0 | Z50: 0 | AA50: 4 | AB50: 0 | AC50: 4 | AD50: Blogs; Conference participation; Interest, working, user, or advisory groups; Staff roles with responsibility for community engagement
A51: Galaxy | B51: 0 | C51: 0 | D51: 0 | E51: 0 | F51: 0 | G51: 0 | H51: 0 | I51: 0 | J51: 0 | K51: 0 | L51: 0 | M51: 0 | N51: 0 | O51: 0 | P51: 0 | Q51: 0 | R51: 0 | S51: 0 | T51: 0 | U51: 0 | V51: 0 | W51: 0 | X51: 0 | Y51: 0 | Z51: 0 | AA51: 0 | AB51: 0 | AC51: 0
A52: GeoServer | B52: 0 | C52: 1 | D52: 1 | E52: 1 | F52: 1 | G52: 0 | H52: 1 | I52: 1 | J52: 0 | K52: 0 | L52: 0 | M52: 0 | N52: 0 | O52: 0 | P52: 0 | Q52: 0 | R52: 0 | S52: 0 | T52: 0 | U52: 0 | V52: 0 | W52: 0 | X52: 0 | Y52: 0 | Z52: 6 | AA52: 0 | AB52: 0 | AC52: 6 | AD52: Blogs; Community calls; Conference participation; Development sprints; Mailing lists and discussion forums (including Slack); Social media
A53: Hyku | B53: 1 | C53: 1 | D53: 1 | E53: 1 | F53: 1 | G53: 1 | H53: 1 | I53: 0 | J53: 1 | K53: 0 | L53: 0 | M53: 1 | N53: 0 | O53: 0 | P53: 1 | Q53: 0 | R53: 0 | S53: 1 | T53: 0 | U53: 0 | V53: 0 | W53: 0 | X53: 0 | Y53: 0 | Z53: 9 | AA53: 2 | AB53: 0 | AC53: 9 | AD53: Annual meetings; Blogs; Community calls; Conference participation; Development sprints; Interest, working, user, or advisory groups; Mailing lists and discussion forums (including Slack); Staff roles with responsibility for community engagement; Webinars and training
A54: Hyrax | B54: 1 | C54: 1 | D54: 1 | E54: 1 | F54: 1 | G54: 1 | H54: 1 | I54: 0 | J54: 1 | K54: 0 | L54: 0 | M54: 1 | N54: 0 | O54: 0 | P54: 0 | Q54: 0 | R54: 0 | S54: 0 | T54: 0 | U54: 0 | V54: 0 | W54: 0 | X54: 0 | Y54: 0 | Z54: 9 | AA54: 0 | AB54: 0 | AC54: 9 | AD54: Annual meetings; Blogs; Community calls; Conference participation; Development sprints; Interest, working, user, or advisory groups; Mailing lists and discussion forums (including Slack); Staff roles with responsibility for community engagement; Webinars and training
A55: IIIF | B55: 0 | C55: 0 | D55: 0 | E55: 0 | F55: 0 | G55: 0 | H55: 0 | I55: 0 | J55: 0 | K55: 0 | L55: 0 | M55: 0 | N55: 0 | O55: 0 | P55: 1 | Q55: 1 | R55: 0 | S55: 0 | T55: 1 | U55: 0 | V55: 1 | W55: 0 | X55: 0 | Y55: 1 | Z55: 0 | AA55: 5 | AB55: 0 | AC55: 5 | AD55: Community calls; Conference participation; Mailing lists and discussion forums (including Slack); Staff roles with responsibility for community engagement; Webinars and training
A56: ImpactU | B56: 0 | C56: 0 | D56: 0 | E56: 0 | F56: 0 | G56: 0 | H56: 0 | I56: 0 | J56: 0 | K56: 0 | L56: 0 | M56: 0 | N56: 0 | O56: 0 | P56: 0 | Q56: 0 | R56: 0 | S56: 0 | T56: 0 | U56: 0 | V56: 0 | W56: 0 | X56: 0 | Y56: 0 | Z56: 0 | AA56: 0 | AB56: 0 | AC56: 0
A57: International Generic Sample Number (IGSN) | B57: 0 | C57: 0 | D57: 0 | E57: 0 | F57: 0 | G57: 0 | H57: 0 | I57: 0 | J57: 0 | K57: 0 | L57: 0 | M57: 0 | N57: 0 | O57: 0 | P57: 0 | Q57: 0 | R57: 0 | S57: 0 | T57: 0 | U57: 0 | V57: 0 | W57: 0 | X57: 0 | Y57: 0 | Z57: 0 | AA57: 0 | AB57: 0 | AC57: 0
A58: InvenioRDM | B58: 0 | C58: 0 | D58: 0 | E58: 0 | F58: 0 | G58: 0 | H58: 0 | I58: 0 | J58: 0 | K58: 0 | L58: 0 | M58: 0 | N58: 0 | O58: 0 | P58: 0 | Q58: 0 | R58: 0 | S58: 0 | T58: 0 | U58: 0 | V58: 1 | W58: 0 | X58: 0 | Y58: 0 | Z58: 0 | AA58: 1 | AB58: 0 | AC58: 1 | AD58: Staff roles with responsibility for community engagement
A59: iRODS | B59: 1 | C59: 0 | D59: 1 | E59: 1 | F59: 0 | G59: 1 | H59: 1 | I59: 1 | J59: 1 | K59: 1 | L59: 1 | M59: 1 | N59: 0 | O59: 0 | P59: 0 | Q59: 0 | R59: 0 | S59: 0 | T59: 0 | U59: 0 | V59: 0 | W59: 0 | X59: 0 | Y59: 0 | Z59: 10 | AA59: 0 | AB59: 0 | AC59: 10 | AD59: Annual meetings; Community calls; Conference participation; Interest, working, user, or advisory groups; Mailing lists and discussion forums (including Slack); Social media; Staff roles with responsibility for community engagement; User research; Volunteer or ambassador network; Webinars and training
A60: Islandora | B60: 1 | C60: 0 | D60: 1 | E60: 1 | F60: 1 | G60: 1 | H60: 1 | I60: 1 | J60: 1 | K60: 1 | L60: 1 | M60: 1 | N60: 0 | O60: 0 | P60: 1 | Q60: 1 | R60: 0 | S60: 1 | T60: 0 | U60: 0 | V60: 0 | W60: 1 | X60: 1 | Y60: 0 | Z60: 11 | AA60: 5 | AB60: 0 | AC60: 11 | AD60: Annual meetings; Community calls; Conference participation; Development sprints; Interest, working, user, or advisory groups; Mailing lists and discussion forums (including Slack); Social media; Staff roles with responsibility for community engagement; User research; Volunteer or ambassador network; Webinars and training
A61: Janeway | B61: 0 | C61: 0 | D61: 0 | E61: 0 | F61: 0 | G61: 0 | H61: 0 | I61: 0 | J61: 0 | K61: 0 | L61: 0 | M61: 0 | N61: 0 | O61: 0 | P61: 0 | Q61: 0 | R61: 0 | S61: 0 | T61: 0 | U61: 0 | V61: 0 | W61: 0 | X61: 0 | Y61: 0 | Z61: 0 | AA61: 0 | AB61: 0 | AC61: 0
A62: JHOVE | B62: 1 | C62: 1 | D62: 1 | E62: 0 | F62: 1 | G62: 1 | H62: 1 | I62: 1 | J62: 1 | K62: 0 | L62: 0 | M62: 1 | N62: 0 | O62: 0 | P62: 0 | Q62: 0 | R62: 0 | S62: 0 | T62: 0 | U62: 0 | V62: 0 | W62: 0 | X62: 0 | Y62: 0 | Z62: 9 | AA62: 0 | AB62: 0 | AC62: 9 | AD62: Annual meetings; Blogs; Community calls; Development sprints; Interest, working, user, or advisory groups; Mailing lists and discussion forums (including Slack); Social media; Staff roles with responsibility for community engagement; Webinars and training
A63: LA Referencia | B63: 0 | C63: 0 | D63: 0 | E63: 0 | F63: 0 | G63: 0 | H63: 0 | I63: 0 | J63: 0 | K63: 0 | L63: 0 | M63: 0 | N63: 0 | O63: 0 | P63: 0 | Q63: 0 | R63: 0 | S63: 0 | T63: 0 | U63: 0 | V63: 0 | W63: 0 | X63: 0 | Y63: 0 | Z63: 0 | AA63: 0 | AB63: 0 | AC63: 0
A64: Manifold | B64: 0 | C64: 0 | D64: 0 | E64: 0 | F64: 0 | G64: 0 | H64: 0 | I64: 0 | J64: 0 | K64: 0 | L64: 0 | M64: 0 | N64: 0 | O64: 0 | P64: 0 | Q64: 0 | R64: 0 | S64: 0 | T64: 0 | U64: 0 | V64: 0 | W64: 0 | X64: 0 | Y64: 0 | Z64: 0 | AA64: 0 | AB64: 0 | AC64: 0
A65: medRxiv | B65: 0 | C65: 1 | D65: 0 | E65: 1 | F65: 0 | G65: 0 | H65: 1 | I65: 1 | J65: 1 | K65: 1 | L65: 1 | M65: 1 | N65: 0 | O65: 0 | P65: 0 | Q65: 0 | R65: 0 | S65: 0 | T65: 0 | U65: 0 | V65: 0 | W65: 1 | X65: 1 | Y65: 0 | Z65: 8 | AA65: 2 | AB65: 0 | AC65: 9 | AD65: Blogs; Conference participation; Mailing lists and discussion forums (including Slack); Other; Social media; Staff roles with responsibility for community engagement; User research; Volunteer or ambassador network; Webinars and training
A66: Metadata Encoding and Transmission Standard (METS) | B66: 0 | C66: 0 | D66: 0 | E66: 1 | F66: 0 | G66: 0 | H66: 1 | I66: 0 | J66: 0 | K66: 0 | L66: 0 | M66: 0 | N66: 0 | O66: 0 | P66: 0 | Q66: 0 | R66: 0 | S66: 0 | T66: 0 | U66: 0 | V66: 0 | W66: 0 | X66: 0 | Y66: 0 | Z66: 2 | AA66: 0 | AB66: 0 | AC66: 2 | AD66: Conference participation; Mailing lists and discussion forums (including Slack)
A67: Mirador | B67: 0 | C67: 0 | D67: 0 | E67: 0 | F67: 0 | G67: 0 | H67: 0 | I67: 0 | J67: 0 | K67: 0 | L67: 0 | M67: 0 | N67: 0 | O67: 0 | P67: 1 | Q67: 0 | R67: 0 | S67: 0 | T67: 1 | U67: 0 | V67: 0 | W67: 1 | X67: 0 | Y67: 0 | Z67: 0 | AA67: 3 | AB67: 0 | AC67: 3 | AD67: Community calls; Mailing lists and discussion forums (including Slack); User research
A68: Mukurtu CMS | B68: 0 | C68: 0 | D68: 0 | E68: 0 | F68: 0 | G68: 0 | H68: 0 | I68: 0 | J68: 0 | K68: 0 | L68: 0 | M68: 0 | N68: 0 | O68: 0 | P68: 0 | Q68: 0 | R68: 0 | S68: 0 | T68: 0 | U68: 0 | V68: 1 | W68: 0 | X68: 0 | Y68: 0 | Z68: 0 | AA68: 1 | AB68: 0 | AC68: 1 | AD68: Staff roles with responsibility for community engagement
A69: MyCoRe | B69: 0 | C69: 0 | D69: 0 | E69: 0 | F69: 0 | G69: 0 | H69: 0 | I69: 0 | J69: 0 | K69: 0 | L69: 0 | M69: 0 | N69: 0 | O69: 0 | P69: 0 | Q69: 0 | R69: 0 | S69: 0 | T69: 0 | U69: 0 | V69: 0 | W69: 0 | X69: 0 | Y69: 0 | Z69: 0 | AA69: 0 | AB69: 0 | AC69: 0
A70: NumPy | B70: 0 | C70: 0 | D70: 0 | E70: 0 | F70: 0 | G70: 0 | H70: 0 | I70: 0 | J70: 0 | K70: 0 | L70: 0 | M70: 0 | N70: 0 | O70: 0 | P70: 0 | Q70: 0 | R70: 0 | S70: 0 | T70: 0 | U70: 0 | V70: 0 | W70: 0 | X70: 0 | Y70: 0 | Z70: 0 | AA70: 0 | AB70: 0 | AC70: 0
A71: OA.Report | B71: 0 | C71: 0 | D71: 0 | E71: 0 | F71: 0 | G71: 0 | H71: 0 | I71: 0 | J71: 0 | K71: 0 | L71: 0 | M71: 0 | N71: 0 | O71: 0 | P71: 0 | Q71: 0 | R71: 0 | S71: 0 | T71: 0 | U71: 0 | V71: 0 | W71: 0 | X71: 0 | Y71: 0 | Z71: 0 | AA71: 0 | AB71: 0 | AC71: 0
A72: OA Switchboard | B72: 0 | C72: 0 | D72: 0 | E72: 0 | F72: 0 | G72: 0 | H72: 0 | I72: 0 | J72: 0 | K72: 0 | L72: 0 | M72: 0 | N72: 0 | O72: 1 | P72: 1 | Q72: 1 | R72: 0 | S72: 1 | T72: 0 | U72: 0 | V72: 0 | W72: 0 | X72: 0 | Y72: 0 | Z72: 0 | AA72: 4 | AB72: 0 | AC72: 4 | AD72: Blogs; Community calls; Conference participation; Interest, working, user, or advisory groups
A73: Omeka | B73: 0 | C73: 0 | D73: 0 | E73: 0 | F73: 0 | G73: 0 | H73: 0 | I73: 0 | J73: 0 | K73: 0 | L73: 0 | M73: 0 | N73: 0 | O73: 0 | P73: 0 | Q73: 0 | R73: 0 | S73: 0 | T73: 0 | U73: 0 | V73: 0 | W73: 0 | X73: 0 | Y73: 0 | Z73: 0 | AA73: 0 | AB73: 0 | AC73: 0
A74: OpenAIRE Graph | B74: 0 | C74: 1 | D74: 1 | E74: 1 | F74: 0 | G74: 1 | H74: 1 | I74: 1 | J74: 1 | K74: 1 | L74: 0 | M74: 1 | N74: 0 | O74: 0 | P74: 0 | Q74: 0 | R74: 0 | S74: 0 | T74: 0 | U74: 0 | V74: 0 | W74: 0 | X74: 0 | Y74: 0 | Z74: 9 | AA74: 0 | AB74: 0 | AC74: 9 | AD74: Blogs; Community calls; Conference participation; Interest, working, user, or advisory groups; Mailing lists and discussion forums (including Slack); Social media; Staff roles with responsibility for community engagement; User research; Webinars and training
A75: OpenAlex | B75: 0 | C75: 0 | D75: 0 | E75: 0 | F75: 0 | G75: 0 | H75: 0 | I75: 0 | J75: 0 | K75: 0 | L75: 0 | M75: 0 | N75: 0 | O75: 0 | P75: 0 | Q75: 0 | R75: 0 | S75: 1 | T75: 0 | U75: 1 | V75: 0 | W75: 0 | X75: 0 | Y75: 1 | Z75: 0 | AA75: 3 | AB75: 0 | AC75: 3 | AD75: Interest, working, user, or advisory groups; Social media; Webinars and training
A76: OpenAPC | B76: 0 | C76: 1 | D76: 0 | E76: 1 | F76: 0 | G76: 0 | H76: 0 | I76: 1 | J76: 0 | K76: 0 | L76: 0 | M76: 1 | N76: 0 | O76: 0 | P76: 0 | Q76: 0 | R76: 0 | S76: 0 | T76: 0 | U76: 0 | V76: 0 | W76: 0 | X76: 0 | Y76: 0 | Z76: 4 | AA76: 0 | AB76: 0 | AC76: 4 | AD76: Blogs; Conference participation; Social media; Webinars and training
A77: OpenCitations | B77: 1 | C77: 1 | D77: 0 | E77: 1 | F77: 0 | G77: 1 | H77: 0 | I77: 1 | J77: 1 | K77: 0 | L77: 0 | M77: 1 | N77: 0 | O77: 0 | P77: 0 | Q77: 0 | R77: 0 | S77: 0 | T77: 0 | U77: 0 | V77: 0 | W77: 0 | X77: 0 | Y77: 0 | Z77: 7 | AA77: 0 | AB77: 0 | AC77: 7 | AD77: Annual meetings; Blogs; Conference participation; Interest, working, user, or advisory groups; Social media; Staff roles with responsibility for community engagement; Webinars and training
A78: openCost | B78: 0 | C78: 1 | D78: 1 | E78: 1 | F78: 0 | G78: 0 | H78: 1 | I78: 0 | J78: 0 | K78: 0 | L78: 0 | M78: 1 | N78: 0 | O78: 0 | P78: 0 | Q78: 0 | R78: 0 | S78: 0 | T78: 0 | U78: 0 | V78: 0 | W78: 0 | X78: 0 | Y78: 0 | Z78: 5 | AA78: 0 | AB78: 0 | AC78: 5 | AD78: Blogs; Community calls; Conference participation; Mailing lists and discussion forums (including Slack); Webinars and training
A79: Open Data Editor | B79: 0 | C79: 1 | D79: 1 | E79: 0 | F79: 0 | G79: 0 | H79: 0 | I79: 1 | J79: 0 | K79: 0 | L79: 0 | M79: 1 | N79: 0 | O79: 0 | P79: 0 | Q79: 0 | R79: 0 | S79: 0 | T79: 0 | U79: 0 | V79: 0 | W79: 0 | X79: 0 | Y79: 0 | Z79: 4 | AA79: 0 | AB79: 0 | AC79: 4 | AD79: Blogs; Community calls; Social media; Webinars and training
A80: OpenEdition | B80: 0 | C80: 0 | D80: 0 | E80: 0 | F80: 0 | G80: 0 | H80: 0 | I80: 0 | J80: 0 | K80: 0 | L80: 0 | M80: 0 | N80: 1 | O80: 0 | P80: 1 | Q80: 0 | R80: 0 | S80: 0 | T80: 0 | U80: 0 | V80: 0 | W80: 0 | X80: 0 | Y80: 1 | Z80: 0 | AA80: 3 | AB80: 0 | AC80: 3 | AD80: Annual meetings; Community calls; Webinars and training
A81: Open Journal Systems (OJS) | B81: 0 | C81: 0 | D81: 0 | E81: 0 | F81: 0 | G81: 0 | H81: 0 | I81: 0 | J81: 0 | K81: 0 | L81: 0 | M81: 0 | N81: 0 | O81: 0 | P81: 0 | Q81: 0 | R81: 1 | S81: 1 | T81: 1 | U81: 0 | V81: 0 | W81: 0 | X81: 0 | Y81: 1 | Z81: 0 | AA81: 4 | AB81: 0 | AC81: 4 | AD81: Development sprints; Interest, working, user, or advisory groups; Mailing lists and discussion forums (including Slack); Webinars and training
A82: Open Monograph Press (OMP) | B82: 0 | C82: 0 | D82: 0 | E82: 0 | F82: 0 | G82: 0 | H82: 0 | I82: 0 | J82: 0 | K82: 0 | L82: 0 | M82: 0 | N82: 0 | O82: 0 | P82: 0 | Q82: 0 | R82: 1 | S82: 1 | T82: 1 | U82: 0 | V82: 0 | W82: 0 | X82: 0 | Y82: 1 | Z82: 0 | AA82: 4 | AB82: 0 | AC82: 4 | AD82: Development sprints; Interest, working, user, or advisory groups; Mailing lists and discussion forums (including Slack); Webinars and training
A83: Open Preprint Systems (OPS) | B83: 0 | C83: 0 | D83: 0 | E83: 0 | F83: 0 | G83: 0 | H83: 0 | I83: 0 | J83: 0 | K83: 0 | L83: 0 | M83: 0 | N83: 0 | O83: 0 | P83: 0 | Q83: 0 | R83: 1 | S83: 1 | T83: 1 | U83: 0 | V83: 0 | W83: 0 | X83: 0 | Y83: 1 | Z83: 0 | AA83: 4 | AB83: 0 | AC83: 4 | AD83: Development sprints; Interest, working, user, or advisory groups; Mailing lists and discussion forums (including Slack); Webinars and training
A84: Openverse | B84: 0 | C84: 0 | D84: 0 | E84: 0 | F84: 0 | G84: 0 | H84: 0 | I84: 0 | J84: 0 | K84: 0 | L84: 0 | M84: 0 | N84: 0 | O84: 0 | P84: 0 | Q84: 0 | R84: 0 | S84: 0 | T84: 0 | U84: 0 | V84: 0 | W84: 0 | X84: 0 | Y84: 0 | Z84: 0 | AA84: 0 | AB84: 0 | AC84: 0
A85: O Portal Brasileiro de Publicações e Dados Científicos em Acesso Aberto (The Brazilian Open Access Publications and Scientific Data Portal) (Oasisbr) | B85: 0 | C85: 0 | D85: 0 | E85: 0 | F85: 0 | G85: 0 | H85: 0 | I85: 0 | J85: 0 | K85: 0 | L85: 0 | M85: 0 | N85: 0 | O85: 0 | P85: 0 | Q85: 0 | R85: 0 | S85: 0 | T85: 0 | U85: 0 | V85: 0 | W85: 0 | X85: 0 | Y85: 0 | Z85: 0 | AA85: 0 | AB85: 0 | AC85: 0
A86: OSF (Open Science Framework) | B86: 0 | C86: 0 | D86: 0 | E86: 0 | F86: 0 | G86: 0 | H86: 0 | I86: 0 | J86: 0 | K86: 0 | L86: 0 | M86: 0 | N86: 0 | O86: 0 | P86: 0 | Q86: 0 | R86: 0 | S86: 0 | T86: 0 | U86: 0 | V86: 0 | W86: 1 | X86: 0 | Y86: 1 | Z86: 0 | AA86: 2 | AB86: 0 | AC86: 2 | AD86: User research; Webinars and training
A87: Oxford Common File Layout | B87: 0 | C87: 0 | D87: 0 | E87: 0 | F87: 0 | G87: 0 | H87: 0 | I87: 0 | J87: 0 | K87: 0 | L87: 0 | M87: 0 | N87: 0 | O87: 0 | P87: 0 | Q87: 0 | R87: 0 | S87: 0 | T87: 0 | U87: 0 | V87: 0 | W87: 0 | X87: 0 | Y87: 0 | Z87: 0 | AA87: 0 | AB87: 0 | AC87: 0
A88: Peer Community In | B88: 0 | C88: 0 | D88: 0 | E88: 0 | F88: 0 | G88: 0 | H88: 0 | I88: 0 | J88: 0 | K88: 0 | L88: 0 | M88: 0 | N88: 0 | O88: 0 | P88: 0 | Q88: 0 | R88: 0 | S88: 0 | T88: 0 | U88: 0 | V88: 0 | W88: 0 | X88: 0 | Y88: 0 | Z88: 0 | AA88: 0 | AB88: 0 | AC88: 0
A89: PKP Preservation Network | B89: 0 | C89: 0 | D89: 0 | E89: 0 | F89: 0 | G89: 0 | H89: 0 | I89: 0 | J89: 0 | K89: 0 | L89: 0 | M89: 0 | N89: 0 | O89: 0 | P89: 0 | Q89: 0 | R89: 0 | S89: 0 | T89: 0 | U89: 0 | V89: 0 | W89: 0 | X89: 0 | Y89: 0 | Z89: 0 | AA89: 0 | AB89: 0 | AC89: 0
A90: PREreview | B90: 0 | C90: 1 | D90: 1 | E90: 1 | F90: 1 | G90: 1 | H90: 1 | I90: 1 | J90: 1 | K90: 1 | L90: 1 | M90: 1 | N90: 0 | O90: 0 | P90: 0 | Q90: 0 | R90: 0 | S90: 0 | T90: 1 | U90: 0 | V90: 0 | W90: 1 | X90: 1 | Y90: 1 | Z90: 11 | AA90: 4 | AB90: 0 | AC90: 11 | AD90: Blogs; Community calls; Conference participation; Development sprints; Interest, working, user, or advisory groups; Mailing lists and discussion forums (including Slack); Social media; Staff roles with responsibility for community engagement; User research; Volunteer or ambassador network; Webinars and training
A91: Pressbooks | B91: 0 | C91: 0 | D91: 0 | E91: 0 | F91: 0 | G91: 0 | H91: 0 | I91: 0 | J91: 0 | K91: 0 | L91: 0 | M91: 0 | N91: 0 | O91: 0 | P91: 1 | Q91: 1 | R91: 0 | S91: 0 | T91: 0 | U91: 0 | V91: 0 | W91: 0 | X91: 0 | Y91: 0 | Z91: 0 | AA91: 2 | AB91: 0 | AC91: 2 | AD91: Community calls; Conference participation
A92: Public Access Submission System | B92: 0 | C92: 0 | D92: 0 | E92: 0 | F92: 0 | G92: 0 | H92: 0 | I92: 0 | J92: 0 | K92: 0 | L92: 0 | M92: 0 | N92: 0 | O92: 0 | P92: 0 | Q92: 0 | R92: 0 | S92: 0 | T92: 0 | U92: 0 | V92: 0 | W92: 0 | X92: 0 | Y92: 0 | Z92: 0 | AA92: 0 | AB92: 0 | AC92: 0
A93: Public Utility Data Liberation (PUDL) | B93: 0 | C93: 1 | D93: 0 | E93: 1 | F93: 1 | G93: 0 | H93: 1 | I93: 1 | J93: 1 | K93: 1 | L93: 0 | M93: 1 | N93: 0 | O93: 0 | P93: 0 | Q93: 0 | R93: 0 | S93: 0 | T93: 0 | U93: 0 | V93: 0 | W93: 0 | X93: 0 | Y93: 0 | Z93: 8 | AA93: 0 | AB93: 0 | AC93: 8 | AD93: Blogs; Conference participation; Development sprints; Mailing lists and discussion forums (including Slack); Social media; Staff roles with responsibility for community engagement; User research; Webinars and training
A94: PubPub | B94: 0 | C94: 0 | D94: 0 | E94: 0 | F94: 0 | G94: 0 | H94: 0 | I94: 0 | J94: 0 | K94: 0 | L94: 0 | M94: 0 | N94: 0 | O94: 0 | P94: 1 | Q94: 1 | R94: 0 | S94: 1 | T94: 0 | U94: 0 | V94: 0 | W94: 1 | X94: 0 | Y94: 0 | Z94: 0 | AA94: 4 | AB94: 0 | AC94: 4 | AD94: Community calls; Conference participation; Interest, working, user, or advisory groups; User research
A95: Pundit | B95: 0 | C95: 1 | D95: 0 | E95: 1 | F95: 0 | G95: 0 | H95: 0 | I95: 1 | J95: 0 | K95: 0 | L95: 0 | M95: 0 | N95: 0 | O95: 0 | P95: 0 | Q95: 0 | R95: 0 | S95: 0 | T95: 0 | U95: 0 | V95: 0 | W95: 0 | X95: 0 | Y95: 0 | Z95: 3 | AA95: 0 | AB95: 0 | AC95: 3 | AD95: Blogs; Conference participation; Social media
A96: pyOpenSci | B96: 0 | C96: 0 | D96: 0 | E96: 0 | F96: 0 | G96: 0 | H96: 0 | I96: 0 | J96: 0 | K96: 0 | L96: 0 | M96: 0 | N96: 0 | O96: 0 | P96: 0 | Q96: 0 | R96: 0 | S96: 0 | T96: 0 | U96: 0 | V96: 0 | W96: 0 | X96: 0 | Y96: 0 | Z96: 0 | AA96: 0 | AB96: 0 | AC96: 0
A97: Renku | B97: 1 | C97: 1 | D97: 1 | E97: 1 | F97: 0 | G97: 0 | H97: 1 | I97: 0 | J97: 0 | K97: 1 | L97: 0 | M97: 1 | N97: 0 | O97: 0 | P97: 0 | Q97: 0 | R97: 0 | S97: 0 | T97: 0 | U97: 0 | V97: 0 | W97: 0 | X97: 0 | Y97: 0 | Z97: 7 | AA97: 0 | AB97: 0 | AC97: 7 | AD97: Annual meetings; Blogs; Community calls; Conference participation; Mailing lists and discussion forums (including Slack); User research; Webinars and training
A98: RePEc | B98: 0 | C98: 1 | D98: 0 | E98: 0 | F98: 0 | G98: 0 | H98: 1 | I98: 0 | J98: 1 | K98: 0 | L98: 1 | M98: 0 | N98: 0 | O98: 0 | P98: 0 | Q98: 0 | R98: 0 | S98: 0 | T98: 0 | U98: 0 | V98: 0 | W98: 0 | X98: 0 | Y98: 0 | Z98: 4 | AA98: 0 | AB98: 0 | AC98: 4 | AD98: Blogs; Mailing lists and discussion forums (including Slack); Staff roles with responsibility for community engagement; Volunteer or ambassador network
A99: Research Organization Registry (ROR) | B99: 1 | C99: 1 | D99: 1 | E99: 1 | F99: 0 | G99: 1 | H99: 1 | I99: 1 | J99: 1 | K99: 0 | L99: 0 | M99: 1 | N99: 0 | O99: 0 | P99: 1 | Q99: 0 | R99: 0 | S99: 1 | T99: 1 | U99: 0 | V99: 0 | W99: 0 | X99: 0 | Y99: 0 | Z99: 9 | AA99: 3 | AB99: 0 | AC99: 10 | AD99: Annual meetings; Blogs; Community calls; Conference participation; Interest, working, user, or advisory groups; Mailing lists and discussion forums (including Slack); Other; Social media; Staff roles with responsibility for community engagement; Webinars and training
A100: Rogue Scholar | B100: 0 | C100: 0 | D100: 0 | E100: 0 | F100: 0 | G100: 0 | H100: 0 | I100: 0 | J100: 0 | K100: 0 | L100: 0 | M100: 0 | N100: 0 | O100: 0 | P100: 0 | Q100: 0 | R100: 0 | S100: 0 | T100: 0 | U100: 0 | V100: 0 | W100: 0 | X100: 0 | Y100: 0 | Z100: 0 | AA100: 0 | AB100: 0 | AC100: 0
...

Sheet Contribution Coding
A1: Service | B1: 040: Contribute funds | C1: 040: Contribute to code | D1: 040: Contribute to documentation | E1: 040: Contribute to education or training | F1: 040: Contribute to governance | G1: 040: Contribute to peer reviews | H1: 040: Contribute to user research or user testing | I1: 040: Contribute to working groups or interest groups | J1: 940 text | K1: Other selected and described | L1: Route count / 9 | M1: Coded routes
A2: 2i2c | B2: 0 | C2: 0 | D2: 0 | E2: 0 | F2: 0 | G2: 0 | H2: 0 | I2: 0 | K2: 0 | L2: 0
A3: Academic Preservation Trust (APTrust) | B3: 1 | C3: 1 | D3: 1 | E3: 1 | F3: 1 | G3: 0 | H3: 1 | I3: 1 | K3: 0 | L3: 7 | M3: Contribute funds; Contribute to code; Contribute to documentation; Contribute to education or training; Contribute to governance; Contribute to user research or user testing; Contribute to working groups or interest groups
A4: AfricArXiv | B4: 0 | C4: 0 | D4: 0 | E4: 0 | F4: 0 | G4: 0 | H4: 0 | I4: 0 | K4: 0 | L4: 0
A5: Arches Heritage Data Management Platform | B5: 0 | C5: 0 | D5: 0 | E5: 0 | F5: 0 | G5: 0 | H5: 0 | I5: 0 | K5: 0 | L5: 0
A6: Archipelago Commons | B6: 0 | C6: 1 | D6: 1 | E6: 0 | F6: 0 | G6: 0 | H6: 0 | I6: 1 | K6: 0 | L6: 3 | M6: Contribute to code; Contribute to documentation; Contribute to working groups or interest groups
A7: Archival Resource Key | B7: 1 | C7: 1 | D7: 1 | E7: 1 | F7: 0 | G7: 0 | H7: 0 | I7: 1 | K7: 0 | L7: 5 | M7: Contribute funds; Contribute to code; Contribute to documentation; Contribute to education or training; Contribute to working groups or interest groups
A8: Archivematica | B8: 0 | C8: 0 | D8: 0 | E8: 0 | F8: 0 | G8: 0 | H8: 0 | I8: 0 | K8: 0 | L8: 0
A9: ArchivesSpace | B9: 0 | C9: 0 | D9: 0 | E9: 0 | F9: 0 | G9: 0 | H9: 0 | I9: 0 | K9: 0 | L9: 0
A10: ARGOS | B10: 0 | C10: 0 | D10: 0 | E10: 0 | F10: 0 | G10: 0 | H10: 0 | I10: 0 | K10: 0 | L10: 0
A11: arXiv | B11: 1 | C11: 1 | D11: 0 | E11: 0 | F11: 0 | G11: 0 | H11: 0 | I11: 1 | K11: 0 | L11: 3 | M11: Contribute funds; Contribute to code; Contribute to working groups or interest groups
A12: AtoM | B12: 0 | C12: 0 | D12: 0 | E12: 0 | F12: 0 | G12: 0 | H12: 0 | I12: 0 | K12: 0 | L12: 0
A13: Avalon Media System | B13: 1 | C13: 1 | D13: 1 | E13: 1 | F13: 1 | G13: 0 | H13: 1 | I13: 0 | K13: 0 | L13: 6 | M13: Contribute funds; Contribute to code; Contribute to documentation; Contribute to education or training; Contribute to governance; Contribute to user research or user testing
A14: Biodiversity Heritage Library | B14: 1 | C14: 0 | D14: 0 | E14: 0 | F14: 0 | G14: 0 | H14: 0 | I14: 0 | K14: 0 | L14: 1 | M14: Contribute funds
A15: bioRxiv | B15: 0 | C15: 0 | D15: 0 | E15: 0 | F15: 0 | G15: 0 | H15: 0 | I15: 0 | K15: 0 | L15: 0
A16: BitCurator Environment | B16: 0 | C16: 1 | D16: 1 | E16: 1 | F16: 1 | G16: 0 | H16: 0 | I16: 1 | K16: 0 | L16: 5 | M16: Contribute to code; Contribute to documentation; Contribute to education or training; Contribute to governance; Contribute to working groups or interest groups
A17: Blacklight | B17: 1 | C17: 1 | D17: 1 | E17: 1 | F17: 1 | G17: 0 | H17: 1 | I17: 1 | K17: 0 | L17: 7 | M17: Contribute funds; Contribute to code; Contribute to documentation; Contribute to education or training; Contribute to governance; Contribute to user research or user testing; Contribute to working groups or interest groups
A18: BrCRIS | B18: 0 | C18: 0 | D18: 0 | E18: 0 | F18: 0 | G18: 0 | H18: 0 | I18: 0 | K18: 0 | L18: 0
A19: Browsertrix | B19: 0 | C19: 1 | D19: 1 | E19: 0 | F19: 0 | G19: 0 | H19: 0 | I19: 0 | K19: 0 | L19: 2 | M19: Contribute to code; Contribute to documentation
A20: CLOCKSS | B20: 0 | C20: 0 | D20: 0 | E20: 0 | F20: 0 | G20: 0 | H20: 0 | I20: 0 | K20: 0 | L20: 0
A21: COAR International Repository Directory (IRD) | B21: 0 | C21: 0 | D21: 1 | E21: 0 | F21: 0 | G21: 0 | H21: 1 | I21: 0 | K21: 0 | L21: 2 | M21: Contribute to documentation; Contribute to user research or user testing
A22: COAR Notify | B22: 0 | C22: 1 | D22: 1 | E22: 1 | F22: 0 | G22: 0 | H22: 1 | I22: 1 | K22: 0 | L22: 5 | M22: Contribute to code; Contribute to documentation; Contribute to education or training; Contribute to user research or user testing; Contribute to working groups or interest groups
A23: CollectiveAccess | B23: 0 | C23: 0 | D23: 0 | E23: 0 | F23: 0 | G23: 0 | H23: 0 | I23: 0 | K23: 0 | L23: 0
A24: CORE | B24: 1 | C24: 1 | D24: 1 | E24: 0 | F24: 0 | G24: 0 | H24: 0 | I24: 0 | K24: 0 | L24: 3 | M24: Contribute funds; Contribute to code; Contribute to documentation
A25: COUNTER Code of Practice | B25: 1 | C25: 0 | D25: 1 | E25: 1 | F25: 1 | G25: 0 | H25: 0 | I25: 1 | K25: 0 | L25: 5 | M25: Contribute funds; Contribute to documentation; Contribute to education or training; Contribute to governance; Contribute to working groups or interest groups
A26: Creative Commons Licenses | B26: 1 | C26: 1 | D26: 0 | E26: 0 | F26: 0 | G26: 0 | H26: 0 | I26: 1 | K26: 0 | L26: 3 | M26: Contribute funds; Contribute to code; Contribute to working groups or interest groups
A27: Crossref Metadata Retrieval | B27: 1 | C27: 1 | D27: 1 | E27: 1 | F27: 0 | G27: 0 | H27: 0 | I27: 1 | K27: 0 | L27: 5 | M27: Contribute funds; Contribute to code; Contribute to documentation; Contribute to education or training; Contribute to working groups or interest groups
A28: D4Science Infrastructure | B28: 0 | C28: 0 | D28: 0 | E28: 0 | F28: 0 | G28: 0 | H28: 0 | I28: 0 | K28: 0 | L28: 0
A29: DART (Digital Archivist's Resource Tool) | B29: 1 | C29: 1 | D29: 1 | E29: 1 | F29: 1 | G29: 0 | H29: 1 | I29: 1 | K29: 0 | L29: 7 | M29: Contribute funds; Contribute to code; Contribute to documentation; Contribute to education or training; Contribute to governance; Contribute to user research or user testing; Contribute to working groups or interest groups
A30: Database Information System | B30: 0 | C30: 0 | D30: 0 | E30: 0 | F30: 0 | G30: 0 | H30: 0 | I30: 1 | K30: 0 | L30: 1 | M30: Contribute to working groups or interest groups
A31: Data Citation Corpus | B31: 0 | C31: 0 | D31: 0 | E31: 0 | F31: 0 | G31: 0 | H31: 0 | I31: 0 | J31: Groups can contribute citations to the Corpus | K31: 1 | L31: 1 | M31: Other
A32: DataCite | B32: 1 | C32: 0 | D32: 1 | E32: 0 | F32: 0 | G32: 0 | H32: 0 | I32: 1 | K32: 0 | L32: 3 | M32: Contribute funds; Contribute to documentation; Contribute to working groups or interest groups
A33: Data Stewardship Wizard | B33: 0 | C33: 1 | D33: 1 | E33: 1 | F33: 1 | G33: 0 | H33: 1 | I33: 0 | K33: 0 | L33: 5 | M33: Contribute to code; Contribute to documentation; Contribute to education or training; Contribute to governance; Contribute to user research or user testing
A34: Dataverse | B34: 0 | C34: 1 | D34: 1 | E34: 1 | F34: 0 | G34: 0 | H34: 0 | I34: 1 | K34: 0 | L34: 4 | M34: Contribute to code; Contribute to documentation; Contribute to education or training; Contribute to working groups or interest groups
A35: DLCM Backend | B35: 0 | C35: 0 | D35: 0 | E35: 0 | F35: 0 | G35: 0 | H35: 0 | I35: 0 | K35: 0 | L35: 0
A36: DLCM Portal | B36: 0 | C36: 0 | D36: 0 | E36: 0 | F36: 0 | G36: 0 | H36: 0 | I36: 0 | K36: 0 | L36: 0
A37: DMP Tool | B37: 0 | C37: 0 | D37: 0 | E37: 0 | F37: 0 | G37: 0 | H37: 0 | I37: 0 | K37: 0 | L37: 0
A38: DOAJ (Directory of Open Access Journals) | B38: 0 | C38: 1 | D38: 1 | E38: 1 | F38: 0 | G38: 0 | H38: 1 | I38: 1 | J38: <p>We have a network of over 100 volunteers who review applications. We have regional representation through our Ambassador network. Some of our volunteers and ambassadors have been with us for more than 10 years.</p> <p>We have a dedicated community engagement role to ensure that we are in touch with the large number of stakeholder groups that use and rely upon DOAJ. When we move to our new governance structure, we will establish a stakeholder council.</p> <p>Our strategy states we will advocate for equity and diversity in global open access journal publishing. To do that, we engage with journal platforms and representative groups from around the world, e.g., the Chinese Academy of Science, KISTI in South Korea, J-STAGE in Japan, Publicera in Sweden, Scielo in Latin America, ASSAf and AJOL in South Africa and more.</p> | K38: 0 | L38: 5 | M38: Contribute to code; Contribute to documentation; Contribute to education or training; Contribute to user research or user testing; Contribute to working groups or interest groups
A39: dokieli | B39: 1 | C39: 1 | D39: 1 | E39: 1 | F39: 0 | G39: 0 | H39: 0 | I39: 0 | K39: 0 | L39: 4 | M39: Contribute funds; Contribute to code; Contribute to documentation; Contribute to education or training
A40: Dryad | B40: 1 | C40: 0 | D40: 0 | E40: 1 | F40: 1 | G40: 0 | H40: 0 | I40: 1 | K40: 0 | L40: 4 | M40: Contribute funds; Contribute to education or training; Contribute to governance; Contribute to working groups or interest groups
A41: DSpace | B41: 1 | C41: 1 | D41: 1 | E41: 1 | F41: 1 | G41: 1 | H41: 0 | I41: 1 | K41: 0 | L41: 7 | M41: Contribute funds; Contribute to code; Contribute to documentation; Contribute to education or training; Contribute to governance; Contribute to peer reviews; Contribute to working groups or interest groups
A42: DuraCloud | B42: 0 | C42: 0 | D42: 0 | E42: 0 | F42: 0 | G42: 0 | H42: 0 | I42: 0 | K42: 0 | L42: 0
A43: Episciences | B43: 0 | C43: 0 | D43: 0 | E43: 0 | F43: 0 | G43: 0 | H43: 0 | I43: 0 | K43: 0 | L43: 0
A44: EPrints | B44: 0 | C44: 0 | D44: 0 | E44: 0 | F44: 0 | G44: 0 | H44: 0 | I44: 0 | K44: 0 | L44: 0
A45: Érudit | B45: 0 | C45: 0 | D45: 0 | E45: 1 | F45: 0 | G45: 1 | H45: 0 | I45: 0 | K45: 0 | L45: 2 | M45: Contribute to education or training; Contribute to peer reviews
A46: Europe PMC | B46: 0 | C46: 1 | D46: 0 | E46: 1 | F46: 0 | G46: 0 | H46: 1 | I46: 0 | K46: 0 | L46: 3 | M46: Contribute to code; Contribute to education or training; Contribute to user research or user testing
A47: FAIR Wizard | B47: 0 | C47: 0 | D47: 1 | E47: 1 | F47: 0 | G47: 0 | H47: 0 | I47: 1 | J47: Content creation | K47: 1 | L47: 4 | M47: Contribute to documentation; Contribute to education or training; Contribute to working groups or interest groups; Other
A48: Fedora | B48: 1 | C48: 1 | D48: 1 | E48: 1 | F48: 1 | G48: 1 | H48: 1 | I48: 1 | K48: 0 | L48: 8 | M48: Contribute funds; Contribute to code; Contribute to documentation; Contribute to education or training; Contribute to governance; Contribute to peer reviews; Contribute to user research or user testing; Contribute to working groups or interest groups
A49: fido | B49: 0 | C49: 1 | D49: 1 | E49: 0 | F49: 0 | G49: 0 | H49: 0 | I49: 1 | K49: 0 | L49: 3 | M49: Contribute to code; Contribute to documentation; Contribute to working groups or interest groups
A50: Fulcrum | B50: 0 | C50: 1 | D50: 0 | E50: 0 | F50: 0 | G50: 0 | H50: 0 | I50: 1 | K50: 0 | L50: 2 | M50: Contribute to code; Contribute to working groups or interest groups
A51: Galaxy | B51: 0 | C51: 0 | D51: 0 | E51: 0 | F51: 0 | G51: 0 | H51: 0 | I51: 0 | K51: 0 | L51: 0
A52: GeoServer | B52: 0 | C52: 1 | D52: 0 | E52: 0 | F52: 0 | G52: 0 | H52: 0 | I52: 0 | K52: 0 | L52: 1 | M52: Contribute to code
A53: Hyku | B53: 1 | C53: 1 | D53: 1 | E53: 1 | F53: 1 | G53: 0 | H53: 0 | I53: 1 | K53: 0 | L53: 6 | M53: Contribute funds; Contribute to code; Contribute to documentation; Contribute to education or training; Contribute to governance; Contribute to working groups or interest groups
A54: Hyrax | B54: 1 | C54: 1 | D54: 1 | E54: 1 | F54: 1 | G54: 0 | H54: 1 | I54: 1 | K54: 0 | L54: 7 | M54: Contribute funds; Contribute to code; Contribute to documentation; Contribute to education or training; Contribute to governance; Contribute to user research or user testing; Contribute to working groups or interest groups
A55: IIIF | B55: 1 | C55: 1 | D55: 1 | E55: 1 | F55: 0 | G55: 0 | H55: 0 | I55: 1 | K55: 0 | L55: 5 | M55: Contribute funds; Contribute to code; Contribute to documentation; Contribute to education or training; Contribute to working groups or interest groups
A56: ImpactU | B56: 0 | C56: 0 | D56: 0 | E56: 0 | F56: 0 | G56: 0 | H56: 0 | I56: 0 | K56: 0 | L56: 0
A57: International Generic Sample Number (IGSN) | B57: 0 | C57: 0 | D57: 0 | E57: 0 | F57: 0 | G57: 0 | H57: 0 | I57: 0 | K57: 0 | L57: 0
A58: InvenioRDM | B58: 1 | C58: 1 | D58: 1 | E58: 1 | F58: 0 | G58: 0 | H58: 0 | I58: 1 | K58: 0 | L58: 5 | M58: Contribute funds; Contribute to code; Contribute to documentation; Contribute to education or training; Contribute to working groups or interest groups
A59: iRODS | B59: 1 | C59: 1 | D59: 1 | E59: 1 | F59: 1 | G59: 0 | H59: 1 | I59: 1 | K59: 0 | L59: 7 | M59: Contribute funds; Contribute to code; Contribute to documentation; Contribute to education or training; Contribute to governance; Contribute to user research or user testing; Contribute to working groups or interest groups
A60: Islandora | B60: 1 | C60: 1 | D60: 1 | E60: 1 | F60: 1 | G60: 0 | H60: 1 | I60: 1 | K60: 0 | L60: 7 | M60: Contribute funds; Contribute to code; Contribute to documentation; Contribute to education or training; Contribute to governance; Contribute to user research or user testing; Contribute to working groups or interest groups
A61: Janeway | B61: 0 | C61: 1 | D61: 1 | E61: 0 | F61: 0 | G61: 0 | H61: 0 | I61: 0 | K61: 0 | L61: 2 | M61: Contribute to code; Contribute to documentation
A62: JHOVE | B62: 0 | C62: 0 | D62: 0 | E62: 0 | F62: 0 | G62: 0 | H62: 0 | I62: 0 | K62: 0 | L62: 0
A63: LA Referencia | B63: 0 | C63: 0 | D63: 0 | E63: 0 | F63: 0 | G63: 0 | H63: 0 | I63: 0 | K63: 0 | L63: 0
A64: Manifold | B64: 0 | C64: 1 | D64: 0 | E64: 0 | F64: 0 | G64: 0 | H64: 0 | I64: 0 | K64: 0 | L64: 1 | M64: Contribute to code
A65: medRxiv | B65: 0 | C65: 0 | D65: 1 | E65: 0 | F65: 0 | G65: 0 | H65: 0 | I65: 0 | K65: 0 | L65: 1 | M65: Contribute to documentation
A66: Metadata Encoding and Transmission Standard (METS) | B66: 0 | C66: 1 | D66: 1 | E66: 1 | F66: 0 | G66: 0 | H66: 1 | I66: 0 | K66: 0 | L66: 4 | M66: Contribute to code; Contribute to documentation; Contribute to education or training; Contribute to user research or user testing
A67: Mirador | B67: 0 | C67: 1 | D67: 1 | E67: 1 | F67: 0 | G67: 0 | H67: 0 | I67: 1 | K67: 0 | L67: 4 | M67: Contribute to code; Contribute to documentation; Contribute to education or training; Contribute to working groups or interest groups
A68: Mukurtu CMS | B68: 0 | C68: 1 | D68: 1 | E68: 0 | F68: 0 | G68: 0 | H68: 0 | I68: 0 | K68: 0 | L68: 2 | M68: Contribute to code; Contribute to documentation
A69: MyCoRe | B69: 0 | C69: 0 | D69: 0 | E69: 0 | F69: 0 | G69: 0 | H69: 0 | I69: 0 | K69: 0 | L69: 0
A70: NumPy | B70: 0 | C70: 0 | D70: 0 | E70: 0 | F70: 0 | G70: 0 | H70: 0 | I70: 0 | K70: 0 | L70: 0
A71: OA.Report | B71: 0 | C71: 0 | D71: 0 | E71: 0 | F71: 0 | G71: 0 | H71: 0 | I71: 0 | K71: 0 | L71: 0
A72: OA Switchboard | B72: 1 | C72: 1 | D72: 1 | E72: 1 | F72: 0 | G72: 0 | H72: 0 | I72: 1 | K72: 0 | L72: 5 | M72: Contribute funds; Contribute to code; Contribute to documentation; Contribute to education or training; Contribute to working groups or interest groups
A73: Omeka | B73: 0 | C73: 1 | D73: 1 | E73: 0 | F73: 0 | G73: 0 | H73: 0 | I73: 0 | K73: 0 | L73: 2 | M73: Contribute to code; Contribute to documentation
A74: OpenAIRE Graph | B74: 0 | C74: 0 | D74: 0 | E74: 0 | F74: 0 | G74: 0 | H74: 0 | I74: 0 | K74: 0 | L74: 0
A75: OpenAlex | B75: 0 | C75: 1 | D75: 0 | E75: 0 | F75: 0 | G75: 0 | H75: 0 | I75: 0 | K75: 0 | L75: 1 | M75: Contribute to code
A76: OpenAPC | B76: 0 | C76: 0 | D76: 0 | E76: 0 | F76: 0 | G76: 0 | H76: 0 | I76: 0 | K76: 0 | L76: 0
A77: OpenCitations | B77: 1 | C77: 1 | D77: 1 | E77: 1 | F77: 0 | G77: 0 | H77: 0 | I77: 1 | K77: 0 | L77: 5 | M77: Contribute funds; Contribute to code; Contribute to documentation; Contribute to education or training; Contribute to working groups or interest groups
A78: openCost | B78: 0 | C78: 0 | D78: 0 | E78: 0 | F78: 0 | G78: 0 | H78: 0 | I78: 0 | K78: 0 | L78: 0
A79: Open Data Editor | B79: 0 | C79: 0 | D79: 0 | E79: 0 | F79: 0 | G79: 0 | H79: 1 | I79: 0 | K79: 0 | L79: 1 | M79: Contribute to user research or user testing
A80: OpenEdition | B80: 0 | C80: 0 | D80: 0 | E80: 0 | F80: 0 | G80: 0 | H80: 0 | I80: 1 | K80: 0 | L80: 1 | M80: Contribute to working groups or interest groups
A81: Open Journal Systems (OJS) | B81: 1 | C81: 1 | D81: 1 | E81: 1 | F81: 0 | G81: 0 | H81: 0 | I81: 1 | K81: 0 | L81: 5 | M81: Contribute funds; Contribute to code; Contribute to documentation; Contribute to education or training; Contribute to working groups or interest groups
A82: Open Monograph Press (OMP) | B82: 1 | C82: 1 | D82: 1 | E82: 1 | F82: 0 | G82: 0 | H82: 0 | I82: 1 | K82: 0 | L82: 5 | M82: Contribute funds; Contribute to code; Contribute to documentation; Contribute to education or training; Contribute to working groups or interest groups
A83: Open Preprint Systems (OPS) | B83: 1 | C83: 1 | D83: 1 | E83: 1 | F83: 0 | G83: 0 | H83: 0 | I83: 1 | K83: 0 | L83: 5 | M83: Contribute funds; Contribute to code; Contribute to documentation; Contribute to education or training; Contribute to working groups or interest groups
A84: Openverse | B84: 0 | C84: 0 | D84: 0 | E84: 0 | F84: 0 | G84: 0 | H84: 0 | I84: 0 | K84: 0 | L84: 0
A85: O Portal Brasileiro de Publicações e Dados Científicos em Acesso Aberto (The Brazilian Open Access Publications and Scientific Data Portal) (Oasisbr) | B85: 0 | C85: 0 | D85: 0 | E85: 0 | F85: 0 | G85: 0 | H85: 0 | I85: 0 | K85: 0 | L85: 0
A86: OSF (Open Science Framework) | B86: 1 | C86: 1 | D86: 1 | E86: 1 | F86: 0 | G86: 0 | H86: 0 | I86: 1 | K86: 0 | L86: 5 | M86: Contribute funds; Contribute to code; Contribute to documentation; Contribute to education or training; Contribute to working groups or interest groups
A87: Oxford Common File Layout | B87: 0 | C87: 1 | D87: 1 | E87: 1 | F87: 0 | G87: 0 | H87: 0 | I87: 0 | K87: 0 | L87: 3 | M87: Contribute to code; Contribute to documentation; Contribute to education or training
A88: Peer Community In | B88: 0 | C88: 0 | D88: 0 | E88: 0 | F88: 0 | G88: 0 | H88: 0 | I88: 0 | K88: 0 | L88: 0
A89: PKP Preservation Network | B89: 0 | C89: 0 | D89: 0 | E89: 0 | F89: 0 | G89: 0 | H89: 0 | I89: 0 | K89: 0 | L89: 0
A90: PREreview | B90: 1 | C90: 0 | D90: 1 | E90: 1 | F90: 0 | G90: 1 | H90: 1 | I90: 1 | J90: PREreview runs an annual Champions Program, more information here: https://prereview.org/trainings#prereview-champions-program | K90: 1 | L90: 7 | M90: Contribute funds; Contribute to documentation; Contribute to education or training; Contribute to peer reviews; Contribute to user research or user testing; Contribute to working groups or interest groups; Other
A91: Pressbooks | B91: 0 | C91: 1 | D91: 1 | E91: 1 | F91: 0 | G91: 0 | H91: 0 | I91: 0 | K91: 0 | L91: 3 | M91: Contribute to code; Contribute to documentation; Contribute to education or training
A92: Public Access Submission System | B92: 1 | C92: 1 | D92: 1 | E92: 0 | F92: 0 | G92: 0 | H92: 0 | I92: 1 | K92: 0 | L92: 4 | M92: Contribute funds; Contribute to code; Contribute to documentation; Contribute to working groups or interest groups
A93: Public Utility Data Liberation (PUDL) | B93: 0 | C93: 0 | D93: 0 | E93: 0 | F93: 0 | G93: 0 | H93: 0 | I93: 0 | K93: 0 | L93: 0
A94: PubPub | B94: 1 | C94: 1 | D94: 1 | E94: 0 | F94: 0 | G94: 0 | H94: 0 | I94: 1 | K94: 0 | L94: 4 | M94: Contribute funds; Contribute to code; Contribute to documentation; Contribute to working groups or interest groups
A95: Pundit | B95: 1 | C95: 1 | D95: 1 | E95: 1 | F95: 1 | G95: 0 | H95: 1 | I95: 1 | K95: 0 | L95: 7 | M95: Contribute funds; Contribute to code; Contribute to documentation; Contribute to education or training; Contribute to governance; Contribute to user research or user testing; Contribute to working groups or interest groups
A96: pyOpenSci | B96: 0 | C96: 0 | D96: 0 | E96: 0 | F96: 0 | G96: 0 | H96: 0 | I96: 0 | K96: 0 | L96: 0
A97: Renku | B97: 0 | C97: 1 | D97: 1 | E97: 1 | F97: 0 | G97: 0 | H97: 1 | I97: 0 | K97: 0 | L97: 4 | M97: Contribute to code; Contribute to documentation; Contribute to education or training; Contribute to user research or user testing
A98: RePEc | B98: 1 | C98: 1 | D98: 0 | E98: 0 | F98: 0 | G98: 0 | H98: 1 | I98: 0 | J98: Sponsor hardware, editor for alert service, contribute metadata | K98: 1 | L98: 4 | M98: Contribute funds; Contribute to code; Contribute to user research or user testing; Other
A99: Research Organization Registry (ROR) | B99: 1 | C99: 1 | D99: 1 | E99: 1 | F99: 0 | G99: 0 | H99: 0 | I99: 1 | K99: 0 | L99: 5 | M99: Contribute funds; Contribute to code; Contribute to documentation; Contribute to education or training; Contribute to working groups or interest groups
A100: Rogue Scholar | B100: 1 | C100: 1 | D100: 0 | E100: 1 | F100: 0 | G100: 0 | H100: 0 | I100: 0 | K100: 0 | L100: 3 | M100: Contribute funds; Contribute to code; Contribute to education or training
...

Sheet Calc
A1: Service | B1: E1 default | C1: E2 preliminary | D1: C1 preliminary | E1: C2 URL score | F1: C3 repository-field score | G1: N1 default | H1: E2 count | I1: C1 count | J1: C2 scoring note | K1: C3 scoring note | L1: Data flags
A2: 2i2c | B2: 100 | C2: 15.3846 | F2: 100 | G2: 100 | H2: 2 | I2: 0 | J2: None: Blank or suspect URL; review required | K2: 100.0: Available public-forge repository URL | L2: 938 coding requires reviewer confirmation; 019 scored from populated repository field; 043 evidence URL should be checked; not scored separately; 116 retained as source evidence only; not scored; 2 unavailable metric(s) scored as 0
A3: Academic Preservation Trust (APTrust) | B3: 100 | C3: 76.9231 | D3: 77.7778 | E3: 50 | F3: 100 | G3: 100 | H3: 10 | I3: 7 | J3: 50.0: Candidate general participation page; verify URL | K3: 100.0: Available public-forge repository URL | L3: 041 scored from available URL tier; 019 scored from populated repository field; 043 evidence URL should be checked; not scored separately; 116 retained as source evidence only; not scored
A4: AfricArXiv | B4: 33 | G4: 100 | H4: 0 | I4: 0 | J4: None: Blank or suspect URL; review required | K4: None: No repository URL supplied | L4: 043 evidence URL should be checked; not scored separately; 4 unavailable metric(s) scored as 0
A5: Arches Heritage Data Management Platform | B5: 100 | E5: 100 | F5: 100 | G5: 100 | H5: 0 | I5: 0 | J5: 100.0: Candidate dedicated contribution guide; verify URL | K5: 100.0: Available public-forge repository URL | L5: 041 scored from available URL tier; 019 scored from populated repository field; 043 evidence URL should be checked; not scored separately; 116 retained as source evidence only; not scored; 2 unavailable metric(s) scored as 0
A6: Archipelago Commons | B6: 100 | C6: 53.8462 | D6: 33.3333 | E6: 100 | F6: 100 | G6: 100 | H6: 7 | I6: 3 | J6: 100.0: Candidate dedicated contribution guide; verify URL | K6: 100.0: Available public-forge repository URL | L6: 938 coding requires reviewer confirmation; 041 scored from available URL tier; 019 scored from populated repository field; 043 evidence URL should be checked; not scored separately; 116 retained as source evidence only; not scored
A7: Archival Resource Key | B7: 100 | D7: 55.5556 | E7: 50 | F7: 100 | G7: 100 | H7: 0 | I7: 5 | J7: 50.0: Candidate general participation page; verify URL | K7: 100.0: Available public-forge repository URL | L7: 041 scored from available URL tier; 019 scored from populated repository field; 043 evidence URL should be checked; not scored separately; 116 retained as source evidence only; not scored; 1 unavailable metric(s) scored as 0
A8: Archivematica | B8: 100 | E8: 100 | F8: 100 | H8: 0 | I8: 0 | J8: 100.0: Candidate dedicated contribution guide; verify URL | K8: 100.0: Available public-forge repository URL | L8: 041 scored from available URL tier; 019 scored from populated repository field; 043 evidence URL should be checked; not scored separately; 116 retained as source evidence only; not scored; 3 unavailable metric(s) scored as 0
A9: ArchivesSpace | B9: 100 | C9: 69.2308 | E9: 100 | F9: 100 | G9: 100 | H9: 9 | I9: 0 | J9: 100.0: Candidate dedicated contribution guide; verify URL | K9: 100.0: Available public-forge repository URL | L9: 041 scored from available URL tier; 019 scored from populated repository field; 043 evidence URL should be checked; not scored separately; 116 retained as source evidence only; not scored; 1 unavailable metric(s) scored as 0
A10: ARGOS | B10: 100 | C10: 61.5385 | F10: 100 | G10: 100 | H10: 8 | I10: 0 | J10: None: Blank or suspect URL; review required | K10: 100.0: Available public-forge repository URL | L10: 019 scored from populated repository field; 043 evidence URL should be checked; not scored separately; 116 retained as source evidence only; not scored; 2 unavailable metric(s) scored as 0
A11: arXiv | B11: 100 | C11: 30.7692 | D11: 33.3333 | E11: 50 | F11: 100 | G11: 100 | H11: 4 | I11: 3 | J11: 50.0: Candidate general participation page; verify URL | K11: 100.0: Available public-forge repository URL | L11: 938 coding requires reviewer confirmation; 041 scored from available URL tier; 019 scored from populated repository field; 043 evidence URL should be checked; not scored separately
A12: AtoM | B12: 67 | F12: 100 | H12: 0 | I12: 0 | J12: None: Blank or suspect URL; review required | K12: 100.0: Available public-forge repository URL | L12: 041 scored from available URL tier; 019 scored from populated repository field; 043 evidence URL should be checked; not scored separately; 4 unavailable metric(s) scored as 0
A13: Avalon Media System | B13: 100 | C13: 38.4615 | D13: 66.6667 | E13: 50 | F13: 100 | G13: 100 | H13: 5 | I13: 6 | J13: 50.0: Candidate general participation page; verify URL | K13: 100.0: Available public-forge repository URL | L13: 041 scored from available URL tier; 019 scored from populated repository field; 043 evidence URL should be checked; not scored separately; 116 retained as source evidence only; not scored
A14: Biodiversity Heritage Library | B14: 100 | C14: 53.8462 | D14: 11.1111 | E14: 100 | F14: 100 | G14: 100 | H14: 7 | I14: 1 | J14: 100.0: Candidate dedicated contribution guide; verify URL | K14: 100.0: Available public-forge repository URL | L14: 041 scored from available URL tier; 019 scored from populated repository field; 043 evidence URL should be checked; not scored separately; 116 retained as source evidence only; not scored
A15: bioRxiv | B15: 100 | C15: 15.3846 | G15: 33 | H15: 2 | I15: 0 | J15: None: Blank or suspect URL; review required | K15: None: No repository URL supplied | L15: 938 coding requires reviewer confirmation; 3 unavailable metric(s) scored as 0
A16: BitCurator Environment | B16: 100 | C16: 53.8462 | D16: 55.5556 | E16: 50 | F16: 100 | G16: 100 | H16: 7 | I16: 5 | J16: 50.0: Candidate general participation page; verify URL | K16: 100.0: Available public-forge repository URL | L16: 041 scored from available URL tier; 019 scored from populated repository field; 043 evidence URL should be checked; not scored separately; 116 retained as source evidence only; not scored
A17: Blacklight | B17: 100 | C17: 69.2308 | D17: 77.7778 | E17: 100 | F17: 100 | G17: 67 | H17: 9 | I17: 7 | J17: 100.0: Candidate dedicated contribution guide; verify URL | K17: 100.0: Available public-forge repository URL | L17: 041 scored from available URL tier; 019 scored from populated repository field; 116 retained as source evidence only; not scored
A18: BrCRIS | B18: 67 | F18: 100 | G18: 100 | H18: 0 | I18: 0 | J18: None: Blank or suspect URL; review required | K18: 100.0: Available public-forge repository URL | L18: 019 scored from populated repository field; 043 evidence URL should be checked; not scored separately; 3 unavailable metric(s) scored as 0
A19: Browsertrix | B19: 100 | C19: 7.6923 | D19: 22.2222 | F19: 100 | G19: 100 | H19: 1 | I19: 2 | J19: None: Blank or suspect URL; review required | K19: 100.0: Available public-forge repository URL | L19: 019 scored from populated repository field; 043 evidence URL should be checked; not scored separately; 116 retained as source evidence only; not scored; 1 unavailable metric(s) scored as 0
A20: CLOCKSS | B20: 100 | F20: 100 | G20: 33 | H20: 0 | I20: 0 | J20: None: Blank or suspect URL; review required | K20: 100.0: Available public-forge repository URL | L20: 019 scored from populated repository field; 116 retained as source evidence only; not scored; 3 unavailable metric(s) scored as 0
A21: COAR International Repository Directory (IRD) | B21: 100 | C21: 30.7692 | D21: 22.2222 | E21: 50 | F21: 100 | G21: 67 | H21: 4 | I21: 2 | J21: 50.0: Candidate general participation page; verify URL | K21: 100.0: Available public-forge repository URL | L21: 041 scored from available URL tier; 019 scored from populated repository field; 116 retained as source evidence only; not scored
A22: COAR Notify | B22: 100 | C22: 38.4615 | D22: 55.5556 | E22: 50 | F22: 100 | G22: 33 | H22: 5 | I22: 5 | J22: 50.0: Candidate general participation page; verify URL | K22: 100.0: Available public-forge repository URL | L22: 041 scored from available URL tier; 019 scored from populated repository field; 116 retained as source evidence only; not scored
A23: CollectiveAccess | B23: 100 | E23: 50 | F23: 100 | H23: 0 | I23: 0 | J23: 50.0: Candidate general participation page; verify URL | K23: 100.0: Available public-forge repository URL | L23: 041 scored from available URL tier; 019 scored from populated repository field; 043 evidence URL should be checked; not scored separately; 116 retained as source evidence only; not scored; 3 unavailable metric(s) scored as 0
A24: CORE | B24: 100 | C24: 7.6923 | D24: 33.3333 | E24: 50 | F24: 100 | G24: 100 | H24: 1 | I24: 3 | J24: 50.0: Candidate general participation page; verify URL | K24: 100.0: Available public-forge repository URL | L24: 938 coding requires reviewer confirmation; 041 scored from available URL tier; 019 scored from populated repository field; 043 evidence URL should be checked; not scored separately; 116 retained as source evidence only; not scored
A25: COUNTER Code of Practice | B25: 100 | C25: 69.2308 | D25: 55.5556 | E25: 50 | F25: 50 | G25: 100 | H25: 9 | I25: 5 | J25: 50.0: Candidate general participation page; verify URL | K25: 50.0: Repository field populated on another/unspecified host | L25: 938 coding requires reviewer confirmation; 041 scored from available URL tier; 019 scored from populated repository field; 043 evidence URL should be checked; not scored separately; 116 retained as source evidence only; not scored
A26: Creative Commons Licenses | B26: 100 | C26: 30.7692 | D26: 33.3333 | E26: 100 | F26: 100 | G26: 100 | H26: 4 | I26: 3 | J26: 100.0: Candidate dedicated contribution guide; verify URL | K26: 100.0: Available public-forge repository URL | L26: 938 coding requires reviewer confirmation; 041 scored from available URL tier; 019 scored from populated repository field; 043 evidence URL should be checked; not scored separately
A27: Crossref Metadata Retrieval | B27: 100 | C27: 61.5385 | D27: 55.5556 | E27: 50 | F27: 100 | G27: 100 | H27: 8 | I27: 5 | J27: 50.0: Candidate general participation page; verify URL | K27: 100.0: Available public-forge repository URL | L27: 938 coding requires reviewer confirmation; 041 scored from available URL tier; 019 scored from populated repository field; 043 evidence URL should be checked; not scored separately; 116 retained as source evidence only; not scored
A28: D4Science Infrastructure | B28: 33 | F28: 50 | G28: 33 | H28: 0 | I28: 0 | J28: None: Blank or suspect URL; review required | K28: 50.0: Repository field populated on another/unspecified host | L28: 019 scored from populated repository field; 3 unavailable metric(s) scored as 0
A29: DART (Digital Archivist's Resource Tool) | B29: 100 | D29: 77.7778 | E29: 50 | F29: 100 | G29: 33 | H29: 0 | I29: 7 | J29: 50.0: Candidate general participation page; verify URL | K29: 100.0: Available public-forge repository URL | L29: 041 scored from available URL tier; 019 scored from populated repository field; 116 retained as source evidence only; not scored; 1 unavailable metric(s) scored as 0
A30: Database Information System | B30: 100 | C30: 53.8462 | D30: 11.1111 | F30: 100 | G30: 33 | H30: 7 | I30: 1 | J30: None: Blank or suspect URL; review required | K30: 100.0: Available public-forge repository URL | L30: 019 scored from populated repository field; 1 unavailable metric(s) scored as 0
A31: Data Citation Corpus | B31: 100 | C31: 46.1538 | D31: 11.1111 | E31: 100 | F31: 100 | G31: 0 | H31: 6 | I31: 1 | J31: 100.0: Candidate dedicated contribution guide; verify URL | K31: 100.0: Available public-forge repository URL | L31: 940 Other route requires reviewer confirmation; 041 scored from available URL tier; 019 scored from populated repository field; 116 retained as source evidence only; not scored
A32: DataCite | B32: 100 | C32: 7.6923 | D32: 33.3333 | E32: 50 | F32: 100 | G32: 100 | H32: 1 | I32: 3 | J32: 50.0: Candidate general participation page; verify URL | K32: 100.0: Available public-forge repository URL | L32: 938 coding requires reviewer confirmation; 041 scored from available URL tier; 019 scored from populated repository field; 043 evidence URL should be checked; not scored separately; 116 retained as source evidence only; not scored
A33: Data Stewardship Wizard | B33: 100 | C33: 76.9231 | D33: 55.5556 | E33: 100 | F33: 100 | G33: 100 | H33: 10 | I33: 5 | J33: 100.0: Candidate dedicated contribution guide; verify URL | K33: 100.0: Available public-forge repository URL | L33: 041 scored from available URL tier; 019 scored from populated repository field; 043 evidence URL should be checked; not scored separately; 116 retained as source evidence only; not scored
A34: Dataverse | B34: 100 | C34: 23.0769 | D34: 44.4444 | E34: 50 | F34: 100 | G34: 100 | H34: 3 | I34: 4 | J34: 50.0: Candidate general participation page; verify URL | K34: 100.0: Available public-forge repository URL | L34: 938 coding requires reviewer confirmation; 041 scored from available URL tier; 019 scored from populated repository field; 043 evidence URL should be checked; not scored separately; 116 retained as source evidence only; not scored
A35: DLCM Backend | B35: 100 | C35: 30.7692 | E35: 100 | F35: 50 | G35: 100 | H35: 4 | I35: 0 | J35: 100.0: Candidate dedicated contribution guide; verify URL | K35: 50.0: Repository field populated on another/unspecified host | L35: 041 scored from available URL tier; 019 scored from populated repository field; 043 evidence URL should be checked; not scored separately; 116 retained as source evidence only; not scored; 1 unavailable metric(s) scored as 0
A36: DLCM Portal | B36: 100 | C36: 30.7692 | E36: 100 | F36: 50 | G36: 100 | H36: 4 | I36: 0 | J36: 100.0: Candidate dedicated contribution guide; verify URL | K36: 50.0: Repository field populated on another/unspecified host | L36: 041 scored from available URL tier; 019 scored from populated repository field; 043 evidence URL should be checked; not scored separately; 116 retained as source evidence only; not scored; 1 unavailable metric(s) scored as 0
A37: DMP Tool | B37: 100 | C37: 61.5385 | F37: 100 | G37: 0 | H37: 8 | I37: 0 | J37: None: Blank or suspect URL; review required | K37: 100.0: Available public-forge repository URL | L37: 019 scored from populated repository field; 2 unavailable metric(s) scored as 0
A38: DOAJ (Directory of Open Access Journals) | B38: 100 | C38: 69.2308 | D38: 55.5556 | F38: 100 | G38: 100 | H38: 9 | I38: 5 | J38: None: Blank or suspect URL; review required | K38: 100.0: Available public-forge repository URL | L38: 938 coding requires reviewer confirmation; 940 Other route requires reviewer confirmation; 019 scored from populated repository field; 043 evidence URL should be checked; not scored separately; 1 unavailable metric(s) scored as 0
A39: dokieli | B39: 100 | C39: 15.3846 | D39: 44.4444 | E39: 50 | F39: 100 | G39: 100 | H39: 2 | I39: 4 | J39: 50.0: Candidate general participation page; verify URL | K39: 100.0: Available public-forge repository URL | L39: 938 coding requires reviewer confirmation; 041 scored from available URL tier; 019 scored from populated repository field; 043 evidence URL should be checked; not scored separately; 116 retained as source evidence only; not scored
A40: Dryad | B40: 100 | C40: 30.7692 | D40: 44.4444 | F40: 100 | G40: 100 | H40: 4 | I40: 4 | J40: None: Blank or suspect URL; review required | K40: 100.0: Available public-forge repository URL | L40: 938 coding requires reviewer confirmation; 019 scored from populated repository field; 043 evidence URL should be checked; not scored separately; 116 retained as source evidence only; not scored; 1 unavailable metric(s) scored as 0
A41: DSpace | B41: 100 | C41: 53.8462 | D41: 77.7778 | E41: 100 | F41: 100 | G41: 100 | H41: 7 | I41: 7 | J41: 100.0: Candidate dedicated contribution guide; verify URL | K41: 100.0: Available public-forge repository URL | L41: 938 coding requires reviewer confirmation; 041 scored from available URL tier; 019 scored from populated repository field; 043 evidence URL should be checked; not scored separately; 116 retained as source evidence only; not scored
A42: DuraCloud | B42: 100 | E42: 100 | F42: 100 | G42: 100 | H42: 0 | I42: 0 | J42: 100.0: Candidate dedicated contribution guide; verify URL | K42: 100.0: Available public-forge repository URL | L42: 041 scored from available URL tier; 019 scored from populated repository field; 043 evidence URL should be checked; not scored separately; 2 unavailable metric(s) scored as 0
A43: Episciences | B43: 67 | F43: 100 | G43: 33 | H43: 0 | I43: 0 | J43: None: Blank or suspect URL; review required | K43: 100.0: Available public-forge repository URL | L43: 019 scored from populated repository field; 3 unavailable metric(s) scored as 0
A44: EPrints | B44: 100 | F44: 100 | G44: 67 | H44: 0 | I44: 0 | J44: None: Blank or suspect URL; review required | K44: 100.0: Available public-forge repository URL | L44: 041 scored from available URL tier; 019 scored from populated repository field; 116 retained as source evidence only; not scored; 3 unavailable metric(s) scored as 0
A45: Érudit | B45: 100 | D45: 22.2222 | E45: 50 | F45: 100 | G45: 100 | H45: 0 | I45: 2 | J45: 50.0: Candidate general participation page; verify URL | K45: 100.0: Available public-forge repository URL | L45: 938 coding requires reviewer confirmation; 041 scored from available URL tier; 019 scored from populated repository field; 043 evidence URL should be checked; not scored separately; 116 retained as source evidence only; not scored; 1 unavailable metric(s) scored as 0
A46: Europe PMC | B46: 100 | C46: 53.8462 | D46: 33.3333 | E46: 50 | F46: 100 | G46: 100 | H46: 7 | I46: 3 | J46: 50.0: Candidate general participation page; verify URL | K46: 100.0: Available public-forge repository URL | L46: 938 coding requires reviewer confirmation; 041 scored from available URL tier; 019 scored from populated repository field; 043 evidence URL should be checked; not scored separately; 116 retained as source evidence only; not scored
A47: FAIR Wizard | B47: 100 | C47: 46.1538 | D47: 44.4444 | G47: 33 | H47: 6 | I47: 4 | J47: None: Blank or suspect URL; review required | K47: None: No repository URL supplied | L47: 940 Other route requires reviewer confirmation; 116 retained as source evidence only; not scored; 2 unavailable metric(s) scored as 0
A48: Fedora | B48: 100 | C48: 76.9231 | D48: 88.8889 | E48: 50 | F48: 100 | G48: 100 | H48: 10 | I48: 8 | J48: 50.0: Candidate general participation page; verify URL | K48: 100.0: Available public-forge repository URL | L48: 938 coding requires reviewer confirmation; 041 scored from available URL tier; 019 scored from populated repository field; 043 evidence URL should be checked; not scored separately; 116 retained as source evidence only; not scored
A49: fido | B49: 100 | C49: 61.5385 | D49: 33.3333 | E49: 50 | F49: 100 | G49: 33 | H49: 8 | I49: 3 | J49: 50.0: Candidate general participation page; verify URL | K49: 100.0: Available public-forge repository URL | L49: 041 scored from available URL tier; 019 scored from populated repository field; 116 retained as source evidence only; not scored
A50: Fulcrum | B50: 100 | C50: 30.7692 | D50: 22.2222 | F50: 100 | G50: 100 | H50: 4 | I50: 2 | J50: None: Blank or suspect URL; review required | K50: 100.0: Available public-forge repository URL | L50: 938 coding requires reviewer confirmation; 019 scored from populated repository field; 043 evidence URL should be checked; not scored separately; 1 unavailable metric(s) scored as 0
A51: Galaxy | B51: 100 | E51: 100 | F51: 100 | G51: 100 | H51: 0 | I51: 0 | J51: 100.0: Candidate dedicated contribution guide; verify URL | K51: 100.0: Available public-forge repository URL | L51: 041 scored from available URL tier; 019 scored from populated repository field; 043 evidence URL should be checked; not scored separately; 116 retained as source evidence only; not scored; 2 unavailable metric(s) scored as 0
A52: GeoServer | B52: 100 | C52: 46.1538 | D52: 11.1111 | E52: 100 | F52: 100 | G52: 100 | H52: 6 | I52: 1 | J52: 100.0: Candidate dedicated contribution guide; verify URL | K52: 100.0: Available public-forge repository URL | L52: 041 scored from available URL tier; 019 scored from populated repository field; 043 evidence URL should be checked; not scored separately; 116 retained as source evidence only; not scored
A53: Hyku | B53: 100 | C53: 69.2308 | D53: 66.6667 | E53: 50 | F53: 100 | G53: 100 | H53: 9 | I53: 6 | J53: 50.0: Candidate general participation page; verify URL | K53: 100.0: Available public-forge repository URL | L53: 938 coding requires reviewer confirmation; 041 scored from available URL tier; 019 scored from populated repository field; 043 evidence URL should be checked; not scored separately
A54: Hyrax | B54: 100 | C54: 69.2308 | D54: 77.7778 | E54: 50 | F54: 100 | G54: 100 | H54: 9 | I54: 7 | J54: 50.0: Candidate general participation page; verify URL | K54: 100.0: Available public-forge repository URL | L54: 041 scored from available URL tier; 019 scored from populated repository field; 043 evidence URL should be checked; not scored separately; 116 retained as source evidence only; not scored
A55: IIIF | B55: 100 | C55: 38.4615 | D55: 55.5556 | E55: 100 | F55: 100 | G55: 100 | H55: 5 | I55: 5 | J55: 100.0: Candidate dedicated contribution guide; verify URL | K55: 100.0: Available public-forge repository URL | L55: 938 coding requires reviewer confirmation; 041 scored from available URL tier; 019 scored from populated repository field; 043 evidence URL should be checked; not scored separately; 116 retained as source evidence only; not scored
A56: ImpactU | F56: 100 | H56: 0 | I56: 0 | J56: None: Blank or suspect URL; review required | K56: 100.0: Available public-forge repository URL | L56: 019 scored from populated repository field; 5 unavailable metric(s) scored as 0
A57: International Generic Sample Number (IGSN) | B57: 100 | F57: 100 | G57: 33 | H57: 0 | I57: 0 | J57: None: Blank or suspect URL; review required | K57: 100.0: Available public-forge repository URL | L57: 019 scored from populated repository field; 116 retained as source evidence only; not scored; 3 unavailable metric(s) scored as 0
A58: InvenioRDM | B58: 100 | C58: 7.6923 | D58: 55.5556 | E58: 100 | F58: 100 | G58: 100 | H58: 1 | I58: 5 | J58: 100.0: Candidate dedicated contribution guide; verify URL | K58: 100.0: Available public-forge repository URL | L58: 938 coding requires reviewer confirmation; 041 scored from available URL tier; 019 scored from populated repository field; 043 evidence URL should be checked; not scored separately
A59: iRODS | B59: 100 | C59: 76.9231 | D59: 77.7778 | E59: 100 | F59: 100 | G59: 100 | H59: 10 | I59: 7 | J59: 100.0: Candidate dedicated contribution guide; verify URL | K59: 100.0: Available public-forge repository URL | L59: 041 scored from available URL tier; 019 scored from populated repository field; 043 evidence URL should be checked; not scored separately; 116 retained as source evidence only; not scored
A60: Islandora | B60: 100 | C60: 84.6154 | D60: 77.7778 | E60: 50 | F60: 100 | G60: 100 | H60: 11 | I60: 7 | J60: 50.0: Candidate general participation page; verify URL | K60: 100.0: Available public-forge repository URL | L60: 938 coding requires reviewer confirmation; 041 scored from available URL tier; 019 scored from populated repository field; 043 evidence URL should be checked; not scored separately
A61: Janeway | B61: 67 | D61: 22.2222 | F61: 100 | G61: 100 | H61: 0 | I61: 2 | J61: None: Blank or suspect URL; review required | K61: 100.0: Available public-forge repository URL | L61: 938 coding requires reviewer confirmation; 041 scored from available URL tier; 019 scored from populated repository field; 043 evidence URL should be checked; not scored separately; 116 retained as source evidence only; not scored; 2 unavailable metric(s) scored as 0
A62: JHOVE | B62: 100 | C62: 69.2308 | E62: 50 | F62: 100 | G62: 67 | H62: 9 | I62: 0 | J62: 50.0: Candidate general participation page; verify URL | K62: 100.0: Available public-forge repository URL | L62: 041 scored from available URL tier; 019 scored from populated repository field; 116 retained as source evidence only; not scored; 1 unavailable metric(s) scored as 0
A63: LA Referencia | B63: 33 | F63: 100 | G63: 67 | H63: 0 | I63: 0 | J63: None: Blank or suspect URL; review required | K63: 100.0: Available public-forge repository URL | L63: 019 scored from populated repository field; 3 unavailable metric(s) scored as 0
A64: Manifold | B64: 100 | D64: 11.1111 | E64: 50 | F64: 100 | H64: 0 | I64: 1 | J64: 50.0: Candidate general participation page; verify URL | K64: 100.0: Available public-forge repository URL | L64: 938 coding requires reviewer confirmation; 041 scored from available URL tier; 019 scored from populated repository field; 2 unavailable metric(s) scored as 0
A65: medRxiv | B65: 100 | C65: 69.2308 | D65: 11.1111 | G65: 33 | H65: 9 | I65: 1 | J65: None: Blank or suspect URL; review required | K65: None: No repository URL supplied | L65: 938 coding requires reviewer confirmation; 2 unavailable metric(s) scored as 0
A66: Metadata Encoding and Transmission Standard (METS) | B66: 100 | C66: 15.3846 | D66: 44.4444 | E66: 50 | F66: 100 | G66: 0 | H66: 2 | I66: 4 | J66: 50.0: Candidate general participation page; verify URL | K66: 100.0: Available public-forge repository URL | L66: 041 scored from available URL tier; 019 scored from populated repository field; 116 retained as source evidence only; not scored
A67: Mirador | B67: 100 | C67: 23.0769 | D67: 44.4444 | E67: 50 | F67: 100 | G67: 100 | H67: 3 | I67: 4 | J67: 50.0: Candidate general participation page; verify URL | K67: 100.0: Available public-forge repository URL | L67: 938 coding requires reviewer confirmation; 041 scored from available URL tier; 019 scored from populated repository field; 043 evidence URL should be checked; not scored separately
A68: Mukurtu CMS | B68: 100 | C68: 7.6923 | D68: 22.2222 | E68: 50 | F68: 100 | G68: 67 | H68: 1 | I68: 2 | J68: 50.0: Candidate general participation page; verify URL | K68: 100.0: Available public-forge repository URL | L68: 938 coding requires reviewer confirmation; 041 scored from available URL tier; 019 scored from populated repository field
A69: MyCoRe | B69: 0 | E69: 100 | F69: 100 | H69: 0 | I69: 0 | J69: 100.0: Candidate dedicated contribution guide; verify URL | K69: 100.0: Available public-forge repository URL | L69: 041 scored from available URL tier; 019 scored from populated repository field; 043 evidence URL should be checked; not scored separately; 3 unavailable metric(s) scored as 0
A70: NumPy | B70: 100 | E70: 100 | F70: 100 | G70: 100 | H70: 0 | I70: 0 | J70: 100.0: Candidate dedicated contribution guide; verify URL | K70: 100.0: Available public-forge repository URL | L70: 041 scored from available URL tier; 019 scored from populated repository field; 043 evidence URL should be checked; not scored separately; 116 retained as source evidence only; not scored; 2 unavailable metric(s) scored as 0
A71: OA.Report | B71: 100 | F71: 100 | G71: 33 | H71: 0 | I71: 0 | J71: None: Blank or suspect URL; review required | K71: 100.0: Available public-forge repository URL | L71: 019 scored from populated repository field; 116 retained as source evidence only; not scored; 3 unavailable metric(s) scored as 0
A72: OA Switchboard | B72: 100 | C72: 30.7692 | D72: 55.5556 | E72: 100 | F72: 100 | G72: 100 | H72: 4 | I72: 5 | J72: 100.0: Candidate dedicated contribution guide; verify URL | K72: 100.0: Available public-forge repository URL | L72: 938 coding requires reviewer confirmation; 041 scored from available URL tier; 019 scored from populated repository field; 043 evidence URL should be checked; not scored separately
A73: Omeka | B73: 67 | D73: 22.2222 | E73: 50 | F73: 100 | G73: 100 | H73: 0 | I73: 2 | J73: 50.0: Candidate general participation page; verify URL | K73: 100.0: Available public-forge repository URL | L73: 938 coding requires reviewer confirmation; 041 scored from available URL tier; 019 scored from populated repository field; 043 evidence URL should be checked; not scored separately; 1 unavailable metric(s) scored as 0
A74: OpenAIRE Graph | B74: 100 | C74: 69.2308 | F74: 50 | G74: 100 | H74: 9 | I74: 0 | J74: None: Blank or suspect URL; review required | K74: 50.0: Repository field populated on another/unspecified host | L74: 019 scored from populated repository field; 043 evidence URL should be checked; not scored separately; 116 retained as source evidence only; not scored; 2 unavailable metric(s) scored as 0
A75: OpenAlex | B75: 100 | C75: 23.0769 | D75: 11.1111 | E75: 50 | F75: 100 | G75: 0 | H75: 3 | I75: 1 | J75: 50.0: Candidate general participation page; verify URL | K75: 100.0: Available public-forge repository URL | L75: 938 coding requires reviewer confirmation; 041 scored from available URL tier; 019 scored from populated repository field
A76: OpenAPC | B76: 100 | C76: 30.7692 | E76: 50 | F76: 100 | G76: 100 | H76: 4 | I76: 0 | J76: 50.0: Candidate general participation page; verify URL | K76: 100.0: Available public-forge repository URL | L76: 041 scored from available URL tier; 019 scored from populated repository field; 043 evidence URL should be checked; not scored separately; 116 retained as source evidence only; not scored; 1 unavailable metric(s) scored as 0
A77: OpenCitations | B77: 33 | C77: 53.8462 | D77: 55.5556 | E77: 50 | F77: 100 | G77: 100 | H77: 7 | I77: 5 | J77: 50.0: Candidate general participation page; verify URL | K77: 100.0: Available public-forge repository URL | L77: 041 scored from available URL tier; 019 scored from populated repository field; 043 evidence URL should be checked; not scored separately; 037 status conflicts with listed 038/938 activity; both scored independently
A78: openCost | B78: 100 | C78: 38.4615 | E78: 50 | F78: 100 | G78: 0 | H78: 5 | I78: 0 | J78: 50.0: Candidate general participation page; verify URL | K78: 100.0: Available public-forge repository URL | L78: 041 scored from available URL tier; 019 scored from populated repository field; 116 retained as source evidence only; not scored; 1 unavailable metric(s) scored as 0
A79: Open Data Editor | B79: 100 | C79: 30.7692 | D79: 11.1111 | E79: 100 | F79: 100 | G79: 100 | H79: 4 | I79: 1 | J79: 100.0: Candidate dedicated contribution guide; verify URL | K79: 100.0: Available public-forge repository URL | L79: 041 scored from available URL tier; 019 scored from populated repository field; 043 evidence URL should be checked; not scored separately; 116 retained as source evidence only; not scored
A80: OpenEdition | B80: 100 | C80: 23.0769 | D80: 11.1111 | F80: 100 | G80: 33 | H80: 3 | I80: 1 | J80: None: Blank or suspect URL; review required | K80: 100.0: Available public-forge repository URL | L80: 938 coding requires reviewer confirmation; 019 scored from populated repository field; 1 unavailable metric(s) scored as 0
A81: Open Journal Systems (OJS) | B81: 100 | C81: 30.7692 | D81: 55.5556 | E81: 100 | F81: 100 | G81: 100 | H81: 4 | I81: 5 | J81: 100.0: Candidate dedicated contribution guide; verify URL | K81: 100.0: Available public-forge repository URL | L81: 938 coding requires reviewer confirmation; 041 scored from available URL tier; 019 scored from populated repository field; 043 evidence URL should be checked; not scored separately
A82: Open Monograph Press (OMP) | B82: 100 | C82: 30.7692 | D82: 55.5556 | E82: 100 | F82: 100 | G82: 100 | H82: 4 | I82: 5 | J82: 100.0: Candidate dedicated contribution guide; verify URL | K82: 100.0: Available public-forge repository URL | L82: 938 coding requires reviewer confirmation; 041 scored from available URL tier; 019 scored from populated repository field; 043 evidence URL should be checked; not scored separately
A83: Open Preprint Systems (OPS) | B83: 100 | C83: 30.7692 | D83: 55.5556 | E83: 100 | F83: 100 | G83: 100 | H83: 4 | I83: 5 | J83: 100.0: Candidate dedicated contribution guide; verify URL | K83: 100.0: Available public-forge repository URL | L83: 938 coding requires reviewer confirmation; 041 scored from available URL tier; 019 scored from populated repository field; 043 evidence URL should be checked; not scored separately
A84: Openverse | B84: 100 | E84: 100 | F84: 100 | G84: 100 | H84: 0 | I84: 0 | J84: 100.0: Candidate dedicated contribution guide; verify URL | K84: 100.0: Available public-forge repository URL | L84: 041 scored from available URL tier; 019 scored from populated repository field; 043 evidence URL should be checked; not scored separately; 116 retained as source evidence only; not scored; 2 unavailable metric(s) scored as 0
A85: O Portal Brasileiro de Publicações e Dados Científicos em Acesso Aberto (The Brazilian Open Access Publications and Scientific Data Portal) (Oasisbr) | B85: 33 | F85: 100 | G85: 33 | H85: 0 | I85: 0 | J85: None: Blank or suspect URL; review required | K85: 100.0: Available public-forge repository URL | L85: 019 scored from populated repository field; 3 unavailable metric(s) scored as 0
A86: OSF (Open Science Framework) | B86: 100 | C86: 15.3846 | D86: 55.5556 | F86: 100 | G86: 100 | H86: 2 | I86: 5 | J86: None: Blank or suspect URL; review required | K86: 100.0: Available public-forge repository URL | L86: 938 coding requires reviewer confirmation; 041 scored from available URL tier; 019 scored from populated repository field; 043 evidence URL should be checked; not scored separately; 1 unavailable metric(s) scored as 0
A87: Oxford Common File Layout | B87: 0 | D87: 33.3333 | E87: 50 | F87: 100 | G87: 0 | H87: 0 | I87: 3 | J87: 50.0: Candidate general participation page; verify URL | K87: 100.0: Available public-forge repository URL | L87: 041 scored from available URL tier; 019 scored from populated repository field; 1 unavailable metric(s) scored as 0
A88: Peer Community In | B88: 100 | F88: 100 | G88: 100 | H88: 0 | I88: 0 | J88: None: Blank or suspect URL; review required | K88: 100.0: Available public-forge repository URL | L88: 938 coding requires reviewer confirmation; 019 scored from populated repository field; 043 evidence URL should be checked; not scored separately; 3 unavailable metric(s) scored as 0
A89: PKP Preservation Network | B89: 100 | E89: 100 | F89: 100 | G89: 100 | H89: 0 | I89: 0 | J89: 100.0: Candidate dedicated contribution guide; verify URL | K89: 100.0: Available public-forge repository URL | L89: 041 scored from available URL tier; 019 scored from populated repository field; 043 evidence URL should be checked; not scored separately; 116 retained as source evidence only; not scored; 2 unavailable metric(s) scored as 0
A90: PREreview | B90: 100 | C90: 84.6154 | D90: 77.7778 | E90: 50 | F90: 100 | G90: 100 | H90: 11 | I90: 7 | J90: 50.0: Candidate general participation page; verify URL | K90: 100.0: Available public-forge repository URL | L90: 938 coding requires reviewer confirmation; 940 Other route requires reviewer confirmation; 041 scored from available URL tier; 019 scored from populated repository field; 043 evidence URL should be checked; not scored separately; 116 retained as source evidence only; not scored
A91: Pressbooks | B91: 100 | C91: 15.3846 | D91: 33.3333 | F91: 100 | G91: 33 | H91: 2 | I91: 3 | J91: None: Blank or suspect URL; review required | K91: 100.0: Available public-forge repository URL | L91: 938 coding requires reviewer confirmation; 019 scored from populated repository field; 1 unavailable metric(s) scored as 0
A92: Public Access Submission System | B92: 67 | D92: 44.4444 | E92: 100 | F92: 100 | G92: 100 | H92: 0 | I92: 4 | J92: 100.0: Candidate dedicated contribution guide; verify URL | K92: 100.0: Available public-forge repository URL | L92: 041 scored from available URL tier; 019 scored from populated repository field; 043 evidence URL should be checked; not scored separately; 1 unavailable metric(s) scored as 0
A93: Public Utility Data Liberation (PUDL) | B93: 100 | C93: 61.5385 | E93: 100 | F93: 100 | G93: 100 | H93: 8 | I93: 0 | J93: 100.0: Candidate dedicated contribution guide; verify URL | K93: 100.0: Available public-forge repository URL | L93: 041 scored from available URL tier; 019 scored from populated repository field; 043 evidence URL should be checked; not scored separately; 116 retained as source evidence only; not scored; 1 unavailable metric(s) scored as 0
A94: PubPub | B94: 100 | C94: 30.7692 | D94: 44.4444 | E94: 50 | F94: 100 | G94: 100 | H94: 4 | I94: 4 | J94: 50.0: Candidate general participation page; verify URL | K94: 100.0: Available public-forge repository URL | L94: 938 coding requires reviewer confirmation; 041 scored from available URL tier; 019 scored from populated repository field; 043 evidence URL should be checked; not scored separately
A95: Pundit | B95: 33 | C95: 23.0769 | D95: 77.7778 | F95: 100 | G95: 0 | H95: 3 | I95: 7 | J95: None: Blank or suspect URL; review required | K95: 100.0: Available public-forge repository URL | L95: 019 scored from populated repository field; 037 status conflicts with listed 038/938 activity; both scored independently; 1 unavailable metric(s) scored as 0
A96: pyOpenSci | B96: 67 | E96: 100 | F96: 100 | G96: 100 | H96: 0 | I96: 0 | J96: 100.0: Candidate dedicated contribution guide; verify URL | K96: 100.0: Available public-forge repository URL | L96: 041 scored from available URL tier; 019 scored from populated repository field; 043 evidence URL should be checked; not scored separately; 2 unavailable metric(s) scored as 0
A97: Renku | B97: 100 | C97: 53.8462 | D97: 44.4444 | E97: 100 | F97: 100 | G97: 33 | H97: 7 | I97: 4 | J97: 100.0: Candidate dedicated contribution guide; verify URL | K97: 100.0: Available public-forge repository URL | L97: 041 scored from available URL tier; 019 scored from populated repository field; 116 retained as source evidence only; not scored
A98: RePEc | B98: 100 | C98: 30.7692 | D98: 44.4444 | F98: 100 | G98: 0 | H98: 4 | I98: 4 | J98: None: Blank or suspect URL; review required | K98: 100.0: Available public-forge repository URL | L98: 940 Other route requires reviewer confirmation; 019 scored from populated repository field; 116 retained as source evidence only; not scored; 1 unavailable metric(s) scored as 0
A99: Research Organization Registry (ROR) | B99: 100 | C99: 76.9231 | D99: 55.5556 | E99: 100 | F99: 100 | G99: 100 | H99: 10 | I99: 5 | J99: 100.0: Candidate dedicated contribution guide; verify URL | K99: 100.0: Available public-forge repository URL | L99: 938 coding requires reviewer confirmation; 041 scored from available URL tier; 019 scored from populated repository field; 043 evidence URL should be checked; not scored separately; 116 retained as source evidence only; not scored
A100: Rogue Scholar | B100: 67 | D100: 33.3333 | F100: 100 | G100: 33 | H100: 0 | I100: 3 | J100: None: Blank or suspect URL; review required | K100: 100.0: Available public-forge repository URL | L100: 041 scored from available URL tier; 019 scored from populated repository field; 2 unavailable metric(s) scored as 0
...

Sheet Review Queue
A1: Service | B1: Review item | C1: Source value / coded proposal | D1: Reviewer decision | E1: Reviewer notes
A2: 2i2c | B2: 938 free-text activity coding | C2: <p>There are a lot of different kinds of communities we might use to answer this, but here are some relevant pages for a few key types of communities.</p> <p>Our key stakeholders page defines the types of communities we aim to serve: <a href="https://compass.2i2c.org/organization/mission/">https://compass.2i2c.org/organization/mission/</a></p> <p>Our shared responsibility model page describes the kinds of roles that exist in the service and how we aim to share them with communities: <a href="https://docs.2i2c.org/about/service/">https://docs.2i2c.org/about/service/</a></p> <p>Our Open Source Strategy section describes the approach we take towards engaging with and supporting OS communities: <a href="https://compass.2i2c.org/open-source/">https://compass.2i2c.org/open-source/</a></p> <p>All of these are continually evolving, but are a good first start. See also calendars and meetings: <a href="https://compass.2i2c.org/reference/calendar/">https://compass.2i2c.org/reference/calendar/</a></p> We take a lot of inspiration from the Principles of Open Scholarly Infrastructure, though we have not formally audited ourselves in comparison to those criteria. This is something we'd love to do, just haven't had time yet (and feel like an external org should do the auditing, not us). | D2: Community calls; Interest, working, user, or advisory groups | E2: Confirm or correct categories; add valid Other only if distinct from the 12 named types.
A3: 2i2c | B3: 019 public repository | C3: https://github.com/2i2c-org/infrastructure | D3: 100.0: Available public-forge repository URL | E3: Scored from the populated repository field; inspect only if the URL or host classification is clearly malformed.
A4: 2i2c | B4: 043 Code of Conduct evidence | C4: https://compass.2i2c.org/code-of-conduct/ | D4: Evidence only | E4: Check whether the linked policy applies to this community; do not score URL separately.
A5: Academic Preservation Trust (APTrust) | B5: 041 contribution guidance URL | C5: https://aptrust.org/resources/working-groups/ | D5: 50.0: Candidate general participation page; verify URL | E5: Scored from the available URL; inspect only if the URL appears suspect or the automatic tier is inaccurate.
A6: Academic Preservation Trust (APTrust) | B6: 019 public repository | C6: https://github.com/APTrust/registry | D6: 100.0: Available public-forge repository URL | E6: Scored from the populated repository field; inspect only if the URL or host classification is clearly malformed.
A7: Academic Preservation Trust (APTrust) | B7: 043 Code of Conduct evidence | C7: https://www.diglib.org/about/code-of-conduct/ | D7: Evidence only | E7: Check whether the linked policy applies to this community; do not score URL separately.
A8: AfricArXiv | B8: 043 Code of Conduct evidence | C8: https://access2perspectives.org/code-of-conduct/ | D8: Evidence only | E8: Check whether the linked policy applies to this community; do not score URL separately.
A9: Arches Heritage Data Management Platform | B9: 041 contribution guidance URL | C9: https://github.com/archesproject/arches/blob/master/CONTRIBUTING.md | D9: 100.0: Candidate dedicated contribution guide; verify URL | E9: Scored from the available URL; inspect only if the URL appears suspect or the automatic tier is inaccurate.
A10: Arches Heritage Data Management Platform | B10: 019 public repository | C10: https://github.com/archesproject | D10: 100.0: Available public-forge repository URL | E10: Scored from the populated repository field; inspect only if the URL or host classification is clearly malformed.
A11: Arches Heritage Data Management Platform | B11: 043 Code of Conduct evidence | C11: https://www.archesproject.org/code-of-conduct/ | D11: Evidence only | E11: Check whether the linked policy applies to this community; do not score URL separately.
A12: Archipelago Commons | B12: 938 free-text activity coding | C12: <p>Questions, use cases, and ideas can be shared with the Archipelago Google Groups forum and on the Archipelago Commons Slack Channel.</p> <p>Stakeholders are also invited to visit, subscribe to, and participate in various active GitHub repositories.</p> | D12: Interest, working, user, or advisory groups; Mailing lists and discussion forums (including Slack) | E12: Confirm or correct categories; add valid Other only if distinct from the 12 named types.
... A109: Dryad | B109: 043 Code of Conduct evidence | C109: https://datadryad.org/stash/code_of_conduct | D109: Evidence only | E109: Check whether the linked policy applies to this community; do not score URL separately.
A110: DSpace | B110: 938 free-text activity coding | C110: COAR Next Generation Repositories Principles <a href="https://ngr.coar-repositories.org/principles/" target="_blank">https://ngr.coar-repositories.org/principles/</a> | E110: Confirm or correct categories; add valid Other only if distinct from the 12 named types.
A111: DSpace | B111: 041 contribution guidance URL | C111: https://dspace.org/community-contributors/ | D111: 100.0: Candidate dedicated contribution guide; verify URL | E111: Scored from the available URL; inspect only if the URL appears suspect or the automatic tier is inaccurate.
A112: DSpace | B112: 019 public repository | C112: https://github.com/DSpace/DSpace | D112: 100.0: Available public-forge repository URL | E112: Scored from the populated repository field; inspect only if the URL or host classification is clearly malformed.
A113: DSpace | B113: 043 Code of Conduct evidence | C113: https://www.lyrasis.org/about/Pages/Code-of-Conduct.aspx | D113: Evidence only | E113: Check whether the linked policy applies to this community; do not score URL separately.
A114: DuraCloud | B114: 041 contribution guidance URL | C114: https://github.com/duracloud/duracloud/blob/develop/CONTRIBUTING.md | D114: 100.0: Candidate dedicated contribution guide; verify URL | E114: Scored from the available URL; inspect only if the URL appears suspect or the automatic tier is inaccurate.
A115: DuraCloud | B115: 019 public repository | C115: https://github.com/duracloud/duracloud | D115: 100.0: Available public-forge repository URL | E115: Scored from the populated repository field; inspect only if the URL or host classification is clearly malformed.
A116: DuraCloud | B116: 043 Code of Conduct evidence | C116: https://lyrasis.org/code-of-conduct/ | D116: Evidence only | E116: Check whether the linked policy applies to this community; do not score URL separately.
A117: Episciences | B117: 019 public repository | C117: https://github.com/CCSDForge/episciences | D117: 100.0: Available public-forge repository URL | E117: Scored from the populated repository field; inspect only if the URL or host classification is clearly malformed.
A118: EPrints | B118: 041 contribution guidance URL | C118: https://wiki.eprints.org/w/Main_Page#Contributing_to_the_Wiki; | D118: None: Blank or suspect URL; review required | E118: Scored from the available URL; inspect only if the URL appears suspect or the automatic tier is inaccurate.
A119: EPrints | B119: 019 public repository | C119: https://github.com/eprints/eprints3.4 | D119: 100.0: Available public-forge repository URL | E119: Scored from the populated repository field; inspect only if the URL or host classification is clearly malformed.
A120: Érudit | B120: 938 free-text activity coding | C120: DORA, Dimensions charter, Helsinki initiative | E120: Confirm or correct categories; add valid Other only if distinct from the 12 named types.
A121: Érudit | B121: 041 contribution guidance URL | C121: https://www.erudit.org/public/documents/TOR_CoalitionPublica_Journal%20User%20Group.pdf | D121: 50.0: Candidate general participation page; verify URL | E121: Scored from the available URL; inspect only if the URL appears suspect or the automatic tier is inaccurate.
A122: Érudit | B122: 019 public repository | C122: https://github.com/erudit/eruditorg | D122: 100.0: Available public-forge repository URL | E122: Scored from the populated repository field; inspect only if the URL or host classification is clearly malformed.
A123: Érudit | B123: 043 Code of Conduct evidence | C123: https://www.erudit.org/public/documents/CoalitionPublica_bilingue.pdf | D123: Evidence only | E123: Check whether the linked policy applies to this community; do not score URL separately.
A124: Europe PMC | B124: 938 free-text activity coding | C124: Dedicated staff for community outreach and engagement. Regular events and webinars with recordings openly available to the community. Developer forum for programmatic users. Strong user research program that includes insights from different stakeholder groups and informs the service roadmap. Free outreach resources available on a dedicated website page (<a href="https://europepmc.org/Outreach" target="_blank">https://europepmc.org/Outreach</a>). Europe PMC conducted a POSI self-audit in 2022: <a href="http://blog.europepmc.org/2022/02/EPMC-adopts-POSI.html" target="_blank">http://blog.europepmc.org/2022/02/EPMC-adopts-POSI.html</a> | D124: Blogs; Conference participation; Interest, working, user, or advisory groups; Mailing lists and discussion forums (including Slack); Staff roles with responsibility for community engagement; User research; Webinars and training | E124: Confirm or correct categories; add valid Other only if distinct from the 12 named types.
A125: Europe PMC | B125: 041 contribution guidance URL | C125: https://europepmc.org/Outreach | D125: 50.0: Candidate general participation page; verify URL | E125: Scored from the available URL; inspect only if the URL appears suspect or the automatic tier is inaccurate.
A126: Europe PMC | B126: 019 public repository | C126: https://github.com/EuropePMC | D126: 100.0: Available public-forge repository URL | E126: Scored from the populated repository field; inspect only if the URL or host classification is clearly malformed.
A127: Europe PMC | B127: 043 Code of Conduct evidence | C127: https://www.embl.org/about/info/course-and-conference-office/information-for-participants/code-of-conduct/ | D127: Evidence only | E127: Check whether the linked policy applies to this community; do not score URL separately.
A128: FAIR Wizard | B128: 940 Other contribution route | C128: Content creation | D128: Other | E128: Confirm this is selected in 040 and describes a distinct route.
A129: Fedora | B129: 938 free-text activity coding | C129: Fedora maintains active engagement of its community members through the following activities: <ul> <li>Weekly open tech meetings to foster technical conversations, provide support and discuss development objectives <li>Maintenance of a community Slack with designated channels for targeted discussion <li>Monthly newsletter to keep the community informed on current initiatives, priorities and opportunities to engage <li>Annual virtual conference-style event to bring users together to showcase and discuss current work </ul> <a href="https://wiki.lyrasis.org/display/FF/Fedora+Repository+Home" target="_blank">https://wiki.lyrasis.org/display/FF/Fedora+Repository+Home</a> Currently investigating POSI (Principles for Open Scholarly Infrastructure). | D129: Community calls; Conference participation; Mailing lists and discussion forums (including Slack) | E129: Confirm or correct categories; add valid Other only if distinct from the 12 named types.
A130: Fedora | B130: 041 contribution guidance URL | C130: https://wiki.lyrasis.org/display/FF/Developer+Resources | D130: 50.0: Candidate general participation page; verify URL | E130: Scored from the available URL; inspect only if the URL appears suspect or the automatic tier is inaccurate.
A131: Fedora | B131: 019 public repository | C131: https://github.com/fcrepo/fcrepo | D131: 100.0: Available public-forge repository URL | E131: Scored from the populated repository field; inspect only if the URL or host classification is clearly malformed.
A132: Fedora | B132: 043 Code of Conduct evidence | C132: https://www.lyrasis.org/about/Pages/Code-of-Conduct.aspx | D132: Evidence only | E132: Check whether the linked policy applies to this community; do not score URL separately.
... A167: Islandora | B167: 043 Code of Conduct evidence | C167: https://www.islandora.ca/code-of-conduct | D167: Evidence only | E167: Check whether the linked policy applies to this community; do not score URL separately.
A168: Janeway | B168: 938 free-text activity coding | C168: We are planning to complete a POSI evaluation. | E168: Confirm or correct categories; add valid Other only if distinct from the 12 named types.
A169: Janeway | B169: 041 contribution guidance URL | C169: https://discord.com/invite/MdPpd4cSTC | D169: None: Blank or suspect URL; review required | E169: Scored from the available URL; inspect only if the URL appears suspect or the automatic tier is inaccurate.
A170: Janeway | B170: 019 public repository | C170: https://github.com/birkbeckctp/ | D170: 100.0: Available public-forge repository URL | E170: Scored from the populated repository field; inspect only if the URL or host classification is clearly malformed.
A171: Janeway | B171: 043 Code of Conduct evidence | C171: https://github.com/BirkbeckCTP/janeway/blob/master/CODE_OF_CONDUCT.md | D171: Evidence only | E171: Check whether the linked policy applies to this community; do not score URL separately.
A172: JHOVE | B172: 041 contribution guidance URL | C172: https://jhove.openpreservation.org/about/ | D172: 50.0: Candidate general participation page; verify URL | E172: Scored from the available URL; inspect only if the URL appears suspect or the automatic tier is inaccurate.
A173: JHOVE | B173: 019 public repository | C173: https://github.com/openpreserve/jhove | D173: 100.0: Available public-forge repository URL | E173: Scored from the populated repository field; inspect only if the URL or host classification is clearly malformed.
A174: LA Referencia | B174: 019 public repository | C174: https://github.com/lareferencia | D174: 100.0: Available public-forge repository URL | E174: Scored from the populated repository field; inspect only if the URL or host classification is clearly malformed.
A175: Manifold | B175: 938 free-text activity coding | C175: Multiple <a href="https://manifoldapp.org/community" target="_blank">communication channels</a> | E175: Confirm or correct categories; add valid Other only if distinct from the 12 named types.
A176: Manifold | B176: 041 contribution guidance URL | C176: https://manifoldscholar.github.io/manifold-docusaurus/docs/developers/local_development | D176: 50.0: Candidate general participation page; verify URL | E176: Scored from the available URL; inspect only if the URL appears suspect or the automatic tier is inaccurate.
A177: Manifold | B177: 019 public repository | C177: https://github.com/ManifoldScholar/manifold | D177: 100.0: Available public-forge repository URL | E177: Scored from the populated repository field; inspect only if the URL or host classification is clearly malformed.
A178: medRxiv | B178: 938 free-text activity coding | C178: medRxiv Affiliates are members of the life sciences community who provide feedback on the service, act as advocates, and help in screening material submitted. Integrated the FAST principles for preprint peer review into our <a href="https://connect.medrxiv.org/news/2022/03/21/commenting_on_preprints" target="_blank">commenting policy</a>. Participation in development of publishing metadata standards | D178: User research; Volunteer or ambassador network | E178: Confirm or correct categories; add valid Other only if distinct from the 12 named types.
A179: Metadata Encoding and Transmission Standard (METS) | B179: 041 contribution guidance URL | C179: https://github.com/mets/wiki/wiki/Board-Membership-Criteria-&-Procedures | D179: 50.0: Candidate general participation page; verify URL | E179: Scored from the available URL; inspect only if the URL appears suspect or the automatic tier is inaccurate.
A180: Metadata Encoding and Transmission Standard (METS) | B180: 019 public repository | C180: https://github.com/mets | D180: 100.0: Available public-forge repository URL | E180: Scored from the populated repository field; inspect only if the URL or host classification is clearly malformed.
A181: Mirador | B181: 938 free-text activity coding | C181: <p>Mirador's development, design, and maintenance is driven by community needs and ongoing feedback and discussion. Join us at our regularly scheduled <a href="https://stanford.zoom.us/j/92780284062?pwd=Znp3TlJQUWZQZ2d1cG1hQUJLbS8ydz09 target="_blank">community calls</a> or review the <a href="https://docs.google.com/document/d/1wWozmLxUsN7QRWzekiIMjjuShhDIsJw0P0lIaiARSa8/edit" target="_blank">call notes</a>, on IIIF slack or the iiif-discuss mailing list. To suggest features, report bugs, and clarify usage, submit a GitHub issue.</p> <p><li>Slack channels within IIIF organization #mirador and #mirador-dev</li> <li><a href="https://github.com/ProjectMirador/mirador/discussions" target="_blank">Github</a></li> <li><a href="https://groups.google.com/g/iiif-discuss" target="_blank">IIIF Google group discussion</a></li></p> | D181: Community calls; Mailing lists and discussion forums (including Slack); User research | E181: Confirm or correct categories; add valid Other only if distinct from the 12 named types.
A182: Mirador | B182: 041 contribution guidance URL | C182: https://github.com/ProjectMirador/mirador/discussions | D182: 50.0: Candidate general participation page; verify URL | E182: Scored from the available URL; inspect only if the URL appears suspect or the automatic tier is inaccurate.
A183: Mirador | B183: 019 public repository | C183: https://github.com/projectmirador/mirador | D183: 100.0: Available public-forge repository URL | E183: Scored from the populated repository field; inspect only if the URL or host classification is clearly malformed.
A184: Mirador | B184: 043 Code of Conduct evidence | C184: https://github.com/ProjectMirador/mirador/blob/master/CODE_OF_CONDUCT.md | D184: Evidence only | E184: Check whether the linked policy applies to this community; do not score URL separately.
A185: Mukurtu CMS | B185: 938 free-text activity coding | C185: Regional Mukurtu Hubs are centers for support, development, and deployment of Mukurtu CMS to Community Spokes and other interested individuals and organizations in their areas. While the core Mukurtu team continues to provide support to anyone interested in Mukurtu, the Hubs take on local support and outreach wherever possible using their existing connections and regional expertise. https://mukurtu.org/mukurtu-hubs-and-spokes/. Staff dedicated to support and community engagement. <li><a href="https://www2.nau.edu/libnap-p/" target="_blank">Protocols for Native American Archival Materials</a></li> <li><a href="https://datascience.codata.org/articles/10.5334/dsj-2020-043" target="_blank">The CARE Principles for Indigenous Data Governance</a></li> | D185: Staff roles with responsibility for community engagement | E185: Confirm or correct categories; add valid Other only if distinct from the 12 named types.
A186: Mukurtu CMS | B186: 041 contribution guidance URL | C186: https://github.com/MukurtuCMS/mukurtucms#developers | D186: 50.0: Candidate general participation page; verify URL | E186: Scored from the available URL; inspect only if the URL appears suspect or the automatic tier is inaccurate.
A187: Mukurtu CMS | B187: 019 public repository | C187: https://github.com/MukurtuCMS/mukurtucms | D187: 100.0: Available public-forge repository URL | E187: Scored from the populated repository field; inspect only if the URL or host classification is clearly malformed.
... A198: OA Switchboard | B198: 043 Code of Conduct evidence | C198: https://www.oaswitchboard.org/governance | D198: Evidence only | E198: Check whether the linked policy applies to this community; do not score URL separately.
A199: Omeka | B199: 938 free-text activity coding | C199: <p>The Omeka Team welcomes contributions from the community. Given the wide varity of skills and areas of interest among the Omeka community, the paths to possible engagement are many. See <a href="https://omeka.org/about/community/" target="_blank">https://omeka.org/about/community/ </a> <p>The Omeka Team's engagement with the community is governed by <a href="https://digitalscholar.org/assets/downloads/Corporation%20for%20Digital%20Scholarship%20%E2%80%93%20Governance%20Policies.pdf">Digital Scholar's Anti-Discrimination policy</a>. | E199: Confirm or correct categories; add valid Other only if distinct from the 12 named types.
A200: Omeka | B200: 041 contribution guidance URL | C200: https://forum.omeka.org/faq | D200: 50.0: Candidate general participation page; verify URL | E200: Scored from the available URL; inspect only if the URL appears suspect or the automatic tier is inaccurate.
A201: Omeka | B201: 019 public repository | C201: https://github.com/omeka | D201: 100.0: Available public-forge repository URL | E201: Scored from the populated repository field; inspect only if the URL or host classification is clearly malformed.
A202: Omeka | B202: 043 Code of Conduct evidence | C202: https://forum.omeka.org/faq | D202: Evidence only | E202: Check whether the linked policy applies to this community; do not score URL separately.
A203: OpenAIRE Graph | B203: 019 public repository | C203: https://code-repo.d4science.org/D-Net/dnet-hadoop | D203: 50.0: Repository field populated on another/unspecified host | E203: Scored from the populated repository field; inspect only if the URL or host classification is clearly malformed.
A204: OpenAIRE Graph | B204: 043 Code of Conduct evidence | C204: https://openaire.flarum.cloud/p/2-guidelines | D204: Evidence only | E204: Check whether the linked policy applies to this community; do not score URL separately.
A205: OpenAlex | B205: 938 free-text activity coding | C205: <li><a href="https://openalex.org/webinars" target="_blank">Webinars</a></li> <li><a href="https://groups.google.com/g/openalex-users" target="_blank">user group</a></li> <li><a href="https://twitter.com/openalex_org" target="_blank">Twitter</a></li> <li><a href="https://mastodon.social/@OpenAlex" target="_blank">Mastodon</a></li> <a href="https://blog.ourresearch.org/posi/" target="_blank">POSI self-audit</a> | D205: Interest, working, user, or advisory groups; Social media; Webinars and training | E205: Confirm or correct categories; add valid Other only if distinct from the 12 named types.
A206: OpenAlex | B206: 041 contribution guidance URL | C206: https://groups.google.com/g/openalex-users?pli=1 | D206: 50.0: Candidate general participation page; verify URL | E206: Scored from the available URL; inspect only if the URL appears suspect or the automatic tier is inaccurate.
A207: OpenAlex | B207: 019 public repository | C207: https://github.com/ourresearch | D207: 100.0: Available public-forge repository URL | E207: Scored from the populated repository field; inspect only if the URL or host classification is clearly malformed.
A208: OpenAPC | B208: 041 contribution guidance URL | C208: https://github.com/OpenAPC/openapc-de/wiki/Data-Submission-Handout | D208: 50.0: Candidate general participation page; verify URL | E208: Scored from the available URL; inspect only if the URL appears suspect or the automatic tier is inaccurate.
A209: OpenAPC | B209: 019 public repository | C209: https://github.com/OpenAPC/openapc-de | D209: 100.0: Available public-forge repository URL | E209: Scored from the populated repository field; inspect only if the URL or host classification is clearly malformed.
A210: OpenAPC | B210: 043 Code of Conduct evidence | C210: https://github.com/OpenAPC/openapc-de/blob/master/CONDUCT.md | D210: Evidence only | E210: Check whether the linked policy applies to this community; do not score URL separately.
A211: OpenCitations | B211: 041 contribution guidance URL | C211: https://opencitations.net/wp-content/uploads/pdf/membership.pdf | D211: 50.0: Candidate general participation page; verify URL | E211: Scored from the available URL; inspect only if the URL appears suspect or the automatic tier is inaccurate.
... A242: Oxford Common File Layout | B242: 019 public repository | C242: https://github.com/OCFL/spec | D242: 100.0: Available public-forge repository URL | E242: Scored from the populated repository field; inspect only if the URL or host classification is clearly malformed.
A243: Peer Community In | B243: 938 free-text activity coding | C243: <p>PCI is member of the Free Journal Network and adheres to its <a href="https://www.fairopenaccess.org/the-fair-open-access-principles/" target="_blank">FAIR Open Access principles</a>.</p> <p>PCI is signatory of the <a href="https://c4disc.org/joint-statement-of-principles/" target="_blank">Joint Statement of Principles of the Coalition for Diversity and Inclusion in Scholarly Communication (C4DISC)</a> .</p> <p>PCI is signatory of <a href="https://sfdora.org/signers/?_signers_keyword=peer%20community%20in" target="_blank">DORA</a>.</p> <p>PCI has completed a <a href="https://peercommunityin.org/2024/04/11/posi/" target="_blank">POSI self-assessment</a>.</p> | E243: Confirm or correct categories; add valid Other only if distinct from the 12 named types.
A244: Peer Community In | B244: 019 public repository | C244: https://github.com/pci-dev | D244: 100.0: Available public-forge repository URL | E244: Scored from the populated repository field; inspect only if the URL or host classification is clearly malformed.
A245: Peer Community In | B245: 043 Code of Conduct evidence | C245: https://peercommunityin.org/2022/12/21/pci-code-of-conduct/ | D245: Evidence only | E245: Check whether the linked policy applies to this community; do not score URL separately.
A246: PKP Preservation Network | B246: 041 contribution guidance URL | C246: https://pkp.sfu.ca/community/members/contribute/ | D246: 100.0: Candidate dedicated contribution guide; verify URL | E246: Scored from the available URL; inspect only if the URL appears suspect or the automatic tier is inaccurate.
A247: PKP Preservation Network | B247: 019 public repository | C247: https://github.com/pkp/pln | D247: 100.0: Available public-forge repository URL | E247: Scored from the populated repository field; inspect only if the URL or host classification is clearly malformed.
A248: PKP Preservation Network | B248: 043 Code of Conduct evidence | C248: https://pkp.sfu.ca/code/ | D248: Evidence only | E248: Check whether the linked policy applies to this community; do not score URL separately.
A249: PREreview | B249: 938 free-text activity coding | C249: <p>Trainings. Our Open Reviewers trainings address the lack of peer-review training by engaging reviewers in discussions on process challenges, personal and structural biases, and self-reflection. Participants gain strategies and tools for providing clear, constructive feedback to manuscripts.</p> <p>Champions. The Champions Program equips researchers to promote open preprint review globally. Each year, selected participants engage in activities to increase research community involvement in open peer review, supported by resources and training.</p> <p>Live Reviews. These topic-centered, interactive preprint review calls are open to anyone bringing a collaborative approach. Facilitated by the PREreview team, Live Reviews model respectful, constructive peer-review practices. Outputs are published on PREreview.org, enhancing manuscripts and supporting journal review workflows.</p> | D249: Mailing lists and discussion forums (including Slack); User research; Volunteer or ambassador network; Webinars and training | E249: Confirm or correct categories; add valid Other only if distinct from the 12 named types.
A250: PREreview | B250: 940 Other contribution route | C250: PREreview runs an annual Champions Program, more information here: https://prereview.org/trainings#prereview-champions-program | D250: Other | E250: Confirm this is selected in 040 and describes a distinct route.
A251: PREreview | B251: 041 contribution guidance URL | C251: https://prereview.org/how-to-use | D251: 50.0: Candidate general participation page; verify URL | E251: Scored from the available URL; inspect only if the URL appears suspect or the automatic tier is inaccurate.
A252: PREreview | B252: 019 public repository | C252: https://github.com/PREreview/prereview.org | D252: 100.0: Available public-forge repository URL | E252: Scored from the populated repository field; inspect only if the URL or host classification is clearly malformed.
A253: PREreview | B253: 043 Code of Conduct evidence | C253: https://prereview.org/code-of-conduct | D253: Evidence only | E253: Check whether the linked policy applies to this community; do not score URL separately.
A254: Pressbooks | B254: 938 free-text activity coding | C254: We have demonstrated a deep commitment to the principles of open since our founding back in 2011, and we have surely signed a few charters/declarations over the years, but in the end we've just focused on doing the work of providing a platform for open creation, for more than a decade and we hope to continue. <li> present (and often sponsor) as many OER events/conferences as we can afford <li> monthly open client / product meetings | D254: Community calls; Conference participation | E254: Confirm or correct categories; add valid Other only if distinct from the 12 named types.
A255: Pressbooks | B255: 019 public repository | C255: https://github.com/pressbooks | D255: 100.0: Available public-forge repository URL | E255: Scored from the populated repository field; inspect only if the URL or host classification is clearly malformed.
... A299: VIVO | B299: 019 public repository | C299: https://github.com/vivo-project | D299: 100.0: Available public-forge repository URL | E299: Scored from the populated repository field; inspect only if the URL or host classification is clearly malformed.
A300: VuFind® | B300: 938 free-text activity coding | C300: <p>The Community places a priority on mutual support and knowledge sharing, maintaining documentation and multiple <a href="https://vufind.org/wiki/community" target="_blank">communication channels</a> in order to welcome newcomers and enable collaborative planning and problem solving.</p> | E300: Confirm or correct categories; add valid Other only if distinct from the 12 named types.
A301: VuFind® | B301: 041 contribution guidance URL | C301: https://github.com/vufind-org/vufind/blob/dev/CONTRIBUTING.md | D301: 100.0: Candidate dedicated contribution guide; verify URL | E301: Scored from the available URL; inspect only if the URL appears suspect or the automatic tier is inaccurate.
A302: VuFind® | B302: 019 public repository | C302: https://github.com/vufind-org | D302: 100.0: Available public-forge repository URL | E302: Scored from the populated repository field; inspect only if the URL or host classification is clearly malformed.
A303: VuFind® | B303: 043 Code of Conduct evidence | C303: https://github.com/vufind-org/vufind/blob/dev/CODE_OF_CONDUCT.md | D303: Evidence only | E303: Check whether the linked policy applies to this community; do not score URL separately.
A304: Zenodo | B304: 041 contribution guidance URL | C304: https://inveniordm.docs.cern.ch/maintenance/newcomers/ | D304: 100.0: Candidate dedicated contribution guide; verify URL | E304: Scored from the available URL; inspect only if the URL appears suspect or the automatic tier is inaccurate.
A305: Zenodo | B305: 019 public repository | C305: https://github.com/zenodo/zenodo-rdm | D305: 100.0: Available public-forge repository URL | E305: Scored from the populated repository field; inspect only if the URL or host classification is clearly malformed.
A306: Zenodo | B306: 043 Code of Conduct evidence | C306: https://inveniordm.docs.cern.ch/contribute/code-of-conduct/ | D306: Evidence only | E306: Check whether the linked policy applies to this community; do not score URL separately.
A307: Zotero | B307: 041 contribution guidance URL | C307: https://www.zotero.org/support/dev/start | D307: 50.0: Candidate general participation page; verify URL | E307: Scored from the available URL; inspect only if the URL appears suspect or the automatic tier is inaccurate.
A308: Zotero | B308: 019 public repository | C308: https://github.com/zotero | D308: 100.0: Available public-forge repository URL | E308: Scored from the populated repository field; inspect only if the URL or host classification is clearly malformed.
A309: Zotero | B309: 043 Code of Conduct evidence | C309: https://www.zotero.org/support/forum_guidelines | D309: Evidence only | E309: Check whether the linked policy applies to this community; do not score URL separately.

Sheet Data
A1: 001_service_name | B1: 008_provider_name | C1: 010_website | D1: 013_location | E1: 014_solution_category | F1: 019_open_code_repository_url | G1: 037_community_engagement_status | H1: 038_community_engagement_activities | I1: 938_community_engagement_activities_other | J1: 116_community_engagement_url | K1: 039_contribution_pathways | L1: 040_contribution_opportunities | M1: 940_contribution_opportunities_other | N1: 041_contribution_guidelines | O1: 042_code_of_conduct_status | P1: 043_code_of_conduct_url | Q1: 048_community_governance_status | R1: 049_community_governance_url | S1: 078_membership_numbers | T1: 107_membership_program_url
A2: 2i2c | B2: Code for Science and Society | C2: https://2i2c.org/ | D2: US | E2: Authoring tool | F2: https://github.com/2i2c-org/infrastructure | G2: Implemented/available | I2: <p>There are a lot of different kinds of communities we might use to answer this, but here are some relevant pages for a few key types of communities.</p> <p>Our key stakeholders page defines the types of communities we aim to serve: <a href="https://compass.2i2c.org/organization/mission/">https://compass.2i2c.org/organization/mission/</a></p> <p>Our shared responsibility model page describes the kinds of roles that exist in the service and how we aim to share them with communities: <a href="https://docs.2i2c.org/about/service/">https://docs.2i2c.org/about/service/</a></p> <p>Our Open Source Strategy section describes the approach we take towards engaging with and supporting OS communities: <a href="https://compass.2i2c.org/open-source/">https://compass.2i2c.org/open-source/</a></p> <p>All of these are continually evolving, but are a good first start. See also calendars and meetings: <a href="https://compass.2i2c.org/reference/calendar/">https://compass.2i2c.org/reference/calendar/</a></p> We take a lot of inspiration from the Principles of Open Scholarly Infrastructure, though we have not formally audited ourselves in comparison to those criteria. This is something we'd love to do, just haven't had time yet (and feel like an external org should do the auditing, not us). | J2: https://compass.2i2c.org/organization/mission/ https://docs.2i2c.org/about/service/ https://compass.2i2c.org/open-source/ https://compass.2i2c.org/reference/calendar/ | K2: Considering | O2: Implemented/available | P2: https://compass.2i2c.org/code-of-conduct/
A3: Academic Preservation Trust (APTrust) | B3: Academic Preservation Trust (APTrust) | C3: https://aptrust.org | D3: US | E3: Digital preservation service | F3: https://github.com/APTrust/registry | G3: Implemented/available | H3: Annual meetings | Blogs | Community calls | Conference participation | Development sprints | Interest, working, user, or advisory groups | Mailing lists and discussion forums (including Slack) | Staff roles with responsibility for community engagement | User research | Webinars and training | J3: https://aptrust.org/resources/interest-groups/ https://aptrust.org/resources/user-groups/ https://aptrust.org/resources/working-groups/ https://aptrust.org/resources/member-meetings/ https://aptrust.org/governance/advisory-committee/ | K3: Implemented/available | L3: Contribute funds | Contribute to code | Contribute to documentation | Contribute to education or training | Contribute to governance | Contribute to user research or user testing | Contribute to working groups or interest groups | N3: https://aptrust.org/resources/working-groups/ | O3: Implemented/available | P3: https://www.diglib.org/about/code-of-conduct/ | Q3: Formal | R3: https://aptrust.org/resources/policies/#governance-manual | S3: 21 | T3: https://aptrust.org/members/
A4: AfricArXiv | B4: UbuntuNet Alliance | C4: https://africarxiv.org/ | D4: MW | E4: Repository service | G4: Considering | K4: Unknown | O4: Implemented/available | P4: https://access2perspectives.org/code-of-conduct/ | Q4: Ad hoc
A5: Arches Heritage Data Management Platform | B5: Getty Conservation Institute (GCI) | C5: https://archesproject.org | D5: US | E5: Data management planning tool or service | F5: https://github.com/archesproject | G5: Implemented/available | J5: https://www.archesproject.org/community-participation/ | K5: Unknown | N5: https://github.com/archesproject/arches/blob/master/CONTRIBUTING.md | O5: Implemented/available | P5: https://www.archesproject.org/code-of-conduct/ | Q5: Formal | R5: https://www.archesproject.org/archesgovernance/
A6: Archipelago Commons | B6: Metropolitan New York Library Council | C6: https://docs.archipelago.nyc/ | D6: US | E6: Digital library, collection or exhibit platform | Repository software | F6: https://github.com/esmero/ | G6: Implemented/available | H6: Community calls | Conference participation | Interest, working, user, or advisory groups | Mailing lists and discussion forums (including Slack) | Staff roles with responsibility for community engagement | Volunteer or ambassador network | Webinars and training | I6: <p>Questions, use cases, and ideas can be shared with the Archipelago Google Groups forum and on the Archipelago Commons Slack Channel.</p> <p>Stakeholders are also invited to visit, subscribe to, and participate in various active GitHub repositories.</p> | J6: https://metro.org/code-of-conduct | K6: Implemented/available | L6: Contribute to code | Contribute to documentation | Contribute to working groups or interest groups | N6: https://docs.archipelago.nyc/1.5.0/giveortake/ | O6: Implemented/available | P6: https://docs.archipelago.nyc/1.5.0/CODE_OF_CONDUCT/ | Q6: Formal | R6: https://metro.org/wp-content/uploads/2025/05/METROBylaws20242.pdf
A7: Archival Resource Key | B7: ARK Alliance | C7: https://arks.org/ | D7: US | E7: Standard, specification or protocol | F7: https://github.com/arks-org | G7: Implemented/available | J7: https://arks.org/community/ | K7: Implemented/available | L7: Contribute funds | Contribute to code | Contribute to documentation | Contribute to education or training | Contribute to working groups or interest groups | N7: https://arks.org/community/ | O7: Implemented/available | P7: https://arks.org/about/ark-community-code-of-conduct/ | Q7: Ad hoc
A8: Archivematica | B8: Artefactual | C8: https://www.archivematica.org/ | D8: CA | E8: Digital preservation system | F8: https://github.com/artefactual/archivematica | G8: Implemented/available | J8: https://groups.google.com/g/archivematica | K8: Unknown | N8: https://contributors.artefactual.com/ | O8: Unknown | P8: https://github.com/artefactual/archivematica/blob/qa/1.x/CODE_OF_CONDUCT.md
A9: ArchivesSpace | B9: ArchivesSpace | C9: https://archivesspace.org/ | D9: US | E9: Archive information management system | Discovery system | F9: https://github.com/archivesspace/archivesspace | G9: Implemented/available | H9: Annual meetings | Blogs | Community calls | Conference participation | Interest, working, user, or advisory groups | Mailing lists and discussion forums (including Slack) | Social media | Staff roles with responsibility for community engagement | Webinars and training | J9: https://archivesspace.atlassian.net/wiki/spaces/ADC/pages/16449553/Contribute+to+ArchivesSpace | K9: Unknown | N9: https://archivesspace.atlassian.net/wiki/spaces/ADC/pages/16449553/Contribute+to+ArchivesSpace | O9: Implemented/available | P9: https://archivesspace.org/archivesspace-code-of-conduct | Q9: Formal | R9: https://archivesspace.org/governance-board-and-councils | S9: 500 | T9: https://archivesspace.org/membership/member-benefits
A10: ARGOS | B10: OpenAIRE | C10: https://argos.openaire.eu/ | E10: Data management planning tool or service | F10: https://github.com/OpenCDMP/OpenCDMP | G10: Implemented/available | H10: Blogs | Community calls | Conference participation | Development sprints | Interest, working, user, or advisory groups | Social media | Staff roles with responsibility for community engagement | Webinars and training | J10: https://catalogue.openaire.eu/service/openaire.argos/resourcesAndSupport | K10: Unknown | O10: Implemented/available | P10: https://openaire.flarum.cloud/p/2-guidelines | Q10: Formal | R10: https://www.openaire.eu/organisation-2 | S10: 52 | T10: https://www.openaire.eu/members
A11: arXiv | B11: Cornell University | C11: https://arxiv.org/ | D11: US | E11: Repository service | F11: https://github.com/arXiv | G11: Implemented/available | I11: <p>arXiv governance consists of three advisory councils with volunteer representatives from across our stakeholder groups. The Science Advisory Council represents the scientific and research community of arXiv (those who create valuable content and who systematically read this content); the Institutions Advisory Council represents the scholarly communications community, including librarians and information science and publishing professionals; the Editorial Advisory Council functions as arXiv's Editorial Board and is both advisory and operational (members are the chairs of the Section Editorial Committees).</p> <p>Section Editorial Committees recruit and onboard arXiv's moderators. arXiv's moderators are volunteer subject matter experts with terminal degrees in their field. They evaluate each submission’s content and category, following arXiv policies. Currently there are 200+ arXiv moderators involved in the day-to-day process of reviewing submissions and resolving issues so that papers can move through to announcement. </p> <p>arXiv’s HTML Papers project is another example of arXiv’s commitment to community engagement – through surveys and forums, arXiv learned that researchers with disabilities were being left behind by the limitations of PDF articles, which happen to currently be the standard format in scientific communication. The HTML Papers project strives to open scientific research to all by providing a tech-readable, user-friendly format (HTML) for every paper, so that every single formula may be read by researchers, regardless of disability. </p> <p>arXiv also collaborates with arXiv users and startup companies (such as ScienceCast and HuggingFace) to discover new ways to make arXiv papers more searchable and create tools for interoperability. arXivLabs is a framework arXiv uses to enabling the arXiv community to contribute to arXiv and develop tools that can benefit the scientific community. </p> <p>arXiv also distributes a yearly survey to active arXiv users to learn what parts of the arXiv service users most value, what parts need improvement, as well as testing where arXiv stands on matters important to the scientific community. This survey routinely receives over 5,000 responses, and arXiv creates strategic initiatives in accordance with the responses.</p> | K11: Implemented/available | L11: Contribute funds | Contribute to code | Contribute to working groups or interest groups | N11: https://info.arxiv.org/labs/index.html | O11: Implemented/available | P11: https://info.arxiv.org/help/policies/code_of_conduct.html | Q11: Formal | R11: https://info.arxiv.org/about/arXiv_bylaws.html | S11: 290
A12: AtoM | B12: Artefactual | C12: https://www.accesstomemory.org/en/ | D12: CA | E12: Archive information management system | F12: https://github.com/artefactual/atom | G12: In progress | K12: Unknown | N12: https://contributors.artefactual.com/cheatsheet.htmlbute_code | O12: Unknown | P12: https://wiki.accesstomemory.org/wiki/Resources/User_forum#Code_of_conduct
A13: Avalon Media System | B13: Indiana University Libraries | C13: https://avalon.samvera.org/ | D13: US | E13: Digital library, collection or exhibit platform | Repository software | F13: https://github.com/avalonmediasystem/avalon | G13: Implemented/available | H13: Annual meetings | Community calls | Conference participation | Interest, working, user, or advisory groups | Mailing lists and discussion forums (including Slack) | J13: https://avalon.samvera.org/contact | K13: Unknown | L13: Contribute funds | Contribute to code | Contribute to documentation | Contribute to education or training | Contribute to governance | Contribute to user research or user testing | N13: https://samvera.atlassian.net/wiki/x/KACfh | O13: Implemented/available | P13: https://samvera.atlassian.net/wiki/x/nAwnG | Q13: Formal | R13: https://samvera.atlassian.net/wiki/spaces/samvera/pages/1387986974/Samvera+Bylaws
A14: Biodiversity Heritage Library | B14: BHL Consortium | C14: https://www.biodiversitylibrary.org/ | D14: US | E14: Digital library, collection or exhibit platform | Open scholarly dataset | Repository service | F14: https://github.com/gbhl/bhl-us | G14: Implemented/available | H14: Annual meetings | Blogs | Conference participation | Mailing lists and discussion forums (including Slack) | Social media | Volunteer or ambassador network | Webinars and training | J14: https://about.biodiversitylibrary.org/get-involved/ | K14: Unknown | L14: Contribute funds | N14: https://about.biodiversitylibrary.org/get-involved/ | O14: Implemented/available | P14: https://about.biodiversitylibrary.org/about/bhl-code-of-conduct/ | Q14: Formal | R14: https://about.biodiversitylibrary.org/about/bylaws/ | S14: 38 | T14: https://about.biodiversitylibrary.org/about/bhl-consortium/
A15: bioRxiv | B15: Cold Spring Harbor Laboratory | C15: https://www.biorxiv.org/ | D15: US | E15: Repository service | G15: Implemented/available | I15: bioRxiv Affiliates are members of the scientific community who provide feedback on the service, act as advocates, and help in screening material submitted. List of affiliates can be found here: https://www.biorxiv.org/content/about-biorxiv Integrated the FAST principles for preprint peer review into our commenting policy here: <a href="https://connect.biorxiv.org/news/2022/03/21/commenting_on_preprints" target="_blank">https://connect.biorxiv.org/news/2022/03/21/commenting_on_preprints</a> | K15: Unknown | O15: Considering | Q15: Ad hoc
A16: BitCurator Environment | B16: BitCurator Consortium | C16: https://bitcuratorconsortium.org/ | E16: Digital preservation tool | F16: https://github.com/bitcurator/bitcurator-salt | G16: Implemented/available | H16: Annual meetings | Blogs | Community calls | Interest, working, user, or advisory groups | Mailing lists and discussion forums (including Slack) | Staff roles with responsibility for community engagement | Webinars and training | J16: https://bitcuratorconsortium.org/get-involved/ | K16: Unknown | L16: Contribute to code | Contribute to documentation | Contribute to education or training | Contribute to governance | Contribute to working groups or interest groups | N16: https://bitcuratorconsortium.org/for-developers/ | O16: Implemented/available | P16: https://bitcuratorconsortium.org/code-of-conduct/ | Q16: Formal | R16: https://bitcuratorconsortium.org/bitcurator-consortium-charter/ | S16: 30 | T16: https://bitcuratorconsortium.org/get-involved/
A17: Blacklight | B17: Blacklight | C17: https://projectblacklight.org/ | D17: US | E17: Discovery system | Integrated Library System (ILS) or Library Services Platform (LSP) | F17: https://github.com/projectblacklight | G17: Implemented/available | H17: Blogs | Community calls | Conference participation | Development sprints | Mailing lists and discussion forums (including Slack) | Social media | User research | Volunteer or ambassador network | Webinars and training | J17: https://github.com/projectblacklight/blacklight/wiki#support | K17: Unknown | L17: Contribute funds | Contribute to code | Contribute to documentation | Contribute to education or training | Contribute to governance | Contribute to user research or user testing | Contribute to working groups or interest groups | N17: https://github.com/projectblacklight/blacklight/wiki#contributing-to-blacklight | O17: In progress | Q17: Ad hoc
A18: BrCRIS | B18: IBICT | C18: https://brcris.ibict.br/ | D18: BR | E18: Discovery system | Research profiling system | F18: https://github.com/projetos-codic-ibict | G18: In progress | K18: Unknown | O18: Implemented/available | P18: https://brcris.ibict.br/about | Q18: Ad hoc
A19: Browsertrix | B19: Webrecorder | C19: https://webrecorder.net/browsertrix/ | D19: US | E19: Digital library, collection or exhibit platform | Web archiving system | F19: https://github.com/webrecorder/browsertrix | G19: Implemented/available | H19: Social media | J19: https://forum.webrecorder.net/ | K19: Unknown | L19: Contribute to code | Contribute to documentation | O19: Implemented/available | P19: https://github.com/webrecorder/browsertrix?tab=coc-ov-file
A20: CLOCKSS | B20: CLOCKSS | C20: https://clockss.org | D20: US | E20: Digital preservation service | F20: https://github.com/lockss | G20: Implemented/available | J20: https://clockss.org/digital-archive-community/ | K20: Unknown | O20: Considering | Q20: Formal | R20: https://clockss.org/wp-content/uploads/2024/03/DIGITAL-DISTRIBUTED-COMMUNITY-ARCHIVE-ByLaws.pdf | S20: 968 | T20: https://clockss.org/join-clockss/
A21: COAR International Repository Directory (IRD) | B21: COAR | C21: https://ird.coar-repositories.org/ | E21: Index or directory | F21: https://github.com/antleaf/IRD | G21: Implemented/available | H21: Blogs | Community calls | Development sprints | Volunteer or ambassador network | J21: https://coar-repositories.org/wp-content/uploads/2025/07/COAR-IRD-Responsible-Organisation-Curation-Processes-website-July-2025.pdf | K21: Unknown | L21: Contribute to documentation | Contribute to user research or user testing | N21: https://coar-repositories.org/what-we-do/coar-international-repository-directory/ | O21: In progress | Q21: Ad hoc
A22: COAR Notify | B22: COAR | C22: https://coar-notify.net/ | E22: Standard, specification or protocol | F22: https://github.com/coar-notify/coar-notify.net | G22: Implemented/available | H22: Blogs | Conference participation | Interest, working, user, or advisory groups | Mailing lists and discussion forums (including Slack) | Webinars and training | J22: https://coar-notify.net/2024/notify-developers-meeting-2024/ | K22: Unknown | L22: Contribute to code | Contribute to documentation | Contribute to education or training | Contribute to user research or user testing | Contribute to working groups or interest groups | N22: https://coar-notify.net/guide/ | O22: Considering | Q22: Ad hoc
A23: CollectiveAccess | B23: Whirl-i-Gig | C23: https://www.collectiveaccess.org/ | D23: US | E23: Archive information management system | Digital asset management system | Digital library, collection or exhibit platform | F23: https://github.com/collectiveaccess | G23: Implemented/available | J23: https://support.collectiveaccess.org | K23: Unknown | N23: https://collectiveaccess.org | O23: Unknown | P23: https://collectiveaccess.org | Q23: Ad hoc
A24: CORE | B24: The Open University | C24: https://core.ac.uk/ | D24: GB | E24: Discovery system | F24: https://github.com/oacore | G24: Implemented/available | I24: Too often as researchers we exist within our own disciplines and institutes, each in our own silos, disconnected from each other. The CORE Researcher Network provides opportunities for those working with CORE data to engage and collaborate with others from within and across disciplines. Connecting disparate researchers and research teams to mutually beneficial ends is a key tenet in creating this network. By fostering these connections we can work together to better understand the nature of our own, and other, domains. CORE conducted a POSI self-audit in 2022: <a href="https://blog.core.ac.uk/2022/05/23/core-our-commitment-to-the-principles-of-open-scholarly-infrastructure/" target="_blank">https://blog.core.ac.uk/2022/05/23/core-our-commitment-to-the-principles-of-open-scholarly-infrastructure/</a> | J24: https://blog.core.ac.uk/2022/05/23/core-our-commitment-to-the-principles-of-open-scholarly-infrastructure/ | K24: Implemented/available | L24: Contribute funds | Contribute to code | Contribute to documentation | Other | N24: https://core.ac.uk/governance/supporters | O24: Implemented/available | P24: https://github.com/oacore/search/blob/master/CODE_OF_CONDUCT.md | Q24: Formal | R24: https://core.ac.uk/governance
A25: COUNTER Code of Practice | B25: COUNTER Metrics | C25: https://www.countermetrics.org/ | D25: GB | E25: Standard, specification or protocol | F25: https://cop5.countermetrics.org/en/5.1/index.html | G25: Implemented/available | H25: Annual meetings | Blogs | Community calls | Conference participation | Interest, working, user, or advisory groups | Mailing lists and discussion forums (including Slack) | Social media | Webinars and training | I25: COUNTER Members have voting rights at our annual general meeting, are eligible to join our committees and working groups as vacancies arise, and receive our consultations and quarterly newsletters and updates. We also work with our members on projects including the development of tools, training events, and resources. <a href="https://www.countermetrics.org/members/" target="_blank">https://www.countermetrics.org/members/</a> | J25: https://www.countermetrics.org/about/strategy/ | K25: Implemented/available | L25: Contribute funds | Contribute to documentation | Contribute to education or training | Contribute to governance | Contribute to working groups or interest groups | N25: https://www.countermetrics.org/about/how-we-work/ | O25: Implemented/available | P25: https://www.countermetrics.org/about/how-we-work/ | Q25: Formal | R25: https://find-and-update.company-information.service.gov.uk/company/04865179/filing-history | T25: https://www.countermetrics.org/members/
A26: Creative Commons Licenses | B26: Creative Commons | C26: https://creativecommons.org/ | D26: US | E26: Standard, specification or protocol | F26: https://github.com/creativecommons | G26: Implemented/available | I26: Dedicated Community Engagement Manager role, annual Global Summit for community members, periodic Community Conversations on emerging topics such as AI and Creative Commons, Community Spotlights on blog | K26: Implemented/available | L26: Contribute funds | Contribute to code | Contribute to working groups or interest groups | N26: https://network.creativecommons.org/get-involved/ | O26: Implemented/available | P26: https://creativecommons.org/code-of-conduct/ | S26: 0
A27: Crossref Metadata Retrieval | B27: Crossref | C27: http://www.crossref.org/services/metadata-retrieval | D27: US | E27: Open scholarly dataset | F27: https://gitlab.com/crossref | G27: Implemented/available | I27: <p>Crossref has a large community engagement program, with around 10 staff who have all taken the CSCCE Foundations course. Activities comprise: <ul> <li> onboarding and education: <a href="https://www.crossref.org/members-area/" target="_blank">https://www.crossref.org/members-area/</a> <li> multilingual webinars and in-person events: <a href="https://www.crossref.org/events/" target="_blank">https://www.crossref.org/events/</a> <li> working and advisory groups: <a href="https://www.crossref.org/working-groups/" target="_blank">https://www.crossref.org/working-groups/</a> <li> speaking at and participating in meetings and other infrastructures' working groups <li> ambassador program (51 people in 37 countries): <a href="https://www.crossref.org/community/ambassadors/" target="_blank">https://www.crossref.org/community/ambassadors/</a> <li> sponsoring organisations (around 120, helping smaller organizations join for free and enrich metadata - a somewhat train-the-trainer activity): <a href="https://www.crossref.org/membership/about-sponsors/" target="_blank">https://www.crossref.org/membership/about-sponsors/</a> <li> Global Equitable Membership (GEM) program: <a href="https://www.crossref.org/gem/" target="_blank">https://www.crossref.org/gem/</a> <li> The PLACE collaboration with COPE, OASPA, and DOAJ: <a href="https://theplace.discourse.group/" target="_blank">https://theplace.discourse.group/</a> <li> Community forum: <a href="https://community.crossref.org" target="_blank"> https://community.crossref.org</a> <li> Blog: <a href="https://www.crossref.org/blog/" target="_blank">https://www.crossref.org/blog/</a> <li> Bimonthly newsletter: <a href="https://www.crossref.org/subscribe-newsletter/" target="_blank">https://www.crossref.org/subscribe-newsletter/</a> <li> R&D team advises others in the community and prototypes new shared solutions: <a href="https://www.crossref.org/labs/" target="_blank">https://www.crossref.org/labs/</a> <li> ORCID auto-update: <a href="https://www.crossref.org/community/orcid/" target="_blank">https://www.crossref.org/community/orcid/</a> <li> MOUs to collaborate with several partner organisations such as PKP and DOAJ, e.g.: <a href="https://www.crossref.org/blog/doaj-and-crossref-sign-agreement-to-remove-barriers-to-scholarly-publishing-for-all/" target="_blank">https://www.crossref.org/blog/doaj-and-crossref-sign-agreement-to-remove-barriers-to-scholarly-publishing-for-all/</a>. <li> We actively support PKP's community co-development of some OJS plugins <li> We support or co-fund many other initiatives such as ROR (<a href="https://ror.org" target="_blank">https://ror.org</a>) </ul> </p> <p>Members of Crossref's community also participate in governance through the <a href="https://www.crossref.org/board-and-governance/elections/">elections process</a>. 20,000 organisations from 160 countries have a vote in Crossref's annual and open board elections, which include more candidates than available seats, from a slate curated by a community-led Nominating Committee. </p> <li> POSI, with two self-assessments and a further report due in 2024 based on the new POSI version - v1.1 <li> SOC 2® accreditation <li> FOREST is under consideration | J27: https://www.crossref.org/members-area/ https://www.crossref.org/events/ https://www.crossref.org/working-groups/ https://www.crossref.org/community/ambassadors/ https://www.crossref.org/membership/about-sponsors/ https://www.crossref.org/membership/about-sponsors/ https://theplace.discourse.group/ https://community.crossref.org https://www.crossref.org/blog/ https://www.crossref.org/subscribe-newsletter/ https://www.crossref.org/labs/ https://www.crossref.org/community/orcid/ https://www.crossref.org/blog/doaj-and-crossref-sign-agreement-to-remove-barriers-to-scholarly-publishing-for-all/. https://ror.org | K27: Implemented/available | L27: Contribute funds | Contribute to code | Contribute to documentation | Contribute to education or training | Contribute to working groups or interest groups | N27: https://www.crossref.org/community | O27: Implemented/available | P27: https://www.crossref.org/code-of-conduct/ | Q27: Formal | R27: https://www.crossref.org/board-and-governance/bylaws/ | S27: 20000
A28: D4Science Infrastructure | B28: National Research Council of Italy | C28: https://www.d4science.org/ | D28: IT | E28: Computing framework | Informal scholarly communications | Repository service | F28: https://code-repo.d4science.org/ | G28: Considering | K28: Unknown | O28: Considering
A29: DART (Digital Archivist's Resource Tool) | B29: Academic Preservation Trust (APTrust) | C29: https://aptrust.github.io/dart-docs/ | D29: US | E29: Digital preservation tool | F29: https://github.com/aptrust/dart/ | G29: Implemented/available | J29: https://aptrust.org/resources/user-groups/dart-user-group/ | K29: Unknown | L29: Contribute funds | Contribute to code | Contribute to documentation | Contribute to education or training | Contribute to governance | Contribute to user research or user testing | Contribute to working groups or interest groups | N29: https://aptrust.org/documentation-page/dart-digital-archivists-resource-tool/ | O29: Considering | Q29: Formal | R29: https://aptrust.org/resources/policies/#governance-manual
A30: Database Information System | B30: University Library of Regensburg | C30: https://dbis.ur.de/?lang=en | D30: DE | E30: Discovery system | Index or directory | F30: https://github.com/ub-regensburg/dbis | G30: Implemented/available | H30: Annual meetings | Blogs | Conference participation | Mailing lists and discussion forums (including Slack) | Staff roles with responsibility for community engagement | User research | Webinars and training | K30: Unknown | L30: Contribute to working groups or interest groups | O30: Considering | Q30: Ad hoc
A31: Data Citation Corpus | B31: Make Data Count | C31: https://makedatacount.org/find-a-tool/#section-1 | E31: Discovery system | Open scholarly dataset | F31: https://github.com/Make-Data-Count-Community/corpus-data-file | G31: Implemented/available | H31: Blogs | Conference participation | Interest, working, user, or advisory groups | Mailing lists and discussion forums (including Slack) | Social media | Webinars and training | J31: https://makedatacount.org/get-involved/ | K31: Unknown | L31: Other | M31: Groups can contribute citations to the Corpus | N31: https://makedatacount.org/get-involved/ | O31: Not planning | Q31: Ad hoc
A32: DataCite | B32: DataCite | C32: https://datacite.org/ | D32: DE | E32: Discovery system | Persistent identifier service | F32: https://github.com/datacite | G32: Implemented/available | I32: DataCite has a dedicated Community Engagement team that consists of 10 full time FTEs. DataCite also convenes a Community Engagement Steering Group (<a href="https://datacite.org/cesg/" target="_blank">https://datacite.org/cesg/</a>). <li> Self-evaluation against POSI (<a href="https://datacite.org/blog/our-commitment-to-posi/" target="_blank">https://datacite.org/blog/our-commitment-to-posi/</a>) <li> DataCite values: <a href="https://datacite.org/what-we-do/" target="_blank">https://datacite.org/what-we-do/</a> | J32: https://datacite.org/cesg/ https://datacite.org/blog/our-commitment-to-posi/ https://datacite.org/what-we-do/ | K32: Considering | L32: Contribute funds | Contribute to documentation | Contribute to working groups or interest groups | Other | N32: https://datacite.org/roadmap/ | O32: Implemented/available | P32: https://datacite.org/datacite-code-of-conduct | Q32: Formal | R32: https://datacite.org/wp-content/uploads/2023/06/Statutes_26April2022.pdf | S32: 1389
A33: Data Stewardship Wizard | B33: DSW Team | C33: https://ds-wizard.org/ | D33: CZ | E33: Data management planning tool or service | F33: https://github.com/ds-wizard | G33: Implemented/available | H33: Annual meetings | Blogs | Community calls | Conference participation | Interest, working, user, or advisory groups | Mailing lists and discussion forums (including Slack) | Social media | User research | Volunteer or ambassador network | Webinars and training | J33: https://discord.gg/MW3H9tdMcT | K33: Unknown | L33: Contribute to code | Contribute to documentation | Contribute to education or training | Contribute to governance | Contribute to user research or user testing | N33: https://guide.ds-wizard.org/en/latest/more/development/contributing.html | O33: Implemented/available | P33: https://discord.com/channels/693010138302513174/1102900416783597620 | Q33: Ad hoc
A34: Dataverse | B34: Harvard University Institute for Quantitative Social Science (IQSS) | C34: https://dataverse.org/ | D34: US | E34: Repository software | F34: https://github.com/IQSS/dataverse | G34: Implemented/available | I34: <p>Dataverse engages extensively with its user community through a variety of media.</p> <li> Monthly Community Calls are held on Zoom to discuss upcoming releases, development contributions from the community, and other topics relevant to our community: <a href="https://dataverse.org/community-calls" target="_blank">https://dataverse.org/community-calls</a>. <li> Dataverse Community and Developer Mailing Lists provide open fora for community members. <li> Annual Community Meetings provide an opportunity to engage around themes such as sustainability of services and infrastructures and Indigenous Data Sovereignty: <a href="https://dataverse.org/events" target="_blank">https://dataverse.org/events</a>. <li> The Global Dataverse Community Consortium (GDCC) is dedicated to providing international organization to existing Dataverse community efforts and will provide a collaborative venue for institutions to leverage economies of scale in support of Dataverse repositories around the world: <a href="https://dataversecommunity.global/" target="_blank">https://dataversecommunity.global/</a>. <li> DataverseTV highlights fantastic video content from the Dataverse community: <a href="https://dataverse.org/dataversetv" target="_blank">https://dataverse.org/dataversetv</a>. <li> Dataverse google group: <a href="https://groups.google.com/g/dataverse-community" target="_blank">https://groups.google.com/g/dataverse-community</a> <li> Joint declaration of Data Citation principles: <a href="https://force11.org/info/joint-declaration-of-data-citation-principles-final/" target="_blank">https://force11.org/info/joint-declaration-of-data-citation-principles-final/</a> <li> It Takes a Village (ITAV): <a href="https://itav.lyrasis.org/" target="_blank">https://itav.lyrasis.org/</a> <li> CARE principles for data: <a href="https://datascience.codata.org/articles/10.5334/dsj-2020-043" target="_blank">https://datascience.codata.org/articles/10.5334/dsj-2020-043</a> <li> FAIR principles for data: <a href="https://www.go-fair.org/fair-principles/" target="_blank">https://www.go-fair.org/fair-principles/</a> | J34: https://dataverse.org/community-calls https://dataverse.org/events https://dataversecommunity.global/ https://dataverse.org/dataversetv https://groups.google.com/g/dataverse-community https://force11.org/info/joint-declaration-of-data-citation-principles-final/ https://itav.lyrasis.org/ https://datascience.codata.org/articles/10.5334/dsj-2020-043 https://www.go-fair.org/fair-principles/ | K34: Implemented/available | L34: Contribute to code | Contribute to documentation | Contribute to education or training | Contribute to working groups or interest groups | N34: https://dataverse.org/community-calls | O34: Implemented/available | P34: https://github.com/IQSS/dataverse/blob/develop/CODE_OF_CONDUCT.md | Q34: Ad hoc | S34: 0
A35: DLCM Backend | B35: DLCM Technology | C35: https://gitlab.unige.ch/dlcm/community/dlcm-backend | D35: CH | E35: Archive information management system | Digital preservation system | F35: https://gitlab.unige.ch/dlcm/community/dlcm-backend | G35: Implemented/available | H35: Community calls | Conference participation | Interest, working, user, or advisory groups | Webinars and training | J35: https://gitlab.unige.ch/dlcm/community/dlcm-backend/-/blob/master/CODE_OF_CONDUCT.adoc?ref_type=heads | K35: Unknown | N35: https://gitlab.unige.ch/dlcm/community/dlcm-backend/-/blob/master/CONTRIBUTING.adoc?ref_type=heads | O35: Implemented/available | P35: https://gitlab.unige.ch/dlcm/community/dlcm-backend/-/blob/master/CODE_OF_CONDUCT.adoc?ref_type=heads | S35: 5 | T35: https://olos.swiss/pricing/memberships
A36: DLCM Portal | B36: DLCM Technology | C36: https://gitlab.unige.ch/dlcm/ui/dlcm-portal | D36: CH | E36: Archive information management system | Digital preservation system | Software preservation service | F36: https://gitlab.unige.ch/dlcm/ui/dlcm-portal | G36: Implemented/available | H36: Community calls | Conference participation | Interest, working, user, or advisory groups | Webinars and training | J36: https://olos.swiss/events | K36: Unknown | N36: https://gitlab.unige.ch/dlcm/ui/dlcm-portal/-/blob/master/CONTRIBUTING.adoc?ref_type=heads | O36: Implemented/available | P36: https://gitlab.unige.ch/dlcm/ui/dlcm-portal/-/blob/master/CODE_OF_CONDUCT.adoc?ref_type=heads | T36: https://olos.swiss/pricing/memberships
A37: DMP Tool | B37: California Digital Library | C37: https://dmptool.org/ | D37: US | E37: Data management planning tool or service | F37: https://github.com/cdluc3/dmptool/wiki | G37: Implemented/available | H37: Blogs | Community calls | Conference participation | Mailing lists and discussion forums (including Slack) | Social media | Staff roles with responsibility for community engagement | User research | Webinars and training | K37: Unknown | L37: Other | O37: Not planning | T37: https://dmptool.org/public_orgs
A38: DOAJ (Directory of Open Access Journals) | B38: DOAJ Foundation | C38: https://doaj.org/ | D38: DK | E38: Discovery system | Index or directory | Open scholarly dataset | F38: https://github.com/DOAJ | G38: Implemented/available | H38: Blogs | Community calls | Conference participation | Interest, working, user, or advisory groups | Social media | User research | Volunteer or ambassador network | Webinars and training | Other | I38: <li> DOAJ recomitted to the Principles of Open Scholarly Infrastructure in 2025: <a href="https://blog.doaj.org/2025/10/20/doaj-recommits-to-the-principles-of-open-scholarly-infrastructure/" target="_blank">https://blog.doaj.org/2025/10/20/doaj-recommits-to-the-principles-of-open-scholarly-infrastructure/</a> and is an active member of the POSI Working Group. <li> Members of the communnity contribute to the quality and accuracy of DOAJ metadata. <li> DOAJ is a signatory and active proponent of the Helsinki Initiative on Multilingualism. | K38: Unknown | L38: Contribute to code | Contribute to documentation | Contribute to education or training | Contribute to user research or user testing | Contribute to working groups or interest groups | M38: <p>We have a network of over 100 volunteers who review applications. We have regional representation through our Ambassador network. Some of our volunteers and ambassadors have been with us for more than 10 years.</p> <p>We have a dedicated community engagement role to ensure that we are in touch with the large number of stakeholder groups that use and rely upon DOAJ. When we move to our new governance structure, we will establish a stakeholder council.</p> <p>Our strategy states we will advocate for equity and diversity in global open access journal publishing. To do that, we engage with journal platforms and representative groups from around the world, e.g., the Chinese Academy of Science, KISTI in South Korea, J-STAGE in Japan, Publicera in Sweden, Scielo in Latin America, ASSAf and AJOL in South Africa and more.</p> | O38: Implemented/available | P38: https://doaj.org/code-of-conduct/ | Q38: Formal | R38: https://doaj.org/about/advisory-board-council/ | S38: 600
A39: dokieli | B39: dokieli | C39: https://dokie.li/ | E39: Annotations system | Authoring tool | Informal scholarly communications | F39: https://github.com/linkeddata/dokieli | G39: Implemented/available | I39: Workshops and presentations at conferences. There is a community chat answering users and developers questions since 2015. W3C TAG Ethical Web Principles: <a href="https://www.w3.org/TR/ethical-web-principles/" target="_blank">https://www.w3.org/TR/ethical-web-principles/</a> | J39: https://www.w3.org/TR/ethical-web-principles/ | K39: Unknown | L39: Contribute funds | Contribute to code | Contribute to documentation | Contribute to education or training | N39: https://github.com/linkeddata/dokieli | O39: Implemented/available | P39: https://github.com/linkeddata/dokieli/blob/main/CODE-OF-CONDUCT.md
A40: Dryad | B40: Dryad | C40: https://datadryad.org/ | D40: US | E40: Repository service | F40: https://github.com/CDL-Dryad/dryad-app | G40: Implemented/available | I40: <p>There are many ways for the community to engage including becoming a member, contributing code, serving on governance, donating towards fundraising campaigns, working on documentation, participating in listservs and events and working groups.</p> <p>Dryad adopted the POSI Principles in 2020 and is a member of the POSI Adopters Group. Read our full self-audit at <a href="https://blog.datadryad.org/2020/12/08/dryads-commitment-to-the-principles-of-open-scholarly-infrastructure" target="_blank">https://blog.datadryad.org/2020/12/08/dryads-commitment-to-the-principles-of-open-scholarly-infrastructure/</a>.</p> | J40: https://blog.datadryad.org/2020/12/08/dryads-commitment-to-the-principles-of-open-scholarly-infrastructure/. | K40: Unknown | L40: Contribute funds | Contribute to education or training | Contribute to governance | Contribute to working groups or interest groups | O40: Implemented/available | P40: https://datadryad.org/stash/code_of_conduct | Q40: Formal | R40: https://datadryad.org/docs/DryadBylaws.pdf | S40: 84
A41: DSpace | B41: Lyrasis | C41: https://dspace.org/ | D41: US | E41: Repository software | F41: https://github.com/DSpace/DSpace | G41: Implemented/available | H41: Annual meetings | Conference participation | Development sprints | Interest, working, user, or advisory groups | Mailing lists and discussion forums (including Slack) | Staff roles with responsibility for community engagement | Webinars and training | I41: COAR Next Generation Repositories Principles <a href="https://ngr.coar-repositories.org/principles/" target="_blank">https://ngr.coar-repositories.org/principles/</a> | J41: https://dspace.org/join-the-community/ | K41: Implemented/available | L41: Contribute funds | Contribute to code | Contribute to documentation | Contribute to education or training | Contribute to governance | Contribute to peer reviews | Contribute to working groups or interest groups | N41: https://dspace.org/community-contributors/ | O41: Implemented/available | P41: https://www.lyrasis.org/about/Pages/Code-of-Conduct.aspx | Q41: Formal | R41: https://dspace.org/governance | S41: 103 | T41: https://dspace.org/meet-our-members/
A42: DuraCloud | B42: Lyrasis | C42: https://lyrasis.org/duracloud/ | D42: US | E42: Digital preservation service | Digital preservation system | Digital preservation tool | F42: https://github.com/duracloud/duracloud | G42: Implemented/available | K42: Unknown | N42: https://github.com/duracloud/duracloud/blob/develop/CONTRIBUTING.md | O42: Implemented/available | P42: https://lyrasis.org/code-of-conduct/
A43: Episciences | B43: Center for Direct Scientific Communication (CCSD) | C43: https://www.episciences.org/ | D43: FR | E43: Peer review system | Publishing system | Submissions system | F43: https://github.com/CCSDForge/episciences | G43: In progress | K43: Unknown | O43: Considering | Q43: Ad hoc | R43: https://www.episciences.org/governance/
A44: EPrints | B44: EPrints Services | C44: https://www.eprints.org/ | D44: GB | E44: Repository software | F44: https://github.com/eprints/eprints3.4 | G44: Implemented/available | J44: https://community.eprints.org | K44: Unknown | N44: https://wiki.eprints.org/w/Main_Page#Contributing_to_the_Wiki; | O44: In progress
A45: Érudit | B45: Érudit | C45: https://www.erudit.org/ | D45: CA | E45: Discovery system | Publishing system | Repository software | F45: https://github.com/erudit/eruditorg | G45: Implemented/available | I45: DORA, Dimensions charter, Helsinki initiative | J45: https://www.coalition-publi.ca/community | K45: Implemented/available | L45: Contribute to education or training | Contribute to peer reviews | N45: https://www.erudit.org/public/documents/TOR_CoalitionPublica_Journal%20User%20Group.pdf | O45: Implemented/available | P45: https://www.erudit.org/public/documents/CoalitionPublica_bilingue.pdf | Q45: Formal | R45: https://apropos.erudit.org/direction-et-conseils/?lang=en | S45: 1200
A46: Europe PMC | B46: EMBL European Bioinformatics Institute (EMBL-EBI) | C46: https://europepmc.org/ | D46: GB | E46: Digital preservation system | Discovery system | Repository service | F46: https://github.com/EuropePMC | G46: Implemented/available | I46: Dedicated staff for community outreach and engagement. Regular events and webinars with recordings openly available to the community. Developer forum for programmatic users. Strong user research program that includes insights from different stakeholder groups and informs the service roadmap. Free outreach resources available on a dedicated website page (<a href="https://europepmc.org/Outreach" target="_blank">https://europepmc.org/Outreach</a>). Europe PMC conducted a POSI self-audit in 2022: <a href="http://blog.europepmc.org/2022/02/EPMC-adopts-POSI.html" target="_blank">http://blog.europepmc.org/2022/02/EPMC-adopts-POSI.html</a> | J46: https://europepmc.org/Outreach http://blog.europepmc.org/2022/02/EPMC-adopts-POSI.html | K46: Implemented/available | L46: Contribute to code | Contribute to education or training | Contribute to user research or user testing | N46: https://europepmc.org/Outreach | O46: Implemented/available | P46: https://www.embl.org/about/info/course-and-conference-office/information-for-participants/code-of-conduct/ | Q46: Formal | R46: https://europepmc.org/Governance
A47: FAIR Wizard | B47: Codevence Solution s.r.o. | C47: https://fair-wizard.com/ | D47: CZ | E47: Data management planning tool or service | G47: Implemented/available | H47: Annual meetings | Blogs | Conference participation | Social media | User research | Webinars and training | J47: https://fair-wizard.com/blog | K47: Unknown | L47: Contribute to documentation | Contribute to education or training | Contribute to working groups or interest groups | Other | M47: Content creation | O47: Considering | Q47: Ad hoc
A48: Fedora | B48: Lyrasis | C48: https://fedorarepository.org/ | D48: US | E48: Repository software | F48: https://github.com/fcrepo/fcrepo | G48: Implemented/available | H48: Annual meetings | Blogs | Community calls | Conference participation | Development sprints | Interest, working, user, or advisory groups | Mailing lists and discussion forums (including Slack) | Social media | Staff roles with responsibility for community engagement | Webinars and training | I48: Fedora maintains active engagement of its community members through the following activities: <ul> <li>Weekly open tech meetings to foster technical conversations, provide support and discuss development objectives <li>Maintenance of a community Slack with designated channels for targeted discussion <li>Monthly newsletter to keep the community informed on current initiatives, priorities and opportunities to engage <li>Annual virtual conference-style event to bring users together to showcase and discuss current work </ul> <a href="https://wiki.lyrasis.org/display/FF/Fedora+Repository+Home" target="_blank">https://wiki.lyrasis.org/display/FF/Fedora+Repository+Home</a> Currently investigating POSI (Principles for Open Scholarly Infrastructure). | J48: https://fedorarepository.org/join-the-community/ | K48: Implemented/available | L48: Contribute funds | Contribute to code | Contribute to documentation | Contribute to education or training | Contribute to governance | Contribute to peer reviews | Contribute to user research or user testing | Contribute to working groups or interest groups | N48: https://wiki.lyrasis.org/display/FF/Developer+Resources | O48: Implemented/available | P48: https://www.lyrasis.org/about/Pages/Code-of-Conduct.aspx | Q48: Formal | R48: https://wiki.lyrasis.org/display/FF/Project+Governance | S48: 46 | T48: https://fedorarepository.org/meet-our-members/
A49: fido | B49: Open Preservation Foundation | C49: https://openpreservation.org/tools/fido | D49: GB | E49: Digital preservation tool | F49: https://github.com/openpreserve/fido | G49: Implemented/available | H49: Annual meetings | Conference participation | Interest, working, user, or advisory groups | Mailing lists and discussion forums (including Slack) | Social media | Staff roles with responsibility for community engagement | User research | Webinars and training | J49: https://openpreservation.org/resources/ | K49: Unknown | L49: Contribute to code | Contribute to documentation | Contribute to working groups or interest groups | N49: https://openpreservation.org/resources/member-groups/ | O49: Considering | Q49: Formal | S49: 32 | T49: https://openpreservation.org/membership/why-join/
